Workbook
Name AddAdditonalName_Country: Test_Data!#REF!
Name AddAdditonalName_FamilyName: Test_Data!#REF!
Name AddAdditonalName_GivenName: Test_Data!#REF!
Name AddAdditonalName_NameType: Test_Data!#REF!
Name AddProbationPeriod_ProbationEndDate: Test_Data!#REF!
Name AddProbationPeriod_ProbationEndDate2: Test_Data!#REF!
Name AddProbationPeriod_ProbationEndDate2: Automation_Lookups!$AO$2:$AO$4
Name AddProbationPeriod_ProbationReviewDate: Test_Data!#REF!
Name AssignPayGroup_ProposedPayGroup: Test_Data!$E$72
Name AssignPayGroup_ProposedPayGroup: Automation_Lookups!$T$2:$T$20
Name AssignPayGroup_ProposedPayGroup2: Test_Data!$F$72
Name AssignPayGroup_ProposedPayGroup2: Automation_Lookups!$T$2
Name AssignPayGroup_ProposedPayGroupFinal: Test_Data!$E$72
Name AssignPayGroup_ProposedPayGroupInitial: Test_Data!$E$72
Name Automation_Ref: Test_Data!$G$14:$J$14
Name AutomationComments: Test_Data!$E$11
Name ChangeMyEmergencyContacts_Address_City: Test_Data!#REF!
Name ChangeMyEmergencyContacts_Address_HouseNumber: Test_Data!#REF!
Name ChangeMyEmergencyContacts_Address_PostalCode: Test_Data!#REF!
Name ChangeMyEmergencyContacts_Address_Province: Test_Data!#REF!
Name ChangeMyEmergencyContacts_Address_StreetName: Test_Data!#REF!
Name ChangeMyEmergencyContacts_Address_Type: Test_Data!#REF!
Name ChangeMyEmergencyContacts_City: Test_Data!#REF!
Name ChangeMyEmergencyContacts_Email_Address: Test_Data!#REF!
Name ChangeMyEmergencyContacts_Email_Type: Test_Data!#REF!
Name ChangeMyEmergencyContacts_EmailAddress: Test_Data!#REF!
Name ChangeMyEmergencyContacts_FamilyName: Test_Data!#REF!
Name ChangeMyEmergencyContacts_GivenName: Test_Data!#REF!
Name ChangeMyEmergencyContacts_LegalName_FamilyName: Test_Data!#REF!
Name ChangeMyEmergencyContacts_LegalName_GivenName: Test_Data!#REF!
Name ChangeMyEmergencyContacts_LegalName_Prefix: Test_Data!#REF!
Name ChangeMyEmergencyContacts_PhoneDevice: Test_Data!#REF!
Name ChangeMyEmergencyContacts_PhoneDevice2: Automation_Lookups!$AJ$2:$AJ$3
Name ChangeMyEmergencyContacts_PhoneNumber: Test_Data!#REF!
Name ChangeMyEmergencyContacts_PostalCode: Test_Data!#REF!
Name ChangeMyEmergencyContacts_PreferredLanguage: Test_Data!#REF!
Name ChangeMyEmergencyContacts_Relationship: Test_Data!#REF!
Name ChangeMyEmergencyContacts_Relationship2: Automation_Lookups!$AI$2:$AI$5
Name ChangeMyEmergencyContacts_StreetName: Test_Data!#REF!
Name ChangeMyGovernmentIDs_NationalIDs_AddEditID: Test_Data!#REF!
Name ChangeMyGovernmentIDs_NationalIDs_AddEditID1: Test_Data!$E$57
Name ChangeMyGovernmentIDs_NationalIDs_AddEditID12: Test_Data!$F$57
Name ChangeMyGovernmentIDs_NationalIDs_AddEditID2: Test_Data!#REF!
Name ChangeMyGovernmentIDs_NationalIDs_AddEditID22: Automation_Lookups!$AL$2:$AL$4
Name ChangeMyGovernmentIDs_NationalIDs_AddEditID22: Test_Data!#REF!
Name ChangeMyGovernmentIDs_NationalIDs_AddEditID3: Test_Data!#REF!
Name ChangeMyGovernmentIDs_NationalIDs_Country1: Test_Data!$E$53
Name ChangeMyGovernmentIDs_NationalIDs_Country12: Test_Data!$F$53
Name ChangeMyGovernmentIDs_NationalIDs_Country2: Test_Data!#REF!
Name ChangeMyGovernmentIDs_NationalIDs_Country22: Test_Data!#REF!
Name ChangeMyGovernmentIDs_NationalIDs_Country3: Test_Data!#REF!
Name ChangeMyGovernmentIDs_NationalIDs_ExpirationDate1: Test_Data!#REF!
Name ChangeMyGovernmentIDs_NationalIDs_ExpirationDate2: Test_Data!#REF!
Name ChangeMyGovernmentIDs_NationalIDs_IssuedBy2: Test_Data!#REF!
Name ChangeMyGovernmentIDs_NationalIDs_IssuedDate1: Test_Data!#REF!
Name ChangeMyGovernmentIDs_NationalIDs_IssuedDate2: Test_Data!#REF!
Name ChangeMyGovernmentIDs_NationalIDs_NationalIDType1: Test_Data!$E$56
Name ChangeMyGovernmentIDs_NationalIDs_NationalIDType12: Test_Data!$F$56
Name ChangeMyGovernmentIDs_NationalIDs_NationalIDType12: Automation_Lookups!$AK$2:$AK$5
Name ChangeMyGovernmentIDs_NationalIDs_NationalIDType2: Test_Data!#REF!

Sheet Information
A1: Version | F1: Info
A6: Version | B6: 0.3 | F6: Info
F7: Dates | G7: For Czech all dates to be entered in format of DD/MM/YYYY
A8: History | F8: Unhighlighted fields | G8: Only data in unhighlighted fields can be changed.
A9: Date | B9: Version | C9: Details | F9: Red highlighted fields | G9: Indicates fields where unique data is required otherwise automation will throw errors
A10: 44061 | B10: 0.3 | C10: Initial Release | F10: Grey highlighted fields | G10: Indicates fields that cannot be changed
F11: Last Run Status / Last Run Error Message | G11: When automation has run for a particular test, we need to check the status is set to Passed and no error messages are present for each test before the automation run for that particular test is considered valid

Sheet Defects
B2: Batch 1 - Summary | E2: Batch 2 - Summary | H2: Batch 3 - Summary | K2: All E2E Cycle 1 - Summary
B3: Description | C3: Total | E3: Description | F3: Total | H3: Description | I3: Total | K3: Description | L3: Total No. | M3: %
B4: Passed | C4: 35 | E4: Passed | F4: 141 | H4: Passed | I4: 0 | K4: Passed | L4: =C4+F4+I4 -> 176 | M4: =L4/L8*100 -> 72.131148
B5: Failed | C5: 17 | E5: Failed | F5: 27 | H5: Failed | I5: 24 | K5: Failed | L5: =C5+F5+I5 -> 68 | M5: =L5/L8*100 -> 27.868852
B6: Not Run | C6: 0 | E6: Not Run | F6: 0 | H6: Not Run | I6: 0 | K6: Not Run | L6: =C6+F6+I6 -> 0 | M6: =L6/L8*100 -> 0
B7: Executed | C7: 52 | E7: Executed | F7: 168 | H7: Executed | I7: 24 | K7: Executed | L7: =C7+F7+I7 -> 244 | M7: =L7/L8*100 -> 100
B8: Total | C8: 52 | E8: Total | F8: 168 | H8: Total | I8: 24 | K8: Total | L8: =C8+F8+I8 -> 244 | M8: =M4+M5+M6 -> 100
B10: Batch 1 - Defects | E10: Batch 2 - Defects | H10: Batch 3 - Defects | K10: All E2E Cycle 1 - Defects
B11: Failed Tests Description | C11: Total | E11: Failed Tests Description | F11: Total | H11: Failed Tests Description | I11: Total | K11: Failed Tests Description | L11: Total No. | M11: %
B12: P&C Salary Assistant/Supervisor Salary Configuration missing | C12: 12 | E12: Grade Profile not populated causing salary to remain blank | F12: 24 | H12: Data issue - Rerun scheduled | I12: 24 | K12: Personal Information Change Approval Email missing after 2nd and final proxy into HR Manager | L12: 44 | M12: =L12/L17*100 -> 35.2
B13: Automation issue with Maiden Name - Gary to discuss with Shane/Andre | C13: 5 | E13: GC - Under Investigation | F13: 3 | H13: Total | I13: 24 | K13: Open button not available to assign paygroup for payroll. Approval required by David Bradley... | L13: 20 | M13: =L13/L17*100 -> 16
B14: Total | C14: =C12+C13 -> 17 | E14: Total | F14: 27 | K14: Grade Profile not populated causing salary to remain blank | L14: 34 | M14: =L14/L17*100 -> 27.2
K15: Data issue - Rerun scheduled | L15: 24 | M15: =L15/L17*100 -> 19.2
K16: GC - Under Investigation | L16: 3 | M16: =L16/L17*100 -> 2.4
K17: Total | L17: =SUM(L12:L16) -> 125 | M17: =SUM(M12:M16) -> 100

Sheet Automation_Lookups
A1: Process2 | B1: ExecutionFlag2 | C1: SupervisoryOrganisation_SupervisoryOrganisation2 | D1: LegalNameInformation_Country2 | E1: ContactInformation_Phone_CountryPhoneCode2 | F1: ContactInformation_Phone_PhoneDevice2 | G1: ContactInformation_Phone_Type2 | H1: ContactInformation_Address_Type2 | I1: ContactInformation_Email_Type2 | J1: JobDetails_HireDate2 | K1: JobDetails_Reason2 | L1: JobDetails_Position2 | M1: JobDetails_EmployeeType2 | N1: JobDetails_JobProfile2 | O1: JobDetails_TimeType2 | P1: JobDetails_Location2 | Q1: JobDetails_AdditionalInformation_WorkShift2 | R1: JobDetails_AdditionalInformation_EndEmploymentDate2 | S1: ChangeOrganizationAssignments_DepartmentSection2 | T1: AssignPayGroup_ProposedPayGroup2 | U1: Proxy_ProxyNumber2 | V1: Proxy_OnBehalfOf2 | W1: MaintainEmployeeContract_Reason2 | X1: MaintainEmployeeContract_Status2 | Y1: MaintainEmployeeContract_ContractType2 | Z1: MaintainEmployeeContract_ContractEndDate2 | AA1: ProposeCompensationHire_GradeProfile2 | AB1: ProposeCompensationHire_Step2 | AC1: EditPassportsandVisas_Country2 | AD1: EditPassportsandVisas_PassportIDType2 | AE1: EditPassportsandVisas_IdentificationNo2 | AF1: EditPassportsandVisas_IssuedDate2 | AG1: EditPassportsandVisas_ExpirationDate2 | AH1: ChangeMyPersonalInformation_MaritalStatus2 | AI1: ChangeMyEmergencyContacts_Relationship2 | AJ1: ChangeMyEmergencyContacts_PhoneDevice2 | AK1: ChangeMyGovernmentIDs_NationalIDs_NationalIDType12 | AL1: ChangeMyGovernmentIDs_NationalIDs_AddEditID22 | AM1: PaymentElectionOption_AccountType2 | AN1: SkillsAndExperience_AddEducation_School2 | AO1: AddProbationPeriod_ProbationEndDate2 | AP1: EditAdditionalData_PayrollTaxDeduction | AQ1: HealthCareProvider_MealVoucher2 | AR1: School1 | AS1: School2 | AT1: ContactInformation_Address_Province2 | AU1: ChangeMyGovernmentIDs_NationalIDs_NationalIDType12 | AV1: ChangeMyGovernmentIDs_NationalIDs_NationalIDType22 | AW1: EditAdditionalData_EstadolIRPF2 | AX1: EditAdditionalData_MinusvaliaRH2
A2: New Hire | B2: Yes | C2: 362 Recruitment (Carolina De La Barrera Crespo (375)) | D2: Czechia | E2: Czechia (+420) | F2: Mobile | G2: Home | H2: Home | I2: Home | J2: =IF(MONTH(TODAY())<10,"0"&MONTH(TODAY())&"/",MONTH(TODAY())&"/") & IF(DAY(TODAY())<10,"0"&DAY(TODAY())&"/",DAY(TODAY())&"/") & YEAR(TODAY()) -> 04/08/2025 | K2: New Hire | L2: Assistant Manager-2 | M2: Fixed Term | N2: DPP/DPC | O2: Full time | P2: 362 Algeciras | Q2: 1 Day | R2: =IF(MONTH(TODAY())<10,"0"&MONTH(TODAY())&"/",MONTH(TODAY())&"/") & IF(DAY(TODAY())<10,"0"&DAY(TODAY())&"/",DAY(TODAY())&"/") & YEAR(TODAY()) -> 04/08/2025 | S2: Accessories | T2: Please select a Spanish Pay Group | U2: 10223439 | V2: Iwona Chrostowska (10223439) | W2: for the purposes of performing any work of casual or seasonal nature | X2: 1st Fixed Term Contract | Y2: Employment Agreement | Z2: =IF(MONTH(TODAY())<10,"0"&MONTH(TODAY())&"/",MONTH(TODAY())&"/") & IF(DAY(TODAY())<10,"0"&DAY(TODAY())&"/",DAY(TODAY())&"/") & YEAR(TODAY()) -> 04/08/2025 | AA2: Defaulted | AB2: Defaulted | AH2: Single | AI2: Father | AJ2: Mobile/Cell | AK2: Social Security Number (NSS) | AL2: Social Security Number (NSS) | AM2: Savings | AN2: N/A | AO2: =IF(MONTH(TODAY()+100)<10,"0"&MONTH(TODAY()+100)&"/",MONTH(TODAY()+100)&"/") & IF(DAY(TODAY()+100)<10,"0"&DAY(TODAY()+100)&"/",DAY(TODAY()+100)&"/") & YEAR(TODAY()+100) -> 07/17/2025 | AP2: Yes | AQ2: Yes | AR2: Střední bez maturity či výučního listu | AS2: stredni bez maturity ci vyucniho listu | AT2: Madrid | AU2: Social Security Number (NSS) | AV2: ID Card (DNI) Number | AW2: Soltero/a, viudo/a, divorciado/a o separado/a legalmente con hijos solteros menores de 18 años o incapacitados judicialmente que conviven exclusivamente con Vd., sin convivir también con el otro progenitor Soltero/a, viudo/a, divorciado/a o separado/a legalmente con hijos solteros menores de 18 años o incapacitados judicialmente que conviven exclusivamente con Vd., sin convivir también con el otro progenitor | AX2: Del 33% hasta el 65%
A3: New Role & New Hire | B3: No | C3: 895 Store Management (Male Teststmanager (10224969)) | D3: Czechia | E3: Czechia (+420) | F3: Landline | G3: Work | H3: Work | I3: Work | J3: =IF(MONTH(TODAY()-10)<10,"0"&MONTH(TODAY()-10)&"/",MONTH(TODAY()-10))&"/" & IF(DAY(TODAY()-10)<10,"0"&DAY(TODAY()-10)&"/",DAY(TODAY()-10)&"/") & YEAR(TODAY()-10) -> 03//29/2025 | L3: Assistant Manager-3 | M3: Intern | N3: Retail Assistant | O3: Part time | Q3: 2 Days | R3: =IF(MONTH(TODAY()+100)<10,"0"&MONTH(TODAY()+100)&"/",MONTH(TODAY()+100)&"/") & IF(DAY(TODAY()+100)<10,"0"&DAY(TODAY()+100)&"/",DAY(TODAY()+100)&"/") & YEAR(TODAY()+100) -> 07/17/2025 | T3: ES Monthly - 15 payments | U3: 10225553 | V3: Kocour Mikeš (10225553) | W3: for the purposes of performing work during the term of office | X3: 2nd Fixed Term Contract | Y3: Agreement to perform work | Z3: =IF(MONTH(TODAY()+100)<10,"0"&MONTH(TODAY()+100)&"/",MONTH(TODAY()+100)&"/") & IF(DAY(TODAY()+100)<10,"0"&DAY(TODAY()+100)&"/",DAY(TODAY()+100)&"/") & YEAR(TODAY()+100) -> 07/17/2025 | AH3: Married | AI3: Mother | AJ3: Telephone - Landline | AK3: ID Card (DNI) Number | AL3: ID Card (DNI) Number | AM3: Checking | AN3: Vseobecne stredni s maturitou | AO3: =IF(MONTH(TODAY()+1000)<10,"0"&MONTH(TODAY()+1000)&"/",MONTH(TODAY()+1000)&"/") & IF(DAY(TODAY()+1000)<10,"0"&DAY(TODAY()+1000)&"/",DAY(TODAY()+1000)&"/") & YEAR(TODAY()+1000) -> 01/03/2028 | AP3: No | AQ3: No | AR3: Střední odborné vzdělání s výučním listem | AS3: stredni odborne vzdelani s vyucnim listem
D4: Poland | E4: Poland (+48) | J4: =IF(MONTH(TODAY()+10)<10,"0"&MONTH(TODAY()+10)&"/",MONTH(TODAY()+10)&"/") & IF(DAY(TODAY()+10)<10,"0"&DAY(TODAY()+10)&"/",DAY(TODAY()+10)&"/") & YEAR(TODAY()+10) -> 04/18/2025 | L4: Test Store Manager-2 | M4: Permanent | N4: Department Manager | Q4: 3 Days | R4: =IF(MONTH(TODAY()+1000)<10,"0"&MONTH(TODAY()+1000)&"/",MONTH(TODAY()+1000)&"/") & IF(DAY(TODAY()+1000)<10,"0"&DAY(TODAY()+1000)&"/",DAY(TODAY()+1000)&"/") & YEAR(TODAY()+1000) -> 01/03/2028 | W4: for the purposes of substituting an employee during his/her excused absence at work | X4: 3rd Fixed Term Contract | Y4: Agreement to complete a job | Z4: =IF(MONTH(TODAY()+1000)<10,"0"&MONTH(TODAY()+1000)&"/",MONTH(TODAY()+1000)&"/") & IF(DAY(TODAY()+1000)<10,"0"&DAY(TODAY()+1000)&"/",DAY(TODAY()+1000)&"/") & YEAR(TODAY()+1000) -> 01/03/2028 | AH4: Not Disclosed | AI4: Spouse | AK4: Alien Identification Number (NIE) | AL4: Alien Identification Number (NIE) | AO4: N/A | AR4: Všeobecné střední s maturitou | AS4: vseobecne stredni s maturitou
D5: Poland | E5: Poland (+48) | L5: N/A | M5: Students | N5: Senior Department Manager | Q5: 4 Days | R5: N/A | W5: No reason necessary | X5: Active | Z5: N/A | AI5: Partner | AK5: Tax Identification Number (NIF) | AR5: Vysokoškolské Bc. | AS5: Vysokoskolske Bc
N6: Supervisor | Q6: 5 Days | X6: Inactive | AR6: Vysokoškolské MUDr., JUDr., Mgr., MgA., Ing. | AS6: vysokoskolske MUDR., JUDr., Mgr., MgA., Ing.
N7: P&C Supervisor | AR7: Vysokoškolské PhDr, PhD, JUDr, MUDr | AS7: vysokoskolske PhDr, PhD, JUDr, MUDr
N8: P&C Assistant | AR8: vyšší odborné DiS | AS8: vyssi odborne DiS
N9: Trainee Manager | AR9: Základní | AS9: Zakladni
N10: Assistant Manager
N11: P&C Manager
N12: Store Manager
N13: Visual Merchandiser Manager
N14: Visual Merchandising Supervisor
N15: Visual Merchandising Assistant
K21: Rehire | U21: 8701839 | V21: Lisanne Kluinhaar (8701839) | W21: Defined contract end date (Determined) | AQ21: Netherlands Retail Assistant
C22: 701 Recruitment (Lisanne Kluinhaar (8701839)) | D22: Netherlands | E22: Netherlands (+31) | K22: Seasonal | W22: Undefined contract end date (Undetermined) | Y22: Part-time( PT ) | AQ22: Netherlands Retail Assistant Cash Office | AR22: Retail Assistant (18)
W23: Intern | Y23: Full-time( FT. ) | AR23: Retail Assistant (19)
C24: Retail - Central & Eastern Europe (Stephen Regan (9910010) (Inherited) | D24: Poland | E24: Poland (+48) | AR24: Retail Assistant (20)
C25: Retail Poland Area: Central Poland (Stephen Regan (9910010) (Inherited)) | D25: Poland | E25: Poland (+48) | AR25: Retail Assistant (21)
AR26: Retail Assistant (22)
AR27: Retail Assistant (23+)
AR28: Retail Assistant (Under 18)

Sheet RC. No
A1: D.O.B | B1: 35139 | C1: 33054 | D1: 31390 | F1: r col b | G1: r col c | H1: r col d
B2: 9603150007 | C2: 9006300006 | D2: 8512090004 | F2: =B2/11 -> 873013637 | G2: =C2/11 -> 818754546 | H2: =D2/11 -> 773826364
B3: =B2+11 -> 9603150018 | C3: =C2+11 -> 9006300017 | D3: =D2+11 -> 8512090015 | F3: =B3/11 -> 873013638 | G3: =C3/11 -> 818754547 | H3: =D3/11 -> 773826365
B4: =B3+11 -> 9603150029 | C4: =C3+11 -> 9006300028 | D4: =D3+11 -> 8512090026 | F4: =B4/11 -> 873013639 | G4: =C4/11 -> 818754548 | H4: =D4/11 -> 773826366
B5: =B4+11 -> 9603150040 | C5: =C4+11 -> 9006300039 | D5: =D4+11 -> 8512090037 | F5: =B5/11 -> 873013640 | G5: =C5/11 -> 818754549 | H5: =D5/11 -> 773826367
B6: =B5+11 -> 9603150051 | C6: =C5+11 -> 9006300050 | D6: =D5+11 -> 8512090048 | F6: =B6/11 -> 873013641 | G6: =C6/11 -> 818754550 | H6: =D6/11 -> 773826368
B7: =B6+11 -> 9603150062 | C7: =C6+11 -> 9006300061 | D7: =D6+11 -> 8512090059 | F7: =B7/11 -> 873013642 | G7: =C7/11 -> 818754551 | H7: =D7/11 -> 773826369
B8: =B7+11 -> 9603150073 | C8: =C7+11 -> 9006300072 | D8: =D7+11 -> 8512090070 | F8: =B8/11 -> 873013643 | G8: =C8/11 -> 818754552 | H8: =D8/11 -> 773826370
B9: =B8+11 -> 9603150084 | C9: =C8+11 -> 9006300083 | D9: =D8+11 -> 8512090081 | F9: =B9/11 -> 873013644 | G9: =C9/11 -> 818754553 | H9: =D9/11 -> 773826371
B10: =B9+11 -> 9603150095 | C10: =C9+11 -> 9006300094 | D10: =D9+11 -> 8512090092 | F10: =B10/11 -> 873013645 | G10: =C10/11 -> 818754554 | H10: =D10/11 -> 773826372
B11: =B10+11 -> 9603150106 | C11: =C10+11 -> 9006300105 | D11: =D10+11 -> 8512090103 | F11: =B11/11 -> 873013646 | G11: =C11/11 -> 818754555 | H11: =D11/11 -> 773826373
B12: =B11+11 -> 9603150117 | C12: =C11+11 -> 9006300116 | D12: =D11+11 -> 8512090114 | F12: =B12/11 -> 873013647 | G12: =C12/11 -> 818754556 | H12: =D12/11 -> 773826374
B13: =B12+11 -> 9603150128 | C13: =C12+11 -> 9006300127 | D13: =D12+11 -> 8512090125 | F13: =B13/11 -> 873013648 | G13: =C13/11 -> 818754557 | H13: =D13/11 -> 773826375
B14: =B13+11 -> 9603150139 | C14: =C13+11 -> 9006300138 | D14: =D13+11 -> 8512090136 | F14: =B14/11 -> 873013649 | G14: =C14/11 -> 818754558 | H14: =D14/11 -> 773826376
... B28: =B27+11 -> 9603150293 | C28: =C27+11 -> 9006300292 | D28: =D27+11 -> 8512090290 | F28: =B28/11 -> 873013663 | G28: =C28/11 -> 818754572 | H28: =D28/11 -> 773826390
B29: =B28+11 -> 9603150304
B30: =B29+11 -> 9603150315
B31: =B30+11 -> 9603150326
B32: =B31+11 -> 9603150337
B33: =B32+11 -> 9603150348
B34: =B33+11 -> 9603150359
B35: =B34+11 -> 9603150370
B36: =B35+11 -> 9603150381
B37: =B36+11 -> 9603150392
B38: =B37+11 -> 9603150403
B39: =B38+11 -> 9603150414
B40: =B39+11 -> 9603150425
... B75: =B74+11 -> 9603150810
B76: =B75+11 -> 9603150821 | X76: New RC Numbers
B77: =B76+11 -> 9603150832 | X77: 9202101337
B78: =B77+11 -> 9603150843 | X78: =SUM(X77)+11 -> 9202101348
B79: =B78+11 -> 9603150854 | X79: =SUM(X78)+11 -> 9202101359
B80: =B79+11 -> 9603150865 | X80: =SUM(X79)+11 -> 9202101370
B81: =B80+11 -> 9603150876 | X81: =SUM(X80)+11 -> 9202101381
B82: =B81+11 -> 9603150887 | X82: =SUM(X81)+11 -> 9202101392
B83: =B82+11 -> 9603150898 | X83: =SUM(X82)+11 -> 9202101403
B84: =B83+11 -> 9603150909 | X84: =SUM(X83)+11 -> 9202101414
B85: =B84+11 -> 9603150920 | X85: =SUM(X84)+11 -> 9202101425
B86: =B85+11 -> 9603150931 | D86: 9603170269 | X86: =SUM(X85)+11 -> 9202101436
D87: =D86+11 -> 9603170280 | F87: 9603170280 | H87: 9603170280 | I87: 9603170291 | J87: 9603170302 | K87: 9603170313 | L87: 9603170324 | M87: 9603170335 | N87: 9603170346 | O87: 9603170357 | P87: 9603170368 | Q87: 9603170379 | R87: 9603170390 | S87: 9603170401 | T87: 9603170412 | X87: =SUM(X86)+11 -> 9202101447
D88: =D87+11 -> 9603170291 | F88: 9603170291 | X88: =SUM(X87)+11 -> 9202101458
D89: =D88+11 -> 9603170302 | F89: 9603170302 | H89: 9603170412 | I89: =H89+11 -> 9603170423 | J89: =I89+11 -> 9603170434 | K89: =J89+11 -> 9603170445 | L89: =K89+11 -> 9603170456 | M89: =L89+11 -> 9603170467 | N89: =M89+11 -> 9603170478 | O89: =N89+11 -> 9603170489 | P89: =O89+11 -> 9603170500 | ... T89: =S89+11 -> 9603170544 | X89: =SUM(X88)+11 -> 9202101469
D90: =D89+11 -> 9603170313 | F90: 9603170313 | X90: =SUM(X89)+11 -> 9202101480
D91: =D90+11 -> 9603170324 | F91: 9603170324 | X91: =SUM(X90)+11 -> 9202101491
D92: =D91+11 -> 9603170335 | F92: 9603170335 | X92: =SUM(X91)+11 -> 9202101502
D93: =D92+11 -> 9603170346 | F93: 9603170346 | X93: =SUM(X92)+11 -> 9202101513
D94: =D93+11 -> 9603170357 | F94: 9603170357 | X94: =SUM(X93)+11 -> 9202101524
D95: =D94+11 -> 9603170368 | F95: 9603170368 | X95: =SUM(X94)+11 -> 9202101535
D96: =D95+11 -> 9603170379 | F96: 9603170379 | X96: =SUM(X95)+11 -> 9202101546
D97: =D96+11 -> 9603170390 | F97: 9603170390 | X97: =SUM(X96)+11 -> 9202101557
D98: =D97+11 -> 9603170401 | F98: 9603170401 | X98: =SUM(X97)+11 -> 9202101568
D99: =D98+11 -> 9603170412 | F99: 9603170412 | X99: =SUM(X98)+11 -> 9202101579
X100: =SUM(X99)+11 -> 9202101590
X101: =SUM(X100)+11 -> 9202101601
X102: =SUM(X101)+11 -> 9202101612
X103: =SUM(X102)+11 -> 9202101623
X104: =SUM(X103)+11 -> 9202101634
X105: =SUM(X104)+11 -> 9202101645
X106: =SUM(X105)+11 -> 9202101656
X107: =SUM(X106)+11 -> 9202101667
X108: =SUM(X107)+11 -> 9202101678
X109: =SUM(X108)+11 -> 9202101689
X110: =SUM(X109)+11 -> 9202101700
X111: =SUM(X110)+11 -> 9202101711
... X133: =SUM(X132)+11 -> 9202101953

Sheet Code_Ranjeeta
B1: Variable Row | C1: Variable Value | D1: Row Number Declaration --------------------------------- intRowProcess = comExcelWorksheet.Range("Process").Row | E1: Value Declaration ------------------------ strProcess = comExcelWorksheet.Cells(intRowProcess, intColTestColumn).Value | F1: Getters
A2: =Test_Data!D3 -> Process | B2: ="Private intRow" & A2 -> Private intRowProcess | C2: ="Private str" & A2 -> Private strProcess | D2: ="intRow" & A2 & " = comExcelWorksheet.Range(""" & A2 & """).Row" -> intRowProcess = comExcelWorksheet.Range("Process").Row | E2: ="str" & A2 & " = comExcelWorksheet.Cells(intRow" & A2 & ", intColTestColumn).Value" -> strProcess = comExcelWorksheet.Cells(intRowProcess, intColTestColumn).Value | F2: ="Public Property Get get" & A2 & "() : get" & A2 & " = str" & A2 & " : End Property" -> Public Property Get getProcess() : getProcess = strProcess : End Property
A3: =Test_Data!D4 -> ExecutionFlag | B3: ="Private intRow" & A3 -> Private intRowExecutionFlag | C3: ="Private str" & A3 -> Private strExecutionFlag | D3: ="intRow" & A3 & " = comExcelWorksheet.Range(""" & A3 & """).Row" -> intRowExecutionFlag = comExcelWorksheet.Range("ExecutionFlag").Row | E3: ="str" & A3 & " = comExcelWorksheet.Cells(intRow" & A3 & ", intColTestColumn).Value" -> strExecutionFlag = comExcelWorksheet.Cells(intRowExecutionFlag, intColTestColumn).Value | F3: ="Public Property Get get" & A3 & "() : get" & A3 & " = str" & A3 & " : End Property" -> Public Property Get getExecutionFlag() : getExecutionFlag = strExecutionFlag : End Property
A4: =Test_Data!D5 -> DataValidationComplete | B4: ="Private intRow" & A4 -> Private intRowDataValidationComplete | C4: ="Private str" & A4 -> Private strDataValidationComplete | D4: ="intRow" & A4 & " = comExcelWorksheet.Range(""" & A4 & """).Row" -> intRowDataValidationComplete = comExcelWorksheet.Range("DataValidationComplete").Row | E4: ="str" & A4 & " = comExcelWorksheet.Cells(intRow" & A4 & ", intColTestColumn).Value" -> strDataValidationComplete = comExcelWorksheet.Cells(intRowDataValidationComplete, intColTestColumn).Value | F4: ="Public Property Get get" & A4 & "() : get" & A4 & " = str" & A4 & " : End Property" -> Public Property Get getDataValidationComplete() : getDataValidationComplete = strDataValidationComplete : End Property
A5: =Test_Data!D6 -> HireNameComplete | B5: ="Private intRow" & A5 -> Private intRowHireNameComplete | C5: ="Private str" & A5 -> Private strHireNameComplete | D5: ="intRow" & A5 & " = comExcelWorksheet.Range(""" & A5 & """).Row" -> intRowHireNameComplete = comExcelWorksheet.Range("HireNameComplete").Row | E5: ="str" & A5 & " = comExcelWorksheet.Cells(intRow" & A5 & ", intColTestColumn).Value" -> strHireNameComplete = comExcelWorksheet.Cells(intRowHireNameComplete, intColTestColumn).Value | F5: ="Public Property Get get" & A5 & "() : get" & A5 & " = str" & A5 & " : End Property" -> Public Property Get getHireNameComplete() : getHireNameComplete = strHireNameComplete : End Property
A6: =Test_Data!D7 -> LastRunTimeandStatus | B6: ="Private intRow" & A6 -> Private intRowLastRunTimeandStatus | C6: ="Private str" & A6 -> Private strLastRunTimeandStatus | D6: ="intRow" & A6 & " = comExcelWorksheet.Range(""" & A6 & """).Row" -> intRowLastRunTimeandStatus = comExcelWorksheet.Range("LastRunTimeandStatus").Row | E6: ="str" & A6 & " = comExcelWorksheet.Cells(intRow" & A6 & ", intColTestColumn).Value" -> strLastRunTimeandStatus = comExcelWorksheet.Cells(intRowLastRunTimeandStatus, intColTestColumn).Value | F6: ="Public Property Get get" & A6 & "() : get" & A6 & " = str" & A6 & " : End Property" -> Public Property Get getLastRunTimeandStatus() : getLastRunTimeandStatus = strLastRunTimeandStatus : End Property
A7: =Test_Data!D8 -> LastRunEmployeeNo | B7: ="Private intRow" & A7 -> Private intRowLastRunEmployeeNo | C7: ="Private str" & A7 -> Private strLastRunEmployeeNo | D7: ="intRow" & A7 & " = comExcelWorksheet.Range(""" & A7 & """).Row" -> intRowLastRunEmployeeNo = comExcelWorksheet.Range("LastRunEmployeeNo").Row | E7: ="str" & A7 & " = comExcelWorksheet.Cells(intRow" & A7 & ", intColTestColumn).Value" -> strLastRunEmployeeNo = comExcelWorksheet.Cells(intRowLastRunEmployeeNo, intColTestColumn).Value | F7: ="Public Property Get get" & A7 & "() : get" & A7 & " = str" & A7 & " : End Property" -> Public Property Get getLastRunEmployeeNo() : getLastRunEmployeeNo = strLastRunEmployeeNo : End Property
A8: =Test_Data!D9 -> LastRunErrorMessage | B8: ="Private intRow" & A8 -> Private intRowLastRunErrorMessage | C8: ="Private str" & A8 -> Private strLastRunErrorMessage | D8: ="intRow" & A8 & " = comExcelWorksheet.Range(""" & A8 & """).Row" -> intRowLastRunErrorMessage = comExcelWorksheet.Range("LastRunErrorMessage").Row | E8: ="str" & A8 & " = comExcelWorksheet.Cells(intRow" & A8 & ", intColTestColumn).Value" -> strLastRunErrorMessage = comExcelWorksheet.Cells(intRowLastRunErrorMessage, intColTestColumn).Value | F8: ="Public Property Get get" & A8 & "() : get" & A8 & " = str" & A8 & " : End Property" -> Public Property Get getLastRunErrorMessage() : getLastRunErrorMessage = strLastRunErrorMessage : End Property
A9: =Test_Data!D10 -> DefectDescription | B9: ="Private intRow" & A9 -> Private intRowDefectDescription | C9: ="Private str" & A9 -> Private strDefectDescription | D9: ="intRow" & A9 & " = comExcelWorksheet.Range(""" & A9 & """).Row" -> intRowDefectDescription = comExcelWorksheet.Range("DefectDescription").Row | E9: ="str" & A9 & " = comExcelWorksheet.Cells(intRow" & A9 & ", intColTestColumn).Value" -> strDefectDescription = comExcelWorksheet.Cells(intRowDefectDescription, intColTestColumn).Value | F9: ="Public Property Get get" & A9 & "() : get" & A9 & " = str" & A9 & " : End Property" -> Public Property Get getDefectDescription() : getDefectDescription = strDefectDescription : End Property
A10: =Test_Data!D11 -> AutomationComments | B10: ="Private intRow" & A10 -> Private intRowAutomationComments | C10: ="Private str" & A10 -> Private strAutomationComments | D10: ="intRow" & A10 & " = comExcelWorksheet.Range(""" & A10 & """).Row" -> intRowAutomationComments = comExcelWorksheet.Range("AutomationComments").Row | E10: ="str" & A10 & " = comExcelWorksheet.Cells(intRow" & A10 & ", intColTestColumn).Value" -> strAutomationComments = comExcelWorksheet.Cells(intRowAutomationComments, intColTestColumn).Value | F10: ="Public Property Get get" & A10 & "() : get" & A10 & " = str" & A10 & " : End Property" -> Public Property Get getAutomationComments() : getAutomationComments = strAutomationComments : End Property
A11: =Test_Data!D12 -> QAComments | B11: ="Private intRow" & A11 -> Private intRowQAComments | C11: ="Private str" & A11 -> Private strQAComments | D11: ="intRow" & A11 & " = comExcelWorksheet.Range(""" & A11 & """).Row" -> intRowQAComments = comExcelWorksheet.Range("QAComments").Row | E11: ="str" & A11 & " = comExcelWorksheet.Cells(intRow" & A11 & ", intColTestColumn).Value" -> strQAComments = comExcelWorksheet.Cells(intRowQAComments, intColTestColumn).Value | F11: ="Public Property Get get" & A11 & "() : get" & A11 & " = str" & A11 & " : End Property" -> Public Property Get getQAComments() : getQAComments = strQAComments : End Property
A12: =Test_Data!D13 -> 0 | B12: ="Private intRow" & A12 -> Private intRow0 | C12: ="Private str" & A12 -> Private str0 | D12: ="intRow" & A12 & " = comExcelWorksheet.Range(""" & A12 & """).Row" -> intRow0 = comExcelWorksheet.Range("0").Row | E12: ="str" & A12 & " = comExcelWorksheet.Cells(intRow" & A12 & ", intColTestColumn).Value" -> str0 = comExcelWorksheet.Cells(intRow0, intColTestColumn).Value | F12: ="Public Property Get get" & A12 & "() : get" & A12 & " = str" & A12 & " : End Property" -> Public Property Get get0() : get0 = str0 : End Property
A13: =Test_Data!D14 -> Automation Ref | B13: ="Private intRow" & A13 -> Private intRowAutomation Ref | C13: ="Private str" & A13 -> Private strAutomation Ref | D13: ="intRow" & A13 & " = comExcelWorksheet.Range(""" & A13 & """).Row" -> intRowAutomation Ref = comExcelWorksheet.Range("Automation Ref").Row | E13: ="str" & A13 & " = comExcelWorksheet.Cells(intRow" & A13 & ", intColTestColumn).Value" -> strAutomation Ref = comExcelWorksheet.Cells(intRowAutomation Ref, intColTestColumn).Value | F13: ="Public Property Get get" & A13 & "() : get" & A13 & " = str" & A13 & " : End Property" -> Public Property Get getAutomation Ref() : getAutomation Ref = strAutomation Ref : End Property
... A25: =Test_Data!D26 -> ContactInformation_Address_Country | B25: ="Private intRow" & A25 -> Private intRowContactInformation_Address_Country | C25: ="Private str" & A25 -> Private strContactInformation_Address_Country | D25: ="intRow" & A25 & " = comExcelWorksheet.Range(""" & A25 & """).Row" -> intRowContactInformation_Address_Country = comExcelWorksheet.Range("ContactInformation_Address_Country").Row | E25: ="str" & A25 & " = comExcelWorksheet.Cells(intRow" & A25 & ", intColTestColumn).Value" -> strContactInformation_Address_Country = comExcelWorksheet.Cells(intRowContactInformation_Address_Country, intColTestColumn).Value | F25: ="Public Property Get get" & A25 & "() : get" & A25 & " = str" & A25 & " : End Property" -> Public Property Get getContactInformation_Address_Country() : getContactInformation_Address_Country = strContactInformation_Address_Country : End Property
A26: =Test_Data!D28 -> ContactInformation_Address_AdressLine1 | B26: ="Private intRow" & A26 -> Private intRowContactInformation_Address_AdressLine1 | C26: ="Private str" & A26 -> Private strContactInformation_Address_AdressLine1 | D26: ="intRow" & A26 & " = comExcelWorksheet.Range(""" & A26 & """).Row" -> intRowContactInformation_Address_AdressLine1 = comExcelWorksheet.Range("ContactInformation_Address_AdressLine1").Row | E26: ="str" & A26 & " = comExcelWorksheet.Cells(intRow" & A26 & ", intColTestColumn).Value" -> strContactInformation_Address_AdressLine1 = comExcelWorksheet.Cells(intRowContactInformation_Address_AdressLine1, intColTestColumn).Value | F26: ="Public Property Get get" & A26 & "() : get" & A26 & " = str" & A26 & " : End Property" -> Public Property Get getContactInformation_Address_AdressLine1() : getContactInformation_Address_AdressLine1 = strContactInformation_Address_AdressLine1 : End Property
A27: =Test_Data!D29 -> ContactInformation_Address_AdressLine2 | B27: ="Private intRow" & A27 -> Private intRowContactInformation_Address_AdressLine2 | C27: ="Private str" & A27 -> Private strContactInformation_Address_AdressLine2 | D27: ="intRow" & A27 & " = comExcelWorksheet.Range(""" & A27 & """).Row" -> intRowContactInformation_Address_AdressLine2 = comExcelWorksheet.Range("ContactInformation_Address_AdressLine2").Row | E27: ="str" & A27 & " = comExcelWorksheet.Cells(intRow" & A27 & ", intColTestColumn).Value" -> strContactInformation_Address_AdressLine2 = comExcelWorksheet.Cells(intRowContactInformation_Address_AdressLine2, intColTestColumn).Value | F27: ="Public Property Get get" & A27 & "() : get" & A27 & " = str" & A27 & " : End Property" -> Public Property Get getContactInformation_Address_AdressLine2() : getContactInformation_Address_AdressLine2 = strContactInformation_Address_AdressLine2 : End Property
A28: =Test_Data!D30 -> ContactInformation_Address_AdressLine3 | B28: ="Private intRow" & A28 -> Private intRowContactInformation_Address_AdressLine3 | C28: ="Private str" & A28 -> Private strContactInformation_Address_AdressLine3 | D28: ="intRow" & A28 & " = comExcelWorksheet.Range(""" & A28 & """).Row" -> intRowContactInformation_Address_AdressLine3 = comExcelWorksheet.Range("ContactInformation_Address_AdressLine3").Row | E28: ="str" & A28 & " = comExcelWorksheet.Cells(intRow" & A28 & ", intColTestColumn).Value" -> strContactInformation_Address_AdressLine3 = comExcelWorksheet.Cells(intRowContactInformation_Address_AdressLine3, intColTestColumn).Value | F28: ="Public Property Get get" & A28 & "() : get" & A28 & " = str" & A28 & " : End Property" -> Public Property Get getContactInformation_Address_AdressLine3() : getContactInformation_Address_AdressLine3 = strContactInformation_Address_AdressLine3 : End Property
A29: =Test_Data!D31 -> ContactInformation_Address_PostalCode | B29: ="Private intRow" & A29 -> Private intRowContactInformation_Address_PostalCode | C29: ="Private str" & A29 -> Private strContactInformation_Address_PostalCode | D29: ="intRow" & A29 & " = comExcelWorksheet.Range(""" & A29 & """).Row" -> intRowContactInformation_Address_PostalCode = comExcelWorksheet.Range("ContactInformation_Address_PostalCode").Row | E29: ="str" & A29 & " = comExcelWorksheet.Cells(intRow" & A29 & ", intColTestColumn).Value" -> strContactInformation_Address_PostalCode = comExcelWorksheet.Cells(intRowContactInformation_Address_PostalCode, intColTestColumn).Value | F29: ="Public Property Get get" & A29 & "() : get" & A29 & " = str" & A29 & " : End Property" -> Public Property Get getContactInformation_Address_PostalCode() : getContactInformation_Address_PostalCode = strContactInformation_Address_PostalCode : End Property
A30: =Test_Data!D32 -> ContactInformation_Address_City | B30: ="Private intRow" & A30 -> Private intRowContactInformation_Address_City | C30: ="Private str" & A30 -> Private strContactInformation_Address_City | D30: ="intRow" & A30 & " = comExcelWorksheet.Range(""" & A30 & """).Row" -> intRowContactInformation_Address_City = comExcelWorksheet.Range("ContactInformation_Address_City").Row | E30: ="str" & A30 & " = comExcelWorksheet.Cells(intRow" & A30 & ", intColTestColumn).Value" -> strContactInformation_Address_City = comExcelWorksheet.Cells(intRowContactInformation_Address_City, intColTestColumn).Value | F30: ="Public Property Get get" & A30 & "() : get" & A30 & " = str" & A30 & " : End Property" -> Public Property Get getContactInformation_Address_City() : getContactInformation_Address_City = strContactInformation_Address_City : End Property
A31: =Test_Data!#REF! -> #REF! | B31: ="Private intRow" & A31 -> #REF! | C31: ="Private str" & A31 -> #REF! | D31: ="intRow" & A31 & " = comExcelWorksheet.Range(""" & A31 & """).Row" -> #REF! | E31: ="str" & A31 & " = comExcelWorksheet.Cells(intRow" & A31 & ", intColTestColumn).Value" -> #REF! | F31: ="Public Property Get get" & A31 & "() : get" & A31 & " = str" & A31 & " : End Property" -> #REF!
A32: =Test_Data!D33 -> ContactInformation_Address_Type | B32: ="Private intRow" & A32 -> Private intRowContactInformation_Address_Type | C32: ="Private str" & A32 -> Private strContactInformation_Address_Type | D32: ="intRow" & A32 & " = comExcelWorksheet.Range(""" & A32 & """).Row" -> intRowContactInformation_Address_Type = comExcelWorksheet.Range("ContactInformation_Address_Type").Row | E32: ="str" & A32 & " = comExcelWorksheet.Cells(intRow" & A32 & ", intColTestColumn).Value" -> strContactInformation_Address_Type = comExcelWorksheet.Cells(intRowContactInformation_Address_Type, intColTestColumn).Value | F32: ="Public Property Get get" & A32 & "() : get" & A32 & " = str" & A32 & " : End Property" -> Public Property Get getContactInformation_Address_Type() : getContactInformation_Address_Type = strContactInformation_Address_Type : End Property
A33: =Test_Data!D34 -> ContactInformation_Address_UseFor | B33: ="Private intRow" & A33 -> Private intRowContactInformation_Address_UseFor | C33: ="Private str" & A33 -> Private strContactInformation_Address_UseFor | D33: ="intRow" & A33 & " = comExcelWorksheet.Range(""" & A33 & """).Row" -> intRowContactInformation_Address_UseFor = comExcelWorksheet.Range("ContactInformation_Address_UseFor").Row | E33: ="str" & A33 & " = comExcelWorksheet.Cells(intRow" & A33 & ", intColTestColumn).Value" -> strContactInformation_Address_UseFor = comExcelWorksheet.Cells(intRowContactInformation_Address_UseFor, intColTestColumn).Value | F33: ="Public Property Get get" & A33 & "() : get" & A33 & " = str" & A33 & " : End Property" -> Public Property Get getContactInformation_Address_UseFor() : getContactInformation_Address_UseFor = strContactInformation_Address_UseFor : End Property
A34: =Test_Data!D35 -> ContactInformation_Email_EmailAddress | B34: ="Private intRow" & A34 -> Private intRowContactInformation_Email_EmailAddress | C34: ="Private str" & A34 -> Private strContactInformation_Email_EmailAddress | D34: ="intRow" & A34 & " = comExcelWorksheet.Range(""" & A34 & """).Row" -> intRowContactInformation_Email_EmailAddress = comExcelWorksheet.Range("ContactInformation_Email_EmailAddress").Row | E34: ="str" & A34 & " = comExcelWorksheet.Cells(intRow" & A34 & ", intColTestColumn).Value" -> strContactInformation_Email_EmailAddress = comExcelWorksheet.Cells(intRowContactInformation_Email_EmailAddress, intColTestColumn).Value | F34: ="Public Property Get get" & A34 & "() : get" & A34 & " = str" & A34 & " : End Property" -> Public Property Get getContactInformation_Email_EmailAddress() : getContactInformation_Email_EmailAddress = strContactInformation_Email_EmailAddress : End Property
A35: =Test_Data!D36 -> ContactInformation_Email_Type | B35: ="Private intRow" & A35 -> Private intRowContactInformation_Email_Type | C35: ="Private str" & A35 -> Private strContactInformation_Email_Type | D35: ="intRow" & A35 & " = comExcelWorksheet.Range(""" & A35 & """).Row" -> intRowContactInformation_Email_Type = comExcelWorksheet.Range("ContactInformation_Email_Type").Row | E35: ="str" & A35 & " = comExcelWorksheet.Cells(intRow" & A35 & ", intColTestColumn).Value" -> strContactInformation_Email_Type = comExcelWorksheet.Cells(intRowContactInformation_Email_Type, intColTestColumn).Value | F35: ="Public Property Get get" & A35 & "() : get" & A35 & " = str" & A35 & " : End Property" -> Public Property Get getContactInformation_Email_Type() : getContactInformation_Email_Type = strContactInformation_Email_Type : End Property
A36: =Test_Data!D37 -> JobDetails_HireDate | B36: ="Private intRow" & A36 -> Private intRowJobDetails_HireDate | C36: ="Private str" & A36 -> Private strJobDetails_HireDate | D36: ="intRow" & A36 & " = comExcelWorksheet.Range(""" & A36 & """).Row" -> intRowJobDetails_HireDate = comExcelWorksheet.Range("JobDetails_HireDate").Row | E36: ="str" & A36 & " = comExcelWorksheet.Cells(intRow" & A36 & ", intColTestColumn).Value" -> strJobDetails_HireDate = comExcelWorksheet.Cells(intRowJobDetails_HireDate, intColTestColumn).Value | F36: ="Public Property Get get" & A36 & "() : get" & A36 & " = str" & A36 & " : End Property" -> Public Property Get getJobDetails_HireDate() : getJobDetails_HireDate = strJobDetails_HireDate : End Property
A37: =Test_Data!D38 -> ManageProbationPeriod_ProbationEndDate | B37: ="Private intRow" & A37 -> Private intRowManageProbationPeriod_ProbationEndDate | C37: ="Private str" & A37 -> Private strManageProbationPeriod_ProbationEndDate | D37: ="intRow" & A37 & " = comExcelWorksheet.Range(""" & A37 & """).Row" -> intRowManageProbationPeriod_ProbationEndDate = comExcelWorksheet.Range("ManageProbationPeriod_ProbationEndDate").Row | E37: ="str" & A37 & " = comExcelWorksheet.Cells(intRow" & A37 & ", intColTestColumn).Value" -> strManageProbationPeriod_ProbationEndDate = comExcelWorksheet.Cells(intRowManageProbationPeriod_ProbationEndDate, intColTestColumn).Value | F37: ="Public Property Get get" & A37 & "() : get" & A37 & " = str" & A37 & " : End Property" -> Public Property Get getManageProbationPeriod_ProbationEndDate() : getManageProbationPeriod_ProbationEndDate = strManageProbationPeriod_ProbationEndDate : End Property
A38: =Test_Data!D39 -> JobDetails_Reason | B38: ="Private intRow" & A38 -> Private intRowJobDetails_Reason | C38: ="Private str" & A38 -> Private strJobDetails_Reason | D38: ="intRow" & A38 & " = comExcelWorksheet.Range(""" & A38 & """).Row" -> intRowJobDetails_Reason = comExcelWorksheet.Range("JobDetails_Reason").Row | E38: ="str" & A38 & " = comExcelWorksheet.Cells(intRow" & A38 & ", intColTestColumn).Value" -> strJobDetails_Reason = comExcelWorksheet.Cells(intRowJobDetails_Reason, intColTestColumn).Value | F38: ="Public Property Get get" & A38 & "() : get" & A38 & " = str" & A38 & " : End Property" -> Public Property Get getJobDetails_Reason() : getJobDetails_Reason = strJobDetails_Reason : End Property
A39: =Test_Data!D40 -> JobDetails_Position | B39: ="Private intRow" & A39 -> Private intRowJobDetails_Position | C39: ="Private str" & A39 -> Private strJobDetails_Position | D39: ="intRow" & A39 & " = comExcelWorksheet.Range(""" & A39 & """).Row" -> intRowJobDetails_Position = comExcelWorksheet.Range("JobDetails_Position").Row | E39: ="str" & A39 & " = comExcelWorksheet.Cells(intRow" & A39 & ", intColTestColumn).Value" -> strJobDetails_Position = comExcelWorksheet.Cells(intRowJobDetails_Position, intColTestColumn).Value | F39: ="Public Property Get get" & A39 & "() : get" & A39 & " = str" & A39 & " : End Property" -> Public Property Get getJobDetails_Position() : getJobDetails_Position = strJobDetails_Position : End Property
A40: =Test_Data!D41 -> JobDetails_EmployeeType | B40: ="Private intRow" & A40 -> Private intRowJobDetails_EmployeeType | C40: ="Private str" & A40 -> Private strJobDetails_EmployeeType | D40: ="intRow" & A40 & " = comExcelWorksheet.Range(""" & A40 & """).Row" -> intRowJobDetails_EmployeeType = comExcelWorksheet.Range("JobDetails_EmployeeType").Row | E40: ="str" & A40 & " = comExcelWorksheet.Cells(intRow" & A40 & ", intColTestColumn).Value" -> strJobDetails_EmployeeType = comExcelWorksheet.Cells(intRowJobDetails_EmployeeType, intColTestColumn).Value | F40: ="Public Property Get get" & A40 & "() : get" & A40 & " = str" & A40 & " : End Property" -> Public Property Get getJobDetails_EmployeeType() : getJobDetails_EmployeeType = strJobDetails_EmployeeType : End Property
A41: =Test_Data!D42 -> JobDetails_JobProfile | B41: ="Private intRow" & A41 -> Private intRowJobDetails_JobProfile | C41: ="Private str" & A41 -> Private strJobDetails_JobProfile | D41: ="intRow" & A41 & " = comExcelWorksheet.Range(""" & A41 & """).Row" -> intRowJobDetails_JobProfile = comExcelWorksheet.Range("JobDetails_JobProfile").Row | E41: ="str" & A41 & " = comExcelWorksheet.Cells(intRow" & A41 & ", intColTestColumn).Value" -> strJobDetails_JobProfile = comExcelWorksheet.Cells(intRowJobDetails_JobProfile, intColTestColumn).Value | F41: ="Public Property Get get" & A41 & "() : get" & A41 & " = str" & A41 & " : End Property" -> Public Property Get getJobDetails_JobProfile() : getJobDetails_JobProfile = strJobDetails_JobProfile : End Property
A42: =Test_Data!D43 -> JobDetails_TimeType | B42: ="Private intRow" & A42 -> Private intRowJobDetails_TimeType | C42: ="Private str" & A42 -> Private strJobDetails_TimeType | D42: ="intRow" & A42 & " = comExcelWorksheet.Range(""" & A42 & """).Row" -> intRowJobDetails_TimeType = comExcelWorksheet.Range("JobDetails_TimeType").Row | E42: ="str" & A42 & " = comExcelWorksheet.Cells(intRow" & A42 & ", intColTestColumn).Value" -> strJobDetails_TimeType = comExcelWorksheet.Cells(intRowJobDetails_TimeType, intColTestColumn).Value | F42: ="Public Property Get get" & A42 & "() : get" & A42 & " = str" & A42 & " : End Property" -> Public Property Get getJobDetails_TimeType() : getJobDetails_TimeType = strJobDetails_TimeType : End Property
A43: =Test_Data!D44 -> JobDetails_Location | B43: ="Private intRow" & A43 -> Private intRowJobDetails_Location | C43: ="Private str" & A43 -> Private strJobDetails_Location | D43: ="intRow" & A43 & " = comExcelWorksheet.Range(""" & A43 & """).Row" -> intRowJobDetails_Location = comExcelWorksheet.Range("JobDetails_Location").Row | E43: ="str" & A43 & " = comExcelWorksheet.Cells(intRow" & A43 & ", intColTestColumn).Value" -> strJobDetails_Location = comExcelWorksheet.Cells(intRowJobDetails_Location, intColTestColumn).Value | F43: ="Public Property Get get" & A43 & "() : get" & A43 & " = str" & A43 & " : End Property" -> Public Property Get getJobDetails_Location() : getJobDetails_Location = strJobDetails_Location : End Property
... A51: =Test_Data!D52 -> ChangeOrganizationAssignments_DepartmentSection | B51: ="Private intRow" & A51 -> Private intRowChangeOrganizationAssignments_DepartmentSection | C51: ="Private str" & A51 -> Private strChangeOrganizationAssignments_DepartmentSection | D51: ="intRow" & A51 & " = comExcelWorksheet.Range(""" & A51 & """).Row" -> intRowChangeOrganizationAssignments_DepartmentSection = comExcelWorksheet.Range("ChangeOrganizationAssignments_DepartmentSection").Row | E51: ="str" & A51 & " = comExcelWorksheet.Cells(intRow" & A51 & ", intColTestColumn).Value" -> strChangeOrganizationAssignments_DepartmentSection = comExcelWorksheet.Cells(intRowChangeOrganizationAssignments_DepartmentSection, intColTestColumn).Value | F51: ="Public Property Get get" & A51 & "() : get" & A51 & " = str" & A51 & " : End Property" -> Public Property Get getChangeOrganizationAssignments_DepartmentSection() : getChangeOrganizationAssignments_DepartmentSection = strChangeOrganizationAssignments_DepartmentSection : End Property
A52: =Test_Data!#REF! -> #REF! | B52: ="Private intRow" & A52 -> #REF! | C52: ="Private str" & A52 -> #REF! | D52: ="intRow" & A52 & " = comExcelWorksheet.Range(""" & A52 & """).Row" -> #REF! | E52: ="str" & A52 & " = comExcelWorksheet.Cells(intRow" & A52 & ", intColTestColumn).Value" -> #REF! | F52: ="Public Property Get get" & A52 & "() : get" & A52 & " = str" & A52 & " : End Property" -> #REF!
A53: =Test_Data!#REF! -> #REF! | B53: ="Private intRow" & A53 -> #REF! | C53: ="Private str" & A53 -> #REF! | D53: ="intRow" & A53 & " = comExcelWorksheet.Range(""" & A53 & """).Row" -> #REF! | E53: ="str" & A53 & " = comExcelWorksheet.Cells(intRow" & A53 & ", intColTestColumn).Value" -> #REF! | F53: ="Public Property Get get" & A53 & "() : get" & A53 & " = str" & A53 & " : End Property" -> #REF!
A54: =Test_Data!D53 -> ChangeMyGovernmentIDs_NationalIDs_Country1 | B54: ="Private intRow" & A54 -> Private intRowChangeMyGovernmentIDs_NationalIDs_Country1 | C54: ="Private str" & A54 -> Private strChangeMyGovernmentIDs_NationalIDs_Country1 | D54: ="intRow" & A54 & " = comExcelWorksheet.Range(""" & A54 & """).Row" -> intRowChangeMyGovernmentIDs_NationalIDs_Country1 = comExcelWorksheet.Range("ChangeMyGovernmentIDs_NationalIDs_Country1").Row | E54: ="str" & A54 & " = comExcelWorksheet.Cells(intRow" & A54 & ", intColTestColumn).Value" -> strChangeMyGovernmentIDs_NationalIDs_Country1 = comExcelWorksheet.Cells(intRowChangeMyGovernmentIDs_NationalIDs_Country1, intColTestColumn).Value | F54: ="Public Property Get get" & A54 & "() : get" & A54 & " = str" & A54 & " : End Property" -> Public Property Get getChangeMyGovernmentIDs_NationalIDs_Country1() : getChangeMyGovernmentIDs_NationalIDs_Country1 = strChangeMyGovernmentIDs_NationalIDs_Country1 : End Property
A55: =Test_Data!D56 -> ChangeMyGovernmentIDs_NationalIDs_NationalIDType1 | B55: ="Private intRow" & A55 -> Private intRowChangeMyGovernmentIDs_NationalIDs_NationalIDType1 | C55: ="Private str" & A55 -> Private strChangeMyGovernmentIDs_NationalIDs_NationalIDType1 | D55: ="intRow" & A55 & " = comExcelWorksheet.Range(""" & A55 & """).Row" -> intRowChangeMyGovernmentIDs_NationalIDs_NationalIDType1 = comExcelWorksheet.Range("ChangeMyGovernmentIDs_NationalIDs_NationalIDType1").Row | E55: ="str" & A55 & " = comExcelWorksheet.Cells(intRow" & A55 & ", intColTestColumn).Value" -> strChangeMyGovernmentIDs_NationalIDs_NationalIDType1 = comExcelWorksheet.Cells(intRowChangeMyGovernmentIDs_NationalIDs_NationalIDType1, intColTestColumn).Value | F55: ="Public Property Get get" & A55 & "() : get" & A55 & " = str" & A55 & " : End Property" -> Public Property Get getChangeMyGovernmentIDs_NationalIDs_NationalIDType1() : getChangeMyGovernmentIDs_NationalIDs_NationalIDType1 = strChangeMyGovernmentIDs_NationalIDs_NationalIDType1 : End Property
A56: =Test_Data!D57 -> ChangeMyGovernmentIDs_NationalIDs_AddEditID1 | B56: ="Private intRow" & A56 -> Private intRowChangeMyGovernmentIDs_NationalIDs_AddEditID1 | C56: ="Private str" & A56 -> Private strChangeMyGovernmentIDs_NationalIDs_AddEditID1 | D56: ="intRow" & A56 & " = comExcelWorksheet.Range(""" & A56 & """).Row" -> intRowChangeMyGovernmentIDs_NationalIDs_AddEditID1 = comExcelWorksheet.Range("ChangeMyGovernmentIDs_NationalIDs_AddEditID1").Row | E56: ="str" & A56 & " = comExcelWorksheet.Cells(intRow" & A56 & ", intColTestColumn).Value" -> strChangeMyGovernmentIDs_NationalIDs_AddEditID1 = comExcelWorksheet.Cells(intRowChangeMyGovernmentIDs_NationalIDs_AddEditID1, intColTestColumn).Value | F56: ="Public Property Get get" & A56 & "() : get" & A56 & " = str" & A56 & " : End Property" -> Public Property Get getChangeMyGovernmentIDs_NationalIDs_AddEditID1() : getChangeMyGovernmentIDs_NationalIDs_AddEditID1 = strChangeMyGovernmentIDs_NationalIDs_AddEditID1 : End Property
A57: =Test_Data!#REF! -> #REF! | B57: ="Private intRow" & A57 -> #REF! | C57: ="Private str" & A57 -> #REF! | D57: ="intRow" & A57 & " = comExcelWorksheet.Range(""" & A57 & """).Row" -> #REF! | E57: ="str" & A57 & " = comExcelWorksheet.Cells(intRow" & A57 & ", intColTestColumn).Value" -> #REF! | F57: ="Public Property Get get" & A57 & "() : get" & A57 & " = str" & A57 & " : End Property" -> #REF!
A58: =Test_Data!#REF! -> #REF! | B58: ="Private intRow" & A58 -> #REF! | C58: ="Private str" & A58 -> #REF! | D58: ="intRow" & A58 & " = comExcelWorksheet.Range(""" & A58 & """).Row" -> #REF! | E58: ="str" & A58 & " = comExcelWorksheet.Cells(intRow" & A58 & ", intColTestColumn).Value" -> #REF! | F58: ="Public Property Get get" & A58 & "() : get" & A58 & " = str" & A58 & " : End Property" -> #REF!
A59: =Test_Data!#REF! -> #REF! | B59: ="Private intRow" & A59 -> #REF! | C59: ="Private str" & A59 -> #REF! | D59: ="intRow" & A59 & " = comExcelWorksheet.Range(""" & A59 & """).Row" -> #REF! | E59: ="str" & A59 & " = comExcelWorksheet.Cells(intRow" & A59 & ", intColTestColumn).Value" -> #REF! | F59: ="Public Property Get get" & A59 & "() : get" & A59 & " = str" & A59 & " : End Property" -> #REF!
A60: =Test_Data!#REF! -> #REF! | B60: ="Private intRow" & A60 -> #REF! | C60: ="Private str" & A60 -> #REF! | D60: ="intRow" & A60 & " = comExcelWorksheet.Range(""" & A60 & """).Row" -> #REF! | E60: ="str" & A60 & " = comExcelWorksheet.Cells(intRow" & A60 & ", intColTestColumn).Value" -> #REF! | F60: ="Public Property Get get" & A60 & "() : get" & A60 & " = str" & A60 & " : End Property" -> #REF!
A61: =Test_Data!D58 -> ChangeMyPersonalInformation_Gender | B61: ="Private intRow" & A61 -> Private intRowChangeMyPersonalInformation_Gender | C61: ="Private str" & A61 -> Private strChangeMyPersonalInformation_Gender | D61: ="intRow" & A61 & " = comExcelWorksheet.Range(""" & A61 & """).Row" -> intRowChangeMyPersonalInformation_Gender = comExcelWorksheet.Range("ChangeMyPersonalInformation_Gender").Row | E61: ="str" & A61 & " = comExcelWorksheet.Cells(intRow" & A61 & ", intColTestColumn).Value" -> strChangeMyPersonalInformation_Gender = comExcelWorksheet.Cells(intRowChangeMyPersonalInformation_Gender, intColTestColumn).Value | F61: ="Public Property Get get" & A61 & "() : get" & A61 & " = str" & A61 & " : End Property" -> Public Property Get getChangeMyPersonalInformation_Gender() : getChangeMyPersonalInformation_Gender = strChangeMyPersonalInformation_Gender : End Property
A62: =Test_Data!D59 -> ChangeMyPersonalInformation_DateOfBirth | B62: ="Private intRow" & A62 -> Private intRowChangeMyPersonalInformation_DateOfBirth | C62: ="Private str" & A62 -> Private strChangeMyPersonalInformation_DateOfBirth | D62: ="intRow" & A62 & " = comExcelWorksheet.Range(""" & A62 & """).Row" -> intRowChangeMyPersonalInformation_DateOfBirth = comExcelWorksheet.Range("ChangeMyPersonalInformation_DateOfBirth").Row | E62: ="str" & A62 & " = comExcelWorksheet.Cells(intRow" & A62 & ", intColTestColumn).Value" -> strChangeMyPersonalInformation_DateOfBirth = comExcelWorksheet.Cells(intRowChangeMyPersonalInformation_DateOfBirth, intColTestColumn).Value | F62: ="Public Property Get get" & A62 & "() : get" & A62 & " = str" & A62 & " : End Property" -> Public Property Get getChangeMyPersonalInformation_DateOfBirth() : getChangeMyPersonalInformation_DateOfBirth = strChangeMyPersonalInformation_DateOfBirth : End Property
A63: =Test_Data!D60 -> ChangeMyPersonalInformation_CountryOfBirth | B63: ="Private intRow" & A63 -> Private intRowChangeMyPersonalInformation_CountryOfBirth | C63: ="Private str" & A63 -> Private strChangeMyPersonalInformation_CountryOfBirth | D63: ="intRow" & A63 & " = comExcelWorksheet.Range(""" & A63 & """).Row" -> intRowChangeMyPersonalInformation_CountryOfBirth = comExcelWorksheet.Range("ChangeMyPersonalInformation_CountryOfBirth").Row | E63: ="str" & A63 & " = comExcelWorksheet.Cells(intRow" & A63 & ", intColTestColumn).Value" -> strChangeMyPersonalInformation_CountryOfBirth = comExcelWorksheet.Cells(intRowChangeMyPersonalInformation_CountryOfBirth, intColTestColumn).Value | F63: ="Public Property Get get" & A63 & "() : get" & A63 & " = str" & A63 & " : End Property" -> Public Property Get getChangeMyPersonalInformation_CountryOfBirth() : getChangeMyPersonalInformation_CountryOfBirth = strChangeMyPersonalInformation_CountryOfBirth : End Property
A64: =Test_Data!D61 -> ChangeMyPersonalInformation_RegionOfBirth | B64: ="Private intRow" & A64 -> Private intRowChangeMyPersonalInformation_RegionOfBirth | C64: ="Private str" & A64 -> Private strChangeMyPersonalInformation_RegionOfBirth | D64: ="intRow" & A64 & " = comExcelWorksheet.Range(""" & A64 & """).Row" -> intRowChangeMyPersonalInformation_RegionOfBirth = comExcelWorksheet.Range("ChangeMyPersonalInformation_RegionOfBirth").Row | E64: ="str" & A64 & " = comExcelWorksheet.Cells(intRow" & A64 & ", intColTestColumn).Value" -> strChangeMyPersonalInformation_RegionOfBirth = comExcelWorksheet.Cells(intRowChangeMyPersonalInformation_RegionOfBirth, intColTestColumn).Value | F64: ="Public Property Get get" & A64 & "() : get" & A64 & " = str" & A64 & " : End Property" -> Public Property Get getChangeMyPersonalInformation_RegionOfBirth() : getChangeMyPersonalInformation_RegionOfBirth = strChangeMyPersonalInformation_RegionOfBirth : End Property
A65: =Test_Data!D62 -> ChangeMyPersonalInformation_CityOfBirth | B65: ="Private intRow" & A65 -> Private intRowChangeMyPersonalInformation_CityOfBirth | C65: ="Private str" & A65 -> Private strChangeMyPersonalInformation_CityOfBirth | D65: ="intRow" & A65 & " = comExcelWorksheet.Range(""" & A65 & """).Row" -> intRowChangeMyPersonalInformation_CityOfBirth = comExcelWorksheet.Range("ChangeMyPersonalInformation_CityOfBirth").Row | E65: ="str" & A65 & " = comExcelWorksheet.Cells(intRow" & A65 & ", intColTestColumn).Value" -> strChangeMyPersonalInformation_CityOfBirth = comExcelWorksheet.Cells(intRowChangeMyPersonalInformation_CityOfBirth, intColTestColumn).Value | F65: ="Public Property Get get" & A65 & "() : get" & A65 & " = str" & A65 & " : End Property" -> Public Property Get getChangeMyPersonalInformation_CityOfBirth() : getChangeMyPersonalInformation_CityOfBirth = strChangeMyPersonalInformation_CityOfBirth : End Property
A66: =Test_Data!D63 -> ChangeMyPersonalInformation_MaritalStatus | B66: ="Private intRow" & A66 -> Private intRowChangeMyPersonalInformation_MaritalStatus | C66: ="Private str" & A66 -> Private strChangeMyPersonalInformation_MaritalStatus | D66: ="intRow" & A66 & " = comExcelWorksheet.Range(""" & A66 & """).Row" -> intRowChangeMyPersonalInformation_MaritalStatus = comExcelWorksheet.Range("ChangeMyPersonalInformation_MaritalStatus").Row | E66: ="str" & A66 & " = comExcelWorksheet.Cells(intRow" & A66 & ", intColTestColumn).Value" -> strChangeMyPersonalInformation_MaritalStatus = comExcelWorksheet.Cells(intRowChangeMyPersonalInformation_MaritalStatus, intColTestColumn).Value | F66: ="Public Property Get get" & A66 & "() : get" & A66 & " = str" & A66 & " : End Property" -> Public Property Get getChangeMyPersonalInformation_MaritalStatus() : getChangeMyPersonalInformation_MaritalStatus = strChangeMyPersonalInformation_MaritalStatus : End Property
A67: =Test_Data!D64 -> ChangeMyPersonalInformation_MaritalStatusDate | B67: ="Private intRow" & A67 -> Private intRowChangeMyPersonalInformation_MaritalStatusDate | C67: ="Private str" & A67 -> Private strChangeMyPersonalInformation_MaritalStatusDate | D67: ="intRow" & A67 & " = comExcelWorksheet.Range(""" & A67 & """).Row" -> intRowChangeMyPersonalInformation_MaritalStatusDate = comExcelWorksheet.Range("ChangeMyPersonalInformation_MaritalStatusDate").Row | E67: ="str" & A67 & " = comExcelWorksheet.Cells(intRow" & A67 & ", intColTestColumn).Value" -> strChangeMyPersonalInformation_MaritalStatusDate = comExcelWorksheet.Cells(intRowChangeMyPersonalInformation_MaritalStatusDate, intColTestColumn).Value | F67: ="Public Property Get get" & A67 & "() : get" & A67 & " = str" & A67 & " : End Property" -> Public Property Get getChangeMyPersonalInformation_MaritalStatusDate() : getChangeMyPersonalInformation_MaritalStatusDate = strChangeMyPersonalInformation_MaritalStatusDate : End Property
A68: =Test_Data!D65 -> ChangeMyPersonalInformation_RaceEthnicity | B68: ="Private intRow" & A68 -> Private intRowChangeMyPersonalInformation_RaceEthnicity | C68: ="Private str" & A68 -> Private strChangeMyPersonalInformation_RaceEthnicity | D68: ="intRow" & A68 & " = comExcelWorksheet.Range(""" & A68 & """).Row" -> intRowChangeMyPersonalInformation_RaceEthnicity = comExcelWorksheet.Range("ChangeMyPersonalInformation_RaceEthnicity").Row | E68: ="str" & A68 & " = comExcelWorksheet.Cells(intRow" & A68 & ", intColTestColumn).Value" -> strChangeMyPersonalInformation_RaceEthnicity = comExcelWorksheet.Cells(intRowChangeMyPersonalInformation_RaceEthnicity, intColTestColumn).Value | F68: ="Public Property Get get" & A68 & "() : get" & A68 & " = str" & A68 & " : End Property" -> Public Property Get getChangeMyPersonalInformation_RaceEthnicity() : getChangeMyPersonalInformation_RaceEthnicity = strChangeMyPersonalInformation_RaceEthnicity : End Property
A69: =Test_Data!D66 -> ChangeMyPersonalInformation_PrimaryNationality | B69: ="Private intRow" & A69 -> Private intRowChangeMyPersonalInformation_PrimaryNationality | C69: ="Private str" & A69 -> Private strChangeMyPersonalInformation_PrimaryNationality | D69: ="intRow" & A69 & " = comExcelWorksheet.Range(""" & A69 & """).Row" -> intRowChangeMyPersonalInformation_PrimaryNationality = comExcelWorksheet.Range("ChangeMyPersonalInformation_PrimaryNationality").Row | E69: ="str" & A69 & " = comExcelWorksheet.Cells(intRow" & A69 & ", intColTestColumn).Value" -> strChangeMyPersonalInformation_PrimaryNationality = comExcelWorksheet.Cells(intRowChangeMyPersonalInformation_PrimaryNationality, intColTestColumn).Value | F69: ="Public Property Get get" & A69 & "() : get" & A69 & " = str" & A69 & " : End Property" -> Public Property Get getChangeMyPersonalInformation_PrimaryNationality() : getChangeMyPersonalInformation_PrimaryNationality = strChangeMyPersonalInformation_PrimaryNationality : End Property
A70: =Test_Data!#REF! -> #REF! | B70: ="Private intRow" & A70 -> #REF! | C70: ="Private str" & A70 -> #REF! | D70: ="intRow" & A70 & " = comExcelWorksheet.Range(""" & A70 & """).Row" -> #REF! | E70: ="str" & A70 & " = comExcelWorksheet.Cells(intRow" & A70 & ", intColTestColumn).Value" -> #REF! | F70: ="Public Property Get get" & A70 & "() : get" & A70 & " = str" & A70 & " : End Property" -> #REF!
A71: =Test_Data!#REF! -> #REF! | B71: ="Private intRow" & A71 -> #REF! | C71: ="Private str" & A71 -> #REF! | D71: ="intRow" & A71 & " = comExcelWorksheet.Range(""" & A71 & """).Row" -> #REF! | E71: ="str" & A71 & " = comExcelWorksheet.Cells(intRow" & A71 & ", intColTestColumn).Value" -> #REF! | F71: ="Public Property Get get" & A71 & "() : get" & A71 & " = str" & A71 & " : End Property" -> #REF!
A72: =Test_Data!D67 -> ProposeCompensationHire_Salary | B72: ="Private intRow" & A72 -> Private intRowProposeCompensationHire_Salary | C72: ="Private str" & A72 -> Private strProposeCompensationHire_Salary | D72: ="intRow" & A72 & " = comExcelWorksheet.Range(""" & A72 & """).Row" -> intRowProposeCompensationHire_Salary = comExcelWorksheet.Range("ProposeCompensationHire_Salary").Row | E72: ="str" & A72 & " = comExcelWorksheet.Cells(intRow" & A72 & ", intColTestColumn).Value" -> strProposeCompensationHire_Salary = comExcelWorksheet.Cells(intRowProposeCompensationHire_Salary, intColTestColumn).Value | F72: ="Public Property Get get" & A72 & "() : get" & A72 & " = str" & A72 & " : End Property" -> Public Property Get getProposeCompensationHire_Salary() : getProposeCompensationHire_Salary = strProposeCompensationHire_Salary : End Property
A73: =Test_Data!D68 -> PaymentElectionOption_BankName | B73: ="Private intRow" & A73 -> Private intRowPaymentElectionOption_BankName | C73: ="Private str" & A73 -> Private strPaymentElectionOption_BankName | D73: ="intRow" & A73 & " = comExcelWorksheet.Range(""" & A73 & """).Row" -> intRowPaymentElectionOption_BankName = comExcelWorksheet.Range("PaymentElectionOption_BankName").Row | E73: ="str" & A73 & " = comExcelWorksheet.Cells(intRow" & A73 & ", intColTestColumn).Value" -> strPaymentElectionOption_BankName = comExcelWorksheet.Cells(intRowPaymentElectionOption_BankName, intColTestColumn).Value | F73: ="Public Property Get get" & A73 & "() : get" & A73 & " = str" & A73 & " : End Property" -> Public Property Get getPaymentElectionOption_BankName() : getPaymentElectionOption_BankName = strPaymentElectionOption_BankName : End Property
A74: =Test_Data!D70 -> PaymentElectionOption_IBAN | B74: ="Private intRow" & A74 -> Private intRowPaymentElectionOption_IBAN | C74: ="Private str" & A74 -> Private strPaymentElectionOption_IBAN | D74: ="intRow" & A74 & " = comExcelWorksheet.Range(""" & A74 & """).Row" -> intRowPaymentElectionOption_IBAN = comExcelWorksheet.Range("PaymentElectionOption_IBAN").Row | E74: ="str" & A74 & " = comExcelWorksheet.Cells(intRow" & A74 & ", intColTestColumn).Value" -> strPaymentElectionOption_IBAN = comExcelWorksheet.Cells(intRowPaymentElectionOption_IBAN, intColTestColumn).Value | F74: ="Public Property Get get" & A74 & "() : get" & A74 & " = str" & A74 & " : End Property" -> Public Property Get getPaymentElectionOption_IBAN() : getPaymentElectionOption_IBAN = strPaymentElectionOption_IBAN : End Property
A75: =Test_Data!D71 -> PaymentElectionOption_AccountType | B75: ="Private intRow" & A75 -> Private intRowPaymentElectionOption_AccountType | C75: ="Private str" & A75 -> Private strPaymentElectionOption_AccountType | D75: ="intRow" & A75 & " = comExcelWorksheet.Range(""" & A75 & """).Row" -> intRowPaymentElectionOption_AccountType = comExcelWorksheet.Range("PaymentElectionOption_AccountType").Row | E75: ="str" & A75 & " = comExcelWorksheet.Cells(intRow" & A75 & ", intColTestColumn).Value" -> strPaymentElectionOption_AccountType = comExcelWorksheet.Cells(intRowPaymentElectionOption_AccountType, intColTestColumn).Value | F75: ="Public Property Get get" & A75 & "() : get" & A75 & " = str" & A75 & " : End Property" -> Public Property Get getPaymentElectionOption_AccountType() : getPaymentElectionOption_AccountType = strPaymentElectionOption_AccountType : End Property
A76: =Test_Data!#REF! -> #REF! | B76: ="Private intRow" & A76 -> #REF! | C76: ="Private str" & A76 -> #REF! | D76: ="intRow" & A76 & " = comExcelWorksheet.Range(""" & A76 & """).Row" -> #REF! | E76: ="str" & A76 & " = comExcelWorksheet.Cells(intRow" & A76 & ", intColTestColumn).Value" -> #REF! | F76: ="Public Property Get get" & A76 & "() : get" & A76 & " = str" & A76 & " : End Property" -> #REF!
A77: =Test_Data!#REF! -> #REF! | B77: ="Private intRow" & A77 -> #REF! | C77: ="Private str" & A77 -> #REF! | D77: ="intRow" & A77 & " = comExcelWorksheet.Range(""" & A77 & """).Row" -> #REF! | E77: ="str" & A77 & " = comExcelWorksheet.Cells(intRow" & A77 & ", intColTestColumn).Value" -> #REF! | F77: ="Public Property Get get" & A77 & "() : get" & A77 & " = str" & A77 & " : End Property" -> #REF!
A78: =Test_Data!#REF! -> #REF! | B78: ="Private intRow" & A78 -> #REF! | C78: ="Private str" & A78 -> #REF! | D78: ="intRow" & A78 & " = comExcelWorksheet.Range(""" & A78 & """).Row" -> #REF! | E78: ="str" & A78 & " = comExcelWorksheet.Cells(intRow" & A78 & ", intColTestColumn).Value" -> #REF! | F78: ="Public Property Get get" & A78 & "() : get" & A78 & " = str" & A78 & " : End Property" -> #REF!
A79: =Test_Data!#REF! -> #REF! | B79: ="Private intRow" & A79 -> #REF! | C79: ="Private str" & A79 -> #REF! | D79: ="intRow" & A79 & " = comExcelWorksheet.Range(""" & A79 & """).Row" -> #REF! | E79: ="str" & A79 & " = comExcelWorksheet.Cells(intRow" & A79 & ", intColTestColumn).Value" -> #REF! | F79: ="Public Property Get get" & A79 & "() : get" & A79 & " = str" & A79 & " : End Property" -> #REF!
A80: =Test_Data!#REF! -> #REF! | B80: ="Private intRow" & A80 -> #REF! | C80: ="Private str" & A80 -> #REF! | D80: ="intRow" & A80 & " = comExcelWorksheet.Range(""" & A80 & """).Row" -> #REF! | E80: ="str" & A80 & " = comExcelWorksheet.Cells(intRow" & A80 & ", intColTestColumn).Value" -> #REF! | F80: ="Public Property Get get" & A80 & "() : get" & A80 & " = str" & A80 & " : End Property" -> #REF!
A81: =Test_Data!#REF! -> #REF! | B81: ="Private intRow" & A81 -> #REF! | C81: ="Private str" & A81 -> #REF! | D81: ="intRow" & A81 & " = comExcelWorksheet.Range(""" & A81 & """).Row" -> #REF! | E81: ="str" & A81 & " = comExcelWorksheet.Cells(intRow" & A81 & ", intColTestColumn).Value" -> #REF! | F81: ="Public Property Get get" & A81 & "() : get" & A81 & " = str" & A81 & " : End Property" -> #REF!
A82: =Test_Data!#REF! -> #REF! | B82: ="Private intRow" & A82 -> #REF! | C82: ="Private str" & A82 -> #REF! | D82: ="intRow" & A82 & " = comExcelWorksheet.Range(""" & A82 & """).Row" -> #REF! | E82: ="str" & A82 & " = comExcelWorksheet.Cells(intRow" & A82 & ", intColTestColumn).Value" -> #REF! | F82: ="Public Property Get get" & A82 & "() : get" & A82 & " = str" & A82 & " : End Property" -> #REF!
A83: =Test_Data!#REF! -> #REF! | B83: ="Private intRow" & A83 -> #REF! | C83: ="Private str" & A83 -> #REF! | D83: ="intRow" & A83 & " = comExcelWorksheet.Range(""" & A83 & """).Row" -> #REF! | E83: ="str" & A83 & " = comExcelWorksheet.Cells(intRow" & A83 & ", intColTestColumn).Value" -> #REF! | F83: ="Public Property Get get" & A83 & "() : get" & A83 & " = str" & A83 & " : End Property" -> #REF!
A84: =Test_Data!#REF! -> #REF! | B84: ="Private intRow" & A84 -> #REF! | C84: ="Private str" & A84 -> #REF! | D84: ="intRow" & A84 & " = comExcelWorksheet.Range(""" & A84 & """).Row" -> #REF! | E84: ="str" & A84 & " = comExcelWorksheet.Cells(intRow" & A84 & ", intColTestColumn).Value" -> #REF! | F84: ="Public Property Get get" & A84 & "() : get" & A84 & " = str" & A84 & " : End Property" -> #REF!
A85: =Test_Data!#REF! -> #REF! | B85: ="Private intRow" & A85 -> #REF! | C85: ="Private str" & A85 -> #REF! | D85: ="intRow" & A85 & " = comExcelWorksheet.Range(""" & A85 & """).Row" -> #REF! | E85: ="str" & A85 & " = comExcelWorksheet.Cells(intRow" & A85 & ", intColTestColumn).Value" -> #REF! | F85: ="Public Property Get get" & A85 & "() : get" & A85 & " = str" & A85 & " : End Property" -> #REF!
A86: =Test_Data!#REF! -> #REF! | B86: ="Private intRow" & A86 -> #REF! | C86: ="Private str" & A86 -> #REF! | D86: ="intRow" & A86 & " = comExcelWorksheet.Range(""" & A86 & """).Row" -> #REF! | E86: ="str" & A86 & " = comExcelWorksheet.Cells(intRow" & A86 & ", intColTestColumn).Value" -> #REF! | F86: ="Public Property Get get" & A86 & "() : get" & A86 & " = str" & A86 & " : End Property" -> #REF!
A87: =Test_Data!#REF! -> #REF! | B87: ="Private intRow" & A87 -> #REF! | C87: ="Private str" & A87 -> #REF! | D87: ="intRow" & A87 & " = comExcelWorksheet.Range(""" & A87 & """).Row" -> #REF! | E87: ="str" & A87 & " = comExcelWorksheet.Cells(intRow" & A87 & ", intColTestColumn).Value" -> #REF! | F87: ="Public Property Get get" & A87 & "() : get" & A87 & " = str" & A87 & " : End Property" -> #REF!
... A89: =Test_Data!#REF! -> #REF! | B89: ="Private intRow" & A89 -> #REF! | C89: ="Private str" & A89 -> #REF! | D89: ="intRow" & A89 & " = comExcelWorksheet.Range(""" & A89 & """).Row" -> #REF! | E89: ="str" & A89 & " = comExcelWorksheet.Cells(intRow" & A89 & ", intColTestColumn).Value" -> #REF! | F89: ="Public Property Get get" & A89 & "() : get" & A89 & " = str" & A89 & " : End Property" -> #REF!
A90: =Test_Data!D72 -> AssignPayGroup_ProposedPayGroupFinal | B90: ="Private intRow" & A90 -> Private intRowAssignPayGroup_ProposedPayGroupFinal | C90: ="Private str" & A90 -> Private strAssignPayGroup_ProposedPayGroupFinal | D90: ="intRow" & A90 & " = comExcelWorksheet.Range(""" & A90 & """).Row" -> intRowAssignPayGroup_ProposedPayGroupFinal = comExcelWorksheet.Range("AssignPayGroup_ProposedPayGroupFinal").Row | E90: ="str" & A90 & " = comExcelWorksheet.Cells(intRow" & A90 & ", intColTestColumn).Value" -> strAssignPayGroup_ProposedPayGroupFinal = comExcelWorksheet.Cells(intRowAssignPayGroup_ProposedPayGroupFinal, intColTestColumn).Value | F90: ="Public Property Get get" & A90 & "() : get" &Code_Ranjeeta!A90 & " = str" & A90 & " : End Property" -> Public Property Get getAssignPayGroup_ProposedPayGroupFinal() : getAssignPayGroup_ProposedPayGroupFinal = strAssignPayGroup_ProposedPayGroupFinal : End Property
A91: PaymentElectionOption_BankIdentificationCode | B91: ="Private intRow" & A91 -> Private intRowPaymentElectionOption_BankIdentificationCode | C91: ="Private str" & A91 -> Private strPaymentElectionOption_BankIdentificationCode | D91: ="intRow" & A91 & " = comExcelWorksheet.Range(""" & A91 & """).Row" -> intRowPaymentElectionOption_BankIdentificationCode = comExcelWorksheet.Range("PaymentElectionOption_BankIdentificationCode").Row | E91: ="str" & A91 & " = comExcelWorksheet.Cells(intRow" & A91 & ", intColTestColumn).Value" -> strPaymentElectionOption_BankIdentificationCode = comExcelWorksheet.Cells(intRowPaymentElectionOption_BankIdentificationCode, intColTestColumn).Value | F91: ="Public Property Get get" & A91 & "() : get" &Code_Ranjeeta!A91 & " = str" & A91 & " : End Property" -> Public Property Get getPaymentElectionOption_BankIdentificationCode() : getPaymentElectionOption_BankIdentificationCode = strPaymentElectionOption_BankIdentificationCode : End Property

Sheet Code_11122019_1000
B1: Variable Row | C1: Variable Row Combined | D1: Variable Value | E1: Variable Value Combined | F1: Row Number Declaration --------------------------------- intRowProcess = comExcelWorksheet.Range("Process").Row | G1: Value Declaration ------------------------ strProcess = comExcelWorksheet.Cells(intRowProcess, intColTestColumn).Value | H1: Getters
A2: =Test_Data!D3 -> Process | B2: ="intRow" & A2 & ", " -> intRowProcess, | C2: =B2 -> intRowProcess, | D2: ="str" & A2 & ", " -> strProcess, | E2: =D2 -> strProcess, | F2: ="intRow" & A2 & " = comExcelWorksheet.Range(""" & A2 & """).Row" -> intRowProcess = comExcelWorksheet.Range("Process").Row | G2: ="str" & A2 & " = comExcelWorksheet.Cells(intRow" & A2 & ", intColTestColumn).Value" -> strProcess = comExcelWorksheet.Cells(intRowProcess, intColTestColumn).Value | H2: ="Public Property Get get" & A2 & "() : get" & A2 & " = str" & A2 & " : End Property" -> Public Property Get getProcess() : getProcess = strProcess : End Property
A3: =Test_Data!D4 -> ExecutionFlag | B3: ="intRow" & A3 & ", " -> intRowExecutionFlag, | C3: =C2 &B3 -> intRowProcess, intRowExecutionFlag, | D3: ="str" & A3 & ", " -> strExecutionFlag, | E3: =E2 &D3 -> strProcess, strExecutionFlag, | F3: ="intRow" & A3 & " = comExcelWorksheet.Range(""" & A3 & """).Row" -> intRowExecutionFlag = comExcelWorksheet.Range("ExecutionFlag").Row | G3: ="str" & A3 & " = comExcelWorksheet.Cells(intRow" & A3 & ", intColTestColumn).Value" -> strExecutionFlag = comExcelWorksheet.Cells(intRowExecutionFlag, intColTestColumn).Value | H3: ="Public Property Get get" & A3 & "() : get" & A3 & " = str" & A3 & " : End Property" -> Public Property Get getExecutionFlag() : getExecutionFlag = strExecutionFlag : End Property
A4: =Test_Data!D5 -> DataValidationComplete | B4: ="intRow" & A4 & ", " -> intRowDataValidationComplete, | C4: =C3 &B4 -> intRowProcess, intRowExecutionFlag, intRowDataValidationComplete, | D4: ="str" & A4 & ", " -> strDataValidationComplete, | E4: =E3 &D4 -> strProcess, strExecutionFlag, strDataValidationComplete, | F4: ="intRow" & A4 & " = comExcelWorksheet.Range(""" & A4 & """).Row" -> intRowDataValidationComplete = comExcelWorksheet.Range("DataValidationComplete").Row | G4: ="str" & A4 & " = comExcelWorksheet.Cells(intRow" & A4 & ", intColTestColumn).Value" -> strDataValidationComplete = comExcelWorksheet.Cells(intRowDataValidationComplete, intColTestColumn).Value | H4: ="Public Property Get get" & A4 & "() : get" & A4 & " = str" & A4 & " : End Property" -> Public Property Get getDataValidationComplete() : getDataValidationComplete = strDataValidationComplete : End Property
A5: =Test_Data!D6 -> HireNameComplete | B5: ="intRow" & A5 & ", " -> intRowHireNameComplete, | C5: =C4 &B5 -> intRowProcess, intRowExecutionFlag, intRowDataValidationComplete, intRowHireNameComplete, | D5: ="str" & A5 & ", " -> strHireNameComplete, | E5: =E4 &D5 -> strProcess, strExecutionFlag, strDataValidationComplete, strHireNameComplete, | F5: ="intRow" & A5 & " = comExcelWorksheet.Range(""" & A5 & """).Row" -> intRowHireNameComplete = comExcelWorksheet.Range("HireNameComplete").Row | G5: ="str" & A5 & " = comExcelWorksheet.Cells(intRow" & A5 & ", intColTestColumn).Value" -> strHireNameComplete = comExcelWorksheet.Cells(intRowHireNameComplete, intColTestColumn).Value | H5: ="Public Property Get get" & A5 & "() : get" & A5 & " = str" & A5 & " : End Property" -> Public Property Get getHireNameComplete() : getHireNameComplete = strHireNameComplete : End Property
A6: =Test_Data!D7 -> LastRunTimeandStatus | B6: ="intRow" & A6 & ", " -> intRowLastRunTimeandStatus, | C6: =C5 &B6 -> intRowProcess, intRowExecutionFlag, intRowDataValidationComplete, intRowHireNameComplete, intRowLastRunTimeandStatus, | D6: ="str" & A6 & ", " -> strLastRunTimeandStatus, | E6: =E5 &D6 -> strProcess, strExecutionFlag, strDataValidationComplete, strHireNameComplete, strLastRunTimeandStatus, | F6: ="intRow" & A6 & " = comExcelWorksheet.Range(""" & A6 & """).Row" -> intRowLastRunTimeandStatus = comExcelWorksheet.Range("LastRunTimeandStatus").Row | G6: ="str" & A6 & " = comExcelWorksheet.Cells(intRow" & A6 & ", intColTestColumn).Value" -> strLastRunTimeandStatus = comExcelWorksheet.Cells(intRowLastRunTimeandStatus, intColTestColumn).Value | H6: ="Public Property Get get" & A6 & "() : get" & A6 & " = str" & A6 & " : End Property" -> Public Property Get getLastRunTimeandStatus() : getLastRunTimeandStatus = strLastRunTimeandStatus : End Property
A7: =Test_Data!D8 -> LastRunEmployeeNo | B7: ="intRow" & A7 & ", " -> intRowLastRunEmployeeNo, | C7: =C6 &B7 -> intRowProcess, intRowExecutionFlag, intRowDataValidationComplete, intRowHireNameComplete, intRowLastRunTimeandStatus, intRowLastRunEmployeeNo, | D7: ="str" & A7 & ", " -> strLastRunEmployeeNo, | E7: =E6 &D7 -> strProcess, strExecutionFlag, strDataValidationComplete, strHireNameComplete, strLastRunTimeandStatus, strLastRunEmployeeNo, | F7: ="intRow" & A7 & " = comExcelWorksheet.Range(""" & A7 & """).Row" -> intRowLastRunEmployeeNo = comExcelWorksheet.Range("LastRunEmployeeNo").Row | G7: ="str" & A7 & " = comExcelWorksheet.Cells(intRow" & A7 & ", intColTestColumn).Value" -> strLastRunEmployeeNo = comExcelWorksheet.Cells(intRowLastRunEmployeeNo, intColTestColumn).Value | H7: ="Public Property Get get" & A7 & "() : get" & A7 & " = str" & A7 & " : End Property" -> Public Property Get getLastRunEmployeeNo() : getLastRunEmployeeNo = strLastRunEmployeeNo : End Property
A8: =Test_Data!D9 -> LastRunErrorMessage | B8: ="intRow" & A8 & ", " -> intRowLastRunErrorMessage, | C8: =C7 &B8 -> intRowProcess, intRowExecutionFlag, intRowDataValidationComplete, intRowHireNameComplete, intRowLastRunTimeandStatus, intRowLastRunEmployeeNo, intRowLastRunErrorMessage, | D8: ="str" & A8 & ", " -> strLastRunErrorMessage, | E8: =E7 &D8 -> strProcess, strExecutionFlag, strDataValidationComplete, strHireNameComplete, strLastRunTimeandStatus, strLastRunEmployeeNo, strLastRunErrorMessage, | F8: ="intRow" & A8 & " = comExcelWorksheet.Range(""" & A8 & """).Row" -> intRowLastRunErrorMessage = comExcelWorksheet.Range("LastRunErrorMessage").Row | G8: ="str" & A8 & " = comExcelWorksheet.Cells(intRow" & A8 & ", intColTestColumn).Value" -> strLastRunErrorMessage = comExcelWorksheet.Cells(intRowLastRunErrorMessage, intColTestColumn).Value | H8: ="Public Property Get get" & A8 & "() : get" & A8 & " = str" & A8 & " : End Property" -> Public Property Get getLastRunErrorMessage() : getLastRunErrorMessage = strLastRunErrorMessage : End Property
A9: =Test_Data!D10 -> DefectDescription | B9: ="intRow" & A9 & ", " -> intRowDefectDescription, | C9: =C8 &B9 -> intRowProcess, intRowExecutionFlag, intRowDataValidationComplete, intRowHireNameComplete, intRowLastRunTimeandStatus, intRowLastRunEmployeeNo, intRowLastRunErrorMessage, intRowDefectDescription, | D9: ="str" & A9 & ", " -> strDefectDescription, | E9: =E8 &D9 -> strProcess, strExecutionFlag, strDataValidationComplete, strHireNameComplete, strLastRunTimeandStatus, strLastRunEmployeeNo, strLastRunErrorMessage, strDefectDescription, | F9: ="intRow" & A9 & " = comExcelWorksheet.Range(""" & A9 & """).Row" -> intRowDefectDescription = comExcelWorksheet.Range("DefectDescription").Row | G9: ="str" & A9 & " = comExcelWorksheet.Cells(intRow" & A9 & ", intColTestColumn).Value" -> strDefectDescription = comExcelWorksheet.Cells(intRowDefectDescription, intColTestColumn).Value | H9: ="Public Property Get get" & A9 & "() : get" & A9 & " = str" & A9 & " : End Property" -> Public Property Get getDefectDescription() : getDefectDescription = strDefectDescription : End Property
A10: =Test_Data!D11 -> AutomationComments | B10: ="intRow" & A10 & ", " -> intRowAutomationComments, | C10: =C9 &B10 -> intRowProcess, intRowExecutionFlag, intRowDataValidationComplete, intRowHireNameComplete, intRowLastRunTimeandStatus, intRowLastRunEmployeeNo, intRowLastRunErrorMessage, intRowDefectDescription, intRowAutomationComments, | D10: ="str" & A10 & ", " -> strAutomationComments, | E10: =E9 &D10 -> strProcess, strExecutionFlag, strDataValidationComplete, strHireNameComplete, strLastRunTimeandStatus, strLastRunEmployeeNo, strLastRunErrorMessage, strDefectDescription, strAutomationComments, | F10: ="intRow" & A10 & " = comExcelWorksheet.Range(""" & A10 & """).Row" -> intRowAutomationComments = comExcelWorksheet.Range("AutomationComments").Row | G10: ="str" & A10 & " = comExcelWorksheet.Cells(intRow" & A10 & ", intColTestColumn).Value" -> strAutomationComments = comExcelWorksheet.Cells(intRowAutomationComments, intColTestColumn).Value | H10: ="Public Property Get get" & A10 & "() : get" & A10 & " = str" & A10 & " : End Property" -> Public Property Get getAutomationComments() : getAutomationComments = strAutomationComments : End Property
A11: =Test_Data!D12 -> QAComments | B11: ="intRow" & A11 & ", " -> intRowQAComments, | C11: =C10 &B11 -> intRowProcess, intRowExecutionFlag, intRowDataValidationComplete, intRowHireNameComplete, intRowLastRunTimeandStatus, intRowLastRunEmployeeNo, intRowLastRunErrorMessage, intRowDefectDescription, intRowAutomationComments, intRowQAComments, | D11: ="str" & A11 & ", " -> strQAComments, | E11: =E10 &D11 -> strProcess, strExecutionFlag, strDataValidationComplete, strHireNameComplete, strLastRunTimeandStatus, strLastRunEmployeeNo, strLastRunErrorMessage, strDefectDescription, strAutomationComments, strQAComments, | F11: ="intRow" & A11 & " = comExcelWorksheet.Range(""" & A11 & """).Row" -> intRowQAComments = comExcelWorksheet.Range("QAComments").Row | G11: ="str" & A11 & " = comExcelWorksheet.Cells(intRow" & A11 & ", intColTestColumn).Value" -> strQAComments = comExcelWorksheet.Cells(intRowQAComments, intColTestColumn).Value | H11: ="Public Property Get get" & A11 & "() : get" & A11 & " = str" & A11 & " : End Property" -> Public Property Get getQAComments() : getQAComments = strQAComments : End Property
A12: =Test_Data!D13 -> 0 | B12: ="intRow" & A12 & ", " -> intRow0, | C12: =C11 &B12 -> intRowProcess, intRowExecutionFlag, intRowDataValidationComplete, intRowHireNameComplete, intRowLastRunTimeandStatus, intRowLastRunEmployeeNo, intRowLastRunErrorMessage, intRowDefectDescription, intRowAutomationComments, intRowQAComments, intRow0, | D12: ="str" & A12 & ", " -> str0, | E12: =E11 &D12 -> strProcess, strExecutionFlag, strDataValidationComplete, strHireNameComplete, strLastRunTimeandStatus, strLastRunEmployeeNo, strLastRunErrorMessage, strDefectDescription, strAutomationComments, strQAComments, str0, | F12: ="intRow" & A12 & " = comExcelWorksheet.Range(""" & A12 & """).Row" -> intRow0 = comExcelWorksheet.Range("0").Row | G12: ="str" & A12 & " = comExcelWorksheet.Cells(intRow" & A12 & ", intColTestColumn).Value" -> str0 = comExcelWorksheet.Cells(intRow0, intColTestColumn).Value | H12: ="Public Property Get get" & A12 & "() : get" & A12 & " = str" & A12 & " : End Property" -> Public Property Get get0() : get0 = str0 : End Property
A13: =Test_Data!D14 -> Automation Ref | B13: ="intRow" & A13 & ", " -> intRowAutomation Ref, | C13: =C12 &B13 -> intRowProcess, intRowExecutionFlag, intRowDataValidationComplete, intRowHireNameComplete, intRowLastRunTimeandStatus, intRowLastRunEmployeeNo, intRowLastRunErrorMessage, intRowDefectDescription, intRowAutomationComments, intRowQAComments, intRow0, intRowAutomation Ref, | D13: ="str" & A13 & ", " -> strAutomation Ref, | E13: =E12 &D13 -> strProcess, strExecutionFlag, strDataValidationComplete, strHireNameComplete, strLastRunTimeandStatus, strLastRunEmployeeNo, strLastRunErrorMessage, strDefectDescription, strAutomationComments, strQAComments, str0, strAutomation Ref, | F13: ="intRow" & A13 & " = comExcelWorksheet.Range(""" & A13 & """).Row" -> intRowAutomation Ref = comExcelWorksheet.Range("Automation Ref").Row | G13: ="str" & A13 & " = comExcelWorksheet.Cells(intRow" & A13 & ", intColTestColumn).Value" -> strAutomation Ref = comExcelWorksheet.Cells(intRowAutomation Ref, intColTestColumn).Value | H13: ="Public Property Get get" & A13 & "() : get" & A13 & " = str" & A13 & " : End Property" -> Public Property Get getAutomation Ref() : getAutomation Ref = strAutomation Ref : End Property
A14: =Test_Data!D15 -> Login_Username | B14: ="intRow" & A14 & ", " -> intRowLogin_Username, | C14: =C13 &B14 -> intRowProcess, intRowExecutionFlag, intRowDataValidationComplete, intRowHireNameComplete, intRowLastRunTimeandStatus, intRowLastRunEmployeeNo, intRowLastRunErrorMessage, intRowDefectDescription, intRowAutomationComments, intRowQAComments, intRow0, intRowAutomation Ref, intRowLogin_Username, | D14: ="str" & A14 & ", " -> strLogin_Username, | E14: =E13 &D14 -> strProcess, strExecutionFlag, strDataValidationComplete, strHireNameComplete, strLastRunTimeandStatus, strLastRunEmployeeNo, strLastRunErrorMessage, strDefectDescription, strAutomationComments, strQAComments, str0, strAutomation Ref, strLogin_Username, | F14: ="intRow" & A14 & " = comExcelWorksheet.Range(""" & A14 & """).Row" -> intRowLogin_Username = comExcelWorksheet.Range("Login_Username").Row | G14: ="str" & A14 & " = comExcelWorksheet.Cells(intRow" & A14 & ", intColTestColumn).Value" -> strLogin_Username = comExcelWorksheet.Cells(intRowLogin_Username, intColTestColumn).Value | H14: ="Public Property Get get" & A14 & "() : get" & A14 & " = str" & A14 & " : End Property" -> Public Property Get getLogin_Username() : getLogin_Username = strLogin_Username : End Property
... A17: =Test_Data!D18 -> LegalNameInformation_Country | B17: ="intRow" & A17 & ", " -> intRowLegalNameInformation_Country, | C17: =C16 &B17 -> intRowProcess, intRowExecutionFlag, intRowDataValidationComplete, intRowHireNameComplete, intRowLastRunTimeandStatus, intRowLastRunEmployeeNo, intRowLastRunErrorMessage, intRowDefectDescription, intRowAutomationComments, intRowQAComments, intRow0, intRowAutomation Ref, intRowLogin_Username, intRowLogin_Password, intRowSupervisoryOrganisation_SupervisoryOrganisation, intRowLegalNameInformation_Country, | D17: ="str" & A17 & ", " -> strLegalNameInformation_Country, | E17: =E16 &D17 -> strProcess, strExecutionFlag, strDataValidationComplete, strHireNameComplete, strLastRunTimeandStatus, strLastRunEmployeeNo, strLastRunErrorMessage, strDefectDescription, strAutomationComments, strQAComments, str0, strAutomation Ref, strLogin_Username, strLogin_Password, strSupervisoryOrganisation_SupervisoryOrganisation, strLegalNameInformation_Country, | F17: ="intRow" & A17 & " = comExcelWorksheet.Range(""" & A17 & """).Row" -> intRowLegalNameInformation_Country = comExcelWorksheet.Range("LegalNameInformation_Country").Row | G17: ="str" & A17 & " = comExcelWorksheet.Cells(intRow" & A17 & ", intColTestColumn).Value" -> strLegalNameInformation_Country = comExcelWorksheet.Cells(intRowLegalNameInformation_Country, intColTestColumn).Value | H17: ="Public Property Get get" & A17 & "() : get" & A17 & " = str" & A17 & " : End Property" -> Public Property Get getLegalNameInformation_Country() : getLegalNameInformation_Country = strLegalNameInformation_Country : End Property
A18: =Test_Data!D20 -> LegalNameInformation_GivenName | B18: ="intRow" & A18 & ", " -> intRowLegalNameInformation_GivenName, | C18: =C17 &B18 -> intRowProcess, intRowExecutionFlag, intRowDataValidationComplete, intRowHireNameComplete, intRowLastRunTimeandStatus, intRowLastRunEmployeeNo, intRowLastRunErrorMessage, intRowDefectDescription, intRowAutomationComments, intRowQAComments, intRow0, intRowAutomation Ref, intRowLogin_Username, intRowLogin_Password, intRowSupervisoryOrganisation_SupervisoryOrganisation, intRowLegalNameInformation_Country, intRowLegalNameInformation_GivenName, | D18: ="str" & A18 & ", " -> strLegalNameInformation_GivenName, | E18: =E17 &D18 -> strProcess, strExecutionFlag, strDataValidationComplete, strHireNameComplete, strLastRunTimeandStatus, strLastRunEmployeeNo, strLastRunErrorMessage, strDefectDescription, strAutomationComments, strQAComments, str0, strAutomation Ref, strLogin_Username, strLogin_Password, strSupervisoryOrganisation_SupervisoryOrganisation, strLegalNameInformation_Country, strLegalNameInformation_GivenName, | F18: ="intRow" & A18 & " = comExcelWorksheet.Range(""" & A18 & """).Row" -> intRowLegalNameInformation_GivenName = comExcelWorksheet.Range("LegalNameInformation_GivenName").Row | G18: ="str" & A18 & " = comExcelWorksheet.Cells(intRow" & A18 & ", intColTestColumn).Value" -> strLegalNameInformation_GivenName = comExcelWorksheet.Cells(intRowLegalNameInformation_GivenName, intColTestColumn).Value | H18: ="Public Property Get get" & A18 & "() : get" & A18 & " = str" & A18 & " : End Property" -> Public Property Get getLegalNameInformation_GivenName() : getLegalNameInformation_GivenName = strLegalNameInformation_GivenName : End Property
A19: =Test_Data!D21 -> LegalNameInformation_FamilyName | B19: ="intRow" & A19 & ", " -> intRowLegalNameInformation_FamilyName, | C19: =C18 &B19 -> intRowProcess, intRowExecutionFlag, intRowDataValidationComplete, intRowHireNameComplete, intRowLastRunTimeandStatus, intRowLastRunEmployeeNo, intRowLastRunErrorMessage, intRowDefectDescription, intRowAutomationComments, intRowQAComments, intRow0, intRowAutomation Ref, intRowLogin_Username, intRowLogin_Password, intRowSupervisoryOrganisation_SupervisoryOrganisation, intRowLegalNameInformation_Country, intRowLegalNameInformation_GivenName, intRowLegalNameInformation_FamilyName, | D19: ="str" & A19 & ", " -> strLegalNameInformation_FamilyName, | E19: =E18 &D19 -> strProcess, strExecutionFlag, strDataValidationComplete, strHireNameComplete, strLastRunTimeandStatus, strLastRunEmployeeNo, strLastRunErrorMessage, strDefectDescription, strAutomationComments, strQAComments, str0, strAutomation Ref, strLogin_Username, strLogin_Password, strSupervisoryOrganisation_SupervisoryOrganisation, strLegalNameInformation_Country, strLegalNameInformation_GivenName, strLegalNameInformation_FamilyName, | F19: ="intRow" & A19 & " = comExcelWorksheet.Range(""" & A19 & """).Row" -> intRowLegalNameInformation_FamilyName = comExcelWorksheet.Range("LegalNameInformation_FamilyName").Row | G19: ="str" & A19 & " = comExcelWorksheet.Cells(intRow" & A19 & ", intColTestColumn).Value" -> strLegalNameInformation_FamilyName = comExcelWorksheet.Cells(intRowLegalNameInformation_FamilyName, intColTestColumn).Value | H19: ="Public Property Get get" & A19 & "() : get" & A19 & " = str" & A19 & " : End Property" -> Public Property Get getLegalNameInformation_FamilyName() : getLegalNameInformation_FamilyName = strLegalNameInformation_FamilyName : End Property
A20: =Test_Data!D22 -> ContactInformation_Phone_PhoneNumber | B20: ="intRow" & A20 & ", " -> intRowContactInformation_Phone_PhoneNumber, | C20: =C19 &B20 -> intRowProcess, intRowExecutionFlag, intRowDataValidationComplete, intRowHireNameComplete, intRowLastRunTimeandStatus, intRowLastRunEmployeeNo, intRowLastRunErrorMessage, intRowDefectDescription, intRowAutomationComments, intRowQAComments, intRow0, intRowAutomation Ref, intRowLogin_Username, intRowLogin_Password, intRowSupervisoryOrganisation_SupervisoryOrganisation, intRowLegalNameInformation_Country, intRowLegalNameInformation_GivenName, intRowLegalNameInformation_FamilyName, intRowContactInformation_Phone_PhoneNumber, | D20: ="str" & A20 & ", " -> strContactInformation_Phone_PhoneNumber, | E20: =E19 &D20 -> strProcess, strExecutionFlag, strDataValidationComplete, strHireNameComplete, strLastRunTimeandStatus, strLastRunEmployeeNo, strLastRunErrorMessage, strDefectDescription, strAutomationComments, strQAComments, str0, strAutomation Ref, strLogin_Username, strLogin_Password, strSupervisoryOrganisation_SupervisoryOrganisation, strLegalNameInformation_Country, strLegalNameInformation_GivenName, strLegalNameInformation_FamilyName, strContactInformation_Phone_PhoneNumber, | F20: ="intRow" & A20 & " = comExcelWorksheet.Range(""" & A20 & """).Row" -> intRowContactInformation_Phone_PhoneNumber = comExcelWorksheet.Range("ContactInformation_Phone_PhoneNumber").Row | G20: ="str" & A20 & " = comExcelWorksheet.Cells(intRow" & A20 & ", intColTestColumn).Value" -> strContactInformation_Phone_PhoneNumber = comExcelWorksheet.Cells(intRowContactInformation_Phone_PhoneNumber, intColTestColumn).Value | H20: ="Public Property Get get" & A20 & "() : get" & A20 & " = str" & A20 & " : End Property" -> Public Property Get getContactInformation_Phone_PhoneNumber() : getContactInformation_Phone_PhoneNumber = strContactInformation_Phone_PhoneNumber : End Property
A21: =Test_Data!D23 -> ContactInformation_Phone_PhoneDevice | B21: ="intRow" & A21 & ", " -> intRowContactInformation_Phone_PhoneDevice, | C21: =C20 &B21 -> intRowProcess, intRowExecutionFlag, intRowDataValidationComplete, intRowHireNameComplete, intRowLastRunTimeandStatus, intRowLastRunEmployeeNo, intRowLastRunErrorMessage, intRowDefectDescription, intRowAutomationComments, intRowQAComments, intRow0, intRowAutomation Ref, intRowLogin_Username, intRowLogin_Password, intRowSupervisoryOrganisation_SupervisoryOrganisation, intRowLegalNameInformation_Country, intRowLegalNameInformation_GivenName, intRowLegalNameInformation_FamilyName, intRowContactInformation_Phone_PhoneNumber, intRowContactInformation_Phone_PhoneDevice, | D21: ="str" & A21 & ", " -> strContactInformation_Phone_PhoneDevice, | E21: =E20 &D21 -> strProcess, strExecutionFlag, strDataValidationComplete, strHireNameComplete, strLastRunTimeandStatus, strLastRunEmployeeNo, strLastRunErrorMessage, strDefectDescription, strAutomationComments, strQAComments, str0, strAutomation Ref, strLogin_Username, strLogin_Password, strSupervisoryOrganisation_SupervisoryOrganisation, strLegalNameInformation_Country, strLegalNameInformation_GivenName, strLegalNameInformation_FamilyName, strContactInformation_Phone_PhoneNumber, strContactInformation_Phone_PhoneDevice, | F21: ="intRow" & A21 & " = comExcelWorksheet.Range(""" & A21 & """).Row" -> intRowContactInformation_Phone_PhoneDevice = comExcelWorksheet.Range("ContactInformation_Phone_PhoneDevice").Row | G21: ="str" & A21 & " = comExcelWorksheet.Cells(intRow" & A21 & ", intColTestColumn).Value" -> strContactInformation_Phone_PhoneDevice = comExcelWorksheet.Cells(intRowContactInformation_Phone_PhoneDevice, intColTestColumn).Value | H21: ="Public Property Get get" & A21 & "() : get" & A21 & " = str" & A21 & " : End Property" -> Public Property Get getContactInformation_Phone_PhoneDevice() : getContactInformation_Phone_PhoneDevice = strContactInformation_Phone_PhoneDevice : End Property
A22: =Test_Data!D24 -> ContactInformation_Phone_Type | B22: ="intRow" & A22 & ", " -> intRowContactInformation_Phone_Type, | C22: =C21 &B22 -> intRowProcess, intRowExecutionFlag, intRowDataValidationComplete, intRowHireNameComplete, intRowLastRunTimeandStatus, intRowLastRunEmployeeNo, intRowLastRunErrorMessage, intRowDefectDescription, intRowAutomationComments, intRowQAComments, intRow0, intRowAutomation Ref, intRowLogin_Username, intRowLogin_Password, intRowSupervisoryOrganisation_SupervisoryOrganisation, intRowLegalNameInformation_Country, intRowLegalNameInformation_GivenName, intRowLegalNameInformation_FamilyName, intRowContactInformation_Phone_PhoneNumber, intRowContactInformation_Phone_PhoneDevice, intRowContactInformation_Phone_Type, | D22: ="str" & A22 & ", " -> strContactInformation_Phone_Type, | E22: =E21 &D22 -> strProcess, strExecutionFlag, strDataValidationComplete, strHireNameComplete, strLastRunTimeandStatus, strLastRunEmployeeNo, strLastRunErrorMessage, strDefectDescription, strAutomationComments, strQAComments, str0, strAutomation Ref, strLogin_Username, strLogin_Password, strSupervisoryOrganisation_SupervisoryOrganisation, strLegalNameInformation_Country, strLegalNameInformation_GivenName, strLegalNameInformation_FamilyName, strContactInformation_Phone_PhoneNumber, strContactInformation_Phone_PhoneDevice, strContactInformation_Phone_Type, | F22: ="intRow" & A22 & " = comExcelWorksheet.Range(""" & A22 & """).Row" -> intRowContactInformation_Phone_Type = comExcelWorksheet.Range("ContactInformation_Phone_Type").Row | G22: ="str" & A22 & " = comExcelWorksheet.Cells(intRow" & A22 & ", intColTestColumn).Value" -> strContactInformation_Phone_Type = comExcelWorksheet.Cells(intRowContactInformation_Phone_Type, intColTestColumn).Value | H22: ="Public Property Get get" & A22 & "() : get" & A22 & " = str" & A22 & " : End Property" -> Public Property Get getContactInformation_Phone_Type() : getContactInformation_Phone_Type = strContactInformation_Phone_Type : End Property
A23: =Test_Data!D25 -> ContactInformation_Address_EffectiveDate | B23: ="intRow" & A23 & ", " -> intRowContactInformation_Address_EffectiveDate, | C23: =C22 &B23 -> intRowProcess, intRowExecutionFlag, intRowDataValidationComplete, intRowHireNameComplete, intRowLastRunTimeandStatus, intRowLastRunEmployeeNo, intRowLastRunErrorMessage, intRowDefectDescription, intRowAutomationComments, intRowQAComments, intRow0, intRowAutomation Ref, intRowLogin_Username, intRowLogin_Password, intRowSupervisoryOrganisation_SupervisoryOrganisation, intRowLegalNameInformation_Country, intRowLegalNameInformation_GivenName, intRowLegalNameInformation_FamilyName, intRowContactInformation_Phone_PhoneNumber, intRowContactInformation_Phone_PhoneDevice, intRowContactInformation_Phone_Type, intRowContactInformation_Address_EffectiveDate, | D23: ="str" & A23 & ", " -> strContactInformation_Address_EffectiveDate, | E23: =E22 &D23 -> strProcess, strExecutionFlag, strDataValidationComplete, strHireNameComplete, strLastRunTimeandStatus, strLastRunEmployeeNo, strLastRunErrorMessage, strDefectDescription, strAutomationComments, strQAComments, str0, strAutomation Ref, strLogin_Username, strLogin_Password, strSupervisoryOrganisation_SupervisoryOrganisation, strLegalNameInformation_Country, strLegalNameInformation_GivenName, strLegalNameInformation_FamilyName, strContactInformation_Phone_PhoneNumber, strContactInformation_Phone_PhoneDevice, strContactInformation_Phone_Type, strContactInformation_Address_EffectiveDate, | F23: ="intRow" & A23 & " = comExcelWorksheet.Range(""" & A23 & """).Row" -> intRowContactInformation_Address_EffectiveDate = comExcelWorksheet.Range("ContactInformation_Address_EffectiveDate").Row | G23: ="str" & A23 & " = comExcelWorksheet.Cells(intRow" & A23 & ", intColTestColumn).Value" -> strContactInformation_Address_EffectiveDate = comExcelWorksheet.Cells(intRowContactInformation_Address_EffectiveDate, intColTestColumn).Value | H23: ="Public Property Get get" & A23 & "() : get" & A23 & " = str" & A23 & " : End Property" -> Public Property Get getContactInformation_Address_EffectiveDate() : getContactInformation_Address_EffectiveDate = strContactInformation_Address_EffectiveDate : End Property
A24: =Test_Data!D26 -> ContactInformation_Address_Country | B24: ="intRow" & A24 & ", " -> intRowContactInformation_Address_Country, | C24: =C23 &B24 -> intRowProcess, intRowExecutionFlag, intRowDataValidationComplete, intRowHireNameComplete, intRowLastRunTimeandStatus, intRowLastRunEmployeeNo, intRowLastRunErrorMessage, intRowDefectDescription, intRowAutomationComments, intRowQAComments, intRow0, intRowAutomation Ref, intRowLogin_Username, intRowLogin_Password, intRowSupervisoryOrganisation_SupervisoryOrganisation, intRowLegalNameInformation_Country, intRowLegalNameInformation_GivenName, intRowLegalNameInformation_FamilyName, intRowContactInformation_Phone_PhoneNumber, intRowContactInformation_Phone_PhoneDevice, intRowContactInformation_Phone_Type, intRowContactInformation_Address_EffectiveDate, intRowContactInformation_Address_Country, | D24: ="str" & A24 & ", " -> strContactInformation_Address_Country, | E24: =E23 &D24 -> strProcess, strExecutionFlag, strDataValidationComplete, strHireNameComplete, strLastRunTimeandStatus, strLastRunEmployeeNo, strLastRunErrorMessage, strDefectDescription, strAutomationComments, strQAComments, str0, strAutomation Ref, strLogin_Username, strLogin_Password, strSupervisoryOrganisation_SupervisoryOrganisation, strLegalNameInformation_Country, strLegalNameInformation_GivenName, strLegalNameInformation_FamilyName, strContactInformation_Phone_PhoneNumber, strContactInformation_Phone_PhoneDevice, strContactInformation_Phone_Type, strContactInformation_Address_EffectiveDate, strContactInformation_Address_Country, | F24: ="intRow" & A24 & " = comExcelWorksheet.Range(""" & A24 & """).Row" -> intRowContactInformation_Address_Country = comExcelWorksheet.Range("ContactInformation_Address_Country").Row | G24: ="str" & A24 & " = comExcelWorksheet.Cells(intRow" & A24 & ", intColTestColumn).Value" -> strContactInformation_Address_Country = comExcelWorksheet.Cells(intRowContactInformation_Address_Country, intColTestColumn).Value | H24: ="Public Property Get get" & A24 & "() : get" & A24 & " = str" & A24 & " : End Property" -> Public Property Get getContactInformation_Address_Country() : getContactInformation_Address_Country = strContactInformation_Address_Country : End Property
A25: =Test_Data!D28 -> ContactInformation_Address_AdressLine1 | B25: ="intRow" & A25 & ", " -> intRowContactInformation_Address_AdressLine1, | C25: =C24 &B25 -> intRowProcess, intRowExecutionFlag, intRowDataValidationComplete, intRowHireNameComplete, intRowLastRunTimeandStatus, intRowLastRunEmployeeNo, intRowLastRunErrorMessage, intRowDefectDescription, intRowAutomationComments, intRowQAComments, intRow0, intRowAutomation Ref, intRowLogin_Username, intRowLogin_Password, intRowSupervisoryOrganisation_SupervisoryOrganisation, intRowLegalNameInformation_Country, intRowLegalNameInformation_GivenName, intRowLegalNameInformation_FamilyName, intRowContactInformation_Phone_PhoneNumber, intRowContactInformation_Phone_PhoneDevice, intRowContactInformation_Phone_Type, intRowContactInformation_Address_EffectiveDate, intRowContactInformation_Address_Country, intRowContactInformation_Address_AdressLine1, | D25: ="str" & A25 & ", " -> strContactInformation_Address_AdressLine1, | E25: =E24 &D25 -> strProcess, strExecutionFlag, strDataValidationComplete, strHireNameComplete, strLastRunTimeandStatus, strLastRunEmployeeNo, strLastRunErrorMessage, strDefectDescription, strAutomationComments, strQAComments, str0, strAutomation Ref, strLogin_Username, strLogin_Password, strSupervisoryOrganisation_SupervisoryOrganisation, strLegalNameInformation_Country, strLegalNameInformation_GivenName, strLegalNameInformation_FamilyName, strContactInformation_Phone_PhoneNumber, strContactInformation_Phone_PhoneDevice, strContactInformation_Phone_Type, strContactInformation_Address_EffectiveDate, strContactInformation_Address_Country, strContactInformation_Address_AdressLine1, | F25: ="intRow" & A25 & " = comExcelWorksheet.Range(""" & A25 & """).Row" -> intRowContactInformation_Address_AdressLine1 = comExcelWorksheet.Range("ContactInformation_Address_AdressLine1").Row | G25: ="str" & A25 & " = comExcelWorksheet.Cells(intRow" & A25 & ", intColTestColumn).Value" -> strContactInformation_Address_AdressLine1 = comExcelWorksheet.Cells(intRowContactInformation_Address_AdressLine1, intColTestColumn).Value | H25: ="Public Property Get get" & A25 & "() : get" & A25 & " = str" & A25 & " : End Property" -> Public Property Get getContactInformation_Address_AdressLine1() : getContactInformation_Address_AdressLine1 = strContactInformation_Address_AdressLine1 : End Property
A26: =Test_Data!D29 -> ContactInformation_Address_AdressLine2 | B26: ="intRow" & A26 & ", " -> intRowContactInformation_Address_AdressLine2, | C26: =C25 &B26 -> intRowProcess, intRowExecutionFlag, intRowDataValidationComplete, intRowHireNameComplete, intRowLastRunTimeandStatus, intRowLastRunEmployeeNo, intRowLastRunErrorMessage, intRowDefectDescription, intRowAutomationComments, intRowQAComments, intRow0, intRowAutomation Ref, intRowLogin_Username, intRowLogin_Password, intRowSupervisoryOrganisation_SupervisoryOrganisation, intRowLegalNameInformation_Country, intRowLegalNameInformation_GivenName, intRowLegalNameInformation_FamilyName, intRowContactInformation_Phone_PhoneNumber, intRowContactInformation_Phone_PhoneDevice, intRowContactInformation_Phone_Type, intRowContactInformation_Address_EffectiveDate, intRowContactInformation_Address_Country, intRowContactInformation_Address_AdressLine1, intRowContactInformation_Address_AdressLine2, | D26: ="str" & A26 & ", " -> strContactInformation_Address_AdressLine2, | E26: =E25 &D26 -> strProcess, strExecutionFlag, strDataValidationComplete, strHireNameComplete, strLastRunTimeandStatus, strLastRunEmployeeNo, strLastRunErrorMessage, strDefectDescription, strAutomationComments, strQAComments, str0, strAutomation Ref, strLogin_Username, strLogin_Password, strSupervisoryOrganisation_SupervisoryOrganisation, strLegalNameInformation_Country, strLegalNameInformation_GivenName, strLegalNameInformation_FamilyName, strContactInformation_Phone_PhoneNumber, strContactInformation_Phone_PhoneDevice, strContactInformation_Phone_Type, strContactInformation_Address_EffectiveDate, strContactInformation_Address_Country, strContactInformation_Address_AdressLine1, strContactInformation_Address_AdressLine2, | F26: ="intRow" & A26 & " = comExcelWorksheet.Range(""" & A26 & """).Row" -> intRowContactInformation_Address_AdressLine2 = comExcelWorksheet.Range("ContactInformation_Address_AdressLine2").Row | G26: ="str" & A26 & " = comExcelWorksheet.Cells(intRow" & A26 & ", intColTestColumn).Value" -> strContactInformation_Address_AdressLine2 = comExcelWorksheet.Cells(intRowContactInformation_Address_AdressLine2, intColTestColumn).Value | H26: ="Public Property Get get" & A26 & "() : get" & A26 & " = str" & A26 & " : End Property" -> Public Property Get getContactInformation_Address_AdressLine2() : getContactInformation_Address_AdressLine2 = strContactInformation_Address_AdressLine2 : End Property
A27: =Test_Data!D31 -> ContactInformation_Address_PostalCode | B27: ="intRow" & A27 & ", " -> intRowContactInformation_Address_PostalCode, | C27: =C26 &B27 -> intRowProcess, intRowExecutionFlag, intRowDataValidationComplete, intRowHireNameComplete, intRowLastRunTimeandStatus, intRowLastRunEmployeeNo, intRowLastRunErrorMessage, intRowDefectDescription, intRowAutomationComments, intRowQAComments, intRow0, intRowAutomation Ref, intRowLogin_Username, intRowLogin_Password, intRowSupervisoryOrganisation_SupervisoryOrganisation, intRowLegalNameInformation_Country, intRowLegalNameInformation_GivenName, intRowLegalNameInformation_FamilyName, intRowContactInformation_Phone_PhoneNumber, intRowContactInformation_Phone_PhoneDevice, intRowContactInformation_Phone_Type, intRowContactInformation_Address_EffectiveDate, intRowContactInformation_Address_Country, intRowContactInformation_Address_AdressLine1, intRowContactInformation_Address_AdressLine2, intRowContactInformation_Address_PostalCode, | D27: ="str" & A27 & ", " -> strContactInformation_Address_PostalCode, | E27: =E26 &D27 -> strProcess, strExecutionFlag, strDataValidationComplete, strHireNameComplete, strLastRunTimeandStatus, strLastRunEmployeeNo, strLastRunErrorMessage, strDefectDescription, strAutomationComments, strQAComments, str0, strAutomation Ref, strLogin_Username, strLogin_Password, strSupervisoryOrganisation_SupervisoryOrganisation, strLegalNameInformation_Country, strLegalNameInformation_GivenName, strLegalNameInformation_FamilyName, strContactInformation_Phone_PhoneNumber, strContactInformation_Phone_PhoneDevice, strContactInformation_Phone_Type, strContactInformation_Address_EffectiveDate, strContactInformation_Address_Country, strContactInformation_Address_AdressLine1, strContactInformation_Address_AdressLine2, strContactInformation_Address_PostalCode, | F27: ="intRow" & A27 & " = comExcelWorksheet.Range(""" & A27 & """).Row" -> intRowContactInformation_Address_PostalCode = comExcelWorksheet.Range("ContactInformation_Address_PostalCode").Row | G27: ="str" & A27 & " = comExcelWorksheet.Cells(intRow" & A27 & ", intColTestColumn).Value" -> strContactInformation_Address_PostalCode = comExcelWorksheet.Cells(intRowContactInformation_Address_PostalCode, intColTestColumn).Value | H27: ="Public Property Get get" & A27 & "() : get" & A27 & " = str" & A27 & " : End Property" -> Public Property Get getContactInformation_Address_PostalCode() : getContactInformation_Address_PostalCode = strContactInformation_Address_PostalCode : End Property
A28: =Test_Data!D32 -> ContactInformation_Address_City | B28: ="intRow" & A28 & ", " -> intRowContactInformation_Address_City, | C28: =C27 &B28 -> intRowProcess, intRowExecutionFlag, intRowDataValidationComplete, intRowHireNameComplete, intRowLastRunTimeandStatus, intRowLastRunEmployeeNo, intRowLastRunErrorMessage, intRowDefectDescription, intRowAutomationComments, intRowQAComments, intRow0, intRowAutomation Ref, intRowLogin_Username, intRowLogin_Password, intRowSupervisoryOrganisation_SupervisoryOrganisation, intRowLegalNameInformation_Country, intRowLegalNameInformation_GivenName, intRowLegalNameInformation_FamilyName, intRowContactInformation_Phone_PhoneNumber, intRowContactInformation_Phone_PhoneDevice, intRowContactInformation_Phone_Type, intRowContactInformation_Address_EffectiveDate, intRowContactInformation_Address_Country, intRowContactInformation_Address_AdressLine1, intRowContactInformation_Address_AdressLine2, intRowContactInformation_Address_PostalCode, intRowContactInformation_Address_City, | D28: ="str" & A28 & ", " -> strContactInformation_Address_City, | E28: =E27 &D28 -> strProcess, strExecutionFlag, strDataValidationComplete, strHireNameComplete, strLastRunTimeandStatus, strLastRunEmployeeNo, strLastRunErrorMessage, strDefectDescription, strAutomationComments, strQAComments, str0, strAutomation Ref, strLogin_Username, strLogin_Password, strSupervisoryOrganisation_SupervisoryOrganisation, strLegalNameInformation_Country, strLegalNameInformation_GivenName, strLegalNameInformation_FamilyName, strContactInformation_Phone_PhoneNumber, strContactInformation_Phone_PhoneDevice, strContactInformation_Phone_Type, strContactInformation_Address_EffectiveDate, strContactInformation_Address_Country, strContactInformation_Address_AdressLine1, strContactInformation_Address_AdressLine2, strContactInformation_Address_PostalCode, strContactInformation_Address_City, | F28: ="intRow" & A28 & " = comExcelWorksheet.Range(""" & A28 & """).Row" -> intRowContactInformation_Address_City = comExcelWorksheet.Range("ContactInformation_Address_City").Row | G28: ="str" & A28 & " = comExcelWorksheet.Cells(intRow" & A28 & ", intColTestColumn).Value" -> strContactInformation_Address_City = comExcelWorksheet.Cells(intRowContactInformation_Address_City, intColTestColumn).Value | H28: ="Public Property Get get" & A28 & "() : get" & A28 & " = str" & A28 & " : End Property" -> Public Property Get getContactInformation_Address_City() : getContactInformation_Address_City = strContactInformation_Address_City : End Property
A29: =Test_Data!#REF! -> #REF! | B29: ="intRow" & A29 & ", " -> #REF! | C29: =C28 &B29 -> #REF! | D29: ="str" & A29 & ", " -> #REF! | E29: =E28 &D29 -> #REF! | F29: ="intRow" & A29 & " = comExcelWorksheet.Range(""" & A29 & """).Row" -> #REF! | G29: ="str" & A29 & " = comExcelWorksheet.Cells(intRow" & A29 & ", intColTestColumn).Value" -> #REF! | H29: ="Public Property Get get" & A29 & "() : get" & A29 & " = str" & A29 & " : End Property" -> #REF!
A30: =Test_Data!D33 -> ContactInformation_Address_Type | B30: ="intRow" & A30 & ", " -> intRowContactInformation_Address_Type, | C30: =C29 &B30 -> #REF! | D30: ="str" & A30 & ", " -> strContactInformation_Address_Type, | E30: =E29 &D30 -> #REF! | F30: ="intRow" & A30 & " = comExcelWorksheet.Range(""" & A30 & """).Row" -> intRowContactInformation_Address_Type = comExcelWorksheet.Range("ContactInformation_Address_Type").Row | G30: ="str" & A30 & " = comExcelWorksheet.Cells(intRow" & A30 & ", intColTestColumn).Value" -> strContactInformation_Address_Type = comExcelWorksheet.Cells(intRowContactInformation_Address_Type, intColTestColumn).Value | H30: ="Public Property Get get" & A30 & "() : get" & A30 & " = str" & A30 & " : End Property" -> Public Property Get getContactInformation_Address_Type() : getContactInformation_Address_Type = strContactInformation_Address_Type : End Property
A31: =Test_Data!D34 -> ContactInformation_Address_UseFor | B31: ="intRow" & A31 & ", " -> intRowContactInformation_Address_UseFor, | C31: =C30 &B31 -> #REF! | D31: ="str" & A31 & ", " -> strContactInformation_Address_UseFor, | E31: =E30 &D31 -> #REF! | F31: ="intRow" & A31 & " = comExcelWorksheet.Range(""" & A31 & """).Row" -> intRowContactInformation_Address_UseFor = comExcelWorksheet.Range("ContactInformation_Address_UseFor").Row | G31: ="str" & A31 & " = comExcelWorksheet.Cells(intRow" & A31 & ", intColTestColumn).Value" -> strContactInformation_Address_UseFor = comExcelWorksheet.Cells(intRowContactInformation_Address_UseFor, intColTestColumn).Value | H31: ="Public Property Get get" & A31 & "() : get" & A31 & " = str" & A31 & " : End Property" -> Public Property Get getContactInformation_Address_UseFor() : getContactInformation_Address_UseFor = strContactInformation_Address_UseFor : End Property
A32: =Test_Data!D35 -> ContactInformation_Email_EmailAddress | B32: ="intRow" & A32 & ", " -> intRowContactInformation_Email_EmailAddress, | C32: =C31 &B32 -> #REF! | D32: ="str" & A32 & ", " -> strContactInformation_Email_EmailAddress, | E32: =E31 &D32 -> #REF! | F32: ="intRow" & A32 & " = comExcelWorksheet.Range(""" & A32 & """).Row" -> intRowContactInformation_Email_EmailAddress = comExcelWorksheet.Range("ContactInformation_Email_EmailAddress").Row | G32: ="str" & A32 & " = comExcelWorksheet.Cells(intRow" & A32 & ", intColTestColumn).Value" -> strContactInformation_Email_EmailAddress = comExcelWorksheet.Cells(intRowContactInformation_Email_EmailAddress, intColTestColumn).Value | H32: ="Public Property Get get" & A32 & "() : get" & A32 & " = str" & A32 & " : End Property" -> Public Property Get getContactInformation_Email_EmailAddress() : getContactInformation_Email_EmailAddress = strContactInformation_Email_EmailAddress : End Property
A33: =Test_Data!D36 -> ContactInformation_Email_Type | B33: ="intRow" & A33 & ", " -> intRowContactInformation_Email_Type, | C33: =C32 &B33 -> #REF! | D33: ="str" & A33 & ", " -> strContactInformation_Email_Type, | E33: =E32 &D33 -> #REF! | F33: ="intRow" & A33 & " = comExcelWorksheet.Range(""" & A33 & """).Row" -> intRowContactInformation_Email_Type = comExcelWorksheet.Range("ContactInformation_Email_Type").Row | G33: ="str" & A33 & " = comExcelWorksheet.Cells(intRow" & A33 & ", intColTestColumn).Value" -> strContactInformation_Email_Type = comExcelWorksheet.Cells(intRowContactInformation_Email_Type, intColTestColumn).Value | H33: ="Public Property Get get" & A33 & "() : get" & A33 & " = str" & A33 & " : End Property" -> Public Property Get getContactInformation_Email_Type() : getContactInformation_Email_Type = strContactInformation_Email_Type : End Property
A34: =Test_Data!D37 -> JobDetails_HireDate | B34: ="intRow" & A34 & ", " -> intRowJobDetails_HireDate, | C34: =C33 &B34 -> #REF! | D34: ="str" & A34 & ", " -> strJobDetails_HireDate, | E34: =E33 &D34 -> #REF! | F34: ="intRow" & A34 & " = comExcelWorksheet.Range(""" & A34 & """).Row" -> intRowJobDetails_HireDate = comExcelWorksheet.Range("JobDetails_HireDate").Row | G34: ="str" & A34 & " = comExcelWorksheet.Cells(intRow" & A34 & ", intColTestColumn).Value" -> strJobDetails_HireDate = comExcelWorksheet.Cells(intRowJobDetails_HireDate, intColTestColumn).Value | H34: ="Public Property Get get" & A34 & "() : get" & A34 & " = str" & A34 & " : End Property" -> Public Property Get getJobDetails_HireDate() : getJobDetails_HireDate = strJobDetails_HireDate : End Property
A35: =Test_Data!D39 -> JobDetails_Reason | B35: ="intRow" & A35 & ", " -> intRowJobDetails_Reason, | C35: =C34 &B35 -> #REF! | D35: ="str" & A35 & ", " -> strJobDetails_Reason, | E35: =E34 &D35 -> #REF! | F35: ="intRow" & A35 & " = comExcelWorksheet.Range(""" & A35 & """).Row" -> intRowJobDetails_Reason = comExcelWorksheet.Range("JobDetails_Reason").Row | G35: ="str" & A35 & " = comExcelWorksheet.Cells(intRow" & A35 & ", intColTestColumn).Value" -> strJobDetails_Reason = comExcelWorksheet.Cells(intRowJobDetails_Reason, intColTestColumn).Value | H35: ="Public Property Get get" & A35 & "() : get" & A35 & " = str" & A35 & " : End Property" -> Public Property Get getJobDetails_Reason() : getJobDetails_Reason = strJobDetails_Reason : End Property
A36: =Test_Data!D40 -> JobDetails_Position | B36: ="intRow" & A36 & ", " -> intRowJobDetails_Position, | C36: =C35 &B36 -> #REF! | D36: ="str" & A36 & ", " -> strJobDetails_Position, | E36: =E35 &D36 -> #REF! | F36: ="intRow" & A36 & " = comExcelWorksheet.Range(""" & A36 & """).Row" -> intRowJobDetails_Position = comExcelWorksheet.Range("JobDetails_Position").Row | G36: ="str" & A36 & " = comExcelWorksheet.Cells(intRow" & A36 & ", intColTestColumn).Value" -> strJobDetails_Position = comExcelWorksheet.Cells(intRowJobDetails_Position, intColTestColumn).Value | H36: ="Public Property Get get" & A36 & "() : get" & A36 & " = str" & A36 & " : End Property" -> Public Property Get getJobDetails_Position() : getJobDetails_Position = strJobDetails_Position : End Property
A37: =Test_Data!D41 -> JobDetails_EmployeeType | B37: ="intRow" & A37 & ", " -> intRowJobDetails_EmployeeType, | C37: =C36 &B37 -> #REF! | D37: ="str" & A37 & ", " -> strJobDetails_EmployeeType, | E37: =E36 &D37 -> #REF! | F37: ="intRow" & A37 & " = comExcelWorksheet.Range(""" & A37 & """).Row" -> intRowJobDetails_EmployeeType = comExcelWorksheet.Range("JobDetails_EmployeeType").Row | G37: ="str" & A37 & " = comExcelWorksheet.Cells(intRow" & A37 & ", intColTestColumn).Value" -> strJobDetails_EmployeeType = comExcelWorksheet.Cells(intRowJobDetails_EmployeeType, intColTestColumn).Value | H37: ="Public Property Get get" & A37 & "() : get" & A37 & " = str" & A37 & " : End Property" -> Public Property Get getJobDetails_EmployeeType() : getJobDetails_EmployeeType = strJobDetails_EmployeeType : End Property
A38: =Test_Data!D42 -> JobDetails_JobProfile | B38: ="intRow" & A38 & ", " -> intRowJobDetails_JobProfile, | C38: =C37 &B38 -> #REF! | D38: ="str" & A38 & ", " -> strJobDetails_JobProfile, | E38: =E37 &D38 -> #REF! | F38: ="intRow" & A38 & " = comExcelWorksheet.Range(""" & A38 & """).Row" -> intRowJobDetails_JobProfile = comExcelWorksheet.Range("JobDetails_JobProfile").Row | G38: ="str" & A38 & " = comExcelWorksheet.Cells(intRow" & A38 & ", intColTestColumn).Value" -> strJobDetails_JobProfile = comExcelWorksheet.Cells(intRowJobDetails_JobProfile, intColTestColumn).Value | H38: ="Public Property Get get" & A38 & "() : get" & A38 & " = str" & A38 & " : End Property" -> Public Property Get getJobDetails_JobProfile() : getJobDetails_JobProfile = strJobDetails_JobProfile : End Property
A39: =Test_Data!D43 -> JobDetails_TimeType | B39: ="intRow" & A39 & ", " -> intRowJobDetails_TimeType, | C39: =C38 &B39 -> #REF! | D39: ="str" & A39 & ", " -> strJobDetails_TimeType, | E39: =E38 &D39 -> #REF! | F39: ="intRow" & A39 & " = comExcelWorksheet.Range(""" & A39 & """).Row" -> intRowJobDetails_TimeType = comExcelWorksheet.Range("JobDetails_TimeType").Row | G39: ="str" & A39 & " = comExcelWorksheet.Cells(intRow" & A39 & ", intColTestColumn).Value" -> strJobDetails_TimeType = comExcelWorksheet.Cells(intRowJobDetails_TimeType, intColTestColumn).Value | H39: ="Public Property Get get" & A39 & "() : get" & A39 & " = str" & A39 & " : End Property" -> Public Property Get getJobDetails_TimeType() : getJobDetails_TimeType = strJobDetails_TimeType : End Property
A40: =Test_Data!D44 -> JobDetails_Location | B40: ="intRow" & A40 & ", " -> intRowJobDetails_Location, | C40: =C39 &B40 -> #REF! | D40: ="str" & A40 & ", " -> strJobDetails_Location, | E40: =E39 &D40 -> #REF! | F40: ="intRow" & A40 & " = comExcelWorksheet.Range(""" & A40 & """).Row" -> intRowJobDetails_Location = comExcelWorksheet.Range("JobDetails_Location").Row | G40: ="str" & A40 & " = comExcelWorksheet.Cells(intRow" & A40 & ", intColTestColumn).Value" -> strJobDetails_Location = comExcelWorksheet.Cells(intRowJobDetails_Location, intColTestColumn).Value | H40: ="Public Property Get get" & A40 & "() : get" & A40 & " = str" & A40 & " : End Property" -> Public Property Get getJobDetails_Location() : getJobDetails_Location = strJobDetails_Location : End Property
A41: =Test_Data!D46 -> JobDetails_AdditionalInformation_ScheduledWeeklyHours | B41: ="intRow" & A41 & ", " -> intRowJobDetails_AdditionalInformation_ScheduledWeeklyHours, | C41: =C40 &B41 -> #REF! | D41: ="str" & A41 & ", " -> strJobDetails_AdditionalInformation_ScheduledWeeklyHours, | E41: =E40 &D41 -> #REF! | F41: ="intRow" & A41 & " = comExcelWorksheet.Range(""" & A41 & """).Row" -> intRowJobDetails_AdditionalInformation_ScheduledWeeklyHours = comExcelWorksheet.Range("JobDetails_AdditionalInformation_ScheduledWeeklyHours").Row | G41: ="str" & A41 & " = comExcelWorksheet.Cells(intRow" & A41 & ", intColTestColumn).Value" -> strJobDetails_AdditionalInformation_ScheduledWeeklyHours = comExcelWorksheet.Cells(intRowJobDetails_AdditionalInformation_ScheduledWeeklyHours, intColTestColumn).Value | H41: ="Public Property Get get" & A41 & "() : get" & A41 & " = str" & A41 & " : End Property" -> Public Property Get getJobDetails_AdditionalInformation_ScheduledWeeklyHours() : getJobDetails_AdditionalInformation_ScheduledWeeklyHours = strJobDetails_AdditionalInformation_ScheduledWeeklyHours : End Property
A42: =Test_Data!D47 -> JobDetails_AdditionalInformation_AdditionalJobClassifications | B42: ="intRow" & A42 & ", " -> intRowJobDetails_AdditionalInformation_AdditionalJobClassifications, | C42: =C41 &B42 -> #REF! | D42: ="str" & A42 & ", " -> strJobDetails_AdditionalInformation_AdditionalJobClassifications, | E42: =E41 &D42 -> #REF! | F42: ="intRow" & A42 & " = comExcelWorksheet.Range(""" & A42 & """).Row" -> intRowJobDetails_AdditionalInformation_AdditionalJobClassifications = comExcelWorksheet.Range("JobDetails_AdditionalInformation_AdditionalJobClassifications").Row | G42: ="str" & A42 & " = comExcelWorksheet.Cells(intRow" & A42 & ", intColTestColumn).Value" -> strJobDetails_AdditionalInformation_AdditionalJobClassifications = comExcelWorksheet.Cells(intRowJobDetails_AdditionalInformation_AdditionalJobClassifications, intColTestColumn).Value | H42: ="Public Property Get get" & A42 & "() : get" & A42 & " = str" & A42 & " : End Property" -> Public Property Get getJobDetails_AdditionalInformation_AdditionalJobClassifications() : getJobDetails_AdditionalInformation_AdditionalJobClassifications = strJobDetails_AdditionalInformation_AdditionalJobClassifications : End Property
A43: =Test_Data!D48 -> JobDetails_AdditionalInformation_WorkShift | B43: ="intRow" & A43 & ", " -> intRowJobDetails_AdditionalInformation_WorkShift, | C43: =C42 &B43 -> #REF! | D43: ="str" & A43 & ", " -> strJobDetails_AdditionalInformation_WorkShift, | E43: =E42 &D43 -> #REF! | F43: ="intRow" & A43 & " = comExcelWorksheet.Range(""" & A43 & """).Row" -> intRowJobDetails_AdditionalInformation_WorkShift = comExcelWorksheet.Range("JobDetails_AdditionalInformation_WorkShift").Row | G43: ="str" & A43 & " = comExcelWorksheet.Cells(intRow" & A43 & ", intColTestColumn).Value" -> strJobDetails_AdditionalInformation_WorkShift = comExcelWorksheet.Cells(intRowJobDetails_AdditionalInformation_WorkShift, intColTestColumn).Value | H43: ="Public Property Get get" & A43 & "() : get" & A43 & " = str" & A43 & " : End Property" -> Public Property Get getJobDetails_AdditionalInformation_WorkShift() : getJobDetails_AdditionalInformation_WorkShift = strJobDetails_AdditionalInformation_WorkShift : End Property
A44: =Test_Data!D49 -> JobDetails_AdditionalInformation_EndEmploymentDate | B44: ="intRow" & A44 & ", " -> intRowJobDetails_AdditionalInformation_EndEmploymentDate, | C44: =C43 &B44 -> #REF! | D44: ="str" & A44 & ", " -> strJobDetails_AdditionalInformation_EndEmploymentDate, | E44: =E43 &D44 -> #REF! | F44: ="intRow" & A44 & " = comExcelWorksheet.Range(""" & A44 & """).Row" -> intRowJobDetails_AdditionalInformation_EndEmploymentDate = comExcelWorksheet.Range("JobDetails_AdditionalInformation_EndEmploymentDate").Row | G44: ="str" & A44 & " = comExcelWorksheet.Cells(intRow" & A44 & ", intColTestColumn).Value" -> strJobDetails_AdditionalInformation_EndEmploymentDate = comExcelWorksheet.Cells(intRowJobDetails_AdditionalInformation_EndEmploymentDate, intColTestColumn).Value | H44: ="Public Property Get get" & A44 & "() : get" & A44 & " = str" & A44 & " : End Property" -> Public Property Get getJobDetails_AdditionalInformation_EndEmploymentDate() : getJobDetails_AdditionalInformation_EndEmploymentDate = strJobDetails_AdditionalInformation_EndEmploymentDate : End Property
A45: =Test_Data!D50 -> JobDetails_AdditionalInformation_Comments | B45: ="intRow" & A45 & ", " -> intRowJobDetails_AdditionalInformation_Comments, | C45: =C44 &B45 -> #REF! | D45: ="str" & A45 & ", " -> strJobDetails_AdditionalInformation_Comments, | E45: =E44 &D45 -> #REF! | F45: ="intRow" & A45 & " = comExcelWorksheet.Range(""" & A45 & """).Row" -> intRowJobDetails_AdditionalInformation_Comments = comExcelWorksheet.Range("JobDetails_AdditionalInformation_Comments").Row | G45: ="str" & A45 & " = comExcelWorksheet.Cells(intRow" & A45 & ", intColTestColumn).Value" -> strJobDetails_AdditionalInformation_Comments = comExcelWorksheet.Cells(intRowJobDetails_AdditionalInformation_Comments, intColTestColumn).Value | H45: ="Public Property Get get" & A45 & "() : get" & A45 & " = str" & A45 & " : End Property" -> Public Property Get getJobDetails_AdditionalInformation_Comments() : getJobDetails_AdditionalInformation_Comments = strJobDetails_AdditionalInformation_Comments : End Property
A46: =Test_Data!D51 -> ChangeOrganizationAssignments_CostCenter | B46: ="intRow" & A46 & ", " -> intRowChangeOrganizationAssignments_CostCenter, | C46: =C45 &B46 -> #REF! | D46: ="str" & A46 & ", " -> strChangeOrganizationAssignments_CostCenter, | E46: =E45 &D46 -> #REF! | F46: ="intRow" & A46 & " = comExcelWorksheet.Range(""" & A46 & """).Row" -> intRowChangeOrganizationAssignments_CostCenter = comExcelWorksheet.Range("ChangeOrganizationAssignments_CostCenter").Row | G46: ="str" & A46 & " = comExcelWorksheet.Cells(intRow" & A46 & ", intColTestColumn).Value" -> strChangeOrganizationAssignments_CostCenter = comExcelWorksheet.Cells(intRowChangeOrganizationAssignments_CostCenter, intColTestColumn).Value | H46: ="Public Property Get get" & A46 & "() : get" & A46 & " = str" & A46 & " : End Property" -> Public Property Get getChangeOrganizationAssignments_CostCenter() : getChangeOrganizationAssignments_CostCenter = strChangeOrganizationAssignments_CostCenter : End Property
A47: =Test_Data!D52 -> ChangeOrganizationAssignments_DepartmentSection | B47: ="intRow" & A47 & ", " -> intRowChangeOrganizationAssignments_DepartmentSection, | C47: =C46 &B47 -> #REF! | D47: ="str" & A47 & ", " -> strChangeOrganizationAssignments_DepartmentSection, | E47: =E46 &D47 -> #REF! | F47: ="intRow" & A47 & " = comExcelWorksheet.Range(""" & A47 & """).Row" -> intRowChangeOrganizationAssignments_DepartmentSection = comExcelWorksheet.Range("ChangeOrganizationAssignments_DepartmentSection").Row | G47: ="str" & A47 & " = comExcelWorksheet.Cells(intRow" & A47 & ", intColTestColumn).Value" -> strChangeOrganizationAssignments_DepartmentSection = comExcelWorksheet.Cells(intRowChangeOrganizationAssignments_DepartmentSection, intColTestColumn).Value | H47: ="Public Property Get get" & A47 & "() : get" & A47 & " = str" & A47 & " : End Property" -> Public Property Get getChangeOrganizationAssignments_DepartmentSection() : getChangeOrganizationAssignments_DepartmentSection = strChangeOrganizationAssignments_DepartmentSection : End Property
A48: =Test_Data!D72 -> AssignPayGroup_ProposedPayGroupFinal | B48: ="intRow" & A48 & ", " -> intRowAssignPayGroup_ProposedPayGroupFinal, | C48: =C47 &B48 -> #REF! | D48: ="str" & A48 & ", " -> strAssignPayGroup_ProposedPayGroupFinal, | E48: =E47 &D48 -> #REF! | F48: ="intRow" & A48 & " = comExcelWorksheet.Range(""" & A48 & """).Row" -> intRowAssignPayGroup_ProposedPayGroupFinal = comExcelWorksheet.Range("AssignPayGroup_ProposedPayGroupFinal").Row | G48: ="str" & A48 & " = comExcelWorksheet.Cells(intRow" & A48 & ", intColTestColumn).Value" -> strAssignPayGroup_ProposedPayGroupFinal = comExcelWorksheet.Cells(intRowAssignPayGroup_ProposedPayGroupFinal, intColTestColumn).Value | H48: ="Public Property Get get" & A48 & "() : get" & A48 & " = str" & A48 & " : End Property" -> Public Property Get getAssignPayGroup_ProposedPayGroupFinal() : getAssignPayGroup_ProposedPayGroupFinal = strAssignPayGroup_ProposedPayGroupFinal : End Property
A49: =Test_Data!#REF! -> #REF! | B49: ="intRow" & A49 & ", " -> #REF! | C49: =C48 &B49 -> #REF! | D49: ="str" & A49 & ", " -> #REF! | E49: =E48 &D49 -> #REF! | F49: ="intRow" & A49 & " = comExcelWorksheet.Range(""" & A49 & """).Row" -> #REF! | G49: ="str" & A49 & " = comExcelWorksheet.Cells(intRow" & A49 & ", intColTestColumn).Value" -> #REF! | H49: ="Public Property Get get" & A49 & "() : get" & A49 & " = str" & A49 & " : End Property" -> #REF!
A50: =Test_Data!#REF! -> #REF! | B50: ="intRow" & A50 & ", " -> #REF! | C50: =C49 &B50 -> #REF! | D50: ="str" & A50 & ", " -> #REF! | E50: =E49 &D50 -> #REF! | F50: ="intRow" & A50 & " = comExcelWorksheet.Range(""" & A50 & """).Row" -> #REF! | G50: ="str" & A50 & " = comExcelWorksheet.Cells(intRow" & A50 & ", intColTestColumn).Value" -> #REF! | H50: ="Public Property Get get" & A50 & "() : get" & A50 & " = str" & A50 & " : End Property" -> #REF!
A51: =Test_Data!#REF! -> #REF! | B51: ="intRow" & A51 & ", " -> #REF! | C51: =C50 &B51 -> #REF! | D51: ="str" & A51 & ", " -> #REF! | E51: =E50 &D51 -> #REF! | F51: ="intRow" & A51 & " = comExcelWorksheet.Range(""" & A51 & """).Row" -> #REF! | G51: ="str" & A51 & " = comExcelWorksheet.Cells(intRow" & A51 & ", intColTestColumn).Value" -> #REF! | H51: ="Public Property Get get" & A51 & "() : get" & A51 & " = str" & A51 & " : End Property" -> #REF!
A52: =Test_Data!#REF! -> #REF! | B52: ="intRow" & A52 & ", " -> #REF! | C52: =C51 &B52 -> #REF! | D52: ="str" & A52 & ", " -> #REF! | E52: =E51 &D52 -> #REF! | F52: ="intRow" & A52 & " = comExcelWorksheet.Range(""" & A52 & """).Row" -> #REF! | G52: ="str" & A52 & " = comExcelWorksheet.Cells(intRow" & A52 & ", intColTestColumn).Value" -> #REF! | H52: ="Public Property Get get" & A52 & "() : get" & A52 & " = str" & A52 & " : End Property" -> #REF!
A53: =Test_Data!#REF! -> #REF! | B53: ="intRow" & A53 & ", " -> #REF! | C53: =C52 &B53 -> #REF! | D53: ="str" & A53 & ", " -> #REF! | E53: =E52 &D53 -> #REF! | F53: ="intRow" & A53 & " = comExcelWorksheet.Range(""" & A53 & """).Row" -> #REF! | G53: ="str" & A53 & " = comExcelWorksheet.Cells(intRow" & A53 & ", intColTestColumn).Value" -> #REF! | H53: ="Public Property Get get" & A53 & "() : get" & A53 & " = str" & A53 & " : End Property" -> #REF!
A54: =Test_Data!#REF! -> #REF! | B54: ="intRow" & A54 & ", " -> #REF! | C54: =C53 &B54 -> #REF! | D54: ="str" & A54 & ", " -> #REF! | E54: =E53 &D54 -> #REF! | F54: ="intRow" & A54 & " = comExcelWorksheet.Range(""" & A54 & """).Row" -> #REF! | G54: ="str" & A54 & " = comExcelWorksheet.Cells(intRow" & A54 & ", intColTestColumn).Value" -> #REF! | H54: ="Public Property Get get" & A54 & "() : get" & A54 & " = str" & A54 & " : End Property" -> #REF!
A55: =Test_Data!D67 -> ProposeCompensationHire_Salary | B55: ="intRow" & A55 & ", " -> intRowProposeCompensationHire_Salary, | C55: =C54 &B55 -> #REF! | D55: ="str" & A55 & ", " -> strProposeCompensationHire_Salary, | E55: =E54 &D55 -> #REF! | F55: ="intRow" & A55 & " = comExcelWorksheet.Range(""" & A55 & """).Row" -> intRowProposeCompensationHire_Salary = comExcelWorksheet.Range("ProposeCompensationHire_Salary").Row | G55: ="str" & A55 & " = comExcelWorksheet.Cells(intRow" & A55 & ", intColTestColumn).Value" -> strProposeCompensationHire_Salary = comExcelWorksheet.Cells(intRowProposeCompensationHire_Salary, intColTestColumn).Value | H55: ="Public Property Get get" & A55 & "() : get" & A55 & " = str" & A55 & " : End Property" -> Public Property Get getProposeCompensationHire_Salary() : getProposeCompensationHire_Salary = strProposeCompensationHire_Salary : End Property
A56: =Test_Data!D58 -> ChangeMyPersonalInformation_Gender | B56: ="intRow" & A56 & ", " -> intRowChangeMyPersonalInformation_Gender, | C56: =C55 &B56 -> #REF! | D56: ="str" & A56 & ", " -> strChangeMyPersonalInformation_Gender, | E56: =E55 &D56 -> #REF! | F56: ="intRow" & A56 & " = comExcelWorksheet.Range(""" & A56 & """).Row" -> intRowChangeMyPersonalInformation_Gender = comExcelWorksheet.Range("ChangeMyPersonalInformation_Gender").Row | G56: ="str" & A56 & " = comExcelWorksheet.Cells(intRow" & A56 & ", intColTestColumn).Value" -> strChangeMyPersonalInformation_Gender = comExcelWorksheet.Cells(intRowChangeMyPersonalInformation_Gender, intColTestColumn).Value | H56: ="Public Property Get get" & A56 & "() : get" & A56 & " = str" & A56 & " : End Property" -> Public Property Get getChangeMyPersonalInformation_Gender() : getChangeMyPersonalInformation_Gender = strChangeMyPersonalInformation_Gender : End Property
A57: =Test_Data!D59 -> ChangeMyPersonalInformation_DateOfBirth | B57: ="intRow" & A57 & ", " -> intRowChangeMyPersonalInformation_DateOfBirth, | C57: =C56 &B57 -> #REF! | D57: ="str" & A57 & ", " -> strChangeMyPersonalInformation_DateOfBirth, | E57: =E56 &D57 -> #REF! | F57: ="intRow" & A57 & " = comExcelWorksheet.Range(""" & A57 & """).Row" -> intRowChangeMyPersonalInformation_DateOfBirth = comExcelWorksheet.Range("ChangeMyPersonalInformation_DateOfBirth").Row | G57: ="str" & A57 & " = comExcelWorksheet.Cells(intRow" & A57 & ", intColTestColumn).Value" -> strChangeMyPersonalInformation_DateOfBirth = comExcelWorksheet.Cells(intRowChangeMyPersonalInformation_DateOfBirth, intColTestColumn).Value | H57: ="Public Property Get get" & A57 & "() : get" & A57 & " = str" & A57 & " : End Property" -> Public Property Get getChangeMyPersonalInformation_DateOfBirth() : getChangeMyPersonalInformation_DateOfBirth = strChangeMyPersonalInformation_DateOfBirth : End Property
A58: =Test_Data!D62 -> ChangeMyPersonalInformation_CityOfBirth | B58: ="intRow" & A58 & ", " -> intRowChangeMyPersonalInformation_CityOfBirth, | C58: =C57 &B58 -> #REF! | D58: ="str" & A58 & ", " -> strChangeMyPersonalInformation_CityOfBirth, | E58: =E57 &D58 -> #REF! | F58: ="intRow" & A58 & " = comExcelWorksheet.Range(""" & A58 & """).Row" -> intRowChangeMyPersonalInformation_CityOfBirth = comExcelWorksheet.Range("ChangeMyPersonalInformation_CityOfBirth").Row | G58: ="str" & A58 & " = comExcelWorksheet.Cells(intRow" & A58 & ", intColTestColumn).Value" -> strChangeMyPersonalInformation_CityOfBirth = comExcelWorksheet.Cells(intRowChangeMyPersonalInformation_CityOfBirth, intColTestColumn).Value | H58: ="Public Property Get get" & A58 & "() : get" & A58 & " = str" & A58 & " : End Property" -> Public Property Get getChangeMyPersonalInformation_CityOfBirth() : getChangeMyPersonalInformation_CityOfBirth = strChangeMyPersonalInformation_CityOfBirth : End Property
A59: =Test_Data!D63 -> ChangeMyPersonalInformation_MaritalStatus | B59: ="intRow" & A59 & ", " -> intRowChangeMyPersonalInformation_MaritalStatus, | C59: =C58 &B59 -> #REF! | D59: ="str" & A59 & ", " -> strChangeMyPersonalInformation_MaritalStatus, | E59: =E58 &D59 -> #REF! | F59: ="intRow" & A59 & " = comExcelWorksheet.Range(""" & A59 & """).Row" -> intRowChangeMyPersonalInformation_MaritalStatus = comExcelWorksheet.Range("ChangeMyPersonalInformation_MaritalStatus").Row | G59: ="str" & A59 & " = comExcelWorksheet.Cells(intRow" & A59 & ", intColTestColumn).Value" -> strChangeMyPersonalInformation_MaritalStatus = comExcelWorksheet.Cells(intRowChangeMyPersonalInformation_MaritalStatus, intColTestColumn).Value | H59: ="Public Property Get get" & A59 & "() : get" & A59 & " = str" & A59 & " : End Property" -> Public Property Get getChangeMyPersonalInformation_MaritalStatus() : getChangeMyPersonalInformation_MaritalStatus = strChangeMyPersonalInformation_MaritalStatus : End Property
A60: =Test_Data!D64 -> ChangeMyPersonalInformation_MaritalStatusDate | B60: ="intRow" & A60 & ", " -> intRowChangeMyPersonalInformation_MaritalStatusDate, | C60: =C59 &B60 -> #REF! | D60: ="str" & A60 & ", " -> strChangeMyPersonalInformation_MaritalStatusDate, | E60: =E59 &D60 -> #REF! | F60: ="intRow" & A60 & " = comExcelWorksheet.Range(""" & A60 & """).Row" -> intRowChangeMyPersonalInformation_MaritalStatusDate = comExcelWorksheet.Range("ChangeMyPersonalInformation_MaritalStatusDate").Row | G60: ="str" & A60 & " = comExcelWorksheet.Cells(intRow" & A60 & ", intColTestColumn).Value" -> strChangeMyPersonalInformation_MaritalStatusDate = comExcelWorksheet.Cells(intRowChangeMyPersonalInformation_MaritalStatusDate, intColTestColumn).Value | H60: ="Public Property Get get" & A60 & "() : get" & A60 & " = str" & A60 & " : End Property" -> Public Property Get getChangeMyPersonalInformation_MaritalStatusDate() : getChangeMyPersonalInformation_MaritalStatusDate = strChangeMyPersonalInformation_MaritalStatusDate : End Property
A61: =Test_Data!D66 -> ChangeMyPersonalInformation_PrimaryNationality | B61: ="intRow" & A61 & ", " -> intRowChangeMyPersonalInformation_PrimaryNationality, | C61: =C60 &B61 -> #REF! | D61: ="str" & A61 & ", " -> strChangeMyPersonalInformation_PrimaryNationality, | E61: =E60 &D61 -> #REF! | F61: ="intRow" & A61 & " = comExcelWorksheet.Range(""" & A61 & """).Row" -> intRowChangeMyPersonalInformation_PrimaryNationality = comExcelWorksheet.Range("ChangeMyPersonalInformation_PrimaryNationality").Row | G61: ="str" & A61 & " = comExcelWorksheet.Cells(intRow" & A61 & ", intColTestColumn).Value" -> strChangeMyPersonalInformation_PrimaryNationality = comExcelWorksheet.Cells(intRowChangeMyPersonalInformation_PrimaryNationality, intColTestColumn).Value | H61: ="Public Property Get get" & A61 & "() : get" & A61 & " = str" & A61 & " : End Property" -> Public Property Get getChangeMyPersonalInformation_PrimaryNationality() : getChangeMyPersonalInformation_PrimaryNationality = strChangeMyPersonalInformation_PrimaryNationality : End Property
A62: =Test_Data!D53 -> ChangeMyGovernmentIDs_NationalIDs_Country1 | B62: ="intRow" & A62 & ", " -> intRowChangeMyGovernmentIDs_NationalIDs_Country1, | C62: =C61 &B62 -> #REF! | D62: ="str" & A62 & ", " -> strChangeMyGovernmentIDs_NationalIDs_Country1, | E62: =E61 &D62 -> #REF! | F62: ="intRow" & A62 & " = comExcelWorksheet.Range(""" & A62 & """).Row" -> intRowChangeMyGovernmentIDs_NationalIDs_Country1 = comExcelWorksheet.Range("ChangeMyGovernmentIDs_NationalIDs_Country1").Row | G62: ="str" & A62 & " = comExcelWorksheet.Cells(intRow" & A62 & ", intColTestColumn).Value" -> strChangeMyGovernmentIDs_NationalIDs_Country1 = comExcelWorksheet.Cells(intRowChangeMyGovernmentIDs_NationalIDs_Country1, intColTestColumn).Value | H62: ="Public Property Get get" & A62 & "() : get" & A62 & " = str" & A62 & " : End Property" -> Public Property Get getChangeMyGovernmentIDs_NationalIDs_Country1() : getChangeMyGovernmentIDs_NationalIDs_Country1 = strChangeMyGovernmentIDs_NationalIDs_Country1 : End Property
A63: =Test_Data!D56 -> ChangeMyGovernmentIDs_NationalIDs_NationalIDType1 | B63: ="intRow" & A63 & ", " -> intRowChangeMyGovernmentIDs_NationalIDs_NationalIDType1, | C63: =C62 &B63 -> #REF! | D63: ="str" & A63 & ", " -> strChangeMyGovernmentIDs_NationalIDs_NationalIDType1, | E63: =E62 &D63 -> #REF! | F63: ="intRow" & A63 & " = comExcelWorksheet.Range(""" & A63 & """).Row" -> intRowChangeMyGovernmentIDs_NationalIDs_NationalIDType1 = comExcelWorksheet.Range("ChangeMyGovernmentIDs_NationalIDs_NationalIDType1").Row | G63: ="str" & A63 & " = comExcelWorksheet.Cells(intRow" & A63 & ", intColTestColumn).Value" -> strChangeMyGovernmentIDs_NationalIDs_NationalIDType1 = comExcelWorksheet.Cells(intRowChangeMyGovernmentIDs_NationalIDs_NationalIDType1, intColTestColumn).Value | H63: ="Public Property Get get" & A63 & "() : get" & A63 & " = str" & A63 & " : End Property" -> Public Property Get getChangeMyGovernmentIDs_NationalIDs_NationalIDType1() : getChangeMyGovernmentIDs_NationalIDs_NationalIDType1 = strChangeMyGovernmentIDs_NationalIDs_NationalIDType1 : End Property
A64: =Test_Data!D57 -> ChangeMyGovernmentIDs_NationalIDs_AddEditID1 | B64: ="intRow" & A64 & ", " -> intRowChangeMyGovernmentIDs_NationalIDs_AddEditID1, | C64: =C63 &B64 -> #REF! | D64: ="str" & A64 & ", " -> strChangeMyGovernmentIDs_NationalIDs_AddEditID1, | E64: =E63 &D64 -> #REF! | F64: ="intRow" & A64 & " = comExcelWorksheet.Range(""" & A64 & """).Row" -> intRowChangeMyGovernmentIDs_NationalIDs_AddEditID1 = comExcelWorksheet.Range("ChangeMyGovernmentIDs_NationalIDs_AddEditID1").Row | G64: ="str" & A64 & " = comExcelWorksheet.Cells(intRow" & A64 & ", intColTestColumn).Value" -> strChangeMyGovernmentIDs_NationalIDs_AddEditID1 = comExcelWorksheet.Cells(intRowChangeMyGovernmentIDs_NationalIDs_AddEditID1, intColTestColumn).Value | H64: ="Public Property Get get" & A64 & "() : get" & A64 & " = str" & A64 & " : End Property" -> Public Property Get getChangeMyGovernmentIDs_NationalIDs_AddEditID1() : getChangeMyGovernmentIDs_NationalIDs_AddEditID1 = strChangeMyGovernmentIDs_NationalIDs_AddEditID1 : End Property
A65: =Test_Data!#REF! -> #REF! | B65: ="intRow" & A65 & ", " -> #REF! | C65: =C64 &B65 -> #REF! | D65: ="str" & A65 & ", " -> #REF! | E65: =E64 &D65 -> #REF! | F65: ="intRow" & A65 & " = comExcelWorksheet.Range(""" & A65 & """).Row" -> #REF! | G65: ="str" & A65 & " = comExcelWorksheet.Cells(intRow" & A65 & ", intColTestColumn).Value" -> #REF! | H65: ="Public Property Get get" & A65 & "() : get" & A65 & " = str" & A65 & " : End Property" -> #REF!
A66: =Test_Data!#REF! -> #REF! | B66: ="intRow" & A66 & ", " -> #REF! | C66: =C65 &B66 -> #REF! | D66: ="str" & A66 & ", " -> #REF! | E66: =E65 &D66 -> #REF! | F66: ="intRow" & A66 & " = comExcelWorksheet.Range(""" & A66 & """).Row" -> #REF! | G66: ="str" & A66 & " = comExcelWorksheet.Cells(intRow" & A66 & ", intColTestColumn).Value" -> #REF! | H66: ="Public Property Get get" & A66 & "() : get" & A66 & " = str" & A66 & " : End Property" -> #REF!
A67: =Test_Data!#REF! -> #REF! | B67: ="intRow" & A67 & ", " -> #REF! | C67: =C66 &B67 -> #REF! | D67: ="str" & A67 & ", " -> #REF! | E67: =E66 &D67 -> #REF! | F67: ="intRow" & A67 & " = comExcelWorksheet.Range(""" & A67 & """).Row" -> #REF! | G67: ="str" & A67 & " = comExcelWorksheet.Cells(intRow" & A67 & ", intColTestColumn).Value" -> #REF! | H67: ="Public Property Get get" & A67 & "() : get" & A67 & " = str" & A67 & " : End Property" -> #REF!
A68: =Test_Data!D70 -> PaymentElectionOption_IBAN | B68: ="intRow" & A68 & ", " -> intRowPaymentElectionOption_IBAN, | C68: =C67 &B68 -> #REF! | D68: ="str" & A68 & ", " -> strPaymentElectionOption_IBAN, | E68: =E67 &D68 -> #REF! | F68: ="intRow" & A68 & " = comExcelWorksheet.Range(""" & A68 & """).Row" -> intRowPaymentElectionOption_IBAN = comExcelWorksheet.Range("PaymentElectionOption_IBAN").Row | G68: ="str" & A68 & " = comExcelWorksheet.Cells(intRow" & A68 & ", intColTestColumn).Value" -> strPaymentElectionOption_IBAN = comExcelWorksheet.Cells(intRowPaymentElectionOption_IBAN, intColTestColumn).Value | H68: ="Public Property Get get" & A68 & "() : get" & A68 & " = str" & A68 & " : End Property" -> Public Property Get getPaymentElectionOption_IBAN() : getPaymentElectionOption_IBAN = strPaymentElectionOption_IBAN : End Property
A69: =Test_Data!D71 -> PaymentElectionOption_AccountType | B69: ="intRow" & A69 & ", " -> intRowPaymentElectionOption_AccountType, | C69: =C68 &B69 -> #REF! | D69: ="str" & A69 & ", " -> strPaymentElectionOption_AccountType, | E69: =E68 &D69 -> #REF! | F69: ="intRow" & A69 & " = comExcelWorksheet.Range(""" & A69 & """).Row" -> intRowPaymentElectionOption_AccountType = comExcelWorksheet.Range("PaymentElectionOption_AccountType").Row | G69: ="str" & A69 & " = comExcelWorksheet.Cells(intRow" & A69 & ", intColTestColumn).Value" -> strPaymentElectionOption_AccountType = comExcelWorksheet.Cells(intRowPaymentElectionOption_AccountType, intColTestColumn).Value | H69: ="Public Property Get get" & A69 & "() : get" & A69 & " = str" & A69 & " : End Property" -> Public Property Get getPaymentElectionOption_AccountType() : getPaymentElectionOption_AccountType = strPaymentElectionOption_AccountType : End Property
A70: =Test_Data!#REF! -> #REF! | B70: ="intRow" & A70 & ", " -> #REF! | C70: =C69 &B70 -> #REF! | D70: ="str" & A70 & ", " -> #REF! | E70: =E69 &D70 -> #REF! | F70: ="intRow" & A70 & " = comExcelWorksheet.Range(""" & A70 & """).Row" -> #REF! | G70: ="str" & A70 & " = comExcelWorksheet.Cells(intRow" & A70 & ", intColTestColumn).Value" -> #REF! | H70: ="Public Property Get get" & A70 & "() : get" & A70 & " = str" & A70 & " : End Property" -> #REF!
A71: =Test_Data!#REF! -> #REF! | B71: ="intRow" & A71 & ", " -> #REF! | C71: =C70 &B71 -> #REF! | D71: ="str" & A71 & ", " -> #REF! | E71: =E70 &D71 -> #REF! | F71: ="intRow" & A71 & " = comExcelWorksheet.Range(""" & A71 & """).Row" -> #REF! | G71: ="str" & A71 & " = comExcelWorksheet.Cells(intRow" & A71 & ", intColTestColumn).Value" -> #REF! | H71: ="Public Property Get get" & A71 & "() : get" & A71 & " = str" & A71 & " : End Property" -> #REF!
A72: =Test_Data!#REF! -> #REF! | B72: ="intRow" & A72 & ", " -> #REF! | C72: =C71 &B72 -> #REF! | D72: ="str" & A72 & ", " -> #REF! | E72: =E71 &D72 -> #REF! | F72: ="intRow" & A72 & " = comExcelWorksheet.Range(""" & A72 & """).Row" -> #REF! | G72: ="str" & A72 & " = comExcelWorksheet.Cells(intRow" & A72 & ", intColTestColumn).Value" -> #REF! | H72: ="Public Property Get get" & A72 & "() : get" & A72 & " = str" & A72 & " : End Property" -> #REF!
A73: =Test_Data!#REF! -> #REF! | B73: ="intRow" & A73 & ", " -> #REF! | C73: =C72 &B73 -> #REF! | D73: ="str" & A73 & ", " -> #REF! | E73: =E72 &D73 -> #REF! | F73: ="intRow" & A73 & " = comExcelWorksheet.Range(""" & A73 & """).Row" -> #REF! | G73: ="str" & A73 & " = comExcelWorksheet.Cells(intRow" & A73 & ", intColTestColumn).Value" -> #REF! | H73: ="Public Property Get get" & A73 & "() : get" & A73 & " = str" & A73 & " : End Property" -> #REF!
A74: =Test_Data!#REF! -> #REF! | B74: ="intRow" & A74 & ", " -> #REF! | C74: =C73 &B74 -> #REF! | D74: ="str" & A74 & ", " -> #REF! | E74: =E73 &D74 -> #REF! | F74: ="intRow" & A74 & " = comExcelWorksheet.Range(""" & A74 & """).Row" -> #REF! | G74: ="str" & A74 & " = comExcelWorksheet.Cells(intRow" & A74 & ", intColTestColumn).Value" -> #REF! | H74: ="Public Property Get get" & A74 & "() : get" & A74 & " = str" & A74 & " : End Property" -> #REF!

Sheet Names
B3: Etoecyeone | C3: 1 | D3: one | F3: 1 | G3: one | J3: =G3&H3 -> one | K3: one
B4: Etoecyeone | C4: 2 | D4: two | F4: 2 | G4: two | J4: =G4&H4 -> two | K4: two
B5: Etoecyeone | C5: 3 | D5: three | F5: 3 | G5: three | J5: =G5&H5 -> three | K5: three
B6: Etoecyeone | C6: 4 | D6: four | F6: 4 | G6: four | J6: =G6&H6 -> four | K6: four
B7: Etoecyeone | C7: 5 | D7: five | F7: 5 | G7: five | J7: =G7&H7 -> five | K7: five
B8: Etoecyeone | C8: 6 | D8: six | F8: 6 | G8: six | J8: =G8&H8 -> six | K8: six
B9: Etoecyeone | C9: 7 | D9: seven | F9: 7 | G9: seven | J9: =G9&H9 -> seven | K9: seven
B10: Etoecyeone | C10: 8 | D10: eight | F10: 8 | G10: eight | J10: =G10&H10 -> eight | K10: eight
B11: Etoecyeone | C11: 9 | D11: nine | F11: 9 | G11: nine | J11: =G11&H11 -> nine | K11: nine
B12: Etoecyeone | C12: 10 | D12: ten | F12: 10 | G12: ten | J12: =G12&H12 -> ten | K12: ten
B13: Etoecyeone | C13: 11 | D13: eleven | F13: 11 | G13: eleven | J13: =G13&H13 -> eleven | K13: eleven
B14: Etoecyeone | C14: 12 | D14: twelve | F14: 12 | G14: twelve | J14: =G14&H14 -> twelve | K14: twelve
B15: Etoecyeone | C15: 13 | D15: thirteen | F15: 13 | G15: thirteen | J15: =G15&H15 -> thirteen | K15: thirteen
... B22: Etoecyeone | C22: 20 | D22: twenty | F22: 20 | G22: twenty | J22: =G22&H22 -> twenty | K22: twenty
B23: Etoecyeone | C23: 30 | D23: thirty | F23: 21 | G23: twenty | H23: one | J23: =G23&H23 -> twentyone | K23: twentyone
B24: Etoecyeone | C24: 40 | D24: forty | F24: 22 | G24: twenty | H24: two | J24: =G24&H24 -> twentytwo | K24: twentytwo
B25: Etoecyeone | C25: 50 | D25: fifty | F25: 23 | G25: twenty | H25: three | J25: =G25&H25 -> twentythree | K25: twentythree
B26: Etoecyeone | C26: 60 | D26: sixty | F26: 24 | G26: twenty | H26: four | J26: =G26&H26 -> twentyfour | K26: twentyfour
B27: Etoecyeone | C27: 70 | D27: seventy | F27: 25 | G27: twenty | H27: five | J27: =G27&H27 -> twentyfive | K27: twentyfive
B28: Etoecyeone | C28: 80 | D28: eighty | F28: 26 | G28: twenty | H28: six | J28: =G28&H28 -> twentysix | K28: twentysix
B29: Etoecyeone | C29: 90 | D29: ninety | F29: 27 | G29: twenty | H29: seven | J29: =G29&H29 -> twentyseven | K29: twentyseven
B30: Etoecyeone | C30: 100 | D30: one hundred | F30: 28 | G30: twenty | H30: eight | J30: =G30&H30 -> twentyeight | K30: twentyeight
B31: Etoecyeone | C31: 1000 | D31: one thousand | F31: 29 | G31: twenty | H31: nine | J31: =G31&H31 -> twentynine | K31: twentynine
B32: Etoecyeone | F32: 30 | G32: thirty | J32: =G32&H32 -> thirty | K32: thirty
B33: Etoecyeone | F33: 31 | G33: thirty | H33: one | J33: =G33&H33 -> thirtyone | K33: thirtyone
B34: Etoecyeone | F34: 32 | G34: thirty | H34: two | J34: =G34&H34 -> thirtytwo | K34: thirtytwo
B35: Etoecyeone | F35: 33 | G35: thirty | H35: three | J35: =G35&H35 -> thirtythree | K35: thirtythree
B36: Etoecyeone | F36: 34 | G36: thirty | H36: four | J36: =G36&H36 -> thirtyfour | K36: thirtyfour
B37: Etoecyeone | F37: 35 | G37: thirty | H37: five | J37: =G37&H37 -> thirtyfive | K37: thirtyfive
B38: Etoecyeone | F38: 36 | G38: thirty | H38: six | J38: =G38&H38 -> thirtysix | K38: thirtysix
B39: Etoecyeone | F39: 37 | G39: thirty | H39: seven | J39: =G39&H39 -> thirtyseven | K39: thirtyseven
B40: Etoecyeone | F40: 38 | G40: thirty | H40: eight | J40: =G40&H40 -> thirtyeight | K40: thirtyeight
B41: Etoecyeone | F41: 39 | G41: thirty | H41: nine | J41: =G41&H41 -> thirtynine | K41: thirtynine
B42: Etoecyeone | F42: 40 | G42: forty | J42: =G42&H42 -> forty | K42: forty
B43: Etoecyeone | F43: 41 | G43: forty | H43: one | J43: =G43&H43 -> fortyone | K43: fortyone
B44: Etoecyeone | F44: 42 | G44: forty | H44: two | J44: =G44&H44 -> fortytwo | K44: fortytwo
B45: Etoecyeone | F45: 43 | G45: forty | H45: three | J45: =G45&H45 -> fortythree | K45: fortythree
B46: Etoecyeone | F46: 44 | G46: forty | H46: four | J46: =G46&H46 -> fortyfour | K46: fortyfour
B47: Etoecyeone | F47: 45 | G47: forty | H47: five | J47: =G47&H47 -> fortyfive | K47: fortyfive
B48: Etoecyeone | F48: 46 | G48: forty | H48: six | J48: =G48&H48 -> fortysix | K48: fortysix
B49: Etoecyeone | F49: 47 | G49: forty | H49: seven | J49: =G49&H49 -> fortyseven | K49: fortyseven
B50: Etoecyeone | F50: 48 | G50: forty | H50: eight | J50: =G50&H50 -> fortyeight | K50: fortyeight
B51: Etoecyeone | F51: 49 | G51: forty | H51: nine | J51: =G51&H51 -> fortynine | K51: fortynine
B52: Etoecyeone | F52: 50 | G52: fifty | J52: =G52&H52 -> fifty | K52: fifty
B53: Etoecyeone | F53: 51 | G53: fifty | H53: one | J53: =G53&H53 -> fiftyone | K53: fiftyone
B54: Etoecyeone | F54: 52 | G54: fifty | H54: two | J54: =G54&H54 -> fiftytwo | K54: fiftytwo
B55: ETOE | F55: 53 | G55: fifty | H55: three | J55: =G55&H55 -> fiftythree | K55: fiftythree | U55: ETOEfiftynine | V55: ETOEsixty | W55: ETOEsixtyone | X55: ETOEsixtytwo | Y55: ETOEsixtythree | Z55: ETOEsixtyfour | AA55: ETOEsixtyfive | AB55: ETOEsixtysix | AC55: ETOEsixtyseven | AD55: ETOEsixtyeight | AE55: ETOEsixtynine | AF55: ETOEseventy | AG55: ETOEseventyone | AH55: ETOEseventytwo | AI55: ETOEseventythree | AJ55: ETOEseventyfour | AK55: ETOEseventyfive | AL55: ETOEseventysix | AM55: ETOEseventyseven | AN55: ETOEseventyeight | AO55: ETOEseventynine | AP55: ETOEeighty | AQ55: ETOEeightyone | AR55: ETOEeightytwo | AS55: ETOEeightythree | AT55: ETOEeightyfour | AU55: ETOEeightyfive | AV55: ETOEeightysix | AW55: ETOEeightyseven | AX55: ETOEeightyeight | AY55: ETOEeightynine | AZ55: ETOEninety | BA55: ETOEninetyone | BB55: ETOEninetytwo | BC55: ETOEninetythree | BD55: ETOEninetyfour | BE55: ETOEninetyfive | BF55: ETOEninetysix | BG55: ETOEninetyseven | BH55: ETOEninetyeight | BI55: ETOEninetynine | BJ55: ETOEonezerozero | BK55: ETOEonezerooneone | BL55: ETOEonezerotwotwo | BM55: ETOEonezerothreethree | BN55: ETOEonezerofourfour | BO55: ETOEonezerofivefive | BP55: ETOEonezerosixsix | BQ55: ETOEonezerosevenseven | BR55: ETOEonezeroeighteight | BS55: ETOEonezeroninenine | BT55: ETOEoneonezero | BU55: ETOEoneoneone | BV55: ETOEoneonetwo | BW55: ETOEoneonethree | BX55: ETOEoneonefour | BY55: ETOEoneonefive | BZ55: ETOEoneonesix | CA55: ETOEoneoneseven | CB55: ETOEoneoneeight | CC55: ETOEoneonenine | CD55: ETOEonetwozero | CE55: ETOEonetwoone | CF55: ETOEonetwotwo | CG55: ETOEonetwothree | CH55: ETOEonetwofour | CI55: ETOEonetwofive | CJ55: ETOEonetwosix | CK55: ETOEonetwoseven | CL55: ETOEonetwoeight | CM55: ETOEonetwonine | CN55: ETOEonethreezero | CO55: ETOEonethreeone | CP55: ETOEonethreetwo | CQ55: ETOEonethreethree | CR55: ETOEonethreefour | CS55: ETOEonethreefive | CT55: ETOEonethreesix | CU55: ETOEonethreeseven | CV55: ETOEonethreeeight | CW55: ETOEonethreenine | CX55: ETOEonefourzero | CY55: ETOEonefourone | CZ55: ETOEonefourtwo | DA55: ETOEonefourthree | DB55: ETOEonefourfour | DC55: ETOEonefourfive | DD55: ETOEonefoursix | DE55: ETOEonefourseven | DF55: ETOEonefoureight | DG55: ETOEonefournine | DH55: ETOEonefivezero
B56: ETOE | F56: 54 | G56: fifty | H56: four | J56: =G56&H56 -> fiftyfour | K56: fiftyfour
B57: ETOE | F57: 55 | G57: fifty | H57: five | J57: =G57&H57 -> fiftyfive | K57: fiftyfive
B58: ETOE | F58: 56 | G58: fifty | H58: six | J58: =G58&H58 -> fiftysix | K58: fiftysix
B59: ETOE | F59: 57 | G59: fifty | H59: seven | J59: =G59&H59 -> fiftyseven | K59: fiftyseven
B60: ETOE | F60: 58 | G60: fifty | H60: eight | J60: =G60&H60 -> fiftyeight | K60: fiftyeight
B61: ETOE | F61: 59 | G61: fifty | H61: nine | J61: =G61&H61 -> fiftynine | K61: fiftynine
B62: ETOE | F62: 60 | G62: sixty | J62: =G62&H62 -> sixty | K62: sixty
B63: ETOE | F63: 61 | G63: sixty | H63: one | J63: =G63&H63 -> sixtyone | K63: sixtyone
B64: ETOE | F64: 62 | G64: sixty | H64: two | J64: =G64&H64 -> sixtytwo | K64: sixtytwo
B65: ETOE | F65: 63 | G65: sixty | H65: three | J65: =G65&H65 -> sixtythree | K65: sixtythree
B66: ETOE | F66: 64 | G66: sixty | H66: four | J66: =G66&H66 -> sixtyfour | K66: sixtyfour
B67: ETOE | F67: 65 | G67: sixty | H67: five | J67: =G67&H67 -> sixtyfive | K67: sixtyfive
B68: ETOE | F68: 66 | G68: sixty | H68: six | J68: =G68&H68 -> sixtysix | K68: sixtysix
B69: ETOE | F69: 67 | G69: sixty | H69: seven | J69: =G69&H69 -> sixtyseven | K69: sixtyseven
B70: ETOE | F70: 68 | G70: sixty | H70: eight | J70: =G70&H70 -> sixtyeight | K70: sixtyeight
B71: ETOE | F71: 69 | G71: sixty | H71: nine | J71: =G71&H71 -> sixtynine | K71: sixtynine
B72: ETOE | F72: 70 | G72: seventy | J72: =G72&H72 -> seventy | K72: seventy
B73: ETOE | F73: 71 | G73: seventy | H73: one | J73: =G73&H73 -> seventyone | K73: seventyone
B74: ETOE | F74: 72 | G74: seventy | H74: two | J74: =G74&H74 -> seventytwo | K74: seventytwo
B75: ETOE | F75: 73 | G75: seventy | H75: three | J75: =G75&H75 -> seventythree | K75: seventythree
B76: ETOE | F76: 74 | G76: seventy | H76: four | J76: =G76&H76 -> seventyfour | K76: seventyfour
B77: ETOE | F77: 75 | G77: seventy | H77: five | J77: =G77&H77 -> seventyfive | K77: seventyfive
B78: ETOE | F78: 76 | G78: seventy | H78: six | J78: =G78&H78 -> seventysix | K78: seventysix
B79: ETOE | F79: 77 | G79: seventy | H79: seven | J79: =G79&H79 -> seventyseven | K79: seventyseven
B80: ETOE | F80: 78 | G80: seventy | H80: eight | J80: =G80&H80 -> seventyeight | K80: seventyeight
B81: ETOE | F81: 79 | G81: seventy | H81: nine | J81: =G81&H81 -> seventynine | K81: seventynine
B82: ETOE | F82: 80 | G82: eighty | J82: =G82&H82 -> eighty | K82: eighty
B83: ETOE | F83: 81 | G83: eighty | H83: one | J83: =G83&H83 -> eightyone | K83: eightyone
B84: ETOE | F84: 82 | G84: eighty | H84: two | J84: =G84&H84 -> eightytwo | K84: eightytwo
B85: ETOE | F85: 83 | G85: eighty | H85: three | J85: =G85&H85 -> eightythree | K85: eightythree
B86: ETOE | F86: 84 | G86: eighty | H86: four | J86: =G86&H86 -> eightyfour | K86: eightyfour
B87: ETOE | F87: 85 | G87: eighty | H87: five | J87: =G87&H87 -> eightyfive | K87: eightyfive
B88: ETOE | F88: 86 | G88: eighty | H88: six | J88: =G88&H88 -> eightysix | K88: eightysix
B89: ETOE | F89: 87 | G89: eighty | H89: seven | J89: =G89&H89 -> eightyseven | K89: eightyseven
B90: ETOE | F90: 88 | G90: eighty | H90: eight | J90: =G90&H90 -> eightyeight | K90: eightyeight
B91: ETOE | F91: 89 | G91: eighty | H91: nine | J91: =G91&H91 -> eightynine | K91: eightynine
B92: ETOE | F92: 90 | G92: ninety | J92: =G92&H92 -> ninety | K92: ninety
B93: ETOE | F93: 91 | G93: ninety | H93: one | J93: =G93&H93 -> ninetyone | K93: ninetyone
B94: ETOE | F94: 92 | G94: ninety | H94: two | J94: =G94&H94 -> ninetytwo | K94: ninetytwo
B95: ETOE | F95: 93 | G95: ninety | H95: three | J95: =G95&H95 -> ninetythree | K95: ninetythree
B96: ETOE | F96: 94 | G96: ninety | H96: four | J96: =G96&H96 -> ninetyfour | K96: ninetyfour
B97: ETOE | F97: 95 | G97: ninety | H97: five | J97: =G97&H97 -> ninetyfive | K97: ninetyfive
B98: ETOE | F98: 96 | G98: ninety | H98: six | J98: =G98&H98 -> ninetysix | K98: ninetysix
B99: ETOE | F99: 97 | G99: ninety | H99: seven | J99: =G99&H99 -> ninetyseven | K99: ninetyseven
B100: ETOE | F100: 98 | G100: ninety | H100: eight | J100: =G100&H100 -> ninetyeight | K100: ninetyeight
B101: ETOE | F101: 99 | G101: ninety | H101: nine | J101: =G101&H101 -> ninetynine | K101: ninetynine
B102: ETOE | F102: 100 | G102: one | H102: zero | I102: zero | J102: =G102&H102&I102 -> onezerozero | K102: onezerozero
B103: ETOE | F103: 101 | G103: one | H103: zero | I103: one | J103: =G103&H103&I103 -> onezeroone | K103: onezeroone | U103: Etoecyeoneonehundredone | V103: Etoecyeoneonehundredtwo | W103: Etoecyeoneonehundredthree | X103: Etoecyeoneonehundredfour | Y103: Etoecyeoneonehundredfive | Z103: Etoecyeoneonehundredsix | AA103: Etoecyeoneonehundredseven | AB103: Etoecyeoneonehundredeight | AC103: Etoecyeoneonehundrednine
B104: ETOE | F104: 102 | G104: one | H104: zero | I104: two | J104: =G104&H104&I104 -> onezerotwo | K104: onezerotwo
B105: ETOE | F105: 103 | G105: one | H105: zero | I105: three | J105: =G105&H105&I105 -> onezerothree | K105: onezerothree
B106: ETOE | F106: 104 | G106: one | H106: zero | I106: four | J106: =G106&H106&I106 -> onezerofour | K106: onezerofour
B107: ETOE | F107: 105 | G107: one | H107: zero | I107: five | J107: =G107&H107&I107 -> onezerofive | K107: onezerofive
B108: ETOE | F108: 106 | G108: one | H108: zero | I108: six | J108: =G108&H108&I108 -> onezerosix | K108: onezerosix
...

Sheet Test_Data
A1: Version_Number | C1: Test_ID | D1: Test_ID | E1: Test_ID2 | F1: Notes | G1: Test_1 | H1: Test_2 | I1: Test_3 | J1: Test_4 | K1: Test_5 | L1: Test_6 | M1: Test_7 | N1: Test_8 | O1: Test_9 | P1: Test_10 | Q1: Test_11 | R1: Test_12 | S1: Test_13 | T1: Test_14 | U1: Test_15
A2: 0.3 | C2: Reporting_ID | G2: 1 | H2: 2 | I2: 3 | J2: 4 | K2: 5 | L2: 6 | M2: 7 | N2: 8 | O2: 9 | P2: 10 | Q2: 11 | R2: 12 | S2: 13 | T2: 14 | U2: 15
C3: Process | D3: Process | E3: Process2 | F3: If a manager hire and new role is required then select "New Role and New Hire" otherwise select "New Hire | G3: New Hire | H3: New Role & New Hire | I3: New Role & New Hire | J3: New Role & New Hire | K3: New Role & New Hire | L3: New Role & New Hire | M3: New Role & New Hire | N3: New Hire | O3: New Role & New Hire | P3: New Hire | Q3: New Role & New Hire | R3: New Role & New Hire | S3: New Hire | T3: New Hire | U3: New Hire
C4: Execution Flag | D4: ExecutionFlag | E4: ExecutionFlag2 | F4: If set to No will not execute in next automation run | G4: Yes | H4: Yes | I4: Yes | J4: Yes | K4: Yes | L4: Yes | M4: Yes | N4: Yes | O4: Yes | P4: Yes | Q4: Yes | R4: Yes | S4: Yes | T4: Yes | U4: Yes
C5: Data Validation Complete | D5: DataValidationComplete | E5: DataValidationComplete2 | G5: TRUE | H5: TRUE | I5: TRUE | J5: TRUE | K5: TRUE | L5: TRUE | M5: TRUE | N5: TRUE | O5: TRUE | P5: TRUE | Q5: TRUE | R5: TRUE | S5: TRUE | T5: TRUE | U5: TRUE
C6: Hire Name Complete | D6: HireNameComplete | E6: HireNameComplete2 | G6: TRUE | H6: TRUE | I6: TRUE | J6: TRUE | K6: TRUE | L6: TRUE | M6: TRUE | N6: TRUE | O6: TRUE | P6: TRUE | Q6: TRUE | R6: TRUE | S6: TRUE | T6: TRUE | U6: TRUE
C7: Last Run Time and Status | D7: LastRunTimeandStatus | E7: LastRunTimeandStatus2 | F7: Once test is executed the Execution Timestamp and Pass/Fail status will be recorded here | G7: 06/10/2024 01:23:49 Failed | H7: 06/10/2024 01:35:20 Failed | I7: 06/10/2024 01:37:48 Failed | J7: 06/10/2024 01:49:28 Failed | K7: 06/10/2024 02:01:14 Failed | L7: 06/10/2024 02:12:48 Failed | M7: 06/10/2024 02:24:21 Failed | N7: 06/10/2024 02:34:01 Failed | O7: 06/10/2024 02:45:46 Failed | P7: 06/10/2024 02:55:23 Failed | Q7: 06/10/2024 03:06:58 Failed | R7: 06/10/2024 03:18:29 Failed | S7: 06/10/2024 03:28:11 Failed | T7: 06/10/2024 03:37:48 Failed | U7: 06/10/2024 03:47:28 Failed
C8: Last Run Employee No | D8: LastRunEmployeeNo | E8: LastRunEmployeeNo2 | F8: The newly created employee number will be recorded here
C9: Last Run Error Message | D9: LastRunErrorMessage | E9: LastRunErrorMessage2 | F9: If Automation throws errors, the details will be placed here | G9: Field not found for Class = "PageHireProposeCompensationHire" at Function = "getBasePayRange"_x000D_ Code Number = New Hire 273_x000D_ Location of Failure screenshot = D:\Workday_FailureScreenshot\Test_1_NewHire_Ireland_ 06102024 012341.png_x000D_ _x000D_ Main action error_x000D_ Code Number = New Hire 280_x000D_ Error Number = 9_x000D_ Error Message = Subscript out of range_x000D_ Error Source = Microsoft VBScript runtime error_x000D_ | H9: Field not found for Class = "PageHireProposeCompensationHire" at Function = "getBasePayRange"_x000D_ Code Number = New Hire 273_x000D_ Location of Failure screenshot = D:\Workday_FailureScreenshot\Test_2NewRoleNewHire_Ireland_ 06102024 013512.png_x000D_ _x000D_ Main action error_x000D_ Code Number = New Hire 280_x000D_ Error Number = 9_x000D_ Error Message = Subscript out of range_x000D_ Error Source = Microsoft VBScript runtime error_x000D_ | I9: Field not found for Class = "PageLogin" at Function = "waitExistsUsername"_x000D_ Code Number = Role 175_x000D_ Location of Failure screenshot = D:\Workday_FailureScreenshot\Test_3NewRoleNewHire_Ireland_ 06102024 013641.png_x000D_ _x000D_ Main action error_x000D_ Code Number = Role 175_x000D_ Main action error_x000D_ Code Number = New Hire 120_x000D_ | J9: Field not found for Class = "PageHireProposeCompensationHire" at Function = "getBasePayRange"_x000D_ Code Number = New Hire 273_x000D_ Location of Failure screenshot = D:\Workday_FailureScreenshot\Test_4NewRoleNewHire_Ireland_ 06102024 014920.png_x000D_ _x000D_ Main action error_x000D_ Code Number = New Hire 280_x000D_ Error Number = 9_x000D_ Error Message = Subscript out of range_x000D_ Error Source = Microsoft VBScript runtime error_x000D_ | K9: Field not found for Class = "PageHireProposeCompensationHire" at Function = "getBasePayRange"_x000D_ Code Number = New Hire 273_x000D_ Location of Failure screenshot = D:\Workday_FailureScreenshot\Test_5NewRoleNewHire_Ireland_ 06102024 020106.png_x000D_ _x000D_ Main action error_x000D_ Code Number = New Hire 280_x000D_ Error Number = 9_x000D_ Error Message = Subscript out of range_x000D_ Error Source = Microsoft VBScript runtime error_x000D_ | L9: Field not found for Class = "PageHireProposeCompensationHire" at Function = "getBasePayRange"_x000D_ Code Number = New Hire 273_x000D_ Location of Failure screenshot = D:\Workday_FailureScreenshot\Test_6NewRoleNewHire_Ireland_ 06102024 021240.png_x000D_ _x000D_ Main action error_x000D_ Code Number = New Hire 280_x000D_ Error Number = 9_x000D_ Error Message = Subscript out of range_x000D_ Error Source = Microsoft VBScript runtime error_x000D_ | M9: Field not found for Class = "PageHireProposeCompensationHire" at Function = "getBasePayRange"_x000D_ Code Number = New Hire 273_x000D_ Location of Failure screenshot = D:\Workday_FailureScreenshot\Test_7NewRoleNewHire_Ireland_ 06102024 022413.png_x000D_ _x000D_ Main action error_x000D_ Code Number = New Hire 280_x000D_ Error Number = 9_x000D_ Error Message = Subscript out of range_x000D_ Error Source = Microsoft VBScript runtime error_x000D_ | N9: Field not found for Class = "PageHireProposeCompensationHire" at Function = "getBasePayRange"_x000D_ Code Number = New Hire 273_x000D_ Location of Failure screenshot = D:\Workday_FailureScreenshot\Test_8_NewHire_Ireland_ 06102024 023352.png_x000D_ _x000D_ Main action error_x000D_ Code Number = New Hire 280_x000D_ Error Number = 9_x000D_ Error Message = Subscript out of range_x000D_ Error Source = Microsoft VBScript runtime error_x000D_ | O9: Field not found for Class = "PageHireProposeCompensationHire" at Function = "getBasePayRange"_x000D_ Code Number = New Hire 273_x000D_ Location of Failure screenshot = D:\Workday_FailureScreenshot\Test_9NewRoleNewHire_Ireland_ 06102024 024538.png_x000D_ _x000D_ Main action error_x000D_ Code Number = New Hire 280_x000D_ Error Number = 9_x000D_ Error Message = Subscript out of range_x000D_ Error Source = Microsoft VBScript runtime error_x000D_ | P9: Field not found for Class = "PageHireProposeCompensationHire" at Function = "getBasePayRange"_x000D_ Code Number = New Hire 273_x000D_ Location of Failure screenshot = D:\Workday_FailureScreenshot\Test_10_NewHire_Ireland_ 06102024 025515.png_x000D_ _x000D_ Main action error_x000D_ Code Number = New Hire 280_x000D_ Error Number = 9_x000D_ Error Message = Subscript out of range_x000D_ Error Source = Microsoft VBScript runtime error_x000D_ | Q9: Field not found for Class = "PageHireProposeCompensationHire" at Function = "getBasePayRange"_x000D_ Code Number = New Hire 273_x000D_ Location of Failure screenshot = D:\Workday_FailureScreenshot\Test_11NewRoleNewHire_Ireland_ 06102024 030649.png_x000D_ _x000D_ Main action error_x000D_ Code Number = New Hire 280_x000D_ Error Number = 9_x000D_ Error Message = Subscript out of range_x000D_ Error Source = Microsoft VBScript runtime error_x000D_ | R9: Field not found for Class = "PageHireProposeCompensationHire" at Function = "getBasePayRange"_x000D_ Code Number = New Hire 273_x000D_ Location of Failure screenshot = D:\Workday_FailureScreenshot\Test_12NewRoleNewHire_Ireland_ 06102024 031821.png_x000D_ _x000D_ Main action error_x000D_ Code Number = New Hire 280_x000D_ Error Number = 9_x000D_ Error Message = Subscript out of range_x000D_ Error Source = Microsoft VBScript runtime error_x000D_ | S9: Field not found for Class = "PageHireProposeCompensationHire" at Function = "getBasePayRange"_x000D_ Code Number = New Hire 273_x000D_ Location of Failure screenshot = D:\Workday_FailureScreenshot\Test_13_NewHire_Ireland_ 06102024 032802.png_x000D_ _x000D_ Main action error_x000D_ Code Number = New Hire 280_x000D_ Error Number = 9_x000D_ Error Message = Subscript out of range_x000D_ Error Source = Microsoft VBScript runtime error_x000D_ | T9: Field not found for Class = "PageHireProposeCompensationHire" at Function = "getBasePayRange"_x000D_ Code Number = New Hire 273_x000D_ Location of Failure screenshot = D:\Workday_FailureScreenshot\Test_14_NewHire_Ireland_ 06102024 033740.png_x000D_ _x000D_ Main action error_x000D_ Code Number = New Hire 280_x000D_ Error Number = 9_x000D_ Error Message = Subscript out of range_x000D_ Error Source = Microsoft VBScript runtime error_x000D_ | U9: Field not found for Class = "PageHireProposeCompensationHire" at Function = "getBasePayRange"_x000D_ Code Number = New Hire 273_x000D_ Location of Failure screenshot = D:\Workday_FailureScreenshot\Test_15_NewHire_Ireland_ 06102024 034720.png_x000D_ _x000D_ Main action error_x000D_ Code Number = New Hire 280_x000D_ Error Number = 9_x000D_ Error Message = Subscript out of range_x000D_ Error Source = Microsoft VBScript runtime error_x000D_
C10: Defect Description | D10: DefectDescription | E10: DefectDescription2 | F10: After error investigation by the automation team, the defect description will be completed here
C11: Automation Comments | D11: AutomationComments | E11: AutomationComments2 | F11: Automation team free text field
C12: QA Comments | D12: QAComments | E12: QAComments2 | F12: QA team free text field
A14: Screen | B14: Subscreen | C14: Field | D14: Automation Ref | E14: Lookups Ref | F14: Notes | G14: Test_1 | H14: Test_2 | I14: Test_3 | J14: Test_4 | K14: Test_5 | L14: Test_6 | M14: Test_7 | N14: Test_8 | O14: Test_9 | P14: Test_10 | Q14: Test_11 | R14: Test_12 | S14: Test_13 | T14: Test_14 | U14: Test_15
A15: Login | B15: N/A | C15: Username | D15: =SUBSTITUTE(A15," ","") & "_" & SUBSTITUTE(IF(B15="N/A","",B15& "_")," ","") & SUBSTITUTE(SUBSTITUTE(C15," ",""),"/","") -> Login_Username | E15: =D15&2 -> Login_Username2 | F15: QA user login | G15: 90002195 | H15: 90002195 | I15: 90002195 | J15: 90002195 | K15: 90002195 | L15: 90002195 | M15: 90002195 | N15: 90002195 | O15: 90002195 | P15: 90002195 | Q15: 90002195 | R15: 90002195 | S15: 90002195 | T15: 90002195 | U15: 90002195
A16: Login | B16: N/A | C16: Password | D16: =SUBSTITUTE(A16," ","") & "_" & SUBSTITUTE(IF(B16="N/A","",B16& "_")," ","") & SUBSTITUTE(SUBSTITUTE(C16," ",""),"/","") -> Login_Password | E16: =D16&2 -> Login_Password2 | F16: QA user password | G16: 66eb0ddfe1833a6c0473b8ea80d04ab9d9cf77994b86082d9ff6f77f | H16: 66eb0ddfe1833a6c0473b8ea80d04ab9d9cf77994b86082d9ff6f77f | I16: 66eb0ddfe1833a6c0473b8ea80d04ab9d9cf77994b86082d9ff6f77f | J16: 66eb0ddfe1833a6c0473b8ea80d04ab9d9cf77994b86082d9ff6f77f | K16: 66eb0ddfe1833a6c0473b8ea80d04ab9d9cf77994b86082d9ff6f77f | L16: 66eb0ddfe1833a6c0473b8ea80d04ab9d9cf77994b86082d9ff6f77f | M16: 66eb0ddfe1833a6c0473b8ea80d04ab9d9cf77994b86082d9ff6f77f | N16: 66eb0ddfe1833a6c0473b8ea80d04ab9d9cf77994b86082d9ff6f77f | O16: 66eb0ddfe1833a6c0473b8ea80d04ab9d9cf77994b86082d9ff6f77f | P16: 66eb0ddfe1833a6c0473b8ea80d04ab9d9cf77994b86082d9ff6f77f | Q16: 66eb0ddfe1833a6c0473b8ea80d04ab9d9cf77994b86082d9ff6f77f | R16: 66eb0ddfe1833a6c0473b8ea80d04ab9d9cf77994b86082d9ff6f77f | S16: 66eb0ddfe1833a6c0473b8ea80d04ab9d9cf77994b86082d9ff6f77f | T16: 66eb0ddfe1833a6c0473b8ea80d04ab9d9cf77994b86082d9ff6f77f | U16: 66eb0ddfe1833a6c0473b8ea80d04ab9d9cf77994b86082d9ff6f77f | V16: 66eb0ddfe1833a6c0473b8ea80d04ab9d9cf77994b86082d9ff6f77f
A17: Supervisory Organisation | B17: N/A | C17: Supervisory Organisation | D17: =SUBSTITUTE(A17," ","") & "_" & SUBSTITUTE(IF(B17="N/A","",B17& "_")," ","") & SUBSTITUTE(SUBSTITUTE(C17," ",""),"/","") -> SupervisoryOrganisation_SupervisoryOrganisation | E17: =D17&2 -> SupervisoryOrganisation_SupervisoryOrganisation2 | G17: 001 Recruitment (Zatuw Pupopo (221849)) | H17: 001 Store Management (Mygij Zabuza (100446)) | I17: 001 Store Management (Mygij Zabuza (100446)) | J17: 001 Store Management (Mygij Zabuza (100446)) | K17: 001 Store Management (Mygij Zabuza (100446)) | L17: 001 Store Management (Mygij Zabuza (100446)) | M17: 001 Store Management (Mygij Zabuza (100446)) | N17: 001 Recruitment (Zatuw Pupopo (221849)) | O17: 001 Store Management (Mygij Zabuza (100446)) | P17: 001 Recruitment (Zatuw Pupopo (221849)) | Q17: 001 Store Management (Mygij Zabuza (100446)) | R17: 001 Store Management (Mygij Zabuza (100446)) | S17: 001 Recruitment (Zatuw Pupopo (221849)) | T17: 001 Recruitment (Zatuw Pupopo (221849)) | U17: 001 Recruitment (Zatuw Pupopo (221849))
A18: Legal Name Information | B18: N/A | C18: Country | D18: =SUBSTITUTE(A18," ","") & "_" & SUBSTITUTE(IF(B18="N/A","",B18& "_")," ","") & SUBSTITUTE(SUBSTITUTE(C18," ",""),"/","") -> LegalNameInformation_Country | E18: =D18&2 -> LegalNameInformation_Country2 | F18: Test country to be placed here | G18: Ireland | H18: Ireland | I18: Ireland | J18: Ireland | K18: Ireland | L18: Ireland | M18: Ireland | N18: Ireland | O18: Ireland | P18: Ireland | Q18: Ireland | R18: Ireland | S18: Ireland | T18: Ireland | U18: Ireland
A19: Legal Name Information | B19: N/A | C19: Prefix | D19: =SUBSTITUTE(A19," ","") & "_" & SUBSTITUTE(IF(B19="N/A","",B19& "_")," ","") & SUBSTITUTE(SUBSTITUTE(C19," ",""),"/","") -> LegalNameInformation_Prefix | E19: =D19&2 -> LegalNameInformation_Prefix2 | G19: Mr | H19: Ms | I19: Mr | J19: Ms | K19: Mr | L19: Ms | M19: Mr | N19: Ms | O19: Mr | P19: Ms | Q19: Mr | R19: Ms | S19: Mr | T19: Ms | U19: Mr
A20: Legal Name Information | B20: N/A | C20: Given Name | D20: =SUBSTITUTE(A20," ","") & "_" & SUBSTITUTE(IF(B20="N/A","",B20& "_")," ","") & SUBSTITUTE(SUBSTITUTE(C20," ",""),"/","") -> LegalNameInformation_GivenName | E20: =D20&2 -> LegalNameInformation_GivenName2 | F20: Automation will throw error if not unique | G20: IrelandOne | H20: IrelandTwo | I20: IrelandThree | J20: IrelandFour | K20: IrelandFive | L20: IrelandSix | M20: IrelandSeven | N20: IrelandEight | O20: IrelandNine | P20: IrelandTen | Q20: IrelandEleven | R20: IrelandTwelve | S20: IrelandThirteen | T20: IrelandFourteen | U20: IrelandFifteen
A21: Legal Name Information | B21: N/A | C21: Family Name | D21: =SUBSTITUTE(A21," ","") & "_" & SUBSTITUTE(IF(B21="N/A","",B21& "_")," ","") & SUBSTITUTE(SUBSTITUTE(C21," ",""),"/","") -> LegalNameInformation_FamilyName | E21: =D21&2 -> LegalNameInformation_FamilyName2 | F21: Automation will throw error if not unique | G21: GlobelRegFourOCT | H21: GlobelRegFourOCT | I21: GlobelRegFourOCT | J21: GlobelRegFourOCT | K21: GlobelRegFourOCT | L21: GlobelRegFourOCT | M21: GlobelRegFourOCT | N21: GlobelRegFourOCT | O21: GlobelRegFourOCT | P21: GlobelRegFourOCT | Q21: GlobelRegFourOCT | R21: GlobelRegFourOCT | S21: GlobelRegFourOCT | T21: GlobelRegFourOCT | U21: GlobelRegFourOCT
A22: Contact Information | B22: Phone | C22: Phone Number | D22: =SUBSTITUTE(A22," ","") & "_" & SUBSTITUTE(IF(B22="N/A","",B22& "_")," ","") & SUBSTITUTE(SUBSTITUTE(C22," ",""),"/","") -> ContactInformation_Phone_PhoneNumber | E22: =D22&2 -> ContactInformation_Phone_PhoneNumber2 | G22: 861240232 | H22: 861240232 | I22: 861240232 | J22: 861240232 | K22: 861240232 | L22: 861240232 | M22: 861240232 | N22: 861240232 | O22: 861240232 | P22: 861240232 | Q22: 861240232 | R22: 861240232 | S22: 861240232 | T22: 861240232 | U22: 861240232
A23: Contact Information | B23: Phone | C23: Phone Device | D23: =SUBSTITUTE(A23," ","") & "_" & SUBSTITUTE(IF(B23="N/A","",B23& "_")," ","") & SUBSTITUTE(SUBSTITUTE(C23," ",""),"/","") -> ContactInformation_Phone_PhoneDevice | E23: =D23&2 -> ContactInformation_Phone_PhoneDevice2 | G23: Landline | H23: Landline | I23: Landline | J23: Landline | K23: Landline | L23: Landline | M23: Landline | N23: Landline | O23: Landline | P23: Landline | Q23: Landline | R23: Landline | S23: Landline | T23: Landline | U23: Landline
A24: Contact Information | B24: Phone | C24: Type | D24: =SUBSTITUTE(A24," ","") & "_" & SUBSTITUTE(IF(B24="N/A","",B24& "_")," ","") & SUBSTITUTE(SUBSTITUTE(C24," ",""),"/","") -> ContactInformation_Phone_Type | E24: =D24&2 -> ContactInformation_Phone_Type2 | G24: Home | H24: Home | I24: Home | J24: Home | K24: Home | L24: Home | M24: Home | N24: Home | O24: Home | P24: Home | Q24: Home | R24: Home | S24: Home | T24: Home | U24: Home
A25: Contact Information | B25: Address | C25: Effective Date | D25: =SUBSTITUTE(A25," ","") & "_" & SUBSTITUTE(IF(B25="N/A","",B25& "_")," ","") & SUBSTITUTE(SUBSTITUTE(C25," ",""),"/","") -> ContactInformation_Address_EffectiveDate | E25: =D25&2 -> ContactInformation_Address_EffectiveDate2 | G25: =TODAY()-31 -> 45724 | H25: =TODAY()-31 -> 45724 | I25: =TODAY()-31 -> 45724 | J25: =TODAY()-31 -> 45724 | K25: =TODAY()-31 -> 45724 | L25: =TODAY()-31 -> 45724 | M25: =TODAY()-31 -> 45724 | N25: =TODAY()-31 -> 45724 | ... U25: =TODAY()-31 -> 45724
A26: Contact Information | B26: Address | C26: Country | D26: =SUBSTITUTE(A26," ","") & "_" & SUBSTITUTE(IF(B26="N/A","",B26& "_")," ","") & SUBSTITUTE(SUBSTITUTE(C26," ",""),"/","") -> ContactInformation_Address_Country | E26: =D26&2 -> ContactInformation_Address_Country2 | G26: Ireland | H26: Ireland | I26: Ireland | J26: Ireland | K26: Ireland | L26: Ireland | M26: Ireland | N26: Ireland | O26: Ireland | P26: Ireland | Q26: Ireland | R26: Ireland | S26: Ireland | T26: Ireland | U26: Ireland
A27: Contact Information | B27: Address | C27: County | D27: =SUBSTITUTE(A27," ","") & "_" & SUBSTITUTE(IF(B27="N/A","",B27& "_")," ","") & SUBSTITUTE(SUBSTITUTE(C27," ",""),"/","") -> ContactInformation_Address_County | E27: =D27&2 -> ContactInformation_Address_County2 | G27: Dublin | H27: Dublin | I27: Dublin | J27: Dublin | K27: Dublin | L27: Dublin | M27: Dublin | N27: Dublin | O27: Dublin | P27: Dublin | Q27: Dublin | R27: Dublin | S27: Dublin | T27: Dublin | U27: Dublin
A28: Contact Information | B28: Address | C28: AdressLine1 | D28: =SUBSTITUTE(A28," ","") & "_" & SUBSTITUTE(IF(B28="N/A","",B28& "_")," ","") & SUBSTITUTE(SUBSTITUTE(C28," ",""),"/","") -> ContactInformation_Address_AdressLine1 | E28: =D28&2 -> ContactInformation_Address_AdressLine12 | G28: Automation Street Name | H28: Automation Street Name | I28: Automation Street Name | J28: Automation Street Name | K28: Automation Street Name | L28: Automation Street Name | M28: Automation Street Name | N28: Automation Street Name | O28: Automation Street Name | P28: Automation Street Name | Q28: Automation Street Name | R28: Automation Street Name | S28: Automation Street Name | T28: Automation Street Name | U28: Automation Street Name
A29: Contact Information | B29: Address | C29: AdressLine2 | D29: =SUBSTITUTE(A29," ","") & "_" & SUBSTITUTE(IF(B29="N/A","",B29& "_")," ","") & SUBSTITUTE(SUBSTITUTE(C29," ",""),"/","") -> ContactInformation_Address_AdressLine2 | E29: =D29&2 -> ContactInformation_Address_AdressLine22 | G29: 38 | H29: 38 | I29: 38 | J29: 38 | K29: 38 | L29: 38 | M29: 38 | N29: 38 | O29: 38 | P29: 38 | Q29: 38 | R29: 38 | S29: 38 | T29: 38 | U29: 38
A30: Contact Information | B30: Address | C30: AdressLine3 | D30: =SUBSTITUTE(A30," ","") & "_" & SUBSTITUTE(IF(B30="N/A","",B30& "_")," ","") & SUBSTITUTE(SUBSTITUTE(C30," ",""),"/","") -> ContactInformation_Address_AdressLine3 | E30: =D30&2 -> ContactInformation_Address_AdressLine32 | G30: Dublin | H30: Dublin | I30: Dublin | J30: Dublin | K30: Dublin | L30: Dublin | M30: Dublin | N30: Dublin | O30: Dublin | P30: Dublin | Q30: Dublin | R30: Dublin | S30: Dublin | T30: Dublin | U30: Dublin
A31: Contact Information | B31: Address | C31: Postal Code | D31: =SUBSTITUTE(A31," ","") & "_" & SUBSTITUTE(IF(B31="N/A","",B31& "_")," ","") & SUBSTITUTE(SUBSTITUTE(C31," ",""),"/","") -> ContactInformation_Address_PostalCode | E31: =D31&2 -> ContactInformation_Address_PostalCode2 | G31: D94HG49 | H31: D94HG49 | I31: D94HG49 | J31: D94HG49 | K31: D94HG49 | L31: D94HG49 | M31: D94HG49 | N31: D94HG49 | O31: D94HG49 | P31: D94HG49 | Q31: D94HG49 | R31: D94HG49 | S31: D94HG49 | T31: D94HG49 | U31: D94HG49
A32: Contact Information | B32: Address | C32: City | D32: =SUBSTITUTE(A32," ","") & "_" & SUBSTITUTE(IF(B32="N/A","",B32& "_")," ","") & SUBSTITUTE(SUBSTITUTE(C32," ",""),"/","") -> ContactInformation_Address_City | E32: =D32&2 -> ContactInformation_Address_City2 | G32: Dublin | H32: Dublin | I32: Dublin | J32: Dublin | K32: Dublin | L32: Dublin | M32: Dublin | N32: Dublin | O32: Dublin | P32: Dublin | Q32: Dublin | R32: Dublin | S32: Dublin | T32: Dublin | U32: Dublin
A33: Contact Information | B33: Address | C33: Type | D33: =SUBSTITUTE(A33," ","") & "_" & SUBSTITUTE(IF(B33="N/A","",B33& "_")," ","") & SUBSTITUTE(SUBSTITUTE(C33," ",""),"/","") -> ContactInformation_Address_Type | E33: =D33&2 -> ContactInformation_Address_Type2 | G33: Home | H33: Home | I33: Home | J33: Home | K33: Home | L33: Home | M33: Home | N33: Home | O33: Home | P33: Home | Q33: Home | R33: Home | S33: Home | T33: Home | U33: Home
A34: Contact Information | B34: Address | C34: Use For | D34: =SUBSTITUTE(A34," ","") & "_" & SUBSTITUTE(IF(B34="N/A","",B34& "_")," ","") & SUBSTITUTE(SUBSTITUTE(C34," ",""),"/","") -> ContactInformation_Address_UseFor | E34: =D34&2 -> ContactInformation_Address_UseFor2 | F34: "Permanent" or "Temporary" | G34: Street Address | H34: Street Address | I34: Street Address | J34: Street Address | K34: Street Address | L34: Street Address | M34: Street Address | N34: Street Address | O34: Street Address | P34: Street Address | Q34: Street Address | R34: Street Address | S34: Street Address | T34: Street Address | U34: Street Address
A35: Contact Information | B35: Email | C35: Email Address | D35: =SUBSTITUTE(A35," ","") & "_" & SUBSTITUTE(IF(B35="N/A","",B35& "_")," ","") & SUBSTITUTE(SUBSTITUTE(C35," ",""),"/","") -> ContactInformation_Email_EmailAddress | E35: =D35&2 -> ContactInformation_Email_EmailAddress2 | G35: automation@qe.com | H35: automation@qe.com | I35: automation@qe.com | J35: automation@qe.com | K35: automation@qe.com | L35: automation@qe.com | M35: automation@qe.com | N35: automation@qe.com | O35: automation@qe.com | P35: automation@qe.com | Q35: automation@qe.com | R35: automation@qe.com | S35: automation@qe.com | T35: automation@qe.com | U35: automation@qe.com
A36: Contact Information | B36: Email | C36: Type | D36: =SUBSTITUTE(A36," ","") & "_" & SUBSTITUTE(IF(B36="N/A","",B36& "_")," ","") & SUBSTITUTE(SUBSTITUTE(C36," ",""),"/","") -> ContactInformation_Email_Type | E36: =D36&2 -> ContactInformation_Email_Type2 | G36: Home | H36: Home | I36: Home | J36: Home | K36: Home | L36: Home | M36: Home | N36: Home | O36: Home | P36: Home | Q36: Home | R36: Home | S36: Home | T36: Home | U36: Home
A37: Job Details | B37: N/A | C37: Hire Date | D37: =SUBSTITUTE(A37," ","") & "_" & SUBSTITUTE(IF(B37="N/A","",B37& "_")," ","") & SUBSTITUTE(SUBSTITUTE(C37," ",""),"/","") -> JobDetails_HireDate | E37: =D37&2 -> JobDetails_HireDate2 | G37: =G25 -> 45724 | H37: =H25 -> 45724 | I37: =I25 -> 45724 | J37: =J25 -> 45724 | K37: =K25 -> 45724 | L37: =L25 -> 45724 | M37: =M25 -> 45724 | N37: =N25 -> 45724 | ... U37: =U25 -> 45724
A38: ManageProbationPeriod | B38: N/A | C38: ProbationEndDate | D38: =SUBSTITUTE(A38," ","") & "_" & SUBSTITUTE(IF(B38="N/A","",B38& "_")," ","") & SUBSTITUTE(SUBSTITUTE(C38," ",""),"/","") -> ManageProbationPeriod_ProbationEndDate | E38: =D38&2 -> ManageProbationPeriod_ProbationEndDate2 | G38: =G37+90 -> 45814 | H38: =H37+90 -> 45814 | I38: =I37+90 -> 45814 | J38: =J37+90 -> 45814 | K38: =K37+90 -> 45814 | L38: =L37+90 -> 45814 | M38: =M37+90 -> 45814 | N38: =N37+90 -> 45814 | ... U38: =U37+90 -> 45814
A39: Job Details | B39: N/A | C39: Reason | D39: =SUBSTITUTE(A39," ","") & "_" & SUBSTITUTE(IF(B39="N/A","",B39& "_")," ","") & SUBSTITUTE(SUBSTITUTE(C39," ",""),"/","") -> JobDetails_Reason | E39: =D39&2 -> JobDetails_Reason2 | G39: New Hire | H39: New Hire | I39: New Hire | J39: New Hire | K39: New Hire | L39: New Hire | M39: New Hire | N39: New Hire | O39: New Hire | P39: New Hire | Q39: New Hire | R39: New Hire | S39: New Hire | T39: New Hire | U39: New Hire
A40: Job Details | B40: N/A | C40: Position | D40: =SUBSTITUTE(A40," ","") & "_" & SUBSTITUTE(IF(B40="N/A","",B40& "_")," ","") & SUBSTITUTE(SUBSTITUTE(C40," ",""),"/","") -> JobDetails_Position | E40: =D40&2 -> JobDetails_Position2 | F40: If Process is set to "New Role and New Hire" (Row 2) this position name will be ignored and replaced with the newly created name. | G40: No | H40: Auto 06102024 012454 | I40: Auto 01102024 025359 | J40: Auto 06102024 013855 | K40: Auto 06102024 015033 | L40: Auto 06102024 020218 | M40: Auto 06102024 021353 | N40: No | O40: Auto 06102024 023507 | P40: No | Q40: Auto 06102024 025627 | R40: Auto 06102024 030803 | S40: No | T40: No | U40: No
A41: Job Details | B41: N/A | C41: Employee Type | D41: =SUBSTITUTE(A41," ","") & "_" & SUBSTITUTE(IF(B41="N/A","",B41& "_")," ","") & SUBSTITUTE(SUBSTITUTE(C41," ",""),"/","") -> JobDetails_EmployeeType | E41: =D41&2 -> JobDetails_EmployeeType2 | F41: If Fixed Term ensure contract end date below is populated and not N/A | G41: Permanent | H41: Fixed Term | I41: Permanent | J41: Fixed Term | K41: Permanent | L41: Temporary | M41: Permanent | N41: Fixed Term | O41: Permanent | P41: Fixed Term | Q41: Permanent | R41: Fixed Term | S41: Permanent | T41: Fixed Term | U41: Temporary
A42: Job Details | B42: N/A | C42: Job Profile | D42: =SUBSTITUTE(A42," ","") & "_" & SUBSTITUTE(IF(B42="N/A","",B42& "_")," ","") & SUBSTITUTE(SUBSTITUTE(C42," ",""),"/","") -> JobDetails_JobProfile | E42: =D42&2 -> JobDetails_JobProfile2 | G42: Retail Assistant | H42: Store Manager | I42: Department Manager | J42: Weekend Manager | K42: Team Manager - Retail | L42: Assistant Manager | M42: P&C Manager Stores | N42: Store Person | O42: Trainee Manager | P42: Retail Assistant | Q42: Store Manager | R42: Department Manager | S42: Retail Assistant | T42: Store Person | U42: Supervisor
A43: Job Details | B43: N/A | C43: Time Type | D43: =SUBSTITUTE(A43," ","") & "_" & SUBSTITUTE(IF(B43="N/A","",B43& "_")," ","") & SUBSTITUTE(SUBSTITUTE(C43," ",""),"/","") -> JobDetails_TimeType | E43: =D43&2 -> JobDetails_TimeType2 | G43: Full time | H43: Full time | I43: Full time | J43: Part time | K43: Full time | L43: Full time | M43: Full time | N43: Part time | O43: Part time | P43: Part time | Q43: Part time | R43: Part time | S43: Part time | T43: Part time | U43: Part time
A44: Job Details | B44: N/A | C44: Location | D44: =SUBSTITUTE(A44," ","") & "_" & SUBSTITUTE(IF(B44="N/A","",B44& "_")," ","") & SUBSTITUTE(SUBSTITUTE(C44," ",""),"/","") -> JobDetails_Location | E44: =D44&2 -> JobDetails_Location2 | G44: 001 | H44: 001 | I44: 001 | J44: 001 | K44: 001 | L44: 001 | M44: 001 | N44: 001 | O44: 001 | P44: 001 | Q44: 001 | R44: 001 | S44: 001 | T44: 001 | U44: 001
A45: Job Details | B45: N/A | C45: Pay Rate Type | D45: =SUBSTITUTE(A45," ","") & "_" & SUBSTITUTE(IF(B45="N/A","",B45& "_")," ","") & SUBSTITUTE(SUBSTITUTE(C45," ",""),"/","") -> JobDetails_PayRateType | E45: =D45&2 -> JobDetails_PayRateType2 | G45: Hourly | H45: Salary | I45: Salary | J45: Salary | K45: Salary | L45: Salary | M45: Salary | N45: Hourly | O45: Salary | P45: Hourly | Q45: Salary | R45: Salary | S45: Hourly | T45: Hourly | U45: Hourly
A46: Job Details | B46: Additional Information | C46: Scheduled Weekly Hours | D46: =SUBSTITUTE(A46," ","") & "_" & SUBSTITUTE(IF(B46="N/A","",B46& "_")," ","") & SUBSTITUTE(SUBSTITUTE(C46," ",""),"/","") -> JobDetails_AdditionalInformation_ScheduledWeeklyHours | E46: =D46&2 -> JobDetails_AdditionalInformation_ScheduledWeeklyHours2 | G46: 37.5 | H46: 40 | I46: 40 | J46: 25 | K46: 40 | L46: 40 | M46: 40 | N46: 20 | O46: 21 | P46: 11.5 | Q46: 25 | R46: 21 | S46: 15 | T46: 11.5 | U46: 21
A47: Job Details | B47: Additional Information | C47: Additional Job Classifications | D47: =SUBSTITUTE(A47," ","") & "_" & SUBSTITUTE(IF(B47="N/A","",B47& "_")," ","") & SUBSTITUTE(SUBSTITUTE(C47," ",""),"/","") -> JobDetails_AdditionalInformation_AdditionalJobClassifications | E47: =D47&2 -> JobDetails_AdditionalInformation_AdditionalJobClassifications2 | G47: 508 | H47: 508 | I47: 508 | J47: 508 | K47: 508 | L47: 508 | M47: 508 | N47: 508 | O47: 508 | P47: 508 | Q47: 508 | R47: 508 | S47: 508 | T47: 508 | U47: 508
A48: Job Details | B48: Additional Information | C48: Work Shift | D48: =SUBSTITUTE(A48," ","") & "_" & SUBSTITUTE(IF(B48="N/A","",B48& "_")," ","") & SUBSTITUTE(SUBSTITUTE(C48," ",""),"/","") -> JobDetails_AdditionalInformation_WorkShift | E48: =D48&2 -> JobDetails_AdditionalInformation_WorkShift2 | G48: Default Work Shift (Ireland) | H48: Default Work Shift (Ireland) | I48: Default Work Shift (Ireland) | J48: Default Work Shift (Ireland) | K48: Default Work Shift (Ireland) | L48: Default Work Shift (Ireland) | M48: Default Work Shift (Ireland) | N48: Default Work Shift (Ireland) | O48: Default Work Shift (Ireland) | P48: Default Work Shift (Ireland) | Q48: Default Work Shift (Ireland) | R48: Default Work Shift (Ireland) | S48: Default Work Shift (Ireland) | T48: Default Work Shift (Ireland) | U48: Default Work Shift (Ireland)
A49: Job Details | B49: Additional Information | C49: End Employment Date | D49: =SUBSTITUTE(A49," ","") & "_" & SUBSTITUTE(IF(B49="N/A","",B49& "_")," ","") & SUBSTITUTE(SUBSTITUTE(C49," ",""),"/","") -> JobDetails_AdditionalInformation_EndEmploymentDate | E49: =D49&2 -> JobDetails_AdditionalInformation_EndEmploymentDate2 | F49: Set to N/A when field not present otherwise automation will throw error | G49: N/A | H49: =H37+365 -> 46089 | I49: N/A | J49: =J37+365 -> 46089 | K49: N/A | L49: N/A | M49: N/A | N49: =N37+365 -> 46089 | O49: N/A | P49: =P37+365 -> 46089 | Q49: N/A | R49: =R37+365 -> 46089 | S49: N/A | T49: =T37+365 -> 46089 | U49: N/A
A50: Job Details | B50: Additional Information | C50: Comments | D50: =SUBSTITUTE(A50," ","") & "_" & SUBSTITUTE(IF(B50="N/A","",B50& "_")," ","") & SUBSTITUTE(SUBSTITUTE(C50," ",""),"/","") -> JobDetails_AdditionalInformation_Comments | E50: =D50&2 -> JobDetails_AdditionalInformation_Comments2 | G50: Automation Comments here…. | H50: Automation Comments here…. | I50: Automation Comments here…. | J50: Automation Comments here…. | K50: Automation Comments here…. | L50: Automation Comments here…. | M50: Automation Comments here…. | N50: Automation Comments here…. | O50: Automation Comments here…. | P50: Automation Comments here…. | Q50: Automation Comments here…. | R50: Automation Comments here…. | S50: Automation Comments here…. | T50: Automation Comments here…. | U50: Automation Comments here….
A51: Change Organization Assignments | B51: N/A | C51: Cost Center | D51: =SUBSTITUTE(A51," ","") & "_" & SUBSTITUTE(IF(B51="N/A","",B51& "_")," ","") & SUBSTITUTE(SUBSTITUTE(C51," ",""),"/","") -> ChangeOrganizationAssignments_CostCenter | E51: =D51&2 -> ChangeOrganizationAssignments_CostCenter2 | G51: 94 Retail Operative | H51: 92 Retail Management | I51: 92 Retail Management | J51: 92 Retail Management | K51: 92 Retail Management | L51: 92 Retail Management | M51: 92 Retail Management | N51: 94 Retail Operative | O51: 92 Retail Management | P51: 94 Retail Operative | Q51: 92 Retail Management | R51: 92 Retail Management | S51: 94 Retail Operative | T51: 94 Retail Operative | U51: 94 Retail Operative
A52: Change Organization Assignments | B52: N/A | C52: Department Section | D52: =SUBSTITUTE(A52," ","") & "_" & SUBSTITUTE(IF(B52="N/A","",B52& "_")," ","") & SUBSTITUTE(SUBSTITUTE(C52," ",""),"/","") -> ChangeOrganizationAssignments_DepartmentSection | E52: =D52&2 -> ChangeOrganizationAssignments_DepartmentSection2 | G52: 01 Accessories | H52: 251 | I52: 251 | J52: 252 Weekend Management | K52: 251 | L52: 251 | M52: 251 | N52: 01 Accessories | O52: 251 | P52: 23 Health & Beauty | Q52: 251 | R52: 251 | S52: 06 Menswear | T52: 255 Stockroom | U52: 253 Supervisors
A53: Change My Government IDs | B53: National IDs | C53: Country1 | D53: =SUBSTITUTE(A53," ","") & "_" & SUBSTITUTE(IF(B53="N/A","",B53& "_")," ","") & SUBSTITUTE(SUBSTITUTE(C53," ",""),"/","") -> ChangeMyGovernmentIDs_NationalIDs_Country1 | E53: =D53&2 -> ChangeMyGovernmentIDs_NationalIDs_Country12 | G53: Ireland | H53: Ireland | I53: Ireland | J53: Ireland | K53: Ireland | L53: Ireland | M53: Ireland | N53: Ireland | O53: Ireland | P53: Ireland | Q53: Ireland | R53: Ireland | S53: Ireland | T53: Ireland | U53: Ireland
A54: Propose Compensation Hire | B54: N/A | C54: Grade Profile | D54: =SUBSTITUTE(A54," ","") & "_" & SUBSTITUTE(IF(B54="N/A","",B54& "_")," ","") & SUBSTITUTE(SUBSTITUTE(C54," ",""),"/","") -> ProposeCompensationHire_GradeProfile | E54: =D54&2 -> ProposeCompensationHire_GradeProfile2 | G54: N/A | H54: N/A | I54: N/A | J54: ROI Weekend Manager (Year 1) | K54: ROI Team Manager - Retail (Probationary) | L54: N/A | M54: N/A | N54: N/A | O54: ROI Trainee Manager (Probationary) | P54: N/A | Q54: N/A | R54: N/A | S54: N/A | T54: N/A | U54: N/A
A55: Propose Compensation Hire | B55: N/A | C55: Step | D55: =SUBSTITUTE(A55," ","") & "_" & SUBSTITUTE(IF(B55="N/A","",B55& "_")," ","") & SUBSTITUTE(SUBSTITUTE(C55," ",""),"/","") -> ProposeCompensationHire_Step | E55: =D55&2 -> ProposeCompensationHire_Step2 | G55: N/A | H55: N/A | I55: N/A | J55: N/A | K55: Initial Step- ROI TM-Prob | L55: N/A | M55: N/A | N55: N/A | O55: N/A | P55: N/A | Q55: N/A | R55: N/A | S55: N/A | T55: N/A | U55: N/A
A56: Change My Government IDs | B56: National IDs | C56: National ID Type1 | D56: =SUBSTITUTE(A56," ","") & "_" & SUBSTITUTE(IF(B56="N/A","",B56& "_")," ","") & SUBSTITUTE(SUBSTITUTE(C56," ",""),"/","") -> ChangeMyGovernmentIDs_NationalIDs_NationalIDType1 | E56: =D56&2 -> ChangeMyGovernmentIDs_NationalIDs_NationalIDType12 | G56: Personal Public Service Number | H56: Personal Public Service Number (PPS no) | I56: Personal Public Service Number (PPS no) | J56: Personal Public Service Number (PPS no) | K56: Personal Public Service Number (PPS no) | L56: Personal Public Service Number (PPS no) | M56: Personal Public Service Number (PPS no) | N56: Personal Public Service Number (PPS no) | O56: Personal Public Service Number (PPS no) | P56: Personal Public Service Number (PPS no) | Q56: Personal Public Service Number (PPS no) | R56: Personal Public Service Number (PPS no) | S56: Personal Public Service Number (PPS no) | T56: Personal Public Service Number (PPS no) | U56: Personal Public Service Number (PPS no)
A57: Change My Government IDs | B57: National IDs | C57: Add Edit ID1 | D57: =SUBSTITUTE(A57," ","") & "_" & SUBSTITUTE(IF(B57="N/A","",B57& "_")," ","") & SUBSTITUTE(SUBSTITUTE(C57," ",""),"/","") -> ChangeMyGovernmentIDs_NationalIDs_AddEditID1 | E57: =D57&2 -> ChangeMyGovernmentIDs_NationalIDs_AddEditID12 | F57: Automation will throw error if not unique | G57: 2576950JA | H57: 2576951JA | I57: 2576952JA | J57: 2576953JA | K57: 2576954JA | L57: 2576955JA | M57: 2576956JA | N57: 2576957JA | O57: 2576958JA | P57: 2576959JA | Q57: 2576960JA | R57: 2576961JA | S57: 2576962JA | T57: 2576963JA | U57: 2576964JA
A58: Change My Personal Information | B58: N/A | C58: Gender | D58: =SUBSTITUTE(A58," ","") & "_" & SUBSTITUTE(IF(B58="N/A","",B58& "_")," ","") & SUBSTITUTE(SUBSTITUTE(C58," ",""),"/","") -> ChangeMyPersonalInformation_Gender | E58: =D58&2 -> ChangeMyPersonalInformation_Gender2 | G58: Male | H58: Female | I58: Male | J58: Female | K58: Male | L58: Female | M58: Male | N58: Female | O58: Male | P58: Female | Q58: Male | R58: Female | S58: Male | T58: Female | U58: Male
A59: Change My Personal Information | B59: N/A | C59: Date Of Birth | D59: =SUBSTITUTE(A59," ","") & "_" & SUBSTITUTE(IF(B59="N/A","",B59& "_")," ","") & SUBSTITUTE(SUBSTITUTE(C59," ",""),"/","") -> ChangeMyPersonalInformation_DateOfBirth | E59: =D59&2 -> ChangeMyPersonalInformation_DateOfBirth2 | G59: 35591 | H59: 35591 | I59: 35591 | J59: 35591 | K59: 35591 | L59: 35591 | M59: 35591 | N59: 35591 | O59: 35591 | P59: 35591 | Q59: 35591 | R59: 35591 | S59: 35591 | T59: 35591 | U59: 35591
A60: Change My Personal Information | B60: N/A | C60: Country Of Birth | D60: =SUBSTITUTE(A60," ","") & "_" & SUBSTITUTE(IF(B60="N/A","",B60& "_")," ","") & SUBSTITUTE(SUBSTITUTE(C60," ",""),"/","") -> ChangeMyPersonalInformation_CountryOfBirth | E60: =D60&2 -> ChangeMyPersonalInformation_CountryOfBirth2 | G60: Ireland | H60: Irel | I60: Irel | J60: Irel | K60: Irel | L60: Ireland | M60: Ireland | N60: Ireland | O60: Ireland | P60: Ireland | Q60: Ireland | R60: Ireland | S60: Ireland | T60: Ireland | U60: Ireland
A61: Change My Personal Information | B61: N/A | C61: Region Of Birth | D61: =SUBSTITUTE(A61," ","") & "_" & SUBSTITUTE(IF(B61="N/A","",B61& "_")," ","") & SUBSTITUTE(SUBSTITUTE(C61," ",""),"/","") -> ChangeMyPersonalInformation_RegionOfBirth | E61: =D61&2 -> ChangeMyPersonalInformation_RegionOfBirth2 | G61: Dublin | H61: Dublin | I61: Dublin | J61: Dublin | K61: Dublin | L61: Dublin | M61: Dublin | N61: Dublin | O61: Dublin | P61: Dublin | Q61: Dublin | R61: Dublin | S61: Dublin | T61: Dublin | U61: Dublin
A62: Change My Personal Information | B62: N/A | C62: City Of Birth | D62: =SUBSTITUTE(A62," ","") & "_" & SUBSTITUTE(IF(B62="N/A","",B62& "_")," ","") & SUBSTITUTE(SUBSTITUTE(C62," ",""),"/","") -> ChangeMyPersonalInformation_CityOfBirth | E62: =D62&2 -> ChangeMyPersonalInformation_CityOfBirth2 | G62: Dublin | H62: Dublin | I62: Dublin | J62: Dublin | K62: Dublin | L62: Dublin | M62: Dublin | N62: Dublin | O62: Dublin | P62: Dublin | Q62: Dublin | R62: Dublin | S62: Dublin | T62: Dublin | U62: Dublin
A63: Change My Personal Information | B63: N/A | C63: Marital Status | D63: =SUBSTITUTE(A63," ","") & "_" & SUBSTITUTE(IF(B63="N/A","",B63& "_")," ","") & SUBSTITUTE(SUBSTITUTE(C63," ",""),"/","") -> ChangeMyPersonalInformation_MaritalStatus | E63: =D63&2 -> ChangeMyPersonalInformation_MaritalStatus2 | G63: Married | H63: Married | I63: Married | J63: Married | K63: Married | L63: Married | M63: Married | N63: Married | O63: Married | P63: Married | Q63: Married | R63: Married | S63: Married | T63: Married | U63: Married
A64: Change My Personal Information | B64: N/A | C64: Marital Status Date | D64: =SUBSTITUTE(A64," ","") & "_" & SUBSTITUTE(IF(B64="N/A","",B64& "_")," ","") & SUBSTITUTE(SUBSTITUTE(C64," ",""),"/","") -> ChangeMyPersonalInformation_MaritalStatusDate | E64: =D64&2 -> ChangeMyPersonalInformation_MaritalStatusDate2 | G64: 28/10/2021 | H64: 28/10/2021 | I64: 28/10/2021 | J64: 28/10/2021 | K64: 28/10/2021 | L64: 28/10/2021 | M64: 28/10/2021 | N64: 28/10/2021 | O64: 28/10/2021 | P64: 28/10/2021 | Q64: 28/10/2021 | R64: 28/10/2021 | S64: 28/10/2021 | T64: 28/10/2021 | U64: 28/10/2021
A65: Change My Personal Information | B65: N/A | C65: Race/Ethnicity | D65: =SUBSTITUTE(A65," ","") & "_" & SUBSTITUTE(IF(B65="N/A","",B65& "_")," ","") & SUBSTITUTE(SUBSTITUTE(C65," ",""),"/","") -> ChangeMyPersonalInformation_RaceEthnicity | E65: =D65&2 -> ChangeMyPersonalInformation_RaceEthnicity2 | G65: White - Irish (Ireland) | H65: White - Irish (Ireland) | I65: White - Irish (Ireland) | J65: White - Irish (Ireland) | K65: White - Irish (Ireland) | L65: White - Irish (Ireland) | M65: White - Irish (Ireland) | N65: White - Irish (Ireland) | O65: White - Irish (Ireland) | P65: White - Irish (Ireland) | Q65: White - Irish (Ireland) | R65: White - Irish (Ireland) | S65: White - Irish (Ireland) | T65: White - Irish (Ireland) | U65: White - Irish (Ireland)
A66: Change My Personal Information | B66: N/A | C66: Primary Nationality | D66: =SUBSTITUTE(A66," ","") & "_" & SUBSTITUTE(IF(B66="N/A","",B66& "_")," ","") & SUBSTITUTE(SUBSTITUTE(C66," ",""),"/","") -> ChangeMyPersonalInformation_PrimaryNationality | E66: =D66&2 -> ChangeMyPersonalInformation_PrimaryNationality2 | G66: Ireland | H66: Ireland | I66: Ireland | J66: Ireland | K66: Ireland | L66: Ireland | M66: Ireland | N66: Ireland | O66: Ireland | P66: Ireland | Q66: Ireland | R66: Ireland | S66: Ireland | T66: Ireland | U66: Ireland
A67: Propose Compensation Hire | B67: N/A | C67: Salary | D67: =SUBSTITUTE(A67," ","") & "_" & SUBSTITUTE(IF(B67="N/A","",B67& "_")," ","") & SUBSTITUTE(SUBSTITUTE(C67," ",""),"/","") -> ProposeCompensationHire_Salary | E67: =D67&2 -> ProposeCompensationHire_Salary2 | G67: Defaulted | H67: Defaulted | I67: Defaulted | J67: Defaulted | K67: Defaulted | L67: Defaulted | M67: Defaulted | N67: Defaulted | O67: Defaulted | P67: Defaulted | Q67: Defaulted | R67: Defaulted | S67: Defaulted | T67: Defaulted | U67: Defaulted
A68: Payment Election Option | B68: N/A | C68: Bank Name | D68: =SUBSTITUTE(A68," ","") & "_" & SUBSTITUTE(IF(B68="N/A","",B68& "_")," ","") & SUBSTITUTE(SUBSTITUTE(C68," ",""),"/","") -> PaymentElectionOption_BankName | E68: =D68&2 -> PaymentElectionOption_BankName2 | G68: AIB | H68: AIB | I68: AIB | J68: AIB | K68: AIB | L68: AIB | M68: AIB | N68: AIB | O68: AIB | P68: AIB | Q68: AIB | R68: AIB | S68: AIB | T68: AIB | U68: AIB
A69: Payment Election Option | B69: N/A | C69: Bank Identification Code | D69: =SUBSTITUTE(A69," ","") & "_" & SUBSTITUTE(IF(B69="N/A","",B69& "_")," ","") & SUBSTITUTE(SUBSTITUTE(C69," ",""),"/","") -> PaymentElectionOption_BankIdentificationCode | E69: =D69&2 -> PaymentElectionOption_BankIdentificationCode2 | G69: BOFIIE2D | H69: BOFIIE2D | I69: BOFIIE2D | J69: BOFIIE2D | K69: BOFIIE2D | L69: BOFIIE2D | M69: BOFIIE2D | N69: BOFIIE2D | O69: BOFIIE2D | P69: BOFIIE2D | Q69: BOFIIE2D | R69: BOFIIE2D | S69: BOFIIE2D | T69: BOFIIE2D | U69: BOFIIE2D
A70: Payment Election Option | B70: N/A | C70: IBAN | D70: =SUBSTITUTE(A70," ","") & "_" & SUBSTITUTE(IF(B70="N/A","",B70& "_")," ","") & SUBSTITUTE(SUBSTITUTE(C70," ",""),"/","") -> PaymentElectionOption_IBAN | E70: =D70&2 -> PaymentElectionOption_IBAN2 | G70: IE29AIBK93115212345678 | H70: IE29AIBK93115212345678 | I70: IE29AIBK93115212345678 | J70: IE29AIBK93115212345678 | K70: IE29AIBK93115212345678 | L70: IE29AIBK93115212345678 | M70: IE29AIBK93115212345678 | N70: IE29AIBK93115212345678 | O70: IE29AIBK93115212345678 | P70: IE29AIBK93115212345678 | Q70: IE29AIBK93115212345678 | R70: IE29AIBK93115212345678 | S70: IE29AIBK93115212345678 | T70: IE29AIBK93115212345678 | U70: IE29AIBK93115212345678
