Workbook
Name AddProbationPeriod_EndDate: Test_Data!$F$38
Name AddProbationPeriod_ProbationEndDate: Test_Data!#REF!
Name AddProbationPeriod_ProbationEndDate2: Automation_Lookups!$BB$2:$BB$4
Name AddProbationPeriod_StartDate: Test_Data!$F$37
Name AssignPayGroup_ProposedPayGroup: Test_Data!#REF!
Name AssignPayGroup_ProposedPayGroup: Automation_Lookups!$AH$2:$AH$20
Name AssignPayGroup_ProposedPayGroup2: Automation_Lookups!$AH$2
Name AssignPayGroup_ProposedPayGroupFinal: Test_Data!#REF!
Name Automation_Ref: Test_Data!#REF!
Name AutomationComments: Test_Data!$F$9
Name ChangeJob_AssignCollectiveAgreement_CollectiveAgreement: Test_Data!$F$42
Name ChangeJob_AssignCollectiveAgreement_Level: Test_Data!$F$44
Name ChangeJob_AssignCollectiveAgreement_ProfessionalCategory: Test_Data!$F$43
Name ChangeJob_Company_CostCentre: Test_Data!$F$35
Name ChangeJob_Company_Department: Test_Data!$F$36
Name ChangeJob_JobClassifications_AdditionalJobClassifications: Test_Data!$F$27
Name ChangeJob_JobClassifications_AssignmentType: Test_Data!$F$33
Name ChangeJob_JobClassifications_DefaultWeeklyHours: Test_Data!$F$31
Name ChangeJob_JobClassifications_EmployeeType: Test_Data!$F$28
Name ChangeJob_JobClassifications_EndEmploymentDate: Test_Data!$F$32
Name ChangeJob_JobClassifications_FirstDayofWork: Test_Data!$F$34
Name ChangeJob_JobClassifications_PayRateType: Test_Data!$F$30
Name ChangeJob_JobClassifications_TimeType: Test_Data!$F$29
Name ChangeJob_JobProfile_JobProfile: Test_Data!$F$22
Name ChangeJob_JobProfile_JobTitle: Test_Data!$F$23
Name ChangeJob_LocationDetails_Location: Test_Data!$F$24
Name ChangeJob_LocationDetails_ScheduledWeeklyHours: Test_Data!$F$25
Name ChangeJob_LocationDetails_WorkShift: Test_Data!$F$26
Name ChangeJob_LocationDetails_WorkShift2: Automation_Lookups!$I$2:$I$6
Name ChangeJob_Start_EffectiveDate: Test_Data!$F$16
Name ChangeJob_Start_NewLocation: Test_Data!$F$20
Name ChangeJob_Start_NewLocation2: Automation_Lookups!$G$2:$G$3
Name ChangeJob_Start_NewManager: Test_Data!$F$18
Name ChangeJob_Start_NewManager2: Automation_Lookups!$E$2:$E$3
Name ChangeJob_Start_NewTeam: Test_Data!$F$19
Name ChangeJob_Start_NewTeam2: Automation_Lookups!$F$2:$F$3
Name ChangeJob_Start_NextPayPeriod: Test_Data!$F$21
Name ChangeJob_Start_NextPayPeriod2: Automation_Lookups!$H$2:$H$3
Name ChangeJob_Start_NextPayPeriod22: Automation_Lookups!$I$2:$I$6
Name ChangeJob_Start_Reason: Test_Data!$F$17
Name ChangeJob_Start_Reason2: Automation_Lookups!$D$2:$D$3
Name ChangeMyEmergencyContacts_City: Test_Data!#REF!
Name ChangeMyEmergencyContacts_EmailAddress: Test_Data!#REF!
Name ChangeMyEmergencyContacts_FamilyName: Test_Data!#REF!
Name ChangeMyEmergencyContacts_GivenName: Test_Data!#REF!
Name ChangeMyEmergencyContacts_PhoneDevice: Test_Data!#REF!
Name ChangeMyEmergencyContacts_PhoneDevice2: Automation_Lookups!$AX$2:$AX$3
Name ChangeMyEmergencyContacts_PhoneNumber: Test_Data!#REF!
Name ChangeMyEmergencyContacts_PostalCode: Test_Data!#REF!
Name ChangeMyEmergencyContacts_Relationship: Test_Data!#REF!
Name ChangeMyEmergencyContacts_Relationship2: Automation_Lookups!$AW$2:$AW$5
Name ChangeMyEmergencyContacts_StreetName: Test_Data!#REF!
Name ChangeMyGovernmentIDs_NationalIDs_AddEditID: Test_Data!#REF!
Name ChangeMyGovernmentIDs_NationalIDs_AddEditID1: Test_Data!#REF!
Name ChangeMyGovernmentIDs_NationalIDs_AddEditID2: Test_Data!#REF!
Name ChangeMyGovernmentIDs_NationalIDs_Country1: Test_Data!#REF!
Name ChangeMyGovernmentIDs_NationalIDs_Country2: Test_Data!#REF!
Name ChangeMyGovernmentIDs_NationalIDs_NationalIDType1: Test_Data!#REF!
Name ChangeMyGovernmentIDs_NationalIDs_NationalIDType12: Automation_Lookups!$BH$2
Name ChangeMyGovernmentIDs_NationalIDs_NationalIDType2: Test_Data!#REF!

Sheet Information
A1: Version | F1: Info
A6: Version | B6: 0.3 | F6: Info
F7: Dates | G7: For Czech all dates to be entered in format of DD/MM/YYYY
A8: History | F8: Unhighlighted fields | G8: Only data in unhighlighted fields can be changed.
A9: Date | B9: Version | C9: Details | F9: Red highlighted fields | G9: Indicates fields where unique data is required otherwise automation will throw errors
A10: 44061 | B10: 0.3 | C10: Initial Release | F10: Grey highlighted fields | G10: Indicates fields that cannot be changed
F11: Last Run Status / Last Run Error Message | G11: When automation has run for a particular test, we need to check the status is set to Passed and no error messages are present for each test before the automation run for that particular test is considered valid

Sheet Test_Data
B1: Version_Number | D1: Test_ID | E1: =SUBSTITUTE(D1," ","") -> Test_ID | F1: =E1&2 -> Test_ID2 | G1: Notes | H1: Test_1 | I1: Test_2 | J1: Test_3 | K1: Test_4 | L1: Test_5 | M1: Test_6 | N1: Test_7 | O1: Test_8 | P1: Test_9 | Q1: Test_10 | R1: Test_11 | S1: Test_12 | T1: Test_13 | U1: Test_14 | V1: Test_15 | W1: Test_16 | X1: Test_17 | Y1: Test_18 | Z1: Test_19 | AA1: Test_20 | AB1: Test_21 | AC1: Test_22 | AD1: Test_23 | AE1: Test_24 | AF1: Test_25 | AG1: Test_26 | AH1: Test_27 | AI1: Test_28 | AJ1: Test_29 | AK1: Test_30 | AL1: Test_31 | AM1: Test_32 | AN1: Test_33 | AO1: Test_34 | AP1: Test_35 | AQ1: Test_36 | AR1: Test_37 | AS1: Test_38 | AT1: Test_39 | AU1: Test_40 | AV1: Test_41 | AW1: Test_42 | AX1: Test_43 | AY1: Test_44 | AZ1: Test_45 | BA1: Test_46 | BB1: Test_47 | BC1: Test_48 | BD1: Test_49 | BE1: Test_50 | BF1: Test_51 | BG1: Test_52 | BH1: Test_53 | BI1: Test_54 | BJ1: Test_55 | BK1: Test_56 | BL1: Test_57 | BM1: Test_58 | BN1: Test_59 | BO1: Test_60 | BP1: Test_61 | BQ1: Test_62 | BR1: Test_63 | BS1: Test_64 | BT1: Test_65 | BU1: Test_66 | BV1: Test_67 | BW1: Test_68 | BX1: Test_69 | BY1: Test_70 | BZ1: Test_71 | CA1: Test_72 | CB1: Test_73 | CC1: Test_74 | CD1: Test_75 | CE1: Test_76 | CF1: Test_77 | CG1: Test_78 | CH1: Test_79 | CI1: Test_80 | CJ1: Test_81 | CK1: Test_82 | CL1: Test_83 | CM1: Test_84 | CN1: Test_85 | CO1: Test_86 | CP1: Test_87 | CQ1: Test_88 | CR1: Test_89 | CS1: Test_90 | CT1: Test_91 | CU1: Test_92 | CV1: Test_93 | CW1: Test_94 | CX1: Test_95 | CY1: Test_96 | CZ1: Test_97 | DA1: Test_98 | DB1: Test_99
B2: =Information!B6 -> 0.3 | D2: Reporting_ID | H2: 1 | I2: 2 | J2: 3 | K2: 4 | L2: 5 | M2: 6 | N2: 7 | O2: 8 | P2: 9 | Q2: 10 | R2: 11 | S2: 12 | T2: 13 | U2: 14 | V2: 15 | W2: 16 | X2: 17 | Y2: 18 | Z2: 19 | AA2: 20 | AB2: 21 | AC2: 22 | AD2: 23 | AE2: 24 | AF2: 25 | AG2: 26 | AH2: 27 | AI2: 28 | AJ2: 29 | AK2: 30 | AL2: 31 | AM2: 32 | AN2: 33 | AO2: 34 | AP2: 35 | AQ2: 36 | AR2: 37 | AS2: 38 | AT2: 39 | AU2: 40 | AV2: 41 | AW2: 42 | AX2: 43 | AY2: 44 | AZ2: 45 | BA2: 46 | BB2: 47 | BC2: 48 | BD2: 49 | BE2: 50 | BF2: 51 | BG2: 52 | BH2: 53 | BI2: 54 | BJ2: 55 | BK2: 56 | BL2: 57 | BM2: 58 | BN2: 59 | BO2: 60 | BP2: 61 | BQ2: 62 | BR2: 63 | BS2: 64 | BT2: 65 | BU2: 66 | BV2: 67 | BW2: 68 | BX2: 69 | BY2: 70 | BZ2: 71 | CA2: 72 | CB2: 73 | CC2: 74 | CD2: 75 | CE2: 76 | CF2: 77 | CG2: 78 | CH2: 79 | CI2: 80 | CJ2: 81 | CK2: 82 | CL2: 83 | CM2: 84 | CN2: 85 | CO2: 86 | CP2: 87 | CQ2: 88 | CR2: 89 | CS2: 90 | CT2: 91 | CU2: 92 | CV2: 93 | CW2: 94 | CX2: 95 | CY2: 96 | CZ2: 97 | DA2: 98 | DB2: 99
D3: Process | E3: =SUBSTITUTE(D3," ","") -> Process | F3: =E3&2 -> Process2 | G3: If a manager hire and new role is required then select "New Role and New Hire" otherwise select "New Hire | H3: FullTime_To_PartTime | I3: FullTime_To_PartTime | J3: FullTime_To_PartTime | K3: FullTime_To_PartTime | L3: FullTime_To_PartTime | M3: FullTime_To_PartTime | N3: FullTime_To_PartTime | O3: FullTime_To_PartTime | P3: FullTime_To_PartTime | Q3: FullTime_To_PartTime | R3: FullTime_To_PartTime | S3: FullTime_To_PartTime | T3: FullTime_To_PartTime | U3: FullTime_To_PartTime | V3: FullTime_To_PartTime | W3: FullTime_To_PartTime | X3: FullTime_To_PartTime | Y3: FullTime_To_PartTime | Z3: FullTime_To_PartTime | AA3: FullTime_To_PartTime | AB3: FullTime_To_PartTime | AC3: FullTime_To_PartTime | AD3: FullTime_To_PartTime | AE3: FullTime_To_PartTime | AF3: FullTime_To_PartTime | AG3: FullTime_To_PartTime | AH3: FullTime_To_PartTime | AI3: FullTime_To_PartTime | AJ3: FullTime_To_PartTime | AK3: FullTime_To_PartTime | AL3: FullTime_To_PartTime | AM3: FullTime_To_PartTime | AN3: FullTime_To_PartTime | AO3: FullTime_To_PartTime | AP3: FullTime_To_PartTime | AQ3: FullTime_To_PartTime | AR3: FullTime_To_PartTime | AS3: FullTime_To_PartTime | AT3: FullTime_To_PartTime | AU3: FullTime_To_PartTime | AV3: FullTime_To_PartTime | AW3: FullTime_To_PartTime | AX3: FullTime_To_PartTime | AY3: FullTime_To_PartTime | AZ3: FullTime_To_PartTime | BA3: FullTime_To_PartTime | BB3: FullTime_To_PartTime | BC3: FullTime_To_PartTime | BD3: FullTime_To_PartTime | BE3: FullTime_To_PartTime | BF3: FullTime_To_PartTime | BG3: FullTime_To_PartTime | BH3: FullTime_To_PartTime | BI3: FullTime_To_PartTime | BJ3: FullTime_To_PartTime | BK3: FullTime_To_PartTime | BL3: FullTime_To_PartTime | BM3: FullTime_To_PartTime | BN3: FullTime_To_PartTime | BO3: FullTime_To_PartTime | BP3: FullTime_To_PartTime | BQ3: FullTime_To_PartTime | BR3: FullTime_To_PartTime | BS3: FullTime_To_PartTime | BT3: FullTime_To_PartTime | BU3: FullTime_To_PartTime | BV3: FullTime_To_PartTime | BW3: FullTime_To_PartTime | BX3: FullTime_To_PartTime | BY3: FullTime_To_PartTime | BZ3: FullTime_To_PartTime | CA3: FullTime_To_PartTime | CB3: FullTime_To_PartTime | CC3: FullTime_To_PartTime | CD3: FullTime_To_PartTime | CE3: FullTime_To_PartTime | CF3: FullTime_To_PartTime | CG3: FullTime_To_PartTime | CH3: FullTime_To_PartTime | CI3: FullTime_To_PartTime | CJ3: FullTime_To_PartTime | CK3: FullTime_To_PartTime | CL3: FullTime_To_PartTime | CM3: FullTime_To_PartTime | CN3: FullTime_To_PartTime | CO3: FullTime_To_PartTime | CP3: FullTime_To_PartTime | CQ3: FullTime_To_PartTime | CR3: FullTime_To_PartTime | CS3: FullTime_To_PartTime | CT3: FullTime_To_PartTime | CU3: FullTime_To_PartTime | CV3: FullTime_To_PartTime | CW3: FullTime_To_PartTime | CX3: FullTime_To_PartTime | CY3: FullTime_To_PartTime | CZ3: FullTime_To_PartTime | DA3: FullTime_To_PartTime | DB3: FullTime_To_PartTime
D4: Execution Flag | E4: =SUBSTITUTE(D4," ","") -> ExecutionFlag | F4: =E4&2 -> ExecutionFlag2 | G4: If set to No will not execute in next automation run | H4: Yes | I4: Yes | J4: Yes | K4: Yes | L4: Yes | M4: Yes | N4: Yes | O4: Yes | P4: Yes | Q4: Yes | R4: Yes | S4: Yes | T4: Yes | U4: Yes | V4: Yes | W4: Yes | X4: Yes | Y4: Yes | Z4: Yes | AA4: Yes | AB4: Yes | AC4: Yes | AD4: Yes | AE4: Yes | AF4: Yes | AG4: Yes | AH4: Yes | AI4: Yes | AJ4: Yes | AK4: Yes | AL4: Yes | AM4: Yes | AN4: Yes | AO4: Yes | AP4: Yes | AQ4: Yes | AR4: Yes | AS4: Yes | AT4: Yes | AU4: Yes | AV4: Yes | AW4: Yes | AX4: Yes | AY4: Yes | AZ4: Yes | BA4: Yes | BB4: Yes | BC4: Yes | BD4: Yes | BE4: Yes | BF4: Yes | BG4: Yes | BH4: Yes | BI4: Yes | BJ4: Yes | BK4: Yes | BL4: Yes | BM4: Yes | BN4: Yes | BO4: Yes | BP4: Yes | BQ4: Yes | BR4: Yes | BS4: Yes | BT4: Yes | BU4: Yes | BV4: Yes | BW4: Yes | BX4: Yes | BY4: Yes | BZ4: Yes | CA4: Yes | CB4: Yes | CC4: Yes | CD4: Yes | CE4: Yes | CF4: Yes | CG4: Yes | CH4: Yes | CI4: Yes | CJ4: Yes | CK4: Yes | CL4: Yes | CM4: Yes | CN4: Yes | CO4: Yes | CP4: Yes | CQ4: Yes | CR4: Yes | CS4: Yes | CT4: Yes | CU4: Yes | CV4: Yes | CW4: Yes | CX4: Yes | CY4: Yes | CZ4: Yes | DA4: Yes | DB4: Yes
D5: Country | E5: =SUBSTITUTE(D5," ","") -> Country | F5: =E5&2 -> Country2 | H5: Czechia | I5: Czechia | J5: Czechia | K5: Czechia | L5: Czechia | M5: Czechia | N5: Czechia | O5: Czechia | P5: Czechia | Q5: Czechia | R5: Czechia | S5: Czechia | T5: Czechia | U5: Czechia | V5: Czechia | W5: Czechia | X5: Czechia | Y5: Czechia | Z5: Czechia | AA5: Czechia | AB5: Czechia | AC5: Czechia | AD5: Czechia | AE5: Czechia | AF5: Czechia | AG5: Czechia | AH5: Czechia | AI5: Czechia | AJ5: Czechia | AK5: Czechia | AL5: Czechia | AM5: Czechia | AN5: Czechia | AO5: Czechia | AP5: Czechia | AQ5: Czechia | AR5: Czechia | AS5: Czechia | AT5: Czechia | AU5: Czechia | AV5: Czechia | AW5: Czechia | AX5: Czechia | AY5: Czechia | AZ5: Czechia | BA5: Czechia | BB5: Czechia | BC5: Czechia | BD5: Czechia | BE5: Czechia | BF5: Czechia | BG5: Czechia | BH5: Czechia | BI5: Czechia | BJ5: Czechia | BK5: Czechia | BL5: Czechia | BM5: Czechia | BN5: Czechia | BO5: Czechia | BP5: Czechia | BQ5: Czechia | BR5: Czechia | BS5: Czechia | BT5: Czechia | BU5: Czechia | BV5: Czechia | BW5: Czechia | BX5: Czechia | BY5: Czechia | BZ5: Czechia | CA5: Czechia | CB5: Czechia | CC5: Czechia | CD5: Czechia | CE5: Czechia | CF5: Czechia | CG5: Czechia | CH5: Czechia | CI5: Czechia | CJ5: Czechia | CK5: Czechia | CL5: Czechia | CM5: Czechia | CN5: Czechia | CO5: Czechia | CP5: Czechia | CQ5: Czechia | CR5: Czechia | CS5: Czechia | CT5: Czechia | CU5: Czechia | CV5: Czechia | CW5: Czechia | CX5: Czechia | CY5: Czechia | CZ5: Czechia | DA5: Czechia | DB5: Czechia
D6: Last Run Time and Status | E6: =SUBSTITUTE(D6," ","") -> LastRunTimeandStatus | F6: =E6&2 -> LastRunTimeandStatus2 | G6: Once test is executed the Execution Timestamp and Pass/Fail status will be recorded here
A7: Portugal-Fixed_To_Permanent | D7: Last Run Error Message | E7: =SUBSTITUTE(D7," ","") -> LastRunErrorMessage | F7: =E7&2 -> LastRunErrorMessage2 | G7: If Automation throws errors, the details will be placed here
D8: Defect Description | E8: =SUBSTITUTE(D8," ","") -> DefectDescription | F8: =E8&2 -> DefectDescription2 | G8: After error investigation by the automation team, the defect description will be completed here
D9: Automation Comments | E9: =SUBSTITUTE(D9," ","") -> AutomationComments | F9: =E9&2 -> AutomationComments2 | G9: Automation team free text field
D10: QA Comments | E10: =SUBSTITUTE(D10," ","") -> QAComments | F10: =E10&2 -> QAComments2 | G10: QA team free text field
B12: Screen | C12: Subscreen | D12: Field | E12: Automation Ref | F12: Lookups Ref | H12: Test_1 | I12: Test_2 | J12: Test_3 | K12: Test_4 | L12: Test_5 | M12: Test_6 | N12: Test_7 | O12: Test_8 | P12: Test_9 | Q12: Test_10 | R12: Test_11 | S12: Test_12 | T12: Test_13 | U12: Test_14 | V12: Test_15 | W12: Test_16 | X12: Test_17 | Y12: Test_18 | Z12: Test_19 | AA12: Test_20 | AB12: Test_21 | AC12: Test_22 | AD12: Test_23 | AE12: Test_24 | AF12: Test_25 | AG12: Test_26 | AH12: Test_27 | AI12: Test_28 | AJ12: Test_29 | AK12: Test_30 | AL12: Test_31 | AM12: Test_32 | AN12: Test_33 | AO12: Test_34 | AP12: Test_35 | AQ12: Test_36 | AR12: Test_37 | AS12: Test_38 | AT12: Test_39 | AU12: Test_40 | AV12: Test_41 | AW12: Test_42 | AX12: Test_43 | AY12: Test_44 | AZ12: Test_45 | BA12: Test_46 | BB12: Test_47 | BC12: Test_48 | BD12: Test_49 | BE12: Test_50 | BF12: Test_51 | BG12: Test_52 | BH12: Test_53 | BI12: Test_54 | BJ12: Test_55 | BK12: Test_56 | BL12: Test_57 | BM12: Test_58 | BN12: Test_59 | BO12: Test_60 | BP12: Test_61 | BQ12: Test_62 | BR12: Test_63 | BS12: Test_64 | BT12: Test_65 | BU12: Test_66 | BV12: Test_67 | BW12: Test_68 | BX12: Test_69 | BY12: Test_70 | BZ12: Test_71 | CA12: Test_72 | CB12: Test_73 | CC12: Test_74 | CD12: Test_75 | CE12: Test_76 | CF12: Test_77 | CG12: Test_78 | CH12: Test_79 | CI12: Test_80 | CJ12: Test_81 | CK12: Test_82 | CL12: Test_83 | CM12: Test_84 | CN12: Test_85 | CO12: Test_86 | CP12: Test_87 | CQ12: Test_88 | CR12: Test_89 | CS12: Test_90 | CT12: Test_91 | CU12: Test_92 | CV12: Test_93 | CW12: Test_94 | CX12: Test_95 | CY12: Test_96 | CZ12: Test_97 | DA12: Test_98 | DB12: Test_99
A13: Romania-Promotion, Portugal-PT_To_FT, Portugal-Fixed_To_Permanent | B13: Login | C13: N/A | D13: Username | E13: =SUBSTITUTE(B13," ","") & "_" & SUBSTITUTE(IF(C13="N/A","",C13& "_")," ","") & SUBSTITUTE(SUBSTITUTE(D13," ",""),"/","") -> Login_Username | F13: =E13&2 -> Login_Username2 | H13: 90002195 | I13: 90002195 | J13: 90002195 | K13: 90002195 | L13: 90002195 | M13: 90002195 | N13: 90002195 | O13: 90002195 | P13: 90002195 | Q13: 90002195 | R13: 90002195 | S13: 90002195 | T13: 90002195 | U13: 90002195 | V13: 90002195 | W13: 90002195 | X13: 90002195 | Y13: 90002195 | Z13: 90002195 | AA13: 90002195 | AB13: 90002195 | AC13: 90002195 | AD13: 90002195 | AE13: 90002195 | AF13: 90002195 | AG13: 90002195 | AH13: 90002195 | AI13: 90002195 | AJ13: 90002195 | AK13: 90002195 | AL13: 90002195 | AM13: 90002195 | AN13: 90002195 | AO13: 90002195 | AP13: 90002195 | AQ13: 90002195 | AR13: 90002195 | AS13: 90002195 | AT13: 90002195 | AU13: 90002195 | AV13: 90002195 | AW13: 90002195 | AX13: 90002195 | AY13: 90002195 | AZ13: 90002195 | BA13: 90002195 | BB13: 90002195 | BC13: 90002195 | BD13: 90002195 | BE13: 90002195 | BF13: 90002195 | BG13: 90002195 | BH13: 90002195 | BI13: 90002195 | BJ13: 90002195 | BK13: 90002195 | BL13: 90002195 | BM13: 90002195 | BN13: 90002195 | BO13: 90002195 | BP13: 90002195 | BQ13: 90002195 | BR13: 90002195 | BS13: 90002195 | BT13: 90002195 | BU13: 90002195 | BV13: 90002195 | BW13: 90002195 | BX13: 90002195 | BY13: 90002195 | BZ13: 90002195 | CA13: 90002195 | CB13: 90002195 | CC13: 90002195 | CD13: 90002195 | CE13: 90002195 | CF13: 90002195 | CG13: 90002195 | CH13: 90002195 | CI13: 90002195 | CJ13: 90002195 | CK13: 90002195 | CL13: 90002195 | CM13: 90002195 | CN13: 90002195 | CO13: 90002195 | CP13: 90002195 | CQ13: 90002195 | CR13: 90002195 | CS13: 90002195 | CT13: 90002195 | CU13: 90002195 | CV13: 90002195 | CW13: 90002195 | CX13: 90002195 | CY13: 90002195 | CZ13: 90002195 | DA13: 90002195 | DB13: 90002195
A14: Romania-Promotion, Portugal-PT_To_FT, Portugal-Fixed_To_Permanent | B14: Login | C14: N/A | D14: Password | E14: =SUBSTITUTE(B14," ","") & "_" & SUBSTITUTE(IF(C14="N/A","",C14& "_")," ","") & SUBSTITUTE(SUBSTITUTE(D14," ",""),"/","") -> Login_Password | F14: =E14&2 -> Login_Password2 | H14: 65b795c1bf6d6c61cb007af2857d7d25d389ffbd49fc2e3cd7e638df | I14: 65b795c1bf6d6c61cb007af2857d7d25d389ffbd49fc2e3cd7e638df | J14: 65b795c1bf6d6c61cb007af2857d7d25d389ffbd49fc2e3cd7e638df | K14: 65b795c1bf6d6c61cb007af2857d7d25d389ffbd49fc2e3cd7e638df | L14: 65b795c1bf6d6c61cb007af2857d7d25d389ffbd49fc2e3cd7e638df | M14: 65b795c1bf6d6c61cb007af2857d7d25d389ffbd49fc2e3cd7e638df | N14: 65b795c1bf6d6c61cb007af2857d7d25d389ffbd49fc2e3cd7e638df | O14: 65b795c1bf6d6c61cb007af2857d7d25d389ffbd49fc2e3cd7e638df | P14: 65b795c1bf6d6c61cb007af2857d7d25d389ffbd49fc2e3cd7e638df | Q14: 65b795c1bf6d6c61cb007af2857d7d25d389ffbd49fc2e3cd7e638df | R14: 65b795c1bf6d6c61cb007af2857d7d25d389ffbd49fc2e3cd7e638df | S14: 65b795c1bf6d6c61cb007af2857d7d25d389ffbd49fc2e3cd7e638df | T14: 65b795c1bf6d6c61cb007af2857d7d25d389ffbd49fc2e3cd7e638df | U14: 65b795c1bf6d6c61cb007af2857d7d25d389ffbd49fc2e3cd7e638df | V14: 65b795c1bf6d6c61cb007af2857d7d25d389ffbd49fc2e3cd7e638df | W14: 65b795c1bf6d6c61cb007af2857d7d25d389ffbd49fc2e3cd7e638df | X14: 65b795c1bf6d6c61cb007af2857d7d25d389ffbd49fc2e3cd7e638df | Y14: 65b795c1bf6d6c61cb007af2857d7d25d389ffbd49fc2e3cd7e638df | Z14: 65b795c1bf6d6c61cb007af2857d7d25d389ffbd49fc2e3cd7e638df | AA14: 65b795c1bf6d6c61cb007af2857d7d25d389ffbd49fc2e3cd7e638df | AB14: 65b795c1bf6d6c61cb007af2857d7d25d389ffbd49fc2e3cd7e638df | AC14: 65b795c1bf6d6c61cb007af2857d7d25d389ffbd49fc2e3cd7e638df | AD14: 65b795c1bf6d6c61cb007af2857d7d25d389ffbd49fc2e3cd7e638df | AE14: 65b795c1bf6d6c61cb007af2857d7d25d389ffbd49fc2e3cd7e638df | AF14: 65b795c1bf6d6c61cb007af2857d7d25d389ffbd49fc2e3cd7e638df | AG14: 65b795c1bf6d6c61cb007af2857d7d25d389ffbd49fc2e3cd7e638df | AH14: 65b795c1bf6d6c61cb007af2857d7d25d389ffbd49fc2e3cd7e638df | AI14: 65b795c1bf6d6c61cb007af2857d7d25d389ffbd49fc2e3cd7e638df | AJ14: 65b795c1bf6d6c61cb007af2857d7d25d389ffbd49fc2e3cd7e638df | AK14: 65b795c1bf6d6c61cb007af2857d7d25d389ffbd49fc2e3cd7e638df | AL14: 65b795c1bf6d6c61cb007af2857d7d25d389ffbd49fc2e3cd7e638df | AM14: 65b795c1bf6d6c61cb007af2857d7d25d389ffbd49fc2e3cd7e638df | AN14: 65b795c1bf6d6c61cb007af2857d7d25d389ffbd49fc2e3cd7e638df | AO14: 65b795c1bf6d6c61cb007af2857d7d25d389ffbd49fc2e3cd7e638df | AP14: 65b795c1bf6d6c61cb007af2857d7d25d389ffbd49fc2e3cd7e638df | AQ14: 65b795c1bf6d6c61cb007af2857d7d25d389ffbd49fc2e3cd7e638df | AR14: 65b795c1bf6d6c61cb007af2857d7d25d389ffbd49fc2e3cd7e638df | AS14: 65b795c1bf6d6c61cb007af2857d7d25d389ffbd49fc2e3cd7e638df | AT14: 65b795c1bf6d6c61cb007af2857d7d25d389ffbd49fc2e3cd7e638df | AU14: 65b795c1bf6d6c61cb007af2857d7d25d389ffbd49fc2e3cd7e638df | AV14: 65b795c1bf6d6c61cb007af2857d7d25d389ffbd49fc2e3cd7e638df | AW14: 65b795c1bf6d6c61cb007af2857d7d25d389ffbd49fc2e3cd7e638df | AX14: 65b795c1bf6d6c61cb007af2857d7d25d389ffbd49fc2e3cd7e638df | AY14: 65b795c1bf6d6c61cb007af2857d7d25d389ffbd49fc2e3cd7e638df | AZ14: 65b795c1bf6d6c61cb007af2857d7d25d389ffbd49fc2e3cd7e638df | BA14: 65b795c1bf6d6c61cb007af2857d7d25d389ffbd49fc2e3cd7e638df | BB14: 65b795c1bf6d6c61cb007af2857d7d25d389ffbd49fc2e3cd7e638df | BC14: 65b795c1bf6d6c61cb007af2857d7d25d389ffbd49fc2e3cd7e638df | BD14: 65b795c1bf6d6c61cb007af2857d7d25d389ffbd49fc2e3cd7e638df | BE14: 65b795c1bf6d6c61cb007af2857d7d25d389ffbd49fc2e3cd7e638df | BF14: 65b795c1bf6d6c61cb007af2857d7d25d389ffbd49fc2e3cd7e638df | BG14: 65b795c1bf6d6c61cb007af2857d7d25d389ffbd49fc2e3cd7e638df | BH14: 65b795c1bf6d6c61cb007af2857d7d25d389ffbd49fc2e3cd7e638df | BI14: 65b795c1bf6d6c61cb007af2857d7d25d389ffbd49fc2e3cd7e638df | BJ14: 65b795c1bf6d6c61cb007af2857d7d25d389ffbd49fc2e3cd7e638df | BK14: 65b795c1bf6d6c61cb007af2857d7d25d389ffbd49fc2e3cd7e638df | BL14: 65b795c1bf6d6c61cb007af2857d7d25d389ffbd49fc2e3cd7e638df | BM14: 65b795c1bf6d6c61cb007af2857d7d25d389ffbd49fc2e3cd7e638df | BN14: 65b795c1bf6d6c61cb007af2857d7d25d389ffbd49fc2e3cd7e638df | BO14: 65b795c1bf6d6c61cb007af2857d7d25d389ffbd49fc2e3cd7e638df | BP14: 65b795c1bf6d6c61cb007af2857d7d25d389ffbd49fc2e3cd7e638df | BQ14: 65b795c1bf6d6c61cb007af2857d7d25d389ffbd49fc2e3cd7e638df | BR14: 65b795c1bf6d6c61cb007af2857d7d25d389ffbd49fc2e3cd7e638df | BS14: 65b795c1bf6d6c61cb007af2857d7d25d389ffbd49fc2e3cd7e638df | BT14: 65b795c1bf6d6c61cb007af2857d7d25d389ffbd49fc2e3cd7e638df | BU14: 65b795c1bf6d6c61cb007af2857d7d25d389ffbd49fc2e3cd7e638df | BV14: 65b795c1bf6d6c61cb007af2857d7d25d389ffbd49fc2e3cd7e638df | BW14: 65b795c1bf6d6c61cb007af2857d7d25d389ffbd49fc2e3cd7e638df | BX14: 65b795c1bf6d6c61cb007af2857d7d25d389ffbd49fc2e3cd7e638df | BY14: 65b795c1bf6d6c61cb007af2857d7d25d389ffbd49fc2e3cd7e638df | BZ14: 65b795c1bf6d6c61cb007af2857d7d25d389ffbd49fc2e3cd7e638df | CA14: 65b795c1bf6d6c61cb007af2857d7d25d389ffbd49fc2e3cd7e638df | CB14: 65b795c1bf6d6c61cb007af2857d7d25d389ffbd49fc2e3cd7e638df | CC14: 65b795c1bf6d6c61cb007af2857d7d25d389ffbd49fc2e3cd7e638df | CD14: 65b795c1bf6d6c61cb007af2857d7d25d389ffbd49fc2e3cd7e638df | CE14: 65b795c1bf6d6c61cb007af2857d7d25d389ffbd49fc2e3cd7e638df | CF14: 65b795c1bf6d6c61cb007af2857d7d25d389ffbd49fc2e3cd7e638df | CG14: 65b795c1bf6d6c61cb007af2857d7d25d389ffbd49fc2e3cd7e638df | CH14: 65b795c1bf6d6c61cb007af2857d7d25d389ffbd49fc2e3cd7e638df | CI14: 65b795c1bf6d6c61cb007af2857d7d25d389ffbd49fc2e3cd7e638df | CJ14: 65b795c1bf6d6c61cb007af2857d7d25d389ffbd49fc2e3cd7e638df | CK14: 65b795c1bf6d6c61cb007af2857d7d25d389ffbd49fc2e3cd7e638df | CL14: 65b795c1bf6d6c61cb007af2857d7d25d389ffbd49fc2e3cd7e638df | CM14: 65b795c1bf6d6c61cb007af2857d7d25d389ffbd49fc2e3cd7e638df | CN14: 65b795c1bf6d6c61cb007af2857d7d25d389ffbd49fc2e3cd7e638df | CO14: 65b795c1bf6d6c61cb007af2857d7d25d389ffbd49fc2e3cd7e638df | CP14: 65b795c1bf6d6c61cb007af2857d7d25d389ffbd49fc2e3cd7e638df | CQ14: 65b795c1bf6d6c61cb007af2857d7d25d389ffbd49fc2e3cd7e638df | CR14: 65b795c1bf6d6c61cb007af2857d7d25d389ffbd49fc2e3cd7e638df | CS14: 65b795c1bf6d6c61cb007af2857d7d25d389ffbd49fc2e3cd7e638df | CT14: 65b795c1bf6d6c61cb007af2857d7d25d389ffbd49fc2e3cd7e638df | CU14: 65b795c1bf6d6c61cb007af2857d7d25d389ffbd49fc2e3cd7e638df | CV14: 65b795c1bf6d6c61cb007af2857d7d25d389ffbd49fc2e3cd7e638df | CW14: 65b795c1bf6d6c61cb007af2857d7d25d389ffbd49fc2e3cd7e638df | CX14: 65b795c1bf6d6c61cb007af2857d7d25d389ffbd49fc2e3cd7e638df | CY14: 65b795c1bf6d6c61cb007af2857d7d25d389ffbd49fc2e3cd7e638df | CZ14: 65b795c1bf6d6c61cb007af2857d7d25d389ffbd49fc2e3cd7e638df | DA14: 65b795c1bf6d6c61cb007af2857d7d25d389ffbd49fc2e3cd7e638df | DB14: 65b795c1bf6d6c61cb007af2857d7d25d389ffbd49fc2e3cd7e638df
A15: Romania-Promotion, Portugal-PT_To_FT, Portugal-Fixed_To_Permanent | B15: Proxy | C15: N/A | D15: Employee ID | E15: =SUBSTITUTE(B15," ","") & "_" & SUBSTITUTE(IF(C15="N/A","",C15& "_")," ","") & SUBSTITUTE(SUBSTITUTE(D15," ",""),"/","") -> Proxy_EmployeeID | F15: =E15&2 -> Proxy_EmployeeID2 | H15: 10543013 | I15: 10565020 | J15: 10550629 | K15: 10616945 | L15: 10628812 | M15: 10514677 | N15: 10576087 | O15: 10576250 | P15: 10581486 | Q15: 10576088 | R15: 10576897 | S15: 10509271 | T15: 10616779 | U15: 10575849 | V15: 10506533 | W15: 10576183 | X15: 10537124 | Y15: 10565049 | Z15: 10502364 | AA15: 10540543 | AB15: 10561673 | AC15: 10581485 | AD15: 10495993 | AE15: 10513485 | AF15: 10256836 | AG15: 10576095 | AH15: 10588288 | AI15: 10250271 | AJ15: 10568627 | AK15: 10568608 | AL15: 10511417 | AM15: 10513256 | AN15: 10598394 | AO15: 10543072 | AP15: 10628115 | AQ15: 10622284 | AR15: 10622213 | AS15: 10514684 | AT15: 10572404 | AU15: 10622265 | AV15: 10568803 | AW15: 10602155 | AX15: 10588040 | AY15: 10598424 | AZ15: 10580440 | BA15: 10626863 | BB15: 10250339 | BC15: 10511328 | BD15: 10602135 | BE15: 10573791 | BF15: 10561077 | BG15: 10598420 | BH15: 10572393 | BI15: 10502373 | BJ15: 10496001 | BK15: 10616941 | BL15: 10588308 | BM15: 10250345 | BN15: 10255631 | BO15: 10611180 | BP15: 10543391 | BQ15: 10540442 | BR15: 10580332 | BS15: 10573944 | BT15: 10509268 | BU15: 10576104 | BV15: 10611099 | BW15: 10594430 | BX15: 10616798 | BY15: 10596934 | BZ15: 10562732 | CA15: 10587789 | CB15: 10602117 | CC15: 10510348 | CD15: 10573948 | CE15: 10575863 | CF15: 10594588 | CG15: 10502368 | CH15: 10611139 | CI15: 10550764 | CJ15: 10581468 | CK15: 10626908 | CL15: 10647669 | CM15: 10628810 | CN15: 10602148 | CO15: 10647796 | CP15: 10626782 | CQ15: 10253414 | CR15: 10513662 | CS15: 10619279 | CT15: 10607473 | CU15: 10550601 | CV15: 10253758 | CW15: 10607744 | CX15: 10584861 | CY15: 10579983 | CZ15: 10591841 | DA15: 10562707 | DB15: 10544843
A16: Romania-Promotion, Portugal-PT_To_FT, Portugal-Fixed_To_Permanent | B16: Change Job | C16: Start | D16: Effective Date | E16: =SUBSTITUTE(B16," ","") & "_" & SUBSTITUTE(IF(C16="N/A","",C16& "_")," ","") & SUBSTITUTE(SUBSTITUTE(D16," ",""),"/","") -> ChangeJob_Start_EffectiveDate | F16: =E16&2 -> ChangeJob_Start_EffectiveDate2 | H16: 45627 | I16: 45627 | J16: 45627 | K16: 45627 | L16: 45627 | M16: 45627 | N16: 45627 | O16: 45627 | P16: 45627 | Q16: 45627 | R16: 45627 | S16: 45627 | T16: 45627 | U16: 45627 | V16: 45627 | W16: 45627 | X16: 45627 | Y16: 45627 | Z16: 45627 | AA16: 45627 | AB16: 45627 | AC16: 45627 | AD16: 45627 | AE16: 45627 | AF16: 45627 | AG16: 45627 | AH16: 45627 | AI16: 45627 | AJ16: 45627 | AK16: 45627 | AL16: 45627 | AM16: 45627 | AN16: 45627 | AO16: 45627 | AP16: 45627 | AQ16: 45627 | AR16: 45627 | AS16: 45627 | AT16: 45627 | AU16: 45627 | AV16: 45627 | AW16: 45627 | AX16: 45627 | AY16: 45627 | AZ16: 45627 | BA16: 45627 | BB16: 45627 | BC16: 45627 | BD16: 45627 | BE16: 45627 | BF16: 45627 | BG16: 45627 | BH16: 45627 | BI16: 45627 | BJ16: 45627 | BK16: 45627 | BL16: 45627 | BM16: 45627 | BN16: 45627 | BO16: 45627 | BP16: 45627 | BQ16: 45627 | BR16: 45627 | BS16: 45627 | BT16: 45627 | BU16: 45627 | BV16: 45627 | BW16: 45627 | BX16: 45627 | BY16: 45627 | BZ16: 45627 | CA16: 45627 | CB16: 45627 | CC16: 45627 | CD16: 45627 | CE16: 45627 | CF16: 45627 | CG16: 45627 | CH16: 45627 | CI16: 45627 | CJ16: 45627 | CK16: 45627 | CL16: 45627 | CM16: 45627 | CN16: 45627 | CO16: 45627 | CP16: 45627 | CQ16: 45627 | CR16: 45627 | CS16: 45627 | CT16: 45627 | CU16: 45627 | CV16: 45627 | CW16: 45627 | CX16: 45627 | CY16: 45627 | CZ16: 45627 | DA16: 45627 | DB16: 45627
A17: Romania-Promotion, Portugal-PT_To_FT, Portugal-Fixed_To_Permanent | B17: Change Job | C17: Start | D17: Reason | E17: =SUBSTITUTE(B17," ","") & "_" & SUBSTITUTE(IF(C17="N/A","",C17& "_")," ","") & SUBSTITUTE(SUBSTITUTE(D17," ",""),"/","") -> ChangeJob_Start_Reason | F17: =E17&2 -> ChangeJob_Start_Reason2 | G17: Choice of Contractual Change/Promotion | H17: Change of Hours, Employee Type, Time Type, End Employment Date | I17: Change of Hours, Employee Type, Time Type, End Employment Date | J17: Change of Hours, Employee Type, Time Type, End Employment Date | K17: Change of Hours, Employee Type, Time Type, End Employment Date | L17: Change of Hours, Employee Type, Time Type, End Employment Date | M17: Change of Hours, Employee Type, Time Type, End Employment Date | N17: Change of Hours, Employee Type, Time Type, End Employment Date | O17: Change of Hours, Employee Type, Time Type, End Employment Date | P17: Change of Hours, Employee Type, Time Type, End Employment Date | Q17: Change of Hours, Employee Type, Time Type, End Employment Date | R17: Change of Hours, Employee Type, Time Type, End Employment Date | S17: Change of Hours, Employee Type, Time Type, End Employment Date | T17: Change of Hours, Employee Type, Time Type, End Employment Date | U17: Change of Hours, Employee Type, Time Type, End Employment Date | V17: Change of Hours, Employee Type, Time Type, End Employment Date | W17: Change of Hours, Employee Type, Time Type, End Employment Date | X17: Change of Hours, Employee Type, Time Type, End Employment Date | Y17: Change of Hours, Employee Type, Time Type, End Employment Date | Z17: Change of Hours, Employee Type, Time Type, End Employment Date | AA17: Change of Hours, Employee Type, Time Type, End Employment Date | AB17: Change of Hours, Employee Type, Time Type, End Employment Date | AC17: Change of Hours, Employee Type, Time Type, End Employment Date | AD17: Change of Hours, Employee Type, Time Type, End Employment Date | AE17: Change of Hours, Employee Type, Time Type, End Employment Date | AF17: Change of Hours, Employee Type, Time Type, End Employment Date | AG17: Change of Hours, Employee Type, Time Type, End Employment Date | AH17: Change of Hours, Employee Type, Time Type, End Employment Date | AI17: Change of Hours, Employee Type, Time Type, End Employment Date | AJ17: Change of Hours, Employee Type, Time Type, End Employment Date | AK17: Change of Hours, Employee Type, Time Type, End Employment Date | AL17: Change of Hours, Employee Type, Time Type, End Employment Date | AM17: Change of Hours, Employee Type, Time Type, End Employment Date | AN17: Change of Hours, Employee Type, Time Type, End Employment Date | AO17: Change of Hours, Employee Type, Time Type, End Employment Date | AP17: Change of Hours, Employee Type, Time Type, End Employment Date | AQ17: Change of Hours, Employee Type, Time Type, End Employment Date | AR17: Change of Hours, Employee Type, Time Type, End Employment Date | AS17: Change of Hours, Employee Type, Time Type, End Employment Date | AT17: Change of Hours, Employee Type, Time Type, End Employment Date | AU17: Change of Hours, Employee Type, Time Type, End Employment Date | AV17: Change of Hours, Employee Type, Time Type, End Employment Date | AW17: Change of Hours, Employee Type, Time Type, End Employment Date | AX17: Change of Hours, Employee Type, Time Type, End Employment Date | AY17: Change of Hours, Employee Type, Time Type, End Employment Date | AZ17: Change of Hours, Employee Type, Time Type, End Employment Date | BA17: Change of Hours, Employee Type, Time Type, End Employment Date | BB17: Change of Hours, Employee Type, Time Type, End Employment Date | BC17: Change of Hours, Employee Type, Time Type, End Employment Date | BD17: Change of Hours, Employee Type, Time Type, End Employment Date | BE17: Change of Hours, Employee Type, Time Type, End Employment Date | BF17: Change of Hours, Employee Type, Time Type, End Employment Date | BG17: Change of Hours, Employee Type, Time Type, End Employment Date | BH17: Change of Hours, Employee Type, Time Type, End Employment Date | BI17: Change of Hours, Employee Type, Time Type, End Employment Date | BJ17: Change of Hours, Employee Type, Time Type, End Employment Date | BK17: Change of Hours, Employee Type, Time Type, End Employment Date | BL17: Change of Hours, Employee Type, Time Type, End Employment Date | BM17: Change of Hours, Employee Type, Time Type, End Employment Date | BN17: Change of Hours, Employee Type, Time Type, End Employment Date | BO17: Change of Hours, Employee Type, Time Type, End Employment Date | BP17: Change of Hours, Employee Type, Time Type, End Employment Date | BQ17: Change of Hours, Employee Type, Time Type, End Employment Date | BR17: Change of Hours, Employee Type, Time Type, End Employment Date | BS17: Change of Hours, Employee Type, Time Type, End Employment Date | BT17: Change of Hours, Employee Type, Time Type, End Employment Date | BU17: Change of Hours, Employee Type, Time Type, End Employment Date | BV17: Change of Hours, Employee Type, Time Type, End Employment Date | BW17: Change of Hours, Employee Type, Time Type, End Employment Date | BX17: Change of Hours, Employee Type, Time Type, End Employment Date | BY17: Change of Hours, Employee Type, Time Type, End Employment Date | BZ17: Change of Hours, Employee Type, Time Type, End Employment Date | CA17: Change of Hours, Employee Type, Time Type, End Employment Date | CB17: Change of Hours, Employee Type, Time Type, End Employment Date | CC17: Change of Hours, Employee Type, Time Type, End Employment Date | CD17: Change of Hours, Employee Type, Time Type, End Employment Date | CE17: Change of Hours, Employee Type, Time Type, End Employment Date | CF17: Change of Hours, Employee Type, Time Type, End Employment Date | CG17: Change of Hours, Employee Type, Time Type, End Employment Date | CH17: Change of Hours, Employee Type, Time Type, End Employment Date | CI17: Change of Hours, Employee Type, Time Type, End Employment Date | CJ17: Change of Hours, Employee Type, Time Type, End Employment Date | CK17: Change of Hours, Employee Type, Time Type, End Employment Date | CL17: Change of Hours, Employee Type, Time Type, End Employment Date | CM17: Change of Hours, Employee Type, Time Type, End Employment Date | CN17: Change of Hours, Employee Type, Time Type, End Employment Date | CO17: Change of Hours, Employee Type, Time Type, End Employment Date | CP17: Change of Hours, Employee Type, Time Type, End Employment Date | CQ17: Change of Hours, Employee Type, Time Type, End Employment Date | CR17: Change of Hours, Employee Type, Time Type, End Employment Date | CS17: Change of Hours, Employee Type, Time Type, End Employment Date | CT17: Change of Hours, Employee Type, Time Type, End Employment Date | CU17: Change of Hours, Employee Type, Time Type, End Employment Date | CV17: Change of Hours, Employee Type, Time Type, End Employment Date | CW17: Change of Hours, Employee Type, Time Type, End Employment Date | CX17: Change of Hours, Employee Type, Time Type, End Employment Date | CY17: Change of Hours, Employee Type, Time Type, End Employment Date | CZ17: Change of Hours, Employee Type, Time Type, End Employment Date | DA17: Change of Hours, Employee Type, Time Type, End Employment Date | DB17: Change of Hours, Employee Type, Time Type, End Employment Date
A18: Romania-Promotion | B18: Change Job | C18: Start | D18: New Manager | E18: =SUBSTITUTE(B18," ","") & "_" & SUBSTITUTE(IF(C18="N/A","",C18& "_")," ","") & SUBSTITUTE(SUBSTITUTE(D18," ",""),"/","") -> ChangeJob_Start_NewManager | F18: =E18&2 -> ChangeJob_Start_NewManager2 | G18: Only needed if promoted to manager. Otherwise N/A | H18: N/A | I18: N/A | J18: N/A | K18: N/A | L18: N/A | M18: N/A | N18: N/A | O18: N/A | P18: N/A | Q18: N/A | R18: N/A | S18: N/A | T18: N/A | U18: N/A | V18: N/A | W18: N/A | X18: N/A | Y18: N/A | Z18: N/A | AA18: N/A | AB18: N/A | AC18: N/A | AD18: N/A | AE18: N/A | AF18: N/A | AG18: N/A | AH18: N/A | AI18: N/A | AJ18: N/A | AK18: N/A | AL18: N/A | AM18: N/A | AN18: N/A | AO18: N/A | AP18: N/A | AQ18: N/A | AR18: N/A | AS18: N/A | AT18: N/A | AU18: N/A | AV18: N/A | AW18: N/A | AX18: N/A | AY18: N/A | AZ18: N/A | BA18: N/A | BB18: N/A | BC18: N/A | BD18: N/A | BE18: N/A | BF18: N/A | BG18: N/A | BH18: N/A | BI18: N/A | BJ18: N/A | BK18: N/A | BL18: N/A | BM18: N/A | BN18: N/A | BO18: N/A | BP18: N/A | BQ18: N/A | BR18: N/A | BS18: N/A | BT18: N/A | BU18: N/A | BV18: N/A | BW18: N/A | BX18: N/A | BY18: N/A | BZ18: N/A | CA18: N/A | CB18: N/A | CC18: N/A | CD18: N/A | CE18: N/A | CF18: N/A | CG18: N/A | CH18: N/A | CI18: N/A | CJ18: N/A | CK18: N/A | CL18: N/A | CM18: N/A | CN18: N/A | CO18: N/A | CP18: N/A | CQ18: N/A | CR18: N/A | CS18: N/A | CT18: N/A | CU18: N/A | CV18: N/A | CW18: N/A | CX18: N/A | CY18: N/A | CZ18: N/A | DA18: N/A | DB18: N/A
A19: Romania-Promotion | B19: Change Job | C19: Start | D19: New Team | E19: =SUBSTITUTE(B19," ","") & "_" & SUBSTITUTE(IF(C19="N/A","",C19& "_")," ","") & SUBSTITUTE(SUBSTITUTE(D19," ",""),"/","") -> ChangeJob_Start_NewTeam | F19: =E19&2 -> ChangeJob_Start_NewTeam2 | G19: Only needed if changing store. Otherwise N/A | H19: N/A | I19: N/A | J19: N/A | K19: N/A | L19: N/A | M19: N/A | N19: N/A | O19: N/A | P19: N/A | Q19: N/A | R19: N/A | S19: N/A | T19: N/A | U19: N/A | V19: N/A | W19: N/A | X19: N/A | Y19: N/A | Z19: N/A | AA19: N/A | AB19: N/A | AC19: N/A | AD19: N/A | AE19: N/A | AF19: N/A | AG19: N/A | AH19: N/A | AI19: N/A | AJ19: N/A | AK19: N/A | AL19: N/A | AM19: N/A | AN19: N/A | AO19: N/A | AP19: N/A | AQ19: N/A | AR19: N/A | AS19: N/A | AT19: N/A | AU19: N/A | AV19: N/A | AW19: N/A | AX19: N/A | AY19: N/A | AZ19: N/A | BA19: N/A | BB19: N/A | BC19: N/A | BD19: N/A | BE19: N/A | BF19: N/A | BG19: N/A | BH19: N/A | BI19: N/A | BJ19: N/A | BK19: N/A | BL19: N/A | BM19: N/A | BN19: N/A | BO19: N/A | BP19: N/A | BQ19: N/A | BR19: N/A | BS19: N/A | BT19: N/A | BU19: N/A | BV19: N/A | BW19: N/A | BX19: N/A | BY19: N/A | BZ19: N/A | CA19: N/A | CB19: N/A | CC19: N/A | CD19: N/A | CE19: N/A | CF19: N/A | CG19: N/A | CH19: N/A | CI19: N/A | CJ19: N/A | CK19: N/A | CL19: N/A | CM19: N/A | CN19: N/A | CO19: N/A | CP19: N/A | CQ19: N/A | CR19: N/A | CS19: N/A | CT19: N/A | CU19: N/A | CV19: N/A | CW19: N/A | CX19: N/A | CY19: N/A | CZ19: N/A | DA19: N/A | DB19: N/A
A20: Romania-Promotion | B20: Change Job | C20: Start | D20: New Location | E20: =SUBSTITUTE(B20," ","") & "_" & SUBSTITUTE(IF(C20="N/A","",C20& "_")," ","") & SUBSTITUTE(SUBSTITUTE(D20," ",""),"/","") -> ChangeJob_Start_NewLocation | F20: =E20&2 -> ChangeJob_Start_NewLocation2 | G20: Only needed if changing store. Otherwise N/A | H20: N/A | I20: N/A | J20: N/A | K20: N/A | L20: N/A | M20: N/A | N20: N/A | O20: N/A | P20: N/A | Q20: N/A | R20: N/A | S20: N/A | T20: N/A | U20: N/A | V20: N/A | W20: N/A | X20: N/A | Y20: N/A | Z20: N/A | AA20: N/A | AB20: N/A | AC20: N/A | AD20: N/A | AE20: N/A | AF20: N/A | AG20: N/A | AH20: N/A | AI20: N/A | AJ20: N/A | AK20: N/A | AL20: N/A | AM20: N/A | AN20: N/A | AO20: N/A | AP20: N/A | AQ20: N/A | AR20: N/A | AS20: N/A | AT20: N/A | AU20: N/A | AV20: N/A | AW20: N/A | AX20: N/A | AY20: N/A | AZ20: N/A | BA20: N/A | BB20: N/A | BC20: N/A | BD20: N/A | BE20: N/A | BF20: N/A | BG20: N/A | BH20: N/A | BI20: N/A | BJ20: N/A | BK20: N/A | BL20: N/A | BM20: N/A | BN20: N/A | BO20: N/A | BP20: N/A | BQ20: N/A | BR20: N/A | BS20: N/A | BT20: N/A | BU20: N/A | BV20: N/A | BW20: N/A | BX20: N/A | BY20: N/A | BZ20: N/A | CA20: N/A | CB20: N/A | CC20: N/A | CD20: N/A | CE20: N/A | CF20: N/A | CG20: N/A | CH20: N/A | CI20: N/A | CJ20: N/A | CK20: N/A | CL20: N/A | CM20: N/A | CN20: N/A | CO20: N/A | CP20: N/A | CQ20: N/A | CR20: N/A | CS20: N/A | CT20: N/A | CU20: N/A | CV20: N/A | CW20: N/A | CX20: N/A | CY20: N/A | CZ20: N/A | DA20: N/A | DB20: N/A
A21: Romania-Promotion | B21: Change Job | C21: Start | D21: Next Pay Period | E21: =SUBSTITUTE(B21," ","") & "_" & SUBSTITUTE(IF(C21="N/A","",C21& "_")," ","") & SUBSTITUTE(SUBSTITUTE(D21," ",""),"/","") -> ChangeJob_Start_NextPayPeriod | F21: =E21&2 -> ChangeJob_Start_NextPayPeriod2 | H21: N/A | I21: N/A | J21: N/A | K21: N/A | L21: N/A | M21: N/A | N21: N/A | O21: N/A | P21: N/A | Q21: N/A | R21: N/A | S21: N/A | T21: N/A | U21: N/A | V21: N/A | W21: N/A | X21: N/A | Y21: N/A | Z21: N/A | AA21: N/A | AB21: N/A | AC21: N/A | AD21: N/A | AE21: N/A | AF21: N/A | AG21: N/A | AH21: N/A | AI21: N/A | AJ21: N/A | AK21: N/A | AL21: N/A | AM21: N/A | AN21: N/A | AO21: N/A | AP21: N/A | AQ21: N/A | AR21: N/A | AS21: N/A | AT21: N/A | AU21: N/A | AV21: N/A | AW21: N/A | AX21: N/A | AY21: N/A | AZ21: N/A | BA21: N/A | BB21: N/A | BC21: N/A | BD21: N/A | BE21: N/A | BF21: N/A | BG21: N/A | BH21: N/A | BI21: N/A | BJ21: N/A | BK21: N/A | BL21: N/A | BM21: N/A | BN21: N/A | BO21: N/A | BP21: N/A | BQ21: N/A | BR21: N/A | BS21: N/A | BT21: N/A | BU21: N/A | BV21: N/A | BW21: N/A | BX21: N/A | BY21: N/A | BZ21: N/A | CA21: N/A | CB21: N/A | CC21: N/A | CD21: N/A | CE21: N/A | CF21: N/A | CG21: N/A | CH21: N/A | CI21: N/A | CJ21: N/A | CK21: N/A | CL21: N/A | CM21: N/A | CN21: N/A | CO21: N/A | CP21: N/A | CQ21: N/A | CR21: N/A | CS21: N/A | CT21: N/A | CU21: N/A | CV21: N/A | CW21: N/A | CX21: N/A | CY21: N/A | CZ21: N/A | DA21: N/A | DB21: N/A
A22: Romania-Promotion | B22: Change Job | C22: Job Profile | D22: Job Profile | E22: =SUBSTITUTE(B22," ","") & "_" & SUBSTITUTE(IF(C22="N/A","",C22& "_")," ","") & SUBSTITUTE(SUBSTITUTE(D22," ",""),"/","") -> ChangeJob_JobProfile_JobProfile | F22: =E22&2 -> ChangeJob_JobProfile_JobProfile2 | H22: N/A | I22: N/A | J22: N/A | K22: N/A | L22: N/A | M22: N/A | N22: N/A | O22: N/A | P22: N/A | Q22: N/A | R22: N/A | S22: N/A | T22: N/A | U22: N/A | V22: N/A | W22: N/A | X22: N/A | Y22: N/A | Z22: N/A | AA22: N/A | AB22: N/A | AC22: N/A | AD22: N/A | AE22: N/A | AF22: N/A | AG22: N/A | AH22: N/A | AI22: N/A | AJ22: N/A | AK22: N/A | AL22: N/A | AM22: N/A | AN22: N/A | AO22: N/A | AP22: N/A | AQ22: N/A | AR22: N/A | AS22: N/A | AT22: N/A | AU22: N/A | AV22: N/A | AW22: N/A | AX22: N/A | AY22: N/A | AZ22: N/A | BA22: N/A | BB22: N/A | BC22: N/A | BD22: N/A | BE22: N/A | BF22: N/A | BG22: N/A | BH22: N/A | BI22: N/A | BJ22: N/A | BK22: N/A | BL22: N/A | BM22: N/A | BN22: N/A | BO22: N/A | BP22: N/A | BQ22: N/A | BR22: N/A | BS22: N/A | BT22: N/A | BU22: N/A | BV22: N/A | BW22: N/A | BX22: N/A | BY22: N/A | BZ22: N/A | CA22: N/A | CB22: N/A | CC22: N/A | CD22: N/A | CE22: N/A | CF22: N/A | CG22: N/A | CH22: N/A | CI22: N/A | CJ22: N/A | CK22: N/A | CL22: N/A | CM22: N/A | CN22: N/A | CO22: N/A | CP22: N/A | CQ22: N/A | CR22: N/A | CS22: N/A | CT22: N/A | CU22: N/A | CV22: N/A | CW22: N/A | CX22: N/A | CY22: N/A | CZ22: N/A | DA22: N/A | DB22: N/A
A23: Romania-Promotion | B23: Change Job | C23: Job Profile | D23: Job Title | E23: =SUBSTITUTE(B23," ","") & "_" & SUBSTITUTE(IF(C23="N/A","",C23& "_")," ","") & SUBSTITUTE(SUBSTITUTE(D23," ",""),"/","") -> ChangeJob_JobProfile_JobTitle | F23: =E23&2 -> ChangeJob_JobProfile_JobTitle2 | H23: N/A | I23: N/A | J23: N/A | K23: N/A | L23: N/A | M23: N/A | N23: N/A | O23: N/A | P23: N/A | Q23: N/A | R23: N/A | S23: N/A | T23: N/A | U23: N/A | V23: N/A | W23: N/A | X23: N/A | Y23: N/A | Z23: N/A | AA23: N/A | AB23: N/A | AC23: N/A | AD23: N/A | AE23: N/A | AF23: N/A | AG23: N/A | AH23: N/A | AI23: N/A | AJ23: N/A | AK23: N/A | AL23: N/A | AM23: N/A | AN23: N/A | AO23: N/A | AP23: N/A | AQ23: N/A | AR23: N/A | AS23: N/A | AT23: N/A | AU23: N/A | AV23: N/A | AW23: N/A | AX23: N/A | AY23: N/A | AZ23: N/A | BA23: N/A | BB23: N/A | BC23: N/A | BD23: N/A | BE23: N/A | BF23: N/A | BG23: N/A | BH23: N/A | BI23: N/A | BJ23: N/A | BK23: N/A | BL23: N/A | BM23: N/A | BN23: N/A | BO23: N/A | BP23: N/A | BQ23: N/A | BR23: N/A | BS23: N/A | BT23: N/A | BU23: N/A | BV23: N/A | BW23: N/A | BX23: N/A | BY23: N/A | BZ23: N/A | CA23: N/A | CB23: N/A | CC23: N/A | CD23: N/A | CE23: N/A | CF23: N/A | CG23: N/A | CH23: N/A | CI23: N/A | CJ23: N/A | CK23: N/A | CL23: N/A | CM23: N/A | CN23: N/A | CO23: N/A | CP23: N/A | CQ23: N/A | CR23: N/A | CS23: N/A | CT23: N/A | CU23: N/A | CV23: N/A | CW23: N/A | CX23: N/A | CY23: N/A | CZ23: N/A | DA23: N/A | DB23: N/A
A24: Romania-Promotion | B24: Change Job | C24: Location Details | D24: Location | E24: =SUBSTITUTE(B24," ","") & "_" & SUBSTITUTE(IF(C24="N/A","",C24& "_")," ","") & SUBSTITUTE(SUBSTITUTE(D24," ",""),"/","") -> ChangeJob_LocationDetails_Location | F24: =E24&2 -> ChangeJob_LocationDetails_Location2 | H24: 895 | I24: 895 | J24: 895 | K24: 895 | L24: 895 | M24: 895 | N24: 895 | O24: 895 | P24: 895 | Q24: 895 | R24: 895 | S24: 895 | T24: 895 | U24: 895 | V24: 895 | W24: 895 | X24: 895 | Y24: 895 | Z24: 895 | AA24: 895 | AB24: 895 | AC24: 895 | AD24: 895 | AE24: 895 | AF24: 895 | AG24: 895 | AH24: 895 | AI24: 895 | AJ24: 895 | AK24: 895 | AL24: 895 | AM24: 895 | AN24: 895 | AO24: 895 | AP24: 895 | AQ24: 895 | AR24: 895 | AS24: 895 | AT24: 895 | AU24: 895 | AV24: 895 | AW24: 895 | AX24: 895 | AY24: 895 | AZ24: 895 | BA24: 895 | BB24: 895 | BC24: 895 | BD24: 895 | BE24: 895 | BF24: 895 | BG24: 895 | BH24: 895 | BI24: 895 | BJ24: 895 | BK24: 895 | BL24: 895 | BM24: 895 | BN24: 895 | BO24: 895 | BP24: 895 | BQ24: 895 | BR24: 895 | BS24: 895 | BT24: 895 | BU24: 895 | BV24: 895 | BW24: 895 | BX24: 895 | BY24: 895 | BZ24: 895 | CA24: 895 | CB24: 895 | CC24: 895 | CD24: 895 | CE24: 895 | CF24: 895 | CG24: 895 | CH24: 895 | CI24: 895 | CJ24: 895 | CK24: 895 | CL24: 895 | CM24: 895 | CN24: 895 | CO24: 895 | CP24: 895 | CQ24: 895 | CR24: 895 | CS24: 895 | CT24: 895 | CU24: 895 | CV24: 895 | CW24: 895 | CX24: 895 | CY24: 895 | CZ24: 895 | DA24: 895 | DB24: 895
A25: Romania-Promotion | B25: Change Job | C25: Location Details | D25: Scheduled Weekly Hours | E25: =SUBSTITUTE(B25," ","") & "_" & SUBSTITUTE(IF(C25="N/A","",C25& "_")," ","") & SUBSTITUTE(SUBSTITUTE(D25," ",""),"/","") -> ChangeJob_LocationDetails_ScheduledWeeklyHours | F25: =E25&2 -> ChangeJob_LocationDetails_ScheduledWeeklyHours2 | G25: Set to 100 for full time for Spain & 40 For FT Portugal | H25: N/A | I25: N/A | J25: N/A | K25: N/A | L25: N/A | M25: N/A | N25: N/A | O25: N/A | P25: N/A | Q25: N/A | R25: N/A | S25: N/A | T25: N/A | U25: N/A | V25: N/A | W25: N/A | X25: N/A | Y25: N/A | Z25: N/A | AA25: N/A | AB25: N/A | AC25: N/A | AD25: N/A | AE25: N/A | AF25: N/A | AG25: N/A | AH25: N/A | AI25: N/A | AJ25: N/A | AK25: N/A | AL25: N/A | AM25: N/A | AN25: N/A | AO25: N/A | AP25: N/A | AQ25: N/A | AR25: N/A | AS25: N/A | AT25: N/A | AU25: N/A | AV25: N/A | AW25: N/A | AX25: N/A | AY25: N/A | AZ25: N/A | BA25: N/A | BB25: N/A | BC25: N/A | BD25: N/A | BE25: N/A | BF25: N/A | BG25: N/A | BH25: N/A | BI25: N/A | BJ25: N/A | BK25: N/A | BL25: N/A | BM25: N/A | BN25: N/A | BO25: N/A | BP25: N/A | BQ25: N/A | BR25: N/A | BS25: N/A | BT25: N/A | BU25: N/A | BV25: N/A | BW25: N/A | BX25: N/A | BY25: N/A | BZ25: N/A | CA25: N/A | CB25: N/A | CC25: N/A | CD25: N/A | CE25: N/A | CF25: N/A | CG25: N/A | CH25: N/A | CI25: N/A | CJ25: N/A | CK25: N/A | CL25: N/A | CM25: N/A | CN25: N/A | CO25: N/A | CP25: N/A | CQ25: N/A | CR25: N/A | CS25: N/A | CT25: N/A | CU25: N/A | CV25: N/A | CW25: N/A | CX25: N/A | CY25: N/A | CZ25: N/A | DA25: N/A | DB25: N/A
A26: Romania-Promotion | B26: Change Job | C26: Location Details | D26: Work Shift | E26: =SUBSTITUTE(B26," ","") & "_" & SUBSTITUTE(IF(C26="N/A","",C26& "_")," ","") & SUBSTITUTE(SUBSTITUTE(D26," ",""),"/","") -> ChangeJob_LocationDetails_WorkShift | F26: =E26&2 -> ChangeJob_LocationDetails_WorkShift2 | G26: Should be 5 days for full time | H26: N/A | I26: N/A | J26: N/A | K26: N/A | L26: N/A | M26: N/A | N26: N/A | O26: N/A | P26: N/A | Q26: N/A | R26: N/A | S26: N/A | T26: N/A | U26: N/A | V26: N/A | W26: N/A | X26: N/A | Y26: N/A | Z26: N/A | AA26: N/A | AB26: N/A | AC26: N/A | AD26: N/A | AE26: N/A | AF26: N/A | AG26: N/A | AH26: N/A | AI26: N/A | AJ26: N/A | AK26: N/A | AL26: N/A | AM26: N/A | AN26: N/A | AO26: N/A | AP26: N/A | AQ26: N/A | AR26: N/A | AS26: N/A | AT26: N/A | AU26: N/A | AV26: N/A | AW26: N/A | AX26: N/A | AY26: N/A | AZ26: N/A | BA26: N/A | BB26: N/A | BC26: N/A | BD26: N/A | BE26: N/A | BF26: N/A | BG26: N/A | BH26: N/A | BI26: N/A | BJ26: N/A | BK26: N/A | BL26: N/A | BM26: N/A | BN26: N/A | BO26: N/A | BP26: N/A | BQ26: N/A | BR26: N/A | BS26: N/A | BT26: N/A | BU26: N/A | BV26: N/A | BW26: N/A | BX26: N/A | BY26: N/A | BZ26: N/A | CA26: N/A | CB26: N/A | CC26: N/A | CD26: N/A | CE26: N/A | CF26: N/A | CG26: N/A | CH26: N/A | CI26: N/A | CJ26: N/A | CK26: N/A | CL26: N/A | CM26: N/A | CN26: N/A | CO26: N/A | CP26: N/A | CQ26: N/A | CR26: N/A | CS26: N/A | CT26: N/A | CU26: N/A | CV26: N/A | CW26: N/A | CX26: N/A | CY26: N/A | CZ26: N/A | DA26: N/A | DB26: N/A
A27: Romania-Promotion | B27: Change Job | C27: Job Classifications | D27: Additional Job Classifications | E27: =SUBSTITUTE(B27," ","") & "_" & SUBSTITUTE(IF(C27="N/A","",C27& "_")," ","") & SUBSTITUTE(SUBSTITUTE(D27," ",""),"/","") -> ChangeJob_JobClassifications_AdditionalJobClassifications | F27: =E27&2 -> ChangeJob_JobClassifications_AdditionalJobClassifications2 | H27: N/A | I27: N/A | J27: N/A | K27: N/A | L27: N/A | M27: N/A | N27: N/A | O27: N/A | P27: N/A | Q27: N/A | R27: N/A | S27: N/A | T27: N/A | U27: N/A | V27: N/A | W27: N/A | X27: N/A | Y27: N/A | Z27: N/A | AA27: N/A | AB27: N/A | AC27: N/A | AD27: N/A | AE27: N/A | AF27: N/A | AG27: N/A | AH27: N/A | AI27: N/A | AJ27: N/A | AK27: N/A | AL27: N/A | AM27: N/A | AN27: N/A | AO27: N/A | AP27: N/A | AQ27: N/A | AR27: N/A | AS27: N/A | AT27: N/A | AU27: N/A | AV27: N/A | AW27: N/A | AX27: N/A | AY27: N/A | AZ27: N/A | BA27: N/A | BB27: N/A | BC27: N/A | BD27: N/A | BE27: N/A | BF27: N/A | BG27: N/A | BH27: N/A | BI27: N/A | BJ27: N/A | BK27: N/A | BL27: N/A | BM27: N/A | BN27: N/A | BO27: N/A | BP27: N/A | BQ27: N/A | BR27: N/A | BS27: N/A | BT27: N/A | BU27: N/A | BV27: N/A | BW27: N/A | BX27: N/A | BY27: N/A | BZ27: N/A | CA27: N/A | CB27: N/A | CC27: N/A | CD27: N/A | CE27: N/A | CF27: N/A | CG27: N/A | CH27: N/A | CI27: N/A | CJ27: N/A | CK27: N/A | CL27: N/A | CM27: N/A | CN27: N/A | CO27: N/A | CP27: N/A | CQ27: N/A | CR27: N/A | CS27: N/A | CT27: N/A | CU27: N/A | CV27: N/A | CW27: N/A | CX27: N/A | CY27: N/A | CZ27: N/A | DA27: N/A | DB27: N/A
A28: Romania-Promotion, Portugal-Fixed_To_Permanent | B28: Change Job | C28: Job Classifications | D28: Employee Type | E28: =SUBSTITUTE(B28," ","") & "_" & SUBSTITUTE(IF(C28="N/A","",C28& "_")," ","") & SUBSTITUTE(SUBSTITUTE(D28," ",""),"/","") -> ChangeJob_JobClassifications_EmployeeType | F28: =E28&2 -> ChangeJob_JobClassifications_EmployeeType2 | G28: Choice of Permanent/Fixed | H28: N/A | I28: N/A | J28: N/A | K28: N/A | L28: N/A | M28: N/A | N28: N/A | O28: N/A | P28: N/A | Q28: N/A | R28: N/A | S28: N/A | T28: N/A | U28: N/A | V28: N/A | W28: N/A | X28: N/A | Y28: N/A | Z28: N/A | AA28: N/A | AB28: N/A | AC28: N/A | AD28: N/A | AE28: N/A | AF28: N/A | AG28: N/A | AH28: N/A | AI28: N/A | AJ28: N/A | AK28: N/A | AL28: N/A | AM28: N/A | AN28: N/A | AO28: N/A | AP28: N/A | AQ28: N/A | AR28: N/A | AS28: N/A | AT28: N/A | AU28: N/A | AV28: N/A | AW28: N/A | AX28: N/A | AY28: N/A | AZ28: N/A | BA28: N/A | BB28: N/A | BC28: N/A | BD28: N/A | BE28: N/A | BF28: N/A | BG28: N/A | BH28: N/A | BI28: N/A | BJ28: N/A | BK28: N/A | BL28: N/A | BM28: N/A | BN28: N/A | BO28: N/A | BP28: N/A | BQ28: N/A | BR28: N/A | BS28: N/A | BT28: N/A | BU28: N/A | BV28: N/A | BW28: N/A | BX28: N/A | BY28: N/A | BZ28: N/A | CA28: N/A | CB28: N/A | CC28: N/A | CD28: N/A | CE28: N/A | CF28: N/A | CG28: N/A | CH28: N/A | CI28: N/A | CJ28: N/A | CK28: N/A | CL28: N/A | CM28: N/A | CN28: N/A | CO28: N/A | CP28: N/A | CQ28: N/A | CR28: N/A | CS28: N/A | CT28: N/A | CU28: N/A | CV28: N/A | CW28: N/A | CX28: N/A | CY28: N/A | CZ28: N/A | DA28: N/A | DB28: N/A
A29: Romania-Promotion, Portugal-PT_To_FT | B29: Change Job | C29: Job Classifications | D29: Time Type | E29: =SUBSTITUTE(B29," ","") & "_" & SUBSTITUTE(IF(C29="N/A","",C29& "_")," ","") & SUBSTITUTE(SUBSTITUTE(D29," ",""),"/","") -> ChangeJob_JobClassifications_TimeType | F29: =E29&2 -> ChangeJob_JobClassifications_TimeType2 | G29: Choice of Full Time/Part Time | H29: N/A | I29: N/A | J29: N/A | K29: N/A | L29: N/A | M29: N/A | N29: N/A | O29: N/A | P29: N/A | Q29: N/A | R29: N/A | S29: N/A | T29: N/A | U29: N/A | V29: N/A | W29: N/A | X29: N/A | Y29: N/A | Z29: N/A | AA29: N/A | AB29: N/A | AC29: N/A | AD29: N/A | AE29: N/A | AF29: N/A | AG29: N/A | AH29: N/A | AI29: N/A | AJ29: N/A | AK29: N/A | AL29: N/A | AM29: N/A | AN29: N/A | AO29: N/A | AP29: N/A | AQ29: N/A | AR29: N/A | AS29: N/A | AT29: N/A | AU29: N/A | AV29: N/A | AW29: N/A | AX29: N/A | AY29: N/A | AZ29: N/A | BA29: N/A | BB29: N/A | BC29: N/A | BD29: N/A | BE29: N/A | BF29: N/A | BG29: N/A | BH29: N/A | BI29: N/A | BJ29: N/A | BK29: N/A | BL29: N/A | BM29: N/A | BN29: N/A | BO29: N/A | BP29: N/A | BQ29: N/A | BR29: N/A | BS29: N/A | BT29: N/A | BU29: N/A | BV29: N/A | BW29: N/A | BX29: N/A | BY29: N/A | BZ29: N/A | CA29: N/A | CB29: N/A | CC29: N/A | CD29: N/A | CE29: N/A | CF29: N/A | CG29: N/A | CH29: N/A | CI29: N/A | CJ29: N/A | CK29: N/A | CL29: N/A | CM29: N/A | CN29: N/A | CO29: N/A | CP29: N/A | CQ29: N/A | CR29: N/A | CS29: N/A | CT29: N/A | CU29: N/A | CV29: N/A | CW29: N/A | CX29: N/A | CY29: N/A | CZ29: N/A | DA29: N/A | DB29: N/A
A30: Romania-Promotion | B30: Change Job | C30: Job Classifications | D30: Pay Rate Type | E30: =SUBSTITUTE(B30," ","") & "_" & SUBSTITUTE(IF(C30="N/A","",C30& "_")," ","") & SUBSTITUTE(SUBSTITUTE(D30," ",""),"/","") -> ChangeJob_JobClassifications_PayRateType | F30: =E30&2 -> ChangeJob_JobClassifications_PayRateType2 | G30: Choice of Salary/Hourly/ | H30: N/A | I30: N/A | J30: N/A | K30: N/A | L30: N/A | M30: N/A | N30: N/A | O30: N/A | P30: N/A | Q30: N/A | R30: N/A | S30: N/A | T30: N/A | U30: N/A | V30: N/A | W30: N/A | X30: N/A | Y30: N/A | Z30: N/A | AA30: N/A | AB30: N/A | AC30: N/A | AD30: N/A | AE30: N/A | AF30: N/A | AG30: N/A | AH30: N/A | AI30: N/A | AJ30: N/A | AK30: N/A | AL30: N/A | AM30: N/A | AN30: N/A | AO30: N/A | AP30: N/A | AQ30: N/A | AR30: N/A | AS30: N/A | AT30: N/A | AU30: N/A | AV30: N/A | AW30: N/A | AX30: N/A | AY30: N/A | AZ30: N/A | BA30: N/A | BB30: N/A | BC30: N/A | BD30: N/A | BE30: N/A | BF30: N/A | BG30: N/A | BH30: N/A | BI30: N/A | BJ30: N/A | BK30: N/A | BL30: N/A | BM30: N/A | BN30: N/A | BO30: N/A | BP30: N/A | BQ30: N/A | BR30: N/A | BS30: N/A | BT30: N/A | BU30: N/A | BV30: N/A | BW30: N/A | BX30: N/A | BY30: N/A | BZ30: N/A | CA30: N/A | CB30: N/A | CC30: N/A | CD30: N/A | CE30: N/A | CF30: N/A | CG30: N/A | CH30: N/A | CI30: N/A | CJ30: N/A | CK30: N/A | CL30: N/A | CM30: N/A | CN30: N/A | CO30: N/A | CP30: N/A | CQ30: N/A | CR30: N/A | CS30: N/A | CT30: N/A | CU30: N/A | CV30: N/A | CW30: N/A | CX30: N/A | CY30: N/A | CZ30: N/A | DA30: N/A | DB30: N/A
A31: Romania-Promotion | B31: Change Job | C31: Job Classifications | D31: Default Weekly Hours | E31: =SUBSTITUTE(B31," ","") & "_" & SUBSTITUTE(IF(C31="N/A","",C31& "_")," ","") & SUBSTITUTE(SUBSTITUTE(D31," ",""),"/","") -> ChangeJob_JobClassifications_DefaultWeeklyHours | F31: =E31&2 -> ChangeJob_JobClassifications_DefaultWeeklyHours2 | H31: N/A | I31: N/A | J31: N/A | K31: N/A | L31: N/A | M31: N/A | N31: N/A | O31: N/A | P31: N/A | Q31: N/A | R31: N/A | S31: N/A | T31: N/A | U31: N/A | V31: N/A | W31: N/A | X31: N/A | Y31: N/A | Z31: N/A | AA31: N/A | AB31: N/A | AC31: N/A | AD31: N/A | AE31: N/A | AF31: N/A | AG31: N/A | AH31: N/A | AI31: N/A | AJ31: N/A | AK31: N/A | AL31: N/A | AM31: N/A | AN31: N/A | AO31: N/A | AP31: N/A | AQ31: N/A | AR31: N/A | AS31: N/A | AT31: N/A | AU31: N/A | AV31: N/A | AW31: N/A | AX31: N/A | AY31: N/A | AZ31: N/A | BA31: N/A | BB31: N/A | BC31: N/A | BD31: N/A | BE31: N/A | BF31: N/A | BG31: N/A | BH31: N/A | BI31: N/A | BJ31: N/A | BK31: N/A | BL31: N/A | BM31: N/A | BN31: N/A | BO31: N/A | BP31: N/A | BQ31: N/A | BR31: N/A | BS31: N/A | BT31: N/A | BU31: N/A | BV31: N/A | BW31: N/A | BX31: N/A | BY31: N/A | BZ31: N/A | CA31: N/A | CB31: N/A | CC31: N/A | CD31: N/A | CE31: N/A | CF31: N/A | CG31: N/A | CH31: N/A | CI31: N/A | CJ31: N/A | CK31: N/A | CL31: N/A | CM31: N/A | CN31: N/A | CO31: N/A | CP31: N/A | CQ31: N/A | CR31: N/A | CS31: N/A | CT31: N/A | CU31: N/A | CV31: N/A | CW31: N/A | CX31: N/A | CY31: N/A | CZ31: N/A | DA31: N/A | DB31: N/A
A32: Romania-Promotion | B32: Change Job | C32: Job Classifications | D32: End Employment Date | E32: =SUBSTITUTE(B32," ","") & "_" & SUBSTITUTE(IF(C32="N/A","",C32& "_")," ","") & SUBSTITUTE(SUBSTITUTE(D32," ",""),"/","") -> ChangeJob_JobClassifications_EndEmploymentDate | F32: =E32&2 -> ChangeJob_JobClassifications_EndEmploymentDate2 | H32: 46022 | I32: 46022 | J32: 46022 | K32: 46022 | L32: 46022 | M32: 46022 | N32: 46022 | O32: 46022 | P32: 46022 | Q32: 46022 | R32: 46022 | S32: 46022 | T32: 46022 | U32: 46022 | V32: 46022 | W32: 46022 | X32: 46022 | Y32: 46022 | Z32: 46022 | AA32: 46022 | AB32: 46022 | AC32: 46022 | AD32: 46022 | AE32: 46022 | AF32: 46022 | AG32: 46022 | AH32: 46022 | AI32: 46022 | AJ32: 46022 | AK32: 46022 | AL32: 46022 | AM32: 46022 | AN32: 46022 | AO32: 46022 | AP32: 46022 | AQ32: 46022 | AR32: 46022 | AS32: 46022 | AT32: 46022 | AU32: 46022 | AV32: 46022 | AW32: 46022 | AX32: 46022 | AY32: 46022 | AZ32: 46022 | BA32: 46022 | BB32: 46022 | BC32: 46022 | BD32: 46022 | BE32: 46022 | BF32: 46022 | BG32: 46022 | BH32: 46022 | BI32: 46022 | BJ32: 46022 | BK32: 46022 | BL32: 46022 | BM32: 46022 | BN32: 46022 | BO32: 46022 | BP32: 46022 | BQ32: 46022 | BR32: 46022 | BS32: 46022 | BT32: 46022 | BU32: 46022 | BV32: 46022 | BW32: 46022 | BX32: 46022 | BY32: 46022 | BZ32: 46022 | CA32: 46022 | CB32: 46022 | CC32: 46022 | CD32: 46022 | CE32: 46022 | CF32: 46022 | CG32: 46022 | CH32: 46022 | CI32: 46022 | CJ32: 46022 | CK32: 46022 | CL32: 46022 | CM32: 46022 | CN32: 46022 | CO32: 46022 | CP32: 46022 | CQ32: 46022 | CR32: 46022 | CS32: 46022 | CT32: 46022 | CU32: 46022 | CV32: 46022 | CW32: 46022 | CX32: 46022 | CY32: 46022 | CZ32: 46022 | DA32: 46022 | DB32: 46022
A33: Romania-Promotion | B33: Change Job | C33: Job Classifications | D33: Assignment Type | E33: =SUBSTITUTE(B33," ","") & "_" & SUBSTITUTE(IF(C33="N/A","",C33& "_")," ","") & SUBSTITUTE(SUBSTITUTE(D33," ",""),"/","") -> ChangeJob_JobClassifications_AssignmentType | F33: =E33&2 -> ChangeJob_JobClassifications_AssignmentType2 | H33: N/A | I33: N/A | J33: N/A | K33: N/A | L33: N/A | M33: N/A | N33: N/A | O33: N/A | P33: N/A | Q33: N/A | R33: N/A | S33: N/A | T33: N/A | U33: N/A | V33: N/A | W33: N/A | X33: N/A | Y33: N/A | Z33: N/A | AA33: N/A | AB33: N/A | AC33: N/A | AD33: N/A | AE33: N/A | AF33: N/A | AG33: N/A | AH33: N/A | AI33: N/A | AJ33: N/A | AK33: N/A | AL33: N/A | AM33: N/A | AN33: N/A | AO33: N/A | AP33: N/A | AQ33: N/A | AR33: N/A | AS33: N/A | AT33: N/A | AU33: N/A | AV33: N/A | AW33: N/A | AX33: N/A | AY33: N/A | AZ33: N/A | BA33: N/A | BB33: N/A | BC33: N/A | BD33: N/A | BE33: N/A | BF33: N/A | BG33: N/A | BH33: N/A | BI33: N/A | BJ33: N/A | BK33: N/A | BL33: N/A | BM33: N/A | BN33: N/A | BO33: N/A | BP33: N/A | BQ33: N/A | BR33: N/A | BS33: N/A | BT33: N/A | BU33: N/A | BV33: N/A | BW33: N/A | BX33: N/A | BY33: N/A | BZ33: N/A | CA33: N/A | CB33: N/A | CC33: N/A | CD33: N/A | CE33: N/A | CF33: N/A | CG33: N/A | CH33: N/A | CI33: N/A | CJ33: N/A | CK33: N/A | CL33: N/A | CM33: N/A | CN33: N/A | CO33: N/A | CP33: N/A | CQ33: N/A | CR33: N/A | CS33: N/A | CT33: N/A | CU33: N/A | CV33: N/A | CW33: N/A | CX33: N/A | CY33: N/A | CZ33: N/A | DA33: N/A | DB33: N/A
A34: Romania-Promotion | B34: Change Job | C34: Job Classifications | D34: First Day of Work | E34: =SUBSTITUTE(B34," ","") & "_" & SUBSTITUTE(IF(C34="N/A","",C34& "_")," ","") & SUBSTITUTE(SUBSTITUTE(D34," ",""),"/","") -> ChangeJob_JobClassifications_FirstDayofWork | F34: =E34&2 -> ChangeJob_JobClassifications_FirstDayofWork2 | H34: N/A | I34: N/A | J34: N/A | K34: N/A | L34: N/A | M34: N/A | N34: N/A | O34: N/A | P34: N/A | Q34: N/A | R34: N/A | S34: N/A | T34: N/A | U34: N/A | V34: N/A | W34: N/A | X34: N/A | Y34: N/A | Z34: N/A | AA34: N/A | AB34: N/A | AC34: N/A | AD34: N/A | AE34: N/A | AF34: N/A | AG34: N/A | AH34: N/A | AI34: N/A | AJ34: N/A | AK34: N/A | AL34: N/A | AM34: N/A | AN34: N/A | AO34: N/A | AP34: N/A | AQ34: N/A | AR34: N/A | AS34: N/A | AT34: N/A | AU34: N/A | AV34: N/A | AW34: N/A | AX34: N/A | AY34: N/A | AZ34: N/A | BA34: N/A | BB34: N/A | BC34: N/A | BD34: N/A | BE34: N/A | BF34: N/A | BG34: N/A | BH34: N/A | BI34: N/A | BJ34: N/A | BK34: N/A | BL34: N/A | BM34: N/A | BN34: N/A | BO34: N/A | BP34: N/A | BQ34: N/A | BR34: N/A | BS34: N/A | BT34: N/A | BU34: N/A | BV34: N/A | BW34: N/A | BX34: N/A | BY34: N/A | BZ34: N/A | CA34: N/A | CB34: N/A | CC34: N/A | CD34: N/A | CE34: N/A | CF34: N/A | CG34: N/A | CH34: N/A | CI34: N/A | CJ34: N/A | CK34: N/A | CL34: N/A | CM34: N/A | CN34: N/A | CO34: N/A | CP34: N/A | CQ34: N/A | CR34: N/A | CS34: N/A | CT34: N/A | CU34: N/A | CV34: N/A | CW34: N/A | CX34: N/A | CY34: N/A | CZ34: N/A | DA34: N/A | DB34: N/A
A35: Romania-Promotion | B35: Change Job | C35: Company | D35: Cost Centre | E35: =SUBSTITUTE(B35," ","") & "_" & SUBSTITUTE(IF(C35="N/A","",C35& "_")," ","") & SUBSTITUTE(SUBSTITUTE(D35," ",""),"/","") -> ChangeJob_Company_CostCentre | F35: =E35&2 -> ChangeJob_Company_CostCentre2 | G35: Set to N/A if not promotion | H35: N/A | I35: N/A | J35: N/A | K35: N/A | L35: N/A | M35: N/A | N35: N/A | O35: N/A | P35: N/A | Q35: N/A | R35: N/A | S35: N/A | T35: N/A | U35: N/A | V35: N/A | W35: N/A | X35: N/A | Y35: N/A | Z35: N/A | AA35: N/A | AB35: N/A | AC35: N/A | AD35: N/A | AE35: N/A | AF35: N/A | AG35: N/A | AH35: N/A | AI35: N/A | AJ35: N/A | AK35: N/A | AL35: N/A | AM35: N/A | AN35: N/A | AO35: N/A | AP35: N/A | AQ35: N/A | AR35: N/A | AS35: N/A | AT35: N/A | AU35: N/A | AV35: N/A | AW35: N/A | AX35: N/A | AY35: N/A | AZ35: N/A | BA35: N/A | BB35: N/A | BC35: N/A | BD35: N/A | BE35: N/A | BF35: N/A | BG35: N/A | BH35: N/A | BI35: N/A | BJ35: N/A | BK35: N/A | BL35: N/A | BM35: N/A | BN35: N/A | BO35: N/A | BP35: N/A | BQ35: N/A | BR35: N/A | BS35: N/A | BT35: N/A | BU35: N/A | BV35: N/A | BW35: N/A | BX35: N/A | BY35: N/A | BZ35: N/A | CA35: N/A | CB35: N/A | CC35: N/A | CD35: N/A | CE35: N/A | CF35: N/A | CG35: N/A | CH35: N/A | CI35: N/A | CJ35: N/A | CK35: N/A | CL35: N/A | CM35: N/A | CN35: N/A | CO35: N/A | CP35: N/A | CQ35: N/A | CR35: N/A | CS35: N/A | CT35: N/A | CU35: N/A | CV35: N/A | CW35: N/A | CX35: N/A | CY35: N/A | CZ35: N/A | DA35: N/A | DB35: N/A
A36: Romania-Promotion | B36: Change Job | C36: Company | D36: Department | E36: =SUBSTITUTE(B36," ","") & "_" & SUBSTITUTE(IF(C36="N/A","",C36& "_")," ","") & SUBSTITUTE(SUBSTITUTE(D36," ",""),"/","") -> ChangeJob_Company_Department | F36: =E36&2 -> ChangeJob_Company_Department2 | G36: Set to N/A if department is the same | H36: N/A | I36: N/A | J36: N/A | K36: N/A | L36: N/A | M36: N/A | N36: N/A | O36: N/A | P36: N/A | Q36: N/A | R36: N/A | S36: N/A | T36: N/A | U36: N/A | V36: N/A | W36: N/A | X36: N/A | Y36: N/A | Z36: N/A | AA36: N/A | AB36: N/A | AC36: N/A | AD36: N/A | AE36: N/A | AF36: N/A | AG36: N/A | AH36: N/A | AI36: N/A | AJ36: N/A | AK36: N/A | AL36: N/A | AM36: N/A | AN36: N/A | AO36: N/A | AP36: N/A | AQ36: N/A | AR36: N/A | AS36: N/A | AT36: N/A | AU36: N/A | AV36: N/A | AW36: N/A | AX36: N/A | AY36: N/A | AZ36: N/A | BA36: N/A | BB36: N/A | BC36: N/A | BD36: N/A | BE36: N/A | BF36: N/A | BG36: N/A | BH36: N/A | BI36: N/A | BJ36: N/A | BK36: N/A | BL36: N/A | BM36: N/A | BN36: N/A | BO36: N/A | BP36: N/A | BQ36: N/A | BR36: N/A | BS36: N/A | BT36: N/A | BU36: N/A | BV36: N/A | BW36: N/A | BX36: N/A | BY36: N/A | BZ36: N/A | CA36: N/A | CB36: N/A | CC36: N/A | CD36: N/A | CE36: N/A | CF36: N/A | CG36: N/A | CH36: N/A | CI36: N/A | CJ36: N/A | CK36: N/A | CL36: N/A | CM36: N/A | CN36: N/A | CO36: N/A | CP36: N/A | CQ36: N/A | CR36: N/A | CS36: N/A | CT36: N/A | CU36: N/A | CV36: N/A | CW36: N/A | CX36: N/A | CY36: N/A | CZ36: N/A | DA36: N/A | DB36: N/A
A37: Romania-Promotion | B37: Add Probation Period | C37: N/A | D37: Start Date | E37: =SUBSTITUTE(B37," ","") & "_" & SUBSTITUTE(IF(C37="N/A","",C37& "_")," ","") & SUBSTITUTE(SUBSTITUTE(D37," ",""),"/","") -> AddProbationPeriod_StartDate | F37: =E37&2 -> AddProbationPeriod_StartDate2 | H37: N/A | I37: N/A | J37: N/A | K37: N/A | L37: N/A | M37: N/A | N37: N/A | O37: N/A | P37: N/A | Q37: N/A | R37: N/A | S37: N/A | T37: N/A | U37: N/A | V37: N/A | W37: N/A | X37: N/A | Y37: N/A | Z37: N/A | AA37: N/A | AB37: N/A | AC37: N/A | AD37: N/A | AE37: N/A | AF37: N/A | AG37: N/A | AH37: N/A | AI37: N/A | AJ37: N/A | AK37: N/A | AL37: N/A | AM37: N/A | AN37: N/A | AO37: N/A | AP37: N/A | AQ37: N/A | AR37: N/A | AS37: N/A | AT37: N/A | AU37: N/A | AV37: N/A | AW37: N/A | AX37: N/A | AY37: N/A | AZ37: N/A | BA37: N/A | BB37: N/A | BC37: N/A | BD37: N/A | BE37: N/A | BF37: N/A | BG37: N/A | BH37: N/A | BI37: N/A | BJ37: N/A | BK37: N/A | BL37: N/A | BM37: N/A | BN37: N/A | BO37: N/A | BP37: N/A | BQ37: N/A | BR37: N/A | BS37: N/A | BT37: N/A | BU37: N/A | BV37: N/A | BW37: N/A | BX37: N/A | BY37: N/A | BZ37: N/A | CA37: N/A | CB37: N/A | CC37: N/A | CD37: N/A | CE37: N/A | CF37: N/A | CG37: N/A | CH37: N/A | CI37: N/A | CJ37: N/A | CK37: N/A | CL37: N/A | CM37: N/A | CN37: N/A | CO37: N/A | CP37: N/A | CQ37: N/A | CR37: N/A | CS37: N/A | CT37: N/A | CU37: N/A | CV37: N/A | CW37: N/A | CX37: N/A | CY37: N/A | CZ37: N/A | DA37: N/A | DB37: N/A
A38: Romania-Promotion | B38: Add Probation Period | C38: N/A | D38: End Date | E38: =SUBSTITUTE(B38," ","") & "_" & SUBSTITUTE(IF(C38="N/A","",C38& "_")," ","") & SUBSTITUTE(SUBSTITUTE(D38," ",""),"/","") -> AddProbationPeriod_EndDate | F38: =E38&2 -> AddProbationPeriod_EndDate2 | G38: For promotion must have value | H38: N/A | I38: N/A | J38: N/A | K38: N/A | L38: N/A | M38: N/A | N38: N/A | O38: N/A | P38: N/A | Q38: N/A | R38: N/A | S38: N/A | T38: N/A | U38: N/A | V38: N/A | W38: N/A | X38: N/A | Y38: N/A | Z38: N/A | AA38: N/A | AB38: N/A | AC38: N/A | AD38: N/A | AE38: N/A | AF38: N/A | AG38: N/A | AH38: N/A | AI38: N/A | AJ38: N/A | AK38: N/A | AL38: N/A | AM38: N/A | AN38: N/A | AO38: N/A | AP38: N/A | AQ38: N/A | AR38: N/A | AS38: N/A | AT38: N/A | AU38: N/A | AV38: N/A | AW38: N/A | AX38: N/A | AY38: N/A | AZ38: N/A | BA38: N/A | BB38: N/A | BC38: N/A | BD38: N/A | BE38: N/A | BF38: N/A | BG38: N/A | BH38: N/A | BI38: N/A | BJ38: N/A | BK38: N/A | BL38: N/A | BM38: N/A | BN38: N/A | BO38: N/A | BP38: N/A | BQ38: N/A | BR38: N/A | BS38: N/A | BT38: N/A | BU38: N/A | BV38: N/A | BW38: N/A | BX38: N/A | BY38: N/A | BZ38: N/A | CA38: N/A | CB38: N/A | CC38: N/A | CD38: N/A | CE38: N/A | CF38: N/A | CG38: N/A | CH38: N/A | CI38: N/A | CJ38: N/A | CK38: N/A | CL38: N/A | CM38: N/A | CN38: N/A | CO38: N/A | CP38: N/A | CQ38: N/A | CR38: N/A | CS38: N/A | CT38: N/A | CU38: N/A | CV38: N/A | CW38: N/A | CX38: N/A | CY38: N/A | CZ38: N/A | DA38: N/A | DB38: N/A
B39: Propose Compensation Change | C39: N/A | D39: Salary | E39: =SUBSTITUTE(B39," ","") & "_" & SUBSTITUTE(IF(C39="N/A","",C39& "_")," ","") & SUBSTITUTE(SUBSTITUTE(D39," ",""),"/","") -> ProposeCompensationChange_Salary | F39: =E39&2 -> ProposeCompensationChange_Salary2 | G39: Portugal Supervisor needs amount = €1234 | H39: N/A | I39: N/A | J39: N/A | K39: N/A | L39: N/A | M39: N/A | N39: N/A | O39: N/A | P39: N/A | Q39: N/A | R39: N/A | S39: N/A | T39: N/A | U39: N/A | V39: N/A | W39: N/A | X39: N/A | Y39: N/A | Z39: N/A | AA39: N/A | AB39: N/A | AC39: N/A | AD39: N/A | AE39: N/A | AF39: N/A | AG39: N/A | AH39: N/A | AI39: N/A | AJ39: N/A | AK39: N/A | AL39: N/A | AM39: N/A | AN39: N/A | AO39: N/A | AP39: N/A | AQ39: N/A | AR39: N/A | AS39: N/A | AT39: N/A | AU39: N/A | AV39: N/A | AW39: N/A | AX39: N/A | AY39: N/A | AZ39: N/A | BA39: N/A | BB39: N/A | BC39: N/A | BD39: N/A | BE39: N/A | BF39: N/A | BG39: N/A | BH39: N/A | BI39: N/A | BJ39: N/A | BK39: N/A | BL39: N/A | BM39: N/A | BN39: N/A | BO39: N/A | BP39: N/A | BQ39: N/A | BR39: N/A | BS39: N/A | BT39: N/A | BU39: N/A | BV39: N/A | BW39: N/A | BX39: N/A | BY39: N/A | BZ39: N/A | CA39: N/A | CB39: N/A | CC39: N/A | CD39: N/A | CE39: N/A | CF39: N/A | CG39: N/A | CH39: N/A | CI39: N/A | CJ39: N/A | CK39: N/A | CL39: N/A | CM39: N/A | CN39: N/A | CO39: N/A | CP39: N/A | CQ39: N/A | CR39: N/A | CS39: N/A | CT39: N/A | CU39: N/A | CV39: N/A | CW39: N/A | CX39: N/A | CY39: N/A | CZ39: N/A | DA39: N/A | DB39: N/A
B40: ProposeCompensationHire | C40: N/A | D40: Grade Profile | E40: =SUBSTITUTE(B40," ","") & "_" & SUBSTITUTE(IF(C40="N/A","",C40& "_")," ","") & SUBSTITUTE(SUBSTITUTE(D40," ",""),"/","") -> ProposeCompensationHire_GradeProfile | F40: =E40&2 -> ProposeCompensationHire_GradeProfile2 | G40: for Demotion | H40: N/A | I40: N/A | J40: N/A | K40: N/A | L40: N/A | M40: N/A | N40: N/A | O40: N/A | P40: N/A | Q40: N/A | R40: N/A | S40: N/A | T40: N/A | U40: N/A | V40: N/A | W40: N/A | X40: N/A | Y40: N/A | Z40: N/A | AA40: N/A | AB40: N/A | AC40: N/A | AD40: N/A | AE40: N/A | AF40: N/A | AG40: N/A | AH40: N/A | AI40: N/A | AJ40: N/A | AK40: N/A | AL40: N/A | AM40: N/A | AN40: N/A | AO40: N/A | AP40: N/A | AQ40: N/A | AR40: N/A | AS40: N/A | AT40: N/A | AU40: N/A | AV40: N/A | AW40: N/A | AX40: N/A | AY40: N/A | AZ40: N/A | BA40: N/A | BB40: N/A | BC40: N/A | BD40: N/A | BE40: N/A | BF40: N/A | BG40: N/A | BH40: N/A | BI40: N/A | BJ40: N/A | BK40: N/A | BL40: N/A | BM40: N/A | BN40: N/A | BO40: N/A | BP40: N/A | BQ40: N/A | BR40: N/A | BS40: N/A | BT40: N/A | BU40: N/A | BV40: N/A | BW40: N/A | BX40: N/A | BY40: N/A | BZ40: N/A | CA40: N/A | CB40: N/A | CC40: N/A | CD40: N/A | CE40: N/A | CF40: N/A | CG40: N/A | CH40: N/A | CI40: N/A | CJ40: N/A | CK40: N/A | CL40: N/A | CM40: N/A | CN40: N/A | CO40: N/A | CP40: N/A | CQ40: N/A | CR40: N/A | CS40: N/A | CT40: N/A | CU40: N/A | CV40: N/A | CW40: N/A | CX40: N/A | CY40: N/A | CZ40: N/A | DA40: N/A | DB40: N/A
B41: ProposeCompensationHire | C41: N/A | D41: Step | E41: =SUBSTITUTE(B41," ","") & "_" & SUBSTITUTE(IF(C41="N/A","",C41& "_")," ","") & SUBSTITUTE(SUBSTITUTE(D41," ",""),"/","") -> ProposeCompensationHire_Step | F41: =E41&2 -> ProposeCompensationHire_Step2 | G41: for Demotion | H41: N/A | I41: N/A | J41: N/A | K41: N/A | L41: N/A | M41: N/A | N41: N/A | O41: N/A | P41: N/A | Q41: N/A | R41: N/A | S41: N/A | T41: N/A | U41: N/A | V41: N/A | W41: N/A | X41: N/A | Y41: N/A | Z41: N/A | AA41: N/A | AB41: N/A | AC41: N/A | AD41: N/A | AE41: N/A | AF41: N/A | AG41: N/A | AH41: N/A | AI41: N/A | AJ41: N/A | AK41: N/A | AL41: N/A | AM41: N/A | AN41: N/A | AO41: N/A | AP41: N/A | AQ41: N/A | AR41: N/A | AS41: N/A | AT41: N/A | AU41: N/A | AV41: N/A | AW41: N/A | AX41: N/A | AY41: N/A | AZ41: N/A | BA41: N/A | BB41: N/A | BC41: N/A | BD41: N/A | BE41: N/A | BF41: N/A | BG41: N/A | BH41: N/A | BI41: N/A | BJ41: N/A | BK41: N/A | BL41: N/A | BM41: N/A | BN41: N/A | BO41: N/A | BP41: N/A | BQ41: N/A | BR41: N/A | BS41: N/A | BT41: N/A | BU41: N/A | BV41: N/A | BW41: N/A | BX41: N/A | BY41: N/A | BZ41: N/A | CA41: N/A | CB41: N/A | CC41: N/A | CD41: N/A | CE41: N/A | CF41: N/A | CG41: N/A | CH41: N/A | CI41: N/A | CJ41: N/A | CK41: N/A | CL41: N/A | CM41: N/A | CN41: N/A | CO41: N/A | CP41: N/A | CQ41: N/A | CR41: N/A | CS41: N/A | CT41: N/A | CU41: N/A | CV41: N/A | CW41: N/A | CX41: N/A | CY41: N/A | CZ41: N/A | DA41: N/A | DB41: N/A
B42: Change Job | C42: Assign Collective Agreement | D42: Collective Agreement | E42: =SUBSTITUTE(B42," ","") & "_" & SUBSTITUTE(IF(C42="N/A","",C42& "_")," ","") & SUBSTITUTE(SUBSTITUTE(D42," ",""),"/","") -> ChangeJob_AssignCollectiveAgreement_CollectiveAgreement | F42: =E42&2 -> ChangeJob_AssignCollectiveAgreement_CollectiveAgreement2 | H42: N/A | I42: N/A | J42: N/A | K42: N/A | L42: N/A | M42: N/A | N42: N/A | O42: N/A | P42: N/A | Q42: N/A | R42: N/A | S42: N/A | T42: N/A | U42: N/A | V42: N/A | W42: N/A | X42: N/A | Y42: N/A | Z42: N/A | AA42: N/A | AB42: N/A | AC42: N/A | AD42: N/A | AE42: N/A | AF42: N/A | AG42: N/A | AH42: N/A | AI42: N/A | AJ42: N/A | AK42: N/A | AL42: N/A | AM42: N/A | AN42: N/A | AO42: N/A | AP42: N/A | AQ42: N/A | AR42: N/A | AS42: N/A | AT42: N/A | AU42: N/A | AV42: N/A | AW42: N/A | AX42: N/A | AY42: N/A | AZ42: N/A | BA42: N/A | BB42: N/A | BC42: N/A | BD42: N/A | BE42: N/A | BF42: N/A | BG42: N/A | BH42: N/A | BI42: N/A | BJ42: N/A | BK42: N/A | BL42: N/A | BM42: N/A | BN42: N/A | BO42: N/A | BP42: N/A | BQ42: N/A | BR42: N/A | BS42: N/A | BT42: N/A | BU42: N/A | BV42: N/A | BW42: N/A | BX42: N/A | BY42: N/A | BZ42: N/A | CA42: N/A | CB42: N/A | CC42: N/A | CD42: N/A | CE42: N/A | CF42: N/A | CG42: N/A | CH42: N/A | CI42: N/A | CJ42: N/A | CK42: N/A | CL42: N/A | CM42: N/A | CN42: N/A | CO42: N/A | CP42: N/A | CQ42: N/A | CR42: N/A | CS42: N/A | CT42: N/A | CU42: N/A | CV42: N/A | CW42: N/A | CX42: N/A | CY42: N/A | CZ42: N/A | DA42: N/A | DB42: N/A
B43: Change Job | C43: Assign Collective Agreement | D43: Professional Category | E43: =SUBSTITUTE(B43," ","") & "_" & SUBSTITUTE(IF(C43="N/A","",C43& "_")," ","") & SUBSTITUTE(SUBSTITUTE(D43," ",""),"/","") -> ChangeJob_AssignCollectiveAgreement_ProfessionalCategory | F43: =E43&2 -> ChangeJob_AssignCollectiveAgreement_ProfessionalCategory2 | H43: N/A | I43: N/A | J43: N/A | K43: N/A | L43: N/A | M43: N/A | N43: N/A | O43: N/A | P43: N/A | Q43: N/A | R43: N/A | S43: N/A | T43: N/A | U43: N/A | V43: N/A | W43: N/A | X43: N/A | Y43: N/A | Z43: N/A | AA43: N/A | AB43: N/A | AC43: N/A | AD43: N/A | AE43: N/A | AF43: N/A | AG43: N/A | AH43: N/A | AI43: N/A | AJ43: N/A | AK43: N/A | AL43: N/A | AM43: N/A | AN43: N/A | AO43: N/A | AP43: N/A | AQ43: N/A | AR43: N/A | AS43: N/A | AT43: N/A | AU43: N/A | AV43: N/A | AW43: N/A | AX43: N/A | AY43: N/A | AZ43: N/A | BA43: N/A | BB43: N/A | BC43: N/A | BD43: N/A | BE43: N/A | BF43: N/A | BG43: N/A | BH43: N/A | BI43: N/A | BJ43: N/A | BK43: N/A | BL43: N/A | BM43: N/A | BN43: N/A | BO43: N/A | BP43: N/A | BQ43: N/A | BR43: N/A | BS43: N/A | BT43: N/A | BU43: N/A | BV43: N/A | BW43: N/A | BX43: N/A | BY43: N/A | BZ43: N/A | CA43: N/A | CB43: N/A | CC43: N/A | CD43: N/A | CE43: N/A | CF43: N/A | CG43: N/A | CH43: N/A | CI43: N/A | CJ43: N/A | CK43: N/A | CL43: N/A | CM43: N/A | CN43: N/A | CO43: N/A | CP43: N/A | CQ43: N/A | CR43: N/A | CS43: N/A | CT43: N/A | CU43: N/A | CV43: N/A | CW43: N/A | CX43: N/A | CY43: N/A | CZ43: N/A | DA43: N/A | DB43: N/A
B44: Change Job | C44: Assign Collective Agreement | D44: Level | E44: =SUBSTITUTE(B44," ","") & "_" & SUBSTITUTE(IF(C44="N/A","",C44& "_")," ","") & SUBSTITUTE(SUBSTITUTE(D44," ",""),"/","") -> ChangeJob_AssignCollectiveAgreement_Level | F44: =E44&2 -> ChangeJob_AssignCollectiveAgreement_Level2 | H44: N/A | I44: N/A | J44: N/A | K44: N/A | L44: N/A | M44: N/A | N44: N/A | O44: N/A | P44: N/A | Q44: N/A | R44: N/A | S44: N/A | T44: N/A | U44: N/A | V44: N/A | W44: N/A | X44: N/A | Y44: N/A | Z44: N/A | AA44: N/A | AB44: N/A | AC44: N/A | AD44: N/A | AE44: N/A | AF44: N/A | AG44: N/A | AH44: N/A | AI44: N/A | AJ44: N/A | AK44: N/A | AL44: N/A | AM44: N/A | AN44: N/A | AO44: N/A | AP44: N/A | AQ44: N/A | AR44: N/A | AS44: N/A | AT44: N/A | AU44: N/A | AV44: N/A | AW44: N/A | AX44: N/A | AY44: N/A | AZ44: N/A | BA44: N/A | BB44: N/A | BC44: N/A | BD44: N/A | BE44: N/A | BF44: N/A | BG44: N/A | BH44: N/A | BI44: N/A | BJ44: N/A | BK44: N/A | BL44: N/A | BM44: N/A | BN44: N/A | BO44: N/A | BP44: N/A | BQ44: N/A | BR44: N/A | BS44: N/A | BT44: N/A | BU44: N/A | BV44: N/A | BW44: N/A | BX44: N/A | BY44: N/A | BZ44: N/A | CA44: N/A | CB44: N/A | CC44: N/A | CD44: N/A | CE44: N/A | CF44: N/A | CG44: N/A | CH44: N/A | CI44: N/A | CJ44: N/A | CK44: N/A | CL44: N/A | CM44: N/A | CN44: N/A | CO44: N/A | CP44: N/A | CQ44: N/A | CR44: N/A | CS44: N/A | CT44: N/A | CU44: N/A | CV44: N/A | CW44: N/A | CX44: N/A | CY44: N/A | CZ44: N/A | DA44: N/A | DB44: N/A
B45: ContractAddendumInfo | C45: N/A | D45: TerminateAddendumEffectiveDate | E45: =SUBSTITUTE(B45," ","") & "_" & SUBSTITUTE(IF(C45="N/A","",C45& "_")," ","") & SUBSTITUTE(SUBSTITUTE(D45," ",""),"/","") -> ContractAddendumInfo_TerminateAddendumEffectiveDate | F45: =E45&2 -> ContractAddendumInfo_TerminateAddendumEffectiveDate2 | H45: N/A | I45: N/A | J45: N/A | K45: N/A | L45: N/A | M45: N/A | N45: N/A | O45: N/A | P45: N/A | Q45: N/A | R45: N/A | S45: N/A | T45: N/A | U45: N/A | V45: N/A | W45: N/A | X45: N/A | Y45: N/A | Z45: N/A | AA45: N/A | AB45: N/A | AC45: N/A | AD45: N/A | AE45: N/A | AF45: N/A | AG45: N/A | AH45: N/A | AI45: N/A | AJ45: N/A | AK45: N/A | AL45: N/A | AM45: N/A | AN45: N/A | AO45: N/A | AP45: N/A | AQ45: N/A | AR45: N/A | AS45: N/A | AT45: N/A | AU45: N/A | AV45: N/A | AW45: N/A | AX45: N/A | AY45: N/A | AZ45: N/A | BA45: N/A | BB45: N/A | BC45: N/A | BD45: N/A | BE45: N/A | BF45: N/A | BG45: N/A | BH45: N/A | BI45: N/A | BJ45: N/A | BK45: N/A | BL45: N/A | BM45: N/A | BN45: N/A | BO45: N/A | BP45: N/A | BQ45: N/A | BR45: N/A | BS45: N/A | BT45: N/A | BU45: N/A | BV45: N/A | BW45: N/A | BX45: N/A | BY45: N/A | BZ45: N/A | CA45: N/A | CB45: N/A | CC45: N/A | CD45: N/A | CE45: N/A | CF45: N/A | CG45: N/A | CH45: N/A | CI45: N/A | CJ45: N/A | CK45: N/A | CL45: N/A | CM45: N/A | CN45: N/A | CO45: N/A | CP45: N/A | CQ45: N/A | CR45: N/A | CS45: N/A | CT45: N/A | CU45: N/A | CV45: N/A | CW45: N/A | CX45: N/A | CY45: N/A | CZ45: N/A | DA45: N/A | DB45: N/A
B46: ContractAddendumInfo | C46: N/A | D46: AddendumEndDate | E46: =SUBSTITUTE(B46," ","") & "_" & SUBSTITUTE(IF(C46="N/A","",C46& "_")," ","") & SUBSTITUTE(SUBSTITUTE(D46," ",""),"/","") -> ContractAddendumInfo_AddendumEndDate | F46: =E46&2 -> ContractAddendumInfo_AddendumEndDate2 | H46: N/A | I46: N/A | J46: N/A | K46: N/A | L46: N/A | M46: N/A | N46: N/A | O46: N/A | P46: N/A | Q46: N/A | R46: N/A | S46: N/A | T46: N/A | U46: N/A | V46: N/A | W46: N/A | X46: N/A | Y46: N/A | Z46: N/A | AA46: N/A | AB46: N/A | AC46: N/A | AD46: N/A | AE46: N/A | AF46: N/A | AG46: N/A | AH46: N/A | AI46: N/A | AJ46: N/A | AK46: N/A | AL46: N/A | AM46: N/A | AN46: N/A | AO46: N/A | AP46: N/A | AQ46: N/A | AR46: N/A | AS46: N/A | AT46: N/A | AU46: N/A | AV46: N/A | AW46: N/A | AX46: N/A | AY46: N/A | AZ46: N/A | BA46: N/A | BB46: N/A | BC46: N/A | BD46: N/A | BE46: N/A | BF46: N/A | BG46: N/A | BH46: N/A | BI46: N/A | BJ46: N/A | BK46: N/A | BL46: N/A | BM46: N/A | BN46: N/A | BO46: N/A | BP46: N/A | BQ46: N/A | BR46: N/A | BS46: N/A | BT46: N/A | BU46: N/A | BV46: N/A | BW46: N/A | BX46: N/A | BY46: N/A | BZ46: N/A | CA46: N/A | CB46: N/A | CC46: N/A | CD46: N/A | CE46: N/A | CF46: N/A | CG46: N/A | CH46: N/A | CI46: N/A | CJ46: N/A | CK46: N/A | CL46: N/A | CM46: N/A | CN46: N/A | CO46: N/A | CP46: N/A | CQ46: N/A | CR46: N/A | CS46: N/A | CT46: N/A | CU46: N/A | CV46: N/A | CW46: N/A | CX46: N/A | CY46: N/A | CZ46: N/A | DA46: N/A | DB46: N/A
B47: ContractAddendumInfo | C47: N/A | D47: AddendumCreationDate | E47: =SUBSTITUTE(B47," ","") & "_" & SUBSTITUTE(IF(C47="N/A","",C47& "_")," ","") & SUBSTITUTE(SUBSTITUTE(D47," ",""),"/","") -> ContractAddendumInfo_AddendumCreationDate | F47: =E47&2 -> ContractAddendumInfo_AddendumCreationDate2 | H47: N/A | I47: N/A | J47: N/A | K47: N/A | L47: N/A | M47: N/A | N47: N/A | O47: N/A | P47: N/A | Q47: N/A | R47: N/A | S47: N/A | T47: N/A | U47: N/A | V47: N/A | W47: N/A | X47: N/A | Y47: N/A | Z47: N/A | AA47: N/A | AB47: N/A | AC47: N/A | AD47: N/A | AE47: N/A | AF47: N/A | AG47: N/A | AH47: N/A | AI47: N/A | AJ47: N/A | AK47: N/A | AL47: N/A | AM47: N/A | AN47: N/A | AO47: N/A | AP47: N/A | AQ47: N/A | AR47: N/A | AS47: N/A | AT47: N/A | AU47: N/A | AV47: N/A | AW47: N/A | AX47: N/A | AY47: N/A | AZ47: N/A | BA47: N/A | BB47: N/A | BC47: N/A | BD47: N/A | BE47: N/A | BF47: N/A | BG47: N/A | BH47: N/A | BI47: N/A | BJ47: N/A | BK47: N/A | BL47: N/A | BM47: N/A | BN47: N/A | BO47: N/A | BP47: N/A | BQ47: N/A | BR47: N/A | BS47: N/A | BT47: N/A | BU47: N/A | BV47: N/A | BW47: N/A | BX47: N/A | BY47: N/A | BZ47: N/A | CA47: N/A | CB47: N/A | CC47: N/A | CD47: N/A | CE47: N/A | CF47: N/A | CG47: N/A | CH47: N/A | CI47: N/A | CJ47: N/A | CK47: N/A | CL47: N/A | CM47: N/A | CN47: N/A | CO47: N/A | CP47: N/A | CQ47: N/A | CR47: N/A | CS47: N/A | CT47: N/A | CU47: N/A | CV47: N/A | CW47: N/A | CX47: N/A | CY47: N/A | CZ47: N/A | DA47: N/A | DB47: N/A

Sheet Sheet1
A1: 10286580 | B1: 10286658
A2: 10286586 | B2: 10286659
A3: 10286587 | B3: 10286660
A4: 10286588 | B4: 10286661
A5: 10286589

Sheet Defects
B2: Batch 1 - Summary | E2: Batch 2 - Summary | H2: Batch 3 - Summary | K2: All E2E Cycle 1 - Summary
B3: Description | C3: Total | E3: Description | F3: Total | H3: Description | I3: Total | K3: Description | L3: Total No. | M3: %
B4: Passed | C4: 35 | E4: Passed | F4: 141 | H4: Passed | I4: 0 | K4: Passed | L4: =C4+F4+I4 -> 176 | M4: =L4/L8*100 -> 72.131148
B5: Failed | C5: 17 | E5: Failed | F5: 27 | H5: Failed | I5: 24 | K5: Failed | L5: =C5+F5+I5 -> 68 | M5: =L5/L8*100 -> 27.868852
B6: Not Run | C6: 0 | E6: Not Run | F6: 0 | H6: Not Run | I6: 0 | K6: Not Run | L6: =C6+F6+I6 -> 0 | M6: =L6/L8*100 -> 0
B7: Executed | C7: 52 | E7: Executed | F7: 168 | H7: Executed | I7: 24 | K7: Executed | L7: =C7+F7+I7 -> 244 | M7: =L7/L8*100 -> 100
B8: Total | C8: 52 | E8: Total | F8: 168 | H8: Total | I8: 24 | K8: Total | L8: =C8+F8+I8 -> 244 | M8: =M4+M5+M6 -> 100
B10: Batch 1 - Defects | E10: Batch 2 - Defects | H10: Batch 3 - Defects | K10: All E2E Cycle 1 - Defects
B11: Failed Tests Description | C11: Total | E11: Failed Tests Description | F11: Total | H11: Failed Tests Description | I11: Total | K11: Failed Tests Description | L11: Total No. | M11: %
B12: P&C Salary Assistant/Supervisor Salary Configuration missing | C12: 12 | E12: Grade Profile not populated causing salary to remain blank | F12: 24 | H12: Data issue - Rerun scheduled | I12: 24 | K12: Personal Information Change Approval Email missing after 2nd and final proxy into HR Manager | L12: 44 | M12: =L12/L17*100 -> 35.2
B13: Automation issue with Maiden Name - Gary to discuss with Shane/Andre | C13: 5 | E13: GC - Under Investigation | F13: 3 | H13: Total | I13: 24 | K13: Open button not available to assign paygroup for payroll. Approval required by David Bradley... | L13: 20 | M13: =L13/L17*100 -> 16
B14: Total | C14: =C12+C13 -> 17 | E14: Total | F14: 27 | K14: Grade Profile not populated causing salary to remain blank | L14: 34 | M14: =L14/L17*100 -> 27.2
K15: Data issue - Rerun scheduled | L15: 24 | M15: =L15/L17*100 -> 19.2
K16: GC - Under Investigation | L16: 3 | M16: =L16/L17*100 -> 2.4
K17: Total | L17: =SUM(L12:L16) -> 125 | M17: =SUM(M12:M16) -> 100

Sheet Automation_Lookups
A1: Process2 | B1: ExecutionFlag2 | C1: Country2 | D1: ChangeJob_Start_Reason2 | E1: ChangeJob_Start_NewManager2 | F1: ChangeJob_Start_NewTeam2 | G1: ChangeJob_Start_NewLocation2 | H1: ChangeJob_Start_NextPayPeriod2 | I1: ChangeJob_LocationDetails_WorkShift2 | Q1: SupervisoryOrganisation_SupervisoryOrganisation2 | R1: LegalNameInformation_Country2 | S1: ContactInformation_Phone_CountryPhoneCode2 | T1: ContactInformation_Phone_PhoneDevice2 | U1: ContactInformation_Phone_Type2 | V1: ContactInformation_Address_Type2 | W1: ContactInformation_Email_Type2 | X1: JobDetails_HireDate2 | Y1: JobDetails_Reason2 | Z1: JobDetails_Position2 | AA1: JobDetails_EmployeeType2 | AB1: JobDetails_JobProfile2 | AC1: JobDetails_TimeType2 | AD1: JobDetails_Location2 | AE1: JobDetails_AdditionalInformation_WorkShift2 | AF1: JobDetails_AdditionalInformation_EndEmploymentDate2 | AG1: ChangeOrganizationAssignments_DepartmentSection2 | AH1: AssignPayGroup_ProposedPayGroup2 | AI1: Proxy_ProxyNumber2 | AJ1: Proxy_OnBehalfOf2 | AK1: MaintainEmployeeContract_Reason2 | AL1: MaintainEmployeeContract_Status2 | AM1: MaintainEmployeeContract_ContractType2 | AN1: MaintainEmployeeContract_ContractEndDate2 | AO1: ProposeCompensationHire_GradeProfile2 | AP1: ProposeCompensationHire_Step2 | AQ1: EditPassportsandVisas_Country2 | AR1: EditPassportsandVisas_PassportIDType2 | AS1: EditPassportsandVisas_IdentificationNo2 | AT1: EditPassportsandVisas_IssuedDate2 | AU1: EditPassportsandVisas_ExpirationDate2 | AV1: ChangeMyPersonalInformation_MaritalStatus2 | AW1: ChangeMyEmergencyContacts_Relationship2 | AX1: ChangeMyEmergencyContacts_PhoneDevice2 | AY1: ChangeMyGovernmentIDs_NationalIDs_NationalIDType2 | AZ1: PaymentElectionOption_AccountType2 | BA1: SkillsAndExperience_AddEducation_School2 | BB1: AddProbationPeriod_ProbationEndDate2 | BC1: EditAdditionalData_PayrollTaxDeduction | BD1: HealthCareProvider_MealVoucher2 | BE1: School1 | BF1: School2 | BG1: ContactInformation_Address_Province2 | BH1: ChangeMyGovernmentIDs_NationalIDs_NationalIDType12 | BI1: ChangeMyGovernmentIDs_NationalIDs_NationalIDType22 | BJ1: EditAdditionalData_EstadolIRPF2 | BK1: EditAdditionalData_MinusvaliaRH2
A2: Promotion_To_Manager | B2: Yes | C2: Slovakia | D2: Promotion | H2: TRUE | I2: 1 Day | Q2: 362 Recruitment (Carolina De La Barrera Crespo (375)) | R2: Czechia | S2: Czechia (+420) | T2: Mobile | U2: Home | V2: Home | W2: Home | X2: =IF(MONTH(TODAY())<10,"0"&MONTH(TODAY())&"/",MONTH(TODAY())&"/") & IF(DAY(TODAY())<10,"0"&DAY(TODAY())&"/",DAY(TODAY())&"/") & YEAR(TODAY()) -> 01/23/2025 | Y2: New Hire | Z2: Assistant Manager-2 | AA2: Fixed Term | AB2: DPP/DPC | AC2: Full time | AD2: 362 Algeciras | AE2: 1 Day | AF2: =IF(MONTH(TODAY())<10,"0"&MONTH(TODAY())&"/",MONTH(TODAY())&"/") & IF(DAY(TODAY())<10,"0"&DAY(TODAY())&"/",DAY(TODAY())&"/") & YEAR(TODAY()) -> 01/23/2025 | AG2: Accessories | AH2: Please select a Spanish Pay Group | AI2: 10223439 | AJ2: Iwona Chrostowska (10223439) | AK2: for the purposes of performing any work of casual or seasonal nature | AL2: 1st Fixed Term Contract | AM2: Employment Agreement | AN2: =IF(MONTH(TODAY())<10,"0"&MONTH(TODAY())&"/",MONTH(TODAY())&"/") & IF(DAY(TODAY())<10,"0"&DAY(TODAY())&"/",DAY(TODAY())&"/") & YEAR(TODAY()) -> 01/23/2025 | AO2: Defaulted | AP2: Defaulted | AV2: Single | AW2: Father | AX2: Mobile/Cell | AY2: Social Security Number (NSS) | AZ2: Savings | BA2: N/A | BB2: =IF(MONTH(TODAY()+100)<10,"0"&MONTH(TODAY()+100)&"/",MONTH(TODAY()+100)&"/") & IF(DAY(TODAY()+100)<10,"0"&DAY(TODAY()+100)&"/",DAY(TODAY()+100)&"/") & YEAR(TODAY()+100) -> 05/03/2025 | BC2: Yes | BD2: Yes | BE2: Střední bez maturity či výučního listu | BF2: stredni bez maturity ci vyucniho listu | BG2: Madrid | BH2: Social Security Number (NSS) | BI2: ID Card (DNI) Number | BJ2: Soltero/a, viudo/a, divorciado/a o separado/a legalmente con hijos solteros menores de 18 años o incapacitados judicialmente que conviven exclusivamente con Vd., sin convivir también con el otro progenitor Soltero/a, viudo/a, divorciado/a o separado/a legalmente con hijos solteros menores de 18 años o incapacitados judicialmente que conviven exclusivamente con Vd., sin convivir también con el otro progenitor | BK2: Del 33% hasta el 65%
A3: PartTime_To_FullTime | B3: No | C3: Slovenia | D3: Change of Hours, Employee Type, Time Type, End Employment Date | H3: FALSE | I3: 2 Days | Q3: 895 Store Management (Male Teststmanager (10224969)) | R3: Czechia | S3: Czechia (+420) | T3: Landline | U3: Work | V3: Work | W3: Work | X3: =IF(MONTH(TODAY()-10)<10,"0"&MONTH(TODAY()-10)&"/",MONTH(TODAY()-10))&"/" & IF(DAY(TODAY()-10)<10,"0"&DAY(TODAY()-10)&"/",DAY(TODAY()-10)&"/") & YEAR(TODAY()-10) -> 01//13/2025 | Z3: Assistant Manager-3 | AA3: Intern | AB3: Retail Assistant | AC3: Part time | AE3: 2 Days | AF3: =IF(MONTH(TODAY()+100)<10,"0"&MONTH(TODAY()+100)&"/",MONTH(TODAY()+100)&"/") & IF(DAY(TODAY()+100)<10,"0"&DAY(TODAY()+100)&"/",DAY(TODAY()+100)&"/") & YEAR(TODAY()+100) -> 05/03/2025 | AH3: ES Monthly - 15 payments | AI3: 10225553 | AJ3: Kocour Mikeš (10225553) | AK3: for the purposes of performing work during the term of office | AL3: 2nd Fixed Term Contract | AM3: Agreement to perform work | AN3: =IF(MONTH(TODAY()+100)<10,"0"&MONTH(TODAY()+100)&"/",MONTH(TODAY()+100)&"/") & IF(DAY(TODAY()+100)<10,"0"&DAY(TODAY()+100)&"/",DAY(TODAY()+100)&"/") & YEAR(TODAY()+100) -> 05/03/2025 | AV3: Married | AW3: Mother | AX3: Telephone - Landline | AY3: ID Card (DNI) Number | AZ3: Checking | BA3: Vseobecne stredni s maturitou | BB3: =IF(MONTH(TODAY()+1000)<10,"0"&MONTH(TODAY()+1000)&"/",MONTH(TODAY()+1000)&"/") & IF(DAY(TODAY()+1000)<10,"0"&DAY(TODAY()+1000)&"/",DAY(TODAY()+1000)&"/") & YEAR(TODAY()+1000) -> 10/20/2027 | BC3: No | BD3: No | BE3: Střední odborné vzdělání s výučním listem | BF3: stredni odborne vzdelani s vyucnim listem
A4: FullTime_To_PartTime | C4: USA | D4: Step Back | I4: 3 Days | R4: Poland | S4: Poland (+48) | X4: =IF(MONTH(TODAY()+10)<10,"0"&MONTH(TODAY()+10)&"/",MONTH(TODAY()+10)&"/") & IF(DAY(TODAY()+10)<10,"0"&DAY(TODAY()+10)&"/",DAY(TODAY()+10)&"/") & YEAR(TODAY()+10) -> 02/02/2025 | Z4: Test Store Manager-2 | AA4: Permanent | AB4: Department Manager | AE4: 3 Days | AF4: =IF(MONTH(TODAY()+1000)<10,"0"&MONTH(TODAY()+1000)&"/",MONTH(TODAY()+1000)&"/") & IF(DAY(TODAY()+1000)<10,"0"&DAY(TODAY()+1000)&"/",DAY(TODAY()+1000)&"/") & YEAR(TODAY()+1000) -> 10/20/2027 | AK4: for the purposes of substituting an employee during his/her excused absence at work | AL4: 3rd Fixed Term Contract | AM4: Agreement to complete a job | AN4: =IF(MONTH(TODAY()+1000)<10,"0"&MONTH(TODAY()+1000)&"/",MONTH(TODAY()+1000)&"/") & IF(DAY(TODAY()+1000)<10,"0"&DAY(TODAY()+1000)&"/",DAY(TODAY()+1000)&"/") & YEAR(TODAY()+1000) -> 10/20/2027 | AV4: Not Disclosed | AW4: Spouse | BB4: N/A | BE4: Všeobecné střední s maturitou | BF4: vseobecne stredni s maturitou
A5: Demotion | C5: UK | I5: 4 Days | R5: Poland | S5: Poland (+48) | Z5: N/A | AA5: Students | AB5: Senior Department Manager | AE5: 4 Days | AF5: N/A | AK5: No reason necessary | AL5: Active | AN5: N/A | AW5: Partner | BE5: Vysokoškolské Bc. | BF5: Vysokoskolske Bc
A6: Promotion | C6: Czechia | I6: 5 Days | AB6: Supervisor | AE6: 5 Days | AL6: Inactive | BE6: Vysokoškolské MUDr., JUDr., Mgr., MgA., Ing. | BF6: vysokoskolske MUDR., JUDr., Mgr., MgA., Ing.
A7: Permanent | C7: Italy | AB7: P&C Supervisor | BE7: Vysokoškolské PhDr, PhD, JUDr, MUDr | BF7: vysokoskolske PhDr, PhD, JUDr, MUDr
C8: Portugal | AB8: P&C Assistant | BE8: vyšší odborné DiS | BF8: vyssi odborne DiS
C9: France | AB9: Trainee Manager | BE9: Základní | BF9: Zakladni
C10: Poland | AB10: Assistant Manager
C11: Romania | AB11: P&C Manager
C12: Ireland | AB12: Store Manager
C13: Belgium | AB13: Visual Merchandiser Manager
C14: Netherlands | AB14: Visual Merchandising Supervisor
C15: Spain | AB15: Visual Merchandising Assistant
Y21: Rehire | AI21: 8701839 | AJ21: Lisanne Kluinhaar (8701839) | AK21: Defined contract end date (Determined) | BD21: Netherlands Retail Assistant
Q22: 701 Recruitment (Lisanne Kluinhaar (8701839)) | R22: Netherlands | S22: Netherlands (+31) | Y22: Seasonal | AK22: Undefined contract end date (Undetermined) | AM22: Part-time( PT ) | BD22: Netherlands Retail Assistant Cash Office | BE22: Retail Assistant (18)
AK23: Intern | AM23: Full-time( FT. ) | BE23: Retail Assistant (19)
Q24: Retail - Central & Eastern Europe (Stephen Regan (9910010) (Inherited) | R24: Poland | S24: Poland (+48) | BE24: Retail Assistant (20)
Q25: Retail Poland Area: Central Poland (Stephen Regan (9910010) (Inherited)) | R25: Poland | S25: Poland (+48) | BE25: Retail Assistant (21)
BE26: Retail Assistant (22)
BE27: Retail Assistant (23+)
BE28: Retail Assistant (Under 18)

Sheet RC. No
A1: D.O.B | B1: 35139 | C1: 33054 | D1: 31390 | F1: r col b | G1: r col c | H1: r col d
B2: 9603150007 | C2: 9006300006 | D2: 8512090004 | F2: =B2/11 -> 873013637 | G2: =C2/11 -> 818754546 | H2: =D2/11 -> 773826364
B3: =B2+11 -> 9603150018 | C3: =C2+11 -> 9006300017 | D3: =D2+11 -> 8512090015 | F3: =B3/11 -> 873013638 | G3: =C3/11 -> 818754547 | H3: =D3/11 -> 773826365
B4: =B3+11 -> 9603150029 | C4: =C3+11 -> 9006300028 | D4: =D3+11 -> 8512090026 | F4: =B4/11 -> 873013639 | G4: =C4/11 -> 818754548 | H4: =D4/11 -> 773826366
B5: =B4+11 -> 9603150040 | C5: =C4+11 -> 9006300039 | D5: =D4+11 -> 8512090037 | F5: =B5/11 -> 873013640 | G5: =C5/11 -> 818754549 | H5: =D5/11 -> 773826367
B6: =B5+11 -> 9603150051 | C6: =C5+11 -> 9006300050 | D6: =D5+11 -> 8512090048 | F6: =B6/11 -> 873013641 | G6: =C6/11 -> 818754550 | H6: =D6/11 -> 773826368
B7: =B6+11 -> 9603150062 | C7: =C6+11 -> 9006300061 | D7: =D6+11 -> 8512090059 | F7: =B7/11 -> 873013642 | G7: =C7/11 -> 818754551 | H7: =D7/11 -> 773826369
B8: =B7+11 -> 9603150073 | C8: =C7+11 -> 9006300072 | D8: =D7+11 -> 8512090070 | F8: =B8/11 -> 873013643 | G8: =C8/11 -> 818754552 | H8: =D8/11 -> 773826370
B9: =B8+11 -> 9603150084 | C9: =C8+11 -> 9006300083 | D9: =D8+11 -> 8512090081 | F9: =B9/11 -> 873013644 | G9: =C9/11 -> 818754553 | H9: =D9/11 -> 773826371
B10: =B9+11 -> 9603150095 | C10: =C9+11 -> 9006300094 | D10: =D9+11 -> 8512090092 | F10: =B10/11 -> 873013645 | G10: =C10/11 -> 818754554 | H10: =D10/11 -> 773826372
B11: =B10+11 -> 9603150106 | C11: =C10+11 -> 9006300105 | D11: =D10+11 -> 8512090103 | F11: =B11/11 -> 873013646 | G11: =C11/11 -> 818754555 | H11: =D11/11 -> 773826373
B12: =B11+11 -> 9603150117 | C12: =C11+11 -> 9006300116 | D12: =D11+11 -> 8512090114 | F12: =B12/11 -> 873013647 | G12: =C12/11 -> 818754556 | H12: =D12/11 -> 773826374
B13: =B12+11 -> 9603150128 | C13: =C12+11 -> 9006300127 | D13: =D12+11 -> 8512090125 | F13: =B13/11 -> 873013648 | G13: =C13/11 -> 818754557 | H13: =D13/11 -> 773826375
B14: =B13+11 -> 9603150139 | C14: =C13+11 -> 9006300138 | D14: =D13+11 -> 8512090136 | F14: =B14/11 -> 873013649 | G14: =C14/11 -> 818754558 | H14: =D14/11 -> 773826376
... B28: =B27+11 -> 9603150293 | C28: =C27+11 -> 9006300292 | D28: =D27+11 -> 8512090290 | F28: =B28/11 -> 873013663 | G28: =C28/11 -> 818754572 | H28: =D28/11 -> 773826390
B29: =B28+11 -> 9603150304
B30: =B29+11 -> 9603150315
B31: =B30+11 -> 9603150326
B32: =B31+11 -> 9603150337
B33: =B32+11 -> 9603150348
B34: =B33+11 -> 9603150359
B35: =B34+11 -> 9603150370
B36: =B35+11 -> 9603150381
B37: =B36+11 -> 9603150392
B38: =B37+11 -> 9603150403
B39: =B38+11 -> 9603150414
B40: =B39+11 -> 9603150425
... B75: =B74+11 -> 9603150810
B76: =B75+11 -> 9603150821 | X76: New RC Numbers
B77: =B76+11 -> 9603150832 | X77: 9202101337
B78: =B77+11 -> 9603150843 | X78: =SUM(X77)+11 -> 9202101348
B79: =B78+11 -> 9603150854 | X79: =SUM(X78)+11 -> 9202101359
B80: =B79+11 -> 9603150865 | X80: =SUM(X79)+11 -> 9202101370
B81: =B80+11 -> 9603150876 | X81: =SUM(X80)+11 -> 9202101381
B82: =B81+11 -> 9603150887 | X82: =SUM(X81)+11 -> 9202101392
B83: =B82+11 -> 9603150898 | X83: =SUM(X82)+11 -> 9202101403
B84: =B83+11 -> 9603150909 | X84: =SUM(X83)+11 -> 9202101414
B85: =B84+11 -> 9603150920 | X85: =SUM(X84)+11 -> 9202101425
B86: =B85+11 -> 9603150931 | D86: 9603170269 | X86: =SUM(X85)+11 -> 9202101436
D87: =D86+11 -> 9603170280 | F87: 9603170280 | H87: 9603170280 | I87: 9603170291 | J87: 9603170302 | K87: 9603170313 | L87: 9603170324 | M87: 9603170335 | N87: 9603170346 | O87: 9603170357 | P87: 9603170368 | Q87: 9603170379 | R87: 9603170390 | S87: 9603170401 | T87: 9603170412 | X87: =SUM(X86)+11 -> 9202101447
D88: =D87+11 -> 9603170291 | F88: 9603170291 | X88: =SUM(X87)+11 -> 9202101458
D89: =D88+11 -> 9603170302 | F89: 9603170302 | H89: 9603170412 | I89: =H89+11 -> 9603170423 | J89: =I89+11 -> 9603170434 | K89: =J89+11 -> 9603170445 | L89: =K89+11 -> 9603170456 | M89: =L89+11 -> 9603170467 | N89: =M89+11 -> 9603170478 | O89: =N89+11 -> 9603170489 | P89: =O89+11 -> 9603170500 | ... T89: =S89+11 -> 9603170544 | X89: =SUM(X88)+11 -> 9202101469
D90: =D89+11 -> 9603170313 | F90: 9603170313 | X90: =SUM(X89)+11 -> 9202101480
D91: =D90+11 -> 9603170324 | F91: 9603170324 | X91: =SUM(X90)+11 -> 9202101491
D92: =D91+11 -> 9603170335 | F92: 9603170335 | X92: =SUM(X91)+11 -> 9202101502
D93: =D92+11 -> 9603170346 | F93: 9603170346 | X93: =SUM(X92)+11 -> 9202101513
D94: =D93+11 -> 9603170357 | F94: 9603170357 | X94: =SUM(X93)+11 -> 9202101524
D95: =D94+11 -> 9603170368 | F95: 9603170368 | X95: =SUM(X94)+11 -> 9202101535
D96: =D95+11 -> 9603170379 | F96: 9603170379 | X96: =SUM(X95)+11 -> 9202101546
D97: =D96+11 -> 9603170390 | F97: 9603170390 | X97: =SUM(X96)+11 -> 9202101557
D98: =D97+11 -> 9603170401 | F98: 9603170401 | X98: =SUM(X97)+11 -> 9202101568
D99: =D98+11 -> 9603170412 | F99: 9603170412 | X99: =SUM(X98)+11 -> 9202101579
X100: =SUM(X99)+11 -> 9202101590
X101: =SUM(X100)+11 -> 9202101601
X102: =SUM(X101)+11 -> 9202101612
X103: =SUM(X102)+11 -> 9202101623
X104: =SUM(X103)+11 -> 9202101634
X105: =SUM(X104)+11 -> 9202101645
X106: =SUM(X105)+11 -> 9202101656
X107: =SUM(X106)+11 -> 9202101667
X108: =SUM(X107)+11 -> 9202101678
X109: =SUM(X108)+11 -> 9202101689
X110: =SUM(X109)+11 -> 9202101700
X111: =SUM(X110)+11 -> 9202101711
... X133: =SUM(X132)+11 -> 9202101953

Sheet Code_11122019_1000
B1: Variable Row | C1: Variable Row Combined | D1: Variable Value | E1: Variable Value Combined | F1: Row Number Declaration --------------------------------- intRowProcess = comExcelWorksheet.Range("Process").Row | G1: Value Declaration ------------------------ strProcess = comExcelWorksheet.Cells(intRowProcess, intColTestColumn).Value | H1: Getters
A2: =Test_Data!E3 -> Process | B2: ="intRow" & A2 & ", " -> intRowProcess, | C2: =B2 -> intRowProcess, | D2: ="str" & A2 & ", " -> strProcess, | E2: =D2 -> strProcess, | F2: ="intRow" & A2 & " = comExcelWorksheet.Range(""" & A2 & """).Row" -> intRowProcess = comExcelWorksheet.Range("Process").Row | G2: ="str" & A2 & " = comExcelWorksheet.Cells(intRow" & A2 & ", intColTestColumn).Value" -> strProcess = comExcelWorksheet.Cells(intRowProcess, intColTestColumn).Value | H2: ="Public Property Get get" & A2 & "() : get" & A2 & " = str" & A2 & " : End Property" -> Public Property Get getProcess() : getProcess = strProcess : End Property
A3: =Test_Data!E4 -> ExecutionFlag | B3: ="intRow" & A3 & ", " -> intRowExecutionFlag, | C3: =B3 -> intRowExecutionFlag, | D3: ="str" & A3 & ", " -> strExecutionFlag, | E3: =E2 & " " & D3 -> strProcess, strExecutionFlag, | F3: ="intRow" & A3 & " = comExcelWorksheet.Range(""" & A3 & """).Row" -> intRowExecutionFlag = comExcelWorksheet.Range("ExecutionFlag").Row | G3: ="str" & A3 & " = comExcelWorksheet.Cells(intRow" & A3 & ", intColTestColumn).Value" -> strExecutionFlag = comExcelWorksheet.Cells(intRowExecutionFlag, intColTestColumn).Value | H3: ="Public Property Get get" & A3 & "() : get" & A3 & " = str" & A3 & " : End Property" -> Public Property Get getExecutionFlag() : getExecutionFlag = strExecutionFlag : End Property
A4: =Test_Data!E5 -> Country | B4: ="intRow" & A4 & ", " -> intRowCountry, | C4: =B4 -> intRowCountry, | D4: ="str" & A4 & ", " -> strCountry, | E4: =E3 & " " & D4 -> strProcess, strExecutionFlag, strCountry, | F4: ="intRow" & A4 & " = comExcelWorksheet.Range(""" & A4 & """).Row" -> intRowCountry = comExcelWorksheet.Range("Country").Row | G4: ="str" & A4 & " = comExcelWorksheet.Cells(intRow" & A4 & ", intColTestColumn).Value" -> strCountry = comExcelWorksheet.Cells(intRowCountry, intColTestColumn).Value | H4: ="Public Property Get get" & A4 & "() : get" & A4 & " = str" & A4 & " : End Property" -> Public Property Get getCountry() : getCountry = strCountry : End Property
A5: =Test_Data!E6 -> LastRunTimeandStatus | B5: ="intRow" & A5 & ", " -> intRowLastRunTimeandStatus, | C5: =B5 -> intRowLastRunTimeandStatus, | D5: ="str" & A5 & ", " -> strLastRunTimeandStatus, | E5: =E4 & " " & D5 -> strProcess, strExecutionFlag, strCountry, strLastRunTimeandStatus, | F5: ="intRow" & A5 & " = comExcelWorksheet.Range(""" & A5 & """).Row" -> intRowLastRunTimeandStatus = comExcelWorksheet.Range("LastRunTimeandStatus").Row | G5: ="str" & A5 & " = comExcelWorksheet.Cells(intRow" & A5 & ", intColTestColumn).Value" -> strLastRunTimeandStatus = comExcelWorksheet.Cells(intRowLastRunTimeandStatus, intColTestColumn).Value | H5: ="Public Property Get get" & A5 & "() : get" & A5 & " = str" & A5 & " : End Property" -> Public Property Get getLastRunTimeandStatus() : getLastRunTimeandStatus = strLastRunTimeandStatus : End Property
A6: =Test_Data!E7 -> LastRunErrorMessage | B6: ="intRow" & A6 & ", " -> intRowLastRunErrorMessage, | C6: =B6 -> intRowLastRunErrorMessage, | D6: ="str" & A6 & ", " -> strLastRunErrorMessage, | E6: =E5 & " " & D6 -> strProcess, strExecutionFlag, strCountry, strLastRunTimeandStatus, strLastRunErrorMessage, | F6: ="intRow" & A6 & " = comExcelWorksheet.Range(""" & A6 & """).Row" -> intRowLastRunErrorMessage = comExcelWorksheet.Range("LastRunErrorMessage").Row | G6: ="str" & A6 & " = comExcelWorksheet.Cells(intRow" & A6 & ", intColTestColumn).Value" -> strLastRunErrorMessage = comExcelWorksheet.Cells(intRowLastRunErrorMessage, intColTestColumn).Value | H6: ="Public Property Get get" & A6 & "() : get" & A6 & " = str" & A6 & " : End Property" -> Public Property Get getLastRunErrorMessage() : getLastRunErrorMessage = strLastRunErrorMessage : End Property
A7: =Test_Data!E13 -> Login_Username | B7: ="intRow" & A7 & ", " -> intRowLogin_Username, | C7: =B7 -> intRowLogin_Username, | D7: ="str" & A7 & ", " -> strLogin_Username, | E7: =E6 & " " & D7 -> strProcess, strExecutionFlag, strCountry, strLastRunTimeandStatus, strLastRunErrorMessage, strLogin_Username, | F7: ="intRow" & A7 & " = comExcelWorksheet.Range(""" & A7 & """).Row" -> intRowLogin_Username = comExcelWorksheet.Range("Login_Username").Row | G7: ="str" & A7 & " = comExcelWorksheet.Cells(intRow" & A7 & ", intColTestColumn).Value" -> strLogin_Username = comExcelWorksheet.Cells(intRowLogin_Username, intColTestColumn).Value | H7: ="Public Property Get get" & A7 & "() : get" & A7 & " = str" & A7 & " : End Property" -> Public Property Get getLogin_Username() : getLogin_Username = strLogin_Username : End Property
A8: =Test_Data!E14 -> Login_Password | B8: ="intRow" & A8 & ", " -> intRowLogin_Password, | C8: =B8 -> intRowLogin_Password, | D8: ="str" & A8 & ", " -> strLogin_Password, | E8: =E7 & " " & D8 -> strProcess, strExecutionFlag, strCountry, strLastRunTimeandStatus, strLastRunErrorMessage, strLogin_Username, strLogin_Password, | F8: ="intRow" & A8 & " = comExcelWorksheet.Range(""" & A8 & """).Row" -> intRowLogin_Password = comExcelWorksheet.Range("Login_Password").Row | G8: ="str" & A8 & " = comExcelWorksheet.Cells(intRow" & A8 & ", intColTestColumn).Value" -> strLogin_Password = comExcelWorksheet.Cells(intRowLogin_Password, intColTestColumn).Value | H8: ="Public Property Get get" & A8 & "() : get" & A8 & " = str" & A8 & " : End Property" -> Public Property Get getLogin_Password() : getLogin_Password = strLogin_Password : End Property
A9: =Test_Data!#REF! -> #REF! | B9: ="intRow" & A9 & ", " -> #REF! | C9: =B9 -> #REF! | D9: ="str" & A9 & ", " -> #REF! | E9: =E8 & " " & D9 -> #REF! | F9: ="intRow" & A9 & " = comExcelWorksheet.Range(""" & A9 & """).Row" -> #REF! | G9: ="str" & A9 & " = comExcelWorksheet.Cells(intRow" & A9 & ", intColTestColumn).Value" -> #REF! | H9: ="Public Property Get get" & A9 & "() : get" & A9 & " = str" & A9 & " : End Property" -> #REF!
A10: =Test_Data!#REF! -> #REF! | B10: ="intRow" & A10 & ", " -> #REF! | C10: =B10 -> #REF! | D10: ="str" & A10 & ", " -> #REF! | E10: =E9 & " " & D10 -> #REF! | F10: ="intRow" & A10 & " = comExcelWorksheet.Range(""" & A10 & """).Row" -> #REF! | G10: ="str" & A10 & " = comExcelWorksheet.Cells(intRow" & A10 & ", intColTestColumn).Value" -> #REF! | H10: ="Public Property Get get" & A10 & "() : get" & A10 & " = str" & A10 & " : End Property" -> #REF!
A11: =Test_Data!E15 -> Proxy_EmployeeID | B11: ="intRow" & A11 & ", " -> intRowProxy_EmployeeID, | C11: =B11 -> intRowProxy_EmployeeID, | D11: ="str" & A11 & ", " -> strProxy_EmployeeID, | E11: =E10 & " " & D11 -> #REF! | F11: ="intRow" & A11 & " = comExcelWorksheet.Range(""" & A11 & """).Row" -> intRowProxy_EmployeeID = comExcelWorksheet.Range("Proxy_EmployeeID").Row | G11: ="str" & A11 & " = comExcelWorksheet.Cells(intRow" & A11 & ", intColTestColumn).Value" -> strProxy_EmployeeID = comExcelWorksheet.Cells(intRowProxy_EmployeeID, intColTestColumn).Value | H11: ="Public Property Get get" & A11 & "() : get" & A11 & " = str" & A11 & " : End Property" -> Public Property Get getProxy_EmployeeID() : getProxy_EmployeeID = strProxy_EmployeeID : End Property
A12: =Test_Data!#REF! -> #REF! | B12: ="intRow" & A12 & ", " -> #REF! | C12: =B12 -> #REF! | D12: ="str" & A12 & ", " -> #REF! | E12: =E11 & " " & D12 -> #REF! | F12: ="intRow" & A12 & " = comExcelWorksheet.Range(""" & A12 & """).Row" -> #REF! | G12: ="str" & A12 & " = comExcelWorksheet.Cells(intRow" & A12 & ", intColTestColumn).Value" -> #REF! | H12: ="Public Property Get get" & A12 & "() : get" & A12 & " = str" & A12 & " : End Property" -> #REF!
A13: =Test_Data!E16 -> ChangeJob_Start_EffectiveDate | B13: ="intRow" & A13 & ", " -> intRowChangeJob_Start_EffectiveDate, | C13: =B13 -> intRowChangeJob_Start_EffectiveDate, | D13: ="str" & A13 & ", " -> strChangeJob_Start_EffectiveDate, | E13: =E12 & " " & D13 -> #REF! | F13: ="intRow" & A13 & " = comExcelWorksheet.Range(""" & A13 & """).Row" -> intRowChangeJob_Start_EffectiveDate = comExcelWorksheet.Range("ChangeJob_Start_EffectiveDate").Row | G13: ="str" & A13 & " = comExcelWorksheet.Cells(intRow" & A13 & ", intColTestColumn).Value" -> strChangeJob_Start_EffectiveDate = comExcelWorksheet.Cells(intRowChangeJob_Start_EffectiveDate, intColTestColumn).Value | H13: ="Public Property Get get" & A13 & "() : get" & A13 & " = str" & A13 & " : End Property" -> Public Property Get getChangeJob_Start_EffectiveDate() : getChangeJob_Start_EffectiveDate = strChangeJob_Start_EffectiveDate : End Property
A14: =Test_Data!E17 -> ChangeJob_Start_Reason | B14: ="intRow" & A14 & ", " -> intRowChangeJob_Start_Reason, | C14: =B14 -> intRowChangeJob_Start_Reason, | D14: ="str" & A14 & ", " -> strChangeJob_Start_Reason, | E14: =E13 & " " & D14 -> #REF! | F14: ="intRow" & A14 & " = comExcelWorksheet.Range(""" & A14 & """).Row" -> intRowChangeJob_Start_Reason = comExcelWorksheet.Range("ChangeJob_Start_Reason").Row | G14: ="str" & A14 & " = comExcelWorksheet.Cells(intRow" & A14 & ", intColTestColumn).Value" -> strChangeJob_Start_Reason = comExcelWorksheet.Cells(intRowChangeJob_Start_Reason, intColTestColumn).Value | H14: ="Public Property Get get" & A14 & "() : get" & A14 & " = str" & A14 & " : End Property" -> Public Property Get getChangeJob_Start_Reason() : getChangeJob_Start_Reason = strChangeJob_Start_Reason : End Property
A15: =Test_Data!E18 -> ChangeJob_Start_NewManager | B15: ="intRow" & A15 & ", " -> intRowChangeJob_Start_NewManager, | C15: =B15 -> intRowChangeJob_Start_NewManager, | D15: ="str" & A15 & ", " -> strChangeJob_Start_NewManager, | E15: =E14 & " " & D15 -> #REF! | F15: ="intRow" & A15 & " = comExcelWorksheet.Range(""" & A15 & """).Row" -> intRowChangeJob_Start_NewManager = comExcelWorksheet.Range("ChangeJob_Start_NewManager").Row | G15: ="str" & A15 & " = comExcelWorksheet.Cells(intRow" & A15 & ", intColTestColumn).Value" -> strChangeJob_Start_NewManager = comExcelWorksheet.Cells(intRowChangeJob_Start_NewManager, intColTestColumn).Value | H15: ="Public Property Get get" & A15 & "() : get" & A15 & " = str" & A15 & " : End Property" -> Public Property Get getChangeJob_Start_NewManager() : getChangeJob_Start_NewManager = strChangeJob_Start_NewManager : End Property
A16: =Test_Data!E19 -> ChangeJob_Start_NewTeam | B16: ="intRow" & A16 & ", " -> intRowChangeJob_Start_NewTeam, | C16: =B16 -> intRowChangeJob_Start_NewTeam, | D16: ="str" & A16 & ", " -> strChangeJob_Start_NewTeam, | E16: =E15 & " " & D16 -> #REF! | F16: ="intRow" & A16 & " = comExcelWorksheet.Range(""" & A16 & """).Row" -> intRowChangeJob_Start_NewTeam = comExcelWorksheet.Range("ChangeJob_Start_NewTeam").Row | G16: ="str" & A16 & " = comExcelWorksheet.Cells(intRow" & A16 & ", intColTestColumn).Value" -> strChangeJob_Start_NewTeam = comExcelWorksheet.Cells(intRowChangeJob_Start_NewTeam, intColTestColumn).Value | H16: ="Public Property Get get" & A16 & "() : get" & A16 & " = str" & A16 & " : End Property" -> Public Property Get getChangeJob_Start_NewTeam() : getChangeJob_Start_NewTeam = strChangeJob_Start_NewTeam : End Property
A17: =Test_Data!E20 -> ChangeJob_Start_NewLocation | B17: ="intRow" & A17 & ", " -> intRowChangeJob_Start_NewLocation, | C17: =B17 -> intRowChangeJob_Start_NewLocation, | D17: ="str" & A17 & ", " -> strChangeJob_Start_NewLocation, | E17: =E16 & " " & D17 -> #REF! | F17: ="intRow" & A17 & " = comExcelWorksheet.Range(""" & A17 & """).Row" -> intRowChangeJob_Start_NewLocation = comExcelWorksheet.Range("ChangeJob_Start_NewLocation").Row | G17: ="str" & A17 & " = comExcelWorksheet.Cells(intRow" & A17 & ", intColTestColumn).Value" -> strChangeJob_Start_NewLocation = comExcelWorksheet.Cells(intRowChangeJob_Start_NewLocation, intColTestColumn).Value | H17: ="Public Property Get get" & A17 & "() : get" & A17 & " = str" & A17 & " : End Property" -> Public Property Get getChangeJob_Start_NewLocation() : getChangeJob_Start_NewLocation = strChangeJob_Start_NewLocation : End Property
A18: =Test_Data!E21 -> ChangeJob_Start_NextPayPeriod | B18: ="intRow" & A18 & ", " -> intRowChangeJob_Start_NextPayPeriod, | C18: =B18 -> intRowChangeJob_Start_NextPayPeriod, | D18: ="str" & A18 & ", " -> strChangeJob_Start_NextPayPeriod, | E18: =E17 & " " & D18 -> #REF! | F18: ="intRow" & A18 & " = comExcelWorksheet.Range(""" & A18 & """).Row" -> intRowChangeJob_Start_NextPayPeriod = comExcelWorksheet.Range("ChangeJob_Start_NextPayPeriod").Row | G18: ="str" & A18 & " = comExcelWorksheet.Cells(intRow" & A18 & ", intColTestColumn).Value" -> strChangeJob_Start_NextPayPeriod = comExcelWorksheet.Cells(intRowChangeJob_Start_NextPayPeriod, intColTestColumn).Value | H18: ="Public Property Get get" & A18 & "() : get" & A18 & " = str" & A18 & " : End Property" -> Public Property Get getChangeJob_Start_NextPayPeriod() : getChangeJob_Start_NextPayPeriod = strChangeJob_Start_NextPayPeriod : End Property
A19: =Test_Data!E22 -> ChangeJob_JobProfile_JobProfile | B19: ="intRow" & A19 & ", " -> intRowChangeJob_JobProfile_JobProfile, | C19: =B19 -> intRowChangeJob_JobProfile_JobProfile, | D19: ="str" & A19 & ", " -> strChangeJob_JobProfile_JobProfile, | E19: =E18 & " " & D19 -> #REF! | F19: ="intRow" & A19 & " = comExcelWorksheet.Range(""" & A19 & """).Row" -> intRowChangeJob_JobProfile_JobProfile = comExcelWorksheet.Range("ChangeJob_JobProfile_JobProfile").Row | G19: ="str" & A19 & " = comExcelWorksheet.Cells(intRow" & A19 & ", intColTestColumn).Value" -> strChangeJob_JobProfile_JobProfile = comExcelWorksheet.Cells(intRowChangeJob_JobProfile_JobProfile, intColTestColumn).Value | H19: ="Public Property Get get" & A19 & "() : get" & A19 & " = str" & A19 & " : End Property" -> Public Property Get getChangeJob_JobProfile_JobProfile() : getChangeJob_JobProfile_JobProfile = strChangeJob_JobProfile_JobProfile : End Property
A20: =Test_Data!E23 -> ChangeJob_JobProfile_JobTitle | B20: ="intRow" & A20 & ", " -> intRowChangeJob_JobProfile_JobTitle, | C20: =B20 -> intRowChangeJob_JobProfile_JobTitle, | D20: ="str" & A20 & ", " -> strChangeJob_JobProfile_JobTitle, | E20: =E19 & " " & D20 -> #REF! | F20: ="intRow" & A20 & " = comExcelWorksheet.Range(""" & A20 & """).Row" -> intRowChangeJob_JobProfile_JobTitle = comExcelWorksheet.Range("ChangeJob_JobProfile_JobTitle").Row | G20: ="str" & A20 & " = comExcelWorksheet.Cells(intRow" & A20 & ", intColTestColumn).Value" -> strChangeJob_JobProfile_JobTitle = comExcelWorksheet.Cells(intRowChangeJob_JobProfile_JobTitle, intColTestColumn).Value | H20: ="Public Property Get get" & A20 & "() : get" & A20 & " = str" & A20 & " : End Property" -> Public Property Get getChangeJob_JobProfile_JobTitle() : getChangeJob_JobProfile_JobTitle = strChangeJob_JobProfile_JobTitle : End Property
A21: =Test_Data!E24 -> ChangeJob_LocationDetails_Location | B21: ="intRow" & A21 & ", " -> intRowChangeJob_LocationDetails_Location, | C21: =B21 -> intRowChangeJob_LocationDetails_Location, | D21: ="str" & A21 & ", " -> strChangeJob_LocationDetails_Location, | E21: =E20 & " " & D21 -> #REF! | F21: ="intRow" & A21 & " = comExcelWorksheet.Range(""" & A21 & """).Row" -> intRowChangeJob_LocationDetails_Location = comExcelWorksheet.Range("ChangeJob_LocationDetails_Location").Row | G21: ="str" & A21 & " = comExcelWorksheet.Cells(intRow" & A21 & ", intColTestColumn).Value" -> strChangeJob_LocationDetails_Location = comExcelWorksheet.Cells(intRowChangeJob_LocationDetails_Location, intColTestColumn).Value | H21: ="Public Property Get get" & A21 & "() : get" & A21 & " = str" & A21 & " : End Property" -> Public Property Get getChangeJob_LocationDetails_Location() : getChangeJob_LocationDetails_Location = strChangeJob_LocationDetails_Location : End Property
A22: =Test_Data!E25 -> ChangeJob_LocationDetails_ScheduledWeeklyHours | B22: ="intRow" & A22 & ", " -> intRowChangeJob_LocationDetails_ScheduledWeeklyHours, | C22: =B22 -> intRowChangeJob_LocationDetails_ScheduledWeeklyHours, | D22: ="str" & A22 & ", " -> strChangeJob_LocationDetails_ScheduledWeeklyHours, | E22: =E21 & " " & D22 -> #REF! | F22: ="intRow" & A22 & " = comExcelWorksheet.Range(""" & A22 & """).Row" -> intRowChangeJob_LocationDetails_ScheduledWeeklyHours = comExcelWorksheet.Range("ChangeJob_LocationDetails_ScheduledWeeklyHours").Row | G22: ="str" & A22 & " = comExcelWorksheet.Cells(intRow" & A22 & ", intColTestColumn).Value" -> strChangeJob_LocationDetails_ScheduledWeeklyHours = comExcelWorksheet.Cells(intRowChangeJob_LocationDetails_ScheduledWeeklyHours, intColTestColumn).Value | H22: ="Public Property Get get" & A22 & "() : get" & A22 & " = str" & A22 & " : End Property" -> Public Property Get getChangeJob_LocationDetails_ScheduledWeeklyHours() : getChangeJob_LocationDetails_ScheduledWeeklyHours = strChangeJob_LocationDetails_ScheduledWeeklyHours : End Property
A23: =Test_Data!E26 -> ChangeJob_LocationDetails_WorkShift | B23: ="intRow" & A23 & ", " -> intRowChangeJob_LocationDetails_WorkShift, | C23: =B23 -> intRowChangeJob_LocationDetails_WorkShift, | D23: ="str" & A23 & ", " -> strChangeJob_LocationDetails_WorkShift, | E23: =E22 & " " & D23 -> #REF! | F23: ="intRow" & A23 & " = comExcelWorksheet.Range(""" & A23 & """).Row" -> intRowChangeJob_LocationDetails_WorkShift = comExcelWorksheet.Range("ChangeJob_LocationDetails_WorkShift").Row | G23: ="str" & A23 & " = comExcelWorksheet.Cells(intRow" & A23 & ", intColTestColumn).Value" -> strChangeJob_LocationDetails_WorkShift = comExcelWorksheet.Cells(intRowChangeJob_LocationDetails_WorkShift, intColTestColumn).Value | H23: ="Public Property Get get" & A23 & "() : get" & A23 & " = str" & A23 & " : End Property" -> Public Property Get getChangeJob_LocationDetails_WorkShift() : getChangeJob_LocationDetails_WorkShift = strChangeJob_LocationDetails_WorkShift : End Property
A24: =Test_Data!E27 -> ChangeJob_JobClassifications_AdditionalJobClassifications | B24: ="intRow" & A24 & ", " -> intRowChangeJob_JobClassifications_AdditionalJobClassifications, | C24: =B24 -> intRowChangeJob_JobClassifications_AdditionalJobClassifications, | D24: ="str" & A24 & ", " -> strChangeJob_JobClassifications_AdditionalJobClassifications, | E24: =E23 & " " & D24 -> #REF! | F24: ="intRow" & A24 & " = comExcelWorksheet.Range(""" & A24 & """).Row" -> intRowChangeJob_JobClassifications_AdditionalJobClassifications = comExcelWorksheet.Range("ChangeJob_JobClassifications_AdditionalJobClassifications").Row | G24: ="str" & A24 & " = comExcelWorksheet.Cells(intRow" & A24 & ", intColTestColumn).Value" -> strChangeJob_JobClassifications_AdditionalJobClassifications = comExcelWorksheet.Cells(intRowChangeJob_JobClassifications_AdditionalJobClassifications, intColTestColumn).Value | H24: ="Public Property Get get" & A24 & "() : get" & A24 & " = str" & A24 & " : End Property" -> Public Property Get getChangeJob_JobClassifications_AdditionalJobClassifications() : getChangeJob_JobClassifications_AdditionalJobClassifications = strChangeJob_JobClassifications_AdditionalJobClassifications : End Property
... A31: =Test_Data!E34 -> ChangeJob_JobClassifications_FirstDayofWork | B31: ="intRow" & A31 & ", " -> intRowChangeJob_JobClassifications_FirstDayofWork, | C31: =B31 -> intRowChangeJob_JobClassifications_FirstDayofWork, | D31: ="str" & A31 & ", " -> strChangeJob_JobClassifications_FirstDayofWork, | E31: =E30 & " " & D31 -> #REF! | F31: ="intRow" & A31 & " = comExcelWorksheet.Range(""" & A31 & """).Row" -> intRowChangeJob_JobClassifications_FirstDayofWork = comExcelWorksheet.Range("ChangeJob_JobClassifications_FirstDayofWork").Row | G31: ="str" & A31 & " = comExcelWorksheet.Cells(intRow" & A31 & ", intColTestColumn).Value" -> strChangeJob_JobClassifications_FirstDayofWork = comExcelWorksheet.Cells(intRowChangeJob_JobClassifications_FirstDayofWork, intColTestColumn).Value | H31: ="Public Property Get get" & A31 & "() : get" & A31 & " = str" & A31 & " : End Property" -> Public Property Get getChangeJob_JobClassifications_FirstDayofWork() : getChangeJob_JobClassifications_FirstDayofWork = strChangeJob_JobClassifications_FirstDayofWork : End Property
A32: =Test_Data!E40 -> ProposeCompensationHire_GradeProfile | B32: ="intRow" & A32 & ", " -> intRowProposeCompensationHire_GradeProfile, | C32: =B32 -> intRowProposeCompensationHire_GradeProfile, | D32: ="str" & A32 & ", " -> strProposeCompensationHire_GradeProfile, | E32: =E31 & " " & D32 -> #REF! | F32: ="intRow" & A32 & " = comExcelWorksheet.Range(""" & A32 & """).Row" -> intRowProposeCompensationHire_GradeProfile = comExcelWorksheet.Range("ProposeCompensationHire_GradeProfile").Row | G32: ="str" & A32 & " = comExcelWorksheet.Cells(intRow" & A32 & ", intColTestColumn).Value" -> strProposeCompensationHire_GradeProfile = comExcelWorksheet.Cells(intRowProposeCompensationHire_GradeProfile, intColTestColumn).Value | H32: ="Public Property Get get" & A32 & "() : get" & A32 & " = str" & A32 & " : End Property" -> Public Property Get getProposeCompensationHire_GradeProfile() : getProposeCompensationHire_GradeProfile = strProposeCompensationHire_GradeProfile : End Property
A33: =Test_Data!E41 -> ProposeCompensationHire_Step | B33: ="intRow" & A33 & ", " -> intRowProposeCompensationHire_Step, | C33: =B33 -> intRowProposeCompensationHire_Step, | D33: ="str" & A33 & ", " -> strProposeCompensationHire_Step, | E33: =E32 & " " & D33 -> #REF! | F33: ="intRow" & A33 & " = comExcelWorksheet.Range(""" & A33 & """).Row" -> intRowProposeCompensationHire_Step = comExcelWorksheet.Range("ProposeCompensationHire_Step").Row | G33: ="str" & A33 & " = comExcelWorksheet.Cells(intRow" & A33 & ", intColTestColumn).Value" -> strProposeCompensationHire_Step = comExcelWorksheet.Cells(intRowProposeCompensationHire_Step, intColTestColumn).Value | H33: ="Public Property Get get" & A33 & "() : get" & A33 & " = str" & A33 & " : End Property" -> Public Property Get getProposeCompensationHire_Step() : getProposeCompensationHire_Step = strProposeCompensationHire_Step : End Property

Sheet Names
A1: Abigail | B1: Abraham | C1: NUL8H1001 | D1: 44444441001
A2: Adam | B2: Allan | C2: NUL8H1002 | D2: 44444441002
A3: Adrian | B3: Alsop | C3: NUL8H1003 | D3: 44444441003
A4: Alan | B4: Anderson | C4: NUL8H1004 | D4: 44444441004
A5: Alexander | B5: Arnold | C5: NUL8H1005 | D5: 44444441005 | H5: Abigail | I5: Adam | J5: Adrian | K5: Alan | L5: Alexander | M5: Alexandra | N5: Alison | O5: Amanda | P5: Amelia | Q5: Amy | R5: Andrea | S5: Andrew | T5: Angela | U5: Anna | V5: Anne | W5: Anthony | X5: Audrey | Y5: Austin | Z5: Ava | AA5: Bella
A6: Alexandra | B6: Avery | C6: NUL8H1006 | D6: 44444441006
A7: Alison | B7: Bailey | C7: NUL8H1007 | D7: 44444441007 | H7: Abraham | I7: Allan | J7: Alsop | K7: Anderson | L7: Arnold | M7: Avery | N7: Bailey | O7: Baker | P7: Ball | Q7: Bell | R7: Berry | S7: Black | T7: Blake | U7: Bond | V7: Bower | W7: Brown | X7: Buckland | Y7: Burgess | Z7: Butler | AA7: Cameron
A8: Amanda | B8: Baker | C8: NUL8H1008 | D8: 44444441008
A9: Amelia | B9: Ball | C9: NUL8H1009 | D9: 44444441009 | H9: NUL8H1001 | I9: NUL8H1002 | J9: NUL8H1003 | K9: NUL8H1004 | L9: NUL8H1005 | M9: NUL8H1006 | N9: NUL8H1007 | O9: NUL8H1008 | P9: NUL8H1009 | Q9: NUL8H1010
A10: Amy | B10: Bell | C10: NUL8H1010 | D10: 44444441010
A11: Andrea | B11: Berry | C11: NUL8H1011 | D11: 44444441011 | H11: 44444441001 | I11: 44444441002 | J11: 44444441003 | K11: 44444441004 | L11: 44444441005 | M11: 44444441006 | N11: 44444441007 | O11: 44444441008 | P11: 44444441009 | Q11: 44444441010 | R11: 44444441011 | S11: 44444441012 | T11: 44444441013 | U11: 44444441014 | V11: 44444441015 | W11: 44444441016 | X11: 44444441017 | Y11: 44444441018 | Z11: 44444441019 | AA11: 44444441020
A12: Andrew | B12: Black | C12: NUL8H1012 | D12: 44444441012
A13: Angela | B13: Blake | C13: NUL8H1013 | D13: 44444441013
A14: Anna | B14: Bond | C14: NUL8H1014 | D14: 44444441014
A15: Anne | B15: Bower | C15: NUL8H1015 | D15: 44444441015
A16: Anthony | B16: Brown | C16: NUL8H1016 | D16: 44444441016
A17: Audrey | B17: Buckland | C17: NUL8H1017 | D17: 44444441017
A18: Austin | B18: Burgess | C18: NUL8H1018 | D18: 44444441018
A19: Ava | B19: Butler | C19: NUL8H1019 | D19: 44444441019
A20: Bella | B20: Cameron | C20: NUL8H1020 | D20: 44444441020
A21: Benjamin | B21: Campbell | C21: NUL8H1021 | D21: 44444441021
A22: Bernadette | B22: Carr | C22: NUL8H1022 | D22: 44444441022
A23: Blake | B23: Chapman | C23: NUL8H1023 | D23: 44444441023
... A149: Sue | B149: Young | C149: NUL8H1149 | D149: 44444441149
A150: Theresa | C150: NUL8H1150 | D150: 44444441150
A151: Thomas | C151: NUL8H1151 | D151: 44444441151
A152: Tim | C152: NUL8H1152 | D152: 44444441152
A153: Tracey | C153: NUL8H1153 | D153: 44444441153
A154: Trevor | C154: NUL8H1154 | D154: 44444441154
A155: Una | C155: NUL8H1155 | D155: 44444441155
A156: Vanessa | C156: NUL8H1156 | D156: 44444441156
A157: Victor | C157: NUL8H1157 | D157: 44444441157
A158: Victoria | C158: NUL8H1158 | D158: 44444441158
A159: Virginia | C159: NUL8H1159 | D159: 44444441159
A160: Wanda | C160: NUL8H1160 | D160: 44444441160
A161: Warren | C161: NUL8H1161 | D161: 44444441161
... A165: Zoe | C165: NUL8H1165 | D165: 44444441165
