Workbook
Name AddDependent_AddEditID: Test_Data!#REF!
Name AddDependent_DateOfBirth: Test_Data!#REF!
Name AddDependent_EffectiveDate: Test_Data!#REF!
Name AddDependent_Gender: Test_Data!#REF!
Name AddDependent_GivenName: Test_Data!#REF!
Name AddDependent_LastName: Test_Data!#REF!
Name AddDependent_LivesWithWorker: Test_Data!#REF!
Name AddDependent_LivingWithWorkerEffectiveDate: Test_Data!#REF!
Name AddDependent_NationalIDCountry: Test_Data!#REF!
Name AddDependent_NationalIDType: Test_Data!#REF!
Name AddDependent_Relationship: Test_Data!#REF!
Name AddProbationPeriod_ProbationEndDate: Test_Data!$E$53
Name AddProbationPeriod_ProbationEndDate2: Test_Data!$F$53
Name AddProbationPeriod_ProbationEndDate2: Automation_Lookups!$AO$2:$AO$4
Name AssignPayGroup_ProposedPayGroup: Test_Data!$E$50
Name AssignPayGroup_ProposedPayGroup: Automation_Lookups!$T$2:$T$20
Name AssignPayGroup_ProposedPayGroup2: Test_Data!$F$50
Name AssignPayGroup_ProposedPayGroup2: Automation_Lookups!$T$2
Name Automation_Ref: Test_Data!$G$14:$J$14
Name AutomationComments: Test_Data!$E$11
Name ChangeMyEmergencyContacts_City: Test_Data!#REF!
Name ChangeMyEmergencyContacts_EmailAddress: Test_Data!#REF!
Name ChangeMyEmergencyContacts_FamilyName: Test_Data!#REF!
Name ChangeMyEmergencyContacts_GivenName: Test_Data!#REF!
Name ChangeMyEmergencyContacts_PhoneDevice: Test_Data!#REF!
Name ChangeMyEmergencyContacts_PhoneDevice2: Automation_Lookups!$AJ$2:$AJ$3
Name ChangeMyEmergencyContacts_PhoneNumber: Test_Data!#REF!
Name ChangeMyEmergencyContacts_PostalCode: Test_Data!#REF!
Name ChangeMyEmergencyContacts_Relationship: Test_Data!#REF!
Name ChangeMyEmergencyContacts_Relationship2: Automation_Lookups!$AI$2:$AI$5
Name ChangeMyEmergencyContacts_StreetName: Test_Data!#REF!
Name ChangeMyGovernmentIDs_NationalIDs_AddEditID: Test_Data!$E$68
Name ChangeMyGovernmentIDs_NationalIDs_AddEditID1: Test_Data!$E$65
Name ChangeMyGovernmentIDs_NationalIDs_AddEditID12: Test_Data!$F$65
Name ChangeMyGovernmentIDs_NationalIDs_AddEditID2: Test_Data!$E$68
Name ChangeMyGovernmentIDs_NationalIDs_AddEditID22: Automation_Lookups!$AL$2:$AL$4
Name ChangeMyGovernmentIDs_NationalIDs_AddEditID22: Test_Data!$F$68
Name ChangeMyGovernmentIDs_NationalIDs_AddEditID3: Test_Data!#REF!
Name ChangeMyGovernmentIDs_NationalIDs_Country1: Test_Data!$E$63
Name ChangeMyGovernmentIDs_NationalIDs_Country12: Test_Data!$F$63
Name ChangeMyGovernmentIDs_NationalIDs_Country2: Test_Data!$E$66
Name ChangeMyGovernmentIDs_NationalIDs_Country22: Test_Data!$F$66
Name ChangeMyGovernmentIDs_NationalIDs_Country3: Test_Data!#REF!
Name ChangeMyGovernmentIDs_NationalIDs_NationalIDType1: Test_Data!$E$64
Name ChangeMyGovernmentIDs_NationalIDs_NationalIDType12: Test_Data!$F$64
Name ChangeMyGovernmentIDs_NationalIDs_NationalIDType12: Automation_Lookups!$AK$2:$AK$5
Name ChangeMyGovernmentIDs_NationalIDs_NationalIDType2: Test_Data!$E$67
Name ChangeMyGovernmentIDs_NationalIDs_NationalIDType2: Automation_Lookups!$AL$2:$AL$4
Name ChangeMyGovernmentIDs_NationalIDs_NationalIDType22: Test_Data!$F$67
Name ChangeMyGovernmentIDs_NationalIDs_NationalIDType22: Automation_Lookups!$AL$2:$AL$4
Name ChangeMyGovernmentIDs_NationalIDs_NationalIDType3: Test_Data!#REF!
Name ChangeMyPersonalInformation_CitizenshipStatus: Test_Data!$E$62
Name ChangeMyPersonalInformation_CityOfBirth: Test_Data!$E$59
Name ChangeMyPersonalInformation_CityOfBirth2: Test_Data!$F$59
Name ChangeMyPersonalInformation_CountryTerritoryOfBirth: Test_Data!$E$57
Name ChangeMyPersonalInformation_CountryTerritoryOfBirth2: Test_Data!$F$57
Name ChangeMyPersonalInformation_DateOfBirth: Test_Data!$E$56
Name ChangeMyPersonalInformation_DateOfBirth2: Test_Data!$F$56
Name ChangeMyPersonalInformation_Gender: Test_Data!$E$55
Name ChangeMyPersonalInformation_Gender2: Test_Data!$F$55

Sheet Information
A1: Version | F1: Info
A6: Version | B6: 0.3 | F6: Info
F7: Dates | G7: For Czech all dates to be entered in format of DD/MM/YYYY
A8: History | F8: Unhighlighted fields | G8: Only data in unhighlighted fields can be changed.
A9: Date | B9: Version | C9: Details | F9: Red highlighted fields | G9: Indicates fields where unique data is required otherwise automation will throw errors
A10: 44061 | B10: 0.3 | C10: Initial Release | F10: Grey highlighted fields | G10: Indicates fields that cannot be changed
F11: Last Run Status / Last Run Error Message | G11: When automation has run for a particular test, we need to check the status is set to Passed and no error messages are present for each test before the automation run for that particular test is considered valid

Sheet Defects
B2: Batch 1 - Summary | E2: Batch 2 - Summary | H2: Batch 3 - Summary | K2: All E2E Cycle 1 - Summary
B3: Description | C3: Total | E3: Description | F3: Total | H3: Description | I3: Total | K3: Description | L3: Total No. | M3: %
B4: Passed | C4: 35 | E4: Passed | F4: 141 | H4: Passed | I4: 0 | K4: Passed | L4: =C4+F4+I4 -> 176 | M4: =L4/L8*100 -> 72.131148
B5: Failed | C5: 17 | E5: Failed | F5: 27 | H5: Failed | I5: 24 | K5: Failed | L5: =C5+F5+I5 -> 68 | M5: =L5/L8*100 -> 27.868852
B6: Not Run | C6: 0 | E6: Not Run | F6: 0 | H6: Not Run | I6: 0 | K6: Not Run | L6: =C6+F6+I6 -> 0 | M6: =L6/L8*100 -> 0
B7: Executed | C7: 52 | E7: Executed | F7: 168 | H7: Executed | I7: 24 | K7: Executed | L7: =C7+F7+I7 -> 244 | M7: =L7/L8*100 -> 100
B8: Total | C8: 52 | E8: Total | F8: 168 | H8: Total | I8: 24 | K8: Total | L8: =C8+F8+I8 -> 244 | M8: =M4+M5+M6 -> 100
B10: Batch 1 - Defects | E10: Batch 2 - Defects | H10: Batch 3 - Defects | K10: All E2E Cycle 1 - Defects
B11: Failed Tests Description | C11: Total | E11: Failed Tests Description | F11: Total | H11: Failed Tests Description | I11: Total | K11: Failed Tests Description | L11: Total No. | M11: %
B12: P&C Salary Assistant/Supervisor Salary Configuration missing | C12: 12 | E12: Grade Profile not populated causing salary to remain blank | F12: 24 | H12: Data issue - Rerun scheduled | I12: 24 | K12: Personal Information Change Approval Email missing after 2nd and final proxy into HR Manager | L12: 44 | M12: =L12/L17*100 -> 35.2
B13: Automation issue with Maiden Name - Gary to discuss with Shane/Andre | C13: 5 | E13: GC - Under Investigation | F13: 3 | H13: Total | I13: 24 | K13: Open button not available to assign paygroup for payroll. Approval required by David Bradley... | L13: 20 | M13: =L13/L17*100 -> 16
B14: Total | C14: =C12+C13 -> 17 | E14: Total | F14: 27 | K14: Grade Profile not populated causing salary to remain blank | L14: 34 | M14: =L14/L17*100 -> 27.2
K15: Data issue - Rerun scheduled | L15: 24 | M15: =L15/L17*100 -> 19.2
K16: GC - Under Investigation | L16: 3 | M16: =L16/L17*100 -> 2.4
K17: Total | L17: =SUM(L12:L16) -> 125 | M17: =SUM(M12:M16) -> 100

Sheet Automation_Lookups
A1: Process2 | B1: ExecutionFlag2 | C1: SupervisoryOrganisation_SupervisoryOrganisation2 | D1: LegalNameInformation_Country2 | E1: ContactInformation_Phone_CountryPhoneCode2 | F1: ContactInformation_Phone_PhoneDevice2 | G1: ContactInformation_Phone_Type2 | H1: ContactInformation_Address_Type2 | I1: ContactInformation_Email_Type2 | J1: JobDetails_HireDate2 | K1: JobDetails_Reason2 | L1: JobDetails_Position2 | M1: JobDetails_EmployeeType2 | N1: JobDetails_JobProfile2 | O1: JobDetails_TimeType2 | P1: JobDetails_Location2 | Q1: JobDetails_AdditionalInformation_WorkShift2 | R1: JobDetails_AdditionalInformation_EndEmploymentDate2 | S1: ChangeOrganizationAssignments_DepartmentSection2 | T1: AssignPayGroup_ProposedPayGroup2 | U1: Proxy_ProxyNumber2 | V1: Proxy_OnBehalfOf2 | W1: MaintainEmployeeContract_Reason2 | X1: MaintainEmployeeContract_Status2 | Y1: MaintainEmployeeContract_ContractType2 | Z1: MaintainEmployeeContract_ContractEndDate2 | AA1: ProposeCompensationHire_GradeProfile2 | AB1: ProposeCompensationHire_Step2 | AC1: EditPassportsandVisas_Country2 | AD1: EditPassportsandVisas_PassportIDType2 | AE1: EditPassportsandVisas_IdentificationNo2 | AF1: EditPassportsandVisas_IssuedDate2 | AG1: EditPassportsandVisas_ExpirationDate2 | AH1: ChangeMyPersonalInformation_MaritalStatus2 | AI1: ChangeMyEmergencyContacts_Relationship2 | AJ1: ChangeMyEmergencyContacts_PhoneDevice2 | AK1: ChangeMyGovernmentIDs_NationalIDs_NationalIDType12 | AL1: ChangeMyGovernmentIDs_NationalIDs_AddEditID22 | AM1: PaymentElectionOption_AccountType2 | AN1: SkillsAndExperience_AddEducation_School2 | AO1: AddProbationPeriod_ProbationEndDate2 | AP1: EditAdditionalData_PayrollTaxDeduction | AQ1: HealthCareProvider_MealVoucher2 | AR1: School1 | AS1: School2 | AT1: ContactInformation_Address_Province2 | AU1: ChangeMyGovernmentIDs_NationalIDs_NationalIDType12 | AV1: ChangeMyGovernmentIDs_NationalIDs_NationalIDType22 | AW1: EditAdditionalData_EstadolIRPF2 | AX1: EditAdditionalData_MinusvaliaRH2
A2: New Hire | B2: Yes | C2: 362 Recruitment (Carolina De La Barrera Crespo (375)) | D2: Czechia | E2: Czechia (+420) | F2: Mobile | G2: Home | H2: Home | I2: Home | J2: =IF(MONTH(TODAY())<10,"0"&MONTH(TODAY())&"/",MONTH(TODAY())&"/") & IF(DAY(TODAY())<10,"0"&DAY(TODAY())&"/",DAY(TODAY())&"/") & YEAR(TODAY()) -> 10/15/2024 | K2: New Hire | L2: Assistant Manager-2 | M2: Fixed Term | N2: DPP/DPC | O2: Full time | P2: 362 Algeciras | Q2: 1 Day | R2: =IF(MONTH(TODAY())<10,"0"&MONTH(TODAY())&"/",MONTH(TODAY())&"/") & IF(DAY(TODAY())<10,"0"&DAY(TODAY())&"/",DAY(TODAY())&"/") & YEAR(TODAY()) -> 10/15/2024 | S2: Accessories | T2: Please select a Spanish Pay Group | U2: 10223439 | V2: Iwona Chrostowska (10223439) | W2: for the purposes of performing any work of casual or seasonal nature | X2: 1st Fixed Term Contract | Y2: Employment Agreement | Z2: =IF(MONTH(TODAY())<10,"0"&MONTH(TODAY())&"/",MONTH(TODAY())&"/") & IF(DAY(TODAY())<10,"0"&DAY(TODAY())&"/",DAY(TODAY())&"/") & YEAR(TODAY()) -> 10/15/2024 | AA2: Defaulted | AB2: Defaulted | AH2: Single | AI2: Father | AJ2: Mobile/Cell | AK2: Social Security Number (NSS) | AL2: Social Security Number (NSS) | AM2: Savings | AN2: N/A | AO2: =IF(MONTH(TODAY()+100)<10,"0"&MONTH(TODAY()+100)&"/",MONTH(TODAY()+100)&"/") & IF(DAY(TODAY()+100)<10,"0"&DAY(TODAY()+100)&"/",DAY(TODAY()+100)&"/") & YEAR(TODAY()+100) -> 01/23/2025 | AP2: Yes | AQ2: Yes | AR2: Střední bez maturity či výučního listu | AS2: stredni bez maturity ci vyucniho listu | AT2: Madrid | AU2: Social Security Number (NSS) | AV2: ID Card (DNI) Number | AW2: Soltero/a, viudo/a, divorciado/a o separado/a legalmente con hijos solteros menores de 18 años o incapacitados judicialmente que conviven exclusivamente con Vd., sin convivir también con el otro progenitor Soltero/a, viudo/a, divorciado/a o separado/a legalmente con hijos solteros menores de 18 años o incapacitados judicialmente que conviven exclusivamente con Vd., sin convivir también con el otro progenitor | AX2: Del 33% hasta el 65%
A3: New Role & New Hire | B3: No | C3: 895 Store Management (Male Teststmanager (10224969)) | D3: Czechia | E3: Czechia (+420) | F3: Landline | G3: Work | H3: Work | I3: Work | J3: =IF(MONTH(TODAY()-10)<10,"0"&MONTH(TODAY()-10)&"/",MONTH(TODAY()-10))&"/" & IF(DAY(TODAY()-10)<10,"0"&DAY(TODAY()-10)&"/",DAY(TODAY()-10)&"/") & YEAR(TODAY()-10) -> 10/05/2024 | L3: Assistant Manager-3 | M3: Intern | N3: Retail Assistant | O3: Part time | Q3: 2 Days | R3: =IF(MONTH(TODAY()+100)<10,"0"&MONTH(TODAY()+100)&"/",MONTH(TODAY()+100)&"/") & IF(DAY(TODAY()+100)<10,"0"&DAY(TODAY()+100)&"/",DAY(TODAY()+100)&"/") & YEAR(TODAY()+100) -> 01/23/2025 | T3: ES Monthly - 15 payments | U3: 10225553 | V3: Kocour Mikeš (10225553) | W3: for the purposes of performing work during the term of office | X3: 2nd Fixed Term Contract | Y3: Agreement to perform work | Z3: =IF(MONTH(TODAY()+100)<10,"0"&MONTH(TODAY()+100)&"/",MONTH(TODAY()+100)&"/") & IF(DAY(TODAY()+100)<10,"0"&DAY(TODAY()+100)&"/",DAY(TODAY()+100)&"/") & YEAR(TODAY()+100) -> 01/23/2025 | AH3: Married | AI3: Mother | AJ3: Telephone - Landline | AK3: ID Card (DNI) Number | AL3: ID Card (DNI) Number | AM3: Checking | AN3: Vseobecne stredni s maturitou | AO3: =IF(MONTH(TODAY()+1000)<10,"0"&MONTH(TODAY()+1000)&"/",MONTH(TODAY()+1000)&"/") & IF(DAY(TODAY()+1000)<10,"0"&DAY(TODAY()+1000)&"/",DAY(TODAY()+1000)&"/") & YEAR(TODAY()+1000) -> 07/12/2027 | AP3: No | AQ3: No | AR3: Střední odborné vzdělání s výučním listem | AS3: stredni odborne vzdelani s vyucnim listem
D4: Poland | E4: Poland (+48) | J4: =IF(MONTH(TODAY()+10)<10,"0"&MONTH(TODAY()+10)&"/",MONTH(TODAY()+10)&"/") & IF(DAY(TODAY()+10)<10,"0"&DAY(TODAY()+10)&"/",DAY(TODAY()+10)&"/") & YEAR(TODAY()+10) -> 10/25/2024 | L4: Test Store Manager-2 | M4: Permanent | N4: Department Manager | Q4: 3 Days | R4: =IF(MONTH(TODAY()+1000)<10,"0"&MONTH(TODAY()+1000)&"/",MONTH(TODAY()+1000)&"/") & IF(DAY(TODAY()+1000)<10,"0"&DAY(TODAY()+1000)&"/",DAY(TODAY()+1000)&"/") & YEAR(TODAY()+1000) -> 07/12/2027 | W4: for the purposes of substituting an employee during his/her excused absence at work | X4: 3rd Fixed Term Contract | Y4: Agreement to complete a job | Z4: =IF(MONTH(TODAY()+1000)<10,"0"&MONTH(TODAY()+1000)&"/",MONTH(TODAY()+1000)&"/") & IF(DAY(TODAY()+1000)<10,"0"&DAY(TODAY()+1000)&"/",DAY(TODAY()+1000)&"/") & YEAR(TODAY()+1000) -> 07/12/2027 | AH4: Not Disclosed | AI4: Spouse | AK4: Alien Identification Number (NIE) | AL4: Alien Identification Number (NIE) | AO4: N/A | AR4: Všeobecné střední s maturitou | AS4: vseobecne stredni s maturitou
D5: Poland | E5: Poland (+48) | L5: N/A | M5: Students | N5: Senior Department Manager | Q5: 4 Days | R5: N/A | W5: No reason necessary | X5: Active | Z5: N/A | AI5: Partner | AK5: Tax Identification Number (NIF) | AR5: Vysokoškolské Bc. | AS5: Vysokoskolske Bc
N6: Supervisor | Q6: 5 Days | X6: Inactive | AR6: Vysokoškolské MUDr., JUDr., Mgr., MgA., Ing. | AS6: vysokoskolske MUDR., JUDr., Mgr., MgA., Ing.
N7: P&C Supervisor | AR7: Vysokoškolské PhDr, PhD, JUDr, MUDr | AS7: vysokoskolske PhDr, PhD, JUDr, MUDr
N8: P&C Assistant | AR8: vyšší odborné DiS | AS8: vyssi odborne DiS
N9: Trainee Manager | AR9: Základní | AS9: Zakladni
N10: Assistant Manager
N11: P&C Manager
N12: Store Manager
N13: Visual Merchandiser Manager
N14: Visual Merchandising Supervisor
N15: Visual Merchandising Assistant
K21: Rehire | U21: 8701839 | V21: Lisanne Kluinhaar (8701839) | W21: Defined contract end date (Determined) | AQ21: Netherlands Retail Assistant
C22: 701 Recruitment (Lisanne Kluinhaar (8701839)) | D22: Netherlands | E22: Netherlands (+31) | K22: Seasonal | W22: Undefined contract end date (Undetermined) | Y22: Part-time( PT ) | AQ22: Netherlands Retail Assistant Cash Office | AR22: Retail Assistant (18)
W23: Intern | Y23: Full-time( FT. ) | AR23: Retail Assistant (19)
C24: Retail - Central & Eastern Europe (Stephen Regan (9910010) (Inherited) | D24: Poland | E24: Poland (+48) | AR24: Retail Assistant (20)
C25: Retail Poland Area: Central Poland (Stephen Regan (9910010) (Inherited)) | D25: Poland | E25: Poland (+48) | AR25: Retail Assistant (21)
AR26: Retail Assistant (22)
AR27: Retail Assistant (23+)
AR28: Retail Assistant (Under 18)

Sheet RC. No
A1: D.O.B | B1: 35139 | C1: 33054 | D1: 31390 | F1: r col b | G1: r col c | H1: r col d
B2: 9603150007 | C2: 9006300006 | D2: 8512090004 | F2: =B2/11 -> 873013637 | G2: =C2/11 -> 818754546 | H2: =D2/11 -> 773826364
B3: =B2+11 -> 9603150018 | C3: =C2+11 -> 9006300017 | D3: =D2+11 -> 8512090015 | F3: =B3/11 -> 873013638 | G3: =C3/11 -> 818754547 | H3: =D3/11 -> 773826365
B4: =B3+11 -> 9603150029 | C4: =C3+11 -> 9006300028 | D4: =D3+11 -> 8512090026 | F4: =B4/11 -> 873013639 | G4: =C4/11 -> 818754548 | H4: =D4/11 -> 773826366
B5: =B4+11 -> 9603150040 | C5: =C4+11 -> 9006300039 | D5: =D4+11 -> 8512090037 | F5: =B5/11 -> 873013640 | G5: =C5/11 -> 818754549 | H5: =D5/11 -> 773826367
B6: =B5+11 -> 9603150051 | C6: =C5+11 -> 9006300050 | D6: =D5+11 -> 8512090048 | F6: =B6/11 -> 873013641 | G6: =C6/11 -> 818754550 | H6: =D6/11 -> 773826368
B7: =B6+11 -> 9603150062 | C7: =C6+11 -> 9006300061 | D7: =D6+11 -> 8512090059 | F7: =B7/11 -> 873013642 | G7: =C7/11 -> 818754551 | H7: =D7/11 -> 773826369
B8: =B7+11 -> 9603150073 | C8: =C7+11 -> 9006300072 | D8: =D7+11 -> 8512090070 | F8: =B8/11 -> 873013643 | G8: =C8/11 -> 818754552 | H8: =D8/11 -> 773826370
B9: =B8+11 -> 9603150084 | C9: =C8+11 -> 9006300083 | D9: =D8+11 -> 8512090081 | F9: =B9/11 -> 873013644 | G9: =C9/11 -> 818754553 | H9: =D9/11 -> 773826371
B10: =B9+11 -> 9603150095 | C10: =C9+11 -> 9006300094 | D10: =D9+11 -> 8512090092 | F10: =B10/11 -> 873013645 | G10: =C10/11 -> 818754554 | H10: =D10/11 -> 773826372
B11: =B10+11 -> 9603150106 | C11: =C10+11 -> 9006300105 | D11: =D10+11 -> 8512090103 | F11: =B11/11 -> 873013646 | G11: =C11/11 -> 818754555 | H11: =D11/11 -> 773826373
B12: =B11+11 -> 9603150117 | C12: =C11+11 -> 9006300116 | D12: =D11+11 -> 8512090114 | F12: =B12/11 -> 873013647 | G12: =C12/11 -> 818754556 | H12: =D12/11 -> 773826374
B13: =B12+11 -> 9603150128 | C13: =C12+11 -> 9006300127 | D13: =D12+11 -> 8512090125 | F13: =B13/11 -> 873013648 | G13: =C13/11 -> 818754557 | H13: =D13/11 -> 773826375
B14: =B13+11 -> 9603150139 | C14: =C13+11 -> 9006300138 | D14: =D13+11 -> 8512090136 | F14: =B14/11 -> 873013649 | G14: =C14/11 -> 818754558 | H14: =D14/11 -> 773826376
... B28: =B27+11 -> 9603150293 | C28: =C27+11 -> 9006300292 | D28: =D27+11 -> 8512090290 | F28: =B28/11 -> 873013663 | G28: =C28/11 -> 818754572 | H28: =D28/11 -> 773826390
B29: =B28+11 -> 9603150304
B30: =B29+11 -> 9603150315
B31: =B30+11 -> 9603150326
B32: =B31+11 -> 9603150337
B33: =B32+11 -> 9603150348
B34: =B33+11 -> 9603150359
B35: =B34+11 -> 9603150370
B36: =B35+11 -> 9603150381
B37: =B36+11 -> 9603150392
B38: =B37+11 -> 9603150403
B39: =B38+11 -> 9603150414
B40: =B39+11 -> 9603150425
... B75: =B74+11 -> 9603150810
B76: =B75+11 -> 9603150821 | X76: New RC Numbers
B77: =B76+11 -> 9603150832 | X77: 9202101337
B78: =B77+11 -> 9603150843 | X78: =SUM(X77)+11 -> 9202101348
B79: =B78+11 -> 9603150854 | X79: =SUM(X78)+11 -> 9202101359
B80: =B79+11 -> 9603150865 | X80: =SUM(X79)+11 -> 9202101370
B81: =B80+11 -> 9603150876 | X81: =SUM(X80)+11 -> 9202101381
B82: =B81+11 -> 9603150887 | X82: =SUM(X81)+11 -> 9202101392
B83: =B82+11 -> 9603150898 | X83: =SUM(X82)+11 -> 9202101403
B84: =B83+11 -> 9603150909 | X84: =SUM(X83)+11 -> 9202101414
B85: =B84+11 -> 9603150920 | X85: =SUM(X84)+11 -> 9202101425
B86: =B85+11 -> 9603150931 | D86: 9603170269 | X86: =SUM(X85)+11 -> 9202101436
D87: =D86+11 -> 9603170280 | F87: 9603170280 | H87: 9603170280 | I87: 9603170291 | J87: 9603170302 | K87: 9603170313 | L87: 9603170324 | M87: 9603170335 | N87: 9603170346 | O87: 9603170357 | P87: 9603170368 | Q87: 9603170379 | R87: 9603170390 | S87: 9603170401 | T87: 9603170412 | X87: =SUM(X86)+11 -> 9202101447
D88: =D87+11 -> 9603170291 | F88: 9603170291 | X88: =SUM(X87)+11 -> 9202101458
D89: =D88+11 -> 9603170302 | F89: 9603170302 | H89: 9603170412 | I89: =H89+11 -> 9603170423 | J89: =I89+11 -> 9603170434 | K89: =J89+11 -> 9603170445 | L89: =K89+11 -> 9603170456 | M89: =L89+11 -> 9603170467 | N89: =M89+11 -> 9603170478 | O89: =N89+11 -> 9603170489 | P89: =O89+11 -> 9603170500 | ... T89: =S89+11 -> 9603170544 | X89: =SUM(X88)+11 -> 9202101469
D90: =D89+11 -> 9603170313 | F90: 9603170313 | X90: =SUM(X89)+11 -> 9202101480
D91: =D90+11 -> 9603170324 | F91: 9603170324 | X91: =SUM(X90)+11 -> 9202101491
D92: =D91+11 -> 9603170335 | F92: 9603170335 | X92: =SUM(X91)+11 -> 9202101502
D93: =D92+11 -> 9603170346 | F93: 9603170346 | X93: =SUM(X92)+11 -> 9202101513
D94: =D93+11 -> 9603170357 | F94: 9603170357 | X94: =SUM(X93)+11 -> 9202101524
D95: =D94+11 -> 9603170368 | F95: 9603170368 | X95: =SUM(X94)+11 -> 9202101535
D96: =D95+11 -> 9603170379 | F96: 9603170379 | X96: =SUM(X95)+11 -> 9202101546
D97: =D96+11 -> 9603170390 | F97: 9603170390 | X97: =SUM(X96)+11 -> 9202101557
D98: =D97+11 -> 9603170401 | F98: 9603170401 | X98: =SUM(X97)+11 -> 9202101568
D99: =D98+11 -> 9603170412 | F99: 9603170412 | X99: =SUM(X98)+11 -> 9202101579
X100: =SUM(X99)+11 -> 9202101590
X101: =SUM(X100)+11 -> 9202101601
X102: =SUM(X101)+11 -> 9202101612
X103: =SUM(X102)+11 -> 9202101623
X104: =SUM(X103)+11 -> 9202101634
X105: =SUM(X104)+11 -> 9202101645
X106: =SUM(X105)+11 -> 9202101656
X107: =SUM(X106)+11 -> 9202101667
X108: =SUM(X107)+11 -> 9202101678
X109: =SUM(X108)+11 -> 9202101689
X110: =SUM(X109)+11 -> 9202101700
X111: =SUM(X110)+11 -> 9202101711
... X133: =SUM(X132)+11 -> 9202101953

Sheet Code_11122019_1000
B1: Variable Row | C1: Variable Row Combined | D1: Variable Value | E1: Variable Value Combined | F1: Row Number Declaration --------------------------------- intRowProcess = comExcelWorksheet.Range("Process").Row | G1: Value Declaration ------------------------ strProcess = comExcelWorksheet.Cells(intRowProcess, intColTestColumn).Value | H1: Getters
A2: =Test_Data!D3 -> Process | B2: ="intRow" & A2 & ", " -> intRowProcess, | C2: =B2 -> intRowProcess, | D2: ="str" & A2 & ", " -> strProcess, | E2: =D2 -> strProcess, | F2: ="intRow" & A2 & " = comExcelWorksheet.Range(""" & A2 & """).Row" -> intRowProcess = comExcelWorksheet.Range("Process").Row | G2: ="str" & A2 & " = comExcelWorksheet.Cells(intRow" & A2 & ", intColTestColumn).Value" -> strProcess = comExcelWorksheet.Cells(intRowProcess, intColTestColumn).Value | H2: ="Public Property Get get" & A2 & "() : get" & A2 & " = str" & A2 & " : End Property" -> Public Property Get getProcess() : getProcess = strProcess : End Property
A3: =Test_Data!D4 -> ExecutionFlag | B3: ="intRow" & A3 & ", " -> intRowExecutionFlag, | C3: =C2 &B3 -> intRowProcess, intRowExecutionFlag, | D3: ="str" & A3 & ", " -> strExecutionFlag, | E3: =E2 &D3 -> strProcess, strExecutionFlag, | F3: ="intRow" & A3 & " = comExcelWorksheet.Range(""" & A3 & """).Row" -> intRowExecutionFlag = comExcelWorksheet.Range("ExecutionFlag").Row | G3: ="str" & A3 & " = comExcelWorksheet.Cells(intRow" & A3 & ", intColTestColumn).Value" -> strExecutionFlag = comExcelWorksheet.Cells(intRowExecutionFlag, intColTestColumn).Value | H3: ="Public Property Get get" & A3 & "() : get" & A3 & " = str" & A3 & " : End Property" -> Public Property Get getExecutionFlag() : getExecutionFlag = strExecutionFlag : End Property
A4: =Test_Data!D7 -> LastRunTimeandStatus | B4: ="intRow" & A4 & ", " -> intRowLastRunTimeandStatus, | C4: =C3 &B4 -> intRowProcess, intRowExecutionFlag, intRowLastRunTimeandStatus, | D4: ="str" & A4 & ", " -> strLastRunTimeandStatus, | E4: =E3 &D4 -> strProcess, strExecutionFlag, strLastRunTimeandStatus, | F4: ="intRow" & A4 & " = comExcelWorksheet.Range(""" & A4 & """).Row" -> intRowLastRunTimeandStatus = comExcelWorksheet.Range("LastRunTimeandStatus").Row | G4: ="str" & A4 & " = comExcelWorksheet.Cells(intRow" & A4 & ", intColTestColumn).Value" -> strLastRunTimeandStatus = comExcelWorksheet.Cells(intRowLastRunTimeandStatus, intColTestColumn).Value | H4: ="Public Property Get get" & A4 & "() : get" & A4 & " = str" & A4 & " : End Property" -> Public Property Get getLastRunTimeandStatus() : getLastRunTimeandStatus = strLastRunTimeandStatus : End Property
A5: =Test_Data!D8 -> LastRunEmployeeNo | B5: ="intRow" & A5 & ", " -> intRowLastRunEmployeeNo, | C5: =C4 &B5 -> intRowProcess, intRowExecutionFlag, intRowLastRunTimeandStatus, intRowLastRunEmployeeNo, | D5: ="str" & A5 & ", " -> strLastRunEmployeeNo, | E5: =E4 &D5 -> strProcess, strExecutionFlag, strLastRunTimeandStatus, strLastRunEmployeeNo, | F5: ="intRow" & A5 & " = comExcelWorksheet.Range(""" & A5 & """).Row" -> intRowLastRunEmployeeNo = comExcelWorksheet.Range("LastRunEmployeeNo").Row | G5: ="str" & A5 & " = comExcelWorksheet.Cells(intRow" & A5 & ", intColTestColumn).Value" -> strLastRunEmployeeNo = comExcelWorksheet.Cells(intRowLastRunEmployeeNo, intColTestColumn).Value | H5: ="Public Property Get get" & A5 & "() : get" & A5 & " = str" & A5 & " : End Property" -> Public Property Get getLastRunEmployeeNo() : getLastRunEmployeeNo = strLastRunEmployeeNo : End Property
A6: =Test_Data!D9 -> LastRunErrorMessage | B6: ="intRow" & A6 & ", " -> intRowLastRunErrorMessage, | C6: =C5 &B6 -> intRowProcess, intRowExecutionFlag, intRowLastRunTimeandStatus, intRowLastRunEmployeeNo, intRowLastRunErrorMessage, | D6: ="str" & A6 & ", " -> strLastRunErrorMessage, | E6: =E5 &D6 -> strProcess, strExecutionFlag, strLastRunTimeandStatus, strLastRunEmployeeNo, strLastRunErrorMessage, | F6: ="intRow" & A6 & " = comExcelWorksheet.Range(""" & A6 & """).Row" -> intRowLastRunErrorMessage = comExcelWorksheet.Range("LastRunErrorMessage").Row | G6: ="str" & A6 & " = comExcelWorksheet.Cells(intRow" & A6 & ", intColTestColumn).Value" -> strLastRunErrorMessage = comExcelWorksheet.Cells(intRowLastRunErrorMessage, intColTestColumn).Value | H6: ="Public Property Get get" & A6 & "() : get" & A6 & " = str" & A6 & " : End Property" -> Public Property Get getLastRunErrorMessage() : getLastRunErrorMessage = strLastRunErrorMessage : End Property
A7: =Test_Data!D10 -> DefectDescription | B7: ="intRow" & A7 & ", " -> intRowDefectDescription, | C7: =C6 &B7 -> intRowProcess, intRowExecutionFlag, intRowLastRunTimeandStatus, intRowLastRunEmployeeNo, intRowLastRunErrorMessage, intRowDefectDescription, | D7: ="str" & A7 & ", " -> strDefectDescription, | E7: =E6 &D7 -> strProcess, strExecutionFlag, strLastRunTimeandStatus, strLastRunEmployeeNo, strLastRunErrorMessage, strDefectDescription, | F7: ="intRow" & A7 & " = comExcelWorksheet.Range(""" & A7 & """).Row" -> intRowDefectDescription = comExcelWorksheet.Range("DefectDescription").Row | G7: ="str" & A7 & " = comExcelWorksheet.Cells(intRow" & A7 & ", intColTestColumn).Value" -> strDefectDescription = comExcelWorksheet.Cells(intRowDefectDescription, intColTestColumn).Value | H7: ="Public Property Get get" & A7 & "() : get" & A7 & " = str" & A7 & " : End Property" -> Public Property Get getDefectDescription() : getDefectDescription = strDefectDescription : End Property
A8: =Test_Data!D11 -> AutomationComments | B8: ="intRow" & A8 & ", " -> intRowAutomationComments, | C8: =C7 &B8 -> intRowProcess, intRowExecutionFlag, intRowLastRunTimeandStatus, intRowLastRunEmployeeNo, intRowLastRunErrorMessage, intRowDefectDescription, intRowAutomationComments, | D8: ="str" & A8 & ", " -> strAutomationComments, | E8: =E7 &D8 -> strProcess, strExecutionFlag, strLastRunTimeandStatus, strLastRunEmployeeNo, strLastRunErrorMessage, strDefectDescription, strAutomationComments, | F8: ="intRow" & A8 & " = comExcelWorksheet.Range(""" & A8 & """).Row" -> intRowAutomationComments = comExcelWorksheet.Range("AutomationComments").Row | G8: ="str" & A8 & " = comExcelWorksheet.Cells(intRow" & A8 & ", intColTestColumn).Value" -> strAutomationComments = comExcelWorksheet.Cells(intRowAutomationComments, intColTestColumn).Value | H8: ="Public Property Get get" & A8 & "() : get" & A8 & " = str" & A8 & " : End Property" -> Public Property Get getAutomationComments() : getAutomationComments = strAutomationComments : End Property
A9: =Test_Data!D12 -> QAComments | B9: ="intRow" & A9 & ", " -> intRowQAComments, | C9: =C8 &B9 -> intRowProcess, intRowExecutionFlag, intRowLastRunTimeandStatus, intRowLastRunEmployeeNo, intRowLastRunErrorMessage, intRowDefectDescription, intRowAutomationComments, intRowQAComments, | D9: ="str" & A9 & ", " -> strQAComments, | E9: =E8 &D9 -> strProcess, strExecutionFlag, strLastRunTimeandStatus, strLastRunEmployeeNo, strLastRunErrorMessage, strDefectDescription, strAutomationComments, strQAComments, | F9: ="intRow" & A9 & " = comExcelWorksheet.Range(""" & A9 & """).Row" -> intRowQAComments = comExcelWorksheet.Range("QAComments").Row | G9: ="str" & A9 & " = comExcelWorksheet.Cells(intRow" & A9 & ", intColTestColumn).Value" -> strQAComments = comExcelWorksheet.Cells(intRowQAComments, intColTestColumn).Value | H9: ="Public Property Get get" & A9 & "() : get" & A9 & " = str" & A9 & " : End Property" -> Public Property Get getQAComments() : getQAComments = strQAComments : End Property
A10: =Test_Data!D13 -> 0 | B10: ="intRow" & A10 & ", " -> intRow0, | C10: =C9 &B10 -> intRowProcess, intRowExecutionFlag, intRowLastRunTimeandStatus, intRowLastRunEmployeeNo, intRowLastRunErrorMessage, intRowDefectDescription, intRowAutomationComments, intRowQAComments, intRow0, | D10: ="str" & A10 & ", " -> str0, | E10: =E9 &D10 -> strProcess, strExecutionFlag, strLastRunTimeandStatus, strLastRunEmployeeNo, strLastRunErrorMessage, strDefectDescription, strAutomationComments, strQAComments, str0, | F10: ="intRow" & A10 & " = comExcelWorksheet.Range(""" & A10 & """).Row" -> intRow0 = comExcelWorksheet.Range("0").Row | G10: ="str" & A10 & " = comExcelWorksheet.Cells(intRow" & A10 & ", intColTestColumn).Value" -> str0 = comExcelWorksheet.Cells(intRow0, intColTestColumn).Value | H10: ="Public Property Get get" & A10 & "() : get" & A10 & " = str" & A10 & " : End Property" -> Public Property Get get0() : get0 = str0 : End Property
A11: =Test_Data!D14 -> Automation Ref | B11: ="intRow" & A11 & ", " -> intRowAutomation Ref, | C11: =C10 &B11 -> intRowProcess, intRowExecutionFlag, intRowLastRunTimeandStatus, intRowLastRunEmployeeNo, intRowLastRunErrorMessage, intRowDefectDescription, intRowAutomationComments, intRowQAComments, intRow0, intRowAutomation Ref, | D11: ="str" & A11 & ", " -> strAutomation Ref, | E11: =E10 &D11 -> strProcess, strExecutionFlag, strLastRunTimeandStatus, strLastRunEmployeeNo, strLastRunErrorMessage, strDefectDescription, strAutomationComments, strQAComments, str0, strAutomation Ref, | F11: ="intRow" & A11 & " = comExcelWorksheet.Range(""" & A11 & """).Row" -> intRowAutomation Ref = comExcelWorksheet.Range("Automation Ref").Row | G11: ="str" & A11 & " = comExcelWorksheet.Cells(intRow" & A11 & ", intColTestColumn).Value" -> strAutomation Ref = comExcelWorksheet.Cells(intRowAutomation Ref, intColTestColumn).Value | H11: ="Public Property Get get" & A11 & "() : get" & A11 & " = str" & A11 & " : End Property" -> Public Property Get getAutomation Ref() : getAutomation Ref = strAutomation Ref : End Property
A12: =Test_Data!D15 -> Login_Username | B12: ="intRow" & A12 & ", " -> intRowLogin_Username, | C12: =C11 &B12 -> intRowProcess, intRowExecutionFlag, intRowLastRunTimeandStatus, intRowLastRunEmployeeNo, intRowLastRunErrorMessage, intRowDefectDescription, intRowAutomationComments, intRowQAComments, intRow0, intRowAutomation Ref, intRowLogin_Username, | D12: ="str" & A12 & ", " -> strLogin_Username, | E12: =E11 &D12 -> strProcess, strExecutionFlag, strLastRunTimeandStatus, strLastRunEmployeeNo, strLastRunErrorMessage, strDefectDescription, strAutomationComments, strQAComments, str0, strAutomation Ref, strLogin_Username, | F12: ="intRow" & A12 & " = comExcelWorksheet.Range(""" & A12 & """).Row" -> intRowLogin_Username = comExcelWorksheet.Range("Login_Username").Row | G12: ="str" & A12 & " = comExcelWorksheet.Cells(intRow" & A12 & ", intColTestColumn).Value" -> strLogin_Username = comExcelWorksheet.Cells(intRowLogin_Username, intColTestColumn).Value | H12: ="Public Property Get get" & A12 & "() : get" & A12 & " = str" & A12 & " : End Property" -> Public Property Get getLogin_Username() : getLogin_Username = strLogin_Username : End Property
A13: =Test_Data!D16 -> Login_Password | B13: ="intRow" & A13 & ", " -> intRowLogin_Password, | C13: =C12 &B13 -> intRowProcess, intRowExecutionFlag, intRowLastRunTimeandStatus, intRowLastRunEmployeeNo, intRowLastRunErrorMessage, intRowDefectDescription, intRowAutomationComments, intRowQAComments, intRow0, intRowAutomation Ref, intRowLogin_Username, intRowLogin_Password, | D13: ="str" & A13 & ", " -> strLogin_Password, | E13: =E12 &D13 -> strProcess, strExecutionFlag, strLastRunTimeandStatus, strLastRunEmployeeNo, strLastRunErrorMessage, strDefectDescription, strAutomationComments, strQAComments, str0, strAutomation Ref, strLogin_Username, strLogin_Password, | F13: ="intRow" & A13 & " = comExcelWorksheet.Range(""" & A13 & """).Row" -> intRowLogin_Password = comExcelWorksheet.Range("Login_Password").Row | G13: ="str" & A13 & " = comExcelWorksheet.Cells(intRow" & A13 & ", intColTestColumn).Value" -> strLogin_Password = comExcelWorksheet.Cells(intRowLogin_Password, intColTestColumn).Value | H13: ="Public Property Get get" & A13 & "() : get" & A13 & " = str" & A13 & " : End Property" -> Public Property Get getLogin_Password() : getLogin_Password = strLogin_Password : End Property
A14: =Test_Data!D17 -> SupervisoryOrganisation_SupervisoryOrganisation | B14: ="intRow" & A14 & ", " -> intRowSupervisoryOrganisation_SupervisoryOrganisation, | C14: =C13 &B14 -> intRowProcess, intRowExecutionFlag, intRowLastRunTimeandStatus, intRowLastRunEmployeeNo, intRowLastRunErrorMessage, intRowDefectDescription, intRowAutomationComments, intRowQAComments, intRow0, intRowAutomation Ref, intRowLogin_Username, intRowLogin_Password, intRowSupervisoryOrganisation_SupervisoryOrganisation, | D14: ="str" & A14 & ", " -> strSupervisoryOrganisation_SupervisoryOrganisation, | E14: =E13 &D14 -> strProcess, strExecutionFlag, strLastRunTimeandStatus, strLastRunEmployeeNo, strLastRunErrorMessage, strDefectDescription, strAutomationComments, strQAComments, str0, strAutomation Ref, strLogin_Username, strLogin_Password, strSupervisoryOrganisation_SupervisoryOrganisation, | F14: ="intRow" & A14 & " = comExcelWorksheet.Range(""" & A14 & """).Row" -> intRowSupervisoryOrganisation_SupervisoryOrganisation = comExcelWorksheet.Range("SupervisoryOrganisation_SupervisoryOrganisation").Row | G14: ="str" & A14 & " = comExcelWorksheet.Cells(intRow" & A14 & ", intColTestColumn).Value" -> strSupervisoryOrganisation_SupervisoryOrganisation = comExcelWorksheet.Cells(intRowSupervisoryOrganisation_SupervisoryOrganisation, intColTestColumn).Value | H14: ="Public Property Get get" & A14 & "() : get" & A14 & " = str" & A14 & " : End Property" -> Public Property Get getSupervisoryOrganisation_SupervisoryOrganisation() : getSupervisoryOrganisation_SupervisoryOrganisation = strSupervisoryOrganisation_SupervisoryOrganisation : End Property
A15: =Test_Data!#REF! -> #REF! | B15: ="intRow" & A15 & ", " -> #REF! | C15: =C14 &B15 -> #REF! | D15: ="str" & A15 & ", " -> #REF! | E15: =E14 &D15 -> #REF! | F15: ="intRow" & A15 & " = comExcelWorksheet.Range(""" & A15 & """).Row" -> #REF! | G15: ="str" & A15 & " = comExcelWorksheet.Cells(intRow" & A15 & ", intColTestColumn).Value" -> #REF! | H15: ="Public Property Get get" & A15 & "() : get" & A15 & " = str" & A15 & " : End Property" -> #REF!
A16: =Test_Data!D18 -> LegalNameInformation_GivenName | B16: ="intRow" & A16 & ", " -> intRowLegalNameInformation_GivenName, | C16: =C15 &B16 -> #REF! | D16: ="str" & A16 & ", " -> strLegalNameInformation_GivenName, | E16: =E15 &D16 -> #REF! | F16: ="intRow" & A16 & " = comExcelWorksheet.Range(""" & A16 & """).Row" -> intRowLegalNameInformation_GivenName = comExcelWorksheet.Range("LegalNameInformation_GivenName").Row | G16: ="str" & A16 & " = comExcelWorksheet.Cells(intRow" & A16 & ", intColTestColumn).Value" -> strLegalNameInformation_GivenName = comExcelWorksheet.Cells(intRowLegalNameInformation_GivenName, intColTestColumn).Value | H16: ="Public Property Get get" & A16 & "() : get" & A16 & " = str" & A16 & " : End Property" -> Public Property Get getLegalNameInformation_GivenName() : getLegalNameInformation_GivenName = strLegalNameInformation_GivenName : End Property
A17: =Test_Data!#REF! -> #REF! | B17: ="intRow" & A17 & ", " -> #REF! | C17: =C16 &B17 -> #REF! | D17: ="str" & A17 & ", " -> #REF! | E17: =E16 &D17 -> #REF! | F17: ="intRow" & A17 & " = comExcelWorksheet.Range(""" & A17 & """).Row" -> #REF! | G17: ="str" & A17 & " = comExcelWorksheet.Cells(intRow" & A17 & ", intColTestColumn).Value" -> #REF! | H17: ="Public Property Get get" & A17 & "() : get" & A17 & " = str" & A17 & " : End Property" -> #REF!
A18: =Test_Data!D19 -> LegalNameInformation_FirstLastName | B18: ="intRow" & A18 & ", " -> intRowLegalNameInformation_FirstLastName, | C18: =C17 &B18 -> #REF! | D18: ="str" & A18 & ", " -> strLegalNameInformation_FirstLastName, | E18: =E17 &D18 -> #REF! | F18: ="intRow" & A18 & " = comExcelWorksheet.Range(""" & A18 & """).Row" -> intRowLegalNameInformation_FirstLastName = comExcelWorksheet.Range("LegalNameInformation_FirstLastName").Row | G18: ="str" & A18 & " = comExcelWorksheet.Cells(intRow" & A18 & ", intColTestColumn).Value" -> strLegalNameInformation_FirstLastName = comExcelWorksheet.Cells(intRowLegalNameInformation_FirstLastName, intColTestColumn).Value | H18: ="Public Property Get get" & A18 & "() : get" & A18 & " = str" & A18 & " : End Property" -> Public Property Get getLegalNameInformation_FirstLastName() : getLegalNameInformation_FirstLastName = strLegalNameInformation_FirstLastName : End Property
A19: =Test_Data!#REF! -> #REF! | B19: ="intRow" & A19 & ", " -> #REF! | C19: =C18 &B19 -> #REF! | D19: ="str" & A19 & ", " -> #REF! | E19: =E18 &D19 -> #REF! | F19: ="intRow" & A19 & " = comExcelWorksheet.Range(""" & A19 & """).Row" -> #REF! | G19: ="str" & A19 & " = comExcelWorksheet.Cells(intRow" & A19 & ", intColTestColumn).Value" -> #REF! | H19: ="Public Property Get get" & A19 & "() : get" & A19 & " = str" & A19 & " : End Property" -> #REF!
A20: =Test_Data!D22 -> ContactInformation_Phone_PhoneNumber | B20: ="intRow" & A20 & ", " -> intRowContactInformation_Phone_PhoneNumber, | C20: =C19 &B20 -> #REF! | D20: ="str" & A20 & ", " -> strContactInformation_Phone_PhoneNumber, | E20: =E19 &D20 -> #REF! | F20: ="intRow" & A20 & " = comExcelWorksheet.Range(""" & A20 & """).Row" -> intRowContactInformation_Phone_PhoneNumber = comExcelWorksheet.Range("ContactInformation_Phone_PhoneNumber").Row | G20: ="str" & A20 & " = comExcelWorksheet.Cells(intRow" & A20 & ", intColTestColumn).Value" -> strContactInformation_Phone_PhoneNumber = comExcelWorksheet.Cells(intRowContactInformation_Phone_PhoneNumber, intColTestColumn).Value | H20: ="Public Property Get get" & A20 & "() : get" & A20 & " = str" & A20 & " : End Property" -> Public Property Get getContactInformation_Phone_PhoneNumber() : getContactInformation_Phone_PhoneNumber = strContactInformation_Phone_PhoneNumber : End Property
A21: =Test_Data!D23 -> ContactInformation_Phone_PhoneDevice | B21: ="intRow" & A21 & ", " -> intRowContactInformation_Phone_PhoneDevice, | C21: =C20 &B21 -> #REF! | D21: ="str" & A21 & ", " -> strContactInformation_Phone_PhoneDevice, | E21: =E20 &D21 -> #REF! | F21: ="intRow" & A21 & " = comExcelWorksheet.Range(""" & A21 & """).Row" -> intRowContactInformation_Phone_PhoneDevice = comExcelWorksheet.Range("ContactInformation_Phone_PhoneDevice").Row | G21: ="str" & A21 & " = comExcelWorksheet.Cells(intRow" & A21 & ", intColTestColumn).Value" -> strContactInformation_Phone_PhoneDevice = comExcelWorksheet.Cells(intRowContactInformation_Phone_PhoneDevice, intColTestColumn).Value | H21: ="Public Property Get get" & A21 & "() : get" & A21 & " = str" & A21 & " : End Property" -> Public Property Get getContactInformation_Phone_PhoneDevice() : getContactInformation_Phone_PhoneDevice = strContactInformation_Phone_PhoneDevice : End Property
A22: =Test_Data!D24 -> ContactInformation_Phone_Type | B22: ="intRow" & A22 & ", " -> intRowContactInformation_Phone_Type, | C22: =C21 &B22 -> #REF! | D22: ="str" & A22 & ", " -> strContactInformation_Phone_Type, | E22: =E21 &D22 -> #REF! | F22: ="intRow" & A22 & " = comExcelWorksheet.Range(""" & A22 & """).Row" -> intRowContactInformation_Phone_Type = comExcelWorksheet.Range("ContactInformation_Phone_Type").Row | G22: ="str" & A22 & " = comExcelWorksheet.Cells(intRow" & A22 & ", intColTestColumn).Value" -> strContactInformation_Phone_Type = comExcelWorksheet.Cells(intRowContactInformation_Phone_Type, intColTestColumn).Value | H22: ="Public Property Get get" & A22 & "() : get" & A22 & " = str" & A22 & " : End Property" -> Public Property Get getContactInformation_Phone_Type() : getContactInformation_Phone_Type = strContactInformation_Phone_Type : End Property
A23: =Test_Data!D25 -> ContactInformation_Address_EffectiveDate | B23: ="intRow" & A23 & ", " -> intRowContactInformation_Address_EffectiveDate, | C23: =C22 &B23 -> #REF! | D23: ="str" & A23 & ", " -> strContactInformation_Address_EffectiveDate, | E23: =E22 &D23 -> #REF! | F23: ="intRow" & A23 & " = comExcelWorksheet.Range(""" & A23 & """).Row" -> intRowContactInformation_Address_EffectiveDate = comExcelWorksheet.Range("ContactInformation_Address_EffectiveDate").Row | G23: ="str" & A23 & " = comExcelWorksheet.Cells(intRow" & A23 & ", intColTestColumn).Value" -> strContactInformation_Address_EffectiveDate = comExcelWorksheet.Cells(intRowContactInformation_Address_EffectiveDate, intColTestColumn).Value | H23: ="Public Property Get get" & A23 & "() : get" & A23 & " = str" & A23 & " : End Property" -> Public Property Get getContactInformation_Address_EffectiveDate() : getContactInformation_Address_EffectiveDate = strContactInformation_Address_EffectiveDate : End Property
A24: =Test_Data!D26 -> ContactInformation_Address_Country | B24: ="intRow" & A24 & ", " -> intRowContactInformation_Address_Country, | C24: =C23 &B24 -> #REF! | D24: ="str" & A24 & ", " -> strContactInformation_Address_Country, | E24: =E23 &D24 -> #REF! | F24: ="intRow" & A24 & " = comExcelWorksheet.Range(""" & A24 & """).Row" -> intRowContactInformation_Address_Country = comExcelWorksheet.Range("ContactInformation_Address_Country").Row | G24: ="str" & A24 & " = comExcelWorksheet.Cells(intRow" & A24 & ", intColTestColumn).Value" -> strContactInformation_Address_Country = comExcelWorksheet.Cells(intRowContactInformation_Address_Country, intColTestColumn).Value | H24: ="Public Property Get get" & A24 & "() : get" & A24 & " = str" & A24 & " : End Property" -> Public Property Get getContactInformation_Address_Country() : getContactInformation_Address_Country = strContactInformation_Address_Country : End Property
A25: =Test_Data!D27 -> ContactInformation_Address_NameOfStreet | B25: ="intRow" & A25 & ", " -> intRowContactInformation_Address_NameOfStreet, | C25: =C24 &B25 -> #REF! | D25: ="str" & A25 & ", " -> strContactInformation_Address_NameOfStreet, | E25: =E24 &D25 -> #REF! | F25: ="intRow" & A25 & " = comExcelWorksheet.Range(""" & A25 & """).Row" -> intRowContactInformation_Address_NameOfStreet = comExcelWorksheet.Range("ContactInformation_Address_NameOfStreet").Row | G25: ="str" & A25 & " = comExcelWorksheet.Cells(intRow" & A25 & ", intColTestColumn).Value" -> strContactInformation_Address_NameOfStreet = comExcelWorksheet.Cells(intRowContactInformation_Address_NameOfStreet, intColTestColumn).Value | H25: ="Public Property Get get" & A25 & "() : get" & A25 & " = str" & A25 & " : End Property" -> Public Property Get getContactInformation_Address_NameOfStreet() : getContactInformation_Address_NameOfStreet = strContactInformation_Address_NameOfStreet : End Property
A26: =Test_Data!#REF! -> #REF! | B26: ="intRow" & A26 & ", " -> #REF! | C26: =C25 &B26 -> #REF! | D26: ="str" & A26 & ", " -> #REF! | E26: =E25 &D26 -> #REF! | F26: ="intRow" & A26 & " = comExcelWorksheet.Range(""" & A26 & """).Row" -> #REF! | G26: ="str" & A26 & " = comExcelWorksheet.Cells(intRow" & A26 & ", intColTestColumn).Value" -> #REF! | H26: ="Public Property Get get" & A26 & "() : get" & A26 & " = str" & A26 & " : End Property" -> #REF!
A27: =Test_Data!D30 -> ContactInformation_Address_City | B27: ="intRow" & A27 & ", " -> intRowContactInformation_Address_City, | C27: =C26 &B27 -> #REF! | D27: ="str" & A27 & ", " -> strContactInformation_Address_City, | E27: =E26 &D27 -> #REF! | F27: ="intRow" & A27 & " = comExcelWorksheet.Range(""" & A27 & """).Row" -> intRowContactInformation_Address_City = comExcelWorksheet.Range("ContactInformation_Address_City").Row | G27: ="str" & A27 & " = comExcelWorksheet.Cells(intRow" & A27 & ", intColTestColumn).Value" -> strContactInformation_Address_City = comExcelWorksheet.Cells(intRowContactInformation_Address_City, intColTestColumn).Value | H27: ="Public Property Get get" & A27 & "() : get" & A27 & " = str" & A27 & " : End Property" -> Public Property Get getContactInformation_Address_City() : getContactInformation_Address_City = strContactInformation_Address_City : End Property
A28: =Test_Data!D29 -> ContactInformation_Address_PostalCode | B28: ="intRow" & A28 & ", " -> intRowContactInformation_Address_PostalCode, | C28: =C27 &B28 -> #REF! | D28: ="str" & A28 & ", " -> strContactInformation_Address_PostalCode, | E28: =E27 &D28 -> #REF! | F28: ="intRow" & A28 & " = comExcelWorksheet.Range(""" & A28 & """).Row" -> intRowContactInformation_Address_PostalCode = comExcelWorksheet.Range("ContactInformation_Address_PostalCode").Row | G28: ="str" & A28 & " = comExcelWorksheet.Cells(intRow" & A28 & ", intColTestColumn).Value" -> strContactInformation_Address_PostalCode = comExcelWorksheet.Cells(intRowContactInformation_Address_PostalCode, intColTestColumn).Value | H28: ="Public Property Get get" & A28 & "() : get" & A28 & " = str" & A28 & " : End Property" -> Public Property Get getContactInformation_Address_PostalCode() : getContactInformation_Address_PostalCode = strContactInformation_Address_PostalCode : End Property
A29: =Test_Data!D32 -> ContactInformation_Address_Type | B29: ="intRow" & A29 & ", " -> intRowContactInformation_Address_Type, | C29: =C28 &B29 -> #REF! | D29: ="str" & A29 & ", " -> strContactInformation_Address_Type, | E29: =E28 &D29 -> #REF! | F29: ="intRow" & A29 & " = comExcelWorksheet.Range(""" & A29 & """).Row" -> intRowContactInformation_Address_Type = comExcelWorksheet.Range("ContactInformation_Address_Type").Row | G29: ="str" & A29 & " = comExcelWorksheet.Cells(intRow" & A29 & ", intColTestColumn).Value" -> strContactInformation_Address_Type = comExcelWorksheet.Cells(intRowContactInformation_Address_Type, intColTestColumn).Value | H29: ="Public Property Get get" & A29 & "() : get" & A29 & " = str" & A29 & " : End Property" -> Public Property Get getContactInformation_Address_Type() : getContactInformation_Address_Type = strContactInformation_Address_Type : End Property
A30: =Test_Data!D33 -> ContactInformation_Address_UseFor | B30: ="intRow" & A30 & ", " -> intRowContactInformation_Address_UseFor, | C30: =C29 &B30 -> #REF! | D30: ="str" & A30 & ", " -> strContactInformation_Address_UseFor, | E30: =E29 &D30 -> #REF! | F30: ="intRow" & A30 & " = comExcelWorksheet.Range(""" & A30 & """).Row" -> intRowContactInformation_Address_UseFor = comExcelWorksheet.Range("ContactInformation_Address_UseFor").Row | G30: ="str" & A30 & " = comExcelWorksheet.Cells(intRow" & A30 & ", intColTestColumn).Value" -> strContactInformation_Address_UseFor = comExcelWorksheet.Cells(intRowContactInformation_Address_UseFor, intColTestColumn).Value | H30: ="Public Property Get get" & A30 & "() : get" & A30 & " = str" & A30 & " : End Property" -> Public Property Get getContactInformation_Address_UseFor() : getContactInformation_Address_UseFor = strContactInformation_Address_UseFor : End Property
A31: =Test_Data!D34 -> ContactInformation_Email_EmailAddress | B31: ="intRow" & A31 & ", " -> intRowContactInformation_Email_EmailAddress, | C31: =C30 &B31 -> #REF! | D31: ="str" & A31 & ", " -> strContactInformation_Email_EmailAddress, | E31: =E30 &D31 -> #REF! | F31: ="intRow" & A31 & " = comExcelWorksheet.Range(""" & A31 & """).Row" -> intRowContactInformation_Email_EmailAddress = comExcelWorksheet.Range("ContactInformation_Email_EmailAddress").Row | G31: ="str" & A31 & " = comExcelWorksheet.Cells(intRow" & A31 & ", intColTestColumn).Value" -> strContactInformation_Email_EmailAddress = comExcelWorksheet.Cells(intRowContactInformation_Email_EmailAddress, intColTestColumn).Value | H31: ="Public Property Get get" & A31 & "() : get" & A31 & " = str" & A31 & " : End Property" -> Public Property Get getContactInformation_Email_EmailAddress() : getContactInformation_Email_EmailAddress = strContactInformation_Email_EmailAddress : End Property
A32: =Test_Data!D35 -> ContactInformation_Email_Type | B32: ="intRow" & A32 & ", " -> intRowContactInformation_Email_Type, | C32: =C31 &B32 -> #REF! | D32: ="str" & A32 & ", " -> strContactInformation_Email_Type, | E32: =E31 &D32 -> #REF! | F32: ="intRow" & A32 & " = comExcelWorksheet.Range(""" & A32 & """).Row" -> intRowContactInformation_Email_Type = comExcelWorksheet.Range("ContactInformation_Email_Type").Row | G32: ="str" & A32 & " = comExcelWorksheet.Cells(intRow" & A32 & ", intColTestColumn).Value" -> strContactInformation_Email_Type = comExcelWorksheet.Cells(intRowContactInformation_Email_Type, intColTestColumn).Value | H32: ="Public Property Get get" & A32 & "() : get" & A32 & " = str" & A32 & " : End Property" -> Public Property Get getContactInformation_Email_Type() : getContactInformation_Email_Type = strContactInformation_Email_Type : End Property
A33: =Test_Data!D36 -> JobDetails_HireDate | B33: ="intRow" & A33 & ", " -> intRowJobDetails_HireDate, | C33: =C32 &B33 -> #REF! | D33: ="str" & A33 & ", " -> strJobDetails_HireDate, | E33: =E32 &D33 -> #REF! | F33: ="intRow" & A33 & " = comExcelWorksheet.Range(""" & A33 & """).Row" -> intRowJobDetails_HireDate = comExcelWorksheet.Range("JobDetails_HireDate").Row | G33: ="str" & A33 & " = comExcelWorksheet.Cells(intRow" & A33 & ", intColTestColumn).Value" -> strJobDetails_HireDate = comExcelWorksheet.Cells(intRowJobDetails_HireDate, intColTestColumn).Value | H33: ="Public Property Get get" & A33 & "() : get" & A33 & " = str" & A33 & " : End Property" -> Public Property Get getJobDetails_HireDate() : getJobDetails_HireDate = strJobDetails_HireDate : End Property
A34: =Test_Data!D37 -> JobDetails_Reason | B34: ="intRow" & A34 & ", " -> intRowJobDetails_Reason, | C34: =C33 &B34 -> #REF! | D34: ="str" & A34 & ", " -> strJobDetails_Reason, | E34: =E33 &D34 -> #REF! | F34: ="intRow" & A34 & " = comExcelWorksheet.Range(""" & A34 & """).Row" -> intRowJobDetails_Reason = comExcelWorksheet.Range("JobDetails_Reason").Row | G34: ="str" & A34 & " = comExcelWorksheet.Cells(intRow" & A34 & ", intColTestColumn).Value" -> strJobDetails_Reason = comExcelWorksheet.Cells(intRowJobDetails_Reason, intColTestColumn).Value | H34: ="Public Property Get get" & A34 & "() : get" & A34 & " = str" & A34 & " : End Property" -> Public Property Get getJobDetails_Reason() : getJobDetails_Reason = strJobDetails_Reason : End Property
A35: =Test_Data!D38 -> JobDetails_Position | B35: ="intRow" & A35 & ", " -> intRowJobDetails_Position, | C35: =C34 &B35 -> #REF! | D35: ="str" & A35 & ", " -> strJobDetails_Position, | E35: =E34 &D35 -> #REF! | F35: ="intRow" & A35 & " = comExcelWorksheet.Range(""" & A35 & """).Row" -> intRowJobDetails_Position = comExcelWorksheet.Range("JobDetails_Position").Row | G35: ="str" & A35 & " = comExcelWorksheet.Cells(intRow" & A35 & ", intColTestColumn).Value" -> strJobDetails_Position = comExcelWorksheet.Cells(intRowJobDetails_Position, intColTestColumn).Value | H35: ="Public Property Get get" & A35 & "() : get" & A35 & " = str" & A35 & " : End Property" -> Public Property Get getJobDetails_Position() : getJobDetails_Position = strJobDetails_Position : End Property
A36: =Test_Data!D39 -> JobDetails_EmployeeType | B36: ="intRow" & A36 & ", " -> intRowJobDetails_EmployeeType, | C36: =C35 &B36 -> #REF! | D36: ="str" & A36 & ", " -> strJobDetails_EmployeeType, | E36: =E35 &D36 -> #REF! | F36: ="intRow" & A36 & " = comExcelWorksheet.Range(""" & A36 & """).Row" -> intRowJobDetails_EmployeeType = comExcelWorksheet.Range("JobDetails_EmployeeType").Row | G36: ="str" & A36 & " = comExcelWorksheet.Cells(intRow" & A36 & ", intColTestColumn).Value" -> strJobDetails_EmployeeType = comExcelWorksheet.Cells(intRowJobDetails_EmployeeType, intColTestColumn).Value | H36: ="Public Property Get get" & A36 & "() : get" & A36 & " = str" & A36 & " : End Property" -> Public Property Get getJobDetails_EmployeeType() : getJobDetails_EmployeeType = strJobDetails_EmployeeType : End Property
A37: =Test_Data!D40 -> JobDetails_JobProfile | B37: ="intRow" & A37 & ", " -> intRowJobDetails_JobProfile, | C37: =C36 &B37 -> #REF! | D37: ="str" & A37 & ", " -> strJobDetails_JobProfile, | E37: =E36 &D37 -> #REF! | F37: ="intRow" & A37 & " = comExcelWorksheet.Range(""" & A37 & """).Row" -> intRowJobDetails_JobProfile = comExcelWorksheet.Range("JobDetails_JobProfile").Row | G37: ="str" & A37 & " = comExcelWorksheet.Cells(intRow" & A37 & ", intColTestColumn).Value" -> strJobDetails_JobProfile = comExcelWorksheet.Cells(intRowJobDetails_JobProfile, intColTestColumn).Value | H37: ="Public Property Get get" & A37 & "() : get" & A37 & " = str" & A37 & " : End Property" -> Public Property Get getJobDetails_JobProfile() : getJobDetails_JobProfile = strJobDetails_JobProfile : End Property
A38: =Test_Data!D41 -> JobDetails_TimeType | B38: ="intRow" & A38 & ", " -> intRowJobDetails_TimeType, | C38: =C37 &B38 -> #REF! | D38: ="str" & A38 & ", " -> strJobDetails_TimeType, | E38: =E37 &D38 -> #REF! | F38: ="intRow" & A38 & " = comExcelWorksheet.Range(""" & A38 & """).Row" -> intRowJobDetails_TimeType = comExcelWorksheet.Range("JobDetails_TimeType").Row | G38: ="str" & A38 & " = comExcelWorksheet.Cells(intRow" & A38 & ", intColTestColumn).Value" -> strJobDetails_TimeType = comExcelWorksheet.Cells(intRowJobDetails_TimeType, intColTestColumn).Value | H38: ="Public Property Get get" & A38 & "() : get" & A38 & " = str" & A38 & " : End Property" -> Public Property Get getJobDetails_TimeType() : getJobDetails_TimeType = strJobDetails_TimeType : End Property
A39: =Test_Data!D42 -> JobDetails_Location | B39: ="intRow" & A39 & ", " -> intRowJobDetails_Location, | C39: =C38 &B39 -> #REF! | D39: ="str" & A39 & ", " -> strJobDetails_Location, | E39: =E38 &D39 -> #REF! | F39: ="intRow" & A39 & " = comExcelWorksheet.Range(""" & A39 & """).Row" -> intRowJobDetails_Location = comExcelWorksheet.Range("JobDetails_Location").Row | G39: ="str" & A39 & " = comExcelWorksheet.Cells(intRow" & A39 & ", intColTestColumn).Value" -> strJobDetails_Location = comExcelWorksheet.Cells(intRowJobDetails_Location, intColTestColumn).Value | H39: ="Public Property Get get" & A39 & "() : get" & A39 & " = str" & A39 & " : End Property" -> Public Property Get getJobDetails_Location() : getJobDetails_Location = strJobDetails_Location : End Property
A40: =Test_Data!D43 -> JobDetails_AdditionalInformation_ScheduledWeeklyHours | B40: ="intRow" & A40 & ", " -> intRowJobDetails_AdditionalInformation_ScheduledWeeklyHours, | C40: =C39 &B40 -> #REF! | D40: ="str" & A40 & ", " -> strJobDetails_AdditionalInformation_ScheduledWeeklyHours, | E40: =E39 &D40 -> #REF! | F40: ="intRow" & A40 & " = comExcelWorksheet.Range(""" & A40 & """).Row" -> intRowJobDetails_AdditionalInformation_ScheduledWeeklyHours = comExcelWorksheet.Range("JobDetails_AdditionalInformation_ScheduledWeeklyHours").Row | G40: ="str" & A40 & " = comExcelWorksheet.Cells(intRow" & A40 & ", intColTestColumn).Value" -> strJobDetails_AdditionalInformation_ScheduledWeeklyHours = comExcelWorksheet.Cells(intRowJobDetails_AdditionalInformation_ScheduledWeeklyHours, intColTestColumn).Value | H40: ="Public Property Get get" & A40 & "() : get" & A40 & " = str" & A40 & " : End Property" -> Public Property Get getJobDetails_AdditionalInformation_ScheduledWeeklyHours() : getJobDetails_AdditionalInformation_ScheduledWeeklyHours = strJobDetails_AdditionalInformation_ScheduledWeeklyHours : End Property
A41: =Test_Data!D45 -> JobDetails_AdditionalInformation_WorkShift | B41: ="intRow" & A41 & ", " -> intRowJobDetails_AdditionalInformation_WorkShift, | C41: =C40 &B41 -> #REF! | D41: ="str" & A41 & ", " -> strJobDetails_AdditionalInformation_WorkShift, | E41: =E40 &D41 -> #REF! | F41: ="intRow" & A41 & " = comExcelWorksheet.Range(""" & A41 & """).Row" -> intRowJobDetails_AdditionalInformation_WorkShift = comExcelWorksheet.Range("JobDetails_AdditionalInformation_WorkShift").Row | G41: ="str" & A41 & " = comExcelWorksheet.Cells(intRow" & A41 & ", intColTestColumn).Value" -> strJobDetails_AdditionalInformation_WorkShift = comExcelWorksheet.Cells(intRowJobDetails_AdditionalInformation_WorkShift, intColTestColumn).Value | H41: ="Public Property Get get" & A41 & "() : get" & A41 & " = str" & A41 & " : End Property" -> Public Property Get getJobDetails_AdditionalInformation_WorkShift() : getJobDetails_AdditionalInformation_WorkShift = strJobDetails_AdditionalInformation_WorkShift : End Property
A42: =Test_Data!D46 -> JobDetails_AdditionalInformation_EndEmploymentDate | B42: ="intRow" & A42 & ", " -> intRowJobDetails_AdditionalInformation_EndEmploymentDate, | C42: =C41 &B42 -> #REF! | D42: ="str" & A42 & ", " -> strJobDetails_AdditionalInformation_EndEmploymentDate, | E42: =E41 &D42 -> #REF! | F42: ="intRow" & A42 & " = comExcelWorksheet.Range(""" & A42 & """).Row" -> intRowJobDetails_AdditionalInformation_EndEmploymentDate = comExcelWorksheet.Range("JobDetails_AdditionalInformation_EndEmploymentDate").Row | G42: ="str" & A42 & " = comExcelWorksheet.Cells(intRow" & A42 & ", intColTestColumn).Value" -> strJobDetails_AdditionalInformation_EndEmploymentDate = comExcelWorksheet.Cells(intRowJobDetails_AdditionalInformation_EndEmploymentDate, intColTestColumn).Value | H42: ="Public Property Get get" & A42 & "() : get" & A42 & " = str" & A42 & " : End Property" -> Public Property Get getJobDetails_AdditionalInformation_EndEmploymentDate() : getJobDetails_AdditionalInformation_EndEmploymentDate = strJobDetails_AdditionalInformation_EndEmploymentDate : End Property
A43: =Test_Data!D47 -> JobDetails_AdditionalInformation_Comments | B43: ="intRow" & A43 & ", " -> intRowJobDetails_AdditionalInformation_Comments, | C43: =C42 &B43 -> #REF! | D43: ="str" & A43 & ", " -> strJobDetails_AdditionalInformation_Comments, | E43: =E42 &D43 -> #REF! | F43: ="intRow" & A43 & " = comExcelWorksheet.Range(""" & A43 & """).Row" -> intRowJobDetails_AdditionalInformation_Comments = comExcelWorksheet.Range("JobDetails_AdditionalInformation_Comments").Row | G43: ="str" & A43 & " = comExcelWorksheet.Cells(intRow" & A43 & ", intColTestColumn).Value" -> strJobDetails_AdditionalInformation_Comments = comExcelWorksheet.Cells(intRowJobDetails_AdditionalInformation_Comments, intColTestColumn).Value | H43: ="Public Property Get get" & A43 & "() : get" & A43 & " = str" & A43 & " : End Property" -> Public Property Get getJobDetails_AdditionalInformation_Comments() : getJobDetails_AdditionalInformation_Comments = strJobDetails_AdditionalInformation_Comments : End Property
A44: =Test_Data!#REF! -> #REF! | B44: ="intRow" & A44 & ", " -> #REF! | C44: =C43 &B44 -> #REF! | D44: ="str" & A44 & ", " -> #REF! | E44: =E43 &D44 -> #REF! | F44: ="intRow" & A44 & " = comExcelWorksheet.Range(""" & A44 & """).Row" -> #REF! | G44: ="str" & A44 & " = comExcelWorksheet.Cells(intRow" & A44 & ", intColTestColumn).Value" -> #REF! | H44: ="Public Property Get get" & A44 & "() : get" & A44 & " = str" & A44 & " : End Property" -> #REF!
A45: =Test_Data!#REF! -> #REF! | B45: ="intRow" & A45 & ", " -> #REF! | C45: =C44 &B45 -> #REF! | D45: ="str" & A45 & ", " -> #REF! | E45: =E44 &D45 -> #REF! | F45: ="intRow" & A45 & " = comExcelWorksheet.Range(""" & A45 & """).Row" -> #REF! | G45: ="str" & A45 & " = comExcelWorksheet.Cells(intRow" & A45 & ", intColTestColumn).Value" -> #REF! | H45: ="Public Property Get get" & A45 & "() : get" & A45 & " = str" & A45 & " : End Property" -> #REF!
A46: =Test_Data!D48 -> ChangeOrganizationAssignments_CostCenter | B46: ="intRow" & A46 & ", " -> intRowChangeOrganizationAssignments_CostCenter, | C46: =C45 &B46 -> #REF! | D46: ="str" & A46 & ", " -> strChangeOrganizationAssignments_CostCenter, | E46: =E45 &D46 -> #REF! | F46: ="intRow" & A46 & " = comExcelWorksheet.Range(""" & A46 & """).Row" -> intRowChangeOrganizationAssignments_CostCenter = comExcelWorksheet.Range("ChangeOrganizationAssignments_CostCenter").Row | G46: ="str" & A46 & " = comExcelWorksheet.Cells(intRow" & A46 & ", intColTestColumn).Value" -> strChangeOrganizationAssignments_CostCenter = comExcelWorksheet.Cells(intRowChangeOrganizationAssignments_CostCenter, intColTestColumn).Value | H46: ="Public Property Get get" & A46 & "() : get" & A46 & " = str" & A46 & " : End Property" -> Public Property Get getChangeOrganizationAssignments_CostCenter() : getChangeOrganizationAssignments_CostCenter = strChangeOrganizationAssignments_CostCenter : End Property
A47: =Test_Data!D49 -> ChangeOrganizationAssignments_DepartmentSection | B47: ="intRow" & A47 & ", " -> intRowChangeOrganizationAssignments_DepartmentSection, | C47: =C46 &B47 -> #REF! | D47: ="str" & A47 & ", " -> strChangeOrganizationAssignments_DepartmentSection, | E47: =E46 &D47 -> #REF! | F47: ="intRow" & A47 & " = comExcelWorksheet.Range(""" & A47 & """).Row" -> intRowChangeOrganizationAssignments_DepartmentSection = comExcelWorksheet.Range("ChangeOrganizationAssignments_DepartmentSection").Row | G47: ="str" & A47 & " = comExcelWorksheet.Cells(intRow" & A47 & ", intColTestColumn).Value" -> strChangeOrganizationAssignments_DepartmentSection = comExcelWorksheet.Cells(intRowChangeOrganizationAssignments_DepartmentSection, intColTestColumn).Value | H47: ="Public Property Get get" & A47 & "() : get" & A47 & " = str" & A47 & " : End Property" -> Public Property Get getChangeOrganizationAssignments_DepartmentSection() : getChangeOrganizationAssignments_DepartmentSection = strChangeOrganizationAssignments_DepartmentSection : End Property
A48: =Test_Data!D50 -> AssignPayGroup_ProposedPayGroup | B48: ="intRow" & A48 & ", " -> intRowAssignPayGroup_ProposedPayGroup, | C48: =C47 &B48 -> #REF! | D48: ="str" & A48 & ", " -> strAssignPayGroup_ProposedPayGroup, | E48: =E47 &D48 -> #REF! | F48: ="intRow" & A48 & " = comExcelWorksheet.Range(""" & A48 & """).Row" -> intRowAssignPayGroup_ProposedPayGroup = comExcelWorksheet.Range("AssignPayGroup_ProposedPayGroup").Row | G48: ="str" & A48 & " = comExcelWorksheet.Cells(intRow" & A48 & ", intColTestColumn).Value" -> strAssignPayGroup_ProposedPayGroup = comExcelWorksheet.Cells(intRowAssignPayGroup_ProposedPayGroup, intColTestColumn).Value | H48: ="Public Property Get get" & A48 & "() : get" & A48 & " = str" & A48 & " : End Property" -> Public Property Get getAssignPayGroup_ProposedPayGroup() : getAssignPayGroup_ProposedPayGroup = strAssignPayGroup_ProposedPayGroup : End Property
A49: =Test_Data!D53 -> AddProbationPeriod_ProbationEndDate | B49: ="intRow" & A49 & ", " -> intRowAddProbationPeriod_ProbationEndDate, | C49: =C48 &B49 -> #REF! | D49: ="str" & A49 & ", " -> strAddProbationPeriod_ProbationEndDate, | E49: =E48 &D49 -> #REF! | F49: ="intRow" & A49 & " = comExcelWorksheet.Range(""" & A49 & """).Row" -> intRowAddProbationPeriod_ProbationEndDate = comExcelWorksheet.Range("AddProbationPeriod_ProbationEndDate").Row | G49: ="str" & A49 & " = comExcelWorksheet.Cells(intRow" & A49 & ", intColTestColumn).Value" -> strAddProbationPeriod_ProbationEndDate = comExcelWorksheet.Cells(intRowAddProbationPeriod_ProbationEndDate, intColTestColumn).Value | H49: ="Public Property Get get" & A49 & "() : get" & A49 & " = str" & A49 & " : End Property" -> Public Property Get getAddProbationPeriod_ProbationEndDate() : getAddProbationPeriod_ProbationEndDate = strAddProbationPeriod_ProbationEndDate : End Property
A50: =Test_Data!#REF! -> #REF! | B50: ="intRow" & A50 & ", " -> #REF! | C50: =C49 &B50 -> #REF! | D50: ="str" & A50 & ", " -> #REF! | E50: =E49 &D50 -> #REF! | F50: ="intRow" & A50 & " = comExcelWorksheet.Range(""" & A50 & """).Row" -> #REF! | G50: ="str" & A50 & " = comExcelWorksheet.Cells(intRow" & A50 & ", intColTestColumn).Value" -> #REF! | H50: ="Public Property Get get" & A50 & "() : get" & A50 & " = str" & A50 & " : End Property" -> #REF!
A51: =Test_Data!#REF! -> #REF! | B51: ="intRow" & A51 & ", " -> #REF! | C51: =C50 &B51 -> #REF! | D51: ="str" & A51 & ", " -> #REF! | E51: =E50 &D51 -> #REF! | F51: ="intRow" & A51 & " = comExcelWorksheet.Range(""" & A51 & """).Row" -> #REF! | G51: ="str" & A51 & " = comExcelWorksheet.Cells(intRow" & A51 & ", intColTestColumn).Value" -> #REF! | H51: ="Public Property Get get" & A51 & "() : get" & A51 & " = str" & A51 & " : End Property" -> #REF!
A52: =Test_Data!#REF! -> #REF! | B52: ="intRow" & A52 & ", " -> #REF! | C52: =C51 &B52 -> #REF! | D52: ="str" & A52 & ", " -> #REF! | E52: =E51 &D52 -> #REF! | F52: ="intRow" & A52 & " = comExcelWorksheet.Range(""" & A52 & """).Row" -> #REF! | G52: ="str" & A52 & " = comExcelWorksheet.Cells(intRow" & A52 & ", intColTestColumn).Value" -> #REF! | H52: ="Public Property Get get" & A52 & "() : get" & A52 & " = str" & A52 & " : End Property" -> #REF!
A53: =Test_Data!#REF! -> #REF! | B53: ="intRow" & A53 & ", " -> #REF! | C53: =C52 &B53 -> #REF! | D53: ="str" & A53 & ", " -> #REF! | E53: =E52 &D53 -> #REF! | F53: ="intRow" & A53 & " = comExcelWorksheet.Range(""" & A53 & """).Row" -> #REF! | G53: ="str" & A53 & " = comExcelWorksheet.Cells(intRow" & A53 & ", intColTestColumn).Value" -> #REF! | H53: ="Public Property Get get" & A53 & "() : get" & A53 & " = str" & A53 & " : End Property" -> #REF!
A54: =Test_Data!#REF! -> #REF! | B54: ="intRow" & A54 & ", " -> #REF! | C54: =C53 &B54 -> #REF! | D54: ="str" & A54 & ", " -> #REF! | E54: =E53 &D54 -> #REF! | F54: ="intRow" & A54 & " = comExcelWorksheet.Range(""" & A54 & """).Row" -> #REF! | G54: ="str" & A54 & " = comExcelWorksheet.Cells(intRow" & A54 & ", intColTestColumn).Value" -> #REF! | H54: ="Public Property Get get" & A54 & "() : get" & A54 & " = str" & A54 & " : End Property" -> #REF!
A55: =Test_Data!#REF! -> #REF! | B55: ="intRow" & A55 & ", " -> #REF! | C55: =C54 &B55 -> #REF! | D55: ="str" & A55 & ", " -> #REF! | E55: =E54 &D55 -> #REF! | F55: ="intRow" & A55 & " = comExcelWorksheet.Range(""" & A55 & """).Row" -> #REF! | G55: ="str" & A55 & " = comExcelWorksheet.Cells(intRow" & A55 & ", intColTestColumn).Value" -> #REF! | H55: ="Public Property Get get" & A55 & "() : get" & A55 & " = str" & A55 & " : End Property" -> #REF!
A56: =Test_Data!D54 -> ProposeCompensationHire_Salary | B56: ="intRow" & A56 & ", " -> intRowProposeCompensationHire_Salary, | C56: =C55 &B56 -> #REF! | D56: ="str" & A56 & ", " -> strProposeCompensationHire_Salary, | E56: =E55 &D56 -> #REF! | F56: ="intRow" & A56 & " = comExcelWorksheet.Range(""" & A56 & """).Row" -> intRowProposeCompensationHire_Salary = comExcelWorksheet.Range("ProposeCompensationHire_Salary").Row | G56: ="str" & A56 & " = comExcelWorksheet.Cells(intRow" & A56 & ", intColTestColumn).Value" -> strProposeCompensationHire_Salary = comExcelWorksheet.Cells(intRowProposeCompensationHire_Salary, intColTestColumn).Value | H56: ="Public Property Get get" & A56 & "() : get" & A56 & " = str" & A56 & " : End Property" -> Public Property Get getProposeCompensationHire_Salary() : getProposeCompensationHire_Salary = strProposeCompensationHire_Salary : End Property
A57: =Test_Data!#REF! -> #REF! | B57: ="intRow" & A57 & ", " -> #REF! | C57: =C56 &B57 -> #REF! | D57: ="str" & A57 & ", " -> #REF! | E57: =E56 &D57 -> #REF! | F57: ="intRow" & A57 & " = comExcelWorksheet.Range(""" & A57 & """).Row" -> #REF! | G57: ="str" & A57 & " = comExcelWorksheet.Cells(intRow" & A57 & ", intColTestColumn).Value" -> #REF! | H57: ="Public Property Get get" & A57 & "() : get" & A57 & " = str" & A57 & " : End Property" -> #REF!
A58: =Test_Data!#REF! -> #REF! | B58: ="intRow" & A58 & ", " -> #REF! | C58: =C57 &B58 -> #REF! | D58: ="str" & A58 & ", " -> #REF! | E58: =E57 &D58 -> #REF! | F58: ="intRow" & A58 & " = comExcelWorksheet.Range(""" & A58 & """).Row" -> #REF! | G58: ="str" & A58 & " = comExcelWorksheet.Cells(intRow" & A58 & ", intColTestColumn).Value" -> #REF! | H58: ="Public Property Get get" & A58 & "() : get" & A58 & " = str" & A58 & " : End Property" -> #REF!
A59: =Test_Data!#REF! -> #REF! | B59: ="intRow" & A59 & ", " -> #REF! | C59: =C58 &B59 -> #REF! | D59: ="str" & A59 & ", " -> #REF! | E59: =E58 &D59 -> #REF! | F59: ="intRow" & A59 & " = comExcelWorksheet.Range(""" & A59 & """).Row" -> #REF! | G59: ="str" & A59 & " = comExcelWorksheet.Cells(intRow" & A59 & ", intColTestColumn).Value" -> #REF! | H59: ="Public Property Get get" & A59 & "() : get" & A59 & " = str" & A59 & " : End Property" -> #REF!
A60: =Test_Data!#REF! -> #REF! | B60: ="intRow" & A60 & ", " -> #REF! | C60: =C59 &B60 -> #REF! | D60: ="str" & A60 & ", " -> #REF! | E60: =E59 &D60 -> #REF! | F60: ="intRow" & A60 & " = comExcelWorksheet.Range(""" & A60 & """).Row" -> #REF! | G60: ="str" & A60 & " = comExcelWorksheet.Cells(intRow" & A60 & ", intColTestColumn).Value" -> #REF! | H60: ="Public Property Get get" & A60 & "() : get" & A60 & " = str" & A60 & " : End Property" -> #REF!
A61: =Test_Data!#REF! -> #REF! | B61: ="intRow" & A61 & ", " -> #REF! | C61: =C60 &B61 -> #REF! | D61: ="str" & A61 & ", " -> #REF! | E61: =E60 &D61 -> #REF! | F61: ="intRow" & A61 & " = comExcelWorksheet.Range(""" & A61 & """).Row" -> #REF! | G61: ="str" & A61 & " = comExcelWorksheet.Cells(intRow" & A61 & ", intColTestColumn).Value" -> #REF! | H61: ="Public Property Get get" & A61 & "() : get" & A61 & " = str" & A61 & " : End Property" -> #REF!
A62: =Test_Data!D55 -> ChangeMyPersonalInformation_Gender | B62: ="intRow" & A62 & ", " -> intRowChangeMyPersonalInformation_Gender, | C62: =C61 &B62 -> #REF! | D62: ="str" & A62 & ", " -> strChangeMyPersonalInformation_Gender, | E62: =E61 &D62 -> #REF! | F62: ="intRow" & A62 & " = comExcelWorksheet.Range(""" & A62 & """).Row" -> intRowChangeMyPersonalInformation_Gender = comExcelWorksheet.Range("ChangeMyPersonalInformation_Gender").Row | G62: ="str" & A62 & " = comExcelWorksheet.Cells(intRow" & A62 & ", intColTestColumn).Value" -> strChangeMyPersonalInformation_Gender = comExcelWorksheet.Cells(intRowChangeMyPersonalInformation_Gender, intColTestColumn).Value | H62: ="Public Property Get get" & A62 & "() : get" & A62 & " = str" & A62 & " : End Property" -> Public Property Get getChangeMyPersonalInformation_Gender() : getChangeMyPersonalInformation_Gender = strChangeMyPersonalInformation_Gender : End Property
A63: =Test_Data!D56 -> ChangeMyPersonalInformation_DateOfBirth | B63: ="intRow" & A63 & ", " -> intRowChangeMyPersonalInformation_DateOfBirth, | C63: =C62 &B63 -> #REF! | D63: ="str" & A63 & ", " -> strChangeMyPersonalInformation_DateOfBirth, | E63: =E62 &D63 -> #REF! | F63: ="intRow" & A63 & " = comExcelWorksheet.Range(""" & A63 & """).Row" -> intRowChangeMyPersonalInformation_DateOfBirth = comExcelWorksheet.Range("ChangeMyPersonalInformation_DateOfBirth").Row | G63: ="str" & A63 & " = comExcelWorksheet.Cells(intRow" & A63 & ", intColTestColumn).Value" -> strChangeMyPersonalInformation_DateOfBirth = comExcelWorksheet.Cells(intRowChangeMyPersonalInformation_DateOfBirth, intColTestColumn).Value | H63: ="Public Property Get get" & A63 & "() : get" & A63 & " = str" & A63 & " : End Property" -> Public Property Get getChangeMyPersonalInformation_DateOfBirth() : getChangeMyPersonalInformation_DateOfBirth = strChangeMyPersonalInformation_DateOfBirth : End Property
A64: =Test_Data!D60 -> ChangeMyPersonalInformation_MaritalStatus | B64: ="intRow" & A64 & ", " -> intRowChangeMyPersonalInformation_MaritalStatus, | C64: =C63 &B64 -> #REF! | D64: ="str" & A64 & ", " -> strChangeMyPersonalInformation_MaritalStatus, | E64: =E63 &D64 -> #REF! | F64: ="intRow" & A64 & " = comExcelWorksheet.Range(""" & A64 & """).Row" -> intRowChangeMyPersonalInformation_MaritalStatus = comExcelWorksheet.Range("ChangeMyPersonalInformation_MaritalStatus").Row | G64: ="str" & A64 & " = comExcelWorksheet.Cells(intRow" & A64 & ", intColTestColumn).Value" -> strChangeMyPersonalInformation_MaritalStatus = comExcelWorksheet.Cells(intRowChangeMyPersonalInformation_MaritalStatus, intColTestColumn).Value | H64: ="Public Property Get get" & A64 & "() : get" & A64 & " = str" & A64 & " : End Property" -> Public Property Get getChangeMyPersonalInformation_MaritalStatus() : getChangeMyPersonalInformation_MaritalStatus = strChangeMyPersonalInformation_MaritalStatus : End Property
A65: =Test_Data!D61 -> ChangeMyPersonalInformation_MaritalStatusDate | B65: ="intRow" & A65 & ", " -> intRowChangeMyPersonalInformation_MaritalStatusDate, | C65: =C64 &B65 -> #REF! | D65: ="str" & A65 & ", " -> strChangeMyPersonalInformation_MaritalStatusDate, | E65: =E64 &D65 -> #REF! | F65: ="intRow" & A65 & " = comExcelWorksheet.Range(""" & A65 & """).Row" -> intRowChangeMyPersonalInformation_MaritalStatusDate = comExcelWorksheet.Range("ChangeMyPersonalInformation_MaritalStatusDate").Row | G65: ="str" & A65 & " = comExcelWorksheet.Cells(intRow" & A65 & ", intColTestColumn).Value" -> strChangeMyPersonalInformation_MaritalStatusDate = comExcelWorksheet.Cells(intRowChangeMyPersonalInformation_MaritalStatusDate, intColTestColumn).Value | H65: ="Public Property Get get" & A65 & "() : get" & A65 & " = str" & A65 & " : End Property" -> Public Property Get getChangeMyPersonalInformation_MaritalStatusDate() : getChangeMyPersonalInformation_MaritalStatusDate = strChangeMyPersonalInformation_MaritalStatusDate : End Property
A66: =Test_Data!D59 -> ChangeMyPersonalInformation_CityOfBirth | B66: ="intRow" & A66 & ", " -> intRowChangeMyPersonalInformation_CityOfBirth, | C66: =C65 &B66 -> #REF! | D66: ="str" & A66 & ", " -> strChangeMyPersonalInformation_CityOfBirth, | E66: =E65 &D66 -> #REF! | F66: ="intRow" & A66 & " = comExcelWorksheet.Range(""" & A66 & """).Row" -> intRowChangeMyPersonalInformation_CityOfBirth = comExcelWorksheet.Range("ChangeMyPersonalInformation_CityOfBirth").Row | G66: ="str" & A66 & " = comExcelWorksheet.Cells(intRow" & A66 & ", intColTestColumn).Value" -> strChangeMyPersonalInformation_CityOfBirth = comExcelWorksheet.Cells(intRowChangeMyPersonalInformation_CityOfBirth, intColTestColumn).Value | H66: ="Public Property Get get" & A66 & "() : get" & A66 & " = str" & A66 & " : End Property" -> Public Property Get getChangeMyPersonalInformation_CityOfBirth() : getChangeMyPersonalInformation_CityOfBirth = strChangeMyPersonalInformation_CityOfBirth : End Property
A67: =Test_Data!D62 -> ChangeMyPersonalInformation_PrimaryNationality | B67: ="intRow" & A67 & ", " -> intRowChangeMyPersonalInformation_PrimaryNationality, | C67: =C66 &B67 -> #REF! | D67: ="str" & A67 & ", " -> strChangeMyPersonalInformation_PrimaryNationality, | E67: =E66 &D67 -> #REF! | F67: ="intRow" & A67 & " = comExcelWorksheet.Range(""" & A67 & """).Row" -> intRowChangeMyPersonalInformation_PrimaryNationality = comExcelWorksheet.Range("ChangeMyPersonalInformation_PrimaryNationality").Row | G67: ="str" & A67 & " = comExcelWorksheet.Cells(intRow" & A67 & ", intColTestColumn).Value" -> strChangeMyPersonalInformation_PrimaryNationality = comExcelWorksheet.Cells(intRowChangeMyPersonalInformation_PrimaryNationality, intColTestColumn).Value | H67: ="Public Property Get get" & A67 & "() : get" & A67 & " = str" & A67 & " : End Property" -> Public Property Get getChangeMyPersonalInformation_PrimaryNationality() : getChangeMyPersonalInformation_PrimaryNationality = strChangeMyPersonalInformation_PrimaryNationality : End Property
A68: =Test_Data!#REF! -> #REF! | B68: ="intRow" & A68 & ", " -> #REF! | C68: =C67 &B68 -> #REF! | D68: ="str" & A68 & ", " -> #REF! | E68: =E67 &D68 -> #REF! | F68: ="intRow" & A68 & " = comExcelWorksheet.Range(""" & A68 & """).Row" -> #REF! | G68: ="str" & A68 & " = comExcelWorksheet.Cells(intRow" & A68 & ", intColTestColumn).Value" -> #REF! | H68: ="Public Property Get get" & A68 & "() : get" & A68 & " = str" & A68 & " : End Property" -> #REF!
A69: =Test_Data!#REF! -> #REF! | B69: ="intRow" & A69 & ", " -> #REF! | C69: =C68 &B69 -> #REF! | D69: ="str" & A69 & ", " -> #REF! | E69: =E68 &D69 -> #REF! | F69: ="intRow" & A69 & " = comExcelWorksheet.Range(""" & A69 & """).Row" -> #REF! | G69: ="str" & A69 & " = comExcelWorksheet.Cells(intRow" & A69 & ", intColTestColumn).Value" -> #REF! | H69: ="Public Property Get get" & A69 & "() : get" & A69 & " = str" & A69 & " : End Property" -> #REF!
A70: =Test_Data!#REF! -> #REF! | B70: ="intRow" & A70 & ", " -> #REF! | C70: =C69 &B70 -> #REF! | D70: ="str" & A70 & ", " -> #REF! | E70: =E69 &D70 -> #REF! | F70: ="intRow" & A70 & " = comExcelWorksheet.Range(""" & A70 & """).Row" -> #REF! | G70: ="str" & A70 & " = comExcelWorksheet.Cells(intRow" & A70 & ", intColTestColumn).Value" -> #REF! | H70: ="Public Property Get get" & A70 & "() : get" & A70 & " = str" & A70 & " : End Property" -> #REF!
A71: =Test_Data!#REF! -> #REF! | B71: ="intRow" & A71 & ", " -> #REF! | C71: =C70 &B71 -> #REF! | D71: ="str" & A71 & ", " -> #REF! | E71: =E70 &D71 -> #REF! | F71: ="intRow" & A71 & " = comExcelWorksheet.Range(""" & A71 & """).Row" -> #REF! | G71: ="str" & A71 & " = comExcelWorksheet.Cells(intRow" & A71 & ", intColTestColumn).Value" -> #REF! | H71: ="Public Property Get get" & A71 & "() : get" & A71 & " = str" & A71 & " : End Property" -> #REF!
A72: =Test_Data!#REF! -> #REF! | B72: ="intRow" & A72 & ", " -> #REF! | C72: =C71 &B72 -> #REF! | D72: ="str" & A72 & ", " -> #REF! | E72: =E71 &D72 -> #REF! | F72: ="intRow" & A72 & " = comExcelWorksheet.Range(""" & A72 & """).Row" -> #REF! | G72: ="str" & A72 & " = comExcelWorksheet.Cells(intRow" & A72 & ", intColTestColumn).Value" -> #REF! | H72: ="Public Property Get get" & A72 & "() : get" & A72 & " = str" & A72 & " : End Property" -> #REF!
A73: =Test_Data!#REF! -> #REF! | B73: ="intRow" & A73 & ", " -> #REF! | C73: =C72 &B73 -> #REF! | D73: ="str" & A73 & ", " -> #REF! | E73: =E72 &D73 -> #REF! | F73: ="intRow" & A73 & " = comExcelWorksheet.Range(""" & A73 & """).Row" -> #REF! | G73: ="str" & A73 & " = comExcelWorksheet.Cells(intRow" & A73 & ", intColTestColumn).Value" -> #REF! | H73: ="Public Property Get get" & A73 & "() : get" & A73 & " = str" & A73 & " : End Property" -> #REF!
A74: =Test_Data!#REF! -> #REF! | B74: ="intRow" & A74 & ", " -> #REF! | C74: =C73 &B74 -> #REF! | D74: ="str" & A74 & ", " -> #REF! | E74: =E73 &D74 -> #REF! | F74: ="intRow" & A74 & " = comExcelWorksheet.Range(""" & A74 & """).Row" -> #REF! | G74: ="str" & A74 & " = comExcelWorksheet.Cells(intRow" & A74 & ", intColTestColumn).Value" -> #REF! | H74: ="Public Property Get get" & A74 & "() : get" & A74 & " = str" & A74 & " : End Property" -> #REF!
A75: =Test_Data!#REF! -> #REF! | B75: ="intRow" & A75 & ", " -> #REF! | C75: =C74 &B75 -> #REF! | D75: ="str" & A75 & ", " -> #REF! | E75: =E74 &D75 -> #REF! | F75: ="intRow" & A75 & " = comExcelWorksheet.Range(""" & A75 & """).Row" -> #REF! | G75: ="str" & A75 & " = comExcelWorksheet.Cells(intRow" & A75 & ", intColTestColumn).Value" -> #REF! | H75: ="Public Property Get get" & A75 & "() : get" & A75 & " = str" & A75 & " : End Property" -> #REF!
A76: =Test_Data!#REF! -> #REF! | B76: ="intRow" & A76 & ", " -> #REF! | C76: =C75 &B76 -> #REF! | D76: ="str" & A76 & ", " -> #REF! | E76: =E75 &D76 -> #REF! | F76: ="intRow" & A76 & " = comExcelWorksheet.Range(""" & A76 & """).Row" -> #REF! | G76: ="str" & A76 & " = comExcelWorksheet.Cells(intRow" & A76 & ", intColTestColumn).Value" -> #REF! | H76: ="Public Property Get get" & A76 & "() : get" & A76 & " = str" & A76 & " : End Property" -> #REF!
A77: =Test_Data!D66 -> ChangeMyGovernmentIDs_NationalIDs_Country2 | B77: ="intRow" & A77 & ", " -> intRowChangeMyGovernmentIDs_NationalIDs_Country2, | C77: =C76 &B77 -> #REF! | D77: ="str" & A77 & ", " -> strChangeMyGovernmentIDs_NationalIDs_Country2, | E77: =E76 &D77 -> #REF! | F77: ="intRow" & A77 & " = comExcelWorksheet.Range(""" & A77 & """).Row" -> intRowChangeMyGovernmentIDs_NationalIDs_Country2 = comExcelWorksheet.Range("ChangeMyGovernmentIDs_NationalIDs_Country2").Row | G77: ="str" & A77 & " = comExcelWorksheet.Cells(intRow" & A77 & ", intColTestColumn).Value" -> strChangeMyGovernmentIDs_NationalIDs_Country2 = comExcelWorksheet.Cells(intRowChangeMyGovernmentIDs_NationalIDs_Country2, intColTestColumn).Value | H77: ="Public Property Get get" & A77 & "() : get" & A77 & " = str" & A77 & " : End Property" -> Public Property Get getChangeMyGovernmentIDs_NationalIDs_Country2() : getChangeMyGovernmentIDs_NationalIDs_Country2 = strChangeMyGovernmentIDs_NationalIDs_Country2 : End Property
A78: =Test_Data!D67 -> ChangeMyGovernmentIDs_NationalIDs_NationalIDType2 | B78: ="intRow" & A78 & ", " -> intRowChangeMyGovernmentIDs_NationalIDs_NationalIDType2, | C78: =C77 &B78 -> #REF! | D78: ="str" & A78 & ", " -> strChangeMyGovernmentIDs_NationalIDs_NationalIDType2, | E78: =E77 &D78 -> #REF! | F78: ="intRow" & A78 & " = comExcelWorksheet.Range(""" & A78 & """).Row" -> intRowChangeMyGovernmentIDs_NationalIDs_NationalIDType2 = comExcelWorksheet.Range("ChangeMyGovernmentIDs_NationalIDs_NationalIDType2").Row | G78: ="str" & A78 & " = comExcelWorksheet.Cells(intRow" & A78 & ", intColTestColumn).Value" -> strChangeMyGovernmentIDs_NationalIDs_NationalIDType2 = comExcelWorksheet.Cells(intRowChangeMyGovernmentIDs_NationalIDs_NationalIDType2, intColTestColumn).Value | H78: ="Public Property Get get" & A78 & "() : get" & A78 & " = str" & A78 & " : End Property" -> Public Property Get getChangeMyGovernmentIDs_NationalIDs_NationalIDType2() : getChangeMyGovernmentIDs_NationalIDs_NationalIDType2 = strChangeMyGovernmentIDs_NationalIDs_NationalIDType2 : End Property
A79: =Test_Data!D68 -> ChangeMyGovernmentIDs_NationalIDs_AddEditID2 | B79: ="intRow" & A79 & ", " -> intRowChangeMyGovernmentIDs_NationalIDs_AddEditID2, | C79: =C78 &B79 -> #REF! | D79: ="str" & A79 & ", " -> strChangeMyGovernmentIDs_NationalIDs_AddEditID2, | E79: =E78 &D79 -> #REF! | F79: ="intRow" & A79 & " = comExcelWorksheet.Range(""" & A79 & """).Row" -> intRowChangeMyGovernmentIDs_NationalIDs_AddEditID2 = comExcelWorksheet.Range("ChangeMyGovernmentIDs_NationalIDs_AddEditID2").Row | G79: ="str" & A79 & " = comExcelWorksheet.Cells(intRow" & A79 & ", intColTestColumn).Value" -> strChangeMyGovernmentIDs_NationalIDs_AddEditID2 = comExcelWorksheet.Cells(intRowChangeMyGovernmentIDs_NationalIDs_AddEditID2, intColTestColumn).Value | H79: ="Public Property Get get" & A79 & "() : get" & A79 & " = str" & A79 & " : End Property" -> Public Property Get getChangeMyGovernmentIDs_NationalIDs_AddEditID2() : getChangeMyGovernmentIDs_NationalIDs_AddEditID2 = strChangeMyGovernmentIDs_NationalIDs_AddEditID2 : End Property
A80: =Test_Data!D69 -> PaymentElectionOption_BankCode | B80: ="intRow" & A80 & ", " -> intRowPaymentElectionOption_BankCode, | C80: =C79 &B80 -> #REF! | D80: ="str" & A80 & ", " -> strPaymentElectionOption_BankCode, | E80: =E79 &D80 -> #REF! | F80: ="intRow" & A80 & " = comExcelWorksheet.Range(""" & A80 & """).Row" -> intRowPaymentElectionOption_BankCode = comExcelWorksheet.Range("PaymentElectionOption_BankCode").Row | G80: ="str" & A80 & " = comExcelWorksheet.Cells(intRow" & A80 & ", intColTestColumn).Value" -> strPaymentElectionOption_BankCode = comExcelWorksheet.Cells(intRowPaymentElectionOption_BankCode, intColTestColumn).Value | H80: ="Public Property Get get" & A80 & "() : get" & A80 & " = str" & A80 & " : End Property" -> Public Property Get getPaymentElectionOption_BankCode() : getPaymentElectionOption_BankCode = strPaymentElectionOption_BankCode : End Property
A81: =Test_Data!#REF! -> #REF! | B81: ="intRow" & A81 & ", " -> #REF! | C81: =C80 &B81 -> #REF! | D81: ="str" & A81 & ", " -> #REF! | E81: =E80 &D81 -> #REF! | F81: ="intRow" & A81 & " = comExcelWorksheet.Range(""" & A81 & """).Row" -> #REF! | G81: ="str" & A81 & " = comExcelWorksheet.Cells(intRow" & A81 & ", intColTestColumn).Value" -> #REF! | H81: ="Public Property Get get" & A81 & "() : get" & A81 & " = str" & A81 & " : End Property" -> #REF!
A82: =Test_Data!D70 -> PaymentElectionOption_AccountType | B82: ="intRow" & A82 & ", " -> intRowPaymentElectionOption_AccountType, | C82: =C81 &B82 -> #REF! | D82: ="str" & A82 & ", " -> strPaymentElectionOption_AccountType, | E82: =E81 &D82 -> #REF! | F82: ="intRow" & A82 & " = comExcelWorksheet.Range(""" & A82 & """).Row" -> intRowPaymentElectionOption_AccountType = comExcelWorksheet.Range("PaymentElectionOption_AccountType").Row | G82: ="str" & A82 & " = comExcelWorksheet.Cells(intRow" & A82 & ", intColTestColumn).Value" -> strPaymentElectionOption_AccountType = comExcelWorksheet.Cells(intRowPaymentElectionOption_AccountType, intColTestColumn).Value | H82: ="Public Property Get get" & A82 & "() : get" & A82 & " = str" & A82 & " : End Property" -> Public Property Get getPaymentElectionOption_AccountType() : getPaymentElectionOption_AccountType = strPaymentElectionOption_AccountType : End Property
A83: =Test_Data!#REF! -> #REF! | B83: ="intRow" & A83 & ", " -> #REF! | C83: =C82 &B83 -> #REF! | D83: ="str" & A83 & ", " -> #REF! | E83: =E82 &D83 -> #REF! | F83: ="intRow" & A83 & " = comExcelWorksheet.Range(""" & A83 & """).Row" -> #REF! | G83: ="str" & A83 & " = comExcelWorksheet.Cells(intRow" & A83 & ", intColTestColumn).Value" -> #REF! | H83: ="Public Property Get get" & A83 & "() : get" & A83 & " = str" & A83 & " : End Property" -> #REF!
A84: =Test_Data!D71 -> PaymentElectionOption_IBAN | B84: ="intRow" & A84 & ", " -> intRowPaymentElectionOption_IBAN, | C84: =C83 &B84 -> #REF! | D84: ="str" & A84 & ", " -> strPaymentElectionOption_IBAN, | E84: =E83 &D84 -> #REF! | F84: ="intRow" & A84 & " = comExcelWorksheet.Range(""" & A84 & """).Row" -> intRowPaymentElectionOption_IBAN = comExcelWorksheet.Range("PaymentElectionOption_IBAN").Row | G84: ="str" & A84 & " = comExcelWorksheet.Cells(intRow" & A84 & ", intColTestColumn).Value" -> strPaymentElectionOption_IBAN = comExcelWorksheet.Cells(intRowPaymentElectionOption_IBAN, intColTestColumn).Value | H84: ="Public Property Get get" & A84 & "() : get" & A84 & " = str" & A84 & " : End Property" -> Public Property Get getPaymentElectionOption_IBAN() : getPaymentElectionOption_IBAN = strPaymentElectionOption_IBAN : End Property
A85: =Test_Data!#REF! -> #REF! | B85: ="intRow" & A85 & ", " -> #REF! | C85: =C84 &B85 -> #REF! | D85: ="str" & A85 & ", " -> #REF! | E85: =E84 &D85 -> #REF! | F85: ="intRow" & A85 & " = comExcelWorksheet.Range(""" & A85 & """).Row" -> #REF! | G85: ="str" & A85 & " = comExcelWorksheet.Cells(intRow" & A85 & ", intColTestColumn).Value" -> #REF! | H85: ="Public Property Get get" & A85 & "() : get" & A85 & " = str" & A85 & " : End Property" -> #REF!
A86: =Test_Data!#REF! -> #REF! | B86: ="intRow" & A86 & ", " -> #REF! | C86: =C85 &B86 -> #REF! | D86: ="str" & A86 & ", " -> #REF! | E86: =E85 &D86 -> #REF! | F86: ="intRow" & A86 & " = comExcelWorksheet.Range(""" & A86 & """).Row" -> #REF! | G86: ="str" & A86 & " = comExcelWorksheet.Cells(intRow" & A86 & ", intColTestColumn).Value" -> #REF! | H86: ="Public Property Get get" & A86 & "() : get" & A86 & " = str" & A86 & " : End Property" -> #REF!
A87: =Test_Data!#REF! -> #REF! | B87: ="intRow" & A87 & ", " -> #REF! | C87: =C86 &B87 -> #REF! | D87: ="str" & A87 & ", " -> #REF! | E87: =E86 &D87 -> #REF! | F87: ="intRow" & A87 & " = comExcelWorksheet.Range(""" & A87 & """).Row" -> #REF! | G87: ="str" & A87 & " = comExcelWorksheet.Cells(intRow" & A87 & ", intColTestColumn).Value" -> #REF! | H87: ="Public Property Get get" & A87 & "() : get" & A87 & " = str" & A87 & " : End Property" -> #REF!
A88: =Test_Data!#REF! -> #REF! | B88: ="intRow" & A88 & ", " -> #REF! | C88: =C87 &B88 -> #REF! | D88: ="str" & A88 & ", " -> #REF! | E88: =E87 &D88 -> #REF! | F88: ="intRow" & A88 & " = comExcelWorksheet.Range(""" & A88 & """).Row" -> #REF! | G88: ="str" & A88 & " = comExcelWorksheet.Cells(intRow" & A88 & ", intColTestColumn).Value" -> #REF! | H88: ="Public Property Get get" & A88 & "() : get" & A88 & " = str" & A88 & " : End Property" -> #REF!
A89: =Test_Data!#REF! -> #REF! | B89: ="intRow" & A89 & ", " -> #REF! | C89: =C88 &B89 -> #REF! | D89: ="str" & A89 & ", " -> #REF! | E89: =E88 &D89 -> #REF! | F89: ="intRow" & A89 & " = comExcelWorksheet.Range(""" & A89 & """).Row" -> #REF! | G89: ="str" & A89 & " = comExcelWorksheet.Cells(intRow" & A89 & ", intColTestColumn).Value" -> #REF! | H89: ="Public Property Get get" & A89 & "() : get" & A89 & " = str" & A89 & " : End Property" -> #REF!
A90: =Test_Data!#REF! -> #REF! | B90: ="intRow" & A90 & ", " -> #REF! | C90: =C89 &B90 -> #REF! | D90: ="str" & A90 & ", " -> #REF! | E90: =E89 &D90 -> #REF! | F90: ="intRow" & A90 & " = comExcelWorksheet.Range(""" & A90 & """).Row" -> #REF! | G90: ="str" & A90 & " = comExcelWorksheet.Cells(intRow" & A90 & ", intColTestColumn).Value" -> #REF! | H90: ="Public Property Get get" & A90 & "() : get" & A90 & " = str" & A90 & " : End Property" -> #REF!
A91: =Test_Data!#REF! -> #REF! | B91: ="intRow" & A91 & ", " -> #REF! | C91: =C90 &B91 -> #REF! | D91: ="str" & A91 & ", " -> #REF! | E91: =E90 &D91 -> #REF! | F91: ="intRow" & A91 & " = comExcelWorksheet.Range(""" & A91 & """).Row" -> #REF! | G91: ="str" & A91 & " = comExcelWorksheet.Cells(intRow" & A91 & ", intColTestColumn).Value" -> #REF! | H91: ="Public Property Get get" & A91 & "() : get" & A91 & " = str" & A91 & " : End Property" -> #REF!
A92: =Test_Data!#REF! -> #REF! | B92: ="intRow" & A92 & ", " -> #REF! | C92: =C91 &B92 -> #REF! | D92: ="str" & A92 & ", " -> #REF! | E92: =E91 &D92 -> #REF! | F92: ="intRow" & A92 & " = comExcelWorksheet.Range(""" & A92 & """).Row" -> #REF! | G92: ="str" & A92 & " = comExcelWorksheet.Cells(intRow" & A92 & ", intColTestColumn).Value" -> #REF! | H92: ="Public Property Get get" & A92 & "() : get" & A92 & " = str" & A92 & " : End Property" -> #REF!
A93: =Test_Data!#REF! -> #REF! | B93: ="intRow" & A93 & ", " -> #REF! | C93: =C92 &B93 -> #REF! | D93: ="str" & A93 & ", " -> #REF! | E93: =E92 &D93 -> #REF! | F93: ="intRow" & A93 & " = comExcelWorksheet.Range(""" & A93 & """).Row" -> #REF! | G93: ="str" & A93 & " = comExcelWorksheet.Cells(intRow" & A93 & ", intColTestColumn).Value" -> #REF! | H93: ="Public Property Get get" & A93 & "() : get" & A93 & " = str" & A93 & " : End Property" -> #REF!
A94: =Test_Data!#REF! -> #REF! | B94: ="intRow" & A94 & ", " -> #REF! | C94: =C93 &B94 -> #REF! | D94: ="str" & A94 & ", " -> #REF! | E94: =E93 &D94 -> #REF! | F94: ="intRow" & A94 & " = comExcelWorksheet.Range(""" & A94 & """).Row" -> #REF! | G94: ="str" & A94 & " = comExcelWorksheet.Cells(intRow" & A94 & ", intColTestColumn).Value" -> #REF! | H94: ="Public Property Get get" & A94 & "() : get" & A94 & " = str" & A94 & " : End Property" -> #REF!
A95: =Test_Data!#REF! -> #REF! | B95: ="intRow" & A95 & ", " -> #REF! | C95: =C94 &B95 -> #REF! | D95: ="str" & A95 & ", " -> #REF! | E95: =E94 &D95 -> #REF! | F95: ="intRow" & A95 & " = comExcelWorksheet.Range(""" & A95 & """).Row" -> #REF! | G95: ="str" & A95 & " = comExcelWorksheet.Cells(intRow" & A95 & ", intColTestColumn).Value" -> #REF! | H95: ="Public Property Get get" & A95 & "() : get" & A95 & " = str" & A95 & " : End Property" -> #REF!
A96: =Test_Data!#REF! -> #REF! | B96: ="intRow" & A96 & ", " -> #REF! | C96: =C95 &B96 -> #REF! | D96: ="str" & A96 & ", " -> #REF! | E96: =E95 &D96 -> #REF! | F96: ="intRow" & A96 & " = comExcelWorksheet.Range(""" & A96 & """).Row" -> #REF! | G96: ="str" & A96 & " = comExcelWorksheet.Cells(intRow" & A96 & ", intColTestColumn).Value" -> #REF! | H96: ="Public Property Get get" & A96 & "() : get" & A96 & " = str" & A96 & " : End Property" -> #REF!
... A99: =Test_Data!#REF! -> #REF! | B99: ="intRow" & A99 & ", " -> #REF! | C99: =C98 &B99 -> #REF! | D99: ="str" & A99 & ", " -> #REF! | E99: =E98 &D99 -> #REF! | F99: ="intRow" & A99 & " = comExcelWorksheet.Range(""" & A99 & """).Row" -> #REF! | G99: ="str" & A99 & " = comExcelWorksheet.Cells(intRow" & A99 & ", intColTestColumn).Value" -> #REF! | H99: ="Public Property Get get" & A99 & "() : get" & A99 & " = str" & A99 & " : End Property" -> #REF!

Sheet Names
B3: Etoecyeone | C3: 1 | D3: one | F3: 1 | G3: one | J3: =G3&H3 -> one | K3: one
B4: Etoecyeone | C4: 2 | D4: two | F4: 2 | G4: two | J4: =G4&H4 -> two | K4: two
B5: Etoecyeone | C5: 3 | D5: three | F5: 3 | G5: three | J5: =G5&H5 -> three | K5: three
B6: Etoecyeone | C6: 4 | D6: four | F6: 4 | G6: four | J6: =G6&H6 -> four | K6: four
B7: Etoecyeone | C7: 5 | D7: five | F7: 5 | G7: five | J7: =G7&H7 -> five | K7: five
B8: Etoecyeone | C8: 6 | D8: six | F8: 6 | G8: six | J8: =G8&H8 -> six | K8: six
B9: Etoecyeone | C9: 7 | D9: seven | F9: 7 | G9: seven | J9: =G9&H9 -> seven | K9: seven
B10: Etoecyeone | C10: 8 | D10: eight | F10: 8 | G10: eight | J10: =G10&H10 -> eight | K10: eight
B11: Etoecyeone | C11: 9 | D11: nine | F11: 9 | G11: nine | J11: =G11&H11 -> nine | K11: nine
B12: Etoecyeone | C12: 10 | D12: ten | F12: 10 | G12: ten | J12: =G12&H12 -> ten | K12: ten
B13: Etoecyeone | C13: 11 | D13: eleven | F13: 11 | G13: eleven | J13: =G13&H13 -> eleven | K13: eleven
B14: Etoecyeone | C14: 12 | D14: twelve | F14: 12 | G14: twelve | J14: =G14&H14 -> twelve | K14: twelve
B15: Etoecyeone | C15: 13 | D15: thirteen | F15: 13 | G15: thirteen | J15: =G15&H15 -> thirteen | K15: thirteen
... B22: Etoecyeone | C22: 20 | D22: twenty | F22: 20 | G22: twenty | J22: =G22&H22 -> twenty | K22: twenty
B23: Etoecyeone | C23: 30 | D23: thirty | F23: 21 | G23: twenty | H23: one | J23: =G23&H23 -> twentyone | K23: twentyone
B24: Etoecyeone | C24: 40 | D24: forty | F24: 22 | G24: twenty | H24: two | J24: =G24&H24 -> twentytwo | K24: twentytwo
B25: Etoecyeone | C25: 50 | D25: fifty | F25: 23 | G25: twenty | H25: three | J25: =G25&H25 -> twentythree | K25: twentythree
B26: Etoecyeone | C26: 60 | D26: sixty | F26: 24 | G26: twenty | H26: four | J26: =G26&H26 -> twentyfour | K26: twentyfour
B27: Etoecyeone | C27: 70 | D27: seventy | F27: 25 | G27: twenty | H27: five | J27: =G27&H27 -> twentyfive | K27: twentyfive
B28: Etoecyeone | C28: 80 | D28: eighty | F28: 26 | G28: twenty | H28: six | J28: =G28&H28 -> twentysix | K28: twentysix
B29: Etoecyeone | C29: 90 | D29: ninety | F29: 27 | G29: twenty | H29: seven | J29: =G29&H29 -> twentyseven | K29: twentyseven
B30: Etoecyeone | C30: 100 | D30: one hundred | F30: 28 | G30: twenty | H30: eight | J30: =G30&H30 -> twentyeight | K30: twentyeight
B31: Etoecyeone | C31: 1000 | D31: one thousand | F31: 29 | G31: twenty | H31: nine | J31: =G31&H31 -> twentynine | K31: twentynine
B32: Etoecyeone | F32: 30 | G32: thirty | J32: =G32&H32 -> thirty | K32: thirty
B33: Etoecyeone | F33: 31 | G33: thirty | H33: one | J33: =G33&H33 -> thirtyone | K33: thirtyone
B34: Etoecyeone | F34: 32 | G34: thirty | H34: two | J34: =G34&H34 -> thirtytwo | K34: thirtytwo
B35: Etoecyeone | F35: 33 | G35: thirty | H35: three | J35: =G35&H35 -> thirtythree | K35: thirtythree
B36: Etoecyeone | F36: 34 | G36: thirty | H36: four | J36: =G36&H36 -> thirtyfour | K36: thirtyfour
B37: Etoecyeone | F37: 35 | G37: thirty | H37: five | J37: =G37&H37 -> thirtyfive | K37: thirtyfive
B38: Etoecyeone | F38: 36 | G38: thirty | H38: six | J38: =G38&H38 -> thirtysix | K38: thirtysix
B39: Etoecyeone | F39: 37 | G39: thirty | H39: seven | J39: =G39&H39 -> thirtyseven | K39: thirtyseven
B40: Etoecyeone | F40: 38 | G40: thirty | H40: eight | J40: =G40&H40 -> thirtyeight | K40: thirtyeight
B41: Etoecyeone | F41: 39 | G41: thirty | H41: nine | J41: =G41&H41 -> thirtynine | K41: thirtynine
B42: Etoecyeone | F42: 40 | G42: forty | J42: =G42&H42 -> forty | K42: forty
B43: Etoecyeone | F43: 41 | G43: forty | H43: one | J43: =G43&H43 -> fortyone | K43: fortyone
B44: Etoecyeone | F44: 42 | G44: forty | H44: two | J44: =G44&H44 -> fortytwo | K44: fortytwo
B45: Etoecyeone | F45: 43 | G45: forty | H45: three | J45: =G45&H45 -> fortythree | K45: fortythree
B46: Etoecyeone | F46: 44 | G46: forty | H46: four | J46: =G46&H46 -> fortyfour | K46: fortyfour
B47: Etoecyeone | F47: 45 | G47: forty | H47: five | J47: =G47&H47 -> fortyfive | K47: fortyfive
B48: Etoecyeone | F48: 46 | G48: forty | H48: six | J48: =G48&H48 -> fortysix | K48: fortysix
B49: Etoecyeone | F49: 47 | G49: forty | H49: seven | J49: =G49&H49 -> fortyseven | K49: fortyseven
B50: Etoecyeone | F50: 48 | G50: forty | H50: eight | J50: =G50&H50 -> fortyeight | K50: fortyeight
B51: Etoecyeone | F51: 49 | G51: forty | H51: nine | J51: =G51&H51 -> fortynine | K51: fortynine
B52: Etoecyeone | F52: 50 | G52: fifty | J52: =G52&H52 -> fifty | K52: fifty
B53: Etoecyeone | F53: 51 | G53: fifty | H53: one | J53: =G53&H53 -> fiftyone | K53: fiftyone
B54: Etoecyeone | F54: 52 | G54: fifty | H54: two | J54: =G54&H54 -> fiftytwo | K54: fiftytwo
B55: ETOE | F55: 53 | G55: fifty | H55: three | J55: =G55&H55 -> fiftythree | K55: fiftythree | U55: ETOEfiftynine | V55: ETOEsixty | W55: ETOEsixtyone | X55: ETOEsixtytwo | Y55: ETOEsixtythree | Z55: ETOEsixtyfour | AA55: ETOEsixtyfive | AB55: ETOEsixtysix | AC55: ETOEsixtyseven | AD55: ETOEsixtyeight | AE55: ETOEsixtynine | AF55: ETOEseventy | AG55: ETOEseventyone | AH55: ETOEseventytwo | AI55: ETOEseventythree | AJ55: ETOEseventyfour | AK55: ETOEseventyfive | AL55: ETOEseventysix | AM55: ETOEseventyseven | AN55: ETOEseventyeight | AO55: ETOEseventynine | AP55: ETOEeighty | AQ55: ETOEeightyone | AR55: ETOEeightytwo | AS55: ETOEeightythree | AT55: ETOEeightyfour | AU55: ETOEeightyfive | AV55: ETOEeightysix | AW55: ETOEeightyseven | AX55: ETOEeightyeight | AY55: ETOEeightynine | AZ55: ETOEninety | BA55: ETOEninetyone | BB55: ETOEninetytwo | BC55: ETOEninetythree | BD55: ETOEninetyfour | BE55: ETOEninetyfive | BF55: ETOEninetysix | BG55: ETOEninetyseven | BH55: ETOEninetyeight | BI55: ETOEninetynine | BJ55: ETOEonezerozero | BK55: ETOEonezerooneone | BL55: ETOEonezerotwotwo | BM55: ETOEonezerothreethree | BN55: ETOEonezerofourfour | BO55: ETOEonezerofivefive | BP55: ETOEonezerosixsix | BQ55: ETOEonezerosevenseven | BR55: ETOEonezeroeighteight | BS55: ETOEonezeroninenine | BT55: ETOEoneonezero | BU55: ETOEoneoneone | BV55: ETOEoneonetwo | BW55: ETOEoneonethree | BX55: ETOEoneonefour | BY55: ETOEoneonefive | BZ55: ETOEoneonesix | CA55: ETOEoneoneseven | CB55: ETOEoneoneeight | CC55: ETOEoneonenine | CD55: ETOEonetwozero | CE55: ETOEonetwoone | CF55: ETOEonetwotwo | CG55: ETOEonetwothree | CH55: ETOEonetwofour | CI55: ETOEonetwofive | CJ55: ETOEonetwosix | CK55: ETOEonetwoseven | CL55: ETOEonetwoeight | CM55: ETOEonetwonine | CN55: ETOEonethreezero | CO55: ETOEonethreeone | CP55: ETOEonethreetwo | CQ55: ETOEonethreethree | CR55: ETOEonethreefour | CS55: ETOEonethreefive | CT55: ETOEonethreesix | CU55: ETOEonethreeseven | CV55: ETOEonethreeeight | CW55: ETOEonethreenine | CX55: ETOEonefourzero | CY55: ETOEonefourone | CZ55: ETOEonefourtwo | DA55: ETOEonefourthree | DB55: ETOEonefourfour | DC55: ETOEonefourfive | DD55: ETOEonefoursix | DE55: ETOEonefourseven | DF55: ETOEonefoureight | DG55: ETOEonefournine | DH55: ETOEonefivezero
B56: ETOE | F56: 54 | G56: fifty | H56: four | J56: =G56&H56 -> fiftyfour | K56: fiftyfour
B57: ETOE | F57: 55 | G57: fifty | H57: five | J57: =G57&H57 -> fiftyfive | K57: fiftyfive
B58: ETOE | F58: 56 | G58: fifty | H58: six | J58: =G58&H58 -> fiftysix | K58: fiftysix
B59: ETOE | F59: 57 | G59: fifty | H59: seven | J59: =G59&H59 -> fiftyseven | K59: fiftyseven
B60: ETOE | F60: 58 | G60: fifty | H60: eight | J60: =G60&H60 -> fiftyeight | K60: fiftyeight
B61: ETOE | F61: 59 | G61: fifty | H61: nine | J61: =G61&H61 -> fiftynine | K61: fiftynine
B62: ETOE | F62: 60 | G62: sixty | J62: =G62&H62 -> sixty | K62: sixty
B63: ETOE | F63: 61 | G63: sixty | H63: one | J63: =G63&H63 -> sixtyone | K63: sixtyone
B64: ETOE | F64: 62 | G64: sixty | H64: two | J64: =G64&H64 -> sixtytwo | K64: sixtytwo
B65: ETOE | F65: 63 | G65: sixty | H65: three | J65: =G65&H65 -> sixtythree | K65: sixtythree
B66: ETOE | F66: 64 | G66: sixty | H66: four | J66: =G66&H66 -> sixtyfour | K66: sixtyfour
B67: ETOE | F67: 65 | G67: sixty | H67: five | J67: =G67&H67 -> sixtyfive | K67: sixtyfive
B68: ETOE | F68: 66 | G68: sixty | H68: six | J68: =G68&H68 -> sixtysix | K68: sixtysix
B69: ETOE | F69: 67 | G69: sixty | H69: seven | J69: =G69&H69 -> sixtyseven | K69: sixtyseven
B70: ETOE | F70: 68 | G70: sixty | H70: eight | J70: =G70&H70 -> sixtyeight | K70: sixtyeight
B71: ETOE | F71: 69 | G71: sixty | H71: nine | J71: =G71&H71 -> sixtynine | K71: sixtynine
B72: ETOE | F72: 70 | G72: seventy | J72: =G72&H72 -> seventy | K72: seventy
B73: ETOE | F73: 71 | G73: seventy | H73: one | J73: =G73&H73 -> seventyone | K73: seventyone
B74: ETOE | F74: 72 | G74: seventy | H74: two | J74: =G74&H74 -> seventytwo | K74: seventytwo
B75: ETOE | F75: 73 | G75: seventy | H75: three | J75: =G75&H75 -> seventythree | K75: seventythree
B76: ETOE | F76: 74 | G76: seventy | H76: four | J76: =G76&H76 -> seventyfour | K76: seventyfour
B77: ETOE | F77: 75 | G77: seventy | H77: five | J77: =G77&H77 -> seventyfive | K77: seventyfive
B78: ETOE | F78: 76 | G78: seventy | H78: six | J78: =G78&H78 -> seventysix | K78: seventysix
B79: ETOE | F79: 77 | G79: seventy | H79: seven | J79: =G79&H79 -> seventyseven | K79: seventyseven
B80: ETOE | F80: 78 | G80: seventy | H80: eight | J80: =G80&H80 -> seventyeight | K80: seventyeight
B81: ETOE | F81: 79 | G81: seventy | H81: nine | J81: =G81&H81 -> seventynine | K81: seventynine
B82: ETOE | F82: 80 | G82: eighty | J82: =G82&H82 -> eighty | K82: eighty
B83: ETOE | F83: 81 | G83: eighty | H83: one | J83: =G83&H83 -> eightyone | K83: eightyone
B84: ETOE | F84: 82 | G84: eighty | H84: two | J84: =G84&H84 -> eightytwo | K84: eightytwo
B85: ETOE | F85: 83 | G85: eighty | H85: three | J85: =G85&H85 -> eightythree | K85: eightythree
B86: ETOE | F86: 84 | G86: eighty | H86: four | J86: =G86&H86 -> eightyfour | K86: eightyfour
B87: ETOE | F87: 85 | G87: eighty | H87: five | J87: =G87&H87 -> eightyfive | K87: eightyfive
B88: ETOE | F88: 86 | G88: eighty | H88: six | J88: =G88&H88 -> eightysix | K88: eightysix
B89: ETOE | F89: 87 | G89: eighty | H89: seven | J89: =G89&H89 -> eightyseven | K89: eightyseven
B90: ETOE | F90: 88 | G90: eighty | H90: eight | J90: =G90&H90 -> eightyeight | K90: eightyeight
B91: ETOE | F91: 89 | G91: eighty | H91: nine | J91: =G91&H91 -> eightynine | K91: eightynine
B92: ETOE | F92: 90 | G92: ninety | J92: =G92&H92 -> ninety | K92: ninety
B93: ETOE | F93: 91 | G93: ninety | H93: one | J93: =G93&H93 -> ninetyone | K93: ninetyone
B94: ETOE | F94: 92 | G94: ninety | H94: two | J94: =G94&H94 -> ninetytwo | K94: ninetytwo
B95: ETOE | F95: 93 | G95: ninety | H95: three | J95: =G95&H95 -> ninetythree | K95: ninetythree
B96: ETOE | F96: 94 | G96: ninety | H96: four | J96: =G96&H96 -> ninetyfour | K96: ninetyfour
B97: ETOE | F97: 95 | G97: ninety | H97: five | J97: =G97&H97 -> ninetyfive | K97: ninetyfive
B98: ETOE | F98: 96 | G98: ninety | H98: six | J98: =G98&H98 -> ninetysix | K98: ninetysix
B99: ETOE | F99: 97 | G99: ninety | H99: seven | J99: =G99&H99 -> ninetyseven | K99: ninetyseven
B100: ETOE | F100: 98 | G100: ninety | H100: eight | J100: =G100&H100 -> ninetyeight | K100: ninetyeight
B101: ETOE | F101: 99 | G101: ninety | H101: nine | J101: =G101&H101 -> ninetynine | K101: ninetynine
B102: ETOE | F102: 100 | G102: one | H102: zero | I102: zero | J102: =G102&H102&I102 -> onezerozero | K102: onezerozero
B103: ETOE | F103: 101 | G103: one | H103: zero | I103: one | J103: =G103&H103&I103 -> onezeroone | K103: onezeroone | U103: Etoecyeoneonehundredone | V103: Etoecyeoneonehundredtwo | W103: Etoecyeoneonehundredthree | X103: Etoecyeoneonehundredfour | Y103: Etoecyeoneonehundredfive | Z103: Etoecyeoneonehundredsix | AA103: Etoecyeoneonehundredseven | AB103: Etoecyeoneonehundredeight | AC103: Etoecyeoneonehundrednine
B104: ETOE | F104: 102 | G104: one | H104: zero | I104: two | J104: =G104&H104&I104 -> onezerotwo | K104: onezerotwo
B105: ETOE | F105: 103 | G105: one | H105: zero | I105: three | J105: =G105&H105&I105 -> onezerothree | K105: onezerothree
B106: ETOE | F106: 104 | G106: one | H106: zero | I106: four | J106: =G106&H106&I106 -> onezerofour | K106: onezerofour
B107: ETOE | F107: 105 | G107: one | H107: zero | I107: five | J107: =G107&H107&I107 -> onezerofive | K107: onezerofive
B108: ETOE | F108: 106 | G108: one | H108: zero | I108: six | J108: =G108&H108&I108 -> onezerosix | K108: onezerosix
...

Sheet Test_Data
A1: Version_Number | C1: Test_ID | D1: Test_ID | E1: Test_ID2 | F1: Notes | G1: Test_1 | H1: Test_2 | I1: Test_3 | J1: Test_4 | K1: Test_5 | L1: Test_6 | M1: Test_7 | N1: Test_8 | O1: Test_9 | P1: Test_10 | Q1: Test_11 | R1: Test_12 | S1: Test_13 | T1: Test_14 | U1: Test_15
A2: 0.3 | C2: Reporting_ID | G2: 1 | H2: 2 | I2: 3 | J2: 4 | K2: 5 | L2: 6 | M2: 7 | N2: 8 | O2: 9 | P2: 10 | Q2: 11 | R2: 12 | S2: 13 | T2: 14 | U2: 15
C3: Process | D3: Process | E3: Process2 | F3: If a manager hire and new role is required then select "New Role and New Hire" otherwise select "New Hire | G3: New Hire | H3: New Hire | I3: New Role & New Hire | J3: New Hire | K3: New Role & New Hire | L3: New Role & New Hire | M3: New Role & New Hire | N3: New Role & New Hire | O3: New Role & New Hire | P3: New Role & New Hire | Q3: New Hire | R3: New Hire | S3: New Hire | T3: New Hire | U3: New Hire
C4: Execution Flag | D4: ExecutionFlag | E4: ExecutionFlag2 | F4: If set to No will not execute in next automation run | G4: No | H4: No | I4: No | J4: Yes | K4: No | L4: No | M4: No | N4: No | O4: Yes | P4: Yes | Q4: Yes | R4: Yes | S4: Yes | T4: Yes | U4: Yes
C5: Data Validation Complete | D5: DataValidationComplete | E5: DataValidationComplete2 | G5: TRUE | H5: TRUE | I5: TRUE | J5: TRUE | K5: TRUE | L5: TRUE | M5: TRUE | N5: TRUE | O5: TRUE | P5: TRUE | Q5: TRUE | R5: TRUE | S5: TRUE | T5: TRUE | U5: TRUE
C6: Hire Name Complete | D6: HireNameComplete | E6: HireNameComplete2 | G6: TRUE | H6: TRUE | I6: TRUE | J6: TRUE | K6: TRUE | L6: TRUE | M6: TRUE | N6: TRUE | O6: TRUE | P6: TRUE | Q6: TRUE | R6: TRUE | S6: TRUE | T6: TRUE | U6: TRUE
C7: Last Run Time and Status | D7: LastRunTimeandStatus | E7: LastRunTimeandStatus2 | F7: Once test is executed the Execution Timestamp and Pass/Fail status will be recorded here | G7: 15/10/2024 04:40:23 Passed | H7: 15/10/2024 04:56:30 Passed | I7: 15/10/2024 05:14:54 Passed | J7: 15/10/2024 05:24:15 Failed | K7: 15/10/2024 05:42:37 Passed | L7: 15/10/2024 06:01:04 Passed | M7: 15/10/2024 06:19:26 Passed | N7: 15/10/2024 06:38:00 Passed | O7: 15/10/2024 06:40:12 Failed | P7: 15/10/2024 06:40:59 Failed | Q7: 15/10/2024 06:42:48 Failed
C8: Last Run Employee No | D8: LastRunEmployeeNo | E8: LastRunEmployeeNo2 | F8: The newly created employee number will be recorded here | G8: 10651050 | H8: 10651051 | I8: 10651052 | K8: 10651053 | L8: 10651054 | M8: 10651055 | N8: 10651056
C9: Last Run Error Message | D9: LastRunErrorMessage | E9: LastRunErrorMessage2 | F9: If Automation throws errors, the details will be placed here | J9: On Screen Page Error_x000D_ - You have not entered an amount within the Compensation Guidelines. (Employee Compensation Event For Hire Employee)_x000D_ Code Number = New Hire 240_x000D_ Location of Failure screenshot = D:\Workday_FailureScreenshot\Test_4_NewHire_Spain_ 15102024 052411.png_x000D_ Main action error_x000D_ Code Number = New Hire 250_x000D_ | O9: Field not found for Class = "PageHireCreatePosition" at Function = "setWorkerSubType"_x000D_ Code Number = Role 185_x000D_ Location of Failure screenshot = D:\Workday_FailureScreenshot\Test_9NewRoleNewHire_Spain_ 15102024 063957.png_x000D_ _x000D_ Main action error_x000D_ Code Number = Role 185_x000D_ Main action error_x000D_ Code Number = New Hire 99_x000D_ | P9: Field not found for Class = "PageSearch" at Function = "clickCreatePosition"_x000D_ Code Number = Role 180_x000D_ Location of Failure screenshot = D:\Workday_FailureScreenshot\Test_10NewRoleNewHire_Spain_ 15102024 064052.png_x000D_ _x000D_ Main action error_x000D_ Code Number = Role 180_x000D_ Main action error_x000D_ Code Number = New Hire 99_x000D_ | Q9: Field not found for Class = "PageSearch" at Function = "waitExistsHireEmployeeLink_2"_x000D_ Code Number = New Hire 100_x000D_ Location of Failure screenshot = D:\Workday_FailureScreenshot\Test_11_NewHire_Spain_ 15102024 064246.png_x000D_ _x000D_ Main action error_x000D_ Code Number = New Hire 110_x000D_
C10: Defect Description | D10: DefectDescription | E10: DefectDescription2 | F10: After error investigation by the automation team, the defect description will be completed here
A11: 90000545 613776f7e8da59d312c64ee2616f91b9792f3e91b38158c8dec27c9d | C11: Automation Comments | D11: AutomationComments | E11: AutomationComments2 | F11: Automation team free text field
A12: 90002195 65b795c1bf6d6c61cb007af2857d7d25d389ffbd49fc2e3cd7e638df | C12: QA Comments | D12: QAComments | E12: QAComments2 | F12: QA team free text field | L12: F
A14: Screen | B14: Subscreen | C14: Field | D14: Automation Ref | E14: Lookups Ref | F14: Notes | G14: Test_1 | H14: Test_2 | I14: Test_3 | J14: Test_4 | K14: Test_5 | L14: Test_6 | M14: Test_7 | N14: Test_8 | O14: Test_9 | P14: Test_10 | Q14: Test_11 | R14: Test_12 | S14: Test_13 | T14: Test_14 | U14: Test_15
A15: Login | B15: N/A | C15: Username | D15: Login_Username | E15: Login_Username2 | F15: QA user login | G15: 90002195 | H15: 90002195 | I15: 90002195 | J15: 90002195 | K15: 90002195 | L15: 90002195 | M15: 90002195 | N15: 90002195 | O15: 90002195 | P15: 90002195 | Q15: 90002195 | R15: 90002195 | S15: 90002195 | T15: 90002195 | U15: 90002195
A16: Login | B16: N/A | C16: Password | D16: Login_Password | E16: Login_Password2 | F16: QA user password | G16: 66eb0ddfe1833a6c0473b8ea80d04ab9d9cf77994b86082d9ff6f77f | H16: 66eb0ddfe1833a6c0473b8ea80d04ab9d9cf77994b86082d9ff6f77f | I16: 66eb0ddfe1833a6c0473b8ea80d04ab9d9cf77994b86082d9ff6f77f | J16: 66eb0ddfe1833a6c0473b8ea80d04ab9d9cf77994b86082d9ff6f77f | K16: 66eb0ddfe1833a6c0473b8ea80d04ab9d9cf77994b86082d9ff6f77f | L16: 66eb0ddfe1833a6c0473b8ea80d04ab9d9cf77994b86082d9ff6f77f | M16: 66eb0ddfe1833a6c0473b8ea80d04ab9d9cf77994b86082d9ff6f77f | N16: 66eb0ddfe1833a6c0473b8ea80d04ab9d9cf77994b86082d9ff6f77f | O16: 66eb0ddfe1833a6c0473b8ea80d04ab9d9cf77994b86082d9ff6f77f | P16: 66eb0ddfe1833a6c0473b8ea80d04ab9d9cf77994b86082d9ff6f77f | Q16: 66eb0ddfe1833a6c0473b8ea80d04ab9d9cf77994b86082d9ff6f77f | R16: 66eb0ddfe1833a6c0473b8ea80d04ab9d9cf77994b86082d9ff6f77f | S16: 66eb0ddfe1833a6c0473b8ea80d04ab9d9cf77994b86082d9ff6f77f | T16: 66eb0ddfe1833a6c0473b8ea80d04ab9d9cf77994b86082d9ff6f77f | U16: 66eb0ddfe1833a6c0473b8ea80d04ab9d9cf77994b86082d9ff6f77f
A17: Supervisory Organisation | B17: N/A | C17: Supervisory Organisation | D17: SupervisoryOrganisation_SupervisoryOrganisation | E17: SupervisoryOrganisation_SupervisoryOrganisation2 | G17: 356 Recruitment (Tyzuc Dycyvo Cabuve (2577) (Inherited)) | H17: 356 Recruitment (Tyzuc Dycyvo Cabuve (2577) (Inherited)) | I17: 365 Store Management (Zadeb Razohe Gykywi (10274587)) | J17: 356 Recruitment (Tyzuc Dycyvo Cabuve (2577) (Inherited)) | K17: 365 Store Management (Zadeb Razohe Gykywi (10274587)) | L17: 365 Store Management (Zadeb Razohe Gykywi (10274587)) | M17: 365 Store Management (Zadeb Razohe Gykywi (10274587)) | N17: 365 Store Management (Zadeb Razohe Gykywi (10274587)) | O17: 365 Store Management (Zadeb Razohe Gykywi (10274587)) | P17: 365 Store Management (Zadeb Razohe Gykywi (10274587)) | Q17: 356 Recruitment (Tyzuc Dycyvo Cabuve (2577) (Inherited)) | R17: 356 Recruitment (Tyzuc Dycyvo Cabuve (2577) (Inherited)) | S17: 356 Recruitment (Tyzuc Dycyvo Cabuve (2577) (Inherited)) | T17: 356 Recruitment (Tyzuc Dycyvo Cabuve (2577) (Inherited)) | U17: 356 Recruitment (Tyzuc Dycyvo Cabuve (2577) (Inherited))
A18: Legal Name Information | B18: N/A | C18: Given Name | D18: LegalNameInformation_GivenName | E18: LegalNameInformation_GivenName2 | F18: Automation will throw error if not unique | G18: SpainOne | H18: SpainTwo | I18: SpainThree | J18: SpainFour | K18: SpainFive | L18: SpainSix | M18: SpainSeven | N18: SpainEight | O18: SpainNine | P18: SpainTen | Q18: SpainEleven | R18: SpainTweleve | S18: SpainThirteen | T18: SpainFourteen | U18: SpainFifteen
A19: Legal Name Information | B19: N/A | C19: First Last Name | D19: LegalNameInformation_FirstLastName | E19: LegalNameInformation_FirstLastName2 | F19: Automation will throw error if not unique | G19: GlobelRegElevenOct | H19: GlobelRegElevenOct | I19: GlobelRegElevenOct | J19: GlobelRegElevenOctAs | K19: GlobelRegElevenOct | L19: GlobelRegElevenOct | M19: GlobelRegElevenOct | N19: GlobelRegElevenOct | O19: GlobelRegElevenOct | P19: GlobelRegElevenOct | Q19: GlobelRegElevenOct | R19: GlobelRegElevenOct | S19: GlobelRegElevenOct | T19: GlobelRegElevenOct | U19: GlobelRegElevenOct
A20: Legal Name Information | B20: N/A | C20: Second Last Name | D20: LegalNameInformation_SecondLastName | E20: LegalNameInformation_SecondLastName2 | F20: Automation will throw error if not unique | G20: Demo | H20: Mkaa | I20: RPOneNEWYEar | J20: RPOne | K20: RPOne | L20: RPOne | M20: RPOne | N20: RPOne | O20: RPOne | P20: RPOne | Q20: RPOne | R20: RPOne | S20: RPOne | T20: RPOne | U20: RPOne
A21: Legal Name Information | B21: N/A | C21: Country | D21: =SUBSTITUTE(A21," ","") & "_" & SUBSTITUTE(IF(B21="N/A","",B21& "_")," ","") & SUBSTITUTE(SUBSTITUTE(C21," ",""),"/","") -> LegalNameInformation_Country | E21: =D21&2 -> LegalNameInformation_Country2 | F21: Test country to be placed here | G21: Spain | H21: Spain | I21: Spain | J21: Spain | K21: Spain | L21: Spain | M21: Spain | N21: Spain | O21: Spain | P21: Spain | Q21: Spain | R21: Spain | S21: Spain | T21: Spain | U21: Spain
A22: Contact Information | B22: Phone | C22: Phone Number | D22: ContactInformation_Phone_PhoneNumber | E22: ContactInformation_Phone_PhoneNumber2 | G22: 919193393 | H22: 919193394 | I22: 919193436 | J22: 919193396 | K22: 919193397 | L22: 919193397 | M22: 919193397 | N22: 919193397 | O22: 919193397 | P22: 919193397 | Q22: 919193397 | R22: 919193397 | S22: 919193397 | T22: 919193397 | U22: 919193397
A23: Contact Information | B23: Phone | C23: Phone Device | D23: ContactInformation_Phone_PhoneDevice | E23: ContactInformation_Phone_PhoneDevice2 | G23: Landline | H23: Landline | I23: Landline | J23: Landline | K23: Landline | L23: Landline | M23: Landline | N23: Landline | O23: Landline | P23: Landline | Q23: Landline | R23: Landline | S23: Landline | T23: Landline | U23: Landline
A24: Contact Information | B24: Phone | C24: Type | D24: ContactInformation_Phone_Type | E24: ContactInformation_Phone_Type2 | G24: Home | H24: Home | I24: Home | J24: Home | K24: Home | L24: Home | M24: Home | N24: Home | O24: Home | P24: Home | Q24: Home | R24: Home | S24: Home | T24: Home | U24: Home
A25: Contact Information | B25: Address | C25: Effective Date | D25: ContactInformation_Address_EffectiveDate | E25: ContactInformation_Address_EffectiveDate2 | G25: =TODAY()-7 -> 45573 | H25: =TODAY()-7 -> 45573 | I25: =TODAY()-7 -> 45573 | J25: =TODAY()-7 -> 45573 | K25: =TODAY()-7 -> 45573 | L25: =TODAY()-7 -> 45573 | M25: =TODAY()-7 -> 45573 | N25: =TODAY()-7 -> 45573 | ... U25: =TODAY()-7 -> 45573
A26: Contact Information | B26: Address | C26: Country | D26: ContactInformation_Address_Country | E26: ContactInformation_Address_Country2 | G26: Spain | H26: Spain | I26: Spain | J26: Spain | K26: Spain | L26: Spain | M26: Spain | N26: Spain | O26: Spain | P26: Spain | Q26: Spain | R26: Spain | S26: Spain | T26: Spain | U26: Spain
A27: Contact Information | B27: Address | C27: Name Of Street | D27: ContactInformation_Address_NameOfStreet | E27: ContactInformation_Address_NameOfStreet2 | G27: Automation Street Name | H27: Automation Street Name | I27: Automation Street Name | J27: Automation Street Name | K27: Automation Street Name | L27: Automation Street Name | M27: Automation Street Name | N27: Automation Street Name | O27: Automation Street Name | P27: Automation Street Name | Q27: Automation Street Name | R27: Automation Street Name | S27: Automation Street Name | T27: Automation Street Name | U27: Automation Street Name
A28: Contact Information | B28: Address | C28: House Number | D28: ContactInformation_Address_HouseNumber | E28: ContactInformation_Address_HouseNumber2 | G28: 44 | H28: 44 | I28: 44 | J28: 44 | K28: 44 | L28: 44 | M28: 44 | N28: 44 | O28: 44 | P28: 44 | Q28: 44 | R28: 44 | S28: 44 | T28: 44 | U28: 44
A29: Contact Information | B29: Address | C29: Postal Code | D29: ContactInformation_Address_PostalCode | E29: ContactInformation_Address_PostalCode2 | G29: 28013 | H29: 28013 | I29: 28013 | J29: 28013 | K29: 28013 | L29: 28013 | M29: 28013 | N29: 28013 | O29: 28013 | P29: 28013 | Q29: 28013 | R29: 28013 | S29: 28013 | T29: 28013 | U29: 28013
A30: Contact Information | B30: Address | C30: City | D30: ContactInformation_Address_City | E30: ContactInformation_Address_City2 | G30: Madrid | H30: Madrid | I30: Madrid | J30: Madrid | K30: Madrid | L30: Madrid | M30: Madrid | N30: Madrid | O30: Madrid | P30: Madrid | Q30: Madrid | R30: Madrid | S30: Madrid | T30: Madrid | U30: Madrid
A31: Contact Information | B31: Address | C31: Province | D31: ContactInformation_Address_Province | E31: ContactInformation_Address_Province2 | G31: Madrid | H31: Madrid | I31: Madrid | J31: Madrid | K31: Madrid | L31: Madrid | M31: Madrid | N31: Madrid | O31: Madrid | P31: Madrid | Q31: Madrid | R31: Madrid | S31: Madrid | T31: Madrid | U31: Madrid
A32: Contact Information | B32: Address | C32: Type | D32: ContactInformation_Address_Type | E32: ContactInformation_Address_Type2 | G32: Home | H32: Home | I32: Home | J32: Home | K32: Home | L32: Home | M32: Home | N32: Home | O32: Home | P32: Home | Q32: Home | R32: Home | S32: Home | T32: Home | U32: Home
A33: Contact Information | B33: Address | C33: Use For | D33: ContactInformation_Address_UseFor | E33: ContactInformation_Address_UseFor2 | F33: "Permanent" or "Temporary" | G33: Street Address | H33: Street Address | I33: Street Address | J33: Street Address | K33: Street Address | L33: Street Address | M33: Street Address | N33: Street Address | O33: Street Address | P33: Street Address | Q33: Street Address | R33: Street Address | S33: Street Address | T33: Street Address | U33: Street Address
A34: Contact Information | B34: Email | C34: Email Address | D34: ContactInformation_Email_EmailAddress | E34: ContactInformation_Email_EmailAddress2 | G34: automation@qe.com | H34: automation@qe.com | I34: automation@qe.com | J34: automation@qe.com | K34: automation@qe.com | L34: automation@qe.com | M34: automation@qe.com | N34: automation@qe.com | O34: automation@qe.com | P34: automation@qe.com | Q34: automation@qe.com | R34: automation@qe.com | S34: automation@qe.com | T34: automation@qe.com | U34: automation@qe.com
A35: Contact Information | B35: Email | C35: Type | D35: ContactInformation_Email_Type | E35: ContactInformation_Email_Type2 | G35: Home | H35: Home | I35: Home | J35: Home | K35: Home | L35: Home | M35: Home | N35: Home | O35: Home | P35: Home | Q35: Home | R35: Home | S35: Home | T35: Home | U35: Home
A36: Job Details | B36: N/A | C36: Hire Date | D36: JobDetails_HireDate | E36: JobDetails_HireDate2 | G36: =TODAY()-7 -> 45573 | H36: =TODAY()-7 -> 45573 | I36: =TODAY()-7 -> 45573 | J36: =TODAY()-7 -> 45573 | K36: =TODAY()-7 -> 45573 | L36: =TODAY()-7 -> 45573 | M36: =TODAY()-7 -> 45573 | N36: =TODAY()-7 -> 45573 | ... U36: =TODAY()-7 -> 45573
A37: Job Details | B37: N/A | C37: Reason | D37: JobDetails_Reason | E37: JobDetails_Reason2 | G37: New Hire | H37: New Hire | I37: New Hire | J37: New Hire | K37: New Hire | L37: New Hire | M37: New Hire | N37: New Hire | O37: New Hire | P37: New Hire | Q37: New Hire | R37: New Hire | S37: New Hire | T37: New Hire | U37: New Hire
A38: Job Details | B38: N/A | C38: Position | D38: JobDetails_Position | E38: JobDetails_Position2 | F38: If Process is set to "New Role and New Hire" (Row 2) this position name will be ignored and replaced with the newly created name. | G38: N/A | H38: N/A | I38: Auto 15102024 045735 | J38: N/A | K38: Auto 15102024 052519 | L38: Auto 15102024 054343 | M38: Auto 15102024 060209 | N38: Auto 15102024 062030 | O38: Auto 15102024 063905 | P38: Auto 02102024 123123 | Q38: N/A | R38: N/A | S38: N/A | T38: N/A | U38: N/A
A39: Job Details | B39: N/A | C39: Employee Type | D39: JobDetails_EmployeeType | E39: JobDetails_EmployeeType2 | F39: If Fixed Term ensure contract end date below is populated and not N/A | G39: Permanent | H39: Fixed Term | I39: Permanent | J39: Permanent | K39: Fixed Term | L39: Permanent | M39: Permanent | N39: Fixed Term | O39: Permanent | P39: Permanent | Q39: Intern | R39: Temporary (Fixed Purpose) | S39: Permanent | T39: Fixed Term | U39: Temporary (Fixed Purpose)
A40: Job Details | B40: N/A | C40: Job Profile | D40: JobDetails_JobProfile | E40: JobDetails_JobProfile2 | G40: Retail Assistant | H40: Retail Assistant | I40: Department Manager | J40: Supervisor | K40: Trainee Manager | L40: Assistant Manager | M40: Team Manager - Retail | N40: Store Manager | O40: P&C Manager Stores | P40: Operations Manager | Q40: Retail Assistant | R40: Retail Assistant | S40: Visual Merchandiser | T40: Operational Support | U40: Retail Assistant
A41: Job Details | B41: N/A | C41: Time Type | D41: JobDetails_TimeType | E41: JobDetails_TimeType2 | G41: Full time | H41: Part time | I41: Full time | J41: Part time | K41: Part time | L41: Full time | M41: Part time | N41: Full time | O41: Full time | P41: Full time | Q41: Part time | R41: Part time | S41: Full time | T41: Full time | U41: Full time
A42: Job Details | B42: N/A | C42: Location | D42: JobDetails_Location | E42: JobDetails_Location2 | G42: 356 | H42: 356 | I42: 365 | J42: 356 | K42: 365 | L42: 365 | M42: 365 | N42: 365 | O42: 365 | P42: 365 | Q42: 356 | R42: 356 | S42: 356 | T42: 356 | U42: 356
A43: Job Details | B43: Additional Information | C43: Scheduled Weekly Hours | D43: JobDetails_AdditionalInformation_ScheduledWeeklyHours | E43: JobDetails_AdditionalInformation_ScheduledWeeklyHours2 | G43: 100 | H43: 50 | I43: 100 | J43: 60 | K43: 50 | L43: 100 | M43: 50 | N43: 100 | O43: 100 | P43: 100 | Q43: 40 | R43: 20 | S43: 100 | T43: 100 | U43: 100
A44: Job Details | B44: Additional Information | C44: Additional Job Classifications | D44: JobDetails_AdditionalInformation_AdditionalJobClassifications | E44: JobDetails_AdditionalInformation_AdditionalJobClassifications2 | G44: 508 - Tiempo Completo 40 Hrs (Category Spain-Spain)@AP.TP.NOC - Temporal TP Apertura Nocturno (Clausula Adicional (Additional Contract Clauses)-Spain)@001 - ETT (Employee Internal Contract-Spain) | H44: 508 - Tiempo Completo 40 Hrs (Category Spain-Spain)@AP.TP.NOC - Temporal TP Apertura Nocturno (Clausula Adicional (Additional Contract Clauses)-Spain)@001 - ETT (Employee Internal Contract-Spain) | I44: 508 - Tiempo Completo 40 Hrs (Category Spain-Spain)@AP.TP.NOC - Temporal TP Apertura Nocturno (Clausula Adicional (Additional Contract Clauses)-Spain)@001 - ETT (Employee Internal Contract-Spain) | J44: 508 - Tiempo Completo 40 Hrs (Category Spain-Spain)@AP.TP.NOC - Temporal TP Apertura Nocturno (Clausula Adicional (Additional Contract Clauses)-Spain)@001 - ETT (Employee Internal Contract-Spain) | K44: 508 - Tiempo Completo 40 Hrs (Category Spain-Spain)@AP.TP.NOC - Temporal TP Apertura Nocturno (Clausula Adicional (Additional Contract Clauses)-Spain)@001 - ETT (Employee Internal Contract-Spain) | L44: 508 - Tiempo Completo 40 Hrs (Category Spain-Spain)@AP.TP.NOC - Temporal TP Apertura Nocturno (Clausula Adicional (Additional Contract Clauses)-Spain)@001 - ETT (Employee Internal Contract-Spain) | M44: 508 - Tiempo Completo 40 Hrs (Category Spain-Spain)@AP.TP.NOC - Temporal TP Apertura Nocturno (Clausula Adicional (Additional Contract Clauses)-Spain)@001 - ETT (Employee Internal Contract-Spain) | N44: 508 - Tiempo Completo 40 Hrs (Category Spain-Spain)@AP.TP.NOC - Temporal TP Apertura Nocturno (Clausula Adicional (Additional Contract Clauses)-Spain)@001 - ETT (Employee Internal Contract-Spain) | O44: 508 - Tiempo Completo 40 Hrs (Category Spain-Spain)@AP.TP.NOC - Temporal TP Apertura Nocturno (Clausula Adicional (Additional Contract Clauses)-Spain)@001 - ETT (Employee Internal Contract-Spain) | P44: 508 - Tiempo Completo 40 Hrs (Category Spain-Spain)@AP.TP.NOC - Temporal TP Apertura Nocturno (Clausula Adicional (Additional Contract Clauses)-Spain)@001 - ETT (Employee Internal Contract-Spain) | Q44: 508 - Tiempo Completo 40 Hrs (Category Spain-Spain)@AP.TP.NOC - Temporal TP Apertura Nocturno (Clausula Adicional (Additional Contract Clauses)-Spain)@001 - ETT (Employee Internal Contract-Spain) | R44: 508 - Tiempo Completo 40 Hrs (Category Spain-Spain)@AP.TP.NOC - Temporal TP Apertura Nocturno (Clausula Adicional (Additional Contract Clauses)-Spain)@001 - ETT (Employee Internal Contract-Spain) | S44: 508 - Tiempo Completo 40 Hrs (Category Spain-Spain)@AP.TP.NOC - Temporal TP Apertura Nocturno (Clausula Adicional (Additional Contract Clauses)-Spain)@001 - ETT (Employee Internal Contract-Spain) | T44: 508 - Tiempo Completo 40 Hrs (Category Spain-Spain)@AP.TP.NOC - Temporal TP Apertura Nocturno (Clausula Adicional (Additional Contract Clauses)-Spain)@001 - ETT (Employee Internal Contract-Spain) | U44: 508 - Tiempo Completo 40 Hrs (Category Spain-Spain)@AP.TP.NOC - Temporal TP Apertura Nocturno (Clausula Adicional (Additional Contract Clauses)-Spain)@001 - ETT (Employee Internal Contract-Spain)
A45: Job Details | B45: Additional Information | C45: Work Shift | D45: JobDetails_AdditionalInformation_WorkShift | E45: JobDetails_AdditionalInformation_WorkShift2 | G45: 5 Days | H45: 3 Days | I45: 5 Days | J45: 4 Days | K45: 5 Days | L45: 5 Days | M45: 5 Days | N45: 5 Days | O45: 5 Days | P45: 5 Days | Q45: 5 Days | R45: 5 Days | S45: 5 Days | T45: 5 Days | U45: 5 Days
A46: Job Details | B46: Additional Information | C46: End Employment Date | D46: JobDetails_AdditionalInformation_EndEmploymentDate | E46: JobDetails_AdditionalInformation_EndEmploymentDate2 | F46: Set to N/A when field not present otherwise automation will throw error | G46: N/A | H46: =TODAY()+365 -> 45945 | I46: N/A | J46: N/A | K46: =TODAY()+365 -> 45945 | L46: N/A | M46: N/A | N46: =TODAY()+365 -> 45945 | O46: N/A | P46: N/A | Q46: =TODAY()+365 -> 45945 | R46: N/A | S46: N/A | T46: =TODAY()+365 -> 45945 | U46: N/A
A47: Job Details | B47: Additional Information | C47: Comments | D47: JobDetails_AdditionalInformation_Comments | E47: JobDetails_AdditionalInformation_Comments2 | G47: Automation Comments here…. | H47: Automation Comments here…. | I47: Automation Comments here…. | J47: Automation Comments here…. | K47: Automation Comments here…. | L47: Automation Comments here…. | M47: Automation Comments here…. | N47: Automation Comments here…. | O47: Automation Comments here…. | P47: Automation Comments here…. | Q47: Automation Comments here…. | R47: Automation Comments here…. | S47: Automation Comments here…. | T47: Automation Comments here…. | U47: Automation Comments here….
A48: Change Organization Assignments | B48: N/A | C48: Cost Center | D48: ChangeOrganizationAssignments_CostCenter | E48: ChangeOrganizationAssignments_CostCenter2 | G48: 94 | H48: 94 | I48: 92 | J48: 94 | K48: 92 | L48: 92 | M48: 92 | N48: 92 | O48: 92 | P48: 92 | Q48: 94 | R48: 94 | S48: 94 | T48: 94 | U48: 94
A49: Change Organization Assignments | B49: N/A | C49: Department Section | D49: ChangeOrganizationAssignments_DepartmentSection | E49: ChangeOrganizationAssignments_DepartmentSection2 | G49: 15 Childrens Accessories | H49: 16 Mens Accessories | I49: 251 Management Retail | J49: 253 Supervisors | K49: 251 Management Retail | L49: 251 Management Retail | M49: 251 Management Retail | N49: 251 Management Retail | O49: 251 Management Retail | P49: 251 Management Retail | Q49: 15 Childrens Accessories | R49: 16 Mens Accessories | S49: 256 | T49: 16 Mens Accessories | U49: 15 Childrens Accessories
A50: Assign Pay Group | B50: N/A | C50: Proposed Pay Group | D50: AssignPayGroup_ProposedPayGroup | E50: AssignPayGroup_ProposedPayGroup2 | G50: ES Monthly - 12 payments | H50: ES Monthly - 12 payments | I50: ES Monthly - 12 payments | J50: ES Monthly - 12 payments | K50: ES Monthly - 12 payments | L50: ES Monthly - 12 payments | M50: ES Monthly - 12 payments | N50: ES Monthly - 12 payments | O50: ES Monthly - 12 payments | P50: ES Monthly - 12 payments | Q50: ES Monthly - 12 payments | R50: ES Monthly - 12 payments | S50: ES Monthly - 12 payments | T50: ES Monthly - 12 payments | U50: ES Monthly - 12 payments
A51: Edit Additional Data | B51: N/A | C51: Estadol IRPF | D51: EditAdditionalData_EstadolIRPF | E51: EditAdditionalData_EstadolIRPF2 | G51: Soltero/a | H51: Soltero | I51: Soltero/a | J51: Soltero/a | K51: Soltero/a | L51: Soltero/a | M51: Soltero/a | N51: Soltero/a | O51: Soltero/a | P51: Soltero/a | Q51: Soltero/a | R51: Soltero/a | S51: Soltero/a | T51: Soltero/a | U51: Soltero/a
A52: Edit Additional Data | B52: N/A | C52: Minusvalia RH | D52: EditAdditionalData_MinusvaliaRH | E52: EditAdditionalData_MinusvaliaRH2 | G52: Del 33% hasta el 65% | H52: Del 33% hasta el 65% | I52: Del 33% hasta el 65% | J52: Del 33% hasta el 65% | K52: Del 33% hasta el 65% | L52: Del 33% hasta el 65% | M52: Del 33% hasta el 65% | N52: Del 33% hasta el 65% | O52: Del 33% hasta el 65% | P52: Del 33% hasta el 65% | Q52: Del 33% hasta el 65% | R52: Del 33% hasta el 65% | S52: Del 33% hasta el 65% | T52: Del 33% hasta el 65% | U52: Del 33% hasta el 65%
A53: Add Probation Period | B53: N/A | C53: Probation End Date | D53: AddProbationPeriod_ProbationEndDate | E53: AddProbationPeriod_ProbationEndDate2 | G53: =TODAY()+7 -> 45587 | H53: =TODAY()+7 -> 45587 | I53: =TODAY()+7 -> 45587 | J53: =TODAY()+7 -> 45587 | K53: =TODAY()+7 -> 45587 | L53: =TODAY()+7 -> 45587 | M53: =TODAY()+7 -> 45587 | N53: =TODAY()+7 -> 45587 | ... U53: =TODAY()+7 -> 45587
A54: Propose Compensation Hire | B54: N/A | C54: Salary | D54: ProposeCompensationHire_Salary | E54: ProposeCompensationHire_Salary2 | G54: Defaulted | H54: Defaulted | I54: Defaulted | J54: Defaulted | K54: Defaulted | L54: Defaulted | M54: Defaulted | N54: Defaulted | O54: Defaulted | P54: Defaulted | Q54: Defaulted | R54: Defaulted | S54: Defaulted | T54: Defaulted | U54: Defaulted
A55: Change My Personal Information | B55: N/A | C55: Gender | D55: ChangeMyPersonalInformation_Gender | E55: ChangeMyPersonalInformation_Gender2 | G55: Female | H55: Female | I55: Female | J55: Female | K55: Female | L55: Female | M55: Female | N55: Female | O55: Female | P55: Female | Q55: Female | R55: Female | S55: Female | T55: Female | U55: Female
A56: Change My Personal Information | B56: N/A | C56: Date Of Birth | D56: ChangeMyPersonalInformation_DateOfBirth | E56: ChangeMyPersonalInformation_DateOfBirth2 | G56: 29221 | H56: 29221 | I56: 29221 | J56: 29221 | K56: 29221 | L56: 29221 | M56: 29221 | N56: 29221 | O56: 29221 | P56: 29221 | Q56: 29221 | R56: 29221 | S56: 29221 | T56: 29221 | U56: 29221
A57: Change My Personal Information | B57: N/A | C57: Country Territory Of Birth | D57: ChangeMyPersonalInformation_CountryTerritoryOfBirth | E57: ChangeMyPersonalInformation_CountryTerritoryOfBirth2 | G57: Spain | H57: Spain | I57: Spain | J57: Spain | K57: Spain | L57: Spain | M57: Spain | N57: Spain | O57: Spain | P57: Spain | Q57: Spain | R57: Spain | S57: Spain | T57: Spain | U57: Spain
A58: Change My Personal Information | B58: N/A | C58: Region Of Birth | D58: ChangeMyPersonalInformation_RegionOfBirth | E58: ChangeMyPersonalInformation_RegionOfBirth2 | G58: Baleares | H58: Baleares | I58: Baleares | J58: Baleares | K58: Baleares | L58: Baleares | M58: Baleares | N58: Baleares | O58: Baleares | P58: Baleares | Q58: Baleares | R58: Baleares | S58: Baleares | T58: Baleares | U58: Baleares
A59: Change My Personal Information | B59: N/A | C59: City Of Birth | D59: ChangeMyPersonalInformation_CityOfBirth | E59: ChangeMyPersonalInformation_CityOfBirth2 | G59: Madrid | H59: Madrid | I59: Madrid | J59: Madrid | K59: Madrid | L59: Madrid | M59: Madrid | N59: Madrid | O59: Madrid | P59: Madrid | Q59: Madrid | R59: Madrid | S59: Madrid | T59: Madrid | U59: Madrid
A60: Change My Personal Information | B60: N/A | C60: Marital Status | D60: ChangeMyPersonalInformation_MaritalStatus | E60: ChangeMyPersonalInformation_MaritalStatus2 | G60: Married | H60: Married | I60: Married | J60: Married | K60: Married | L60: Married | M60: Married | N60: Married | O60: Married | P60: Married | Q60: Married | R60: Married | S60: Married | T60: Married | U60: Married
A61: Change My Personal Information | B61: N/A | C61: Marital Status Date | D61: ChangeMyPersonalInformation_MaritalStatusDate | E61: ChangeMyPersonalInformation_MaritalStatusDate2 | G61: 28/10/2011 | H61: 28/10/2011 | I61: 28/10/2011 | J61: 28/10/2011 | K61: 28/10/2011 | L61: 28/10/2011 | M61: 28/10/2011 | N61: 28/10/2011 | O61: 28/10/2011 | P61: 28/10/2011 | Q61: 28/10/2011 | R61: 28/10/2011 | S61: 28/10/2011 | T61: 28/10/2011 | U61: 28/10/2011
A62: Change My Personal Information | B62: N/A | C62: Primary Nationality | D62: ChangeMyPersonalInformation_PrimaryNationality | E62: ChangeMyPersonalInformation_PrimaryNationality2 | G62: Spain | H62: Spain | I62: Spain | J62: Spain | K62: Spain | L62: Spain | M62: Spain | N62: Spain | O62: Spain | P62: Spain | Q62: Spain | R62: Spain | S62: Spain | T62: Spain | U62: Spain
A63: Change My Government IDs | B63: National IDs | C63: Country1 | D63: ChangeMyGovernmentIDs_NationalIDs_Country1 | E63: ChangeMyGovernmentIDs_NationalIDs_Country12 | G63: Spain | H63: Spain | I63: Spain | J63: Spain | K63: Spain | L63: Spain | M63: Spain | N63: Spain | O63: Spain | P63: Spain | Q63: Spain | R63: Spain | S63: Spain | T63: Spain | U63: Spain
A64: Change My Government IDs | B64: National IDs | C64: National ID Type1 | D64: ChangeMyGovernmentIDs_NationalIDs_NationalIDType1 | E64: ChangeMyGovernmentIDs_NationalIDs_NationalIDType12 | G64: Social Security Number (NSS) | H64: Social Security Number (NSS) | I64: Social Security Number (NSS) | J64: Social Security Number (NSS) | K64: Social Security Number (NSS) | L64: Social Security Number (NSS) | M64: Social Security Number (NSS) | N64: Social Security Number (NSS) | O64: Social Security Number (NSS) | P64: Social Security Number (NSS) | Q64: Social Security Number (NSS) | R64: Social Security Number (NSS) | S64: Social Security Number (NSS) | T64: Social Security Number (NSS) | U64: Social Security Number (NSS)
A65: Change My Government IDs | B65: National IDs | C65: Add Edit ID1 | D65: ChangeMyGovernmentIDs_NationalIDs_AddEditID1 | E65: ChangeMyGovernmentIDs_NationalIDs_AddEditID12 | F65: Automation will throw error if not unique | G65: 281000345374 | H65: 281000345475 | I65: 281000345576 | J65: 281000346889 | K65: 281000345778 | L65: 281000345879 | M65: 281000345980 | N65: 281000346081 | O65: 281000346182 | P65: 281000346283 | Q65: 281000346384 | R65: 281000346485 | S65: 281000346586 | T65: 281000346687 | U65: 281000346788
A66: Change My Government IDs | B66: National IDs | C66: Country2 | D66: ChangeMyGovernmentIDs_NationalIDs_Country2 | E66: ChangeMyGovernmentIDs_NationalIDs_Country22 | G66: Spain | H66: Spain | I66: Spain | J66: Spain | K66: Spain | L66: Spain | M66: Spain | N66: Spain | O66: Spain | P66: Spain | Q66: Spain | R66: Spain | S66: Spain | T66: Spain | U66: Spain
A67: Change My Government IDs | B67: National IDs | C67: National ID Type2 | D67: ChangeMyGovernmentIDs_NationalIDs_NationalIDType2 | E67: ChangeMyGovernmentIDs_NationalIDs_NationalIDType22 | G67: ID Card (DNI) Number | H67: ID Card (DNI) Number | I67: ID Card (DNI) Number | J67: ID Card (DNI) Number | K67: ID Card (DNI) Number | L67: ID Card (DNI) Number | M67: ID Card (DNI) Number | N67: ID Card (DNI) Number | O67: ID Card (DNI) Number | P67: ID Card (DNI) Number | Q67: ID Card (DNI) Number | R67: ID Card (DNI) Number | S67: ID Card (DNI) Number | T67: ID Card (DNI) Number | U67: ID Card (DNI) Number
A68: Change My Government IDs | B68: National IDs | C68: Add Edit ID2 | D68: ChangeMyGovernmentIDs_NationalIDs_AddEditID2 | E68: ChangeMyGovernmentIDs_NationalIDs_AddEditID22 | F68: Automation will throw error if not unique | G68: 10003453V | H68: 10003454H | I68: 10003455L | J68: 10003468D | K68: 10003457K | L68: 10003458E | M68: 10003459T | N68: 10003460R | O68: 10003461W | P68: 10003462A | Q68: 10003463G | R68: 10003464M | S68: 10003465Y | T68: 10003466F | U68: 10003467P
A69: Payment Election Option | B69: N/A | C69: Bank Code | D69: PaymentElectionOption_BankCode | E69: PaymentElectionOption_BankCode2 | G69: BBVAESMM111 | H69: BBVAESMM111 | I69: BBVAESMM111 | J69: BBVAESMM111 | K69: BBVAESMM111 | L69: BBVAESMM111 | M69: BBVAESMM111 | N69: BBVAESMM111 | O69: BBVAESMM111 | P69: BBVAESMM111 | Q69: BBVAESMM111 | R69: BBVAESMM111 | S69: BBVAESMM111 | T69: BBVAESMM111 | U69: BBVAESMM111
A70: Payment Election Option | B70: N/A | C70: Account Type | D70: PaymentElectionOption_AccountType | E70: PaymentElectionOption_AccountType2 | G70: Checking | H70: Checking | I70: Checking | J70: Checking | K70: Checking | L70: Checking | M70: Checking | N70: Checking | O70: Checking | P70: Checking | Q70: Checking | R70: Checking | S70: Checking | T70: Checking | U70: Checking
A71: Payment Election Option | B71: N/A | C71: IBAN | D71: PaymentElectionOption_IBAN | E71: PaymentElectionOption_IBAN2 | G71: ES91 2100 0418 4502 0005 1332 | H71: ES91 2100 0418 4502 0005 1332 | I71: ES91 2100 0418 4502 0005 1332 | J71: ES91 2100 0418 4502 0005 1332 | K71: ES91 2100 0418 4502 0005 1332 | L71: ES91 2100 0418 4502 0005 1332 | M71: ES91 2100 0418 4502 0005 1332 | N71: ES91 2100 0418 4502 0005 1332 | O71: ES91 2100 0418 4502 0005 1332 | P71: ES91 2100 0418 4502 0005 1332 | Q71: ES91 2100 0418 4502 0005 1332 | R71: ES91 2100 0418 4502 0005 1332 | S71: ES91 2100 0418 4502 0005 1332 | T71: ES91 2100 0418 4502 0005 1332 | U71: ES91 2100 0418 4502 0005 1332

Sheet SpainIDs
D1: 45132.607 | E1: 45132.607
D2: 281000150061 | E2: 10001500L
D3: 281000150162 | E3: 10001501C
D4: 281000150263 | E4: 10001502K
D5: 281000150364 | E5: 10001503E
D6: 281000150465 | E6: 10001504T
D7: 281000150566 | E7: 10001505R
D8: 281000150667 | E8: 10001506W
D9: 281000150768 | E9: 10001507A
D10: 281000150869 | E10: 10001508G
D11: 281000150970 | E11: 10001509M
D12: 281000151071 | E12: 10001510Y
D13: 281000151172 | E13: 10001511F
... D1923: 281000342142 | E1923: 10003421P
B1924: gayatri | C1924: 45562 | D1924: 281000342243 | E1924: 10003422D
D1925: 281000342344 | E1925: 10003423X
D1926: 281000342445 | E1926: 10003424B
D1927: 281000342546 | E1927: 10003425N
D1928: 281000342647 | E1928: 10003426J
D1929: 281000342748 | E1929: 10003427Z
D1930: 281000342849 | E1930: 10003428S
D1931: 281000342950 | E1931: 10003429Q
D1932: 281000343051 | E1932: 10003430V
D1933: 281000343152 | E1933: 10003431H
D1934: 281000343253 | E1934: 10003432L
D1935: 281000343354 | E1935: 10003433C
D1936: 281000343455 | E1936: 10003434K
... D1952: 281000345071 | E1952: 10003450Z
D1953: 281000345172 | E1953: 10003451S | F1953: 45569 | G1953: gayatri
D1954: 281000345273 | E1954: 10003452Q
D1955: 281000345374 | E1955: 10003453V
D1956: 281000345475 | E1956: 10003454H
D1957: 281000345576 | E1957: 10003455L
D1958: 281000345677 | E1958: 10003456C
D1959: 281000345778 | E1959: 10003457K
D1960: 281000345879 | E1960: 10003458E
D1961: 281000345980 | E1961: 10003459T
D1962: 281000346081 | E1962: 10003460R
D1963: 281000346182 | E1963: 10003461W
D1964: 281000346283 | E1964: 10003462A
D1965: 281000346384 | E1965: 10003463G
... D1968: 281000346687 | E1968: 10003466F
D1969: 281000346788 | E1969: 10003467P | F1969: 45576 | G1969: gayatri
D1970: 281000346889 | E1970: 10003468D
D1971: 281000346990 | E1971: 10003469X
D1972: 281000347091 | E1972: 10003470B
D1973: 281000347192 | E1973: 10003471N
D1974: 281000347293 | E1974: 10003472J
D1975: 281000347394 | E1975: 10003473Z
D1976: 281000347495 | E1976: 10003474S
D1977: 281000347596 | E1977: 10003475Q
D1978: 281000347600 | E1978: 10003476V
D1979: 281000347701 | E1979: 10003477H
D1980: 281000347802 | E1980: 10003478L
D1981: 281000347903 | E1981: 10003479C
... D3000: 281000449852 | E3000: 10004498G
D3001: 281000449953 | E3001: 10004499M | F3001: 9022024 | G3001: next 50 ids
D3002: 281000450054 | E3002: 10004500Y
D3003: 281000450155 | E3003: 10004501F
D3004: 281000450256 | E3004: 10004502P
D3005: 281000450357 | E3005: 10004503D
D3006: 281000450458 | E3006: 10004504X
D3007: 281000450559 | E3007: 10004505B
D3008: 281000450660 | E3008: 10004506N
D3009: 281000450761 | E3009: 10004507J
D3010: 281000450862 | E3010: 10004508Z
D3011: 281000450963 | E3011: 10004509S
D3012: 281000451064 | E3012: 10004510Q
D3013: 281000451165 | E3013: 10004511V
... D5001: 281000649916 | E5001: 10006499G
