Workbook
Name AddAdditonalName_Country: Test_Data!#REF!
Name AddAdditonalName_FamilyName: Test_Data!#REF!
Name AddAdditonalName_GivenName: Test_Data!#REF!
Name AddAdditonalName_NameType: Test_Data!#REF!
Name AddProbationPeriod_ProbationEndDate: Test_Data!#REF!
Name AddProbationPeriod_ProbationEndDate2: Test_Data!#REF!
Name AddProbationPeriod_ProbationEndDate2: Automation_Lookups!$AO$2:$AO$4
Name AddProbationPeriod_ProbationReviewDate: Test_Data!#REF!
Name AssignPayGroup_ProposedPayGroup: Test_Data!$E$70
Name AssignPayGroup_ProposedPayGroup: Automation_Lookups!$T$2:$T$20
Name AssignPayGroup_ProposedPayGroup2: Test_Data!$F$70
Name AssignPayGroup_ProposedPayGroup2: Automation_Lookups!$T$2
Name AssignPayGroup_ProposedPayGroupFinal: Test_Data!$E$70
Name AssignPayGroup_ProposedPayGroupInitial: Test_Data!$E$69
Name Automation_Ref: Test_Data!$E$14:$F$14
Name AutomationComments: Test_Data!$E$11:$F$11
Name ChangeMyEmergencyContacts_Address_City: Test_Data!#REF!
Name ChangeMyEmergencyContacts_Address_HouseNumber: Test_Data!#REF!
Name ChangeMyEmergencyContacts_Address_PostalCode: Test_Data!#REF!
Name ChangeMyEmergencyContacts_Address_Province: Test_Data!#REF!
Name ChangeMyEmergencyContacts_Address_StreetName: Test_Data!#REF!
Name ChangeMyEmergencyContacts_Address_Type: Test_Data!#REF!
Name ChangeMyEmergencyContacts_City: Test_Data!#REF!
Name ChangeMyEmergencyContacts_Email_Address: Test_Data!#REF!
Name ChangeMyEmergencyContacts_Email_Type: Test_Data!#REF!
Name ChangeMyEmergencyContacts_EmailAddress: Test_Data!#REF!
Name ChangeMyEmergencyContacts_FamilyName: Test_Data!#REF!
Name ChangeMyEmergencyContacts_GivenName: Test_Data!#REF!
Name ChangeMyEmergencyContacts_LegalName_FamilyName: Test_Data!#REF!
Name ChangeMyEmergencyContacts_LegalName_GivenName: Test_Data!#REF!
Name ChangeMyEmergencyContacts_LegalName_Prefix: Test_Data!#REF!
Name ChangeMyEmergencyContacts_PhoneDevice: Test_Data!#REF!
Name ChangeMyEmergencyContacts_PhoneDevice2: Automation_Lookups!$AJ$2:$AJ$3
Name ChangeMyEmergencyContacts_PhoneNumber: Test_Data!#REF!
Name ChangeMyEmergencyContacts_PostalCode: Test_Data!#REF!
Name ChangeMyEmergencyContacts_PreferredLanguage: Test_Data!#REF!
Name ChangeMyEmergencyContacts_Relationship: Test_Data!#REF!
Name ChangeMyEmergencyContacts_Relationship2: Automation_Lookups!$AI$2:$AI$5
Name ChangeMyEmergencyContacts_StreetName: Test_Data!#REF!
Name ChangeMyGovernmentIDs_NationalIDs_AddEditID: Test_Data!#REF!
Name ChangeMyGovernmentIDs_NationalIDs_AddEditID1: Test_Data!$E$57
Name ChangeMyGovernmentIDs_NationalIDs_AddEditID12: Test_Data!$F$57
Name ChangeMyGovernmentIDs_NationalIDs_AddEditID2: Test_Data!#REF!
Name ChangeMyGovernmentIDs_NationalIDs_AddEditID22: Automation_Lookups!$AL$2:$AL$4
Name ChangeMyGovernmentIDs_NationalIDs_AddEditID22: Test_Data!#REF!
Name ChangeMyGovernmentIDs_NationalIDs_AddEditID3: Test_Data!#REF!
Name ChangeMyGovernmentIDs_NationalIDs_Country1: Test_Data!$E$55
Name ChangeMyGovernmentIDs_NationalIDs_Country12: Test_Data!$F$55
Name ChangeMyGovernmentIDs_NationalIDs_Country2: Test_Data!#REF!
Name ChangeMyGovernmentIDs_NationalIDs_Country22: Test_Data!#REF!
Name ChangeMyGovernmentIDs_NationalIDs_Country3: Test_Data!#REF!
Name ChangeMyGovernmentIDs_NationalIDs_ExpirationDate1: Test_Data!#REF!
Name ChangeMyGovernmentIDs_NationalIDs_ExpirationDate2: Test_Data!#REF!
Name ChangeMyGovernmentIDs_NationalIDs_IssuedBy2: Test_Data!#REF!
Name ChangeMyGovernmentIDs_NationalIDs_IssuedDate1: Test_Data!#REF!
Name ChangeMyGovernmentIDs_NationalIDs_IssuedDate2: Test_Data!#REF!
Name ChangeMyGovernmentIDs_NationalIDs_NationalIDType1: Test_Data!$E$56
Name ChangeMyGovernmentIDs_NationalIDs_NationalIDType12: Test_Data!$F$56
Name ChangeMyGovernmentIDs_NationalIDs_NationalIDType12: Automation_Lookups!$AK$2:$AK$5
Name ChangeMyGovernmentIDs_NationalIDs_NationalIDType2: Test_Data!#REF!

Sheet Information
A1: Version | F1: Info
A6: Version | B6: 0.3 | F6: Info
F7: Dates | G7: For Czech all dates to be entered in format of DD/MM/YYYY
A8: History | F8: Unhighlighted fields | G8: Only data in unhighlighted fields can be changed.
A9: Date | B9: Version | C9: Details | F9: Red highlighted fields | G9: Indicates fields where unique data is required otherwise automation will throw errors
A10: 44061 | B10: 0.3 | C10: Initial Release | F10: Grey highlighted fields | G10: Indicates fields that cannot be changed
F11: Last Run Status / Last Run Error Message | G11: When automation has run for a particular test, we need to check the status is set to Passed and no error messages are present for each test before the automation run for that particular test is considered valid

Sheet Defects
B2: Batch 1 - Summary | E2: Batch 2 - Summary | H2: Batch 3 - Summary | K2: All E2E Cycle 1 - Summary
B3: Description | C3: Total | E3: Description | F3: Total | H3: Description | I3: Total | K3: Description | L3: Total No. | M3: %
B4: Passed | C4: 35 | E4: Passed | F4: 141 | H4: Passed | I4: 0 | K4: Passed | L4: =C4+F4+I4 -> 176 | M4: =L4/L8*100 -> 72.131148
B5: Failed | C5: 17 | E5: Failed | F5: 27 | H5: Failed | I5: 24 | K5: Failed | L5: =C5+F5+I5 -> 68 | M5: =L5/L8*100 -> 27.868852
B6: Not Run | C6: 0 | E6: Not Run | F6: 0 | H6: Not Run | I6: 0 | K6: Not Run | L6: =C6+F6+I6 -> 0 | M6: =L6/L8*100 -> 0
B7: Executed | C7: 52 | E7: Executed | F7: 168 | H7: Executed | I7: 24 | K7: Executed | L7: =C7+F7+I7 -> 244 | M7: =L7/L8*100 -> 100
B8: Total | C8: 52 | E8: Total | F8: 168 | H8: Total | I8: 24 | K8: Total | L8: =C8+F8+I8 -> 244 | M8: =M4+M5+M6 -> 100
B10: Batch 1 - Defects | E10: Batch 2 - Defects | H10: Batch 3 - Defects | K10: All E2E Cycle 1 - Defects
B11: Failed Tests Description | C11: Total | E11: Failed Tests Description | F11: Total | H11: Failed Tests Description | I11: Total | K11: Failed Tests Description | L11: Total No. | M11: %
B12: P&C Salary Assistant/Supervisor Salary Configuration missing | C12: 12 | E12: Grade Profile not populated causing salary to remain blank | F12: 24 | H12: Data issue - Rerun scheduled | I12: 24 | K12: Personal Information Change Approval Email missing after 2nd and final proxy into HR Manager | L12: 44 | M12: =L12/L17*100 -> 35.2
B13: Automation issue with Maiden Name - Gary to discuss with Shane/Andre | C13: 5 | E13: GC - Under Investigation | F13: 3 | H13: Total | I13: 24 | K13: Open button not available to assign paygroup for payroll. Approval required by David Bradley... | L13: 20 | M13: =L13/L17*100 -> 16
B14: Total | C14: =C12+C13 -> 17 | E14: Total | F14: 27 | K14: Grade Profile not populated causing salary to remain blank | L14: 34 | M14: =L14/L17*100 -> 27.2
K15: Data issue - Rerun scheduled | L15: 24 | M15: =L15/L17*100 -> 19.2
K16: GC - Under Investigation | L16: 3 | M16: =L16/L17*100 -> 2.4
K17: Total | L17: =SUM(L12:L16) -> 125 | M17: =SUM(M12:M16) -> 100

Sheet Automation_Lookups
A1: Process2 | B1: ExecutionFlag2 | C1: SupervisoryOrganisation_SupervisoryOrganisation2 | D1: LegalNameInformation_Country2 | E1: ContactInformation_Phone_CountryPhoneCode2 | F1: ContactInformation_Phone_PhoneDevice2 | G1: ContactInformation_Phone_Type2 | H1: ContactInformation_Address_Type2 | I1: ContactInformation_Email_Type2 | J1: JobDetails_HireDate2 | K1: JobDetails_Reason2 | L1: JobDetails_Position2 | M1: JobDetails_EmployeeType2 | N1: JobDetails_JobProfile2 | O1: JobDetails_TimeType2 | P1: JobDetails_Location2 | Q1: JobDetails_AdditionalInformation_WorkShift2 | R1: JobDetails_AdditionalInformation_EndEmploymentDate2 | S1: ChangeOrganizationAssignments_DepartmentSection2 | T1: AssignPayGroup_ProposedPayGroup2 | U1: Proxy_ProxyNumber2 | V1: Proxy_OnBehalfOf2 | W1: MaintainEmployeeContract_Reason2 | X1: MaintainEmployeeContract_Status2 | Y1: MaintainEmployeeContract_ContractType2 | Z1: MaintainEmployeeContract_ContractEndDate2 | AA1: ProposeCompensationHire_GradeProfile2 | AB1: ProposeCompensationHire_Step2 | AC1: EditPassportsandVisas_Country2 | AD1: EditPassportsandVisas_PassportIDType2 | AE1: EditPassportsandVisas_IdentificationNo2 | AF1: EditPassportsandVisas_IssuedDate2 | AG1: EditPassportsandVisas_ExpirationDate2 | AH1: ChangeMyPersonalInformation_MaritalStatus2 | AI1: ChangeMyEmergencyContacts_Relationship2 | AJ1: ChangeMyEmergencyContacts_PhoneDevice2 | AK1: ChangeMyGovernmentIDs_NationalIDs_NationalIDType12 | AL1: ChangeMyGovernmentIDs_NationalIDs_AddEditID22 | AM1: PaymentElectionOption_AccountType2 | AN1: SkillsAndExperience_AddEducation_School2 | AO1: AddProbationPeriod_ProbationEndDate2 | AP1: EditAdditionalData_PayrollTaxDeduction | AQ1: HealthCareProvider_MealVoucher2 | AR1: School1 | AS1: School2 | AT1: ContactInformation_Address_Province2 | AU1: ChangeMyGovernmentIDs_NationalIDs_NationalIDType12 | AV1: ChangeMyGovernmentIDs_NationalIDs_NationalIDType22 | AW1: EditAdditionalData_EstadolIRPF2 | AX1: EditAdditionalData_MinusvaliaRH2
A2: New Hire | B2: Yes | C2: 362 Recruitment (Carolina De La Barrera Crespo (375)) | D2: Czechia | E2: Czechia (+420) | F2: Mobile | G2: Home | H2: Home | I2: Home | J2: =IF(MONTH(TODAY())<10,"0"&MONTH(TODAY())&"/",MONTH(TODAY())&"/") & IF(DAY(TODAY())<10,"0"&DAY(TODAY())&"/",DAY(TODAY())&"/") & YEAR(TODAY()) -> 03/04/2025 | K2: New Hire | L2: Assistant Manager-2 | M2: Fixed Term | N2: DPP/DPC | O2: Full time | P2: 362 Algeciras | Q2: 1 Day | R2: =IF(MONTH(TODAY())<10,"0"&MONTH(TODAY())&"/",MONTH(TODAY())&"/") & IF(DAY(TODAY())<10,"0"&DAY(TODAY())&"/",DAY(TODAY())&"/") & YEAR(TODAY()) -> 03/04/2025 | S2: Accessories | T2: Please select a Spanish Pay Group | U2: 10223439 | V2: Iwona Chrostowska (10223439) | W2: for the purposes of performing any work of casual or seasonal nature | X2: 1st Fixed Term Contract | Y2: Employment Agreement | Z2: =IF(MONTH(TODAY())<10,"0"&MONTH(TODAY())&"/",MONTH(TODAY())&"/") & IF(DAY(TODAY())<10,"0"&DAY(TODAY())&"/",DAY(TODAY())&"/") & YEAR(TODAY()) -> 03/04/2025 | AA2: Defaulted | AB2: Defaulted | AH2: Single | AI2: Father | AJ2: Mobile/Cell | AK2: Social Security Number (NSS) | AL2: Social Security Number (NSS) | AM2: Savings | AN2: N/A | AO2: =IF(MONTH(TODAY()+100)<10,"0"&MONTH(TODAY()+100)&"/",MONTH(TODAY()+100)&"/") & IF(DAY(TODAY()+100)<10,"0"&DAY(TODAY()+100)&"/",DAY(TODAY()+100)&"/") & YEAR(TODAY()+100) -> 06/12/2025 | AP2: Yes | AQ2: Yes | AR2: Střední bez maturity či výučního listu | AS2: stredni bez maturity ci vyucniho listu | AT2: Madrid | AU2: Social Security Number (NSS) | AV2: ID Card (DNI) Number | AW2: Soltero/a, viudo/a, divorciado/a o separado/a legalmente con hijos solteros menores de 18 años o incapacitados judicialmente que conviven exclusivamente con Vd., sin convivir también con el otro progenitor Soltero/a, viudo/a, divorciado/a o separado/a legalmente con hijos solteros menores de 18 años o incapacitados judicialmente que conviven exclusivamente con Vd., sin convivir también con el otro progenitor | AX2: Del 33% hasta el 65%
A3: New Role & New Hire | B3: No | C3: 895 Store Management (Male Teststmanager (10224969)) | D3: Czechia | E3: Czechia (+420) | F3: Landline | G3: Work | H3: Work | I3: Work | J3: =IF(MONTH(TODAY()-10)<10,"0"&MONTH(TODAY()-10)&"/",MONTH(TODAY()-10))&"/" & IF(DAY(TODAY()-10)<10,"0"&DAY(TODAY()-10)&"/",DAY(TODAY()-10)&"/") & YEAR(TODAY()-10) -> 02//22/2025 | L3: Assistant Manager-3 | M3: Intern | N3: Retail Assistant | O3: Part time | Q3: 2 Days | R3: =IF(MONTH(TODAY()+100)<10,"0"&MONTH(TODAY()+100)&"/",MONTH(TODAY()+100)&"/") & IF(DAY(TODAY()+100)<10,"0"&DAY(TODAY()+100)&"/",DAY(TODAY()+100)&"/") & YEAR(TODAY()+100) -> 06/12/2025 | T3: ES Monthly - 15 payments | U3: 10225553 | V3: Kocour Mikeš (10225553) | W3: for the purposes of performing work during the term of office | X3: 2nd Fixed Term Contract | Y3: Agreement to perform work | Z3: =IF(MONTH(TODAY()+100)<10,"0"&MONTH(TODAY()+100)&"/",MONTH(TODAY()+100)&"/") & IF(DAY(TODAY()+100)<10,"0"&DAY(TODAY()+100)&"/",DAY(TODAY()+100)&"/") & YEAR(TODAY()+100) -> 06/12/2025 | AH3: Married | AI3: Mother | AJ3: Telephone - Landline | AK3: ID Card (DNI) Number | AL3: ID Card (DNI) Number | AM3: Checking | AN3: Vseobecne stredni s maturitou | AO3: =IF(MONTH(TODAY()+1000)<10,"0"&MONTH(TODAY()+1000)&"/",MONTH(TODAY()+1000)&"/") & IF(DAY(TODAY()+1000)<10,"0"&DAY(TODAY()+1000)&"/",DAY(TODAY()+1000)&"/") & YEAR(TODAY()+1000) -> 11/29/2027 | AP3: No | AQ3: No | AR3: Střední odborné vzdělání s výučním listem | AS3: stredni odborne vzdelani s vyucnim listem
D4: Poland | E4: Poland (+48) | J4: =IF(MONTH(TODAY()+10)<10,"0"&MONTH(TODAY()+10)&"/",MONTH(TODAY()+10)&"/") & IF(DAY(TODAY()+10)<10,"0"&DAY(TODAY()+10)&"/",DAY(TODAY()+10)&"/") & YEAR(TODAY()+10) -> 03/14/2025 | L4: Test Store Manager-2 | M4: Permanent | N4: Department Manager | Q4: 3 Days | R4: =IF(MONTH(TODAY()+1000)<10,"0"&MONTH(TODAY()+1000)&"/",MONTH(TODAY()+1000)&"/") & IF(DAY(TODAY()+1000)<10,"0"&DAY(TODAY()+1000)&"/",DAY(TODAY()+1000)&"/") & YEAR(TODAY()+1000) -> 11/29/2027 | W4: for the purposes of substituting an employee during his/her excused absence at work | X4: 3rd Fixed Term Contract | Y4: Agreement to complete a job | Z4: =IF(MONTH(TODAY()+1000)<10,"0"&MONTH(TODAY()+1000)&"/",MONTH(TODAY()+1000)&"/") & IF(DAY(TODAY()+1000)<10,"0"&DAY(TODAY()+1000)&"/",DAY(TODAY()+1000)&"/") & YEAR(TODAY()+1000) -> 11/29/2027 | AH4: Not Disclosed | AI4: Spouse | AK4: Alien Identification Number (NIE) | AL4: Alien Identification Number (NIE) | AO4: N/A | AR4: Všeobecné střední s maturitou | AS4: vseobecne stredni s maturitou
D5: Poland | E5: Poland (+48) | L5: N/A | M5: Students | N5: Senior Department Manager | Q5: 4 Days | R5: N/A | W5: No reason necessary | X5: Active | Z5: N/A | AI5: Partner | AK5: Tax Identification Number (NIF) | AR5: Vysokoškolské Bc. | AS5: Vysokoskolske Bc
N6: Supervisor | Q6: 5 Days | X6: Inactive | AR6: Vysokoškolské MUDr., JUDr., Mgr., MgA., Ing. | AS6: vysokoskolske MUDR., JUDr., Mgr., MgA., Ing.
N7: P&C Supervisor | AR7: Vysokoškolské PhDr, PhD, JUDr, MUDr | AS7: vysokoskolske PhDr, PhD, JUDr, MUDr
N8: P&C Assistant | AR8: vyšší odborné DiS | AS8: vyssi odborne DiS
N9: Trainee Manager | AR9: Základní | AS9: Zakladni
N10: Assistant Manager
N11: P&C Manager
N12: Store Manager
N13: Visual Merchandiser Manager
N14: Visual Merchandising Supervisor
N15: Visual Merchandising Assistant
K21: Rehire | U21: 8701839 | V21: Lisanne Kluinhaar (8701839) | W21: Defined contract end date (Determined) | AQ21: Netherlands Retail Assistant
C22: 701 Recruitment (Lisanne Kluinhaar (8701839)) | D22: Netherlands | E22: Netherlands (+31) | K22: Seasonal | W22: Undefined contract end date (Undetermined) | Y22: Part-time( PT ) | AQ22: Netherlands Retail Assistant Cash Office | AR22: Retail Assistant (18)
W23: Intern | Y23: Full-time( FT. ) | AR23: Retail Assistant (19)
C24: Retail - Central & Eastern Europe (Stephen Regan (9910010) (Inherited) | D24: Poland | E24: Poland (+48) | AR24: Retail Assistant (20)
C25: Retail Poland Area: Central Poland (Stephen Regan (9910010) (Inherited)) | D25: Poland | E25: Poland (+48) | AR25: Retail Assistant (21)
AR26: Retail Assistant (22)
AR27: Retail Assistant (23+)
AR28: Retail Assistant (Under 18)

Sheet RC. No
A1: D.O.B | B1: 35139 | C1: 33054 | D1: 31390 | F1: r col b | G1: r col c | H1: r col d
B2: 9603150007 | C2: 9006300006 | D2: 8512090004 | F2: =B2/11 -> 873013637 | G2: =C2/11 -> 818754546 | H2: =D2/11 -> 773826364
B3: =B2+11 -> 9603150018 | C3: =C2+11 -> 9006300017 | D3: =D2+11 -> 8512090015 | F3: =B3/11 -> 873013638 | G3: =C3/11 -> 818754547 | H3: =D3/11 -> 773826365
B4: =B3+11 -> 9603150029 | C4: =C3+11 -> 9006300028 | D4: =D3+11 -> 8512090026 | F4: =B4/11 -> 873013639 | G4: =C4/11 -> 818754548 | H4: =D4/11 -> 773826366
B5: =B4+11 -> 9603150040 | C5: =C4+11 -> 9006300039 | D5: =D4+11 -> 8512090037 | F5: =B5/11 -> 873013640 | G5: =C5/11 -> 818754549 | H5: =D5/11 -> 773826367
B6: =B5+11 -> 9603150051 | C6: =C5+11 -> 9006300050 | D6: =D5+11 -> 8512090048 | F6: =B6/11 -> 873013641 | G6: =C6/11 -> 818754550 | H6: =D6/11 -> 773826368
B7: =B6+11 -> 9603150062 | C7: =C6+11 -> 9006300061 | D7: =D6+11 -> 8512090059 | F7: =B7/11 -> 873013642 | G7: =C7/11 -> 818754551 | H7: =D7/11 -> 773826369
B8: =B7+11 -> 9603150073 | C8: =C7+11 -> 9006300072 | D8: =D7+11 -> 8512090070 | F8: =B8/11 -> 873013643 | G8: =C8/11 -> 818754552 | H8: =D8/11 -> 773826370
B9: =B8+11 -> 9603150084 | C9: =C8+11 -> 9006300083 | D9: =D8+11 -> 8512090081 | F9: =B9/11 -> 873013644 | G9: =C9/11 -> 818754553 | H9: =D9/11 -> 773826371
B10: =B9+11 -> 9603150095 | C10: =C9+11 -> 9006300094 | D10: =D9+11 -> 8512090092 | F10: =B10/11 -> 873013645 | G10: =C10/11 -> 818754554 | H10: =D10/11 -> 773826372
B11: =B10+11 -> 9603150106 | C11: =C10+11 -> 9006300105 | D11: =D10+11 -> 8512090103 | F11: =B11/11 -> 873013646 | G11: =C11/11 -> 818754555 | H11: =D11/11 -> 773826373
B12: =B11+11 -> 9603150117 | C12: =C11+11 -> 9006300116 | D12: =D11+11 -> 8512090114 | F12: =B12/11 -> 873013647 | G12: =C12/11 -> 818754556 | H12: =D12/11 -> 773826374
B13: =B12+11 -> 9603150128 | C13: =C12+11 -> 9006300127 | D13: =D12+11 -> 8512090125 | F13: =B13/11 -> 873013648 | G13: =C13/11 -> 818754557 | H13: =D13/11 -> 773826375
B14: =B13+11 -> 9603150139 | C14: =C13+11 -> 9006300138 | D14: =D13+11 -> 8512090136 | F14: =B14/11 -> 873013649 | G14: =C14/11 -> 818754558 | H14: =D14/11 -> 773826376
... B28: =B27+11 -> 9603150293 | C28: =C27+11 -> 9006300292 | D28: =D27+11 -> 8512090290 | F28: =B28/11 -> 873013663 | G28: =C28/11 -> 818754572 | H28: =D28/11 -> 773826390
B29: =B28+11 -> 9603150304
B30: =B29+11 -> 9603150315
B31: =B30+11 -> 9603150326
B32: =B31+11 -> 9603150337
B33: =B32+11 -> 9603150348
B34: =B33+11 -> 9603150359
B35: =B34+11 -> 9603150370
B36: =B35+11 -> 9603150381
B37: =B36+11 -> 9603150392
B38: =B37+11 -> 9603150403
B39: =B38+11 -> 9603150414
B40: =B39+11 -> 9603150425
... B75: =B74+11 -> 9603150810
B76: =B75+11 -> 9603150821 | X76: New RC Numbers
B77: =B76+11 -> 9603150832 | X77: 9202101337
B78: =B77+11 -> 9603150843 | X78: =SUM(X77)+11 -> 9202101348
B79: =B78+11 -> 9603150854 | X79: =SUM(X78)+11 -> 9202101359
B80: =B79+11 -> 9603150865 | X80: =SUM(X79)+11 -> 9202101370
B81: =B80+11 -> 9603150876 | X81: =SUM(X80)+11 -> 9202101381
B82: =B81+11 -> 9603150887 | X82: =SUM(X81)+11 -> 9202101392
B83: =B82+11 -> 9603150898 | X83: =SUM(X82)+11 -> 9202101403
B84: =B83+11 -> 9603150909 | X84: =SUM(X83)+11 -> 9202101414
B85: =B84+11 -> 9603150920 | X85: =SUM(X84)+11 -> 9202101425
B86: =B85+11 -> 9603150931 | D86: 9603170269 | X86: =SUM(X85)+11 -> 9202101436
D87: =D86+11 -> 9603170280 | F87: 9603170280 | H87: 9603170280 | I87: 9603170291 | J87: 9603170302 | K87: 9603170313 | L87: 9603170324 | M87: 9603170335 | N87: 9603170346 | O87: 9603170357 | P87: 9603170368 | Q87: 9603170379 | R87: 9603170390 | S87: 9603170401 | T87: 9603170412 | X87: =SUM(X86)+11 -> 9202101447
D88: =D87+11 -> 9603170291 | F88: 9603170291 | X88: =SUM(X87)+11 -> 9202101458
D89: =D88+11 -> 9603170302 | F89: 9603170302 | H89: 9603170412 | I89: =H89+11 -> 9603170423 | J89: =I89+11 -> 9603170434 | K89: =J89+11 -> 9603170445 | L89: =K89+11 -> 9603170456 | M89: =L89+11 -> 9603170467 | N89: =M89+11 -> 9603170478 | O89: =N89+11 -> 9603170489 | P89: =O89+11 -> 9603170500 | ... T89: =S89+11 -> 9603170544 | X89: =SUM(X88)+11 -> 9202101469
D90: =D89+11 -> 9603170313 | F90: 9603170313 | X90: =SUM(X89)+11 -> 9202101480
D91: =D90+11 -> 9603170324 | F91: 9603170324 | X91: =SUM(X90)+11 -> 9202101491
D92: =D91+11 -> 9603170335 | F92: 9603170335 | X92: =SUM(X91)+11 -> 9202101502
D93: =D92+11 -> 9603170346 | F93: 9603170346 | X93: =SUM(X92)+11 -> 9202101513
D94: =D93+11 -> 9603170357 | F94: 9603170357 | X94: =SUM(X93)+11 -> 9202101524
D95: =D94+11 -> 9603170368 | F95: 9603170368 | X95: =SUM(X94)+11 -> 9202101535
D96: =D95+11 -> 9603170379 | F96: 9603170379 | X96: =SUM(X95)+11 -> 9202101546
D97: =D96+11 -> 9603170390 | F97: 9603170390 | X97: =SUM(X96)+11 -> 9202101557
D98: =D97+11 -> 9603170401 | F98: 9603170401 | X98: =SUM(X97)+11 -> 9202101568
D99: =D98+11 -> 9603170412 | F99: 9603170412 | X99: =SUM(X98)+11 -> 9202101579
X100: =SUM(X99)+11 -> 9202101590
X101: =SUM(X100)+11 -> 9202101601
X102: =SUM(X101)+11 -> 9202101612
X103: =SUM(X102)+11 -> 9202101623
X104: =SUM(X103)+11 -> 9202101634
X105: =SUM(X104)+11 -> 9202101645
X106: =SUM(X105)+11 -> 9202101656
X107: =SUM(X106)+11 -> 9202101667
X108: =SUM(X107)+11 -> 9202101678
X109: =SUM(X108)+11 -> 9202101689
X110: =SUM(X109)+11 -> 9202101700
X111: =SUM(X110)+11 -> 9202101711
... X133: =SUM(X132)+11 -> 9202101953

Sheet Code_Ranjeeta
B1: Variable Row | C1: Variable Value | D1: Row Number Declaration --------------------------------- intRowProcess = comExcelWorksheet.Range("Process").Row | E1: Value Declaration ------------------------ strProcess = comExcelWorksheet.Cells(intRowProcess, intColTestColumn).Value | F1: Getters
A2: =Test_Data!D3 -> Process | B2: ="Private intRow" & A2 -> Private intRowProcess | C2: ="Private str" & A2 -> Private strProcess | D2: ="intRow" & A2 & " = comExcelWorksheet.Range(""" & A2 & """).Row" -> intRowProcess = comExcelWorksheet.Range("Process").Row | E2: ="str" & A2 & " = comExcelWorksheet.Cells(intRow" & A2 & ", intColTestColumn).Value" -> strProcess = comExcelWorksheet.Cells(intRowProcess, intColTestColumn).Value | F2: ="Public Property Get get" & A2 & "() : get" & A2 & " = str" & A2 & " : End Property" -> Public Property Get getProcess() : getProcess = strProcess : End Property
A3: =Test_Data!D4 -> ExecutionFlag | B3: ="Private intRow" & A3 -> Private intRowExecutionFlag | C3: ="Private str" & A3 -> Private strExecutionFlag | D3: ="intRow" & A3 & " = comExcelWorksheet.Range(""" & A3 & """).Row" -> intRowExecutionFlag = comExcelWorksheet.Range("ExecutionFlag").Row | E3: ="str" & A3 & " = comExcelWorksheet.Cells(intRow" & A3 & ", intColTestColumn).Value" -> strExecutionFlag = comExcelWorksheet.Cells(intRowExecutionFlag, intColTestColumn).Value | F3: ="Public Property Get get" & A3 & "() : get" & A3 & " = str" & A3 & " : End Property" -> Public Property Get getExecutionFlag() : getExecutionFlag = strExecutionFlag : End Property
A4: =Test_Data!D5 -> DataValidationComplete | B4: ="Private intRow" & A4 -> Private intRowDataValidationComplete | C4: ="Private str" & A4 -> Private strDataValidationComplete | D4: ="intRow" & A4 & " = comExcelWorksheet.Range(""" & A4 & """).Row" -> intRowDataValidationComplete = comExcelWorksheet.Range("DataValidationComplete").Row | E4: ="str" & A4 & " = comExcelWorksheet.Cells(intRow" & A4 & ", intColTestColumn).Value" -> strDataValidationComplete = comExcelWorksheet.Cells(intRowDataValidationComplete, intColTestColumn).Value | F4: ="Public Property Get get" & A4 & "() : get" & A4 & " = str" & A4 & " : End Property" -> Public Property Get getDataValidationComplete() : getDataValidationComplete = strDataValidationComplete : End Property
A5: =Test_Data!D6 -> HireNameComplete | B5: ="Private intRow" & A5 -> Private intRowHireNameComplete | C5: ="Private str" & A5 -> Private strHireNameComplete | D5: ="intRow" & A5 & " = comExcelWorksheet.Range(""" & A5 & """).Row" -> intRowHireNameComplete = comExcelWorksheet.Range("HireNameComplete").Row | E5: ="str" & A5 & " = comExcelWorksheet.Cells(intRow" & A5 & ", intColTestColumn).Value" -> strHireNameComplete = comExcelWorksheet.Cells(intRowHireNameComplete, intColTestColumn).Value | F5: ="Public Property Get get" & A5 & "() : get" & A5 & " = str" & A5 & " : End Property" -> Public Property Get getHireNameComplete() : getHireNameComplete = strHireNameComplete : End Property
A6: =Test_Data!D7 -> 0 | B6: ="Private intRow" & A6 -> Private intRow0 | C6: ="Private str" & A6 -> Private str0 | D6: ="intRow" & A6 & " = comExcelWorksheet.Range(""" & A6 & """).Row" -> intRow0 = comExcelWorksheet.Range("0").Row | E6: ="str" & A6 & " = comExcelWorksheet.Cells(intRow" & A6 & ", intColTestColumn).Value" -> str0 = comExcelWorksheet.Cells(intRow0, intColTestColumn).Value | F6: ="Public Property Get get" & A6 & "() : get" & A6 & " = str" & A6 & " : End Property" -> Public Property Get get0() : get0 = str0 : End Property
A7: =Test_Data!D8 -> 0 | B7: ="Private intRow" & A7 -> Private intRow0 | C7: ="Private str" & A7 -> Private str0 | D7: ="intRow" & A7 & " = comExcelWorksheet.Range(""" & A7 & """).Row" -> intRow0 = comExcelWorksheet.Range("0").Row | E7: ="str" & A7 & " = comExcelWorksheet.Cells(intRow" & A7 & ", intColTestColumn).Value" -> str0 = comExcelWorksheet.Cells(intRow0, intColTestColumn).Value | F7: ="Public Property Get get" & A7 & "() : get" & A7 & " = str" & A7 & " : End Property" -> Public Property Get get0() : get0 = str0 : End Property
A8: =Test_Data!D9 -> LastRunErrorMessage | B8: ="Private intRow" & A8 -> Private intRowLastRunErrorMessage | C8: ="Private str" & A8 -> Private strLastRunErrorMessage | D8: ="intRow" & A8 & " = comExcelWorksheet.Range(""" & A8 & """).Row" -> intRowLastRunErrorMessage = comExcelWorksheet.Range("LastRunErrorMessage").Row | E8: ="str" & A8 & " = comExcelWorksheet.Cells(intRow" & A8 & ", intColTestColumn).Value" -> strLastRunErrorMessage = comExcelWorksheet.Cells(intRowLastRunErrorMessage, intColTestColumn).Value | F8: ="Public Property Get get" & A8 & "() : get" & A8 & " = str" & A8 & " : End Property" -> Public Property Get getLastRunErrorMessage() : getLastRunErrorMessage = strLastRunErrorMessage : End Property
A9: =Test_Data!D10 -> DefectDescription | B9: ="Private intRow" & A9 -> Private intRowDefectDescription | C9: ="Private str" & A9 -> Private strDefectDescription | D9: ="intRow" & A9 & " = comExcelWorksheet.Range(""" & A9 & """).Row" -> intRowDefectDescription = comExcelWorksheet.Range("DefectDescription").Row | E9: ="str" & A9 & " = comExcelWorksheet.Cells(intRow" & A9 & ", intColTestColumn).Value" -> strDefectDescription = comExcelWorksheet.Cells(intRowDefectDescription, intColTestColumn).Value | F9: ="Public Property Get get" & A9 & "() : get" & A9 & " = str" & A9 & " : End Property" -> Public Property Get getDefectDescription() : getDefectDescription = strDefectDescription : End Property
A10: =Test_Data!D11 -> AutomationComments | B10: ="Private intRow" & A10 -> Private intRowAutomationComments | C10: ="Private str" & A10 -> Private strAutomationComments | D10: ="intRow" & A10 & " = comExcelWorksheet.Range(""" & A10 & """).Row" -> intRowAutomationComments = comExcelWorksheet.Range("AutomationComments").Row | E10: ="str" & A10 & " = comExcelWorksheet.Cells(intRow" & A10 & ", intColTestColumn).Value" -> strAutomationComments = comExcelWorksheet.Cells(intRowAutomationComments, intColTestColumn).Value | F10: ="Public Property Get get" & A10 & "() : get" & A10 & " = str" & A10 & " : End Property" -> Public Property Get getAutomationComments() : getAutomationComments = strAutomationComments : End Property
A11: =Test_Data!D12 -> QAComments | B11: ="Private intRow" & A11 -> Private intRowQAComments | C11: ="Private str" & A11 -> Private strQAComments | D11: ="intRow" & A11 & " = comExcelWorksheet.Range(""" & A11 & """).Row" -> intRowQAComments = comExcelWorksheet.Range("QAComments").Row | E11: ="str" & A11 & " = comExcelWorksheet.Cells(intRow" & A11 & ", intColTestColumn).Value" -> strQAComments = comExcelWorksheet.Cells(intRowQAComments, intColTestColumn).Value | F11: ="Public Property Get get" & A11 & "() : get" & A11 & " = str" & A11 & " : End Property" -> Public Property Get getQAComments() : getQAComments = strQAComments : End Property
A12: =Test_Data!D13 -> 0 | B12: ="Private intRow" & A12 -> Private intRow0 | C12: ="Private str" & A12 -> Private str0 | D12: ="intRow" & A12 & " = comExcelWorksheet.Range(""" & A12 & """).Row" -> intRow0 = comExcelWorksheet.Range("0").Row | E12: ="str" & A12 & " = comExcelWorksheet.Cells(intRow" & A12 & ", intColTestColumn).Value" -> str0 = comExcelWorksheet.Cells(intRow0, intColTestColumn).Value | F12: ="Public Property Get get" & A12 & "() : get" & A12 & " = str" & A12 & " : End Property" -> Public Property Get get0() : get0 = str0 : End Property
A13: =Test_Data!D14 -> Automation Ref | B13: ="Private intRow" & A13 -> Private intRowAutomation Ref | C13: ="Private str" & A13 -> Private strAutomation Ref | D13: ="intRow" & A13 & " = comExcelWorksheet.Range(""" & A13 & """).Row" -> intRowAutomation Ref = comExcelWorksheet.Range("Automation Ref").Row | E13: ="str" & A13 & " = comExcelWorksheet.Cells(intRow" & A13 & ", intColTestColumn).Value" -> strAutomation Ref = comExcelWorksheet.Cells(intRowAutomation Ref, intColTestColumn).Value | F13: ="Public Property Get get" & A13 & "() : get" & A13 & " = str" & A13 & " : End Property" -> Public Property Get getAutomation Ref() : getAutomation Ref = strAutomation Ref : End Property
A14: =Test_Data!#REF! -> #REF! | B14: ="Private intRow" & A14 -> #REF! | C14: ="Private str" & A14 -> #REF! | D14: ="intRow" & A14 & " = comExcelWorksheet.Range(""" & A14 & """).Row" -> #REF! | E14: ="str" & A14 & " = comExcelWorksheet.Cells(intRow" & A14 & ", intColTestColumn).Value" -> #REF! | F14: ="Public Property Get get" & A14 & "() : get" & A14 & " = str" & A14 & " : End Property" -> #REF!
A15: =Test_Data!#REF! -> #REF! | B15: ="Private intRow" & A15 -> #REF! | C15: ="Private str" & A15 -> #REF! | D15: ="intRow" & A15 & " = comExcelWorksheet.Range(""" & A15 & """).Row" -> #REF! | E15: ="str" & A15 & " = comExcelWorksheet.Cells(intRow" & A15 & ", intColTestColumn).Value" -> #REF! | F15: ="Public Property Get get" & A15 & "() : get" & A15 & " = str" & A15 & " : End Property" -> #REF!
A16: =Test_Data!D15 -> SupervisoryOrganisation_SupervisoryOrganisation | B16: ="Private intRow" & A16 -> Private intRowSupervisoryOrganisation_SupervisoryOrganisation | C16: ="Private str" & A16 -> Private strSupervisoryOrganisation_SupervisoryOrganisation | D16: ="intRow" & A16 & " = comExcelWorksheet.Range(""" & A16 & """).Row" -> intRowSupervisoryOrganisation_SupervisoryOrganisation = comExcelWorksheet.Range("SupervisoryOrganisation_SupervisoryOrganisation").Row | E16: ="str" & A16 & " = comExcelWorksheet.Cells(intRow" & A16 & ", intColTestColumn).Value" -> strSupervisoryOrganisation_SupervisoryOrganisation = comExcelWorksheet.Cells(intRowSupervisoryOrganisation_SupervisoryOrganisation, intColTestColumn).Value | F16: ="Public Property Get get" & A16 & "() : get" & A16 & " = str" & A16 & " : End Property" -> Public Property Get getSupervisoryOrganisation_SupervisoryOrganisation() : getSupervisoryOrganisation_SupervisoryOrganisation = strSupervisoryOrganisation_SupervisoryOrganisation : End Property
A17: =Test_Data!D16 -> LegalNameInformation_Country | B17: ="Private intRow" & A17 -> Private intRowLegalNameInformation_Country | C17: ="Private str" & A17 -> Private strLegalNameInformation_Country | D17: ="intRow" & A17 & " = comExcelWorksheet.Range(""" & A17 & """).Row" -> intRowLegalNameInformation_Country = comExcelWorksheet.Range("LegalNameInformation_Country").Row | E17: ="str" & A17 & " = comExcelWorksheet.Cells(intRow" & A17 & ", intColTestColumn).Value" -> strLegalNameInformation_Country = comExcelWorksheet.Cells(intRowLegalNameInformation_Country, intColTestColumn).Value | F17: ="Public Property Get get" & A17 & "() : get" & A17 & " = str" & A17 & " : End Property" -> Public Property Get getLegalNameInformation_Country() : getLegalNameInformation_Country = strLegalNameInformation_Country : End Property
A18: =Test_Data!D17 -> LegalNameInformation_Prefix | B18: ="Private intRow" & A18 -> Private intRowLegalNameInformation_Prefix | C18: ="Private str" & A18 -> Private strLegalNameInformation_Prefix | D18: ="intRow" & A18 & " = comExcelWorksheet.Range(""" & A18 & """).Row" -> intRowLegalNameInformation_Prefix = comExcelWorksheet.Range("LegalNameInformation_Prefix").Row | E18: ="str" & A18 & " = comExcelWorksheet.Cells(intRow" & A18 & ", intColTestColumn).Value" -> strLegalNameInformation_Prefix = comExcelWorksheet.Cells(intRowLegalNameInformation_Prefix, intColTestColumn).Value | F18: ="Public Property Get get" & A18 & "() : get" & A18 & " = str" & A18 & " : End Property" -> Public Property Get getLegalNameInformation_Prefix() : getLegalNameInformation_Prefix = strLegalNameInformation_Prefix : End Property
A19: =Test_Data!D18 -> LegalNameInformation_GivenName | B19: ="Private intRow" & A19 -> Private intRowLegalNameInformation_GivenName | C19: ="Private str" & A19 -> Private strLegalNameInformation_GivenName | D19: ="intRow" & A19 & " = comExcelWorksheet.Range(""" & A19 & """).Row" -> intRowLegalNameInformation_GivenName = comExcelWorksheet.Range("LegalNameInformation_GivenName").Row | E19: ="str" & A19 & " = comExcelWorksheet.Cells(intRow" & A19 & ", intColTestColumn).Value" -> strLegalNameInformation_GivenName = comExcelWorksheet.Cells(intRowLegalNameInformation_GivenName, intColTestColumn).Value | F19: ="Public Property Get get" & A19 & "() : get" & A19 & " = str" & A19 & " : End Property" -> Public Property Get getLegalNameInformation_GivenName() : getLegalNameInformation_GivenName = strLegalNameInformation_GivenName : End Property
A20: =Test_Data!D19 -> LegalNameInformation_FamilyName | B20: ="Private intRow" & A20 -> Private intRowLegalNameInformation_FamilyName | C20: ="Private str" & A20 -> Private strLegalNameInformation_FamilyName | D20: ="intRow" & A20 & " = comExcelWorksheet.Range(""" & A20 & """).Row" -> intRowLegalNameInformation_FamilyName = comExcelWorksheet.Range("LegalNameInformation_FamilyName").Row | E20: ="str" & A20 & " = comExcelWorksheet.Cells(intRow" & A20 & ", intColTestColumn).Value" -> strLegalNameInformation_FamilyName = comExcelWorksheet.Cells(intRowLegalNameInformation_FamilyName, intColTestColumn).Value | F20: ="Public Property Get get" & A20 & "() : get" & A20 & " = str" & A20 & " : End Property" -> Public Property Get getLegalNameInformation_FamilyName() : getLegalNameInformation_FamilyName = strLegalNameInformation_FamilyName : End Property
A21: =Test_Data!D20 -> ContactInformation_Phone_PhoneNumber | B21: ="Private intRow" & A21 -> Private intRowContactInformation_Phone_PhoneNumber | C21: ="Private str" & A21 -> Private strContactInformation_Phone_PhoneNumber | D21: ="intRow" & A21 & " = comExcelWorksheet.Range(""" & A21 & """).Row" -> intRowContactInformation_Phone_PhoneNumber = comExcelWorksheet.Range("ContactInformation_Phone_PhoneNumber").Row | E21: ="str" & A21 & " = comExcelWorksheet.Cells(intRow" & A21 & ", intColTestColumn).Value" -> strContactInformation_Phone_PhoneNumber = comExcelWorksheet.Cells(intRowContactInformation_Phone_PhoneNumber, intColTestColumn).Value | F21: ="Public Property Get get" & A21 & "() : get" & A21 & " = str" & A21 & " : End Property" -> Public Property Get getContactInformation_Phone_PhoneNumber() : getContactInformation_Phone_PhoneNumber = strContactInformation_Phone_PhoneNumber : End Property
A22: =Test_Data!D21 -> ContactInformation_Phone_PhoneDevice | B22: ="Private intRow" & A22 -> Private intRowContactInformation_Phone_PhoneDevice | C22: ="Private str" & A22 -> Private strContactInformation_Phone_PhoneDevice | D22: ="intRow" & A22 & " = comExcelWorksheet.Range(""" & A22 & """).Row" -> intRowContactInformation_Phone_PhoneDevice = comExcelWorksheet.Range("ContactInformation_Phone_PhoneDevice").Row | E22: ="str" & A22 & " = comExcelWorksheet.Cells(intRow" & A22 & ", intColTestColumn).Value" -> strContactInformation_Phone_PhoneDevice = comExcelWorksheet.Cells(intRowContactInformation_Phone_PhoneDevice, intColTestColumn).Value | F22: ="Public Property Get get" & A22 & "() : get" & A22 & " = str" & A22 & " : End Property" -> Public Property Get getContactInformation_Phone_PhoneDevice() : getContactInformation_Phone_PhoneDevice = strContactInformation_Phone_PhoneDevice : End Property
A23: =Test_Data!D22 -> ContactInformation_Phone_Type | B23: ="Private intRow" & A23 -> Private intRowContactInformation_Phone_Type | C23: ="Private str" & A23 -> Private strContactInformation_Phone_Type | D23: ="intRow" & A23 & " = comExcelWorksheet.Range(""" & A23 & """).Row" -> intRowContactInformation_Phone_Type = comExcelWorksheet.Range("ContactInformation_Phone_Type").Row | E23: ="str" & A23 & " = comExcelWorksheet.Cells(intRow" & A23 & ", intColTestColumn).Value" -> strContactInformation_Phone_Type = comExcelWorksheet.Cells(intRowContactInformation_Phone_Type, intColTestColumn).Value | F23: ="Public Property Get get" & A23 & "() : get" & A23 & " = str" & A23 & " : End Property" -> Public Property Get getContactInformation_Phone_Type() : getContactInformation_Phone_Type = strContactInformation_Phone_Type : End Property
A24: =Test_Data!D23 -> ContactInformation_Address_EffectiveDate | B24: ="Private intRow" & A24 -> Private intRowContactInformation_Address_EffectiveDate | C24: ="Private str" & A24 -> Private strContactInformation_Address_EffectiveDate | D24: ="intRow" & A24 & " = comExcelWorksheet.Range(""" & A24 & """).Row" -> intRowContactInformation_Address_EffectiveDate = comExcelWorksheet.Range("ContactInformation_Address_EffectiveDate").Row | E24: ="str" & A24 & " = comExcelWorksheet.Cells(intRow" & A24 & ", intColTestColumn).Value" -> strContactInformation_Address_EffectiveDate = comExcelWorksheet.Cells(intRowContactInformation_Address_EffectiveDate, intColTestColumn).Value | F24: ="Public Property Get get" & A24 & "() : get" & A24 & " = str" & A24 & " : End Property" -> Public Property Get getContactInformation_Address_EffectiveDate() : getContactInformation_Address_EffectiveDate = strContactInformation_Address_EffectiveDate : End Property
A25: =Test_Data!D24 -> ContactInformation_Address_Country | B25: ="Private intRow" & A25 -> Private intRowContactInformation_Address_Country | C25: ="Private str" & A25 -> Private strContactInformation_Address_Country | D25: ="intRow" & A25 & " = comExcelWorksheet.Range(""" & A25 & """).Row" -> intRowContactInformation_Address_Country = comExcelWorksheet.Range("ContactInformation_Address_Country").Row | E25: ="str" & A25 & " = comExcelWorksheet.Cells(intRow" & A25 & ", intColTestColumn).Value" -> strContactInformation_Address_Country = comExcelWorksheet.Cells(intRowContactInformation_Address_Country, intColTestColumn).Value | F25: ="Public Property Get get" & A25 & "() : get" & A25 & " = str" & A25 & " : End Property" -> Public Property Get getContactInformation_Address_Country() : getContactInformation_Address_Country = strContactInformation_Address_Country : End Property
A26: =Test_Data!#REF! -> #REF! | B26: ="Private intRow" & A26 -> #REF! | C26: ="Private str" & A26 -> #REF! | D26: ="intRow" & A26 & " = comExcelWorksheet.Range(""" & A26 & """).Row" -> #REF! | E26: ="str" & A26 & " = comExcelWorksheet.Cells(intRow" & A26 & ", intColTestColumn).Value" -> #REF! | F26: ="Public Property Get get" & A26 & "() : get" & A26 & " = str" & A26 & " : End Property" -> #REF!
A27: =Test_Data!#REF! -> #REF! | B27: ="Private intRow" & A27 -> #REF! | C27: ="Private str" & A27 -> #REF! | D27: ="intRow" & A27 & " = comExcelWorksheet.Range(""" & A27 & """).Row" -> #REF! | E27: ="str" & A27 & " = comExcelWorksheet.Cells(intRow" & A27 & ", intColTestColumn).Value" -> #REF! | F27: ="Public Property Get get" & A27 & "() : get" & A27 & " = str" & A27 & " : End Property" -> #REF!
A28: =Test_Data!#REF! -> #REF! | B28: ="Private intRow" & A28 -> #REF! | C28: ="Private str" & A28 -> #REF! | D28: ="intRow" & A28 & " = comExcelWorksheet.Range(""" & A28 & """).Row" -> #REF! | E28: ="str" & A28 & " = comExcelWorksheet.Cells(intRow" & A28 & ", intColTestColumn).Value" -> #REF! | F28: ="Public Property Get get" & A28 & "() : get" & A28 & " = str" & A28 & " : End Property" -> #REF!
A29: =Test_Data!D27 -> ContactInformation_Address_PostalCode | B29: ="Private intRow" & A29 -> Private intRowContactInformation_Address_PostalCode | C29: ="Private str" & A29 -> Private strContactInformation_Address_PostalCode | D29: ="intRow" & A29 & " = comExcelWorksheet.Range(""" & A29 & """).Row" -> intRowContactInformation_Address_PostalCode = comExcelWorksheet.Range("ContactInformation_Address_PostalCode").Row | E29: ="str" & A29 & " = comExcelWorksheet.Cells(intRow" & A29 & ", intColTestColumn).Value" -> strContactInformation_Address_PostalCode = comExcelWorksheet.Cells(intRowContactInformation_Address_PostalCode, intColTestColumn).Value | F29: ="Public Property Get get" & A29 & "() : get" & A29 & " = str" & A29 & " : End Property" -> Public Property Get getContactInformation_Address_PostalCode() : getContactInformation_Address_PostalCode = strContactInformation_Address_PostalCode : End Property
A30: =Test_Data!D30 -> ContactInformation_Address_Municipality | B30: ="Private intRow" & A30 -> Private intRowContactInformation_Address_Municipality | C30: ="Private str" & A30 -> Private strContactInformation_Address_Municipality | D30: ="intRow" & A30 & " = comExcelWorksheet.Range(""" & A30 & """).Row" -> intRowContactInformation_Address_Municipality = comExcelWorksheet.Range("ContactInformation_Address_Municipality").Row | E30: ="str" & A30 & " = comExcelWorksheet.Cells(intRow" & A30 & ", intColTestColumn).Value" -> strContactInformation_Address_Municipality = comExcelWorksheet.Cells(intRowContactInformation_Address_Municipality, intColTestColumn).Value | F30: ="Public Property Get get" & A30 & "() : get" & A30 & " = str" & A30 & " : End Property" -> Public Property Get getContactInformation_Address_Municipality() : getContactInformation_Address_Municipality = strContactInformation_Address_Municipality : End Property
A31: =Test_Data!#REF! -> #REF! | B31: ="Private intRow" & A31 -> #REF! | C31: ="Private str" & A31 -> #REF! | D31: ="intRow" & A31 & " = comExcelWorksheet.Range(""" & A31 & """).Row" -> #REF! | E31: ="str" & A31 & " = comExcelWorksheet.Cells(intRow" & A31 & ", intColTestColumn).Value" -> #REF! | F31: ="Public Property Get get" & A31 & "() : get" & A31 & " = str" & A31 & " : End Property" -> #REF!
A32: =Test_Data!D31 -> ContactInformation_Address_District | B32: ="Private intRow" & A32 -> Private intRowContactInformation_Address_District | C32: ="Private str" & A32 -> Private strContactInformation_Address_District | D32: ="intRow" & A32 & " = comExcelWorksheet.Range(""" & A32 & """).Row" -> intRowContactInformation_Address_District = comExcelWorksheet.Range("ContactInformation_Address_District").Row | E32: ="str" & A32 & " = comExcelWorksheet.Cells(intRow" & A32 & ", intColTestColumn).Value" -> strContactInformation_Address_District = comExcelWorksheet.Cells(intRowContactInformation_Address_District, intColTestColumn).Value | F32: ="Public Property Get get" & A32 & "() : get" & A32 & " = str" & A32 & " : End Property" -> Public Property Get getContactInformation_Address_District() : getContactInformation_Address_District = strContactInformation_Address_District : End Property
A33: =Test_Data!D32 -> ContactInformation_Address_Type | B33: ="Private intRow" & A33 -> Private intRowContactInformation_Address_Type | C33: ="Private str" & A33 -> Private strContactInformation_Address_Type | D33: ="intRow" & A33 & " = comExcelWorksheet.Range(""" & A33 & """).Row" -> intRowContactInformation_Address_Type = comExcelWorksheet.Range("ContactInformation_Address_Type").Row | E33: ="str" & A33 & " = comExcelWorksheet.Cells(intRow" & A33 & ", intColTestColumn).Value" -> strContactInformation_Address_Type = comExcelWorksheet.Cells(intRowContactInformation_Address_Type, intColTestColumn).Value | F33: ="Public Property Get get" & A33 & "() : get" & A33 & " = str" & A33 & " : End Property" -> Public Property Get getContactInformation_Address_Type() : getContactInformation_Address_Type = strContactInformation_Address_Type : End Property
A34: =Test_Data!D33 -> ContactInformation_Email_UseFor | B34: ="Private intRow" & A34 -> Private intRowContactInformation_Email_UseFor | C34: ="Private str" & A34 -> Private strContactInformation_Email_UseFor | D34: ="intRow" & A34 & " = comExcelWorksheet.Range(""" & A34 & """).Row" -> intRowContactInformation_Email_UseFor = comExcelWorksheet.Range("ContactInformation_Email_UseFor").Row | E34: ="str" & A34 & " = comExcelWorksheet.Cells(intRow" & A34 & ", intColTestColumn).Value" -> strContactInformation_Email_UseFor = comExcelWorksheet.Cells(intRowContactInformation_Email_UseFor, intColTestColumn).Value | F34: ="Public Property Get get" & A34 & "() : get" & A34 & " = str" & A34 & " : End Property" -> Public Property Get getContactInformation_Email_UseFor() : getContactInformation_Email_UseFor = strContactInformation_Email_UseFor : End Property
A35: =Test_Data!D34 -> ContactInformation_Email_EmailAddress | B35: ="Private intRow" & A35 -> Private intRowContactInformation_Email_EmailAddress | C35: ="Private str" & A35 -> Private strContactInformation_Email_EmailAddress | D35: ="intRow" & A35 & " = comExcelWorksheet.Range(""" & A35 & """).Row" -> intRowContactInformation_Email_EmailAddress = comExcelWorksheet.Range("ContactInformation_Email_EmailAddress").Row | E35: ="str" & A35 & " = comExcelWorksheet.Cells(intRow" & A35 & ", intColTestColumn).Value" -> strContactInformation_Email_EmailAddress = comExcelWorksheet.Cells(intRowContactInformation_Email_EmailAddress, intColTestColumn).Value | F35: ="Public Property Get get" & A35 & "() : get" & A35 & " = str" & A35 & " : End Property" -> Public Property Get getContactInformation_Email_EmailAddress() : getContactInformation_Email_EmailAddress = strContactInformation_Email_EmailAddress : End Property
A36: =Test_Data!D35 -> JobDetails_Type | B36: ="Private intRow" & A36 -> Private intRowJobDetails_Type | C36: ="Private str" & A36 -> Private strJobDetails_Type | D36: ="intRow" & A36 & " = comExcelWorksheet.Range(""" & A36 & """).Row" -> intRowJobDetails_Type = comExcelWorksheet.Range("JobDetails_Type").Row | E36: ="str" & A36 & " = comExcelWorksheet.Cells(intRow" & A36 & ", intColTestColumn).Value" -> strJobDetails_Type = comExcelWorksheet.Cells(intRowJobDetails_Type, intColTestColumn).Value | F36: ="Public Property Get get" & A36 & "() : get" & A36 & " = str" & A36 & " : End Property" -> Public Property Get getJobDetails_Type() : getJobDetails_Type = strJobDetails_Type : End Property
A37: =Test_Data!#REF! -> #REF! | B37: ="Private intRow" & A37 -> #REF! | C37: ="Private str" & A37 -> #REF! | D37: ="intRow" & A37 & " = comExcelWorksheet.Range(""" & A37 & """).Row" -> #REF! | E37: ="str" & A37 & " = comExcelWorksheet.Cells(intRow" & A37 & ", intColTestColumn).Value" -> #REF! | F37: ="Public Property Get get" & A37 & "() : get" & A37 & " = str" & A37 & " : End Property" -> #REF!
A38: =Test_Data!D36 -> JobDetails_HireDate | B38: ="Private intRow" & A38 -> Private intRowJobDetails_HireDate | C38: ="Private str" & A38 -> Private strJobDetails_HireDate | D38: ="intRow" & A38 & " = comExcelWorksheet.Range(""" & A38 & """).Row" -> intRowJobDetails_HireDate = comExcelWorksheet.Range("JobDetails_HireDate").Row | E38: ="str" & A38 & " = comExcelWorksheet.Cells(intRow" & A38 & ", intColTestColumn).Value" -> strJobDetails_HireDate = comExcelWorksheet.Cells(intRowJobDetails_HireDate, intColTestColumn).Value | F38: ="Public Property Get get" & A38 & "() : get" & A38 & " = str" & A38 & " : End Property" -> Public Property Get getJobDetails_HireDate() : getJobDetails_HireDate = strJobDetails_HireDate : End Property
A39: =Test_Data!D37 -> JobDetails_Reason | B39: ="Private intRow" & A39 -> Private intRowJobDetails_Reason | C39: ="Private str" & A39 -> Private strJobDetails_Reason | D39: ="intRow" & A39 & " = comExcelWorksheet.Range(""" & A39 & """).Row" -> intRowJobDetails_Reason = comExcelWorksheet.Range("JobDetails_Reason").Row | E39: ="str" & A39 & " = comExcelWorksheet.Cells(intRow" & A39 & ", intColTestColumn).Value" -> strJobDetails_Reason = comExcelWorksheet.Cells(intRowJobDetails_Reason, intColTestColumn).Value | F39: ="Public Property Get get" & A39 & "() : get" & A39 & " = str" & A39 & " : End Property" -> Public Property Get getJobDetails_Reason() : getJobDetails_Reason = strJobDetails_Reason : End Property
A40: =Test_Data!D38 -> JobDetails_Position | B40: ="Private intRow" & A40 -> Private intRowJobDetails_Position | C40: ="Private str" & A40 -> Private strJobDetails_Position | D40: ="intRow" & A40 & " = comExcelWorksheet.Range(""" & A40 & """).Row" -> intRowJobDetails_Position = comExcelWorksheet.Range("JobDetails_Position").Row | E40: ="str" & A40 & " = comExcelWorksheet.Cells(intRow" & A40 & ", intColTestColumn).Value" -> strJobDetails_Position = comExcelWorksheet.Cells(intRowJobDetails_Position, intColTestColumn).Value | F40: ="Public Property Get get" & A40 & "() : get" & A40 & " = str" & A40 & " : End Property" -> Public Property Get getJobDetails_Position() : getJobDetails_Position = strJobDetails_Position : End Property
A41: =Test_Data!D39 -> JobDetails_EmployeeType | B41: ="Private intRow" & A41 -> Private intRowJobDetails_EmployeeType | C41: ="Private str" & A41 -> Private strJobDetails_EmployeeType | D41: ="intRow" & A41 & " = comExcelWorksheet.Range(""" & A41 & """).Row" -> intRowJobDetails_EmployeeType = comExcelWorksheet.Range("JobDetails_EmployeeType").Row | E41: ="str" & A41 & " = comExcelWorksheet.Cells(intRow" & A41 & ", intColTestColumn).Value" -> strJobDetails_EmployeeType = comExcelWorksheet.Cells(intRowJobDetails_EmployeeType, intColTestColumn).Value | F41: ="Public Property Get get" & A41 & "() : get" & A41 & " = str" & A41 & " : End Property" -> Public Property Get getJobDetails_EmployeeType() : getJobDetails_EmployeeType = strJobDetails_EmployeeType : End Property
A42: =Test_Data!D40 -> JobDetails_JobProfile | B42: ="Private intRow" & A42 -> Private intRowJobDetails_JobProfile | C42: ="Private str" & A42 -> Private strJobDetails_JobProfile | D42: ="intRow" & A42 & " = comExcelWorksheet.Range(""" & A42 & """).Row" -> intRowJobDetails_JobProfile = comExcelWorksheet.Range("JobDetails_JobProfile").Row | E42: ="str" & A42 & " = comExcelWorksheet.Cells(intRow" & A42 & ", intColTestColumn).Value" -> strJobDetails_JobProfile = comExcelWorksheet.Cells(intRowJobDetails_JobProfile, intColTestColumn).Value | F42: ="Public Property Get get" & A42 & "() : get" & A42 & " = str" & A42 & " : End Property" -> Public Property Get getJobDetails_JobProfile() : getJobDetails_JobProfile = strJobDetails_JobProfile : End Property
A43: =Test_Data!D41 -> JobDetails_TimeType | B43: ="Private intRow" & A43 -> Private intRowJobDetails_TimeType | C43: ="Private str" & A43 -> Private strJobDetails_TimeType | D43: ="intRow" & A43 & " = comExcelWorksheet.Range(""" & A43 & """).Row" -> intRowJobDetails_TimeType = comExcelWorksheet.Range("JobDetails_TimeType").Row | E43: ="str" & A43 & " = comExcelWorksheet.Cells(intRow" & A43 & ", intColTestColumn).Value" -> strJobDetails_TimeType = comExcelWorksheet.Cells(intRowJobDetails_TimeType, intColTestColumn).Value | F43: ="Public Property Get get" & A43 & "() : get" & A43 & " = str" & A43 & " : End Property" -> Public Property Get getJobDetails_TimeType() : getJobDetails_TimeType = strJobDetails_TimeType : End Property
A44: =Test_Data!D42 -> JobDetails_Location | B44: ="Private intRow" & A44 -> Private intRowJobDetails_Location | C44: ="Private str" & A44 -> Private strJobDetails_Location | D44: ="intRow" & A44 & " = comExcelWorksheet.Range(""" & A44 & """).Row" -> intRowJobDetails_Location = comExcelWorksheet.Range("JobDetails_Location").Row | E44: ="str" & A44 & " = comExcelWorksheet.Cells(intRow" & A44 & ", intColTestColumn).Value" -> strJobDetails_Location = comExcelWorksheet.Cells(intRowJobDetails_Location, intColTestColumn).Value | F44: ="Public Property Get get" & A44 & "() : get" & A44 & " = str" & A44 & " : End Property" -> Public Property Get getJobDetails_Location() : getJobDetails_Location = strJobDetails_Location : End Property
A45: =Test_Data!D43 -> JobDetails_AdditionalInformation_PayRateType | B45: ="Private intRow" & A45 -> Private intRowJobDetails_AdditionalInformation_PayRateType | C45: ="Private str" & A45 -> Private strJobDetails_AdditionalInformation_PayRateType | D45: ="intRow" & A45 & " = comExcelWorksheet.Range(""" & A45 & """).Row" -> intRowJobDetails_AdditionalInformation_PayRateType = comExcelWorksheet.Range("JobDetails_AdditionalInformation_PayRateType").Row | E45: ="str" & A45 & " = comExcelWorksheet.Cells(intRow" & A45 & ", intColTestColumn).Value" -> strJobDetails_AdditionalInformation_PayRateType = comExcelWorksheet.Cells(intRowJobDetails_AdditionalInformation_PayRateType, intColTestColumn).Value | F45: ="Public Property Get get" & A45 & "() : get" & A45 & " = str" & A45 & " : End Property" -> Public Property Get getJobDetails_AdditionalInformation_PayRateType() : getJobDetails_AdditionalInformation_PayRateType = strJobDetails_AdditionalInformation_PayRateType : End Property
A46: =Test_Data!D44 -> JobDetails_AdditionalInformation_ScheduledWeeklyHours | B46: ="Private intRow" & A46 -> Private intRowJobDetails_AdditionalInformation_ScheduledWeeklyHours | C46: ="Private str" & A46 -> Private strJobDetails_AdditionalInformation_ScheduledWeeklyHours | D46: ="intRow" & A46 & " = comExcelWorksheet.Range(""" & A46 & """).Row" -> intRowJobDetails_AdditionalInformation_ScheduledWeeklyHours = comExcelWorksheet.Range("JobDetails_AdditionalInformation_ScheduledWeeklyHours").Row | E46: ="str" & A46 & " = comExcelWorksheet.Cells(intRow" & A46 & ", intColTestColumn).Value" -> strJobDetails_AdditionalInformation_ScheduledWeeklyHours = comExcelWorksheet.Cells(intRowJobDetails_AdditionalInformation_ScheduledWeeklyHours, intColTestColumn).Value | F46: ="Public Property Get get" & A46 & "() : get" & A46 & " = str" & A46 & " : End Property" -> Public Property Get getJobDetails_AdditionalInformation_ScheduledWeeklyHours() : getJobDetails_AdditionalInformation_ScheduledWeeklyHours = strJobDetails_AdditionalInformation_ScheduledWeeklyHours : End Property
A47: =Test_Data!D45 -> JobDetails_AdditionalInformation_SchoolName | B47: ="Private intRow" & A47 -> Private intRowJobDetails_AdditionalInformation_SchoolName | C47: ="Private str" & A47 -> Private strJobDetails_AdditionalInformation_SchoolName | D47: ="intRow" & A47 & " = comExcelWorksheet.Range(""" & A47 & """).Row" -> intRowJobDetails_AdditionalInformation_SchoolName = comExcelWorksheet.Range("JobDetails_AdditionalInformation_SchoolName").Row | E47: ="str" & A47 & " = comExcelWorksheet.Cells(intRow" & A47 & ", intColTestColumn).Value" -> strJobDetails_AdditionalInformation_SchoolName = comExcelWorksheet.Cells(intRowJobDetails_AdditionalInformation_SchoolName, intColTestColumn).Value | F47: ="Public Property Get get" & A47 & "() : get" & A47 & " = str" & A47 & " : End Property" -> Public Property Get getJobDetails_AdditionalInformation_SchoolName() : getJobDetails_AdditionalInformation_SchoolName = strJobDetails_AdditionalInformation_SchoolName : End Property
A48: =Test_Data!D46 -> JobDetails_AdditionalInformation_SchoolType | B48: ="Private intRow" & A48 -> Private intRowJobDetails_AdditionalInformation_SchoolType | C48: ="Private str" & A48 -> Private strJobDetails_AdditionalInformation_SchoolType | D48: ="intRow" & A48 & " = comExcelWorksheet.Range(""" & A48 & """).Row" -> intRowJobDetails_AdditionalInformation_SchoolType = comExcelWorksheet.Range("JobDetails_AdditionalInformation_SchoolType").Row | E48: ="str" & A48 & " = comExcelWorksheet.Cells(intRow" & A48 & ", intColTestColumn).Value" -> strJobDetails_AdditionalInformation_SchoolType = comExcelWorksheet.Cells(intRowJobDetails_AdditionalInformation_SchoolType, intColTestColumn).Value | F48: ="Public Property Get get" & A48 & "() : get" & A48 & " = str" & A48 & " : End Property" -> Public Property Get getJobDetails_AdditionalInformation_SchoolType() : getJobDetails_AdditionalInformation_SchoolType = strJobDetails_AdditionalInformation_SchoolType : End Property
A49: =Test_Data!D47 -> JobDetails_AdditionalInformation_SchoolStartDate | B49: ="Private intRow" & A49 -> Private intRowJobDetails_AdditionalInformation_SchoolStartDate | C49: ="Private str" & A49 -> Private strJobDetails_AdditionalInformation_SchoolStartDate | D49: ="intRow" & A49 & " = comExcelWorksheet.Range(""" & A49 & """).Row" -> intRowJobDetails_AdditionalInformation_SchoolStartDate = comExcelWorksheet.Range("JobDetails_AdditionalInformation_SchoolStartDate").Row | E49: ="str" & A49 & " = comExcelWorksheet.Cells(intRow" & A49 & ", intColTestColumn).Value" -> strJobDetails_AdditionalInformation_SchoolStartDate = comExcelWorksheet.Cells(intRowJobDetails_AdditionalInformation_SchoolStartDate, intColTestColumn).Value | F49: ="Public Property Get get" & A49 & "() : get" & A49 & " = str" & A49 & " : End Property" -> Public Property Get getJobDetails_AdditionalInformation_SchoolStartDate() : getJobDetails_AdditionalInformation_SchoolStartDate = strJobDetails_AdditionalInformation_SchoolStartDate : End Property
A50: =Test_Data!D53 -> ChangeOrganizationAssignments_Comments | B50: ="Private intRow" & A50 -> Private intRowChangeOrganizationAssignments_Comments | C50: ="Private str" & A50 -> Private strChangeOrganizationAssignments_Comments | D50: ="intRow" & A50 & " = comExcelWorksheet.Range(""" & A50 & """).Row" -> intRowChangeOrganizationAssignments_Comments = comExcelWorksheet.Range("ChangeOrganizationAssignments_Comments").Row | E50: ="str" & A50 & " = comExcelWorksheet.Cells(intRow" & A50 & ", intColTestColumn).Value" -> strChangeOrganizationAssignments_Comments = comExcelWorksheet.Cells(intRowChangeOrganizationAssignments_Comments, intColTestColumn).Value | F50: ="Public Property Get get" & A50 & "() : get" & A50 & " = str" & A50 & " : End Property" -> Public Property Get getChangeOrganizationAssignments_Comments() : getChangeOrganizationAssignments_Comments = strChangeOrganizationAssignments_Comments : End Property
A51: =Test_Data!D54 -> ChangeOrganizationAssignments_ContractType | B51: ="Private intRow" & A51 -> Private intRowChangeOrganizationAssignments_ContractType | C51: ="Private str" & A51 -> Private strChangeOrganizationAssignments_ContractType | D51: ="intRow" & A51 & " = comExcelWorksheet.Range(""" & A51 & """).Row" -> intRowChangeOrganizationAssignments_ContractType = comExcelWorksheet.Range("ChangeOrganizationAssignments_ContractType").Row | E51: ="str" & A51 & " = comExcelWorksheet.Cells(intRow" & A51 & ", intColTestColumn).Value" -> strChangeOrganizationAssignments_ContractType = comExcelWorksheet.Cells(intRowChangeOrganizationAssignments_ContractType, intColTestColumn).Value | F51: ="Public Property Get get" & A51 & "() : get" & A51 & " = str" & A51 & " : End Property" -> Public Property Get getChangeOrganizationAssignments_ContractType() : getChangeOrganizationAssignments_ContractType = strChangeOrganizationAssignments_ContractType : End Property
A52: =Test_Data!#REF! -> #REF! | B52: ="Private intRow" & A52 -> #REF! | C52: ="Private str" & A52 -> #REF! | D52: ="intRow" & A52 & " = comExcelWorksheet.Range(""" & A52 & """).Row" -> #REF! | E52: ="str" & A52 & " = comExcelWorksheet.Cells(intRow" & A52 & ", intColTestColumn).Value" -> #REF! | F52: ="Public Property Get get" & A52 & "() : get" & A52 & " = str" & A52 & " : End Property" -> #REF!
A53: =Test_Data!#REF! -> #REF! | B53: ="Private intRow" & A53 -> #REF! | C53: ="Private str" & A53 -> #REF! | D53: ="intRow" & A53 & " = comExcelWorksheet.Range(""" & A53 & """).Row" -> #REF! | E53: ="str" & A53 & " = comExcelWorksheet.Cells(intRow" & A53 & ", intColTestColumn).Value" -> #REF! | F53: ="Public Property Get get" & A53 & "() : get" & A53 & " = str" & A53 & " : End Property" -> #REF!
A54: =Test_Data!D55 -> ChangeMyGovernmentIDs_NationalIDs_Status | B54: ="Private intRow" & A54 -> Private intRowChangeMyGovernmentIDs_NationalIDs_Status | C54: ="Private str" & A54 -> Private strChangeMyGovernmentIDs_NationalIDs_Status | D54: ="intRow" & A54 & " = comExcelWorksheet.Range(""" & A54 & """).Row" -> intRowChangeMyGovernmentIDs_NationalIDs_Status = comExcelWorksheet.Range("ChangeMyGovernmentIDs_NationalIDs_Status").Row | E54: ="str" & A54 & " = comExcelWorksheet.Cells(intRow" & A54 & ", intColTestColumn).Value" -> strChangeMyGovernmentIDs_NationalIDs_Status = comExcelWorksheet.Cells(intRowChangeMyGovernmentIDs_NationalIDs_Status, intColTestColumn).Value | F54: ="Public Property Get get" & A54 & "() : get" & A54 & " = str" & A54 & " : End Property" -> Public Property Get getChangeMyGovernmentIDs_NationalIDs_Status() : getChangeMyGovernmentIDs_NationalIDs_Status = strChangeMyGovernmentIDs_NationalIDs_Status : End Property
A55: =Test_Data!D56 -> ChangeMyGovernmentIDs_NationalIDs_DateEmployeeSigned | B55: ="Private intRow" & A55 -> Private intRowChangeMyGovernmentIDs_NationalIDs_DateEmployeeSigned | C55: ="Private str" & A55 -> Private strChangeMyGovernmentIDs_NationalIDs_DateEmployeeSigned | D55: ="intRow" & A55 & " = comExcelWorksheet.Range(""" & A55 & """).Row" -> intRowChangeMyGovernmentIDs_NationalIDs_DateEmployeeSigned = comExcelWorksheet.Range("ChangeMyGovernmentIDs_NationalIDs_DateEmployeeSigned").Row | E55: ="str" & A55 & " = comExcelWorksheet.Cells(intRow" & A55 & ", intColTestColumn).Value" -> strChangeMyGovernmentIDs_NationalIDs_DateEmployeeSigned = comExcelWorksheet.Cells(intRowChangeMyGovernmentIDs_NationalIDs_DateEmployeeSigned, intColTestColumn).Value | F55: ="Public Property Get get" & A55 & "() : get" & A55 & " = str" & A55 & " : End Property" -> Public Property Get getChangeMyGovernmentIDs_NationalIDs_DateEmployeeSigned() : getChangeMyGovernmentIDs_NationalIDs_DateEmployeeSigned = strChangeMyGovernmentIDs_NationalIDs_DateEmployeeSigned : End Property
A56: =Test_Data!D57 -> ChangeMyGovernmentIDs_NationalIDs_DateEmployerSigned | B56: ="Private intRow" & A56 -> Private intRowChangeMyGovernmentIDs_NationalIDs_DateEmployerSigned | C56: ="Private str" & A56 -> Private strChangeMyGovernmentIDs_NationalIDs_DateEmployerSigned | D56: ="intRow" & A56 & " = comExcelWorksheet.Range(""" & A56 & """).Row" -> intRowChangeMyGovernmentIDs_NationalIDs_DateEmployerSigned = comExcelWorksheet.Range("ChangeMyGovernmentIDs_NationalIDs_DateEmployerSigned").Row | E56: ="str" & A56 & " = comExcelWorksheet.Cells(intRow" & A56 & ", intColTestColumn).Value" -> strChangeMyGovernmentIDs_NationalIDs_DateEmployerSigned = comExcelWorksheet.Cells(intRowChangeMyGovernmentIDs_NationalIDs_DateEmployerSigned, intColTestColumn).Value | F56: ="Public Property Get get" & A56 & "() : get" & A56 & " = str" & A56 & " : End Property" -> Public Property Get getChangeMyGovernmentIDs_NationalIDs_DateEmployerSigned() : getChangeMyGovernmentIDs_NationalIDs_DateEmployerSigned = strChangeMyGovernmentIDs_NationalIDs_DateEmployerSigned : End Property
A57: =Test_Data!#REF! -> #REF! | B57: ="Private intRow" & A57 -> #REF! | C57: ="Private str" & A57 -> #REF! | D57: ="intRow" & A57 & " = comExcelWorksheet.Range(""" & A57 & """).Row" -> #REF! | E57: ="str" & A57 & " = comExcelWorksheet.Cells(intRow" & A57 & ", intColTestColumn).Value" -> #REF! | F57: ="Public Property Get get" & A57 & "() : get" & A57 & " = str" & A57 & " : End Property" -> #REF!
A58: =Test_Data!#REF! -> #REF! | B58: ="Private intRow" & A58 -> #REF! | C58: ="Private str" & A58 -> #REF! | D58: ="intRow" & A58 & " = comExcelWorksheet.Range(""" & A58 & """).Row" -> #REF! | E58: ="str" & A58 & " = comExcelWorksheet.Cells(intRow" & A58 & ", intColTestColumn).Value" -> #REF! | F58: ="Public Property Get get" & A58 & "() : get" & A58 & " = str" & A58 & " : End Property" -> #REF!
A59: =Test_Data!#REF! -> #REF! | B59: ="Private intRow" & A59 -> #REF! | C59: ="Private str" & A59 -> #REF! | D59: ="intRow" & A59 & " = comExcelWorksheet.Range(""" & A59 & """).Row" -> #REF! | E59: ="str" & A59 & " = comExcelWorksheet.Cells(intRow" & A59 & ", intColTestColumn).Value" -> #REF! | F59: ="Public Property Get get" & A59 & "() : get" & A59 & " = str" & A59 & " : End Property" -> #REF!
A60: =Test_Data!#REF! -> #REF! | B60: ="Private intRow" & A60 -> #REF! | C60: ="Private str" & A60 -> #REF! | D60: ="intRow" & A60 & " = comExcelWorksheet.Range(""" & A60 & """).Row" -> #REF! | E60: ="str" & A60 & " = comExcelWorksheet.Cells(intRow" & A60 & ", intColTestColumn).Value" -> #REF! | F60: ="Public Property Get get" & A60 & "() : get" & A60 & " = str" & A60 & " : End Property" -> #REF!
A61: =Test_Data!D58 -> ChangeMyPersonalInformation_ContractEndDate | B61: ="Private intRow" & A61 -> Private intRowChangeMyPersonalInformation_ContractEndDate | C61: ="Private str" & A61 -> Private strChangeMyPersonalInformation_ContractEndDate | D61: ="intRow" & A61 & " = comExcelWorksheet.Range(""" & A61 & """).Row" -> intRowChangeMyPersonalInformation_ContractEndDate = comExcelWorksheet.Range("ChangeMyPersonalInformation_ContractEndDate").Row | E61: ="str" & A61 & " = comExcelWorksheet.Cells(intRow" & A61 & ", intColTestColumn).Value" -> strChangeMyPersonalInformation_ContractEndDate = comExcelWorksheet.Cells(intRowChangeMyPersonalInformation_ContractEndDate, intColTestColumn).Value | F61: ="Public Property Get get" & A61 & "() : get" & A61 & " = str" & A61 & " : End Property" -> Public Property Get getChangeMyPersonalInformation_ContractEndDate() : getChangeMyPersonalInformation_ContractEndDate = strChangeMyPersonalInformation_ContractEndDate : End Property
A62: =Test_Data!D59 -> ChangeMyPersonalInformation_CostCenter | B62: ="Private intRow" & A62 -> Private intRowChangeMyPersonalInformation_CostCenter | C62: ="Private str" & A62 -> Private strChangeMyPersonalInformation_CostCenter | D62: ="intRow" & A62 & " = comExcelWorksheet.Range(""" & A62 & """).Row" -> intRowChangeMyPersonalInformation_CostCenter = comExcelWorksheet.Range("ChangeMyPersonalInformation_CostCenter").Row | E62: ="str" & A62 & " = comExcelWorksheet.Cells(intRow" & A62 & ", intColTestColumn).Value" -> strChangeMyPersonalInformation_CostCenter = comExcelWorksheet.Cells(intRowChangeMyPersonalInformation_CostCenter, intColTestColumn).Value | F62: ="Public Property Get get" & A62 & "() : get" & A62 & " = str" & A62 & " : End Property" -> Public Property Get getChangeMyPersonalInformation_CostCenter() : getChangeMyPersonalInformation_CostCenter = strChangeMyPersonalInformation_CostCenter : End Property
A63: =Test_Data!#REF! -> #REF! | B63: ="Private intRow" & A63 -> #REF! | C63: ="Private str" & A63 -> #REF! | D63: ="intRow" & A63 & " = comExcelWorksheet.Range(""" & A63 & """).Row" -> #REF! | E63: ="str" & A63 & " = comExcelWorksheet.Cells(intRow" & A63 & ", intColTestColumn).Value" -> #REF! | F63: ="Public Property Get get" & A63 & "() : get" & A63 & " = str" & A63 & " : End Property" -> #REF!
A64: =Test_Data!#REF! -> #REF! | B64: ="Private intRow" & A64 -> #REF! | C64: ="Private str" & A64 -> #REF! | D64: ="intRow" & A64 & " = comExcelWorksheet.Range(""" & A64 & """).Row" -> #REF! | E64: ="str" & A64 & " = comExcelWorksheet.Cells(intRow" & A64 & ", intColTestColumn).Value" -> #REF! | F64: ="Public Property Get get" & A64 & "() : get" & A64 & " = str" & A64 & " : End Property" -> #REF!
A65: =Test_Data!#REF! -> #REF! | B65: ="Private intRow" & A65 -> #REF! | C65: ="Private str" & A65 -> #REF! | D65: ="intRow" & A65 & " = comExcelWorksheet.Range(""" & A65 & """).Row" -> #REF! | E65: ="str" & A65 & " = comExcelWorksheet.Cells(intRow" & A65 & ", intColTestColumn).Value" -> #REF! | F65: ="Public Property Get get" & A65 & "() : get" & A65 & " = str" & A65 & " : End Property" -> #REF!
A66: =Test_Data!#REF! -> #REF! | B66: ="Private intRow" & A66 -> #REF! | C66: ="Private str" & A66 -> #REF! | D66: ="intRow" & A66 & " = comExcelWorksheet.Range(""" & A66 & """).Row" -> #REF! | E66: ="str" & A66 & " = comExcelWorksheet.Cells(intRow" & A66 & ", intColTestColumn).Value" -> #REF! | F66: ="Public Property Get get" & A66 & "() : get" & A66 & " = str" & A66 & " : End Property" -> #REF!
A67: =Test_Data!#REF! -> #REF! | B67: ="Private intRow" & A67 -> #REF! | C67: ="Private str" & A67 -> #REF! | D67: ="intRow" & A67 & " = comExcelWorksheet.Range(""" & A67 & """).Row" -> #REF! | E67: ="str" & A67 & " = comExcelWorksheet.Cells(intRow" & A67 & ", intColTestColumn).Value" -> #REF! | F67: ="Public Property Get get" & A67 & "() : get" & A67 & " = str" & A67 & " : End Property" -> #REF!
A68: =Test_Data!#REF! -> #REF! | B68: ="Private intRow" & A68 -> #REF! | C68: ="Private str" & A68 -> #REF! | D68: ="intRow" & A68 & " = comExcelWorksheet.Range(""" & A68 & """).Row" -> #REF! | E68: ="str" & A68 & " = comExcelWorksheet.Cells(intRow" & A68 & ", intColTestColumn).Value" -> #REF! | F68: ="Public Property Get get" & A68 & "() : get" & A68 & " = str" & A68 & " : End Property" -> #REF!
A69: =Test_Data!#REF! -> #REF! | B69: ="Private intRow" & A69 -> #REF! | C69: ="Private str" & A69 -> #REF! | D69: ="intRow" & A69 & " = comExcelWorksheet.Range(""" & A69 & """).Row" -> #REF! | E69: ="str" & A69 & " = comExcelWorksheet.Cells(intRow" & A69 & ", intColTestColumn).Value" -> #REF! | F69: ="Public Property Get get" & A69 & "() : get" & A69 & " = str" & A69 & " : End Property" -> #REF!
A70: =Test_Data!#REF! -> #REF! | B70: ="Private intRow" & A70 -> #REF! | C70: ="Private str" & A70 -> #REF! | D70: ="intRow" & A70 & " = comExcelWorksheet.Range(""" & A70 & """).Row" -> #REF! | E70: ="str" & A70 & " = comExcelWorksheet.Cells(intRow" & A70 & ", intColTestColumn).Value" -> #REF! | F70: ="Public Property Get get" & A70 & "() : get" & A70 & " = str" & A70 & " : End Property" -> #REF!
A71: =Test_Data!#REF! -> #REF! | B71: ="Private intRow" & A71 -> #REF! | C71: ="Private str" & A71 -> #REF! | D71: ="intRow" & A71 & " = comExcelWorksheet.Range(""" & A71 & """).Row" -> #REF! | E71: ="str" & A71 & " = comExcelWorksheet.Cells(intRow" & A71 & ", intColTestColumn).Value" -> #REF! | F71: ="Public Property Get get" & A71 & "() : get" & A71 & " = str" & A71 & " : End Property" -> #REF!
A72: =Test_Data!#REF! -> #REF! | B72: ="Private intRow" & A72 -> #REF! | C72: ="Private str" & A72 -> #REF! | D72: ="intRow" & A72 & " = comExcelWorksheet.Range(""" & A72 & """).Row" -> #REF! | E72: ="str" & A72 & " = comExcelWorksheet.Cells(intRow" & A72 & ", intColTestColumn).Value" -> #REF! | F72: ="Public Property Get get" & A72 & "() : get" & A72 & " = str" & A72 & " : End Property" -> #REF!
A73: =Test_Data!D68 -> ProposeCompensationHire_NationalIDType1 | B73: ="Private intRow" & A73 -> Private intRowProposeCompensationHire_NationalIDType1 | C73: ="Private str" & A73 -> Private strProposeCompensationHire_NationalIDType1 | D73: ="intRow" & A73 & " = comExcelWorksheet.Range(""" & A73 & """).Row" -> intRowProposeCompensationHire_NationalIDType1 = comExcelWorksheet.Range("ProposeCompensationHire_NationalIDType1").Row | E73: ="str" & A73 & " = comExcelWorksheet.Cells(intRow" & A73 & ", intColTestColumn).Value" -> strProposeCompensationHire_NationalIDType1 = comExcelWorksheet.Cells(intRowProposeCompensationHire_NationalIDType1, intColTestColumn).Value | F73: ="Public Property Get get" & A73 & "() : get" & A73 & " = str" & A73 & " : End Property" -> Public Property Get getProposeCompensationHire_NationalIDType1() : getProposeCompensationHire_NationalIDType1 = strProposeCompensationHire_NationalIDType1 : End Property
A74: =Test_Data!#REF! -> #REF! | B74: ="Private intRow" & A74 -> #REF! | C74: ="Private str" & A74 -> #REF! | D74: ="intRow" & A74 & " = comExcelWorksheet.Range(""" & A74 & """).Row" -> #REF! | E74: ="str" & A74 & " = comExcelWorksheet.Cells(intRow" & A74 & ", intColTestColumn).Value" -> #REF! | F74: ="Public Property Get get" & A74 & "() : get" & A74 & " = str" & A74 & " : End Property" -> #REF!
A75: =Test_Data!#REF! -> #REF! | B75: ="Private intRow" & A75 -> #REF! | C75: ="Private str" & A75 -> #REF! | D75: ="intRow" & A75 & " = comExcelWorksheet.Range(""" & A75 & """).Row" -> #REF! | E75: ="str" & A75 & " = comExcelWorksheet.Cells(intRow" & A75 & ", intColTestColumn).Value" -> #REF! | F75: ="Public Property Get get" & A75 & "() : get" & A75 & " = str" & A75 & " : End Property" -> #REF!
A76: =Test_Data!#REF! -> #REF! | B76: ="Private intRow" & A76 -> #REF! | C76: ="Private str" & A76 -> #REF! | D76: ="intRow" & A76 & " = comExcelWorksheet.Range(""" & A76 & """).Row" -> #REF! | E76: ="str" & A76 & " = comExcelWorksheet.Cells(intRow" & A76 & ", intColTestColumn).Value" -> #REF! | F76: ="Public Property Get get" & A76 & "() : get" & A76 & " = str" & A76 & " : End Property" -> #REF!
A77: =Test_Data!#REF! -> #REF! | B77: ="Private intRow" & A77 -> #REF! | C77: ="Private str" & A77 -> #REF! | D77: ="intRow" & A77 & " = comExcelWorksheet.Range(""" & A77 & """).Row" -> #REF! | E77: ="str" & A77 & " = comExcelWorksheet.Cells(intRow" & A77 & ", intColTestColumn).Value" -> #REF! | F77: ="Public Property Get get" & A77 & "() : get" & A77 & " = str" & A77 & " : End Property" -> #REF!
A78: =Test_Data!#REF! -> #REF! | B78: ="Private intRow" & A78 -> #REF! | C78: ="Private str" & A78 -> #REF! | D78: ="intRow" & A78 & " = comExcelWorksheet.Range(""" & A78 & """).Row" -> #REF! | E78: ="str" & A78 & " = comExcelWorksheet.Cells(intRow" & A78 & ", intColTestColumn).Value" -> #REF! | F78: ="Public Property Get get" & A78 & "() : get" & A78 & " = str" & A78 & " : End Property" -> #REF!
A79: =Test_Data!#REF! -> #REF! | B79: ="Private intRow" & A79 -> #REF! | C79: ="Private str" & A79 -> #REF! | D79: ="intRow" & A79 & " = comExcelWorksheet.Range(""" & A79 & """).Row" -> #REF! | E79: ="str" & A79 & " = comExcelWorksheet.Cells(intRow" & A79 & ", intColTestColumn).Value" -> #REF! | F79: ="Public Property Get get" & A79 & "() : get" & A79 & " = str" & A79 & " : End Property" -> #REF!
A80: =Test_Data!#REF! -> #REF! | B80: ="Private intRow" & A80 -> #REF! | C80: ="Private str" & A80 -> #REF! | D80: ="intRow" & A80 & " = comExcelWorksheet.Range(""" & A80 & """).Row" -> #REF! | E80: ="str" & A80 & " = comExcelWorksheet.Cells(intRow" & A80 & ", intColTestColumn).Value" -> #REF! | F80: ="Public Property Get get" & A80 & "() : get" & A80 & " = str" & A80 & " : End Property" -> #REF!
A81: =Test_Data!#REF! -> #REF! | B81: ="Private intRow" & A81 -> #REF! | C81: ="Private str" & A81 -> #REF! | D81: ="intRow" & A81 & " = comExcelWorksheet.Range(""" & A81 & """).Row" -> #REF! | E81: ="str" & A81 & " = comExcelWorksheet.Cells(intRow" & A81 & ", intColTestColumn).Value" -> #REF! | F81: ="Public Property Get get" & A81 & "() : get" & A81 & " = str" & A81 & " : End Property" -> #REF!
A82: =Test_Data!#REF! -> #REF! | B82: ="Private intRow" & A82 -> #REF! | C82: ="Private str" & A82 -> #REF! | D82: ="intRow" & A82 & " = comExcelWorksheet.Range(""" & A82 & """).Row" -> #REF! | E82: ="str" & A82 & " = comExcelWorksheet.Cells(intRow" & A82 & ", intColTestColumn).Value" -> #REF! | F82: ="Public Property Get get" & A82 & "() : get" & A82 & " = str" & A82 & " : End Property" -> #REF!
A83: =Test_Data!#REF! -> #REF! | B83: ="Private intRow" & A83 -> #REF! | C83: ="Private str" & A83 -> #REF! | D83: ="intRow" & A83 & " = comExcelWorksheet.Range(""" & A83 & """).Row" -> #REF! | E83: ="str" & A83 & " = comExcelWorksheet.Cells(intRow" & A83 & ", intColTestColumn).Value" -> #REF! | F83: ="Public Property Get get" & A83 & "() : get" & A83 & " = str" & A83 & " : End Property" -> #REF!
A84: =Test_Data!#REF! -> #REF! | B84: ="Private intRow" & A84 -> #REF! | C84: ="Private str" & A84 -> #REF! | D84: ="intRow" & A84 & " = comExcelWorksheet.Range(""" & A84 & """).Row" -> #REF! | E84: ="str" & A84 & " = comExcelWorksheet.Cells(intRow" & A84 & ", intColTestColumn).Value" -> #REF! | F84: ="Public Property Get get" & A84 & "() : get" & A84 & " = str" & A84 & " : End Property" -> #REF!
A85: =Test_Data!#REF! -> #REF! | B85: ="Private intRow" & A85 -> #REF! | C85: ="Private str" & A85 -> #REF! | D85: ="intRow" & A85 & " = comExcelWorksheet.Range(""" & A85 & """).Row" -> #REF! | E85: ="str" & A85 & " = comExcelWorksheet.Cells(intRow" & A85 & ", intColTestColumn).Value" -> #REF! | F85: ="Public Property Get get" & A85 & "() : get" & A85 & " = str" & A85 & " : End Property" -> #REF!
... A91: =Test_Data!#REF! -> #REF! | B91: ="Private intRow" & A91 -> #REF! | C91: ="Private str" & A91 -> #REF! | D91: ="intRow" & A91 & " = comExcelWorksheet.Range(""" & A91 & """).Row" -> #REF! | E91: ="str" & A91 & " = comExcelWorksheet.Cells(intRow" & A91 & ", intColTestColumn).Value" -> #REF! | F91: ="Public Property Get get" & A91 & "() : get" & A91 & " = str" & A91 & " : End Property" -> #REF!
A92: =Test_Data!D70 -> AssignPayGroup_Country2 | B92: ="Private intRow" & A92 -> Private intRowAssignPayGroup_Country2 | C92: ="Private str" & A92 -> Private strAssignPayGroup_Country2 | D92: ="intRow" & A92 & " = comExcelWorksheet.Range(""" & A92 & """).Row" -> intRowAssignPayGroup_Country2 = comExcelWorksheet.Range("AssignPayGroup_Country2").Row | E92: ="str" & A92 & " = comExcelWorksheet.Cells(intRow" & A92 & ", intColTestColumn).Value" -> strAssignPayGroup_Country2 = comExcelWorksheet.Cells(intRowAssignPayGroup_Country2, intColTestColumn).Value | F92: ="Public Property Get get" & A92 & "() : get" &Code_Ranjeeta!A92 & " = str" & A92 & " : End Property" -> Public Property Get getAssignPayGroup_Country2() : getAssignPayGroup_Country2 = strAssignPayGroup_Country2 : End Property
A93: =Test_Data!#REF! -> #REF! | B93: ="Private intRow" & A93 -> #REF! | C93: ="Private str" & A93 -> #REF! | D93: ="intRow" & A93 & " = comExcelWorksheet.Range(""" & A93 & """).Row" -> #REF! | E93: ="str" & A93 & " = comExcelWorksheet.Cells(intRow" & A93 & ", intColTestColumn).Value" -> #REF! | F93: ="Public Property Get get" & A93 & "() : get" &Code_Ranjeeta!A93 & " = str" & A93 & " : End Property" -> #REF!
A94: PaymentElectionOption_BankIdentificationCode | B94: ="Private intRow" & A94 -> Private intRowPaymentElectionOption_BankIdentificationCode | C94: ="Private str" & A94 -> Private strPaymentElectionOption_BankIdentificationCode | D94: ="intRow" & A94 & " = comExcelWorksheet.Range(""" & A94 & """).Row" -> intRowPaymentElectionOption_BankIdentificationCode = comExcelWorksheet.Range("PaymentElectionOption_BankIdentificationCode").Row | E94: ="str" & A94 & " = comExcelWorksheet.Cells(intRow" & A94 & ", intColTestColumn).Value" -> strPaymentElectionOption_BankIdentificationCode = comExcelWorksheet.Cells(intRowPaymentElectionOption_BankIdentificationCode, intColTestColumn).Value | F94: ="Public Property Get get" & A94 & "() : get" &Code_Ranjeeta!A94 & " = str" & A94 & " : End Property" -> Public Property Get getPaymentElectionOption_BankIdentificationCode() : getPaymentElectionOption_BankIdentificationCode = strPaymentElectionOption_BankIdentificationCode : End Property

Sheet Code_11122019_1000
B1: Variable Row | C1: Variable Row Combined | D1: Variable Value | E1: Variable Value Combined | F1: Row Number Declaration --------------------------------- intRowProcess = comExcelWorksheet.Range("Process").Row | G1: Value Declaration ------------------------ strProcess = comExcelWorksheet.Cells(intRowProcess, intColTestColumn).Value | H1: Getters
A2: =Test_Data!D3 -> Process | B2: ="intRow" & A2 & ", " -> intRowProcess, | C2: =B2 -> intRowProcess, | D2: ="str" & A2 & ", " -> strProcess, | E2: =D2 -> strProcess, | F2: ="intRow" & A2 & " = comExcelWorksheet.Range(""" & A2 & """).Row" -> intRowProcess = comExcelWorksheet.Range("Process").Row | G2: ="str" & A2 & " = comExcelWorksheet.Cells(intRow" & A2 & ", intColTestColumn).Value" -> strProcess = comExcelWorksheet.Cells(intRowProcess, intColTestColumn).Value | H2: ="Public Property Get get" & A2 & "() : get" & A2 & " = str" & A2 & " : End Property" -> Public Property Get getProcess() : getProcess = strProcess : End Property
A3: =Test_Data!D4 -> ExecutionFlag | B3: ="intRow" & A3 & ", " -> intRowExecutionFlag, | C3: =C2 &B3 -> intRowProcess, intRowExecutionFlag, | D3: ="str" & A3 & ", " -> strExecutionFlag, | E3: =E2 &D3 -> strProcess, strExecutionFlag, | F3: ="intRow" & A3 & " = comExcelWorksheet.Range(""" & A3 & """).Row" -> intRowExecutionFlag = comExcelWorksheet.Range("ExecutionFlag").Row | G3: ="str" & A3 & " = comExcelWorksheet.Cells(intRow" & A3 & ", intColTestColumn).Value" -> strExecutionFlag = comExcelWorksheet.Cells(intRowExecutionFlag, intColTestColumn).Value | H3: ="Public Property Get get" & A3 & "() : get" & A3 & " = str" & A3 & " : End Property" -> Public Property Get getExecutionFlag() : getExecutionFlag = strExecutionFlag : End Property
A4: =Test_Data!D5 -> DataValidationComplete | B4: ="intRow" & A4 & ", " -> intRowDataValidationComplete, | C4: =C3 &B4 -> intRowProcess, intRowExecutionFlag, intRowDataValidationComplete, | D4: ="str" & A4 & ", " -> strDataValidationComplete, | E4: =E3 &D4 -> strProcess, strExecutionFlag, strDataValidationComplete, | F4: ="intRow" & A4 & " = comExcelWorksheet.Range(""" & A4 & """).Row" -> intRowDataValidationComplete = comExcelWorksheet.Range("DataValidationComplete").Row | G4: ="str" & A4 & " = comExcelWorksheet.Cells(intRow" & A4 & ", intColTestColumn).Value" -> strDataValidationComplete = comExcelWorksheet.Cells(intRowDataValidationComplete, intColTestColumn).Value | H4: ="Public Property Get get" & A4 & "() : get" & A4 & " = str" & A4 & " : End Property" -> Public Property Get getDataValidationComplete() : getDataValidationComplete = strDataValidationComplete : End Property
A5: =Test_Data!D6 -> HireNameComplete | B5: ="intRow" & A5 & ", " -> intRowHireNameComplete, | C5: =C4 &B5 -> intRowProcess, intRowExecutionFlag, intRowDataValidationComplete, intRowHireNameComplete, | D5: ="str" & A5 & ", " -> strHireNameComplete, | E5: =E4 &D5 -> strProcess, strExecutionFlag, strDataValidationComplete, strHireNameComplete, | F5: ="intRow" & A5 & " = comExcelWorksheet.Range(""" & A5 & """).Row" -> intRowHireNameComplete = comExcelWorksheet.Range("HireNameComplete").Row | G5: ="str" & A5 & " = comExcelWorksheet.Cells(intRow" & A5 & ", intColTestColumn).Value" -> strHireNameComplete = comExcelWorksheet.Cells(intRowHireNameComplete, intColTestColumn).Value | H5: ="Public Property Get get" & A5 & "() : get" & A5 & " = str" & A5 & " : End Property" -> Public Property Get getHireNameComplete() : getHireNameComplete = strHireNameComplete : End Property
A6: =Test_Data!D7 -> 0 | B6: ="intRow" & A6 & ", " -> intRow0, | C6: =C5 &B6 -> intRowProcess, intRowExecutionFlag, intRowDataValidationComplete, intRowHireNameComplete, intRow0, | D6: ="str" & A6 & ", " -> str0, | E6: =E5 &D6 -> strProcess, strExecutionFlag, strDataValidationComplete, strHireNameComplete, str0, | F6: ="intRow" & A6 & " = comExcelWorksheet.Range(""" & A6 & """).Row" -> intRow0 = comExcelWorksheet.Range("0").Row | G6: ="str" & A6 & " = comExcelWorksheet.Cells(intRow" & A6 & ", intColTestColumn).Value" -> str0 = comExcelWorksheet.Cells(intRow0, intColTestColumn).Value | H6: ="Public Property Get get" & A6 & "() : get" & A6 & " = str" & A6 & " : End Property" -> Public Property Get get0() : get0 = str0 : End Property
A7: =Test_Data!D8 -> 0 | B7: ="intRow" & A7 & ", " -> intRow0, | C7: =C6 &B7 -> intRowProcess, intRowExecutionFlag, intRowDataValidationComplete, intRowHireNameComplete, intRow0, intRow0, | D7: ="str" & A7 & ", " -> str0, | E7: =E6 &D7 -> strProcess, strExecutionFlag, strDataValidationComplete, strHireNameComplete, str0, str0, | F7: ="intRow" & A7 & " = comExcelWorksheet.Range(""" & A7 & """).Row" -> intRow0 = comExcelWorksheet.Range("0").Row | G7: ="str" & A7 & " = comExcelWorksheet.Cells(intRow" & A7 & ", intColTestColumn).Value" -> str0 = comExcelWorksheet.Cells(intRow0, intColTestColumn).Value | H7: ="Public Property Get get" & A7 & "() : get" & A7 & " = str" & A7 & " : End Property" -> Public Property Get get0() : get0 = str0 : End Property
A8: =Test_Data!D9 -> LastRunErrorMessage | B8: ="intRow" & A8 & ", " -> intRowLastRunErrorMessage, | C8: =C7 &B8 -> intRowProcess, intRowExecutionFlag, intRowDataValidationComplete, intRowHireNameComplete, intRow0, intRow0, intRowLastRunErrorMessage, | D8: ="str" & A8 & ", " -> strLastRunErrorMessage, | E8: =E7 &D8 -> strProcess, strExecutionFlag, strDataValidationComplete, strHireNameComplete, str0, str0, strLastRunErrorMessage, | F8: ="intRow" & A8 & " = comExcelWorksheet.Range(""" & A8 & """).Row" -> intRowLastRunErrorMessage = comExcelWorksheet.Range("LastRunErrorMessage").Row | G8: ="str" & A8 & " = comExcelWorksheet.Cells(intRow" & A8 & ", intColTestColumn).Value" -> strLastRunErrorMessage = comExcelWorksheet.Cells(intRowLastRunErrorMessage, intColTestColumn).Value | H8: ="Public Property Get get" & A8 & "() : get" & A8 & " = str" & A8 & " : End Property" -> Public Property Get getLastRunErrorMessage() : getLastRunErrorMessage = strLastRunErrorMessage : End Property
A9: =Test_Data!D10 -> DefectDescription | B9: ="intRow" & A9 & ", " -> intRowDefectDescription, | C9: =C8 &B9 -> intRowProcess, intRowExecutionFlag, intRowDataValidationComplete, intRowHireNameComplete, intRow0, intRow0, intRowLastRunErrorMessage, intRowDefectDescription, | D9: ="str" & A9 & ", " -> strDefectDescription, | E9: =E8 &D9 -> strProcess, strExecutionFlag, strDataValidationComplete, strHireNameComplete, str0, str0, strLastRunErrorMessage, strDefectDescription, | F9: ="intRow" & A9 & " = comExcelWorksheet.Range(""" & A9 & """).Row" -> intRowDefectDescription = comExcelWorksheet.Range("DefectDescription").Row | G9: ="str" & A9 & " = comExcelWorksheet.Cells(intRow" & A9 & ", intColTestColumn).Value" -> strDefectDescription = comExcelWorksheet.Cells(intRowDefectDescription, intColTestColumn).Value | H9: ="Public Property Get get" & A9 & "() : get" & A9 & " = str" & A9 & " : End Property" -> Public Property Get getDefectDescription() : getDefectDescription = strDefectDescription : End Property
A10: =Test_Data!D11 -> AutomationComments | B10: ="intRow" & A10 & ", " -> intRowAutomationComments, | C10: =C9 &B10 -> intRowProcess, intRowExecutionFlag, intRowDataValidationComplete, intRowHireNameComplete, intRow0, intRow0, intRowLastRunErrorMessage, intRowDefectDescription, intRowAutomationComments, | D10: ="str" & A10 & ", " -> strAutomationComments, | E10: =E9 &D10 -> strProcess, strExecutionFlag, strDataValidationComplete, strHireNameComplete, str0, str0, strLastRunErrorMessage, strDefectDescription, strAutomationComments, | F10: ="intRow" & A10 & " = comExcelWorksheet.Range(""" & A10 & """).Row" -> intRowAutomationComments = comExcelWorksheet.Range("AutomationComments").Row | G10: ="str" & A10 & " = comExcelWorksheet.Cells(intRow" & A10 & ", intColTestColumn).Value" -> strAutomationComments = comExcelWorksheet.Cells(intRowAutomationComments, intColTestColumn).Value | H10: ="Public Property Get get" & A10 & "() : get" & A10 & " = str" & A10 & " : End Property" -> Public Property Get getAutomationComments() : getAutomationComments = strAutomationComments : End Property
A11: =Test_Data!D12 -> QAComments | B11: ="intRow" & A11 & ", " -> intRowQAComments, | C11: =C10 &B11 -> intRowProcess, intRowExecutionFlag, intRowDataValidationComplete, intRowHireNameComplete, intRow0, intRow0, intRowLastRunErrorMessage, intRowDefectDescription, intRowAutomationComments, intRowQAComments, | D11: ="str" & A11 & ", " -> strQAComments, | E11: =E10 &D11 -> strProcess, strExecutionFlag, strDataValidationComplete, strHireNameComplete, str0, str0, strLastRunErrorMessage, strDefectDescription, strAutomationComments, strQAComments, | F11: ="intRow" & A11 & " = comExcelWorksheet.Range(""" & A11 & """).Row" -> intRowQAComments = comExcelWorksheet.Range("QAComments").Row | G11: ="str" & A11 & " = comExcelWorksheet.Cells(intRow" & A11 & ", intColTestColumn).Value" -> strQAComments = comExcelWorksheet.Cells(intRowQAComments, intColTestColumn).Value | H11: ="Public Property Get get" & A11 & "() : get" & A11 & " = str" & A11 & " : End Property" -> Public Property Get getQAComments() : getQAComments = strQAComments : End Property
A12: =Test_Data!D13 -> 0 | B12: ="intRow" & A12 & ", " -> intRow0, | C12: =C11 &B12 -> intRowProcess, intRowExecutionFlag, intRowDataValidationComplete, intRowHireNameComplete, intRow0, intRow0, intRowLastRunErrorMessage, intRowDefectDescription, intRowAutomationComments, intRowQAComments, intRow0, | D12: ="str" & A12 & ", " -> str0, | E12: =E11 &D12 -> strProcess, strExecutionFlag, strDataValidationComplete, strHireNameComplete, str0, str0, strLastRunErrorMessage, strDefectDescription, strAutomationComments, strQAComments, str0, | F12: ="intRow" & A12 & " = comExcelWorksheet.Range(""" & A12 & """).Row" -> intRow0 = comExcelWorksheet.Range("0").Row | G12: ="str" & A12 & " = comExcelWorksheet.Cells(intRow" & A12 & ", intColTestColumn).Value" -> str0 = comExcelWorksheet.Cells(intRow0, intColTestColumn).Value | H12: ="Public Property Get get" & A12 & "() : get" & A12 & " = str" & A12 & " : End Property" -> Public Property Get get0() : get0 = str0 : End Property
A13: =Test_Data!D14 -> Automation Ref | B13: ="intRow" & A13 & ", " -> intRowAutomation Ref, | C13: =C12 &B13 -> intRowProcess, intRowExecutionFlag, intRowDataValidationComplete, intRowHireNameComplete, intRow0, intRow0, intRowLastRunErrorMessage, intRowDefectDescription, intRowAutomationComments, intRowQAComments, intRow0, intRowAutomation Ref, | D13: ="str" & A13 & ", " -> strAutomation Ref, | E13: =E12 &D13 -> strProcess, strExecutionFlag, strDataValidationComplete, strHireNameComplete, str0, str0, strLastRunErrorMessage, strDefectDescription, strAutomationComments, strQAComments, str0, strAutomation Ref, | F13: ="intRow" & A13 & " = comExcelWorksheet.Range(""" & A13 & """).Row" -> intRowAutomation Ref = comExcelWorksheet.Range("Automation Ref").Row | G13: ="str" & A13 & " = comExcelWorksheet.Cells(intRow" & A13 & ", intColTestColumn).Value" -> strAutomation Ref = comExcelWorksheet.Cells(intRowAutomation Ref, intColTestColumn).Value | H13: ="Public Property Get get" & A13 & "() : get" & A13 & " = str" & A13 & " : End Property" -> Public Property Get getAutomation Ref() : getAutomation Ref = strAutomation Ref : End Property
A14: =Test_Data!#REF! -> #REF! | B14: ="intRow" & A14 & ", " -> #REF! | C14: =C13 &B14 -> #REF! | D14: ="str" & A14 & ", " -> #REF! | E14: =E13 &D14 -> #REF! | F14: ="intRow" & A14 & " = comExcelWorksheet.Range(""" & A14 & """).Row" -> #REF! | G14: ="str" & A14 & " = comExcelWorksheet.Cells(intRow" & A14 & ", intColTestColumn).Value" -> #REF! | H14: ="Public Property Get get" & A14 & "() : get" & A14 & " = str" & A14 & " : End Property" -> #REF!
A15: =Test_Data!#REF! -> #REF! | B15: ="intRow" & A15 & ", " -> #REF! | C15: =C14 &B15 -> #REF! | D15: ="str" & A15 & ", " -> #REF! | E15: =E14 &D15 -> #REF! | F15: ="intRow" & A15 & " = comExcelWorksheet.Range(""" & A15 & """).Row" -> #REF! | G15: ="str" & A15 & " = comExcelWorksheet.Cells(intRow" & A15 & ", intColTestColumn).Value" -> #REF! | H15: ="Public Property Get get" & A15 & "() : get" & A15 & " = str" & A15 & " : End Property" -> #REF!
A16: =Test_Data!D15 -> SupervisoryOrganisation_SupervisoryOrganisation | B16: ="intRow" & A16 & ", " -> intRowSupervisoryOrganisation_SupervisoryOrganisation, | C16: =C15 &B16 -> #REF! | D16: ="str" & A16 & ", " -> strSupervisoryOrganisation_SupervisoryOrganisation, | E16: =E15 &D16 -> #REF! | F16: ="intRow" & A16 & " = comExcelWorksheet.Range(""" & A16 & """).Row" -> intRowSupervisoryOrganisation_SupervisoryOrganisation = comExcelWorksheet.Range("SupervisoryOrganisation_SupervisoryOrganisation").Row | G16: ="str" & A16 & " = comExcelWorksheet.Cells(intRow" & A16 & ", intColTestColumn).Value" -> strSupervisoryOrganisation_SupervisoryOrganisation = comExcelWorksheet.Cells(intRowSupervisoryOrganisation_SupervisoryOrganisation, intColTestColumn).Value | H16: ="Public Property Get get" & A16 & "() : get" & A16 & " = str" & A16 & " : End Property" -> Public Property Get getSupervisoryOrganisation_SupervisoryOrganisation() : getSupervisoryOrganisation_SupervisoryOrganisation = strSupervisoryOrganisation_SupervisoryOrganisation : End Property
A17: =Test_Data!D16 -> LegalNameInformation_Country | B17: ="intRow" & A17 & ", " -> intRowLegalNameInformation_Country, | C17: =C16 &B17 -> #REF! | D17: ="str" & A17 & ", " -> strLegalNameInformation_Country, | E17: =E16 &D17 -> #REF! | F17: ="intRow" & A17 & " = comExcelWorksheet.Range(""" & A17 & """).Row" -> intRowLegalNameInformation_Country = comExcelWorksheet.Range("LegalNameInformation_Country").Row | G17: ="str" & A17 & " = comExcelWorksheet.Cells(intRow" & A17 & ", intColTestColumn).Value" -> strLegalNameInformation_Country = comExcelWorksheet.Cells(intRowLegalNameInformation_Country, intColTestColumn).Value | H17: ="Public Property Get get" & A17 & "() : get" & A17 & " = str" & A17 & " : End Property" -> Public Property Get getLegalNameInformation_Country() : getLegalNameInformation_Country = strLegalNameInformation_Country : End Property
A18: =Test_Data!D18 -> LegalNameInformation_GivenName | B18: ="intRow" & A18 & ", " -> intRowLegalNameInformation_GivenName, | C18: =C17 &B18 -> #REF! | D18: ="str" & A18 & ", " -> strLegalNameInformation_GivenName, | E18: =E17 &D18 -> #REF! | F18: ="intRow" & A18 & " = comExcelWorksheet.Range(""" & A18 & """).Row" -> intRowLegalNameInformation_GivenName = comExcelWorksheet.Range("LegalNameInformation_GivenName").Row | G18: ="str" & A18 & " = comExcelWorksheet.Cells(intRow" & A18 & ", intColTestColumn).Value" -> strLegalNameInformation_GivenName = comExcelWorksheet.Cells(intRowLegalNameInformation_GivenName, intColTestColumn).Value | H18: ="Public Property Get get" & A18 & "() : get" & A18 & " = str" & A18 & " : End Property" -> Public Property Get getLegalNameInformation_GivenName() : getLegalNameInformation_GivenName = strLegalNameInformation_GivenName : End Property
A19: =Test_Data!D19 -> LegalNameInformation_FamilyName | B19: ="intRow" & A19 & ", " -> intRowLegalNameInformation_FamilyName, | C19: =C18 &B19 -> #REF! | D19: ="str" & A19 & ", " -> strLegalNameInformation_FamilyName, | E19: =E18 &D19 -> #REF! | F19: ="intRow" & A19 & " = comExcelWorksheet.Range(""" & A19 & """).Row" -> intRowLegalNameInformation_FamilyName = comExcelWorksheet.Range("LegalNameInformation_FamilyName").Row | G19: ="str" & A19 & " = comExcelWorksheet.Cells(intRow" & A19 & ", intColTestColumn).Value" -> strLegalNameInformation_FamilyName = comExcelWorksheet.Cells(intRowLegalNameInformation_FamilyName, intColTestColumn).Value | H19: ="Public Property Get get" & A19 & "() : get" & A19 & " = str" & A19 & " : End Property" -> Public Property Get getLegalNameInformation_FamilyName() : getLegalNameInformation_FamilyName = strLegalNameInformation_FamilyName : End Property
A20: =Test_Data!D20 -> ContactInformation_Phone_PhoneNumber | B20: ="intRow" & A20 & ", " -> intRowContactInformation_Phone_PhoneNumber, | C20: =C19 &B20 -> #REF! | D20: ="str" & A20 & ", " -> strContactInformation_Phone_PhoneNumber, | E20: =E19 &D20 -> #REF! | F20: ="intRow" & A20 & " = comExcelWorksheet.Range(""" & A20 & """).Row" -> intRowContactInformation_Phone_PhoneNumber = comExcelWorksheet.Range("ContactInformation_Phone_PhoneNumber").Row | G20: ="str" & A20 & " = comExcelWorksheet.Cells(intRow" & A20 & ", intColTestColumn).Value" -> strContactInformation_Phone_PhoneNumber = comExcelWorksheet.Cells(intRowContactInformation_Phone_PhoneNumber, intColTestColumn).Value | H20: ="Public Property Get get" & A20 & "() : get" & A20 & " = str" & A20 & " : End Property" -> Public Property Get getContactInformation_Phone_PhoneNumber() : getContactInformation_Phone_PhoneNumber = strContactInformation_Phone_PhoneNumber : End Property
A21: =Test_Data!D21 -> ContactInformation_Phone_PhoneDevice | B21: ="intRow" & A21 & ", " -> intRowContactInformation_Phone_PhoneDevice, | C21: =C20 &B21 -> #REF! | D21: ="str" & A21 & ", " -> strContactInformation_Phone_PhoneDevice, | E21: =E20 &D21 -> #REF! | F21: ="intRow" & A21 & " = comExcelWorksheet.Range(""" & A21 & """).Row" -> intRowContactInformation_Phone_PhoneDevice = comExcelWorksheet.Range("ContactInformation_Phone_PhoneDevice").Row | G21: ="str" & A21 & " = comExcelWorksheet.Cells(intRow" & A21 & ", intColTestColumn).Value" -> strContactInformation_Phone_PhoneDevice = comExcelWorksheet.Cells(intRowContactInformation_Phone_PhoneDevice, intColTestColumn).Value | H21: ="Public Property Get get" & A21 & "() : get" & A21 & " = str" & A21 & " : End Property" -> Public Property Get getContactInformation_Phone_PhoneDevice() : getContactInformation_Phone_PhoneDevice = strContactInformation_Phone_PhoneDevice : End Property
A22: =Test_Data!D22 -> ContactInformation_Phone_Type | B22: ="intRow" & A22 & ", " -> intRowContactInformation_Phone_Type, | C22: =C21 &B22 -> #REF! | D22: ="str" & A22 & ", " -> strContactInformation_Phone_Type, | E22: =E21 &D22 -> #REF! | F22: ="intRow" & A22 & " = comExcelWorksheet.Range(""" & A22 & """).Row" -> intRowContactInformation_Phone_Type = comExcelWorksheet.Range("ContactInformation_Phone_Type").Row | G22: ="str" & A22 & " = comExcelWorksheet.Cells(intRow" & A22 & ", intColTestColumn).Value" -> strContactInformation_Phone_Type = comExcelWorksheet.Cells(intRowContactInformation_Phone_Type, intColTestColumn).Value | H22: ="Public Property Get get" & A22 & "() : get" & A22 & " = str" & A22 & " : End Property" -> Public Property Get getContactInformation_Phone_Type() : getContactInformation_Phone_Type = strContactInformation_Phone_Type : End Property
A23: =Test_Data!D23 -> ContactInformation_Address_EffectiveDate | B23: ="intRow" & A23 & ", " -> intRowContactInformation_Address_EffectiveDate, | C23: =C22 &B23 -> #REF! | D23: ="str" & A23 & ", " -> strContactInformation_Address_EffectiveDate, | E23: =E22 &D23 -> #REF! | F23: ="intRow" & A23 & " = comExcelWorksheet.Range(""" & A23 & """).Row" -> intRowContactInformation_Address_EffectiveDate = comExcelWorksheet.Range("ContactInformation_Address_EffectiveDate").Row | G23: ="str" & A23 & " = comExcelWorksheet.Cells(intRow" & A23 & ", intColTestColumn).Value" -> strContactInformation_Address_EffectiveDate = comExcelWorksheet.Cells(intRowContactInformation_Address_EffectiveDate, intColTestColumn).Value | H23: ="Public Property Get get" & A23 & "() : get" & A23 & " = str" & A23 & " : End Property" -> Public Property Get getContactInformation_Address_EffectiveDate() : getContactInformation_Address_EffectiveDate = strContactInformation_Address_EffectiveDate : End Property
A24: =Test_Data!D24 -> ContactInformation_Address_Country | B24: ="intRow" & A24 & ", " -> intRowContactInformation_Address_Country, | C24: =C23 &B24 -> #REF! | D24: ="str" & A24 & ", " -> strContactInformation_Address_Country, | E24: =E23 &D24 -> #REF! | F24: ="intRow" & A24 & " = comExcelWorksheet.Range(""" & A24 & """).Row" -> intRowContactInformation_Address_Country = comExcelWorksheet.Range("ContactInformation_Address_Country").Row | G24: ="str" & A24 & " = comExcelWorksheet.Cells(intRow" & A24 & ", intColTestColumn).Value" -> strContactInformation_Address_Country = comExcelWorksheet.Cells(intRowContactInformation_Address_Country, intColTestColumn).Value | H24: ="Public Property Get get" & A24 & "() : get" & A24 & " = str" & A24 & " : End Property" -> Public Property Get getContactInformation_Address_Country() : getContactInformation_Address_Country = strContactInformation_Address_Country : End Property
A25: =Test_Data!#REF! -> #REF! | B25: ="intRow" & A25 & ", " -> #REF! | C25: =C24 &B25 -> #REF! | D25: ="str" & A25 & ", " -> #REF! | E25: =E24 &D25 -> #REF! | F25: ="intRow" & A25 & " = comExcelWorksheet.Range(""" & A25 & """).Row" -> #REF! | G25: ="str" & A25 & " = comExcelWorksheet.Cells(intRow" & A25 & ", intColTestColumn).Value" -> #REF! | H25: ="Public Property Get get" & A25 & "() : get" & A25 & " = str" & A25 & " : End Property" -> #REF!
A26: =Test_Data!#REF! -> #REF! | B26: ="intRow" & A26 & ", " -> #REF! | C26: =C25 &B26 -> #REF! | D26: ="str" & A26 & ", " -> #REF! | E26: =E25 &D26 -> #REF! | F26: ="intRow" & A26 & " = comExcelWorksheet.Range(""" & A26 & """).Row" -> #REF! | G26: ="str" & A26 & " = comExcelWorksheet.Cells(intRow" & A26 & ", intColTestColumn).Value" -> #REF! | H26: ="Public Property Get get" & A26 & "() : get" & A26 & " = str" & A26 & " : End Property" -> #REF!
A27: =Test_Data!D27 -> ContactInformation_Address_PostalCode | B27: ="intRow" & A27 & ", " -> intRowContactInformation_Address_PostalCode, | C27: =C26 &B27 -> #REF! | D27: ="str" & A27 & ", " -> strContactInformation_Address_PostalCode, | E27: =E26 &D27 -> #REF! | F27: ="intRow" & A27 & " = comExcelWorksheet.Range(""" & A27 & """).Row" -> intRowContactInformation_Address_PostalCode = comExcelWorksheet.Range("ContactInformation_Address_PostalCode").Row | G27: ="str" & A27 & " = comExcelWorksheet.Cells(intRow" & A27 & ", intColTestColumn).Value" -> strContactInformation_Address_PostalCode = comExcelWorksheet.Cells(intRowContactInformation_Address_PostalCode, intColTestColumn).Value | H27: ="Public Property Get get" & A27 & "() : get" & A27 & " = str" & A27 & " : End Property" -> Public Property Get getContactInformation_Address_PostalCode() : getContactInformation_Address_PostalCode = strContactInformation_Address_PostalCode : End Property
A28: =Test_Data!D30 -> ContactInformation_Address_Municipality | B28: ="intRow" & A28 & ", " -> intRowContactInformation_Address_Municipality, | C28: =C27 &B28 -> #REF! | D28: ="str" & A28 & ", " -> strContactInformation_Address_Municipality, | E28: =E27 &D28 -> #REF! | F28: ="intRow" & A28 & " = comExcelWorksheet.Range(""" & A28 & """).Row" -> intRowContactInformation_Address_Municipality = comExcelWorksheet.Range("ContactInformation_Address_Municipality").Row | G28: ="str" & A28 & " = comExcelWorksheet.Cells(intRow" & A28 & ", intColTestColumn).Value" -> strContactInformation_Address_Municipality = comExcelWorksheet.Cells(intRowContactInformation_Address_Municipality, intColTestColumn).Value | H28: ="Public Property Get get" & A28 & "() : get" & A28 & " = str" & A28 & " : End Property" -> Public Property Get getContactInformation_Address_Municipality() : getContactInformation_Address_Municipality = strContactInformation_Address_Municipality : End Property
A29: =Test_Data!#REF! -> #REF! | B29: ="intRow" & A29 & ", " -> #REF! | C29: =C28 &B29 -> #REF! | D29: ="str" & A29 & ", " -> #REF! | E29: =E28 &D29 -> #REF! | F29: ="intRow" & A29 & " = comExcelWorksheet.Range(""" & A29 & """).Row" -> #REF! | G29: ="str" & A29 & " = comExcelWorksheet.Cells(intRow" & A29 & ", intColTestColumn).Value" -> #REF! | H29: ="Public Property Get get" & A29 & "() : get" & A29 & " = str" & A29 & " : End Property" -> #REF!
A30: =Test_Data!D31 -> ContactInformation_Address_District | B30: ="intRow" & A30 & ", " -> intRowContactInformation_Address_District, | C30: =C29 &B30 -> #REF! | D30: ="str" & A30 & ", " -> strContactInformation_Address_District, | E30: =E29 &D30 -> #REF! | F30: ="intRow" & A30 & " = comExcelWorksheet.Range(""" & A30 & """).Row" -> intRowContactInformation_Address_District = comExcelWorksheet.Range("ContactInformation_Address_District").Row | G30: ="str" & A30 & " = comExcelWorksheet.Cells(intRow" & A30 & ", intColTestColumn).Value" -> strContactInformation_Address_District = comExcelWorksheet.Cells(intRowContactInformation_Address_District, intColTestColumn).Value | H30: ="Public Property Get get" & A30 & "() : get" & A30 & " = str" & A30 & " : End Property" -> Public Property Get getContactInformation_Address_District() : getContactInformation_Address_District = strContactInformation_Address_District : End Property
A31: =Test_Data!D32 -> ContactInformation_Address_Type | B31: ="intRow" & A31 & ", " -> intRowContactInformation_Address_Type, | C31: =C30 &B31 -> #REF! | D31: ="str" & A31 & ", " -> strContactInformation_Address_Type, | E31: =E30 &D31 -> #REF! | F31: ="intRow" & A31 & " = comExcelWorksheet.Range(""" & A31 & """).Row" -> intRowContactInformation_Address_Type = comExcelWorksheet.Range("ContactInformation_Address_Type").Row | G31: ="str" & A31 & " = comExcelWorksheet.Cells(intRow" & A31 & ", intColTestColumn).Value" -> strContactInformation_Address_Type = comExcelWorksheet.Cells(intRowContactInformation_Address_Type, intColTestColumn).Value | H31: ="Public Property Get get" & A31 & "() : get" & A31 & " = str" & A31 & " : End Property" -> Public Property Get getContactInformation_Address_Type() : getContactInformation_Address_Type = strContactInformation_Address_Type : End Property
A32: =Test_Data!D33 -> ContactInformation_Email_UseFor | B32: ="intRow" & A32 & ", " -> intRowContactInformation_Email_UseFor, | C32: =C31 &B32 -> #REF! | D32: ="str" & A32 & ", " -> strContactInformation_Email_UseFor, | E32: =E31 &D32 -> #REF! | F32: ="intRow" & A32 & " = comExcelWorksheet.Range(""" & A32 & """).Row" -> intRowContactInformation_Email_UseFor = comExcelWorksheet.Range("ContactInformation_Email_UseFor").Row | G32: ="str" & A32 & " = comExcelWorksheet.Cells(intRow" & A32 & ", intColTestColumn).Value" -> strContactInformation_Email_UseFor = comExcelWorksheet.Cells(intRowContactInformation_Email_UseFor, intColTestColumn).Value | H32: ="Public Property Get get" & A32 & "() : get" & A32 & " = str" & A32 & " : End Property" -> Public Property Get getContactInformation_Email_UseFor() : getContactInformation_Email_UseFor = strContactInformation_Email_UseFor : End Property
A33: =Test_Data!D34 -> ContactInformation_Email_EmailAddress | B33: ="intRow" & A33 & ", " -> intRowContactInformation_Email_EmailAddress, | C33: =C32 &B33 -> #REF! | D33: ="str" & A33 & ", " -> strContactInformation_Email_EmailAddress, | E33: =E32 &D33 -> #REF! | F33: ="intRow" & A33 & " = comExcelWorksheet.Range(""" & A33 & """).Row" -> intRowContactInformation_Email_EmailAddress = comExcelWorksheet.Range("ContactInformation_Email_EmailAddress").Row | G33: ="str" & A33 & " = comExcelWorksheet.Cells(intRow" & A33 & ", intColTestColumn).Value" -> strContactInformation_Email_EmailAddress = comExcelWorksheet.Cells(intRowContactInformation_Email_EmailAddress, intColTestColumn).Value | H33: ="Public Property Get get" & A33 & "() : get" & A33 & " = str" & A33 & " : End Property" -> Public Property Get getContactInformation_Email_EmailAddress() : getContactInformation_Email_EmailAddress = strContactInformation_Email_EmailAddress : End Property
A34: =Test_Data!D35 -> JobDetails_Type | B34: ="intRow" & A34 & ", " -> intRowJobDetails_Type, | C34: =C33 &B34 -> #REF! | D34: ="str" & A34 & ", " -> strJobDetails_Type, | E34: =E33 &D34 -> #REF! | F34: ="intRow" & A34 & " = comExcelWorksheet.Range(""" & A34 & """).Row" -> intRowJobDetails_Type = comExcelWorksheet.Range("JobDetails_Type").Row | G34: ="str" & A34 & " = comExcelWorksheet.Cells(intRow" & A34 & ", intColTestColumn).Value" -> strJobDetails_Type = comExcelWorksheet.Cells(intRowJobDetails_Type, intColTestColumn).Value | H34: ="Public Property Get get" & A34 & "() : get" & A34 & " = str" & A34 & " : End Property" -> Public Property Get getJobDetails_Type() : getJobDetails_Type = strJobDetails_Type : End Property
A35: =Test_Data!D36 -> JobDetails_HireDate | B35: ="intRow" & A35 & ", " -> intRowJobDetails_HireDate, | C35: =C34 &B35 -> #REF! | D35: ="str" & A35 & ", " -> strJobDetails_HireDate, | E35: =E34 &D35 -> #REF! | F35: ="intRow" & A35 & " = comExcelWorksheet.Range(""" & A35 & """).Row" -> intRowJobDetails_HireDate = comExcelWorksheet.Range("JobDetails_HireDate").Row | G35: ="str" & A35 & " = comExcelWorksheet.Cells(intRow" & A35 & ", intColTestColumn).Value" -> strJobDetails_HireDate = comExcelWorksheet.Cells(intRowJobDetails_HireDate, intColTestColumn).Value | H35: ="Public Property Get get" & A35 & "() : get" & A35 & " = str" & A35 & " : End Property" -> Public Property Get getJobDetails_HireDate() : getJobDetails_HireDate = strJobDetails_HireDate : End Property
A36: =Test_Data!D37 -> JobDetails_Reason | B36: ="intRow" & A36 & ", " -> intRowJobDetails_Reason, | C36: =C35 &B36 -> #REF! | D36: ="str" & A36 & ", " -> strJobDetails_Reason, | E36: =E35 &D36 -> #REF! | F36: ="intRow" & A36 & " = comExcelWorksheet.Range(""" & A36 & """).Row" -> intRowJobDetails_Reason = comExcelWorksheet.Range("JobDetails_Reason").Row | G36: ="str" & A36 & " = comExcelWorksheet.Cells(intRow" & A36 & ", intColTestColumn).Value" -> strJobDetails_Reason = comExcelWorksheet.Cells(intRowJobDetails_Reason, intColTestColumn).Value | H36: ="Public Property Get get" & A36 & "() : get" & A36 & " = str" & A36 & " : End Property" -> Public Property Get getJobDetails_Reason() : getJobDetails_Reason = strJobDetails_Reason : End Property
A37: =Test_Data!D38 -> JobDetails_Position | B37: ="intRow" & A37 & ", " -> intRowJobDetails_Position, | C37: =C36 &B37 -> #REF! | D37: ="str" & A37 & ", " -> strJobDetails_Position, | E37: =E36 &D37 -> #REF! | F37: ="intRow" & A37 & " = comExcelWorksheet.Range(""" & A37 & """).Row" -> intRowJobDetails_Position = comExcelWorksheet.Range("JobDetails_Position").Row | G37: ="str" & A37 & " = comExcelWorksheet.Cells(intRow" & A37 & ", intColTestColumn).Value" -> strJobDetails_Position = comExcelWorksheet.Cells(intRowJobDetails_Position, intColTestColumn).Value | H37: ="Public Property Get get" & A37 & "() : get" & A37 & " = str" & A37 & " : End Property" -> Public Property Get getJobDetails_Position() : getJobDetails_Position = strJobDetails_Position : End Property
A38: =Test_Data!D39 -> JobDetails_EmployeeType | B38: ="intRow" & A38 & ", " -> intRowJobDetails_EmployeeType, | C38: =C37 &B38 -> #REF! | D38: ="str" & A38 & ", " -> strJobDetails_EmployeeType, | E38: =E37 &D38 -> #REF! | F38: ="intRow" & A38 & " = comExcelWorksheet.Range(""" & A38 & """).Row" -> intRowJobDetails_EmployeeType = comExcelWorksheet.Range("JobDetails_EmployeeType").Row | G38: ="str" & A38 & " = comExcelWorksheet.Cells(intRow" & A38 & ", intColTestColumn).Value" -> strJobDetails_EmployeeType = comExcelWorksheet.Cells(intRowJobDetails_EmployeeType, intColTestColumn).Value | H38: ="Public Property Get get" & A38 & "() : get" & A38 & " = str" & A38 & " : End Property" -> Public Property Get getJobDetails_EmployeeType() : getJobDetails_EmployeeType = strJobDetails_EmployeeType : End Property
A39: =Test_Data!D40 -> JobDetails_JobProfile | B39: ="intRow" & A39 & ", " -> intRowJobDetails_JobProfile, | C39: =C38 &B39 -> #REF! | D39: ="str" & A39 & ", " -> strJobDetails_JobProfile, | E39: =E38 &D39 -> #REF! | F39: ="intRow" & A39 & " = comExcelWorksheet.Range(""" & A39 & """).Row" -> intRowJobDetails_JobProfile = comExcelWorksheet.Range("JobDetails_JobProfile").Row | G39: ="str" & A39 & " = comExcelWorksheet.Cells(intRow" & A39 & ", intColTestColumn).Value" -> strJobDetails_JobProfile = comExcelWorksheet.Cells(intRowJobDetails_JobProfile, intColTestColumn).Value | H39: ="Public Property Get get" & A39 & "() : get" & A39 & " = str" & A39 & " : End Property" -> Public Property Get getJobDetails_JobProfile() : getJobDetails_JobProfile = strJobDetails_JobProfile : End Property
A40: =Test_Data!D41 -> JobDetails_TimeType | B40: ="intRow" & A40 & ", " -> intRowJobDetails_TimeType, | C40: =C39 &B40 -> #REF! | D40: ="str" & A40 & ", " -> strJobDetails_TimeType, | E40: =E39 &D40 -> #REF! | F40: ="intRow" & A40 & " = comExcelWorksheet.Range(""" & A40 & """).Row" -> intRowJobDetails_TimeType = comExcelWorksheet.Range("JobDetails_TimeType").Row | G40: ="str" & A40 & " = comExcelWorksheet.Cells(intRow" & A40 & ", intColTestColumn).Value" -> strJobDetails_TimeType = comExcelWorksheet.Cells(intRowJobDetails_TimeType, intColTestColumn).Value | H40: ="Public Property Get get" & A40 & "() : get" & A40 & " = str" & A40 & " : End Property" -> Public Property Get getJobDetails_TimeType() : getJobDetails_TimeType = strJobDetails_TimeType : End Property
A41: =Test_Data!D43 -> JobDetails_AdditionalInformation_PayRateType | B41: ="intRow" & A41 & ", " -> intRowJobDetails_AdditionalInformation_PayRateType, | C41: =C40 &B41 -> #REF! | D41: ="str" & A41 & ", " -> strJobDetails_AdditionalInformation_PayRateType, | E41: =E40 &D41 -> #REF! | F41: ="intRow" & A41 & " = comExcelWorksheet.Range(""" & A41 & """).Row" -> intRowJobDetails_AdditionalInformation_PayRateType = comExcelWorksheet.Range("JobDetails_AdditionalInformation_PayRateType").Row | G41: ="str" & A41 & " = comExcelWorksheet.Cells(intRow" & A41 & ", intColTestColumn).Value" -> strJobDetails_AdditionalInformation_PayRateType = comExcelWorksheet.Cells(intRowJobDetails_AdditionalInformation_PayRateType, intColTestColumn).Value | H41: ="Public Property Get get" & A41 & "() : get" & A41 & " = str" & A41 & " : End Property" -> Public Property Get getJobDetails_AdditionalInformation_PayRateType() : getJobDetails_AdditionalInformation_PayRateType = strJobDetails_AdditionalInformation_PayRateType : End Property
A42: =Test_Data!D44 -> JobDetails_AdditionalInformation_ScheduledWeeklyHours | B42: ="intRow" & A42 & ", " -> intRowJobDetails_AdditionalInformation_ScheduledWeeklyHours, | C42: =C41 &B42 -> #REF! | D42: ="str" & A42 & ", " -> strJobDetails_AdditionalInformation_ScheduledWeeklyHours, | E42: =E41 &D42 -> #REF! | F42: ="intRow" & A42 & " = comExcelWorksheet.Range(""" & A42 & """).Row" -> intRowJobDetails_AdditionalInformation_ScheduledWeeklyHours = comExcelWorksheet.Range("JobDetails_AdditionalInformation_ScheduledWeeklyHours").Row | G42: ="str" & A42 & " = comExcelWorksheet.Cells(intRow" & A42 & ", intColTestColumn).Value" -> strJobDetails_AdditionalInformation_ScheduledWeeklyHours = comExcelWorksheet.Cells(intRowJobDetails_AdditionalInformation_ScheduledWeeklyHours, intColTestColumn).Value | H42: ="Public Property Get get" & A42 & "() : get" & A42 & " = str" & A42 & " : End Property" -> Public Property Get getJobDetails_AdditionalInformation_ScheduledWeeklyHours() : getJobDetails_AdditionalInformation_ScheduledWeeklyHours = strJobDetails_AdditionalInformation_ScheduledWeeklyHours : End Property
A43: =Test_Data!D45 -> JobDetails_AdditionalInformation_SchoolName | B43: ="intRow" & A43 & ", " -> intRowJobDetails_AdditionalInformation_SchoolName, | C43: =C42 &B43 -> #REF! | D43: ="str" & A43 & ", " -> strJobDetails_AdditionalInformation_SchoolName, | E43: =E42 &D43 -> #REF! | F43: ="intRow" & A43 & " = comExcelWorksheet.Range(""" & A43 & """).Row" -> intRowJobDetails_AdditionalInformation_SchoolName = comExcelWorksheet.Range("JobDetails_AdditionalInformation_SchoolName").Row | G43: ="str" & A43 & " = comExcelWorksheet.Cells(intRow" & A43 & ", intColTestColumn).Value" -> strJobDetails_AdditionalInformation_SchoolName = comExcelWorksheet.Cells(intRowJobDetails_AdditionalInformation_SchoolName, intColTestColumn).Value | H43: ="Public Property Get get" & A43 & "() : get" & A43 & " = str" & A43 & " : End Property" -> Public Property Get getJobDetails_AdditionalInformation_SchoolName() : getJobDetails_AdditionalInformation_SchoolName = strJobDetails_AdditionalInformation_SchoolName : End Property
A44: =Test_Data!D46 -> JobDetails_AdditionalInformation_SchoolType | B44: ="intRow" & A44 & ", " -> intRowJobDetails_AdditionalInformation_SchoolType, | C44: =C43 &B44 -> #REF! | D44: ="str" & A44 & ", " -> strJobDetails_AdditionalInformation_SchoolType, | E44: =E43 &D44 -> #REF! | F44: ="intRow" & A44 & " = comExcelWorksheet.Range(""" & A44 & """).Row" -> intRowJobDetails_AdditionalInformation_SchoolType = comExcelWorksheet.Range("JobDetails_AdditionalInformation_SchoolType").Row | G44: ="str" & A44 & " = comExcelWorksheet.Cells(intRow" & A44 & ", intColTestColumn).Value" -> strJobDetails_AdditionalInformation_SchoolType = comExcelWorksheet.Cells(intRowJobDetails_AdditionalInformation_SchoolType, intColTestColumn).Value | H44: ="Public Property Get get" & A44 & "() : get" & A44 & " = str" & A44 & " : End Property" -> Public Property Get getJobDetails_AdditionalInformation_SchoolType() : getJobDetails_AdditionalInformation_SchoolType = strJobDetails_AdditionalInformation_SchoolType : End Property
A45: =Test_Data!D47 -> JobDetails_AdditionalInformation_SchoolStartDate | B45: ="intRow" & A45 & ", " -> intRowJobDetails_AdditionalInformation_SchoolStartDate, | C45: =C44 &B45 -> #REF! | D45: ="str" & A45 & ", " -> strJobDetails_AdditionalInformation_SchoolStartDate, | E45: =E44 &D45 -> #REF! | F45: ="intRow" & A45 & " = comExcelWorksheet.Range(""" & A45 & """).Row" -> intRowJobDetails_AdditionalInformation_SchoolStartDate = comExcelWorksheet.Range("JobDetails_AdditionalInformation_SchoolStartDate").Row | G45: ="str" & A45 & " = comExcelWorksheet.Cells(intRow" & A45 & ", intColTestColumn).Value" -> strJobDetails_AdditionalInformation_SchoolStartDate = comExcelWorksheet.Cells(intRowJobDetails_AdditionalInformation_SchoolStartDate, intColTestColumn).Value | H45: ="Public Property Get get" & A45 & "() : get" & A45 & " = str" & A45 & " : End Property" -> Public Property Get getJobDetails_AdditionalInformation_SchoolStartDate() : getJobDetails_AdditionalInformation_SchoolStartDate = strJobDetails_AdditionalInformation_SchoolStartDate : End Property
A46: =Test_Data!D53 -> ChangeOrganizationAssignments_Comments | B46: ="intRow" & A46 & ", " -> intRowChangeOrganizationAssignments_Comments, | C46: =C45 &B46 -> #REF! | D46: ="str" & A46 & ", " -> strChangeOrganizationAssignments_Comments, | E46: =E45 &D46 -> #REF! | F46: ="intRow" & A46 & " = comExcelWorksheet.Range(""" & A46 & """).Row" -> intRowChangeOrganizationAssignments_Comments = comExcelWorksheet.Range("ChangeOrganizationAssignments_Comments").Row | G46: ="str" & A46 & " = comExcelWorksheet.Cells(intRow" & A46 & ", intColTestColumn).Value" -> strChangeOrganizationAssignments_Comments = comExcelWorksheet.Cells(intRowChangeOrganizationAssignments_Comments, intColTestColumn).Value | H46: ="Public Property Get get" & A46 & "() : get" & A46 & " = str" & A46 & " : End Property" -> Public Property Get getChangeOrganizationAssignments_Comments() : getChangeOrganizationAssignments_Comments = strChangeOrganizationAssignments_Comments : End Property
A47: =Test_Data!D54 -> ChangeOrganizationAssignments_ContractType | B47: ="intRow" & A47 & ", " -> intRowChangeOrganizationAssignments_ContractType, | C47: =C46 &B47 -> #REF! | D47: ="str" & A47 & ", " -> strChangeOrganizationAssignments_ContractType, | E47: =E46 &D47 -> #REF! | F47: ="intRow" & A47 & " = comExcelWorksheet.Range(""" & A47 & """).Row" -> intRowChangeOrganizationAssignments_ContractType = comExcelWorksheet.Range("ChangeOrganizationAssignments_ContractType").Row | G47: ="str" & A47 & " = comExcelWorksheet.Cells(intRow" & A47 & ", intColTestColumn).Value" -> strChangeOrganizationAssignments_ContractType = comExcelWorksheet.Cells(intRowChangeOrganizationAssignments_ContractType, intColTestColumn).Value | H47: ="Public Property Get get" & A47 & "() : get" & A47 & " = str" & A47 & " : End Property" -> Public Property Get getChangeOrganizationAssignments_ContractType() : getChangeOrganizationAssignments_ContractType = strChangeOrganizationAssignments_ContractType : End Property
A48: =Test_Data!#REF! -> #REF! | B48: ="intRow" & A48 & ", " -> #REF! | C48: =C47 &B48 -> #REF! | D48: ="str" & A48 & ", " -> #REF! | E48: =E47 &D48 -> #REF! | F48: ="intRow" & A48 & " = comExcelWorksheet.Range(""" & A48 & """).Row" -> #REF! | G48: ="str" & A48 & " = comExcelWorksheet.Cells(intRow" & A48 & ", intColTestColumn).Value" -> #REF! | H48: ="Public Property Get get" & A48 & "() : get" & A48 & " = str" & A48 & " : End Property" -> #REF!
A49: =Test_Data!#REF! -> #REF! | B49: ="intRow" & A49 & ", " -> #REF! | C49: =SUBSTITUTE(#REF!," ","") & "_" & SUBSTITUTE(IF(A49="N/A","",A49& "_")," ","") & SUBSTITUTE(SUBSTITUTE(B49," ",""),"/","") -> #REF! | D49: ="str" & A49 & ", " -> #REF! | E49: =E47 &D49 -> #REF! | F49: ="intRow" & A49 & " = comExcelWorksheet.Range(""" & A49 & """).Row" -> #REF! | G49: ="str" & A49 & " = comExcelWorksheet.Cells(intRow" & A49 & ", intColTestColumn).Value" -> #REF! | H49: ="Public Property Get get" & A49 & "() : get" & A49 & " = str" & A49 & " : End Property" -> #REF! | I49: =SUBSTITUTE(#REF!," ","") & "_" & SUBSTITUTE(IF(G49="N/A","",G49& "_")," ","") & SUBSTITUTE(SUBSTITUTE(H49," ",""),"/","") -> #REF! | J49: =SUBSTITUTE(#REF!," ","") & "_" & SUBSTITUTE(IF(H49="N/A","",H49& "_")," ","") & SUBSTITUTE(SUBSTITUTE(I49," ",""),"/","") -> #REF! | K49: =SUBSTITUTE(#REF!," ","") & "_" & SUBSTITUTE(IF(I49="N/A","",I49& "_")," ","") & SUBSTITUTE(SUBSTITUTE(J49," ",""),"/","") -> #REF! | L49: =SUBSTITUTE(#REF!," ","") & "_" & SUBSTITUTE(IF(J49="N/A","",J49& "_")," ","") & SUBSTITUTE(SUBSTITUTE(K49," ",""),"/","") -> #REF! | M49: =SUBSTITUTE(#REF!," ","") & "_" & SUBSTITUTE(IF(K49="N/A","",K49& "_")," ","") & SUBSTITUTE(SUBSTITUTE(L49," ",""),"/","") -> #REF! | N49: =SUBSTITUTE(#REF!," ","") & "_" & SUBSTITUTE(IF(L49="N/A","",L49& "_")," ","") & SUBSTITUTE(SUBSTITUTE(M49," ",""),"/","") -> #REF! | O49: =SUBSTITUTE(#REF!," ","") & "_" & SUBSTITUTE(IF(M49="N/A","",M49& "_")," ","") & SUBSTITUTE(SUBSTITUTE(N49," ",""),"/","") -> #REF! | P49: =SUBSTITUTE(#REF!," ","") & "_" & SUBSTITUTE(IF(N49="N/A","",N49& "_")," ","") & SUBSTITUTE(SUBSTITUTE(O49," ",""),"/","") -> #REF! | ... BN49: =SUBSTITUTE(#REF!," ","") & "_" & SUBSTITUTE(IF(BL49="N/A","",BL49& "_")," ","") & SUBSTITUTE(SUBSTITUTE(BM49," ",""),"/","") -> #REF! | BO49: =SUBSTITUTE(BL49," ","") & "_" & SUBSTITUTE(IF(BM49="N/A","",BM49& "_")," ","") & SUBSTITUTE(SUBSTITUTE(BN49," ",""),"/","") -> #REF! | BP49: =SUBSTITUTE(BM49," ","") & "_" & SUBSTITUTE(IF(BN49="N/A","",BN49& "_")," ","") & SUBSTITUTE(SUBSTITUTE(BO49," ",""),"/","") -> #REF! | BQ49: =SUBSTITUTE(BN49," ","") & "_" & SUBSTITUTE(IF(BO49="N/A","",BO49& "_")," ","") & SUBSTITUTE(SUBSTITUTE(BP49," ",""),"/","") -> #REF! | BR49: =SUBSTITUTE(BO49," ","") & "_" & SUBSTITUTE(IF(BP49="N/A","",BP49& "_")," ","") & SUBSTITUTE(SUBSTITUTE(BQ49," ",""),"/","") -> #REF! | BS49: =SUBSTITUTE(BP49," ","") & "_" & SUBSTITUTE(IF(BQ49="N/A","",BQ49& "_")," ","") & SUBSTITUTE(SUBSTITUTE(BR49," ",""),"/","") -> #REF! | BT49: =SUBSTITUTE(BQ49," ","") & "_" & SUBSTITUTE(IF(BR49="N/A","",BR49& "_")," ","") & SUBSTITUTE(SUBSTITUTE(BS49," ",""),"/","") -> #REF! | BU49: =SUBSTITUTE(BR49," ","") & "_" & SUBSTITUTE(IF(BS49="N/A","",BS49& "_")," ","") & SUBSTITUTE(SUBSTITUTE(BT49," ",""),"/","") -> #REF! | BV49: =SUBSTITUTE(BS49," ","") & "_" & SUBSTITUTE(IF(BT49="N/A","",BT49& "_")," ","") & SUBSTITUTE(SUBSTITUTE(BU49," ",""),"/","") -> #REF! | ... XFD49: =SUBSTITUTE(XFA49," ","") & "_" & SUBSTITUTE(IF(XFB49="N/A","",XFB49& "_")," ","") & SUBSTITUTE(SUBSTITUTE(XFC49," ",""),"/","") -> #REF!
A50: =Test_Data!D70 -> AssignPayGroup_Country2 | B50: ="intRow" & A50 & ", " -> intRowAssignPayGroup_Country2, | C50: =C47 &B50 -> #REF! | D50: ="str" & A50 & ", " -> strAssignPayGroup_Country2, | E50: =E47 &D50 -> #REF! | F50: ="intRow" & A50 & " = comExcelWorksheet.Range(""" & A50 & """).Row" -> intRowAssignPayGroup_Country2 = comExcelWorksheet.Range("AssignPayGroup_Country2").Row | G50: ="str" & A50 & " = comExcelWorksheet.Cells(intRow" & A50 & ", intColTestColumn).Value" -> strAssignPayGroup_Country2 = comExcelWorksheet.Cells(intRowAssignPayGroup_Country2, intColTestColumn).Value | H50: ="Public Property Get get" & A50 & "() : get" & A50 & " = str" & A50 & " : End Property" -> Public Property Get getAssignPayGroup_Country2() : getAssignPayGroup_Country2 = strAssignPayGroup_Country2 : End Property
A51: =Test_Data!#REF! -> #REF! | B51: ="intRow" & A51 & ", " -> #REF! | C51: =C50 &B51 -> #REF! | D51: ="str" & A51 & ", " -> #REF! | E51: =E50 &D51 -> #REF! | F51: ="intRow" & A51 & " = comExcelWorksheet.Range(""" & A51 & """).Row" -> #REF! | G51: ="str" & A51 & " = comExcelWorksheet.Cells(intRow" & A51 & ", intColTestColumn).Value" -> #REF! | H51: ="Public Property Get get" & A51 & "() : get" & A51 & " = str" & A51 & " : End Property" -> #REF!
A52: =Test_Data!#REF! -> #REF! | B52: ="intRow" & A52 & ", " -> #REF! | C52: =C51 &B52 -> #REF! | D52: ="str" & A52 & ", " -> #REF! | E52: =E51 &D52 -> #REF! | F52: ="intRow" & A52 & " = comExcelWorksheet.Range(""" & A52 & """).Row" -> #REF! | G52: ="str" & A52 & " = comExcelWorksheet.Cells(intRow" & A52 & ", intColTestColumn).Value" -> #REF! | H52: ="Public Property Get get" & A52 & "() : get" & A52 & " = str" & A52 & " : End Property" -> #REF!
A53: =Test_Data!#REF! -> #REF! | B53: ="intRow" & A53 & ", " -> #REF! | C53: =C52 &B53 -> #REF! | D53: ="str" & A53 & ", " -> #REF! | E53: =E52 &D53 -> #REF! | F53: ="intRow" & A53 & " = comExcelWorksheet.Range(""" & A53 & """).Row" -> #REF! | G53: ="str" & A53 & " = comExcelWorksheet.Cells(intRow" & A53 & ", intColTestColumn).Value" -> #REF! | H53: ="Public Property Get get" & A53 & "() : get" & A53 & " = str" & A53 & " : End Property" -> #REF!
A54: =Test_Data!#REF! -> #REF! | B54: ="intRow" & A54 & ", " -> #REF! | C54: =C53 &B54 -> #REF! | D54: ="str" & A54 & ", " -> #REF! | E54: =E53 &D54 -> #REF! | F54: ="intRow" & A54 & " = comExcelWorksheet.Range(""" & A54 & """).Row" -> #REF! | G54: ="str" & A54 & " = comExcelWorksheet.Cells(intRow" & A54 & ", intColTestColumn).Value" -> #REF! | H54: ="Public Property Get get" & A54 & "() : get" & A54 & " = str" & A54 & " : End Property" -> #REF!
A55: =Test_Data!#REF! -> #REF! | B55: ="intRow" & A55 & ", " -> #REF! | C55: =C54 &B55 -> #REF! | D55: ="str" & A55 & ", " -> #REF! | E55: =E54 &D55 -> #REF! | F55: ="intRow" & A55 & " = comExcelWorksheet.Range(""" & A55 & """).Row" -> #REF! | G55: ="str" & A55 & " = comExcelWorksheet.Cells(intRow" & A55 & ", intColTestColumn).Value" -> #REF! | H55: ="Public Property Get get" & A55 & "() : get" & A55 & " = str" & A55 & " : End Property" -> #REF!
A56: =Test_Data!#REF! -> #REF! | B56: ="intRow" & A56 & ", " -> #REF! | C56: =C55 &B56 -> #REF! | D56: ="str" & A56 & ", " -> #REF! | E56: =E55 &D56 -> #REF! | F56: ="intRow" & A56 & " = comExcelWorksheet.Range(""" & A56 & """).Row" -> #REF! | G56: ="str" & A56 & " = comExcelWorksheet.Cells(intRow" & A56 & ", intColTestColumn).Value" -> #REF! | H56: ="Public Property Get get" & A56 & "() : get" & A56 & " = str" & A56 & " : End Property" -> #REF!
A57: =Test_Data!D68 -> ProposeCompensationHire_NationalIDType1 | B57: ="intRow" & A57 & ", " -> intRowProposeCompensationHire_NationalIDType1, | C57: =C56 &B57 -> #REF! | D57: ="str" & A57 & ", " -> strProposeCompensationHire_NationalIDType1, | E57: =E56 &D57 -> #REF! | F57: ="intRow" & A57 & " = comExcelWorksheet.Range(""" & A57 & """).Row" -> intRowProposeCompensationHire_NationalIDType1 = comExcelWorksheet.Range("ProposeCompensationHire_NationalIDType1").Row | G57: ="str" & A57 & " = comExcelWorksheet.Cells(intRow" & A57 & ", intColTestColumn).Value" -> strProposeCompensationHire_NationalIDType1 = comExcelWorksheet.Cells(intRowProposeCompensationHire_NationalIDType1, intColTestColumn).Value | H57: ="Public Property Get get" & A57 & "() : get" & A57 & " = str" & A57 & " : End Property" -> Public Property Get getProposeCompensationHire_NationalIDType1() : getProposeCompensationHire_NationalIDType1 = strProposeCompensationHire_NationalIDType1 : End Property
A58: =Test_Data!D58 -> ChangeMyPersonalInformation_ContractEndDate | B58: ="intRow" & A58 & ", " -> intRowChangeMyPersonalInformation_ContractEndDate, | C58: =C57 &B58 -> #REF! | D58: ="str" & A58 & ", " -> strChangeMyPersonalInformation_ContractEndDate, | E58: =E57 &D58 -> #REF! | F58: ="intRow" & A58 & " = comExcelWorksheet.Range(""" & A58 & """).Row" -> intRowChangeMyPersonalInformation_ContractEndDate = comExcelWorksheet.Range("ChangeMyPersonalInformation_ContractEndDate").Row | G58: ="str" & A58 & " = comExcelWorksheet.Cells(intRow" & A58 & ", intColTestColumn).Value" -> strChangeMyPersonalInformation_ContractEndDate = comExcelWorksheet.Cells(intRowChangeMyPersonalInformation_ContractEndDate, intColTestColumn).Value | H58: ="Public Property Get get" & A58 & "() : get" & A58 & " = str" & A58 & " : End Property" -> Public Property Get getChangeMyPersonalInformation_ContractEndDate() : getChangeMyPersonalInformation_ContractEndDate = strChangeMyPersonalInformation_ContractEndDate : End Property
A59: =Test_Data!D59 -> ChangeMyPersonalInformation_CostCenter | B59: ="intRow" & A59 & ", " -> intRowChangeMyPersonalInformation_CostCenter, | C59: =C58 &B59 -> #REF! | D59: ="str" & A59 & ", " -> strChangeMyPersonalInformation_CostCenter, | E59: =E58 &D59 -> #REF! | F59: ="intRow" & A59 & " = comExcelWorksheet.Range(""" & A59 & """).Row" -> intRowChangeMyPersonalInformation_CostCenter = comExcelWorksheet.Range("ChangeMyPersonalInformation_CostCenter").Row | G59: ="str" & A59 & " = comExcelWorksheet.Cells(intRow" & A59 & ", intColTestColumn).Value" -> strChangeMyPersonalInformation_CostCenter = comExcelWorksheet.Cells(intRowChangeMyPersonalInformation_CostCenter, intColTestColumn).Value | H59: ="Public Property Get get" & A59 & "() : get" & A59 & " = str" & A59 & " : End Property" -> Public Property Get getChangeMyPersonalInformation_CostCenter() : getChangeMyPersonalInformation_CostCenter = strChangeMyPersonalInformation_CostCenter : End Property
A60: =Test_Data!#REF! -> #REF! | B60: ="intRow" & A60 & ", " -> #REF! | C60: =C59 &B60 -> #REF! | D60: ="str" & A60 & ", " -> #REF! | E60: =E59 &D60 -> #REF! | F60: ="intRow" & A60 & " = comExcelWorksheet.Range(""" & A60 & """).Row" -> #REF! | G60: ="str" & A60 & " = comExcelWorksheet.Cells(intRow" & A60 & ", intColTestColumn).Value" -> #REF! | H60: ="Public Property Get get" & A60 & "() : get" & A60 & " = str" & A60 & " : End Property" -> #REF!
A61: =Test_Data!#REF! -> #REF! | B61: ="intRow" & A61 & ", " -> #REF! | C61: =C60 &B61 -> #REF! | D61: ="str" & A61 & ", " -> #REF! | E61: =E60 &D61 -> #REF! | F61: ="intRow" & A61 & " = comExcelWorksheet.Range(""" & A61 & """).Row" -> #REF! | G61: ="str" & A61 & " = comExcelWorksheet.Cells(intRow" & A61 & ", intColTestColumn).Value" -> #REF! | H61: ="Public Property Get get" & A61 & "() : get" & A61 & " = str" & A61 & " : End Property" -> #REF!
A62: =Test_Data!#REF! -> #REF! | B62: ="intRow" & A62 & ", " -> #REF! | C62: =C61 &B62 -> #REF! | D62: ="str" & A62 & ", " -> #REF! | E62: =E61 &D62 -> #REF! | F62: ="intRow" & A62 & " = comExcelWorksheet.Range(""" & A62 & """).Row" -> #REF! | G62: ="str" & A62 & " = comExcelWorksheet.Cells(intRow" & A62 & ", intColTestColumn).Value" -> #REF! | H62: ="Public Property Get get" & A62 & "() : get" & A62 & " = str" & A62 & " : End Property" -> #REF!
A63: =Test_Data!#REF! -> #REF! | B63: ="intRow" & A63 & ", " -> #REF! | C63: =C62 &B63 -> #REF! | D63: ="str" & A63 & ", " -> #REF! | E63: =E62 &D63 -> #REF! | F63: ="intRow" & A63 & " = comExcelWorksheet.Range(""" & A63 & """).Row" -> #REF! | G63: ="str" & A63 & " = comExcelWorksheet.Cells(intRow" & A63 & ", intColTestColumn).Value" -> #REF! | H63: ="Public Property Get get" & A63 & "() : get" & A63 & " = str" & A63 & " : End Property" -> #REF!
A64: =Test_Data!D55 -> ChangeMyGovernmentIDs_NationalIDs_Status | B64: ="intRow" & A64 & ", " -> intRowChangeMyGovernmentIDs_NationalIDs_Status, | C64: =C63 &B64 -> #REF! | D64: ="str" & A64 & ", " -> strChangeMyGovernmentIDs_NationalIDs_Status, | E64: =E63 &D64 -> #REF! | F64: ="intRow" & A64 & " = comExcelWorksheet.Range(""" & A64 & """).Row" -> intRowChangeMyGovernmentIDs_NationalIDs_Status = comExcelWorksheet.Range("ChangeMyGovernmentIDs_NationalIDs_Status").Row | G64: ="str" & A64 & " = comExcelWorksheet.Cells(intRow" & A64 & ", intColTestColumn).Value" -> strChangeMyGovernmentIDs_NationalIDs_Status = comExcelWorksheet.Cells(intRowChangeMyGovernmentIDs_NationalIDs_Status, intColTestColumn).Value | H64: ="Public Property Get get" & A64 & "() : get" & A64 & " = str" & A64 & " : End Property" -> Public Property Get getChangeMyGovernmentIDs_NationalIDs_Status() : getChangeMyGovernmentIDs_NationalIDs_Status = strChangeMyGovernmentIDs_NationalIDs_Status : End Property
A65: =Test_Data!D56 -> ChangeMyGovernmentIDs_NationalIDs_DateEmployeeSigned | B65: ="intRow" & A65 & ", " -> intRowChangeMyGovernmentIDs_NationalIDs_DateEmployeeSigned, | C65: =C64 &B65 -> #REF! | D65: ="str" & A65 & ", " -> strChangeMyGovernmentIDs_NationalIDs_DateEmployeeSigned, | E65: =E64 &D65 -> #REF! | F65: ="intRow" & A65 & " = comExcelWorksheet.Range(""" & A65 & """).Row" -> intRowChangeMyGovernmentIDs_NationalIDs_DateEmployeeSigned = comExcelWorksheet.Range("ChangeMyGovernmentIDs_NationalIDs_DateEmployeeSigned").Row | G65: ="str" & A65 & " = comExcelWorksheet.Cells(intRow" & A65 & ", intColTestColumn).Value" -> strChangeMyGovernmentIDs_NationalIDs_DateEmployeeSigned = comExcelWorksheet.Cells(intRowChangeMyGovernmentIDs_NationalIDs_DateEmployeeSigned, intColTestColumn).Value | H65: ="Public Property Get get" & A65 & "() : get" & A65 & " = str" & A65 & " : End Property" -> Public Property Get getChangeMyGovernmentIDs_NationalIDs_DateEmployeeSigned() : getChangeMyGovernmentIDs_NationalIDs_DateEmployeeSigned = strChangeMyGovernmentIDs_NationalIDs_DateEmployeeSigned : End Property
A66: =Test_Data!D57 -> ChangeMyGovernmentIDs_NationalIDs_DateEmployerSigned | B66: ="intRow" & A66 & ", " -> intRowChangeMyGovernmentIDs_NationalIDs_DateEmployerSigned, | C66: =C65 &B66 -> #REF! | D66: ="str" & A66 & ", " -> strChangeMyGovernmentIDs_NationalIDs_DateEmployerSigned, | E66: =E65 &D66 -> #REF! | F66: ="intRow" & A66 & " = comExcelWorksheet.Range(""" & A66 & """).Row" -> intRowChangeMyGovernmentIDs_NationalIDs_DateEmployerSigned = comExcelWorksheet.Range("ChangeMyGovernmentIDs_NationalIDs_DateEmployerSigned").Row | G66: ="str" & A66 & " = comExcelWorksheet.Cells(intRow" & A66 & ", intColTestColumn).Value" -> strChangeMyGovernmentIDs_NationalIDs_DateEmployerSigned = comExcelWorksheet.Cells(intRowChangeMyGovernmentIDs_NationalIDs_DateEmployerSigned, intColTestColumn).Value | H66: ="Public Property Get get" & A66 & "() : get" & A66 & " = str" & A66 & " : End Property" -> Public Property Get getChangeMyGovernmentIDs_NationalIDs_DateEmployerSigned() : getChangeMyGovernmentIDs_NationalIDs_DateEmployerSigned = strChangeMyGovernmentIDs_NationalIDs_DateEmployerSigned : End Property
A67: =Test_Data!#REF! -> #REF! | B67: ="intRow" & A67 & ", " -> #REF! | C67: =C66 &B67 -> #REF! | D67: ="str" & A67 & ", " -> #REF! | E67: =E66 &D67 -> #REF! | F67: ="intRow" & A67 & " = comExcelWorksheet.Range(""" & A67 & """).Row" -> #REF! | G67: ="str" & A67 & " = comExcelWorksheet.Cells(intRow" & A67 & ", intColTestColumn).Value" -> #REF! | H67: ="Public Property Get get" & A67 & "() : get" & A67 & " = str" & A67 & " : End Property" -> #REF!
A68: =Test_Data!#REF! -> #REF! | B68: ="intRow" & A68 & ", " -> #REF! | C68: =C67 &B68 -> #REF! | D68: ="str" & A68 & ", " -> #REF! | E68: =E67 &D68 -> #REF! | F68: ="intRow" & A68 & " = comExcelWorksheet.Range(""" & A68 & """).Row" -> #REF! | G68: ="str" & A68 & " = comExcelWorksheet.Cells(intRow" & A68 & ", intColTestColumn).Value" -> #REF! | H68: ="Public Property Get get" & A68 & "() : get" & A68 & " = str" & A68 & " : End Property" -> #REF!
A69: =Test_Data!#REF! -> #REF! | B69: ="intRow" & A69 & ", " -> #REF! | C69: =C68 &B69 -> #REF! | D69: ="str" & A69 & ", " -> #REF! | E69: =E68 &D69 -> #REF! | F69: ="intRow" & A69 & " = comExcelWorksheet.Range(""" & A69 & """).Row" -> #REF! | G69: ="str" & A69 & " = comExcelWorksheet.Cells(intRow" & A69 & ", intColTestColumn).Value" -> #REF! | H69: ="Public Property Get get" & A69 & "() : get" & A69 & " = str" & A69 & " : End Property" -> #REF!
A70: =Test_Data!#REF! -> #REF! | B70: ="intRow" & A70 & ", " -> #REF! | C70: =C69 &B70 -> #REF! | D70: ="str" & A70 & ", " -> #REF! | E70: =E69 &D70 -> #REF! | F70: ="intRow" & A70 & " = comExcelWorksheet.Range(""" & A70 & """).Row" -> #REF! | G70: ="str" & A70 & " = comExcelWorksheet.Cells(intRow" & A70 & ", intColTestColumn).Value" -> #REF! | H70: ="Public Property Get get" & A70 & "() : get" & A70 & " = str" & A70 & " : End Property" -> #REF!
A71: =Test_Data!#REF! -> #REF! | B71: ="intRow" & A71 & ", " -> #REF! | C71: =C70 &B71 -> #REF! | D71: ="str" & A71 & ", " -> #REF! | E71: =E70 &D71 -> #REF! | F71: ="intRow" & A71 & " = comExcelWorksheet.Range(""" & A71 & """).Row" -> #REF! | G71: ="str" & A71 & " = comExcelWorksheet.Cells(intRow" & A71 & ", intColTestColumn).Value" -> #REF! | H71: ="Public Property Get get" & A71 & "() : get" & A71 & " = str" & A71 & " : End Property" -> #REF!
A72: =Test_Data!#REF! -> #REF! | B72: ="intRow" & A72 & ", " -> #REF! | C72: =C71 &B72 -> #REF! | D72: ="str" & A72 & ", " -> #REF! | E72: =E71 &D72 -> #REF! | F72: ="intRow" & A72 & " = comExcelWorksheet.Range(""" & A72 & """).Row" -> #REF! | G72: ="str" & A72 & " = comExcelWorksheet.Cells(intRow" & A72 & ", intColTestColumn).Value" -> #REF! | H72: ="Public Property Get get" & A72 & "() : get" & A72 & " = str" & A72 & " : End Property" -> #REF!
A73: =Test_Data!#REF! -> #REF! | B73: ="intRow" & A73 & ", " -> #REF! | C73: =C72 &B73 -> #REF! | D73: ="str" & A73 & ", " -> #REF! | E73: =E72 &D73 -> #REF! | F73: ="intRow" & A73 & " = comExcelWorksheet.Range(""" & A73 & """).Row" -> #REF! | G73: ="str" & A73 & " = comExcelWorksheet.Cells(intRow" & A73 & ", intColTestColumn).Value" -> #REF! | H73: ="Public Property Get get" & A73 & "() : get" & A73 & " = str" & A73 & " : End Property" -> #REF!
A74: =Test_Data!#REF! -> #REF! | B74: ="intRow" & A74 & ", " -> #REF! | C74: =C73 &B74 -> #REF! | D74: ="str" & A74 & ", " -> #REF! | E74: =E73 &D74 -> #REF! | F74: ="intRow" & A74 & " = comExcelWorksheet.Range(""" & A74 & """).Row" -> #REF! | G74: ="str" & A74 & " = comExcelWorksheet.Cells(intRow" & A74 & ", intColTestColumn).Value" -> #REF! | H74: ="Public Property Get get" & A74 & "() : get" & A74 & " = str" & A74 & " : End Property" -> #REF!
A75: =Test_Data!#REF! -> #REF! | B75: ="intRow" & A75 & ", " -> #REF! | C75: =C74 &B75 -> #REF! | D75: ="str" & A75 & ", " -> #REF! | E75: =E74 &D75 -> #REF! | F75: ="intRow" & A75 & " = comExcelWorksheet.Range(""" & A75 & """).Row" -> #REF! | G75: ="str" & A75 & " = comExcelWorksheet.Cells(intRow" & A75 & ", intColTestColumn).Value" -> #REF! | H75: ="Public Property Get get" & A75 & "() : get" & A75 & " = str" & A75 & " : End Property" -> #REF!
A76: =Test_Data!#REF! -> #REF! | B76: ="intRow" & A76 & ", " -> #REF! | C76: =C75 &B76 -> #REF! | D76: ="str" & A76 & ", " -> #REF! | E76: =E75 &D76 -> #REF! | F76: ="intRow" & A76 & " = comExcelWorksheet.Range(""" & A76 & """).Row" -> #REF! | G76: ="str" & A76 & " = comExcelWorksheet.Cells(intRow" & A76 & ", intColTestColumn).Value" -> #REF! | H76: ="Public Property Get get" & A76 & "() : get" & A76 & " = str" & A76 & " : End Property" -> #REF!

Sheet Names
B3: Etoecyeone | C3: 1 | D3: one | F3: 1 | G3: one | J3: =G3&H3 -> one | K3: one
B4: Etoecyeone | C4: 2 | D4: two | F4: 2 | G4: two | J4: =G4&H4 -> two | K4: two
B5: Etoecyeone | C5: 3 | D5: three | F5: 3 | G5: three | J5: =G5&H5 -> three | K5: three
B6: Etoecyeone | C6: 4 | D6: four | F6: 4 | G6: four | J6: =G6&H6 -> four | K6: four
B7: Etoecyeone | C7: 5 | D7: five | F7: 5 | G7: five | J7: =G7&H7 -> five | K7: five
B8: Etoecyeone | C8: 6 | D8: six | F8: 6 | G8: six | J8: =G8&H8 -> six | K8: six
B9: Etoecyeone | C9: 7 | D9: seven | F9: 7 | G9: seven | J9: =G9&H9 -> seven | K9: seven
B10: Etoecyeone | C10: 8 | D10: eight | F10: 8 | G10: eight | J10: =G10&H10 -> eight | K10: eight
B11: Etoecyeone | C11: 9 | D11: nine | F11: 9 | G11: nine | J11: =G11&H11 -> nine | K11: nine
B12: Etoecyeone | C12: 10 | D12: ten | F12: 10 | G12: ten | J12: =G12&H12 -> ten | K12: ten
B13: Etoecyeone | C13: 11 | D13: eleven | F13: 11 | G13: eleven | J13: =G13&H13 -> eleven | K13: eleven
B14: Etoecyeone | C14: 12 | D14: twelve | F14: 12 | G14: twelve | J14: =G14&H14 -> twelve | K14: twelve
B15: Etoecyeone | C15: 13 | D15: thirteen | F15: 13 | G15: thirteen | J15: =G15&H15 -> thirteen | K15: thirteen
... B22: Etoecyeone | C22: 20 | D22: twenty | F22: 20 | G22: twenty | J22: =G22&H22 -> twenty | K22: twenty
B23: Etoecyeone | C23: 30 | D23: thirty | F23: 21 | G23: twenty | H23: one | J23: =G23&H23 -> twentyone | K23: twentyone
B24: Etoecyeone | C24: 40 | D24: forty | F24: 22 | G24: twenty | H24: two | J24: =G24&H24 -> twentytwo | K24: twentytwo
B25: Etoecyeone | C25: 50 | D25: fifty | F25: 23 | G25: twenty | H25: three | J25: =G25&H25 -> twentythree | K25: twentythree
B26: Etoecyeone | C26: 60 | D26: sixty | F26: 24 | G26: twenty | H26: four | J26: =G26&H26 -> twentyfour | K26: twentyfour
B27: Etoecyeone | C27: 70 | D27: seventy | F27: 25 | G27: twenty | H27: five | J27: =G27&H27 -> twentyfive | K27: twentyfive
B28: Etoecyeone | C28: 80 | D28: eighty | F28: 26 | G28: twenty | H28: six | J28: =G28&H28 -> twentysix | K28: twentysix
B29: Etoecyeone | C29: 90 | D29: ninety | F29: 27 | G29: twenty | H29: seven | J29: =G29&H29 -> twentyseven | K29: twentyseven
B30: Etoecyeone | C30: 100 | D30: one hundred | F30: 28 | G30: twenty | H30: eight | J30: =G30&H30 -> twentyeight | K30: twentyeight
B31: Etoecyeone | C31: 1000 | D31: one thousand | F31: 29 | G31: twenty | H31: nine | J31: =G31&H31 -> twentynine | K31: twentynine
B32: Etoecyeone | F32: 30 | G32: thirty | J32: =G32&H32 -> thirty | K32: thirty
B33: Etoecyeone | F33: 31 | G33: thirty | H33: one | J33: =G33&H33 -> thirtyone | K33: thirtyone
B34: Etoecyeone | F34: 32 | G34: thirty | H34: two | J34: =G34&H34 -> thirtytwo | K34: thirtytwo
B35: Etoecyeone | F35: 33 | G35: thirty | H35: three | J35: =G35&H35 -> thirtythree | K35: thirtythree
B36: Etoecyeone | F36: 34 | G36: thirty | H36: four | J36: =G36&H36 -> thirtyfour | K36: thirtyfour
B37: Etoecyeone | F37: 35 | G37: thirty | H37: five | J37: =G37&H37 -> thirtyfive | K37: thirtyfive
B38: Etoecyeone | F38: 36 | G38: thirty | H38: six | J38: =G38&H38 -> thirtysix | K38: thirtysix
B39: Etoecyeone | F39: 37 | G39: thirty | H39: seven | J39: =G39&H39 -> thirtyseven | K39: thirtyseven
B40: Etoecyeone | F40: 38 | G40: thirty | H40: eight | J40: =G40&H40 -> thirtyeight | K40: thirtyeight
B41: Etoecyeone | F41: 39 | G41: thirty | H41: nine | J41: =G41&H41 -> thirtynine | K41: thirtynine
B42: Etoecyeone | F42: 40 | G42: forty | J42: =G42&H42 -> forty | K42: forty
B43: Etoecyeone | F43: 41 | G43: forty | H43: one | J43: =G43&H43 -> fortyone | K43: fortyone
B44: Etoecyeone | F44: 42 | G44: forty | H44: two | J44: =G44&H44 -> fortytwo | K44: fortytwo
B45: Etoecyeone | F45: 43 | G45: forty | H45: three | J45: =G45&H45 -> fortythree | K45: fortythree
B46: Etoecyeone | F46: 44 | G46: forty | H46: four | J46: =G46&H46 -> fortyfour | K46: fortyfour
B47: Etoecyeone | F47: 45 | G47: forty | H47: five | J47: =G47&H47 -> fortyfive | K47: fortyfive
B48: Etoecyeone | F48: 46 | G48: forty | H48: six | J48: =G48&H48 -> fortysix | K48: fortysix
B49: Etoecyeone | F49: 47 | G49: forty | H49: seven | J49: =G49&H49 -> fortyseven | K49: fortyseven
B50: Etoecyeone | F50: 48 | G50: forty | H50: eight | J50: =G50&H50 -> fortyeight | K50: fortyeight
B51: Etoecyeone | F51: 49 | G51: forty | H51: nine | J51: =G51&H51 -> fortynine | K51: fortynine
B52: Etoecyeone | F52: 50 | G52: fifty | J52: =G52&H52 -> fifty | K52: fifty
B53: Etoecyeone | F53: 51 | G53: fifty | H53: one | J53: =G53&H53 -> fiftyone | K53: fiftyone
B54: Etoecyeone | F54: 52 | G54: fifty | H54: two | J54: =G54&H54 -> fiftytwo | K54: fiftytwo
B55: ETOE | F55: 53 | G55: fifty | H55: three | J55: =G55&H55 -> fiftythree | K55: fiftythree | U55: ETOEfiftynine | V55: ETOEsixty | W55: ETOEsixtyone | X55: ETOEsixtytwo | Y55: ETOEsixtythree | Z55: ETOEsixtyfour | AA55: ETOEsixtyfive | AB55: ETOEsixtysix | AC55: ETOEsixtyseven | AD55: ETOEsixtyeight | AE55: ETOEsixtynine | AF55: ETOEseventy | AG55: ETOEseventyone | AH55: ETOEseventytwo | AI55: ETOEseventythree | AJ55: ETOEseventyfour | AK55: ETOEseventyfive | AL55: ETOEseventysix | AM55: ETOEseventyseven | AN55: ETOEseventyeight | AO55: ETOEseventynine | AP55: ETOEeighty | AQ55: ETOEeightyone | AR55: ETOEeightytwo | AS55: ETOEeightythree | AT55: ETOEeightyfour | AU55: ETOEeightyfive | AV55: ETOEeightysix | AW55: ETOEeightyseven | AX55: ETOEeightyeight | AY55: ETOEeightynine | AZ55: ETOEninety | BA55: ETOEninetyone | BB55: ETOEninetytwo | BC55: ETOEninetythree | BD55: ETOEninetyfour | BE55: ETOEninetyfive | BF55: ETOEninetysix | BG55: ETOEninetyseven | BH55: ETOEninetyeight | BI55: ETOEninetynine | BJ55: ETOEonezerozero | BK55: ETOEonezerooneone | BL55: ETOEonezerotwotwo | BM55: ETOEonezerothreethree | BN55: ETOEonezerofourfour | BO55: ETOEonezerofivefive | BP55: ETOEonezerosixsix | BQ55: ETOEonezerosevenseven | BR55: ETOEonezeroeighteight | BS55: ETOEonezeroninenine | BT55: ETOEoneonezero | BU55: ETOEoneoneone | BV55: ETOEoneonetwo | BW55: ETOEoneonethree | BX55: ETOEoneonefour | BY55: ETOEoneonefive | BZ55: ETOEoneonesix | CA55: ETOEoneoneseven | CB55: ETOEoneoneeight | CC55: ETOEoneonenine | CD55: ETOEonetwozero | CE55: ETOEonetwoone | CF55: ETOEonetwotwo | CG55: ETOEonetwothree | CH55: ETOEonetwofour | CI55: ETOEonetwofive | CJ55: ETOEonetwosix | CK55: ETOEonetwoseven | CL55: ETOEonetwoeight | CM55: ETOEonetwonine | CN55: ETOEonethreezero | CO55: ETOEonethreeone | CP55: ETOEonethreetwo | CQ55: ETOEonethreethree | CR55: ETOEonethreefour | CS55: ETOEonethreefive | CT55: ETOEonethreesix | CU55: ETOEonethreeseven | CV55: ETOEonethreeeight | CW55: ETOEonethreenine | CX55: ETOEonefourzero | CY55: ETOEonefourone | CZ55: ETOEonefourtwo | DA55: ETOEonefourthree | DB55: ETOEonefourfour | DC55: ETOEonefourfive | DD55: ETOEonefoursix | DE55: ETOEonefourseven | DF55: ETOEonefoureight | DG55: ETOEonefournine | DH55: ETOEonefivezero
B56: ETOE | F56: 54 | G56: fifty | H56: four | J56: =G56&H56 -> fiftyfour | K56: fiftyfour
B57: ETOE | F57: 55 | G57: fifty | H57: five | J57: =G57&H57 -> fiftyfive | K57: fiftyfive
B58: ETOE | F58: 56 | G58: fifty | H58: six | J58: =G58&H58 -> fiftysix | K58: fiftysix
B59: ETOE | F59: 57 | G59: fifty | H59: seven | J59: =G59&H59 -> fiftyseven | K59: fiftyseven
B60: ETOE | F60: 58 | G60: fifty | H60: eight | J60: =G60&H60 -> fiftyeight | K60: fiftyeight
B61: ETOE | F61: 59 | G61: fifty | H61: nine | J61: =G61&H61 -> fiftynine | K61: fiftynine
B62: ETOE | F62: 60 | G62: sixty | J62: =G62&H62 -> sixty | K62: sixty
B63: ETOE | F63: 61 | G63: sixty | H63: one | J63: =G63&H63 -> sixtyone | K63: sixtyone
B64: ETOE | F64: 62 | G64: sixty | H64: two | J64: =G64&H64 -> sixtytwo | K64: sixtytwo
B65: ETOE | F65: 63 | G65: sixty | H65: three | J65: =G65&H65 -> sixtythree | K65: sixtythree
B66: ETOE | F66: 64 | G66: sixty | H66: four | J66: =G66&H66 -> sixtyfour | K66: sixtyfour
B67: ETOE | F67: 65 | G67: sixty | H67: five | J67: =G67&H67 -> sixtyfive | K67: sixtyfive
B68: ETOE | F68: 66 | G68: sixty | H68: six | J68: =G68&H68 -> sixtysix | K68: sixtysix
B69: ETOE | F69: 67 | G69: sixty | H69: seven | J69: =G69&H69 -> sixtyseven | K69: sixtyseven
B70: ETOE | F70: 68 | G70: sixty | H70: eight | J70: =G70&H70 -> sixtyeight | K70: sixtyeight
B71: ETOE | F71: 69 | G71: sixty | H71: nine | J71: =G71&H71 -> sixtynine | K71: sixtynine
B72: ETOE | F72: 70 | G72: seventy | J72: =G72&H72 -> seventy | K72: seventy
B73: ETOE | F73: 71 | G73: seventy | H73: one | J73: =G73&H73 -> seventyone | K73: seventyone
B74: ETOE | F74: 72 | G74: seventy | H74: two | J74: =G74&H74 -> seventytwo | K74: seventytwo
B75: ETOE | F75: 73 | G75: seventy | H75: three | J75: =G75&H75 -> seventythree | K75: seventythree
B76: ETOE | F76: 74 | G76: seventy | H76: four | J76: =G76&H76 -> seventyfour | K76: seventyfour
B77: ETOE | F77: 75 | G77: seventy | H77: five | J77: =G77&H77 -> seventyfive | K77: seventyfive
B78: ETOE | F78: 76 | G78: seventy | H78: six | J78: =G78&H78 -> seventysix | K78: seventysix
B79: ETOE | F79: 77 | G79: seventy | H79: seven | J79: =G79&H79 -> seventyseven | K79: seventyseven
B80: ETOE | F80: 78 | G80: seventy | H80: eight | J80: =G80&H80 -> seventyeight | K80: seventyeight
B81: ETOE | F81: 79 | G81: seventy | H81: nine | J81: =G81&H81 -> seventynine | K81: seventynine
B82: ETOE | F82: 80 | G82: eighty | J82: =G82&H82 -> eighty | K82: eighty
B83: ETOE | F83: 81 | G83: eighty | H83: one | J83: =G83&H83 -> eightyone | K83: eightyone
B84: ETOE | F84: 82 | G84: eighty | H84: two | J84: =G84&H84 -> eightytwo | K84: eightytwo
B85: ETOE | F85: 83 | G85: eighty | H85: three | J85: =G85&H85 -> eightythree | K85: eightythree
B86: ETOE | F86: 84 | G86: eighty | H86: four | J86: =G86&H86 -> eightyfour | K86: eightyfour
B87: ETOE | F87: 85 | G87: eighty | H87: five | J87: =G87&H87 -> eightyfive | K87: eightyfive
B88: ETOE | F88: 86 | G88: eighty | H88: six | J88: =G88&H88 -> eightysix | K88: eightysix
B89: ETOE | F89: 87 | G89: eighty | H89: seven | J89: =G89&H89 -> eightyseven | K89: eightyseven
B90: ETOE | F90: 88 | G90: eighty | H90: eight | J90: =G90&H90 -> eightyeight | K90: eightyeight
B91: ETOE | F91: 89 | G91: eighty | H91: nine | J91: =G91&H91 -> eightynine | K91: eightynine
B92: ETOE | F92: 90 | G92: ninety | J92: =G92&H92 -> ninety | K92: ninety
B93: ETOE | F93: 91 | G93: ninety | H93: one | J93: =G93&H93 -> ninetyone | K93: ninetyone
B94: ETOE | F94: 92 | G94: ninety | H94: two | J94: =G94&H94 -> ninetytwo | K94: ninetytwo
B95: ETOE | F95: 93 | G95: ninety | H95: three | J95: =G95&H95 -> ninetythree | K95: ninetythree
B96: ETOE | F96: 94 | G96: ninety | H96: four | J96: =G96&H96 -> ninetyfour | K96: ninetyfour
B97: ETOE | F97: 95 | G97: ninety | H97: five | J97: =G97&H97 -> ninetyfive | K97: ninetyfive
B98: ETOE | F98: 96 | G98: ninety | H98: six | J98: =G98&H98 -> ninetysix | K98: ninetysix
B99: ETOE | F99: 97 | G99: ninety | H99: seven | J99: =G99&H99 -> ninetyseven | K99: ninetyseven
B100: ETOE | F100: 98 | G100: ninety | H100: eight | J100: =G100&H100 -> ninetyeight | K100: ninetyeight
B101: ETOE | F101: 99 | G101: ninety | H101: nine | J101: =G101&H101 -> ninetynine | K101: ninetynine
B102: ETOE | F102: 100 | G102: one | H102: zero | I102: zero | J102: =G102&H102&I102 -> onezerozero | K102: onezerozero
B103: ETOE | F103: 101 | G103: one | H103: zero | I103: one | J103: =G103&H103&I103 -> onezeroone | K103: onezeroone | U103: Etoecyeoneonehundredone | V103: Etoecyeoneonehundredtwo | W103: Etoecyeoneonehundredthree | X103: Etoecyeoneonehundredfour | Y103: Etoecyeoneonehundredfive | Z103: Etoecyeoneonehundredsix | AA103: Etoecyeoneonehundredseven | AB103: Etoecyeoneonehundredeight | AC103: Etoecyeoneonehundrednine
B104: ETOE | F104: 102 | G104: one | H104: zero | I104: two | J104: =G104&H104&I104 -> onezerotwo | K104: onezerotwo
B105: ETOE | F105: 103 | G105: one | H105: zero | I105: three | J105: =G105&H105&I105 -> onezerothree | K105: onezerothree
B106: ETOE | F106: 104 | G106: one | H106: zero | I106: four | J106: =G106&H106&I106 -> onezerofour | K106: onezerofour
B107: ETOE | F107: 105 | G107: one | H107: zero | I107: five | J107: =G107&H107&I107 -> onezerofive | K107: onezerofive
B108: ETOE | F108: 106 | G108: one | H108: zero | I108: six | J108: =G108&H108&I108 -> onezerosix | K108: onezerosix
...

Sheet Test_Data
A1: Version_Number | C1: Test_ID | D1: Test_ID | E1: Test_ID2 | F1: Notes | G1: Test_1 | H1: Test_2 | I1: Test_3 | J1: Test_4 | K1: Test_5 | L1: Test_6 | M1: Test_7 | N1: Test_8 | O1: Test_9 | P1: Test_10 | Q1: Test_11 | R1: Test_12 | S1: Test_13 | T1: Test_14 | U1: Test_15 | V1: Test_16 | W1: Test_17 | X1: Test_18 | Y1: Test_19 | Z1: Test_20 | AA1: Test_21 | AB1: Test_22 | AC1: Test_23 | AD1: Test_24 | AE1: Test_25 | AF1: Test_26 | AG1: Test_27 | AH1: Test_28 | AI1: Test_29 | AJ1: Test_30 | AK1: Test_31 | AL1: Test_32 | AM1: Test_33 | AN1: Test_34 | AO1: Test_35 | AP1: Test_36 | AQ1: Test_37 | AR1: Test_38 | AS1: Test_39 | AT1: Test_40 | AU1: Test_41 | AV1: Test_42 | AW1: Test_43 | AX1: Test_44 | AY1: Test_45 | AZ1: Test_46 | BA1: Test_47 | BB1: Test_48 | BC1: Test_49 | BD1: Test_50 | BE1: Test_51 | BF1: Test_52
A2: 0.3 | C2: Reporting_ID | G2: 1 | H2: 2 | I2: 3 | J2: 4 | K2: 5 | L2: 6 | M2: 7 | N2: 8 | O2: 9 | P2: 10 | Q2: 11 | R2: 12 | S2: 13 | T2: 14 | U2: 15 | V2: 16 | W2: 17 | X2: 18 | Y2: 19 | Z2: 20 | AA2: 21 | AB2: 22 | AC2: 23 | AD2: 24 | AE2: 25 | AF2: 26 | AG2: 27 | AH2: 28 | AI2: 29 | AJ2: 30 | AK2: 31 | AL2: 32 | AM2: 33 | AN2: 34 | AO2: 35 | AP2: 36 | AQ2: 37 | AR2: 38 | AS2: 39 | AT2: 40 | AU2: 41 | AV2: 42 | AW2: 43 | AX2: 44 | AY2: 45 | AZ2: 46 | BA2: 47 | BB2: 48 | BC2: 49 | BD2: 50
C3: Process | D3: Process | E3: Process2 | F3: If a manager hire and new role is required then select "New Role and New Hire" otherwise select "New Hire | G3: New Hire | H3: New Hire | I3: New Hire | J3: New Hire | K3: New Hire | L3: New Hire | M3: New Hire | N3: New Hire | O3: New Hire | P3: New Hire | Q3: New Hire | R3: New Hire | S3: New Hire | T3: New Hire | U3: New Hire | V3: New Hire | W3: New Hire | X3: New Hire | Y3: New Hire | Z3: New Hire | AA3: New Hire | AB3: New Hire | AC3: New Hire | AD3: New Hire | AE3: New Hire | AF3: New Hire | AG3: New Hire | AH3: New Hire | AI3: New Hire | AJ3: New Hire | AK3: New Hire | AL3: New Hire | AM3: New Role & New Hire | AN3: New Role & New Hire | AO3: New Role & New Hire | AP3: New Role & New Hire | AQ3: New Role & New Hire | AR3: New Role & New Hire | AS3: New Role & New Hire | AT3: New Role & New Hire | AU3: New Role & New Hire | AV3: New Role & New Hire | AW3: New Role & New Hire | AX3: New Role & New Hire | AY3: New Hire | AZ3: New Hire | BA3: New Hire | BB3: New Hire | BC3: New Hire | BD3: New Hire | BE3: New Hire | BF3: New Hire
C4: Execution Flag | D4: ExecutionFlag | E4: ExecutionFlag2 | F4: If set to No will not execute in next automation run | G4: Yes | H4: Yes | I4: Yes | J4: Yes | K4: Yes | L4: Yes | M4: Yes | N4: Yes | O4: Yes | P4: Yes | Q4: Yes | R4: Yes | S4: Yes | T4: Yes | U4: Yes | V4: Yes | W4: Yes | X4: Yes | Y4: Yes | Z4: Yes | AA4: Yes | AB4: Yes | AC4: Yes | AD4: Yes | AE4: Yes | AF4: Yes | AG4: Yes | AH4: Yes | AI4: Yes | AJ4: Yes | AK4: Yes | AL4: Yes | AM4: Yes | AN4: Yes | AO4: Yes | AP4: Yes | AQ4: Yes | AR4: Yes | AS4: Yes | AT4: Yes | AU4: Yes | AV4: Yes | AW4: Yes | AX4: Yes | AY4: Yes | AZ4: Yes | BA4: Yes | BB4: Yes | BC4: Yes | BD4: Yes | BE4: Yes | BF4: Yes
C5: Data Validation Complete | D5: DataValidationComplete | E5: DataValidationComplete2 | G5: TRUE | H5: TRUE | I5: TRUE | J5: TRUE | K5: TRUE | L5: TRUE | M5: TRUE | N5: TRUE | O5: TRUE | P5: TRUE | Q5: TRUE | R5: TRUE | S5: TRUE | T5: TRUE | U5: TRUE | V5: TRUE | W5: TRUE | X5: TRUE | Y5: TRUE | Z5: TRUE | AA5: TRUE | AB5: TRUE | AC5: TRUE | AD5: TRUE | AE5: TRUE | AF5: TRUE | AG5: TRUE | AH5: TRUE | AI5: TRUE | AJ5: TRUE | AK5: TRUE | AL5: TRUE | AM5: TRUE | AN5: TRUE | AO5: TRUE | AP5: TRUE | AQ5: TRUE | AR5: TRUE | AS5: TRUE | AT5: TRUE | AU5: TRUE | AV5: TRUE | AW5: TRUE | AX5: TRUE | AY5: TRUE | AZ5: TRUE | BA5: TRUE | BB5: TRUE | BC5: TRUE | BD5: TRUE | BE5: TRUE | BF5: TRUE
C6: Hire Name Complete | D6: HireNameComplete | E6: HireNameComplete2 | G6: TRUE | H6: TRUE | I6: TRUE | J6: TRUE | K6: TRUE | L6: TRUE | M6: TRUE | N6: TRUE | O6: TRUE | P6: TRUE | Q6: TRUE | R6: TRUE | S6: TRUE | T6: TRUE | U6: TRUE | V6: TRUE | W6: TRUE | X6: TRUE | Y6: TRUE | Z6: TRUE | AA6: TRUE | AB6: TRUE | AC6: TRUE | AD6: TRUE | AE6: TRUE | AF6: TRUE | AG6: TRUE | AH6: TRUE | AI6: TRUE | AJ6: TRUE | AK6: TRUE | AL6: TRUE | AM6: TRUE | AN6: TRUE | AO6: TRUE | AP6: TRUE | AQ6: TRUE | AR6: TRUE | AS6: TRUE | AT6: TRUE | AU6: TRUE | AV6: TRUE | AW6: TRUE | AX6: TRUE | AY6: TRUE | AZ6: TRUE | BA6: TRUE | BB6: TRUE | BC6: TRUE | BD6: TRUE | BE6: TRUE | BF6: TRUE
C9: Last Run Error Message | D9: LastRunErrorMessage | E9: LastRunErrorMessage2 | F9: If Automation throws errors, the details will be placed here
C10: Defect Description | D10: DefectDescription | E10: DefectDescription2 | F10: After error investigation by the automation team, the defect description will be completed here
C11: Automation Comments | D11: AutomationComments | E11: AutomationComments2 | F11: Automation team free text field
C12: QA Comments | D12: QAComments | E12: QAComments2 | F12: QA team free text field
A14: Screen | B14: Subscreen | C14: Field | D14: Automation Ref | E14: Lookups Ref | F14: Notes
A15: Supervisory Organisation | B15: N/A | C15: Supervisory Organisation | D15: =SUBSTITUTE(A15," ","") & "_" & SUBSTITUTE(IF(B15="N/A","",B15& "_")," ","") & SUBSTITUTE(SUBSTITUTE(C15," ",""),"/","") -> SupervisoryOrganisation_SupervisoryOrganisation | E15: =D15&2 -> SupervisoryOrganisation_SupervisoryOrganisation2 | G15: 766 Recruitment (Gybop Sytavu (10223416)) | H15: 766 Recruitment (Gybop Sytavu (10223416)) | I15: 766 Recruitment (Gybop Sytavu (10223416)) | J15: 766 Recruitment (Gybop Sytavu (10223416)) | K15: 766 Recruitment (Gybop Sytavu (10223416)) | L15: 766 Recruitment (Gybop Sytavu (10223416)) | M15: 766 Recruitment (Gybop Sytavu (10223416)) | N15: 766 Recruitment (Gybop Sytavu (10223416)) | O15: 766 Recruitment (Gybop Sytavu (10223416)) | P15: 766 Recruitment (Gybop Sytavu (10223416)) | Q15: 766 Recruitment (Gybop Sytavu (10223416)) | R15: 766 Recruitment (Gybop Sytavu (10223416)) | S15: 766 Recruitment (Gybop Sytavu (10223416)) | T15: 766 Recruitment (Gybop Sytavu (10223416)) | U15: 766 Recruitment (Gybop Sytavu (10223416)) | V15: 766 Recruitment (Gybop Sytavu (10223416)) | W15: 766 Recruitment (Gybop Sytavu (10223416)) | X15: 766 Recruitment (Gybop Sytavu (10223416)) | Y15: 766 Recruitment (Gybop Sytavu (10223416)) | Z15: 766 Recruitment (Gybop Sytavu (10223416)) | AA15: 766 Recruitment (Gybop Sytavu (10223416)) | AB15: 766 Recruitment (Gybop Sytavu (10223416)) | AC15: 766 Recruitment (Gybop Sytavu (10223416)) | AD15: 766 Recruitment (Gybop Sytavu (10223416)) | AE15: 766 Recruitment (Gybop Sytavu (10223416)) | AF15: 766 Recruitment (Gybop Sytavu (10223416)) | AG15: 766 Recruitment (Gybop Sytavu (10223416)) | AH15: 766 Recruitment (Gybop Sytavu (10223416)) | AI15: 766 Recruitment (Gybop Sytavu (10223416)) | AJ15: 766 Recruitment (Gybop Sytavu (10223416)) | AK15: 766 Recruitment (Gybop Sytavu (10223416)) | AL15: 766 Recruitment (Gybop Sytavu (10223416)) | AM15: 766 Store Management (Datyv Nuhuve (89501374)) | AN15: 766 Store Management (Datyv Nuhuve (89501374)) | AO15: 766 Store Management (Datyv Nuhuve (89501374)) | AP15: 766 Store Management (Datyv Nuhuve (89501374)) | AQ15: 766 Store Management (Datyv Nuhuve (89501374)) | AR15: 766 Store Management (Datyv Nuhuve (89501374)) | AS15: 766 Store Management (Datyv Nuhuve (89501374)) | AT15: 766 Store Management (Datyv Nuhuve (89501374)) | AU15: 766 Store Management (Datyv Nuhuve (89501374)) | AV15: 766 Store Management (Datyv Nuhuve (89501374)) | AW15: 766 Store Management (Datyv Nuhuve (89501374)) | AX15: 766 Store Management (Datyv Nuhuve (89501374)) | AY15: 766 Recruitment (Gybop Sytavu (10223416)) | AZ15: 766 Recruitment (Gybop Sytavu (10223416)) | BA15: 766 Recruitment (Gybop Sytavu (10223416)) | BB15: 766 Recruitment (Gybop Sytavu (10223416)) | BC15: 766 Recruitment (Gybop Sytavu (10223416)) | BD15: 766 Recruitment (Gybop Sytavu (10223416)) | BE15: 766 Recruitment (Gybop Sytavu (10223416)) | BF15: 766 Recruitment (Gybop Sytavu (10223416))
A16: Legal Name Information | B16: N/A | C16: Country | D16: =SUBSTITUTE(A16," ","") & "_" & SUBSTITUTE(IF(B16="N/A","",B16& "_")," ","") & SUBSTITUTE(SUBSTITUTE(C16," ",""),"/","") -> LegalNameInformation_Country | E16: =D16&2 -> LegalNameInformation_Country2 | F16: Test country to be placed here | G16: Poland | H16: Poland | I16: Poland | J16: Poland | K16: Poland | L16: Poland | M16: Poland | N16: Poland | O16: Poland | P16: Poland | Q16: Poland | R16: Poland | S16: Poland | T16: Poland | U16: Poland | V16: Poland | W16: Poland | X16: Poland | Y16: Poland | Z16: Poland | AA16: Poland | AB16: Poland | AC16: Poland | AD16: Poland | AE16: Poland | AF16: Poland | AG16: Poland | AH16: Poland | AI16: Poland | AJ16: Poland | AK16: Poland | AL16: Poland | AM16: Poland | AN16: Poland | AO16: Poland | AP16: Poland | AQ16: Poland | AR16: Poland | AS16: Poland | AT16: Poland | AU16: Poland | AV16: Poland | AW16: Poland | AX16: Poland | AY16: Poland | AZ16: Poland | BA16: Poland | BB16: Poland | BC16: Poland | BD16: Poland | BE16: Poland | BF16: Poland
A17: Legal Name Information | B17: N/A | C17: Prefix | D17: =SUBSTITUTE(A17," ","") & "_" & SUBSTITUTE(IF(B17="N/A","",B17& "_")," ","") & SUBSTITUTE(SUBSTITUTE(C17," ",""),"/","") -> LegalNameInformation_Prefix | E17: =D17&2 -> LegalNameInformation_Prefix2 | G17: NightlyRUNBRN | H17: MangedRUNnightARN | I17: MangedRUNnightARN | J17: NightlyRUNBRN | K17: NightlyRUNBRN | L17: NightlyRUNBRN | M17: NightlyRUNBRN | N17: NightlyRUNBRN | O17: NightlyRUNBRN | P17: NightlyRUNBRN | Q17: NightlyRUNBRN | R17: NightlyRUNBRN | S17: NightlyRUNBRN | T17: NightlyRUNBRN | U17: NightlyRUNBRN | V17: NightlyRUNBRN | W17: NightlyRUNBRN | X17: NightlyRUNBRN | Y17: NightlyRUNBRN | Z17: NightlyRUNBRN | AA17: NightlyRUNBRN | AB17: NightlyRUNBRN | AC17: NightlyRUNBRN | AD17: NightlyRUNBRN | AE17: NightlyRUNBRN | AF17: NightlyRUNBRN | AG17: NightlyRUNBRN | AH17: NightlyRUNBRN | AI17: NightlyRUNBRN | AJ17: NightlyRUNBRN | AK17: NightlyRUNBRN | AL17: NightlyRUNBRN | AM17: NightlyRUNBRN | AN17: NightlyRUNBRN | AO17: NightlyRUNBRN | AP17: NightlyRUNBRN | AQ17: NightlyRUNBRN | AR17: NightlyRUNBRN | AS17: NightlyRUNBRN | AT17: NightlyRUNBRN | AU17: NightlyRUNBRN | AV17: NightlyRUNBRN | AW17: NightlyRUNBRN | AX17: NightlyRUNBRN | AY17: NightlyRUNBRN | AZ17: NightlyRUNBRN | BA17: NightlyRUNBRN | BB17: NightlyRUNBRN | BC17: NightlyRUNBRN | BD17: NightlyRUNBRN | BE17: NightlyRUNBRN | BF17: NightlyRUNBRN
A18: Legal Name Information | B18: N/A | C18: Given Name | D18: =SUBSTITUTE(A18," ","") & "_" & SUBSTITUTE(IF(B18="N/A","",B18& "_")," ","") & SUBSTITUTE(SUBSTITUTE(C18," ",""),"/","") -> LegalNameInformation_GivenName | E18: =D18&2 -> LegalNameInformation_GivenName2 | F18: Automation will throw error if not unique | G18: PolOne | H18: PolTwo | I18: PolThree | J18: PolFour | K18: PolFive | L18: PolSix | M18: PolSeven | N18: PolEight | O18: PolNine | P18: PolTen | Q18: PolEleven | R18: PolTwelve | S18: PolThirteen | T18: PolFourteen | U18: PolFifteen | V18: PolSixteen | W18: PolSeventeen | X18: PolEighteen | Y18: PolNineteen | Z18: PolTwenty | AA18: PolTwentyOne | AB18: PolTwentyTwo | AC18: PolTwentyThree | AD18: PolTwentyFour | AE18: PolTwentyFive | AF18: PolTwentySix | AG18: PolTwentySeven | AH18: PolTwentyEight | AI18: PolTwentyNine | AJ18: PolThirty | AK18: PolThirtyOne | AL18: PolThirtyTwo | AM18: PolOne | AN18: PolTwo | AO18: PolThree | AP18: PolFour | AQ18: PolFive | AR18: PolSix | AS18: PolSeven | AT18: PolEight | AU18: PolNine | AV18: PolTen | AW18: PolEleven | AX18: PolTwelve | AY18: PolThirteen | AZ18: PolFourteen | BA18: PolFifteen | BB18: PolSixteen | BC18: PolSeventeen | BD18: PolEighteen | BE18: PolNineteen | BF18: PolTwenty
A19: Legal Name Information | B19: N/A | C19: Family Name | D19: =SUBSTITUTE(A19," ","") & "_" & SUBSTITUTE(IF(B19="N/A","",B19& "_")," ","") & SUBSTITUTE(SUBSTITUTE(C19," ",""),"/","") -> LegalNameInformation_FamilyName | E19: =D19&2 -> LegalNameInformation_FamilyName2 | F19: Automation will throw error if not unique | G19: PolandEndTwoEnd | H19: PolandEndTwoEnd | I19: GlobelRegSevOCT | J19: PolandEndTwoEnd | K19: PolandEndTwoEnd | L19: PolandEndTwoEnd | M19: PolandEndTwoEnd | N19: PolandEndTwoEnd | O19: PolandEndTwoEnd | P19: PolandEndTwoEnd | Q19: PolandEndTwoEnd | R19: PolandEndTwoEnd | S19: PolandEndTwoEnd | T19: PolandEndTwoEnd | U19: PolandEndTwoEnd | V19: PolandEndTwoEnd | W19: PolandEndTwoEnd | X19: PolandEndTwoEnd | Y19: PolandEndTwoEnd | Z19: PolandEndTwoEnd | AA19: PolandEndTwoEnd | AB19: PolandEndTwoEnd | AC19: PolandEndTwoEnd | AD19: PolandEndTwoEnd | AE19: PolandEndTwoEnd | AF19: PolandEndTwoEnd | AG19: PolandEndTwoEnd | AH19: PolandEndTwoEnd | AI19: PolandEndTwoEnd | AJ19: PolandEndTwoEnd | AK19: PolandEndTwoEnd | AL19: PolandEndTwoEnd | AM19: PolandEndTwoEnd | AN19: PolandEndTwoEnd | AO19: PolandEndTwoEnd | AP19: PolandEndTwoEnd | AQ19: PolandEndTwoEnd | AR19: PolandEndTwoEnd | AS19: PolandEndTwoEnd | AT19: PolandEndTwoEnd | AU19: PolandEndTwoEnd | AV19: PolandEndTwoEnd | AW19: PolandEndTwoEnd | AX19: PolandEndTwoEnd | AY19: PolandEndTwoEnd | AZ19: PolandEndTwoEnd | BA19: PolandEndTwoEnd | BB19: PolandEndTwoEnd | BC19: PolandEndTwoEnd | BD19: PolandEndTwoEnd | BE19: PolandEndTwoEnd | BF19: PolandEndTwoEnd
A20: Contact Information | B20: Phone | C20: PhoneNumber | D20: =SUBSTITUTE(A20," ","") & "_" & SUBSTITUTE(IF(B20="N/A","",B20& "_")," ","") & SUBSTITUTE(SUBSTITUTE(C20," ",""),"/","") -> ContactInformation_Phone_PhoneNumber | E20: =D20&2 -> ContactInformation_Phone_PhoneNumber2 | G20: 698 980 460 | H20: 698 980 460 | I20: 698 980 460 | J20: 698 980 460 | K20: 698 980 460 | L20: 698 980 460 | M20: 698 980 460 | N20: 698 980 460 | O20: 698 980 460 | P20: 698 980 460 | Q20: 698 980 460 | R20: 698 980 460 | S20: 698 980 460 | T20: 698 980 460 | U20: 698 980 460 | V20: 698 980 460 | W20: 698 980 460 | X20: 698 980 460 | Y20: 698 980 460 | Z20: 698 980 460 | AA20: 698 980 460 | AB20: 698 980 460 | AC20: 698 980 460 | AD20: 698 980 460 | AE20: 698 980 460 | AF20: 698 980 460 | AG20: 698 980 460 | AH20: 698 980 460 | AI20: 698 980 460 | AJ20: 698 980 460 | AK20: 698 980 460 | AL20: 698 980 460 | AM20: 698 980 460 | AN20: 698 980 460 | AO20: 698 980 460 | AP20: 698 980 460 | AQ20: 698 980 460 | AR20: 698 980 460 | AS20: 698 980 460 | AT20: 698 980 460 | AU20: 698 980 460 | AV20: 698 980 460 | AW20: 698 980 460 | AX20: 698 980 460 | AY20: 698 980 460 | AZ20: 698 980 460 | BA20: 698 980 460 | BB20: 698 980 460 | BC20: 698 980 460 | BD20: 698 980 460 | BE20: 698 980 460 | BF20: 698 980 460
A21: Contact Information | B21: Phone | C21: PhoneDevice | D21: =SUBSTITUTE(A21," ","") & "_" & SUBSTITUTE(IF(B21="N/A","",B21& "_")," ","") & SUBSTITUTE(SUBSTITUTE(C21," ",""),"/","") -> ContactInformation_Phone_PhoneDevice | E21: =D21&2 -> ContactInformation_Phone_PhoneDevice2 | G21: Landline | H21: Landline | I21: Landline | J21: Landline | K21: Landline | L21: Landline | M21: Landline | N21: Landline | O21: Landline | P21: Landline | Q21: Landline | R21: Landline | S21: Landline | T21: Landline | U21: Landline | V21: Landline | W21: Landline | X21: Landline | Y21: Landline | Z21: Landline | AA21: Landline | AB21: Landline | AC21: Landline | AD21: Landline | AE21: Landline | AF21: Landline | AG21: Landline | AH21: Landline | AI21: Landline | AJ21: Landline | AK21: Landline | AL21: Landline | AM21: Landline | AN21: Landline | AO21: Landline | AP21: Landline | AQ21: Landline | AR21: Landline | AS21: Landline | AT21: Landline | AU21: Landline | AV21: Landline | AW21: Landline | AX21: Landline | AY21: Landline | AZ21: Landline | BA21: Landline | BB21: Landline | BC21: Landline | BD21: Landline | BE21: Landline | BF21: Landline
A22: Contact Information | B22: Phone | C22: Type | D22: =SUBSTITUTE(A22," ","") & "_" & SUBSTITUTE(IF(B22="N/A","",B22& "_")," ","") & SUBSTITUTE(SUBSTITUTE(C22," ",""),"/","") -> ContactInformation_Phone_Type | E22: =D22&2 -> ContactInformation_Phone_Type2 | G22: Home | H22: Home | I22: Home | J22: Home | K22: Home | L22: Home | M22: Home | N22: Home | O22: Home | P22: Home | Q22: Home | R22: Home | S22: Home | T22: Home | U22: Home | V22: Home | W22: Home | X22: Home | Y22: Home | Z22: Home | AA22: Home | AB22: Home | AC22: Home | AD22: Home | AE22: Home | AF22: Home | AG22: Home | AH22: Home | AI22: Home | AJ22: Home | AK22: Home | AL22: Home | AM22: Home | AN22: Home | AO22: Home | AP22: Home | AQ22: Home | AR22: Home | AS22: Home | AT22: Home | AU22: Home | AV22: Home | AW22: Home | AX22: Home | AY22: Home | AZ22: Home | BA22: Home | BB22: Home | BC22: Home | BD22: Home | BE22: Home | BF22: Home
A23: Contact Information | B23: Address | C23: EffectiveDate | D23: =SUBSTITUTE(A23," ","") & "_" & SUBSTITUTE(IF(B23="N/A","",B23& "_")," ","") & SUBSTITUTE(SUBSTITUTE(C23," ",""),"/","") -> ContactInformation_Address_EffectiveDate | E23: =D23&2 -> ContactInformation_Address_EffectiveDate2 | G23: =TODAY()-31 -> 45689 | H23: =TODAY()-31 -> 45689 | I23: =TODAY()-31 -> 45689 | J23: =TODAY()-31 -> 45689 | K23: =TODAY()-31 -> 45689 | L23: =TODAY()-31 -> 45689 | M23: =TODAY()-31 -> 45689 | N23: =TODAY()-31 -> 45689 | ... V23: =TODAY()-31 -> 45689 | W23: =TODAY()+60 -> 45780 | X23: =TODAY()-31 -> 45689 | Y23: =TODAY()-31 -> 45689 | Z23: =TODAY()-31 -> 45689 | AA23: =TODAY()-31 -> 45689 | AB23: =TODAY()-31 -> 45689 | AC23: =TODAY()-31 -> 45689 | AD23: =TODAY()-31 -> 45689 | AE23: =TODAY()-31 -> 45689 | AF23: =TODAY()+91 -> 45811 | AG23: =TODAY()-31 -> 45689 | AH23: =TODAY()+91 -> 45811 | AI23: =TODAY()-31 -> 45689 | AJ23: =TODAY()-31 -> 45689 | AK23: =TODAY()-31 -> 45689 | AL23: =TODAY()-31 -> 45689 | AM23: =TODAY()+14 -> 45734 | AN23: =TODAY()-31 -> 45689 | AO23: =TODAY()-31 -> 45689 | AP23: =TODAY()-31 -> 45689 | AQ23: =TODAY()-31 -> 45689 | AR23: =TODAY()-60 -> 45660 | AS23: =TODAY()-31 -> 45689 | AT23: =TODAY()-31 -> 45689 | AU23: =TODAY()-31 -> 45689 | AV23: =TODAY()-31 -> 45689 | AW23: =TODAY()-31 -> 45689 | AX23: =TODAY()-31 -> 45689 | AY23: =TODAY()-31 -> 45689 | AZ23: =TODAY()-31 -> 45689 | ... BF23: =TODAY()-31 -> 45689
A24: Contact Information | B24: Address | C24: Country | D24: =SUBSTITUTE(A24," ","") & "_" & SUBSTITUTE(IF(B24="N/A","",B24& "_")," ","") & SUBSTITUTE(SUBSTITUTE(C24," ",""),"/","") -> ContactInformation_Address_Country | E24: =D24&2 -> ContactInformation_Address_Country2 | G24: Poland | H24: Poland | I24: Poland | J24: Poland | K24: Poland | L24: Poland | M24: Poland | N24: Poland | O24: Poland | P24: Poland | Q24: Poland | R24: Poland | S24: Poland | T24: Poland | U24: Poland | V24: Poland | W24: Poland | X24: Poland | Y24: Poland | Z24: Poland | AA24: Poland | AB24: Poland | AC24: Poland | AD24: Poland | AE24: Poland | AF24: Poland | AG24: Poland | AH24: Poland | AI24: Poland | AJ24: Poland | AK24: Poland | AL24: Poland | AM24: Poland | AN24: Poland | AO24: Poland | AP24: Poland | AQ24: Poland | AR24: Poland | AS24: Poland | AT24: Poland | AU24: Poland | AV24: Poland | AW24: Poland | AX24: Poland | AY24: Poland | AZ24: Poland | BA24: Poland | BB24: Poland | BC24: Poland | BD24: Poland | BE24: Poland | BF24: Poland
A25: Contact Information | B25: Address | C25: StreetName | D25: =SUBSTITUTE(A25," ","") & "_" & SUBSTITUTE(IF(B25="N/A","",B25& "_")," ","") & SUBSTITUTE(SUBSTITUTE(C25," ",""),"/","") -> ContactInformation_Address_StreetName | E25: =D25&2 -> ContactInformation_Address_StreetName2 | G25: Automation Street Name | H25: Automation Street Name | I25: Automation Street Name | J25: Automation Street Name | K25: Automation Street Name | L25: Automation Street Name | M25: Automation Street Name | N25: Automation Street Name | O25: Automation Street Name | P25: Automation Street Name | Q25: Automation Street Name | R25: Automation Street Name | S25: Automation Street Name | T25: Automation Street Name | U25: Automation Street Name | V25: Automation Street Name | W25: Automation Street Name | X25: Automation Street Name | Y25: Automation Street Name | Z25: Automation Street Name | AA25: Automation Street Name | AB25: Automation Street Name | AC25: Automation Street Name | AD25: Automation Street Name | AE25: Automation Street Name | AF25: Automation Street Name | AG25: Automation Street Name | AH25: Automation Street Name | AI25: Automation Street Name | AJ25: Automation Street Name | AK25: Automation Street Name | AL25: Automation Street Name | AM25: Automation Street Name | AN25: Automation Street Name | AO25: Automation Street Name | AP25: Automation Street Name | AQ25: Automation Street Name | AR25: Automation Street Name | AS25: Automation Street Name | AT25: Automation Street Name | AU25: Automation Street Name | AV25: Automation Street Name | AW25: Automation Street Name | AX25: Automation Street Name | AY25: Automation Street Name | AZ25: Automation Street Name | BA25: Automation Street Name | BB25: Automation Street Name | BC25: Automation Street Name | BD25: Automation Street Name | BE25: Automation Street Name | BF25: Automation Street Name
A26: Contact Information | B26: Address | C26: Province | D26: =SUBSTITUTE(A26," ","") & "_" & SUBSTITUTE(IF(B26="N/A","",B26& "_")," ","") & SUBSTITUTE(SUBSTITUTE(C26," ",""),"/","") -> ContactInformation_Address_Province | E26: =D26&2 -> ContactInformation_Address_Province2 | F26: Voivodeship or Province | G26: Greater Poland | H26: Greater Poland | I26: Greater Poland | J26: Greater Poland | K26: Greater Poland | L26: Greater Poland | M26: Greater Poland | N26: Greater Poland | O26: Greater Poland | P26: Greater Poland | Q26: Greater Poland | R26: Greater Poland | S26: Greater Poland | T26: Greater Poland | U26: Greater Poland | V26: Greater Poland | W26: Greater Poland | X26: Greater Poland | Y26: Greater Poland | Z26: Greater Poland | AA26: Greater Poland | AB26: Greater Poland | AC26: Greater Poland | AD26: Greater Poland | AE26: Greater Poland | AF26: Greater Poland | AG26: Greater Poland | AH26: Greater Poland | AI26: Greater Poland | AJ26: Greater Poland | AK26: Greater Poland | AL26: Greater Poland | AM26: Greater Poland | AN26: Greater Poland | AO26: Greater Poland | AP26: Greater Poland | AQ26: Greater Poland | AR26: Greater Poland | AS26: Greater Poland | AT26: Greater Poland | AU26: Greater Poland | AV26: Greater Poland | AW26: Greater Poland | AX26: Greater Poland | AY26: Greater Poland | AZ26: Greater Poland | BA26: Greater Poland | BB26: Greater Poland | BC26: Greater Poland | BD26: Greater Poland | BE26: Greater Poland | BF26: Greater Poland
A27: Contact Information | B27: Address | C27: PostalCode | D27: =SUBSTITUTE(A27," ","") & "_" & SUBSTITUTE(IF(B27="N/A","",B27& "_")," ","") & SUBSTITUTE(SUBSTITUTE(C27," ",""),"/","") -> ContactInformation_Address_PostalCode | E27: =D27&2 -> ContactInformation_Address_PostalCode2 | G27: 00001 | H27: 00001 | I27: 1 | J27: 1 | K27: 1 | L27: 00001 | M27: 00001 | N27: 1 | O27: 1 | P27: 1 | Q27: 1 | R27: 1 | S27: 1 | T27: 1 | U27: 1 | V27: 1 | W27: 1 | X27: 1 | Y27: 1 | Z27: 1 | AA27: 1 | AB27: 1 | AC27: 1 | AD27: 1 | AE27: 1 | AF27: 1 | AG27: 1 | AH27: 1 | AI27: 1 | AJ27: 1 | AK27: 1 | AL27: 1 | AM27: 1 | AN27: 1 | AO27: 1 | AP27: 1 | AQ27: 1 | AR27: 1 | AS27: 1 | AT27: 1 | AU27: 1 | AV27: 1 | AW27: 1 | AX27: 1 | AY27: 1 | AZ27: 1 | BA27: 1 | BB27: 1 | BC27: 1 | BD27: 1 | BE27: 1 | BF27: 1
A28: Contact Information | B28: Address | C28: City | D28: =SUBSTITUTE(A28," ","") & "_" & SUBSTITUTE(IF(B28="N/A","",B28& "_")," ","") & SUBSTITUTE(SUBSTITUTE(C28," ",""),"/","") -> ContactInformation_Address_City | E28: =D28&2 -> ContactInformation_Address_City2 | G28: Warsaw | H28: Warsaw | I28: Warsaw | J28: Warsaw | K28: Warsaw | L28: Warsaw | M28: Warsaw | N28: Warsaw | O28: Warsaw | P28: Warsaw | Q28: Warsaw | R28: Warsaw | S28: Warsaw | T28: Warsaw | U28: Warsaw | V28: Warsaw | W28: Warsaw | X28: Warsaw | Y28: Warsaw | Z28: Warsaw | AA28: Warsaw | AB28: Warsaw | AC28: Warsaw | AD28: Warsaw | AE28: Warsaw | AF28: Warsaw | AG28: Warsaw | AH28: Warsaw | AI28: Warsaw | AJ28: Warsaw | AK28: Warsaw | AL28: Warsaw | AM28: Warsaw | AN28: Warsaw | AO28: Warsaw | AP28: Warsaw | AQ28: Warsaw | AR28: Warsaw | AS28: Warsaw | AT28: Warsaw | AU28: Warsaw | AV28: Warsaw | AW28: Warsaw | AX28: Warsaw | AY28: Warsaw | AZ28: Warsaw | BA28: Warsaw | BB28: Warsaw | BC28: Warsaw | BD28: Warsaw | BE28: Warsaw | BF28: Warsaw
A29: Contact Information | B29: Address | C29: houseNumber | D29: =SUBSTITUTE(A29," ","") & "_" & SUBSTITUTE(IF(B29="N/A","",B29& "_")," ","") & SUBSTITUTE(SUBSTITUTE(C29," ",""),"/","") -> ContactInformation_Address_houseNumber | E29: =D29&2 -> ContactInformation_Address_houseNumber2 | G29: Test | H29: Test | I29: Test | J29: Test | K29: Test | L29: Test | M29: Test | N29: Test | O29: Test | P29: Test | Q29: Test | R29: Test | S29: Test | T29: Test | U29: Test | V29: Test | W29: Test | X29: Test | Y29: Test | Z29: Test | AA29: Test | AB29: Test | AC29: Test | AD29: Test | AE29: Test | AF29: Test | AG29: Test | AH29: Test | AI29: Test | AJ29: Test | AK29: Test | AL29: Test | AM29: Test | AN29: Test | AO29: Test | AP29: Test | AQ29: Test | AR29: Test | AS29: Test | AT29: Test | AU29: Test | AV29: Test | AW29: Test | AX29: Test | AY29: Test | AZ29: Test | BA29: Test | BB29: Test | BC29: Test | BD29: Test | BE29: Test | BF29: Test
A30: Contact Information | B30: Address | C30: Municipality | D30: =SUBSTITUTE(A30," ","") & "_" & SUBSTITUTE(IF(B30="N/A","",B30& "_")," ","") & SUBSTITUTE(SUBSTITUTE(C30," ",""),"/","") -> ContactInformation_Address_Municipality | E30: =D30&2 -> ContactInformation_Address_Municipality2 | G30: Test | H30: Test | I30: Test | J30: Test | K30: Test | L30: Test | M30: Test | N30: Test | O30: Test | P30: Test | Q30: Test | R30: Test | S30: Test | T30: Test | U30: Test | V30: Test | W30: Test | X30: Test | Y30: Test | Z30: Test | AA30: Test | AB30: Test | AC30: Test | AD30: Test | AE30: Test | AF30: Test | AG30: Test | AH30: Test | AI30: Test | AJ30: Test | AK30: Test | AL30: Test | AM30: Test | AN30: Test | AO30: Test | AP30: Test | AQ30: Test | AR30: Test | AS30: Test | AT30: Test | AU30: Test | AV30: Test | AW30: Test | AX30: Test | AY30: Test | AZ30: Test | BA30: Test | BB30: Test | BC30: Test | BD30: Test | BE30: Test | BF30: Test
A31: Contact Information | B31: Address | C31: District | D31: =SUBSTITUTE(A31," ","") & "_" & SUBSTITUTE(IF(B31="N/A","",B31& "_")," ","") & SUBSTITUTE(SUBSTITUTE(C31," ",""),"/","") -> ContactInformation_Address_District | E31: =D31&2 -> ContactInformation_Address_District2 | G31: Warsaw | H31: Warsaw | I31: Warsaw | J31: Warsaw | K31: Warsaw | L31: Warsaw | M31: Warsaw | N31: Warsaw | O31: Warsaw | P31: Warsaw | Q31: Warsaw | R31: Warsaw | S31: Warsaw | T31: Warsaw | U31: Warsaw | V31: Warsaw | W31: Warsaw | X31: Warsaw | Y31: Warsaw | Z31: Warsaw | AA31: Warsaw | AB31: Warsaw | AC31: Warsaw | AD31: Warsaw | AE31: Warsaw | AF31: Warsaw | AG31: Warsaw | AH31: Warsaw | AI31: Warsaw | AJ31: Warsaw | AK31: Warsaw | AL31: Warsaw | AM31: Warsaw | AN31: Warsaw | AO31: Warsaw | AP31: Warsaw | AQ31: Warsaw | AR31: Warsaw | AS31: Warsaw | AT31: Warsaw | AU31: Warsaw | AV31: Warsaw | AW31: Warsaw | AX31: Warsaw | AY31: Warsaw | AZ31: Warsaw | BA31: Warsaw | BB31: Warsaw | BC31: Warsaw | BD31: Warsaw | BE31: Warsaw | BF31: Warsaw
A32: Contact Information | B32: Address | C32: Type | D32: =SUBSTITUTE(A32," ","") & "_" & SUBSTITUTE(IF(B32="N/A","",B32& "_")," ","") & SUBSTITUTE(SUBSTITUTE(C32," ",""),"/","") -> ContactInformation_Address_Type | E32: =D32&2 -> ContactInformation_Address_Type2 | F32: "Permanent" or "Temporary" | G32: Home | H32: Home | I32: Home | J32: Home | K32: Home | L32: Home | M32: Home | N32: Home | O32: Home | P32: Home | Q32: Home | R32: Home | S32: Home | T32: Home | U32: Home | V32: Home | W32: Home | X32: Home | Y32: Home | Z32: Home | AA32: Home | AB32: Home | AC32: Home | AD32: Home | AE32: Home | AF32: Home | AG32: Home | AH32: Home | AI32: Home | AJ32: Home | AK32: Home | AL32: Home | AM32: Home | AN32: Home | AO32: Home | AP32: Home | AQ32: Home | AR32: Home | AS32: Home | AT32: Home | AU32: Home | AV32: Home | AW32: Home | AX32: Home | AY32: Home | AZ32: Home | BA32: Home | BB32: Home | BC32: Home | BD32: Home | BE32: Home | BF32: Home
A33: Contact Information | B33: Email | C33: UseFor | D33: =SUBSTITUTE(A33," ","") & "_" & SUBSTITUTE(IF(B33="N/A","",B33& "_")," ","") & SUBSTITUTE(SUBSTITUTE(C33," ",""),"/","") -> ContactInformation_Email_UseFor | E33: =D33&2 -> ContactInformation_Email_UseFor2 | G33: Street Address | H33: Street Address | I33: Street Address | J33: Street Address | K33: Street Address | L33: Street Address | M33: Street Address | N33: Street Address | O33: Street Address | P33: Street Address | Q33: Street Address | R33: Street Address | S33: Street Address | T33: Street Address | U33: Street Address | V33: Street Address | W33: Street Address | X33: Street Address | Y33: Street Address | Z33: Street Address | AA33: Street Address | AB33: Street Address | AC33: Street Address | AD33: Street Address | AE33: Street Address | AF33: Street Address | AG33: Street Address | AH33: Street Address | AI33: Street Address | AJ33: Street Address | AK33: Street Address | AL33: Street Address | AM33: Street Address | AN33: Street Address | AO33: Street Address | AP33: Street Address | AQ33: Street Address | AR33: Street Address | AS33: Street Address | AT33: Street Address | AU33: Street Address | AV33: Street Address | AW33: Street Address | AX33: Street Address | AY33: Street Address | AZ33: Street Address | BA33: Street Address | BB33: Street Address | BC33: Street Address | BD33: Street Address | BE33: Street Address | BF33: Street Address
A34: Contact Information | B34: Email | C34: EmailAddress | D34: =SUBSTITUTE(A34," ","") & "_" & SUBSTITUTE(IF(B34="N/A","",B34& "_")," ","") & SUBSTITUTE(SUBSTITUTE(C34," ",""),"/","") -> ContactInformation_Email_EmailAddress | E34: =D34&2 -> ContactInformation_Email_EmailAddress2 | G34: Test001@gmail.com | H34: Test001@gmail.com | I34: Test001@gmail.com | J34: Test001@gmail.com | K34: Test001@gmail.com | L34: Test001@gmail.com | M34: Test001@gmail.com | N34: Test001@gmail.com | O34: Test001@gmail.com | P34: Test001@gmail.com | Q34: Test001@gmail.com | R34: Test001@gmail.com | S34: Test001@gmail.com | T34: Test001@gmail.com | U34: Test001@gmail.com | V34: Test001@gmail.com | W34: Test001@gmail.com | X34: Test001@gmail.com | Y34: Test001@gmail.com | Z34: Test001@gmail.com | AA34: Test001@gmail.com | AB34: Test001@gmail.com | AC34: Test001@gmail.com | AD34: Test001@gmail.com | AE34: Test001@gmail.com | AF34: Test001@gmail.com | AG34: Test001@gmail.com | AH34: Test001@gmail.com | AI34: Test001@gmail.com | AJ34: Test001@gmail.com | AK34: Test001@gmail.com | AL34: Test001@gmail.com | AM34: Test001@gmail.com | AN34: Test001@gmail.com | AO34: Test001@gmail.com | AP34: Test001@gmail.com | AQ34: Test001@gmail.com | AR34: Test001@gmail.com | AS34: Test001@gmail.com | AT34: Test001@gmail.com | AU34: Test001@gmail.com | AV34: Test001@gmail.com | AW34: Test001@gmail.com | AX34: Test001@gmail.com | AY34: Test001@gmail.com | AZ34: Test001@gmail.com | BA34: Test001@gmail.com | BB34: Test001@gmail.com | BC34: Test001@gmail.com | BD34: Test001@gmail.com | BE34: Test001@gmail.com | BF34: Test001@gmail.com
A35: Job Details | B35: N/A | C35: Type | D35: =SUBSTITUTE(A35," ","") & "_" & SUBSTITUTE(IF(B35="N/A","",B35& "_")," ","") & SUBSTITUTE(SUBSTITUTE(C35," ",""),"/","") -> JobDetails_Type | E35: =D35&2 -> JobDetails_Type2 | G35: Home | H35: Home | I35: Home | J35: Home | K35: Home | L35: Home | M35: Home | N35: Home | O35: Home | P35: Home | Q35: Home | R35: Home | S35: Home | T35: Home | U35: Home | V35: Home | W35: Home | X35: Home | Y35: Home | Z35: Home | AA35: Home | AB35: Home | AC35: Home | AD35: Home | AE35: Home | AF35: Home | AG35: Home | AH35: Home | AI35: Home | AJ35: Home | AK35: Home | AL35: Home | AM35: Home | AN35: Home | AO35: Home | AP35: Home | AQ35: Home | AR35: Home | AS35: Home | AT35: Home | AU35: Home | AV35: Home | AW35: Home | AX35: Home | AY35: Home | AZ35: Home | BA35: Home | BB35: Home | BC35: Home | BD35: Home | BE35: Home | BF35: Home
A36: Job Details | B36: N/A | C36: HireDate | D36: =SUBSTITUTE(A36," ","") & "_" & SUBSTITUTE(IF(B36="N/A","",B36& "_")," ","") & SUBSTITUTE(SUBSTITUTE(C36," ",""),"/","") -> JobDetails_HireDate | E36: =D36&2 -> JobDetails_HireDate2 | G36: =G23 -> 45689 | H36: =H23 -> 45689 | I36: =I23 -> 45689 | J36: =J23 -> 45689 | K36: =K23 -> 45689 | L36: =L23 -> 45689 | M36: =M23 -> 45689 | N36: =N23 -> 45689 | ... BF36: =BF23 -> 45689
A37: Job Details | B37: N/A | C37: Reason | D37: =SUBSTITUTE(A37," ","") & "_" & SUBSTITUTE(IF(B37="N/A","",B37& "_")," ","") & SUBSTITUTE(SUBSTITUTE(C37," ",""),"/","") -> JobDetails_Reason | E37: =D37&2 -> JobDetails_Reason2 | F37: If Process is set to "New Role and New Hire" (Row 2) this position name will be ignored and replaced with the newly created name. | G37: New Hire | H37: New Hire | I37: New Hire | J37: New Hire | K37: New Hire | L37: New Hire | M37: New Hire | N37: New Hire | O37: New Hire | P37: New Hire | Q37: New Hire | R37: New Hire | S37: New Hire | T37: New Hire | U37: New Hire | V37: New Hire | W37: New Hire | X37: New Hire | Y37: New Hire | Z37: New Hire | AA37: New Hire | AB37: New Hire | AC37: New Hire | AD37: New Hire | AE37: New Hire | AF37: New Hire | AG37: New Hire | AH37: New Hire | AI37: New Hire | AJ37: New Hire | AK37: New Hire | AL37: New Hire | AM37: New Hire | AN37: New Hire | AO37: New Hire | AP37: New Hire | AQ37: New Hire | AR37: New Hire | AS37: New Hire | AT37: New Hire | AU37: New Hire | AV37: New Hire | AW37: New Hire | AX37: New Hire | AY37: New Hire | AZ37: New Hire | BA37: New Hire | BB37: New Hire | BC37: New Hire | BD37: New Hire | BE37: New Hire | BF37: New Hire
A38: Job Details | B38: N/A | C38: Position | D38: =SUBSTITUTE(A38," ","") & "_" & SUBSTITUTE(IF(B38="N/A","",B38& "_")," ","") & SUBSTITUTE(SUBSTITUTE(C38," ",""),"/","") -> JobDetails_Position | E38: =D38&2 -> JobDetails_Position2 | F38: If Fixed Term ensure contract end date below is populated and not N/A | G38: No | H38: No | I38: No | J38: No | K38: No | L38: No | M38: No | N38: No | O38: No | P38: No | Q38: No | R38: No | S38: No | T38: No | U38: No | V38: No | W38: No | X38: No | Y38: No | Z38: No | AA38: No | AB38: No | AC38: No | AD38: No | AE38: No | AF38: No | AG38: No | AH38: No | AI38: No | AJ38: No | AK38: No | AL38: No | AM38: Yes | AN38: Yes | AO38: Yes | AP38: Yes | AQ38: Yes | AR38: Yes | AS38: Yes | AT38: Yes | AU38: Yes | AV38: Yes | AW38: Yes | AX38: Yes | AY38: No | AZ38: No | BA38: No | BB38: No | BC38: No | BD38: No | BE38: No | BF38: No
A39: Job Details | B39: N/A | C39: EmployeeType | D39: =SUBSTITUTE(A39," ","") & "_" & SUBSTITUTE(IF(B39="N/A","",B39& "_")," ","") & SUBSTITUTE(SUBSTITUTE(C39," ",""),"/","") -> JobDetails_EmployeeType | E39: =D39&2 -> JobDetails_EmployeeType2 | G39: Permanent | H39: Permanent | I39: Permanent | J39: Fixed Term | K39: Fixed Term | L39: Permanent | M39: Permanent | N39: Permanent | O39: Fixed Term | P39: Permanent | Q39: Fixed term | R39: Fixed Term | S39: Permanent | T39: Permanent | U39: Permanent | V39: Fixed Term | W39: Fixed Term | X39: Fixed Term | Y39: Fixed Term | Z39: Permanent | AA39: Permanent | AB39: Fixed Term | AC39: Permanent | AD39: Fixed Term | AE39: Fixed Term | AF39: Fixed Term | AG39: Permanent | AH39: Fixed Term | AI39: Fixed Term | AJ39: Fixed Term | AK39: Permanent | AL39: Permanent | AM39: Fixed Term | AN39: Permanent | AO39: Fixed Term | AP39: Permanent | AQ39: Fixed Term | AR39: Permanent | AS39: Fixed Term | AT39: Permanent | AU39: Fixed Term | AV39: Permanent | AW39: Fixed Term | AX39: Permanent | AY39: Fixed Term | AZ39: Fixed Term | BA39: Permanent | BB39: Permanent | BC39: Fixed Term | BD39: Fixed Term | BE39: Permanent | BF39: Permanent
A40: Job Details | B40: N/A | C40: JobProfile | D40: =SUBSTITUTE(A40," ","") & "_" & SUBSTITUTE(IF(B40="N/A","",B40& "_")," ","") & SUBSTITUTE(SUBSTITUTE(C40," ",""),"/","") -> JobDetails_JobProfile | E40: =D40&2 -> JobDetails_JobProfile2 | G40: Retail Assistant_NEW | H40: Retail Assistant_NEW | I40: Retail Assistant_NEW | J40: Retail Assistant_NEW | K40: Retail Assistant_NEW | L40: Retail Assistant_NEW | M40: Retail Assistant_NEW | N40: Retail Assistant_NEW | O40: Retail Assistant_NEW | P40: Retail Assistant_NEW | Q40: Retail Assistant_NEW | R40: Retail Assistant_NEW | S40: Retail Assistant_NEW | T40: Retail Assistant_NEW | U40: Retail Assistant_NEW | V40: Retail Assistant_NEW | W40: Retail Assistant_NEW | X40: Retail Assistant_NEW | Y40: Retail Assistant_NEW | Z40: Retail Assistant_NEW | AA40: Retail Assistant_NEW | AB40: Retail Assistant_NEW | AC40: Retail Assistant_NEW | AD40: Retail Assistant_NEW | AE40: Visual Merchandiser_NEW | AF40: Visual Merchandiser_NEW | AG40: Visual Merchandiser_NEW | AH40: Visual Merchandiser_NEW | AI40: Operational Support_NEW | AJ40: Operational Support_NEW | AK40: Operational Support_NEW | AL40: Operational Support_NEW | AM40: Store Manager_NEW | AN40: Store Manager_NEW | AO40: P&C Manager_NEW | AP40: P&C Manager_NEW | AQ40: Team Manager_NEW | AR40: Team Manager_NEW | AS40: Assistant Store Manager_NEW | AT40: Assistant Store Manager_NEW | AU40: Assistant P&C Manager_NEW | AV40: Assistant P&C Manager_NEW | AW40: Visual Merchandiser Manager_NEW | AX40: Visual Merchandiser Manager_NEW | AY40: P&C Supervisor_NEW | AZ40: P&C Supervisor_NEW | BA40: P&C Supervisor_NEW | BB40: P&C Supervisor_NEW | BC40: P&C Assistant_NEW | BD40: P&C Assistant_NEW | BE40: P&C Assistant_NEW | BF40: P&C Assistant_NEW
A41: Job Details | B41: N/A | C41: TimeType | D41: =SUBSTITUTE(A41," ","") & "_" & SUBSTITUTE(IF(B41="N/A","",B41& "_")," ","") & SUBSTITUTE(SUBSTITUTE(C41," ",""),"/","") -> JobDetails_TimeType | E41: =D41&2 -> JobDetails_TimeType2 | G41: Part time | H41: Full time | I41: Full time | J41: Full time | K41: Part time | L41: Full time | M41: Part time | N41: Full time | O41: Part time | P41: Part time | Q41: Full Time | R41: Part Time | S41: Part time | T41: Full time | U41: Full time | V41: Full time | W41: Part time | X41: Full time | Y41: Part time | Z41: Full time | AA41: Part time | AB41: Full time | AC41: Full time | AD41: Full time | AE41: Full time | AF41: Part time | AG41: Full time | AH41: Full time | AI41: Full time | AJ41: Part time | AK41: Part time | AL41: Full time | AM41: Full time | AN41: Part time | AO41: Full time | AP41: Full time | AQ41: Full time | AR41: Part time | AS41: Full time | AT41: Part time | AU41: Full time | AV41: Part time | AW41: Full time | AX41: Part time | AY41: Full time | AZ41: Part time | BA41: Full time | BB41: Part time | BC41: Full time | BD41: Full time | BE41: Part time | BF41: Full time
A42: Job Details | B42: N/A | C42: Location | D42: =SUBSTITUTE(A42," ","") & "_" & SUBSTITUTE(IF(B42="N/A","",B42& "_")," ","") & SUBSTITUTE(SUBSTITUTE(C42," ",""),"/","") -> JobDetails_Location | E42: =D42&2 -> JobDetails_Location2 | G42: 766 | H42: 766 | I42: 766 | J42: 766 | K42: 766 | L42: 766 | M42: 766 | N42: 766 | O42: 766 | P42: 766 | Q42: 766 | R42: 766 | S42: 766 | T42: 766 | U42: 766 | V42: 766 | W42: 766 | X42: 766 | Y42: 766 | Z42: 766 | AA42: 766 | AB42: 766 | AC42: 766 | AD42: 766 | AE42: 766 | AF42: 766 | AG42: 766 | AH42: 766 | AI42: 766 | AJ42: 766 | AK42: 766 | AL42: 766 | AM42: 766 | AN42: 766 | AO42: 766 | AP42: 766 | AQ42: 766 | AR42: 766 | AS42: 766 | AT42: 766 | AU42: 766 | AV42: 766 | AW42: 766 | AX42: 766 | AY42: 766 | AZ42: 766 | BA42: 766 | BB42: 766 | BC42: 766 | BD42: 766 | BE42: 766 | BF42: 766
A43: Job Details | B43: Additional Information | C43: PayRateType | D43: =SUBSTITUTE(A43," ","") & "_" & SUBSTITUTE(IF(B43="N/A","",B43& "_")," ","") & SUBSTITUTE(SUBSTITUTE(C43," ",""),"/","") -> JobDetails_AdditionalInformation_PayRateType | E43: =D43&2 -> JobDetails_AdditionalInformation_PayRateType2 | G43: Salary | H43: Salary | I43: Salary | J43: Salary | K43: Salary | L43: Salary | M43: Salary | N43: Salary | O43: Salary | P43: Salary | Q43: Salary | R43: Salary | S43: Salary | T43: Salary | U43: Salary | V43: Salary | W43: Salary | X43: Salary | Y43: Salary | Z43: Salary | AA43: Salary | AB43: Salary | AC43: Salary | AD43: Salary | AE43: Salary | AF43: Salary | AG43: Salary | AH43: Salary | AI43: Salary | AJ43: Salary | AK43: Salary | AL43: Salary | AM43: Salary | AN43: Salary | AO43: Salary | AP43: Salary | AQ43: Salary | AR43: Salary | AS43: Salary | AT43: Salary | AU43: Salary | AV43: Salary | AW43: Salary | AX43: Salary | AY43: Salary | AZ43: Salary | BA43: Salary | BB43: Salary | BC43: Salary | BD43: Salary | BE43: Salary | BF43: Salary
A44: Job Details | B44: Additional Information | C44: ScheduledWeeklyHours | D44: =SUBSTITUTE(A44," ","") & "_" & SUBSTITUTE(IF(B44="N/A","",B44& "_")," ","") & SUBSTITUTE(SUBSTITUTE(C44," ",""),"/","") -> JobDetails_AdditionalInformation_ScheduledWeeklyHours | E44: =D44&2 -> JobDetails_AdditionalInformation_ScheduledWeeklyHours2 | G44: 20 | H44: 40 | I44: 40 | J44: 40 | K44: 20 | L44: 40 | M44: 30 | N44: 40 | O44: 10 | P44: 20 | Q44: 40 | R44: 20 | S44: 20 | T44: 40 | U44: 40 | V44: 40 | W44: 20 | X44: 40 | Y44: 30 | Z44: 40 | AA44: 10 | AB44: 40 | AC44: 40 | AD44: 40 | AE44: 40 | AF44: 20 | AG44: 40 | AH44: 40 | AI44: 40 | AJ44: 20 | AK44: 10 | AL44: 40 | AM44: 40 | AQ44: 40 | AR44: 30 | AS44: 40 | AT44: 10 | AU44: 40 | AV44: 20 | AW44: 40 | AX44: 10 | AY44: 40 | AZ44: 20 | BA44: 40 | BB44: 20 | BC44: 40 | BD44: 40 | BE44: 20 | BF44: 40
A45: Job Details | B45: Additional Information | C45: SchoolName | D45: =SUBSTITUTE(A45," ","") & "_" & SUBSTITUTE(IF(B45="N/A","",B45& "_")," ","") & SUBSTITUTE(SUBSTITUTE(C45," ",""),"/","") -> JobDetails_AdditionalInformation_SchoolName | E45: =D45&2 -> JobDetails_AdditionalInformation_SchoolName2 | G45: Test | H45: Test | I45: Test | J45: Test | K45: Test | L45: Test | M45: Test | N45: Test | O45: Test | P45: Test | Q45: Test | R45: Test | S45: Test | T45: Test | U45: Test | V45: Test | W45: Test | X45: Test | Y45: Test | Z45: Test | AA45: Test | AB45: Test | AC45: Test | AD45: Test | AE45: Test | AF45: Test | AG45: Test | AH45: Test | AI45: Test | AJ45: Test | AK45: Test | AL45: Test | AM45: Test | AN45: Test | AO45: Test | AP45: Test | AQ45: Test | AR45: Test | AS45: Test | AT45: Test | AU45: Test | AV45: Test | AW45: Test | AX45: Test | AY45: Test | AZ45: Test | BA45: Test | BB45: Test | BC45: Test | BD45: Test | BE45: Test | BF45: Test
A46: Job Details | B46: Additional Information | C46: SchoolType | D46: =SUBSTITUTE(A46," ","") & "_" & SUBSTITUTE(IF(B46="N/A","",B46& "_")," ","") & SUBSTITUTE(SUBSTITUTE(C46," ",""),"/","") -> JobDetails_AdditionalInformation_SchoolType | E46: =D46&2 -> JobDetails_AdditionalInformation_SchoolType2 | F46: Set to N/A when field not present otherwise automation will throw error | G46: Za | H46: Za | I46: Za | J46: Za | K46: Za | L46: Za | M46: Za | N46: Za | O46: Za | P46: Za | Q46: Za | R46: Za | S46: Za | T46: Za | U46: Za | V46: Za | W46: Za | X46: Za | Y46: Za | Z46: Za | AA46: Za | AB46: Za | AC46: Za | AD46: Za | AE46: Za | AF46: Za | AG46: Za | AH46: Za | AI46: Za | AJ46: Za | AK46: Za | AL46: Za | AM46: Za | AN46: Za | AO46: Za | AP46: Za | AQ46: Za | AR46: Za | AS46: Za | AT46: Za | AU46: Za | AV46: Za | AW46: Za | AX46: Za | AY46: Za | AZ46: Za | BA46: Za | BB46: Za | BC46: Za | BD46: Za | BE46: Za | BF46: Za
A47: Job Details | B47: Additional Information | C47: SchoolStartDate | D47: =SUBSTITUTE(A47," ","") & "_" & SUBSTITUTE(IF(B47="N/A","",B47& "_")," ","") & SUBSTITUTE(SUBSTITUTE(C47," ",""),"/","") -> JobDetails_AdditionalInformation_SchoolStartDate | E47: =D47&2 -> JobDetails_AdditionalInformation_SchoolStartDate2 | G47: 43831 | H47: 43831 | I47: 43831 | J47: 43831 | K47: 43831 | L47: 43831 | M47: 43831 | N47: 43831 | O47: 43831 | P47: 43831 | Q47: 43831 | R47: 43831 | S47: 43831 | T47: 43831 | U47: 43831 | V47: 43831 | W47: 43831 | X47: 43831 | Y47: 43831 | Z47: 43831 | AA47: 43831 | AB47: 43831 | AC47: 43831 | AD47: 43831 | AE47: 43831 | AF47: 43831 | AG47: 43831 | AH47: 43831 | AI47: 43831 | AJ47: 43831 | AK47: 43831 | AL47: 43831 | AM47: 43831 | AN47: 43831 | AO47: 43831 | AP47: 43831 | AQ47: 43831 | AR47: 43831 | AS47: 43831 | AT47: 43831 | AU47: 43831 | AV47: 43831 | AW47: 43831 | AX47: 43831 | AY47: 43831 | AZ47: 43831 | BA47: 43831 | BB47: 43831 | BC47: 43831 | BD47: 43831 | BE47: 43831 | BF47: 43831
A48: Maintain Employee Contract | B48: N/A | C48: SchoolEndDate | D48: =SUBSTITUTE(A48," ","") & "_" & SUBSTITUTE(IF(B48="N/A","",B48& "_")," ","") & SUBSTITUTE(SUBSTITUTE(C48," ",""),"/","") -> MaintainEmployeeContract_SchoolEndDate | E48: =D48&2 -> MaintainEmployeeContract_SchoolEndDate2 | G48: 45293 | H48: 45293 | I48: 45293 | J48: 45293 | K48: 45293 | L48: 45293 | M48: 45293 | N48: 45293 | O48: 45293 | P48: 45293 | Q48: 45293 | R48: 45293 | S48: 45293 | T48: 45293 | U48: 45293 | V48: 45293 | W48: 45293 | X48: 45293 | Y48: 45293 | Z48: 45293 | AA48: 45293 | AB48: 45293 | AC48: 45293 | AD48: 45293 | AE48: 45293 | AF48: 45293 | AG48: 45293 | AH48: 45293 | AI48: 45293 | AJ48: 45293 | AK48: 45293 | AL48: 45293 | AM48: 45293 | AN48: 45293 | AO48: 45293 | AP48: 45293 | AQ48: 45293 | AR48: 45293 | AS48: 45293 | AT48: 45293 | AU48: 45293 | AV48: 45293 | AW48: 45293 | AX48: 45293 | AY48: 45293 | AZ48: 45293 | BA48: 45293 | BB48: 45293 | BC48: 45293 | BD48: 45293 | BE48: 45293 | BF48: 45293
A49: Maintain Employee Contract | B49: N/A | C49: AdditionalJobClassifications | D49: =SUBSTITUTE(A49," ","") & "_" & SUBSTITUTE(IF(B49="N/A","",B49& "_")," ","") & SUBSTITUTE(SUBSTITUTE(C49," ",""),"/","") -> MaintainEmployeeContract_AdditionalJobClassifications | E49: =D49&2 -> MaintainEmployeeContract_AdditionalJobClassifications2 | F49: Set to N/A when field not present otherwise automation will throw error | G49: RE029_NEW2 | H49: RE024_NEW | I49: RE029_NEW2 | J49: RE023_NEW | K49: RE035_NEW | L49: SD014_NEW | M49: RE029_NEW2 | N49: RE044_NEW | O49: RE029_NEW2 | P49: RE029_NEW2 | Q49: RE030_NEW | R49: RE049_NEW | S49: RE043_NEW | T49: RE029_NEW2 | U49: RE029_NEW2 | V49: RE029_NEW2 | W49: RE029_NEW2 | X49: RE029_NEW2 | Y49: RE029_NEW2 | Z49: RE029_NEW2 | AA49: RE029_NEW2 | AB49: RE029_NEW2 | AC49: RE029_NEW2 | AD49: RE029_NEW2 | AE49: RE029_NEW2 | AF49: RE029_NEW2 | AG49: RE029_NEW2 | AH49: RE029_NEW2 | AI49: RE029_NEW2 | AJ49: RE029_NEW2 | AK49: RE029_NEW2 | AL49: RE029_NEW2 | AM49: RE029_NEW2 | AN49: RE029_NEW2 | AO49: RE029_NEW2 | AP49: RE029_NEW2 | AQ49: RE029_NEW2 | AR49: RE029_NEW2 | AS49: RE029_NEW2 | AT49: RE029_NEW2 | AU49: RE029_NEW2 | AV49: RE029_NEW2 | AW49: RE029_NEW2 | AX49: RE029_NEW2 | AY49: RE029_NEW2 | AZ49: RE029_NEW2 | BA49: RE029_NEW2 | BB49: RE029_NEW2 | BC49: RE029_NEW2 | BD49: RE029_NEW2 | BE49: RE029_NEW2 | BF49: RE029_NEW2
A50: Maintain Employee Contract | B50: N/A | C50: WorkShift | D50: MaintainEmployeeContract_DateEmployeeSigned | E50: MaintainEmployeeContract_DateEmployeeSigned2 | F50: Set to N/A when field not present otherwise automation will throw error | G50: 5 Days | H50: 5 Days (Poland) | I50: 5 Days (Poland) | J50: 5 Days (Poland) | K50: 5 Days (Poland) | L50: 5 Days (Poland) | M50: 5 Days (Poland) | N50: 5 Days (Poland) | O50: 5 Days (Poland) | P50: 5 Days (Poland) | Q50: 5 Days (Poland) | R50: 5 Days (Poland) | S50: 5 Days (Poland) | T50: 5 Days (Poland) | U50: 5 Days (Poland) | V50: 5 Days (Poland) | W50: 5 Days (Poland) | X50: 5 Days (Poland) | Y50: 5 Days (Poland) | Z50: 5 Days (Poland) | AA50: 5 Days (Poland) | AB50: 5 Days (Poland) | AC50: 5 Days (Poland) | AD50: 5 Days (Poland) | AE50: 5 Days (Poland) | AF50: 5 Days (Poland) | AG50: 5 Days (Poland) | AH50: 5 Days (Poland) | AI50: 5 Days (Poland) | AJ50: 5 Days (Poland) | AK50: 5 Days (Poland) | AL50: 5 Days (Poland) | AM50: 5 Days (Poland) | AN50: 5 Days (Poland) | AO50: 5 Days (Poland) | AP50: 5 Days (Poland) | AQ50: 5 Days (Poland) | AR50: 5 Days (Poland) | AS50: 5 Days (Poland) | AT50: 5 Days (Poland) | AU50: 5 Days (Poland) | AV50: 5 Days (Poland) | AW50: 5 Days (Poland) | AX50: 5 Days (Poland) | AY50: 5 Days (Poland) | AZ50: 5 Days (Poland) | BA50: 5 Days (Poland) | BB50: 5 Days (Poland) | BC50: 5 Days (Poland) | BD50: 5 Days (Poland) | BE50: 5 Days (Poland) | BF50: 5 Days (Poland)
A51: Maintain Employee Contract | B51: N/A | C51: EndEmploymentDate | D51: MaintainEmployeeContract_DateEmployerSigned | E51: MaintainEmployeeContract_DateEmployerSigned2 | G51: N/A | H51: N/A | I51: N/A | J51: =TODAY()+365 -> 46085 | K51: =TODAY()+365 -> 46085 | L51: N/A | M51: N/A | N51: N/A | O51: =TODAY()+365 -> 46085 | P51: N/A | Q51: =TODAY()+365 -> 46085 | R51: N/A | S51: =TODAY()+365 -> 46085 | T51: =TODAY()+365 -> 46085 | U51: =TODAY()+365 -> 46085 | V51: =TODAY()+365 -> 46085 | W51: N/A | X51: N/A | Y51: =TODAY()+365 -> 46085 | Z51: N/A | AA51: =TODAY()+365 -> 46085 | AB51: =TODAY()+365 -> 46085 | AC51: =TODAY()+365 -> 46085 | AD51: =TODAY()+365 -> 46085 | AE51: =TODAY()+365 -> 46085 | AF51: =TODAY()+365 -> 46085 | AG51: =TODAY()+365 -> 46085 | AH51: N/A | AI51: N/A | AJ51: =TODAY()+365 -> 46085 | AK51: N/A | AL51: =TODAY()+365 -> 46085 | AM51: N/A | AN51: =TODAY()+365 -> 46085 | AO51: N/A | AP51: =TODAY()+365 -> 46085 | AQ51: N/A | AR51: =TODAY()+365 -> 46085 | AS51: N/A | AT51: =TODAY()+365 -> 46085 | AU51: N/A | AV51: =TODAY()+365 -> 46085 | AW51: =TODAY()+365 -> 46085 | AX51: N/A | AY51: N/A | AZ51: =TODAY()+365 -> 46085 | BA51: =TODAY()+365 -> 46085 | BB51: N/A | BC51: N/A | BD51: =TODAY()+365 -> 46085 | BE51: N/A | BF51: N/A
